/*     */ package com.yisa.engine.trunk;
/*     */ 
/*     */ import java.text.SimpleDateFormat;
/*     */ import java.util.Base64;
/*     */ import java.util.Base64.Decoder;
/*     */ import java.util.Calendar;
/*     */ import java.util.Date;
/*     */ import org.apache.spark.sql.DataFrameReader;
/*     */ import org.apache.spark.sql.Dataset;
/*     */ import org.apache.spark.sql.Row;
/*     */ import org.apache.spark.sql.SparkSession;
/*     */ import org.apache.spark.sql.UDFRegistration;
/*     */ import scala.Array.;
/*     */ import scala.Predef.;
/*     */ import scala.Serializable;
/*     */ import scala.collection.generic.FilterMonadic;
/*     */ import scala.collection.immutable.Nil.;
/*     */ import scala.collection.immutable.Range;
/*     */ import scala.collection.immutable.Range.Inclusive;
/*     */ import scala.collection.immutable.StringOps;
/*     */ import scala.collection.mutable.StringBuilder;
/*     */ import scala.reflect.ClassTag.;
/*     */ import scala.reflect.api.Internals.InternalApi;
/*     */ import scala.reflect.api.Internals.ReificationSupportApi;
/*     */ import scala.reflect.api.JavaUniverse;
/*     */ import scala.reflect.api.JavaUniverse.JavaMirror;
/*     */ import scala.reflect.api.Mirror;
/*     */ import scala.reflect.api.Symbols.ModuleSymbolApi;
/*     */ import scala.reflect.api.TypeCreator;
/*     */ import scala.reflect.api.TypeTags;
/*     */ import scala.reflect.api.TypeTags.TypeTag.;
/*     */ import scala.reflect.api.Types.TypeApi;
/*     */ import scala.reflect.api.Universe;
/*     */ import scala.reflect.runtime.package.;
/*     */ import scala.runtime.AbstractFunction1;
/*     */ import scala.runtime.AbstractFunction1.mcVI.sp;
/*     */ import scala.runtime.AbstractFunction1.mcZI.sp;
/*     */ import scala.runtime.AbstractFunction2;
/*     */ import scala.runtime.CharRef;
/*     */ import scala.runtime.IntRef;
/*     */ import scala.runtime.LongRef;
/*     */ import scala.runtime.ObjectRef;
/*     */ import scala.runtime.RichInt.;
/*     */ 
/*     */ public final class SparkEngineVer21$
/*     */ {
/*     */   public static final  MODULE$;
/*     */   
/*     */   static
/*     */   {
/*     */     new ();
/*     */   }
/*     */   
/*     */   /* Error */
/*     */   public void main(String[] args)
/*     */   {
/*     */     // Byte code:
/*     */     //   0: aconst_null
/*     */     //   1: astore_2
/*     */     //   2: new 18	org/apache/commons/cli/Options
/*     */     //   5: dup
/*     */     //   6: invokespecial 19	org/apache/commons/cli/Options:<init>	()V
/*     */     //   9: astore_3
/*     */     //   10: new 21	org/apache/commons/cli/Option
/*     */     //   13: dup
/*     */     //   14: ldc 23
/*     */     //   16: iconst_1
/*     */     //   17: ldc 25
/*     */     //   19: invokespecial 28	org/apache/commons/cli/Option:<init>	(Ljava/lang/String;ZLjava/lang/String;)V
/*     */     //   22: astore 6
/*     */     //   24: aload 6
/*     */     //   26: iconst_1
/*     */     //   27: invokevirtual 32	org/apache/commons/cli/Option:setRequired	(Z)V
/*     */     //   30: aload_3
/*     */     //   31: aload 6
/*     */     //   33: invokevirtual 36	org/apache/commons/cli/Options:addOption	(Lorg/apache/commons/cli/Option;)Lorg/apache/commons/cli/Options;
/*     */     //   36: pop
/*     */     //   37: new 21	org/apache/commons/cli/Option
/*     */     //   40: dup
/*     */     //   41: ldc 38
/*     */     //   43: iconst_1
/*     */     //   44: ldc 40
/*     */     //   46: invokespecial 28	org/apache/commons/cli/Option:<init>	(Ljava/lang/String;ZLjava/lang/String;)V
/*     */     //   49: astore 7
/*     */     //   51: aload 7
/*     */     //   53: iconst_1
/*     */     //   54: invokevirtual 32	org/apache/commons/cli/Option:setRequired	(Z)V
/*     */     //   57: aload_3
/*     */     //   58: aload 7
/*     */     //   60: invokevirtual 36	org/apache/commons/cli/Options:addOption	(Lorg/apache/commons/cli/Option;)Lorg/apache/commons/cli/Options;
/*     */     //   63: pop
/*     */     //   64: new 21	org/apache/commons/cli/Option
/*     */     //   67: dup
/*     */     //   68: ldc 42
/*     */     //   70: iconst_1
/*     */     //   71: ldc 44
/*     */     //   73: invokespecial 28	org/apache/commons/cli/Option:<init>	(Ljava/lang/String;ZLjava/lang/String;)V
/*     */     //   76: astore 8
/*     */     //   78: aload 8
/*     */     //   80: iconst_1
/*     */     //   81: invokevirtual 32	org/apache/commons/cli/Option:setRequired	(Z)V
/*     */     //   84: aload_3
/*     */     //   85: aload 8
/*     */     //   87: invokevirtual 36	org/apache/commons/cli/Options:addOption	(Lorg/apache/commons/cli/Option;)Lorg/apache/commons/cli/Options;
/*     */     //   90: pop
/*     */     //   91: new 46	org/apache/commons/cli/PosixParser
/*     */     //   94: dup
/*     */     //   95: invokespecial 47	org/apache/commons/cli/PosixParser:<init>	()V
/*     */     //   98: astore 9
/*     */     //   100: aload 9
/*     */     //   102: aload_3
/*     */     //   103: aload_1
/*     */     //   104: invokevirtual 51	org/apache/commons/cli/PosixParser:parse	(Lorg/apache/commons/cli/Options;[Ljava/lang/String;)Lorg/apache/commons/cli/CommandLine;
/*     */     //   107: astore_2
/*     */     //   108: goto +59 -> 167
/*     */     //   111: astore 4
/*     */     //   113: getstatic 56	scala/Predef$:MODULE$	Lscala/Predef$;
/*     */     //   116: ldc 58
/*     */     //   118: invokevirtual 62	scala/Predef$:println	(Ljava/lang/Object;)V
/*     */     //   121: getstatic 56	scala/Predef$:MODULE$	Lscala/Predef$;
/*     */     //   124: aload 4
/*     */     //   126: invokevirtual 66	java/lang/Exception:getMessage	()Ljava/lang/String;
/*     */     //   129: invokevirtual 62	scala/Predef$:println	(Ljava/lang/Object;)V
/*     */     //   132: getstatic 56	scala/Predef$:MODULE$	Lscala/Predef$;
/*     */     //   135: aload 4
/*     */     //   137: invokevirtual 69	java/lang/Exception:printStackTrace	()V
/*     */     //   140: getstatic 75	scala/runtime/BoxedUnit:UNIT	Lscala/runtime/BoxedUnit;
/*     */     //   143: invokevirtual 62	scala/Predef$:println	(Ljava/lang/Object;)V
/*     */     //   146: new 77	org/apache/commons/cli/HelpFormatter
/*     */     //   149: dup
/*     */     //   150: invokespecial 78	org/apache/commons/cli/HelpFormatter:<init>	()V
/*     */     //   153: astore 5
/*     */     //   155: aload 5
/*     */     //   157: ldc 80
/*     */     //   159: aload_3
/*     */     //   160: invokevirtual 84	org/apache/commons/cli/HelpFormatter:printHelp	(Ljava/lang/String;Lorg/apache/commons/cli/Options;)V
/*     */     //   163: iconst_1
/*     */     //   164: invokestatic 90	java/lang/System:exit	(I)V
/*     */     //   167: aload_2
/*     */     //   168: ldc 23
/*     */     //   170: invokevirtual 96	org/apache/commons/cli/CommandLine:getOptionValue	(Ljava/lang/String;)Ljava/lang/String;
/*     */     //   173: astore 10
/*     */     //   175: aload_2
/*     */     //   176: ldc 38
/*     */     //   178: invokevirtual 96	org/apache/commons/cli/CommandLine:getOptionValue	(Ljava/lang/String;)Ljava/lang/String;
/*     */     //   181: astore 11
/*     */     //   183: aload_2
/*     */     //   184: ldc 42
/*     */     //   186: invokevirtual 96	org/apache/commons/cli/CommandLine:getOptionValue	(Ljava/lang/String;)Ljava/lang/String;
/*     */     //   189: astore 12
/*     */     //   191: new 98	com/yisa/wifi/zookeeper/ZookeeperUtil
/*     */     //   194: dup
/*     */     //   195: invokespecial 99	com/yisa/wifi/zookeeper/ZookeeperUtil:<init>	()V
/*     */     //   198: astore 13
/*     */     //   200: aload 13
/*     */     //   202: aload 10
/*     */     //   204: ldc 101
/*     */     //   206: iconst_0
/*     */     //   207: invokevirtual 105	com/yisa/wifi/zookeeper/ZookeeperUtil:getAllConfig	(Ljava/lang/String;Ljava/lang/String;Z)Ljava/util/Map;
/*     */     //   210: astore 14
/*     */     //   212: aload 14
/*     */     //   214: ldc 107
/*     */     //   216: invokeinterface 113 2 0
/*     */     //   221: checkcast 115	java/lang/String
/*     */     //   224: astore 15
/*     */     //   226: aload 14
/*     */     //   228: ldc 117
/*     */     //   230: invokeinterface 113 2 0
/*     */     //   235: checkcast 115	java/lang/String
/*     */     //   238: astore 16
/*     */     //   240: aload 14
/*     */     //   242: ldc 119
/*     */     //   244: invokeinterface 113 2 0
/*     */     //   249: checkcast 115	java/lang/String
/*     */     //   252: astore 17
/*     */     //   254: aload 14
/*     */     //   256: ldc 121
/*     */     //   258: invokeinterface 113 2 0
/*     */     //   263: checkcast 115	java/lang/String
/*     */     //   266: astore 18
/*     */     //   268: ldc 123
/*     */     //   270: astore 19
/*     */     //   272: aload 12
/*     */     //   274: ldc 125
/*     */     //   276: astore 20
/*     */     //   278: dup
/*     */     //   279: ifnonnull +12 -> 291
/*     */     //   282: pop
/*     */     //   283: aload 20
/*     */     //   285: ifnull +14 -> 299
/*     */     //   288: goto +28 -> 316
/*     */     //   291: aload 20
/*     */     //   293: invokevirtual 129	java/lang/Object:equals	(Ljava/lang/Object;)Z
/*     */     //   296: ifeq +20 -> 316
/*     */     //   299: aload 14
/*     */     //   301: ldc -125
/*     */     //   303: invokeinterface 113 2 0
/*     */     //   308: checkcast 115	java/lang/String
/*     */     //   311: astore 19
/*     */     //   313: goto +17 -> 330
/*     */     //   316: aload 14
/*     */     //   318: ldc -123
/*     */     //   320: invokeinterface 113 2 0
/*     */     //   325: checkcast 115	java/lang/String
/*     */     //   328: astore 19
/*     */     //   330: aload 14
/*     */     //   332: ldc -121
/*     */     //   334: invokeinterface 113 2 0
/*     */     //   339: checkcast 115	java/lang/String
/*     */     //   342: astore 21
/*     */     //   344: aload 14
/*     */     //   346: ldc -119
/*     */     //   348: invokeinterface 113 2 0
/*     */     //   353: checkcast 115	java/lang/String
/*     */     //   356: astore 22
/*     */     //   358: new 139	scala/collection/immutable/StringOps
/*     */     //   361: dup
/*     */     //   362: getstatic 56	scala/Predef$:MODULE$	Lscala/Predef$;
/*     */     //   365: aload 14
/*     */     //   367: ldc -115
/*     */     //   369: invokeinterface 113 2 0
/*     */     //   374: checkcast 115	java/lang/String
/*     */     //   377: invokevirtual 144	scala/Predef$:augmentString	(Ljava/lang/String;)Ljava/lang/String;
/*     */     //   380: invokespecial 147	scala/collection/immutable/StringOps:<init>	(Ljava/lang/String;)V
/*     */     //   383: invokevirtual 151	scala/collection/immutable/StringOps:toInt	()I
/*     */     //   386: istore 23
/*     */     //   388: aload 14
/*     */     //   390: ldc -103
/*     */     //   392: invokeinterface 113 2 0
/*     */     //   397: checkcast 115	java/lang/String
/*     */     //   400: astore 24
/*     */     //   402: new 155	scala/collection/mutable/StringBuilder
/*     */     //   405: dup
/*     */     //   406: invokespecial 156	scala/collection/mutable/StringBuilder:<init>	()V
/*     */     //   409: ldc -98
/*     */     //   411: invokevirtual 162	scala/collection/mutable/StringBuilder:append	(Ljava/lang/Object;)Lscala/collection/mutable/StringBuilder;
/*     */     //   414: aload_0
/*     */     //   415: invokevirtual 166	com/yisa/engine/trunk/SparkEngineVer21$:getDateMid	()J
/*     */     //   418: invokestatic 172	scala/runtime/BoxesRunTime:boxToLong	(J)Ljava/lang/Long;
/*     */     //   421: invokevirtual 162	scala/collection/mutable/StringBuilder:append	(Ljava/lang/Object;)Lscala/collection/mutable/StringBuilder;
/*     */     //   424: invokevirtual 175	scala/collection/mutable/StringBuilder:toString	()Ljava/lang/String;
/*     */     //   427: astore 25
/*     */     //   429: ldc -79
/*     */     //   431: astore 26
/*     */     //   433: getstatic 182	org/apache/spark/sql/SparkSession$:MODULE$	Lorg/apache/spark/sql/SparkSession$;
/*     */     //   436: invokevirtual 186	org/apache/spark/sql/SparkSession$:builder	()Lorg/apache/spark/sql/SparkSession$Builder;
/*     */     //   439: ldc -68
/*     */     //   441: invokevirtual 194	org/apache/spark/sql/SparkSession$Builder:appName	(Ljava/lang/String;)Lorg/apache/spark/sql/SparkSession$Builder;
/*     */     //   444: invokevirtual 198	org/apache/spark/sql/SparkSession$Builder:getOrCreate	()Lorg/apache/spark/sql/SparkSession;
/*     */     //   447: astore 27
/*     */     //   449: aload_0
/*     */     //   450: aload 27
/*     */     //   452: aload 15
/*     */     //   454: aload 22
/*     */     //   456: iload 23
/*     */     //   458: invokevirtual 202	com/yisa/engine/trunk/SparkEngineVer21$:loadRealtimeData	(Lorg/apache/spark/sql/SparkSession;Ljava/lang/String;Ljava/lang/String;I)Lorg/apache/spark/sql/Dataset;
/*     */     //   461: astore 28
/*     */     //   463: aload 28
/*     */     //   465: aload 25
/*     */     //   467: invokevirtual 207	org/apache/spark/sql/Dataset:createOrReplaceTempView	(Ljava/lang/String;)V
/*     */     //   470: aload 27
/*     */     //   472: invokevirtual 213	org/apache/spark/sql/SparkSession:catalog	()Lorg/apache/spark/sql/catalog/Catalog;
/*     */     //   475: aload 25
/*     */     //   477: invokevirtual 218	org/apache/spark/sql/catalog/Catalog:cacheTable	(Ljava/lang/String;)V
/*     */     //   480: aload_0
/*     */     //   481: aload 27
/*     */     //   483: aload 15
/*     */     //   485: aload 22
/*     */     //   487: iload 23
/*     */     //   489: invokevirtual 221	com/yisa/engine/trunk/SparkEngineVer21$:loadAlltimeData	(Lorg/apache/spark/sql/SparkSession;Ljava/lang/String;Ljava/lang/String;I)Lorg/apache/spark/sql/Dataset;
/*     */     //   492: astore 29
/*     */     //   494: aload 29
/*     */     //   496: aload 26
/*     */     //   498: invokevirtual 207	org/apache/spark/sql/Dataset:createOrReplaceTempView	(Ljava/lang/String;)V
/*     */     //   501: aload_0
/*     */     //   502: aload 27
/*     */     //   504: invokevirtual 225	com/yisa/engine/trunk/SparkEngineVer21$:registerUDF	(Lorg/apache/spark/sql/SparkSession;)V
/*     */     //   507: aload_0
/*     */     //   508: aload 27
/*     */     //   510: aload 25
/*     */     //   512: aload 24
/*     */     //   514: aload 10
/*     */     //   516: invokevirtual 229	com/yisa/engine/trunk/SparkEngineVer21$:runFirstTask	(Lorg/apache/spark/sql/SparkSession;Ljava/lang/String;Ljava/lang/String;Ljava/lang/String;)V
/*     */     //   519: new 231	java/util/Properties
/*     */     //   522: dup
/*     */     //   523: invokespecial 232	java/util/Properties:<init>	()V
/*     */     //   526: astore 30
/*     */     //   528: aload 30
/*     */     //   530: ldc -22
/*     */     //   532: aload 16
/*     */     //   534: invokevirtual 238	java/util/Properties:put	(Ljava/lang/Object;Ljava/lang/Object;)Ljava/lang/Object;
/*     */     //   537: pop
/*     */     //   538: aload 30
/*     */     //   540: ldc -16
/*     */     //   542: aload 11
/*     */     //   544: invokevirtual 238	java/util/Properties:put	(Ljava/lang/Object;Ljava/lang/Object;)Ljava/lang/Object;
/*     */     //   547: pop
/*     */     //   548: aload 30
/*     */     //   550: ldc -14
/*     */     //   552: ldc -12
/*     */     //   554: invokevirtual 238	java/util/Properties:put	(Ljava/lang/Object;Ljava/lang/Object;)Ljava/lang/Object;
/*     */     //   557: pop
/*     */     //   558: aload 30
/*     */     //   560: ldc -10
/*     */     //   562: ldc -8
/*     */     //   564: invokevirtual 238	java/util/Properties:put	(Ljava/lang/Object;Ljava/lang/Object;)Ljava/lang/Object;
/*     */     //   567: pop
/*     */     //   568: aload 30
/*     */     //   570: ldc -6
/*     */     //   572: ldc -8
/*     */     //   574: invokevirtual 238	java/util/Properties:put	(Ljava/lang/Object;Ljava/lang/Object;)Ljava/lang/Object;
/*     */     //   577: pop
/*     */     //   578: new 252	org/apache/kafka/clients/consumer/KafkaConsumer
/*     */     //   581: dup
/*     */     //   582: aload 30
/*     */     //   584: invokespecial 255	org/apache/kafka/clients/consumer/KafkaConsumer:<init>	(Ljava/util/Properties;)V
/*     */     //   587: astore 31
/*     */     //   589: new 257	java/util/ArrayList
/*     */     //   592: dup
/*     */     //   593: invokespecial 258	java/util/ArrayList:<init>	()V
/*     */     //   596: astore 32
/*     */     //   598: aload 32
/*     */     //   600: aload 19
/*     */     //   602: invokevirtual 261	java/util/ArrayList:add	(Ljava/lang/Object;)Z
/*     */     //   605: pop
/*     */     //   606: aload 31
/*     */     //   608: aload 32
/*     */     //   610: invokevirtual 265	org/apache/kafka/clients/consumer/KafkaConsumer:subscribe	(Ljava/util/List;)V
/*     */     //   613: new 267	java/util/Date
/*     */     //   616: dup
/*     */     //   617: invokespecial 268	java/util/Date:<init>	()V
/*     */     //   620: invokevirtual 271	java/util/Date:getTime	()J
/*     */     //   623: lstore 33
/*     */     //   625: getstatic 276	com/yisa/engine/db/MySQLConnectManager$:MODULE$	Lcom/yisa/engine/db/MySQLConnectManager$;
/*     */     //   628: aload 10
/*     */     //   630: invokevirtual 279	com/yisa/engine/db/MySQLConnectManager$:initConnectionPool	(Ljava/lang/String;)V
/*     */     //   633: getstatic 56	scala/Predef$:MODULE$	Lscala/Predef$;
/*     */     //   636: ldc_w 281
/*     */     //   639: invokevirtual 62	scala/Predef$:println	(Ljava/lang/Object;)V
/*     */     //   642: goto +985 -> 1627
/*     */     //   645: astore 45
/*     */     //   647: getstatic 56	scala/Predef$:MODULE$	Lscala/Predef$;
/*     */     //   650: ldc_w 283
/*     */     //   653: invokevirtual 62	scala/Predef$:println	(Ljava/lang/Object;)V
/*     */     //   656: getstatic 56	scala/Predef$:MODULE$	Lscala/Predef$;
/*     */     //   659: aload 45
/*     */     //   661: invokevirtual 66	java/lang/Exception:getMessage	()Ljava/lang/String;
/*     */     //   664: invokevirtual 62	scala/Predef$:println	(Ljava/lang/Object;)V
/*     */     //   667: getstatic 56	scala/Predef$:MODULE$	Lscala/Predef$;
/*     */     //   670: aload 45
/*     */     //   672: invokevirtual 69	java/lang/Exception:printStackTrace	()V
/*     */     //   675: getstatic 75	scala/runtime/BoxedUnit:UNIT	Lscala/runtime/BoxedUnit;
/*     */     //   678: invokevirtual 62	scala/Predef$:println	(Ljava/lang/Object;)V
/*     */     //   681: getstatic 56	scala/Predef$:MODULE$	Lscala/Predef$;
/*     */     //   684: ldc_w 285
/*     */     //   687: invokevirtual 62	scala/Predef$:println	(Ljava/lang/Object;)V
/*     */     //   690: aload 44
/*     */     //   692: invokeinterface 290 1 0
/*     */     //   697: aload 36
/*     */     //   699: invokeinterface 296 1 0
/*     */     //   704: ifeq +662 -> 1366
/*     */     //   707: getstatic 56	scala/Predef$:MODULE$	Lscala/Predef$;
/*     */     //   710: new 155	scala/collection/mutable/StringBuilder
/*     */     //   713: dup
/*     */     //   714: invokespecial 156	scala/collection/mutable/StringBuilder:<init>	()V
/*     */     //   717: ldc_w 298
/*     */     //   720: invokevirtual 162	scala/collection/mutable/StringBuilder:append	(Ljava/lang/Object;)Lscala/collection/mutable/StringBuilder;
/*     */     //   723: getstatic 303	com/yisa/engine/uitl/TimeUtil$:MODULE$	Lcom/yisa/engine/uitl/TimeUtil$;
/*     */     //   726: lload 33
/*     */     //   728: invokevirtual 307	com/yisa/engine/uitl/TimeUtil$:getStringFromTimestampLong	(J)Ljava/lang/String;
/*     */     //   731: invokevirtual 162	scala/collection/mutable/StringBuilder:append	(Ljava/lang/Object;)Lscala/collection/mutable/StringBuilder;
/*     */     //   734: invokevirtual 175	scala/collection/mutable/StringBuilder:toString	()Ljava/lang/String;
/*     */     //   737: invokevirtual 62	scala/Predef$:println	(Ljava/lang/Object;)V
/*     */     //   740: getstatic 56	scala/Predef$:MODULE$	Lscala/Predef$;
/*     */     //   743: new 155	scala/collection/mutable/StringBuilder
/*     */     //   746: dup
/*     */     //   747: invokespecial 156	scala/collection/mutable/StringBuilder:<init>	()V
/*     */     //   750: ldc_w 309
/*     */     //   753: invokevirtual 162	scala/collection/mutable/StringBuilder:append	(Ljava/lang/Object;)Lscala/collection/mutable/StringBuilder;
/*     */     //   756: aload 25
/*     */     //   758: invokevirtual 162	scala/collection/mutable/StringBuilder:append	(Ljava/lang/Object;)Lscala/collection/mutable/StringBuilder;
/*     */     //   761: invokevirtual 175	scala/collection/mutable/StringBuilder:toString	()Ljava/lang/String;
/*     */     //   764: invokevirtual 62	scala/Predef$:println	(Ljava/lang/Object;)V
/*     */     //   767: new 267	java/util/Date
/*     */     //   770: dup
/*     */     //   771: invokespecial 268	java/util/Date:<init>	()V
/*     */     //   774: invokevirtual 271	java/util/Date:getTime	()J
/*     */     //   777: lstore 38
/*     */     //   779: aload 36
/*     */     //   781: invokeinterface 313 1 0
/*     */     //   786: checkcast 315	org/apache/kafka/clients/consumer/ConsumerRecord
/*     */     //   789: astore 40
/*     */     //   791: getstatic 56	scala/Predef$:MODULE$	Lscala/Predef$;
/*     */     //   794: new 155	scala/collection/mutable/StringBuilder
/*     */     //   797: dup
/*     */     //   798: invokespecial 156	scala/collection/mutable/StringBuilder:<init>	()V
/*     */     //   801: ldc_w 317
/*     */     //   804: invokevirtual 162	scala/collection/mutable/StringBuilder:append	(Ljava/lang/Object;)Lscala/collection/mutable/StringBuilder;
/*     */     //   807: aload 40
/*     */     //   809: invokevirtual 320	org/apache/kafka/clients/consumer/ConsumerRecord:value	()Ljava/lang/Object;
/*     */     //   812: invokevirtual 162	scala/collection/mutable/StringBuilder:append	(Ljava/lang/Object;)Lscala/collection/mutable/StringBuilder;
/*     */     //   815: invokevirtual 175	scala/collection/mutable/StringBuilder:toString	()Ljava/lang/String;
/*     */     //   818: invokevirtual 62	scala/Predef$:println	(Ljava/lang/Object;)V
/*     */     //   821: aload 40
/*     */     //   823: invokevirtual 320	org/apache/kafka/clients/consumer/ConsumerRecord:value	()Ljava/lang/Object;
/*     */     //   826: invokevirtual 321	java/lang/Object:toString	()Ljava/lang/String;
/*     */     //   829: astore 41
/*     */     //   831: aload 41
/*     */     //   833: ldc_w 323
/*     */     //   836: invokevirtual 327	java/lang/String:split	(Ljava/lang/String;)[Ljava/lang/String;
/*     */     //   839: astore 42
/*     */     //   841: aload 42
/*     */     //   843: iconst_0
/*     */     //   844: aaload
/*     */     //   845: astore 43
/*     */     //   847: iconst_1
/*     */     //   848: invokestatic 333	java/util/concurrent/Executors:newFixedThreadPool	(I)Ljava/util/concurrent/ExecutorService;
/*     */     //   851: astore 44
/*     */     //   853: aload 43
/*     */     //   855: astore 47
/*     */     //   857: getstatic 338	com/yisa/engine/common/CommonTaskType$:MODULE$	Lcom/yisa/engine/common/CommonTaskType$;
/*     */     //   860: invokevirtual 341	com/yisa/engine/common/CommonTaskType$:FrequentlyCar	()Ljava/lang/String;
/*     */     //   863: aload 47
/*     */     //   865: astore 48
/*     */     //   867: dup
/*     */     //   868: ifnonnull +12 -> 880
/*     */     //   871: pop
/*     */     //   872: aload 48
/*     */     //   874: ifnull +14 -> 888
/*     */     //   877: goto +43 -> 920
/*     */     //   880: aload 48
/*     */     //   882: invokevirtual 129	java/lang/Object:equals	(Ljava/lang/Object;)Z
/*     */     //   885: ifeq +35 -> 920
/*     */     //   888: getstatic 346	com/yisa/engine/modules/SparkEngineModulesForVer21$:MODULE$	Lcom/yisa/engine/modules/SparkEngineModulesForVer21$;
/*     */     //   891: aload 41
/*     */     //   893: aload 27
/*     */     //   895: aload 25
/*     */     //   897: aload 44
/*     */     //   899: aload 21
/*     */     //   901: aload 24
/*     */     //   903: aload 10
/*     */     //   905: iload 23
/*     */     //   907: aload 18
/*     */     //   909: invokevirtual 349	com/yisa/engine/modules/SparkEngineModulesForVer21$:FrequentlyCar	(Ljava/lang/String;Lorg/apache/spark/sql/SparkSession;Ljava/lang/String;Ljava/util/concurrent/ExecutorService;Ljava/lang/String;Ljava/lang/String;Ljava/lang/String;ILjava/lang/String;)V
/*     */     //   912: getstatic 75	scala/runtime/BoxedUnit:UNIT	Lscala/runtime/BoxedUnit;
/*     */     //   915: astore 49
/*     */     //   917: goto +370 -> 1287
/*     */     //   920: getstatic 338	com/yisa/engine/common/CommonTaskType$:MODULE$	Lcom/yisa/engine/common/CommonTaskType$;
/*     */     //   923: invokevirtual 352	com/yisa/engine/common/CommonTaskType$:SearchCarByPic	()Ljava/lang/String;
/*     */     //   926: aload 47
/*     */     //   928: astore 50
/*     */     //   930: dup
/*     */     //   931: ifnonnull +12 -> 943
/*     */     //   934: pop
/*     */     //   935: aload 50
/*     */     //   937: ifnull +14 -> 951
/*     */     //   940: goto +43 -> 983
/*     */     //   943: aload 50
/*     */     //   945: invokevirtual 129	java/lang/Object:equals	(Ljava/lang/Object;)Z
/*     */     //   948: ifeq +35 -> 983
/*     */     //   951: getstatic 346	com/yisa/engine/modules/SparkEngineModulesForVer21$:MODULE$	Lcom/yisa/engine/modules/SparkEngineModulesForVer21$;
/*     */     //   954: aload 41
/*     */     //   956: aload 27
/*     */     //   958: aload 25
/*     */     //   960: aload 10
/*     */     //   962: iload 23
/*     */     //   964: aload 26
/*     */     //   966: aload 44
/*     */     //   968: aload 18
/*     */     //   970: aload 21
/*     */     //   972: invokevirtual 355	com/yisa/engine/modules/SparkEngineModulesForVer21$:SearchCarByPic	(Ljava/lang/String;Lorg/apache/spark/sql/SparkSession;Ljava/lang/String;Ljava/lang/String;ILjava/lang/String;Ljava/util/concurrent/ExecutorService;Ljava/lang/String;Ljava/lang/String;)V
/*     */     //   975: getstatic 75	scala/runtime/BoxedUnit:UNIT	Lscala/runtime/BoxedUnit;
/*     */     //   978: astore 49
/*     */     //   980: goto +307 -> 1287
/*     */     //   983: getstatic 338	com/yisa/engine/common/CommonTaskType$:MODULE$	Lcom/yisa/engine/common/CommonTaskType$;
/*     */     //   986: invokevirtual 358	com/yisa/engine/common/CommonTaskType$:SearchSimilarPlate	()Ljava/lang/String;
/*     */     //   989: aload 47
/*     */     //   991: astore 51
/*     */     //   993: dup
/*     */     //   994: ifnonnull +12 -> 1006
/*     */     //   997: pop
/*     */     //   998: aload 51
/*     */     //   1000: ifnull +14 -> 1014
/*     */     //   1003: goto +45 -> 1048
/*     */     //   1006: aload 51
/*     */     //   1008: invokevirtual 129	java/lang/Object:equals	(Ljava/lang/Object;)Z
/*     */     //   1011: ifeq +37 -> 1048
/*     */     //   1014: getstatic 346	com/yisa/engine/modules/SparkEngineModulesForVer21$:MODULE$	Lcom/yisa/engine/modules/SparkEngineModulesForVer21$;
/*     */     //   1017: aload 28
/*     */     //   1019: aload 41
/*     */     //   1021: aload 27
/*     */     //   1023: aload 44
/*     */     //   1025: aload 25
/*     */     //   1027: aload 21
/*     */     //   1029: aload 10
/*     */     //   1031: iload 23
/*     */     //   1033: aload 26
/*     */     //   1035: aload 18
/*     */     //   1037: invokevirtual 361	com/yisa/engine/modules/SparkEngineModulesForVer21$:SearchSimilarPlate	(Lorg/apache/spark/sql/Dataset;Ljava/lang/String;Lorg/apache/spark/sql/SparkSession;Ljava/util/concurrent/ExecutorService;Ljava/lang/String;Ljava/lang/String;Ljava/lang/String;ILjava/lang/String;Ljava/lang/String;)V
/*     */     //   1040: getstatic 75	scala/runtime/BoxedUnit:UNIT	Lscala/runtime/BoxedUnit;
/*     */     //   1043: astore 49
/*     */     //   1045: goto +242 -> 1287
/*     */     //   1048: getstatic 338	com/yisa/engine/common/CommonTaskType$:MODULE$	Lcom/yisa/engine/common/CommonTaskType$;
/*     */     //   1051: invokevirtual 364	com/yisa/engine/common/CommonTaskType$:MultiPoint	()Ljava/lang/String;
/*     */     //   1054: aload 47
/*     */     //   1056: astore 52
/*     */     //   1058: dup
/*     */     //   1059: ifnonnull +12 -> 1071
/*     */     //   1062: pop
/*     */     //   1063: aload 52
/*     */     //   1065: ifnull +14 -> 1079
/*     */     //   1068: goto +43 -> 1111
/*     */     //   1071: aload 52
/*     */     //   1073: invokevirtual 129	java/lang/Object:equals	(Ljava/lang/Object;)Z
/*     */     //   1076: ifeq +35 -> 1111
/*     */     //   1079: getstatic 346	com/yisa/engine/modules/SparkEngineModulesForVer21$:MODULE$	Lcom/yisa/engine/modules/SparkEngineModulesForVer21$;
/*     */     //   1082: aload 28
/*     */     //   1084: aload 41
/*     */     //   1086: aload 27
/*     */     //   1088: aload 44
/*     */     //   1090: aload 25
/*     */     //   1092: aload 21
/*     */     //   1094: aload 10
/*     */     //   1096: iload 23
/*     */     //   1098: aload 18
/*     */     //   1100: invokevirtual 367	com/yisa/engine/modules/SparkEngineModulesForVer21$:MultiPoint	(Lorg/apache/spark/sql/Dataset;Ljava/lang/String;Lorg/apache/spark/sql/SparkSession;Ljava/util/concurrent/ExecutorService;Ljava/lang/String;Ljava/lang/String;Ljava/lang/String;ILjava/lang/String;)V
/*     */     //   1103: getstatic 75	scala/runtime/BoxedUnit:UNIT	Lscala/runtime/BoxedUnit;
/*     */     //   1106: astore 49
/*     */     //   1108: goto +179 -> 1287
/*     */     //   1111: getstatic 338	com/yisa/engine/common/CommonTaskType$:MODULE$	Lcom/yisa/engine/common/CommonTaskType$;
/*     */     //   1114: invokevirtual 370	com/yisa/engine/common/CommonTaskType$:CaseCar	()Ljava/lang/String;
/*     */     //   1117: aload 47
/*     */     //   1119: astore 53
/*     */     //   1121: dup
/*     */     //   1122: ifnonnull +12 -> 1134
/*     */     //   1125: pop
/*     */     //   1126: aload 53
/*     */     //   1128: ifnull +14 -> 1142
/*     */     //   1131: goto +43 -> 1174
/*     */     //   1134: aload 53
/*     */     //   1136: invokevirtual 129	java/lang/Object:equals	(Ljava/lang/Object;)Z
/*     */     //   1139: ifeq +35 -> 1174
/*     */     //   1142: getstatic 346	com/yisa/engine/modules/SparkEngineModulesForVer21$:MODULE$	Lcom/yisa/engine/modules/SparkEngineModulesForVer21$;
/*     */     //   1145: aload 28
/*     */     //   1147: aload 41
/*     */     //   1149: aload 27
/*     */     //   1151: aload 44
/*     */     //   1153: aload 25
/*     */     //   1155: aload 21
/*     */     //   1157: aload 10
/*     */     //   1159: iload 23
/*     */     //   1161: aload 18
/*     */     //   1163: invokevirtual 372	com/yisa/engine/modules/SparkEngineModulesForVer21$:CaseCar	(Lorg/apache/spark/sql/Dataset;Ljava/lang/String;Lorg/apache/spark/sql/SparkSession;Ljava/util/concurrent/ExecutorService;Ljava/lang/String;Ljava/lang/String;Ljava/lang/String;ILjava/lang/String;)V
/*     */     //   1166: getstatic 75	scala/runtime/BoxedUnit:UNIT	Lscala/runtime/BoxedUnit;
/*     */     //   1169: astore 49
/*     */     //   1171: goto +116 -> 1287
/*     */     //   1174: getstatic 338	com/yisa/engine/common/CommonTaskType$:MODULE$	Lcom/yisa/engine/common/CommonTaskType$;
/*     */     //   1177: invokevirtual 375	com/yisa/engine/common/CommonTaskType$:EndStation	()Ljava/lang/String;
/*     */     //   1180: aload 47
/*     */     //   1182: astore 54
/*     */     //   1184: dup
/*     */     //   1185: ifnonnull +12 -> 1197
/*     */     //   1188: pop
/*     */     //   1189: aload 54
/*     */     //   1191: ifnull +14 -> 1205
/*     */     //   1194: goto +43 -> 1237
/*     */     //   1197: aload 54
/*     */     //   1199: invokevirtual 129	java/lang/Object:equals	(Ljava/lang/Object;)Z
/*     */     //   1202: ifeq +35 -> 1237
/*     */     //   1205: getstatic 346	com/yisa/engine/modules/SparkEngineModulesForVer21$:MODULE$	Lcom/yisa/engine/modules/SparkEngineModulesForVer21$;
/*     */     //   1208: aload 28
/*     */     //   1210: aload 41
/*     */     //   1212: aload 27
/*     */     //   1214: aload 44
/*     */     //   1216: aload 25
/*     */     //   1218: aload 21
/*     */     //   1220: aload 10
/*     */     //   1222: iload 23
/*     */     //   1224: aload 18
/*     */     //   1226: invokevirtual 377	com/yisa/engine/modules/SparkEngineModulesForVer21$:EndStation	(Lorg/apache/spark/sql/Dataset;Ljava/lang/String;Lorg/apache/spark/sql/SparkSession;Ljava/util/concurrent/ExecutorService;Ljava/lang/String;Ljava/lang/String;Ljava/lang/String;ILjava/lang/String;)V
/*     */     //   1229: getstatic 75	scala/runtime/BoxedUnit:UNIT	Lscala/runtime/BoxedUnit;
/*     */     //   1232: astore 49
/*     */     //   1234: goto +53 -> 1287
/*     */     //   1237: getstatic 338	com/yisa/engine/common/CommonTaskType$:MODULE$	Lcom/yisa/engine/common/CommonTaskType$;
/*     */     //   1240: invokevirtual 380	com/yisa/engine/common/CommonTaskType$:TogetherCar	()Ljava/lang/String;
/*     */     //   1243: aload 47
/*     */     //   1245: astore 55
/*     */     //   1247: dup
/*     */     //   1248: ifnonnull +12 -> 1260
/*     */     //   1251: pop
/*     */     //   1252: aload 55
/*     */     //   1254: ifnull +14 -> 1268
/*     */     //   1257: goto +78 -> 1335
/*     */     //   1260: aload 55
/*     */     //   1262: invokevirtual 129	java/lang/Object:equals	(Ljava/lang/Object;)Z
/*     */     //   1265: ifeq +70 -> 1335
/*     */     //   1268: getstatic 346	com/yisa/engine/modules/SparkEngineModulesForVer21$:MODULE$	Lcom/yisa/engine/modules/SparkEngineModulesForVer21$;
/*     */     //   1271: aload 27
/*     */     //   1273: aload 41
/*     */     //   1275: aload 25
/*     */     //   1277: aload 10
/*     */     //   1279: invokevirtual 382	com/yisa/engine/modules/SparkEngineModulesForVer21$:TogetherCar	(Lorg/apache/spark/sql/SparkSession;Ljava/lang/String;Ljava/lang/String;Ljava/lang/String;)V
/*     */     //   1282: getstatic 75	scala/runtime/BoxedUnit:UNIT	Lscala/runtime/BoxedUnit;
/*     */     //   1285: astore 49
/*     */     //   1287: new 267	java/util/Date
/*     */     //   1290: dup
/*     */     //   1291: invokespecial 268	java/util/Date:<init>	()V
/*     */     //   1294: invokevirtual 271	java/util/Date:getTime	()J
/*     */     //   1297: lstore 56
/*     */     //   1299: getstatic 56	scala/Predef$:MODULE$	Lscala/Predef$;
/*     */     //   1302: new 155	scala/collection/mutable/StringBuilder
/*     */     //   1305: dup
/*     */     //   1306: invokespecial 156	scala/collection/mutable/StringBuilder:<init>	()V
/*     */     //   1309: ldc_w 384
/*     */     //   1312: invokevirtual 162	scala/collection/mutable/StringBuilder:append	(Ljava/lang/Object;)Lscala/collection/mutable/StringBuilder;
/*     */     //   1315: lload 56
/*     */     //   1317: lload 38
/*     */     //   1319: lsub
/*     */     //   1320: invokestatic 172	scala/runtime/BoxesRunTime:boxToLong	(J)Ljava/lang/Long;
/*     */     //   1323: invokevirtual 162	scala/collection/mutable/StringBuilder:append	(Ljava/lang/Object;)Lscala/collection/mutable/StringBuilder;
/*     */     //   1326: invokevirtual 175	scala/collection/mutable/StringBuilder:toString	()Ljava/lang/String;
/*     */     //   1329: invokevirtual 62	scala/Predef$:println	(Ljava/lang/Object;)V
/*     */     //   1332: goto -651 -> 681
/*     */     //   1335: new 386	scala/MatchError
/*     */     //   1338: dup
/*     */     //   1339: aload 47
/*     */     //   1341: invokespecial 388	scala/MatchError:<init>	(Ljava/lang/Object;)V
/*     */     //   1344: athrow
/*     */     //   1345: astore 46
/*     */     //   1347: getstatic 56	scala/Predef$:MODULE$	Lscala/Predef$;
/*     */     //   1350: ldc_w 285
/*     */     //   1353: invokevirtual 62	scala/Predef$:println	(Ljava/lang/Object;)V
/*     */     //   1356: aload 44
/*     */     //   1358: invokeinterface 290 1 0
/*     */     //   1363: aload 46
/*     */     //   1365: athrow
/*     */     //   1366: new 267	java/util/Date
/*     */     //   1369: dup
/*     */     //   1370: invokespecial 268	java/util/Date:<init>	()V
/*     */     //   1373: invokevirtual 271	java/util/Date:getTime	()J
/*     */     //   1376: lstore 58
/*     */     //   1378: lload 58
/*     */     //   1380: lload 33
/*     */     //   1382: lsub
/*     */     //   1383: new 139	scala/collection/immutable/StringOps
/*     */     //   1386: dup
/*     */     //   1387: getstatic 56	scala/Predef$:MODULE$	Lscala/Predef$;
/*     */     //   1390: aload 17
/*     */     //   1392: invokevirtual 144	scala/Predef$:augmentString	(Ljava/lang/String;)Ljava/lang/String;
/*     */     //   1395: invokespecial 147	scala/collection/immutable/StringOps:<init>	(Ljava/lang/String;)V
/*     */     //   1398: invokevirtual 391	scala/collection/immutable/StringOps:toLong	()J
/*     */     //   1401: lcmp
/*     */     //   1402: ifle +225 -> 1627
/*     */     //   1405: getstatic 56	scala/Predef$:MODULE$	Lscala/Predef$;
/*     */     //   1408: new 155	scala/collection/mutable/StringBuilder
/*     */     //   1411: dup
/*     */     //   1412: invokespecial 156	scala/collection/mutable/StringBuilder:<init>	()V
/*     */     //   1415: ldc_w 393
/*     */     //   1418: invokevirtual 162	scala/collection/mutable/StringBuilder:append	(Ljava/lang/Object;)Lscala/collection/mutable/StringBuilder;
/*     */     //   1421: lload 33
/*     */     //   1423: invokestatic 172	scala/runtime/BoxesRunTime:boxToLong	(J)Ljava/lang/Long;
/*     */     //   1426: invokevirtual 162	scala/collection/mutable/StringBuilder:append	(Ljava/lang/Object;)Lscala/collection/mutable/StringBuilder;
/*     */     //   1429: ldc_w 395
/*     */     //   1432: invokevirtual 162	scala/collection/mutable/StringBuilder:append	(Ljava/lang/Object;)Lscala/collection/mutable/StringBuilder;
/*     */     //   1435: aload_0
/*     */     //   1436: invokevirtual 166	com/yisa/engine/trunk/SparkEngineVer21$:getDateMid	()J
/*     */     //   1439: invokestatic 172	scala/runtime/BoxesRunTime:boxToLong	(J)Ljava/lang/Long;
/*     */     //   1442: invokevirtual 162	scala/collection/mutable/StringBuilder:append	(Ljava/lang/Object;)Lscala/collection/mutable/StringBuilder;
/*     */     //   1445: ldc_w 397
/*     */     //   1448: invokevirtual 162	scala/collection/mutable/StringBuilder:append	(Ljava/lang/Object;)Lscala/collection/mutable/StringBuilder;
/*     */     //   1451: invokevirtual 175	scala/collection/mutable/StringBuilder:toString	()Ljava/lang/String;
/*     */     //   1454: invokevirtual 62	scala/Predef$:println	(Ljava/lang/Object;)V
/*     */     //   1457: new 267	java/util/Date
/*     */     //   1460: dup
/*     */     //   1461: invokespecial 268	java/util/Date:<init>	()V
/*     */     //   1464: invokevirtual 271	java/util/Date:getTime	()J
/*     */     //   1467: lstore 60
/*     */     //   1469: aload 27
/*     */     //   1471: invokevirtual 213	org/apache/spark/sql/SparkSession:catalog	()Lorg/apache/spark/sql/catalog/Catalog;
/*     */     //   1474: aload 25
/*     */     //   1476: invokevirtual 400	org/apache/spark/sql/catalog/Catalog:uncacheTable	(Ljava/lang/String;)V
/*     */     //   1479: aload 27
/*     */     //   1481: invokevirtual 213	org/apache/spark/sql/SparkSession:catalog	()Lorg/apache/spark/sql/catalog/Catalog;
/*     */     //   1484: aload 25
/*     */     //   1486: invokevirtual 404	org/apache/spark/sql/catalog/Catalog:dropTempView	(Ljava/lang/String;)Z
/*     */     //   1489: pop
/*     */     //   1490: aload 27
/*     */     //   1492: invokevirtual 213	org/apache/spark/sql/SparkSession:catalog	()Lorg/apache/spark/sql/catalog/Catalog;
/*     */     //   1495: invokevirtual 407	org/apache/spark/sql/catalog/Catalog:clearCache	()V
/*     */     //   1498: ldc2_w 408
/*     */     //   1501: invokestatic 415	java/lang/Thread:sleep	(J)V
/*     */     //   1504: new 155	scala/collection/mutable/StringBuilder
/*     */     //   1507: dup
/*     */     //   1508: invokespecial 156	scala/collection/mutable/StringBuilder:<init>	()V
/*     */     //   1511: ldc -98
/*     */     //   1513: invokevirtual 162	scala/collection/mutable/StringBuilder:append	(Ljava/lang/Object;)Lscala/collection/mutable/StringBuilder;
/*     */     //   1516: lload 58
/*     */     //   1518: invokestatic 172	scala/runtime/BoxesRunTime:boxToLong	(J)Ljava/lang/Long;
/*     */     //   1521: invokevirtual 162	scala/collection/mutable/StringBuilder:append	(Ljava/lang/Object;)Lscala/collection/mutable/StringBuilder;
/*     */     //   1524: invokevirtual 175	scala/collection/mutable/StringBuilder:toString	()Ljava/lang/String;
/*     */     //   1527: astore 25
/*     */     //   1529: aload_0
/*     */     //   1530: aload 27
/*     */     //   1532: aload 15
/*     */     //   1534: aload 22
/*     */     //   1536: iload 23
/*     */     //   1538: invokevirtual 202	com/yisa/engine/trunk/SparkEngineVer21$:loadRealtimeData	(Lorg/apache/spark/sql/SparkSession;Ljava/lang/String;Ljava/lang/String;I)Lorg/apache/spark/sql/Dataset;
/*     */     //   1541: astore 28
/*     */     //   1543: aload 28
/*     */     //   1545: aload 25
/*     */     //   1547: invokevirtual 207	org/apache/spark/sql/Dataset:createOrReplaceTempView	(Ljava/lang/String;)V
/*     */     //   1550: aload 27
/*     */     //   1552: invokevirtual 213	org/apache/spark/sql/SparkSession:catalog	()Lorg/apache/spark/sql/catalog/Catalog;
/*     */     //   1555: aload 25
/*     */     //   1557: invokevirtual 218	org/apache/spark/sql/catalog/Catalog:cacheTable	(Ljava/lang/String;)V
/*     */     //   1560: aload_0
/*     */     //   1561: aload 27
/*     */     //   1563: aload 25
/*     */     //   1565: aload 24
/*     */     //   1567: aload 10
/*     */     //   1569: invokevirtual 229	com/yisa/engine/trunk/SparkEngineVer21$:runFirstTask	(Lorg/apache/spark/sql/SparkSession;Ljava/lang/String;Ljava/lang/String;Ljava/lang/String;)V
/*     */     //   1572: new 267	java/util/Date
/*     */     //   1575: dup
/*     */     //   1576: invokespecial 268	java/util/Date:<init>	()V
/*     */     //   1579: invokevirtual 271	java/util/Date:getTime	()J
/*     */     //   1582: lstore 33
/*     */     //   1584: lload 33
/*     */     //   1586: lstore 62
/*     */     //   1588: getstatic 56	scala/Predef$:MODULE$	Lscala/Predef$;
/*     */     //   1591: new 155	scala/collection/mutable/StringBuilder
/*     */     //   1594: dup
/*     */     //   1595: invokespecial 156	scala/collection/mutable/StringBuilder:<init>	()V
/*     */     //   1598: ldc_w 417
/*     */     //   1601: invokevirtual 162	scala/collection/mutable/StringBuilder:append	(Ljava/lang/Object;)Lscala/collection/mutable/StringBuilder;
/*     */     //   1604: lload 62
/*     */     //   1606: lload 60
/*     */     //   1608: lsub
/*     */     //   1609: invokestatic 172	scala/runtime/BoxesRunTime:boxToLong	(J)Ljava/lang/Long;
/*     */     //   1612: invokevirtual 162	scala/collection/mutable/StringBuilder:append	(Ljava/lang/Object;)Lscala/collection/mutable/StringBuilder;
/*     */     //   1615: ldc_w 419
/*     */     //   1618: invokevirtual 162	scala/collection/mutable/StringBuilder:append	(Ljava/lang/Object;)Lscala/collection/mutable/StringBuilder;
/*     */     //   1621: invokevirtual 175	scala/collection/mutable/StringBuilder:toString	()Ljava/lang/String;
/*     */     //   1624: invokevirtual 62	scala/Predef$:println	(Ljava/lang/Object;)V
/*     */     //   1627: aload 31
/*     */     //   1629: ldc2_w 420
/*     */     //   1632: invokevirtual 425	org/apache/kafka/clients/consumer/KafkaConsumer:poll	(J)Lorg/apache/kafka/clients/consumer/ConsumerRecords;
/*     */     //   1635: astore 35
/*     */     //   1637: aload 35
/*     */     //   1639: invokevirtual 431	org/apache/kafka/clients/consumer/ConsumerRecords:iterator	()Ljava/util/Iterator;
/*     */     //   1642: astore 36
/*     */     //   1644: aload 31
/*     */     //   1646: invokevirtual 434	org/apache/kafka/clients/consumer/KafkaConsumer:commitSync	()V
/*     */     //   1649: goto -952 -> 697
/*     */     //   1652: astore 37
/*     */     //   1654: getstatic 56	scala/Predef$:MODULE$	Lscala/Predef$;
/*     */     //   1657: ldc_w 436
/*     */     //   1660: invokevirtual 62	scala/Predef$:println	(Ljava/lang/Object;)V
/*     */     //   1663: getstatic 56	scala/Predef$:MODULE$	Lscala/Predef$;
/*     */     //   1666: aload 37
/*     */     //   1668: invokevirtual 66	java/lang/Exception:getMessage	()Ljava/lang/String;
/*     */     //   1671: invokevirtual 62	scala/Predef$:println	(Ljava/lang/Object;)V
/*     */     //   1674: getstatic 56	scala/Predef$:MODULE$	Lscala/Predef$;
/*     */     //   1677: aload 37
/*     */     //   1679: invokevirtual 69	java/lang/Exception:printStackTrace	()V
/*     */     //   1682: getstatic 75	scala/runtime/BoxedUnit:UNIT	Lscala/runtime/BoxedUnit;
/*     */     //   1685: invokevirtual 62	scala/Predef$:println	(Ljava/lang/Object;)V
/*     */     //   1688: ldc2_w 437
/*     */     //   1691: invokestatic 415	java/lang/Thread:sleep	(J)V
/*     */     //   1694: aload 31
/*     */     //   1696: invokevirtual 441	org/apache/kafka/clients/consumer/KafkaConsumer:commitAsync	()V
/*     */     //   1699: goto -1002 -> 697
/*     */     // Line number table:
/*     */     //   Java source line #41	-> byte code offset #0
/*     */     //   Java source line #42	-> byte code offset #2
/*     */     //   Java source line #44	-> byte code offset #10
/*     */     //   Java source line #45	-> byte code offset #24
/*     */     //   Java source line #46	-> byte code offset #30
/*     */     //   Java source line #48	-> byte code offset #37
/*     */     //   Java source line #49	-> byte code offset #51
/*     */     //   Java source line #50	-> byte code offset #57
/*     */     //   Java source line #52	-> byte code offset #64
/*     */     //   Java source line #53	-> byte code offset #78
/*     */     //   Java source line #54	-> byte code offset #84
/*     */     //   Java source line #56	-> byte code offset #91
/*     */     //   Java source line #57	-> byte code offset #100
/*     */     //   Java source line #59	-> byte code offset #111
/*     */     //   Java source line #43	-> byte code offset #111
/*     */     //   Java source line #60	-> byte code offset #113
/*     */     //   Java source line #61	-> byte code offset #121
/*     */     //   Java source line #62	-> byte code offset #132
/*     */     //   Java source line #63	-> byte code offset #146
/*     */     //   Java source line #64	-> byte code offset #155
/*     */     //   Java source line #65	-> byte code offset #163
/*     */     //   Java source line #68	-> byte code offset #167
/*     */     //   Java source line #69	-> byte code offset #175
/*     */     //   Java source line #70	-> byte code offset #183
/*     */     //   Java source line #80	-> byte code offset #191
/*     */     //   Java source line #81	-> byte code offset #200
/*     */     //   Java source line #82	-> byte code offset #212
/*     */     //   Java source line #83	-> byte code offset #226
/*     */     //   Java source line #84	-> byte code offset #240
/*     */     //   Java source line #86	-> byte code offset #254
/*     */     //   Java source line #88	-> byte code offset #268
/*     */     //   Java source line #89	-> byte code offset #272
/*     */     //   Java source line #90	-> byte code offset #299
/*     */     //   Java source line #92	-> byte code offset #316
/*     */     //   Java source line #95	-> byte code offset #330
/*     */     //   Java source line #96	-> byte code offset #344
/*     */     //   Java source line #97	-> byte code offset #358
/*     */     //   Java source line #98	-> byte code offset #388
/*     */     //   Java source line #102	-> byte code offset #402
/*     */     //   Java source line #103	-> byte code offset #429
/*     */     //   Java source line #105	-> byte code offset #433
/*     */     //   Java source line #106	-> byte code offset #436
/*     */     //   Java source line #107	-> byte code offset #439
/*     */     //   Java source line #108	-> byte code offset #444
/*     */     //   Java source line #105	-> byte code offset #447
/*     */     //   Java source line #112	-> byte code offset #449
/*     */     //   Java source line #113	-> byte code offset #463
/*     */     //   Java source line #114	-> byte code offset #470
/*     */     //   Java source line #116	-> byte code offset #480
/*     */     //   Java source line #117	-> byte code offset #494
/*     */     //   Java source line #128	-> byte code offset #501
/*     */     //   Java source line #130	-> byte code offset #507
/*     */     //   Java source line #134	-> byte code offset #519
/*     */     //   Java source line #135	-> byte code offset #528
/*     */     //   Java source line #136	-> byte code offset #538
/*     */     //   Java source line #137	-> byte code offset #548
/*     */     //   Java source line #144	-> byte code offset #558
/*     */     //   Java source line #145	-> byte code offset #568
/*     */     //   Java source line #146	-> byte code offset #578
/*     */     //   Java source line #148	-> byte code offset #589
/*     */     //   Java source line #149	-> byte code offset #598
/*     */     //   Java source line #150	-> byte code offset #606
/*     */     //   Java source line #152	-> byte code offset #613
/*     */     //   Java source line #153	-> byte code offset #625
/*     */     //   Java source line #155	-> byte code offset #633
/*     */     //   Java source line #158	-> byte code offset #642
/*     */     //   Java source line #228	-> byte code offset #645
/*     */     //   Java source line #193	-> byte code offset #645
/*     */     //   Java source line #229	-> byte code offset #647
/*     */     //   Java source line #230	-> byte code offset #656
/*     */     //   Java source line #231	-> byte code offset #667
/*     */     //   Java source line #234	-> byte code offset #681
/*     */     //   Java source line #235	-> byte code offset #690
/*     */     //   Java source line #179	-> byte code offset #697
/*     */     //   Java source line #181	-> byte code offset #707
/*     */     //   Java source line #182	-> byte code offset #740
/*     */     //   Java source line #184	-> byte code offset #767
/*     */     //   Java source line #185	-> byte code offset #779
/*     */     //   Java source line #186	-> byte code offset #791
/*     */     //   Java source line #187	-> byte code offset #821
/*     */     //   Java source line #188	-> byte code offset #831
/*     */     //   Java source line #189	-> byte code offset #841
/*     */     //   Java source line #192	-> byte code offset #847
/*     */     //   Java source line #194	-> byte code offset #853
/*     */     //   Java source line #197	-> byte code offset #857
/*     */     //   Java source line #198	-> byte code offset #888
/*     */     //   Java source line #201	-> byte code offset #920
/*     */     //   Java source line #202	-> byte code offset #951
/*     */     //   Java source line #205	-> byte code offset #983
/*     */     //   Java source line #206	-> byte code offset #1014
/*     */     //   Java source line #209	-> byte code offset #1048
/*     */     //   Java source line #210	-> byte code offset #1079
/*     */     //   Java source line #213	-> byte code offset #1111
/*     */     //   Java source line #214	-> byte code offset #1142
/*     */     //   Java source line #217	-> byte code offset #1174
/*     */     //   Java source line #218	-> byte code offset #1205
/*     */     //   Java source line #221	-> byte code offset #1237
/*     */     //   Java source line #222	-> byte code offset #1268
/*     */     //   Java source line #225	-> byte code offset #1287
/*     */     //   Java source line #226	-> byte code offset #1299
/*     */     //   Java source line #194	-> byte code offset #1335
/*     */     //   Java source line #233	-> byte code offset #1345
/*     */     //   Java source line #234	-> byte code offset #1347
/*     */     //   Java source line #235	-> byte code offset #1356
/*     */     //   Java source line #241	-> byte code offset #1366
/*     */     //   Java source line #242	-> byte code offset #1378
/*     */     //   Java source line #243	-> byte code offset #1405
/*     */     //   Java source line #244	-> byte code offset #1457
/*     */     //   Java source line #248	-> byte code offset #1469
/*     */     //   Java source line #249	-> byte code offset #1479
/*     */     //   Java source line #250	-> byte code offset #1490
/*     */     //   Java source line #251	-> byte code offset #1498
/*     */     //   Java source line #254	-> byte code offset #1504
/*     */     //   Java source line #255	-> byte code offset #1529
/*     */     //   Java source line #256	-> byte code offset #1543
/*     */     //   Java source line #258	-> byte code offset #1550
/*     */     //   Java source line #259	-> byte code offset #1560
/*     */     //   Java source line #261	-> byte code offset #1572
/*     */     //   Java source line #263	-> byte code offset #1584
/*     */     //   Java source line #264	-> byte code offset #1588
/*     */     //   Java source line #160	-> byte code offset #1627
/*     */     //   Java source line #161	-> byte code offset #1637
/*     */     //   Java source line #167	-> byte code offset #1644
/*     */     //   Java source line #169	-> byte code offset #1652
/*     */     //   Java source line #166	-> byte code offset #1652
/*     */     //   Java source line #170	-> byte code offset #1654
/*     */     //   Java source line #171	-> byte code offset #1663
/*     */     //   Java source line #172	-> byte code offset #1674
/*     */     //   Java source line #173	-> byte code offset #1688
/*     */     //   Java source line #174	-> byte code offset #1694
/*     */     // Local variable table:
/*     */     //   start	length	slot	name	signature
/*     */     //   0	1702	0	this	
/*     */     //   0	1702	1	args	String[]
/*     */     //   2	1700	2	cmd	org.apache.commons.cli.CommandLine
/*     */     //   10	1692	3	options	org.apache.commons.cli.Options
/*     */     //   155	12	5	formatter	org.apache.commons.cli.HelpFormatter
/*     */     //   24	84	6	zk	org.apache.commons.cli.Option
/*     */     //   51	57	7	kafkaConsumerID	org.apache.commons.cli.Option
/*     */     //   78	30	8	isTest	org.apache.commons.cli.Option
/*     */     //   100	8	9	parser	org.apache.commons.cli.PosixParser
/*     */     //   175	1527	10	zkHostPort	String
/*     */     //   183	1519	11	kafkagroupid	String
/*     */     //   191	1511	12	test	String
/*     */     //   200	1502	13	zkUtil	com.yisa.wifi.zookeeper.ZookeeperUtil
/*     */     //   212	1490	14	configs	java.util.Map
/*     */     //   226	1476	15	hdfsPath	String
/*     */     //   240	1462	16	kafka	String
/*     */     //   254	1448	17	refreshData	String
/*     */     //   268	1434	18	prestoHostPort	String
/*     */     //   272	1430	19	topic	String
/*     */     //   344	1358	21	prestoTableName	String
/*     */     //   358	1344	22	dataPath1	String
/*     */     //   388	1314	23	cacheDays	int
/*     */     //   402	1300	24	frequentlyCarResultTableName	String
/*     */     //   429	1273	25	tableName	String
/*     */     //   433	1269	26	tableNameAll	String
/*     */     //   449	1253	27	sparkSession	SparkSession
/*     */     //   463	1239	28	inittable2	Dataset
/*     */     //   494	1208	29	loadAllData	Dataset
/*     */     //   528	1174	30	props	java.util.Properties
/*     */     //   589	1113	31	consumer	org.apache.kafka.clients.consumer.KafkaConsumer
/*     */     //   598	1104	32	topics	java.util.ArrayList
/*     */     //   625	1077	33	preHour	long
/*     */     //   1637	65	35	records	org.apache.kafka.clients.consumer.ConsumerRecords
/*     */     //   1644	58	36	rei	java.util.Iterator
/*     */     //   779	923	38	now1	long
/*     */     //   791	911	40	record	org.apache.kafka.clients.consumer.ConsumerRecord
/*     */     //   831	871	41	line	String
/*     */     //   841	861	42	line_arr	String[]
/*     */     //   847	855	43	taskType	String
/*     */     //   853	849	44	threadPool	java.util.concurrent.ExecutorService
/*     */     //   1299	33	56	now2	long
/*     */     //   1378	324	58	nowTime	long
/*     */     //   1469	158	60	loadDataStart	long
/*     */     //   1588	39	62	loadDataEnd	long
/*     */     // Exception table:
/*     */     //   from	to	target	type
/*     */     //   10	111	111	java/lang/Exception
/*     */     //   853	1345	645	java/lang/Exception
/*     */     //   645	681	1345	finally
/*     */     //   853	1345	1345	finally
/*     */     //   1644	1652	1652	java/lang/Exception
/*     */   }
/*     */   
/*     */   public Dataset<Row> loadAlltimeData(SparkSession sparkSession, String hdfsPath, String dataPath, int cacheDays)
/*     */   {
/* 271 */     Dataset loadData = sparkSession.read().option("mergeSchema", "true").parquet(new StringBuilder().append(hdfsPath).append(dataPath).toString());
/* 272 */     Dataset loadData_filter = loadData
/* 273 */       .filter("platenumber !=  '0' ")
/* 274 */       .filter(new AbstractFunction1() { public final boolean apply(Row x) { return ((String)x.getAs("platenumber")).length() > 1; }
/* 275 */       }).filter(new AbstractFunction1() { public final boolean apply(Row x) { return ((String)x.getAs("platenumber")).length() < 20; }
/* 276 */       });
/* 277 */     return loadData_filter;
/*     */   }
/*     */   
/*     */   public Dataset<Row> loadRealtimeData(SparkSession sparkSession, String hdfsPath, String dataPath, int cacheDays)
/*     */   {
/* 282 */     Dataset loadData = sparkSession.read().option("mergeSchema", "true").parquet(new StringBuilder().append(hdfsPath).append(dataPath).toString());
/* 283 */     Dataset loadData_filter = loadData
/* 284 */       .filter("platenumber !=  '0' ")
/* 285 */       .filter(new AbstractFunction1() { public final boolean apply(Row x) { return ((String)x.getAs("platenumber")).length() > 1; }
/* 286 */       }).filter(new AbstractFunction1() { public final boolean apply(Row x) { return ((String)x.getAs("platenumber")).length() < 20; }
/* 287 */       }).filter(new StringBuilder().append("dateid >= ").append(getLCacheDataDateid(cacheDays)).toString());
/*     */     
/*     */ 
/*     */ 
/*     */ 
/*     */ 
/* 293 */     return loadData_filter;
/*     */   }
/*     */   
/*     */   public long getDateMid()
/*     */   {
/* 298 */     SimpleDateFormat format = new SimpleDateFormat("yyyyMMddHHmm");
/* 299 */     String date_S = format.format(new Date());
/* 300 */     return new StringOps(Predef..MODULE$.augmentString(date_S.substring(0, new StringOps(Predef..MODULE$.augmentString(date_S)).size() - 2))).toLong();
/*     */   }
/*     */   
/*     */ 
/*     */   public void runFirstTask(SparkSession sparkSession, String tableName, String frequentlyCarResultTableName, String zkHostPort)
/*     */   {
/* 306 */     sparkSession.sql(new StringBuilder().append("select count(*) from ").append(tableName).toString()).show();
/*     */   }
/*     */   
/*     */ 
/*     */ 
/*     */ 
/*     */ 
/*     */ 
/*     */   public void registerUDF(SparkSession sparkSession)
/*     */   {
/* 316 */     JavaUniverse $u = ;;;; {
/* 317 */       public final long apply(String text, final String test2) { final byte[] byteData = Base64.getDecoder().decode(text);
/* 318 */         final byte[] oldData = Base64.getDecoder().decode(test2);
/* 319 */         final LongRef num = LongRef.create(0L);RichInt..MODULE$
/* 320 */           .until$extension0(Predef..MODULE$.intWrapper(0), byteData.length).withFilter(new AbstractFunction1.mcZI.sp() { public boolean apply$mcZI$sp(int i) { return test2.length() > 30; } public final boolean apply(int i) { return apply$mcZI$sp(i); } }).foreach(new AbstractFunction1.mcVI.sp() { public final void apply(int i) { apply$mcVI$sp(i); }
/* 321 */             public void apply$mcVI$sp(int i) { int n = (byteData[i] & 0xFF) - (oldData[i] & 0xFF);
/* 322 */               num.elem += n * n;
/* 323 */             } });
/* 324 */         return num.elem; } }, ((TypeTags)package..MODULE$.universe()).TypeTag().Long(), ((TypeTags)$u).TypeTag().apply((Mirror)$m, new TypeCreator()
/*     */     {
/*     */       public static final long serialVersionUID = 0L;
/*     */       public static final long serialVersionUID = 0L;
/*     */       public static final long serialVersionUID = 0L;
/*     */       public <U extends Universe, > Types.TypeApi apply(Mirror<U> $m$untyped)
/*     */       {
/* 316 */         Universe $u = $m$untyped.universe();Mirror $m = $m$untyped;return $u.internal().reificationSupport().TypeRef($u.internal().reificationSupport().SingleType($u.internal().reificationSupport().ThisType($m.staticPackage("scala").asModule().moduleClass()), $m.staticModule("scala.Predef")), $u.internal().reificationSupport().selectType($m.staticModule("scala.Predef").asModule().moduleClass(), "String"), Nil..MODULE$); } }
/*     */     
/*     */ 
/*     */ 
/*     */ 
/*     */ 
/*     */ 
/*     */ 
/* 324 */       ), ((TypeTags)$u).TypeTag().apply((Mirror)$m, new TypeCreator() { public <U extends Universe, > Types.TypeApi apply(Mirror<U> $m$untyped) { Universe $u = $m$untyped.universe();Mirror $m = $m$untyped;return $u.internal().reificationSupport().TypeRef($u.internal().reificationSupport().SingleType($u.internal().reificationSupport().ThisType($m.staticPackage("scala").asModule().moduleClass()), $m.staticModule("scala.Predef")), $u.internal().reificationSupport().selectType($m.staticModule("scala.Predef").asModule().moduleClass(), "String"), Nil..MODULE$);
/*     */ 
/*     */ 
/*     */ 
/*     */ 
/*     */         }
/*     */         
/*     */ 
/*     */ 
/*     */ 
/*     */ 
/* 327 */       }));
/* 328 */     JavaUniverse $u = ;;;; { public static final long serialVersionUID = 0L;
/*     */       
/* 330 */       public final int apply(final String s1, final String s2) { int len1 = s1.length();
/* 331 */         int len2 = s2.length();
/* 332 */         final IntRef len = IntRef.create(0);
/* 333 */         if ((len1 != len2) || (s1.charAt(0) != s2.charAt(0))) {
/* 334 */           len.elem = 10;
/*     */         }
/*     */         else {
/* 337 */           RichInt..MODULE$.until$extension0(Predef..MODULE$.intWrapper(1), len1).foreach$mVc$sp(new AbstractFunction1.mcVI.sp() { public final void apply(int i) { apply$mcVI$sp(i); }
/*     */             
/* 339 */             public void apply$mcVI$sp(int i) { if (s1.charAt(i) != s2.charAt(i))
/*     */               {
/*     */ 
/*     */ 
/* 343 */                 len.elem += 1; }
/*     */             }
/*     */           });
/*     */         }
/* 347 */         return len.elem; } }, ((TypeTags)package..MODULE$.universe()).TypeTag().Int(), ((TypeTags)$u).TypeTag().apply((Mirror)$m, new TypeCreator()
/*     */     {
/*     */       public static final long serialVersionUID = 0L;
/*     */       public <U extends Universe, > Types.TypeApi apply(Mirror<U> $m$untyped)
/*     */       {
/* 328 */         Universe $u = $m$untyped.universe();Mirror $m = $m$untyped;return $u.internal().reificationSupport().TypeRef($u.internal().reificationSupport().SingleType($u.internal().reificationSupport().ThisType($m.staticPackage("scala").asModule().moduleClass()), $m.staticModule("scala.Predef")), $u.internal().reificationSupport().selectType($m.staticModule("scala.Predef").asModule().moduleClass(), "String"), Nil..MODULE$); } }
/*     */     
/*     */ 
/*     */ 
/*     */ 
/*     */ 
/*     */ 
/*     */ 
/*     */ 
/*     */ 
/*     */ 
/*     */ 
/*     */ 
/*     */ 
/*     */ 
/*     */ 
/*     */ 
/*     */ 
/*     */ 
/* 347 */       ), ((TypeTags)$u).TypeTag().apply((Mirror)$m, new TypeCreator() { public <U extends Universe, > Types.TypeApi apply(Mirror<U> $m$untyped) { Universe $u = $m$untyped.universe();Mirror $m = $m$untyped;return $u.internal().reificationSupport().TypeRef($u.internal().reificationSupport().SingleType($u.internal().reificationSupport().ThisType($m.staticPackage("scala").asModule().moduleClass()), $m.staticModule("scala.Predef")), $u.internal().reificationSupport().selectType($m.staticModule("scala.Predef").asModule().moduleClass(), "String"), Nil..MODULE$);
/*     */ 
/*     */ 
/*     */ 
/*     */ 
/*     */ 
/*     */ 
/*     */ 
/*     */ 
/*     */ 
/*     */         }
/*     */         
/*     */ 
/*     */ 
/*     */ 
/*     */ 
/*     */ 
/*     */ 
/*     */ 
/*     */ 
/*     */ 
/*     */ 
/* 350 */       }));
/* 351 */     JavaUniverse $u = ;;;; {
/* 352 */       public final int apply(final String s, final String t) { int sLen = s.length();
/* 353 */         final int tLen = t.length();
/* 354 */         int si = 0;
/* 355 */         int ti = 0;
/* 356 */         final CharRef ch1 = CharRef.create('\000');
/* 357 */         final CharRef ch2 = CharRef.create('\000');
/* 358 */         final IntRef cost = IntRef.create(0);
/*     */         
/*     */ 
/*     */ 
/*     */ 
/*     */ 
/*     */ 
/*     */ 
/*     */ 
/* 367 */         final ObjectRef d = ObjectRef.create((int[][])Array..MODULE$.ofDim(sLen + 1, tLen + 1, ClassTag..MODULE$.Int()));RichInt..MODULE$
/* 368 */           .to$extension0(Predef..MODULE$.intWrapper(0), sLen).foreach$mVc$sp(new AbstractFunction1.mcVI.sp() { public final void apply(int si) { apply$mcVI$sp(si); }
/* 369 */             public void apply$mcVI$sp(int si) { ((int[][])d.elem)[si][0] = si; }
/* 370 */           });RichInt..MODULE$
/* 371 */           .to$extension0(Predef..MODULE$.intWrapper(0), tLen).foreach$mVc$sp(new AbstractFunction1.mcVI.sp() { public final void apply(int ti) { apply$mcVI$sp(ti); }
/* 372 */             public void apply$mcVI$sp(int ti) { ((int[][])d.elem)[0][ti] = ti; }
/* 373 */           });RichInt..MODULE$
/* 374 */           .to$extension0(Predef..MODULE$.intWrapper(1), sLen).foreach$mVc$sp(new AbstractFunction1.mcVI.sp() { public final void apply(int si) { apply$mcVI$sp(si); }
/* 375 */             public void apply$mcVI$sp(final int si) { ch1.elem = s.charAt(si - 1);RichInt..MODULE$
/* 376 */                 .to$extension0(Predef..MODULE$.intWrapper(1), tLen).foreach$mVc$sp(new AbstractFunction1.mcVI.sp() { public final void apply(int ti) { apply$mcVI$sp(ti); }
/* 377 */                   public void apply$mcVI$sp(int ti) { SparkEngineVer21..anonfun.registerUDF.3..anonfun.apply.6.this.ch2$1.elem = SparkEngineVer21..anonfun.registerUDF.3..anonfun.apply.6.this.t$1.charAt(ti - 1);
/* 378 */                     if (SparkEngineVer21..anonfun.registerUDF.3..anonfun.apply.6.this.ch1$1.elem == SparkEngineVer21..anonfun.registerUDF.3..anonfun.apply.6.this.ch2$1.elem) {
/* 379 */                       SparkEngineVer21..anonfun.registerUDF.3..anonfun.apply.6.this.cost$1.elem = 0;
/*     */                     } else {
/* 381 */                       SparkEngineVer21..anonfun.registerUDF.3..anonfun.apply.6.this.cost$1.elem = 1;
/*     */                     }
/* 383 */                     ((int[][])SparkEngineVer21..anonfun.registerUDF.3..anonfun.apply.6.this.d$1.elem)[si][ti] = Math.min(Math.min(((int[][])SparkEngineVer21..anonfun.registerUDF.3..anonfun.apply.6.this.d$1.elem)[(si - 1)][ti] + 1, ((int[][])SparkEngineVer21..anonfun.registerUDF.3..anonfun.apply.6.this.d$1.elem)[si][(ti - 1)] + 1), ((int[][])SparkEngineVer21..anonfun.registerUDF.3..anonfun.apply.6.this.d$1.elem)[(si - 1)][(ti - 1)] + SparkEngineVer21..anonfun.registerUDF.3..anonfun.apply.6.this.cost$1.elem);
/*     */                   }
/*     */                 });
/*     */             }
/* 351 */           }
/*     */           
/*     */ 
/*     */ 
/*     */ 
/*     */ 
/*     */ 
/*     */ 
/*     */ 
/*     */ 
/*     */ 
/*     */ 
/*     */ 
/*     */ 
/*     */ 
/*     */ 
/*     */ 
/*     */ 
/*     */ 
/*     */ 
/*     */ 
/*     */ 
/*     */ 
/* 374 */           );return 
/*     */         
/* 376 */            ?  :  ?  :  ?  : 
/*     */           
/*     */ 
/*     */ 
/*     */ 
/*     */ 
/*     */ 
/*     */ 
/*     */ 
/*     */ 
/*     */ 
/* 387 */           ((int[][])d.elem)[sLen][tLen]; } }, ((TypeTags)package..MODULE$.universe()).TypeTag().Int(), ((TypeTags)$u).TypeTag().apply((Mirror)$m, new TypeCreator()
/*     */     {
/*     */       public <U extends Universe, > Types.TypeApi apply(Mirror<U> $m$untyped)
/*     */       {
/* 351 */         Universe $u = $m$untyped.universe();Mirror $m = $m$untyped;return $u.internal().reificationSupport().TypeRef($u.internal().reificationSupport().SingleType($u.internal().reificationSupport().ThisType($m.staticPackage("scala").asModule().moduleClass()), $m.staticModule("scala.Predef")), $u.internal().reificationSupport().selectType($m.staticModule("scala.Predef").asModule().moduleClass(), "String"), Nil..MODULE$); } }
/*     */     
/*     */ 
/*     */ 
/*     */ 
/*     */ 
/*     */ 
/*     */ 
/*     */ 
/*     */ 
/*     */ 
/*     */ 
/*     */ 
/*     */ 
/*     */ 
/*     */ 
/*     */ 
/*     */ 
/*     */ 
/*     */ 
/*     */ 
/*     */ 
/*     */ 
/*     */ 
/*     */ 
/*     */ 
/*     */ 
/*     */ 
/*     */ 
/*     */ 
/*     */ 
/*     */ 
/*     */ 
/*     */ 
/*     */ 
/*     */ 
/* 387 */       ), ((TypeTags)$u).TypeTag().apply((Mirror)$m, new TypeCreator() { public <U extends Universe, > Types.TypeApi apply(Mirror<U> $m$untyped) { Universe $u = $m$untyped.universe();Mirror $m = $m$untyped;return $u.internal().reificationSupport().TypeRef($u.internal().reificationSupport().SingleType($u.internal().reificationSupport().ThisType($m.staticPackage("scala").asModule().moduleClass()), $m.staticModule("scala.Predef")), $u.internal().reificationSupport().selectType($m.staticModule("scala.Predef").asModule().moduleClass(), "String"), Nil..MODULE$);
/*     */         }
/*     */       }));
/*     */   }
/*     */   
/*     */ 
/*     */ 
/*     */ 
/*     */   public static final long serialVersionUID = 0L;
/*     */   
/*     */ 
/*     */ 
/*     */   public static final long serialVersionUID = 0L;
/*     */   
/*     */ 
/*     */ 
/*     */   public static final long serialVersionUID = 0L;
/*     */   
/*     */ 
/*     */ 
/*     */   public static final long serialVersionUID = 0L;
/*     */   
/*     */ 
/*     */ 
/*     */   public static final long serialVersionUID = 0L;
/*     */   
/*     */ 
/*     */ 
/*     */   public static final long serialVersionUID = 0L;
/*     */   
/*     */ 
/*     */ 
/*     */   public static final long serialVersionUID = 0L;
/*     */   
/*     */ 
/*     */   public static final long serialVersionUID = 0L;
/*     */   
/*     */ 
/*     */   public static final long serialVersionUID = 0L;
/*     */   
/*     */ 
/*     */   public String getLCacheDataDateid(int days)
/*     */   {
/* 394 */     Calendar cal = Calendar.getInstance();
/* 395 */     cal.setTime(new Date());
/* 396 */     cal.add(5, -days);
/* 397 */     SimpleDateFormat format = new SimpleDateFormat("yyyyMMdd");
/* 398 */     return format.format(cal.getTime());
/*     */   }
/*     */   
/* 401 */   private SparkEngineVer21$() { MODULE$ = this; }
/*     */ }


/* Location:              E:\BaiduYunDownload\\SparkEngine\jars\YISAEngineBySpark2-4.0.6-SNAPSHOT-jar-with-dependencies.jar!\com\yisa\engine\trunk\SparkEngineVer21$.class
 * Java compiler version: 6 (50.0)
 * JD-Core Version:       0.7.1
 */