/*    */ package com.yisa.engine.branch;
/*    */ 
/*    */ import com.google.gson.Gson;
/*    */ import com.google.gson.reflect.TypeToken;
/*    */ import com.yisa.engine.common.InputBean;
/*    */ import java.lang.reflect.Type;
/*    */ import java.sql.Connection;
/*    */ import java.sql.DriverManager;
/*    */ import java.sql.ResultSet;
/*    */ import java.sql.Statement;
/*    */ import org.apache.spark.sql.SparkSession;
/*    */ import scala.Predef.;
/*    */ import scala.Serializable;
/*    */ import scala.collection.mutable.StringBuilder;
/*    */ import scala.reflect.ScalaSignature;
/*    */ import scala.runtime.AbstractFunction1;
/*    */ import scala.runtime.AbstractFunction2;
/*    */ 
/*    */ 
/*    */ 
/*    */ 
/*    */ 
/*    */ 
/*    */ 
/*    */ 
/*    */ 
/*    */ 
/*    */ 
/*    */ 
/*    */ 
/*    */ 
/*    */ @ScalaSignature(bytes="\006\00153A!\001\002\001\027\t!3\013]1sW\026sw-\0338f-J2uN\035+sCZ,G\016V8hKRDWM\035)sKN$xN\003\002\004\t\0051!M]1oG\"T!!\002\004\002\r\025tw-\0338f\025\t9\001\"\001\003zSN\f'\"A\005\002\007\r|Wn\001\001\024\005\001a\001CA\007\021\033\005q!\"A\b\002\013M\034\027\r\\1\n\005Eq!AB!osJ+g\rC\003\024\001\021\005A#\001\004=S:LGO\020\013\002+A\021a\003A\007\002\005!)\001\004\001C\0013\005qAK]1wK2$vnZ3uQ\026\024HC\002\016\036WQ2\004\b\005\002\0167%\021AD\004\002\005+:LG\017C\003\037/\001\007q$\001\007ta\006\0248nU3tg&|g\016\005\002!S5\t\021E\003\002#G\005\0311/\0357\013\005\021*\023!B:qCJ\\'B\001\024(\003\031\t\007/Y2iK*\t\001&A\002pe\036L!AK\021\003\031M\003\030M]6TKN\034\030n\0348\t\0131:\002\031A\027\002\t1Lg.\032\t\003]Er!!D\030\n\005Ar\021A\002)sK\022,g-\003\0023g\t11\013\036:j]\036T!\001\r\b\t\013U:\002\031A\027\002\023Q\f'\r\\3OC6,\007\"B\034\030\001\004i\023A\003>l\021>\034H\017]8si\")\021h\006a\001[\005q\001K]3ti>Dun\035;Q_J$\b\"B\036\001\t\003a\024A\004:fO&\034H\017V7q)\006\024G.\032\013\004[u*\005\"\002 ;\001\004y\024a\004;sCZ,G\016V8hKRDWM]:\021\005\001\033U\"A!\013\005\t#\021AB2p[6|g.\003\002E\003\nI\021J\0349vi\n+\027M\034\005\006ki\002\r!\f\005\006\017\002!\t\001S\001\007O\026$8+\025'\025\t5J%\n\024\005\006}\031\003\ra\020\005\006\027\032\003\r!L\001\003UNDQ!\016$A\0025\002")
/*    */ public class SparkEngineV2ForTravelTogetherPresto
/*    */ {
/*    */   public void TravelTogether(SparkSession sparkSession, String line, String tableName, String zkHostport, String PrestoHostPort)
/*    */   {
/* 37 */     String jdbcTable = "togetherCar_result";
/*    */     
/* 39 */     String[] line_arr = line.split("\\|");
/*    */     
/* 41 */     String jobId = line_arr[1];
/* 42 */     String params = line_arr[2];
/*    */     
/* 44 */     Predef..MODULE$.println(params);
/*    */     
/* 46 */     Gson gson = new Gson();
/* 47 */     Type mapType = new TypeToken() {}.getType();
/* 48 */     InputBean travelTogether = (InputBean)gson.fromJson(params, mapType);
/*    */     
/* 50 */     int countT = travelTogether.count();
/*    */     
/* 52 */     String sqlStr = getSQL(travelTogether, params, tableName);
/* 53 */     Predef..MODULE$.println(new StringBuilder().append("SQL--------------:").append(sqlStr).toString());
/*    */     
/* 55 */     String PrestoURL = new StringBuilder().append("jdbc:presto://").append(PrestoHostPort).append("/hive/yisadata").toString();
/* 56 */     String PrestoUser = "spark";
/* 57 */     String PrestoPwd = "";
/* 58 */     String PrestoDriver = "com.facebook.presto.jdbc.PrestoDriver";
/*    */     
/* 60 */     Class.forName(PrestoDriver);
/* 61 */     Connection conn = DriverManager.getConnection(PrestoURL, PrestoUser, null);
/*    */     
/* 63 */     Statement stmt = conn.createStatement();
/*    */     
/* 65 */     ResultSet rs = stmt.executeQuery(sqlStr);
/*    */   }
/*    */   
/*    */   /* Error */
/*    */   public String registTmpTable(InputBean travelTogethers, String tableName)
/*    */   {
/*    */     // Byte code:
/*    */     //   0: getstatic 146	com/yisa/engine/uitl/TimeUtil$:MODULE$	Lcom/yisa/engine/uitl/TimeUtil$;
/*    */     //   3: aload_1
/*    */     //   4: invokevirtual 149	com/yisa/engine/common/InputBean:startTime	()Ljava/lang/String;
/*    */     //   7: invokevirtual 153	com/yisa/engine/uitl/TimeUtil$:getDateId	(Ljava/lang/String;)I
/*    */     //   10: istore_3
/*    */     //   11: getstatic 146	com/yisa/engine/uitl/TimeUtil$:MODULE$	Lcom/yisa/engine/uitl/TimeUtil$;
/*    */     //   14: aload_1
/*    */     //   15: invokevirtual 156	com/yisa/engine/common/InputBean:endTime	()Ljava/lang/String;
/*    */     //   18: invokevirtual 153	com/yisa/engine/uitl/TimeUtil$:getDateId	(Ljava/lang/String;)I
/*    */     //   21: istore 4
/*    */     //   23: new 158	java/lang/StringBuffer
/*    */     //   26: dup
/*    */     //   27: invokespecial 159	java/lang/StringBuffer:<init>	()V
/*    */     //   30: astore 5
/*    */     //   32: aload 5
/*    */     //   34: ldc -95
/*    */     //   36: invokevirtual 164	java/lang/StringBuffer:append	(Ljava/lang/String;)Ljava/lang/StringBuffer;
/*    */     //   39: ldc -90
/*    */     //   41: invokevirtual 164	java/lang/StringBuffer:append	(Ljava/lang/String;)Ljava/lang/StringBuffer;
/*    */     //   44: aload_2
/*    */     //   45: invokevirtual 164	java/lang/StringBuffer:append	(Ljava/lang/String;)Ljava/lang/StringBuffer;
/*    */     //   48: pop
/*    */     //   49: aload 5
/*    */     //   51: ldc -88
/*    */     //   53: invokevirtual 164	java/lang/StringBuffer:append	(Ljava/lang/String;)Ljava/lang/StringBuffer;
/*    */     //   56: aload_1
/*    */     //   57: invokevirtual 171	com/yisa/engine/common/InputBean:plateNumber	()Ljava/lang/String;
/*    */     //   60: invokevirtual 164	java/lang/StringBuffer:append	(Ljava/lang/String;)Ljava/lang/StringBuffer;
/*    */     //   63: ldc -83
/*    */     //   65: invokevirtual 164	java/lang/StringBuffer:append	(Ljava/lang/String;)Ljava/lang/StringBuffer;
/*    */     //   68: pop
/*    */     //   69: aload 5
/*    */     //   71: ldc -81
/*    */     //   73: invokevirtual 164	java/lang/StringBuffer:append	(Ljava/lang/String;)Ljava/lang/StringBuffer;
/*    */     //   76: getstatic 146	com/yisa/engine/uitl/TimeUtil$:MODULE$	Lcom/yisa/engine/uitl/TimeUtil$;
/*    */     //   79: aload_1
/*    */     //   80: invokevirtual 149	com/yisa/engine/common/InputBean:startTime	()Ljava/lang/String;
/*    */     //   83: invokevirtual 179	com/yisa/engine/uitl/TimeUtil$:getTimestampLong	(Ljava/lang/String;)J
/*    */     //   86: invokevirtual 182	java/lang/StringBuffer:append	(J)Ljava/lang/StringBuffer;
/*    */     //   89: pop
/*    */     //   90: aload 5
/*    */     //   92: ldc -72
/*    */     //   94: invokevirtual 164	java/lang/StringBuffer:append	(Ljava/lang/String;)Ljava/lang/StringBuffer;
/*    */     //   97: getstatic 146	com/yisa/engine/uitl/TimeUtil$:MODULE$	Lcom/yisa/engine/uitl/TimeUtil$;
/*    */     //   100: aload_1
/*    */     //   101: invokevirtual 156	com/yisa/engine/common/InputBean:endTime	()Ljava/lang/String;
/*    */     //   104: invokevirtual 179	com/yisa/engine/uitl/TimeUtil$:getTimestampLong	(Ljava/lang/String;)J
/*    */     //   107: invokevirtual 182	java/lang/StringBuffer:append	(J)Ljava/lang/StringBuffer;
/*    */     //   110: pop
/*    */     //   111: aload_1
/*    */     //   112: invokevirtual 188	com/yisa/engine/common/InputBean:locationId	()[Ljava/lang/String;
/*    */     //   115: aconst_null
/*    */     //   116: if_acmpeq +161 -> 277
/*    */     //   119: aload_1
/*    */     //   120: invokevirtual 188	com/yisa/engine/common/InputBean:locationId	()[Ljava/lang/String;
/*    */     //   123: arraylength
/*    */     //   124: iconst_0
/*    */     //   125: if_icmpeq +152 -> 277
/*    */     //   128: aload_1
/*    */     //   129: invokevirtual 188	com/yisa/engine/common/InputBean:locationId	()[Ljava/lang/String;
/*    */     //   132: iconst_0
/*    */     //   133: aaload
/*    */     //   134: ldc 80
/*    */     //   136: astore 6
/*    */     //   138: dup
/*    */     //   139: ifnonnull +12 -> 151
/*    */     //   142: pop
/*    */     //   143: aload 6
/*    */     //   145: ifnull +132 -> 277
/*    */     //   148: goto +11 -> 159
/*    */     //   151: aload 6
/*    */     //   153: invokevirtual 192	java/lang/Object:equals	(Ljava/lang/Object;)Z
/*    */     //   156: ifne +121 -> 277
/*    */     //   159: aload_1
/*    */     //   160: invokevirtual 188	com/yisa/engine/common/InputBean:locationId	()[Ljava/lang/String;
/*    */     //   163: iconst_0
/*    */     //   164: aaload
/*    */     //   165: ldc -62
/*    */     //   167: astore 7
/*    */     //   169: dup
/*    */     //   170: ifnonnull +12 -> 182
/*    */     //   173: pop
/*    */     //   174: aload 7
/*    */     //   176: ifnull +101 -> 277
/*    */     //   179: goto +11 -> 190
/*    */     //   182: aload 7
/*    */     //   184: invokevirtual 192	java/lang/Object:equals	(Ljava/lang/Object;)Z
/*    */     //   187: ifne +90 -> 277
/*    */     //   190: getstatic 26	scala/Predef$:MODULE$	Lscala/Predef$;
/*    */     //   193: getstatic 26	scala/Predef$:MODULE$	Lscala/Predef$;
/*    */     //   196: aload_1
/*    */     //   197: invokevirtual 188	com/yisa/engine/common/InputBean:locationId	()[Ljava/lang/String;
/*    */     //   200: checkcast 196	[Ljava/lang/Object;
/*    */     //   203: invokevirtual 200	scala/Predef$:refArrayOps	([Ljava/lang/Object;)Lscala/collection/mutable/ArrayOps;
/*    */     //   206: new 202	com/yisa/engine/branch/SparkEngineV2ForTravelTogetherPresto$$anonfun$1
/*    */     //   209: dup
/*    */     //   210: aload_0
/*    */     //   211: invokespecial 203	com/yisa/engine/branch/SparkEngineV2ForTravelTogetherPresto$$anonfun$1:<init>	(Lcom/yisa/engine/branch/SparkEngineV2ForTravelTogetherPresto;)V
/*    */     //   214: getstatic 208	scala/Array$:MODULE$	Lscala/Array$;
/*    */     //   217: getstatic 213	scala/reflect/ClassTag$:MODULE$	Lscala/reflect/ClassTag$;
/*    */     //   220: ldc 16
/*    */     //   222: invokevirtual 217	scala/reflect/ClassTag$:apply	(Ljava/lang/Class;)Lscala/reflect/ClassTag;
/*    */     //   225: invokevirtual 221	scala/Array$:canBuildFrom	(Lscala/reflect/ClassTag;)Lscala/collection/generic/CanBuildFrom;
/*    */     //   228: invokeinterface 227 3 0
/*    */     //   233: checkcast 196	[Ljava/lang/Object;
/*    */     //   236: invokevirtual 200	scala/Predef$:refArrayOps	([Ljava/lang/Object;)Lscala/collection/mutable/ArrayOps;
/*    */     //   239: new 229	com/yisa/engine/branch/SparkEngineV2ForTravelTogetherPresto$$anonfun$2
/*    */     //   242: dup
/*    */     //   243: aload_0
/*    */     //   244: invokespecial 230	com/yisa/engine/branch/SparkEngineV2ForTravelTogetherPresto$$anonfun$2:<init>	(Lcom/yisa/engine/branch/SparkEngineV2ForTravelTogetherPresto;)V
/*    */     //   247: invokeinterface 234 2 0
/*    */     //   252: checkcast 16	java/lang/String
/*    */     //   255: astore 8
/*    */     //   257: aload 5
/*    */     //   259: ldc -20
/*    */     //   261: invokevirtual 164	java/lang/StringBuffer:append	(Ljava/lang/String;)Ljava/lang/StringBuffer;
/*    */     //   264: aload 8
/*    */     //   266: invokevirtual 164	java/lang/StringBuffer:append	(Ljava/lang/String;)Ljava/lang/StringBuffer;
/*    */     //   269: ldc -18
/*    */     //   271: invokevirtual 164	java/lang/StringBuffer:append	(Ljava/lang/String;)Ljava/lang/StringBuffer;
/*    */     //   274: goto +6 -> 280
/*    */     //   277: getstatic 244	scala/runtime/BoxedUnit:UNIT	Lscala/runtime/BoxedUnit;
/*    */     //   280: pop
/*    */     //   281: aload 5
/*    */     //   283: ldc -10
/*    */     //   285: invokevirtual 164	java/lang/StringBuffer:append	(Ljava/lang/String;)Ljava/lang/StringBuffer;
/*    */     //   288: iload_3
/*    */     //   289: invokevirtual 249	java/lang/StringBuffer:append	(I)Ljava/lang/StringBuffer;
/*    */     //   292: pop
/*    */     //   293: aload 5
/*    */     //   295: ldc -5
/*    */     //   297: invokevirtual 164	java/lang/StringBuffer:append	(Ljava/lang/String;)Ljava/lang/StringBuffer;
/*    */     //   300: iload 4
/*    */     //   302: invokevirtual 249	java/lang/StringBuffer:append	(I)Ljava/lang/StringBuffer;
/*    */     //   305: pop
/*    */     //   306: aload 5
/*    */     //   308: invokevirtual 252	java/lang/StringBuffer:toString	()Ljava/lang/String;
/*    */     //   311: areturn
/*    */     // Line number table:
/*    */     //   Java source line #71	-> byte code offset #0
/*    */     //   Java source line #72	-> byte code offset #11
/*    */     //   Java source line #74	-> byte code offset #23
/*    */     //   Java source line #75	-> byte code offset #32
/*    */     //   Java source line #76	-> byte code offset #49
/*    */     //   Java source line #78	-> byte code offset #69
/*    */     //   Java source line #79	-> byte code offset #90
/*    */     //   Java source line #81	-> byte code offset #111
/*    */     //   Java source line #82	-> byte code offset #190
/*    */     //   Java source line #83	-> byte code offset #257
/*    */     //   Java source line #81	-> byte code offset #277
/*    */     //   Java source line #86	-> byte code offset #281
/*    */     //   Java source line #88	-> byte code offset #293
/*    */     //   Java source line #90	-> byte code offset #306
/*    */     // Local variable table:
/*    */     //   start	length	slot	name	signature
/*    */     //   0	312	0	this	SparkEngineV2ForTravelTogetherPresto
/*    */     //   0	312	1	travelTogethers	InputBean
/*    */     //   0	312	2	tableName	String
/*    */     //   11	301	3	startTimeDateid	int
/*    */     //   23	289	4	endTimeDateid	int
/*    */     //   32	280	5	sql	StringBuffer
/*    */     //   257	17	8	l	String
/*    */   }
/*    */   
/*    */   /* Error */
/*    */   public String getSQL(InputBean travelTogethers, String js, String tableName)
/*    */   {
/*    */     // Byte code:
/*    */     //   0: getstatic 146	com/yisa/engine/uitl/TimeUtil$:MODULE$	Lcom/yisa/engine/uitl/TimeUtil$;
/*    */     //   3: aload_1
/*    */     //   4: invokevirtual 149	com/yisa/engine/common/InputBean:startTime	()Ljava/lang/String;
/*    */     //   7: invokevirtual 179	com/yisa/engine/uitl/TimeUtil$:getTimestampLong	(Ljava/lang/String;)J
/*    */     //   10: lstore 4
/*    */     //   12: getstatic 146	com/yisa/engine/uitl/TimeUtil$:MODULE$	Lcom/yisa/engine/uitl/TimeUtil$;
/*    */     //   15: aload_1
/*    */     //   16: invokevirtual 156	com/yisa/engine/common/InputBean:endTime	()Ljava/lang/String;
/*    */     //   19: invokevirtual 179	com/yisa/engine/uitl/TimeUtil$:getTimestampLong	(Ljava/lang/String;)J
/*    */     //   22: lstore 6
/*    */     //   24: getstatic 146	com/yisa/engine/uitl/TimeUtil$:MODULE$	Lcom/yisa/engine/uitl/TimeUtil$;
/*    */     //   27: aload_1
/*    */     //   28: invokevirtual 149	com/yisa/engine/common/InputBean:startTime	()Ljava/lang/String;
/*    */     //   31: invokevirtual 153	com/yisa/engine/uitl/TimeUtil$:getDateId	(Ljava/lang/String;)I
/*    */     //   34: istore 8
/*    */     //   36: getstatic 146	com/yisa/engine/uitl/TimeUtil$:MODULE$	Lcom/yisa/engine/uitl/TimeUtil$;
/*    */     //   39: aload_1
/*    */     //   40: invokevirtual 156	com/yisa/engine/common/InputBean:endTime	()Ljava/lang/String;
/*    */     //   43: invokevirtual 153	com/yisa/engine/uitl/TimeUtil$:getDateId	(Ljava/lang/String;)I
/*    */     //   46: istore 9
/*    */     //   48: new 158	java/lang/StringBuffer
/*    */     //   51: dup
/*    */     //   52: invokespecial 159	java/lang/StringBuffer:<init>	()V
/*    */     //   55: astore 10
/*    */     //   57: aload 10
/*    */     //   59: ldc_w 260
/*    */     //   62: invokevirtual 164	java/lang/StringBuffer:append	(Ljava/lang/String;)Ljava/lang/StringBuffer;
/*    */     //   65: pop
/*    */     //   66: aload 10
/*    */     //   68: ldc_w 262
/*    */     //   71: invokevirtual 164	java/lang/StringBuffer:append	(Ljava/lang/String;)Ljava/lang/StringBuffer;
/*    */     //   74: pop
/*    */     //   75: aload 10
/*    */     //   77: ldc_w 264
/*    */     //   80: invokevirtual 164	java/lang/StringBuffer:append	(Ljava/lang/String;)Ljava/lang/StringBuffer;
/*    */     //   83: pop
/*    */     //   84: aload 10
/*    */     //   86: ldc_w 266
/*    */     //   89: invokevirtual 164	java/lang/StringBuffer:append	(Ljava/lang/String;)Ljava/lang/StringBuffer;
/*    */     //   92: pop
/*    */     //   93: aload 10
/*    */     //   95: ldc_w 268
/*    */     //   98: invokevirtual 164	java/lang/StringBuffer:append	(Ljava/lang/String;)Ljava/lang/StringBuffer;
/*    */     //   101: pop
/*    */     //   102: aload 10
/*    */     //   104: ldc_w 270
/*    */     //   107: invokevirtual 164	java/lang/StringBuffer:append	(Ljava/lang/String;)Ljava/lang/StringBuffer;
/*    */     //   110: pop
/*    */     //   111: aload 10
/*    */     //   113: ldc_w 272
/*    */     //   116: invokevirtual 164	java/lang/StringBuffer:append	(Ljava/lang/String;)Ljava/lang/StringBuffer;
/*    */     //   119: pop
/*    */     //   120: aload 10
/*    */     //   122: ldc_w 274
/*    */     //   125: invokevirtual 164	java/lang/StringBuffer:append	(Ljava/lang/String;)Ljava/lang/StringBuffer;
/*    */     //   128: pop
/*    */     //   129: aload 10
/*    */     //   131: ldc -90
/*    */     //   133: invokevirtual 164	java/lang/StringBuffer:append	(Ljava/lang/String;)Ljava/lang/StringBuffer;
/*    */     //   136: aload_3
/*    */     //   137: invokevirtual 164	java/lang/StringBuffer:append	(Ljava/lang/String;)Ljava/lang/StringBuffer;
/*    */     //   140: ldc_w 276
/*    */     //   143: invokevirtual 164	java/lang/StringBuffer:append	(Ljava/lang/String;)Ljava/lang/StringBuffer;
/*    */     //   146: pop
/*    */     //   147: aload 10
/*    */     //   149: ldc_w 278
/*    */     //   152: invokevirtual 164	java/lang/StringBuffer:append	(Ljava/lang/String;)Ljava/lang/StringBuffer;
/*    */     //   155: pop
/*    */     //   156: aload 10
/*    */     //   158: ldc_w 280
/*    */     //   161: invokevirtual 164	java/lang/StringBuffer:append	(Ljava/lang/String;)Ljava/lang/StringBuffer;
/*    */     //   164: pop
/*    */     //   165: aload 10
/*    */     //   167: aload_0
/*    */     //   168: aload_1
/*    */     //   169: aload_3
/*    */     //   170: invokevirtual 282	com/yisa/engine/branch/SparkEngineV2ForTravelTogetherPresto:registTmpTable	(Lcom/yisa/engine/common/InputBean;Ljava/lang/String;)Ljava/lang/String;
/*    */     //   173: invokevirtual 164	java/lang/StringBuffer:append	(Ljava/lang/String;)Ljava/lang/StringBuffer;
/*    */     //   176: pop
/*    */     //   177: aload 10
/*    */     //   179: ldc_w 284
/*    */     //   182: invokevirtual 164	java/lang/StringBuffer:append	(Ljava/lang/String;)Ljava/lang/StringBuffer;
/*    */     //   185: pop
/*    */     //   186: aload 10
/*    */     //   188: ldc_w 286
/*    */     //   191: invokevirtual 164	java/lang/StringBuffer:append	(Ljava/lang/String;)Ljava/lang/StringBuffer;
/*    */     //   194: ldc_w 288
/*    */     //   197: invokevirtual 164	java/lang/StringBuffer:append	(Ljava/lang/String;)Ljava/lang/StringBuffer;
/*    */     //   200: pop
/*    */     //   201: aload 10
/*    */     //   203: ldc_w 290
/*    */     //   206: invokevirtual 164	java/lang/StringBuffer:append	(Ljava/lang/String;)Ljava/lang/StringBuffer;
/*    */     //   209: ldc_w 292
/*    */     //   212: invokevirtual 164	java/lang/StringBuffer:append	(Ljava/lang/String;)Ljava/lang/StringBuffer;
/*    */     //   215: pop
/*    */     //   216: aload 10
/*    */     //   218: ldc_w 294
/*    */     //   221: invokevirtual 164	java/lang/StringBuffer:append	(Ljava/lang/String;)Ljava/lang/StringBuffer;
/*    */     //   224: pop
/*    */     //   225: aload 10
/*    */     //   227: new 61	scala/collection/mutable/StringBuilder
/*    */     //   230: dup
/*    */     //   231: invokespecial 62	scala/collection/mutable/StringBuilder:<init>	()V
/*    */     //   234: ldc_w 296
/*    */     //   237: invokevirtual 68	scala/collection/mutable/StringBuilder:append	(Ljava/lang/Object;)Lscala/collection/mutable/StringBuilder;
/*    */     //   240: aload_1
/*    */     //   241: invokevirtual 171	com/yisa/engine/common/InputBean:plateNumber	()Ljava/lang/String;
/*    */     //   244: invokevirtual 68	scala/collection/mutable/StringBuilder:append	(Ljava/lang/Object;)Lscala/collection/mutable/StringBuilder;
/*    */     //   247: ldc_w 298
/*    */     //   250: invokevirtual 68	scala/collection/mutable/StringBuilder:append	(Ljava/lang/Object;)Lscala/collection/mutable/StringBuilder;
/*    */     //   253: invokevirtual 72	scala/collection/mutable/StringBuilder:toString	()Ljava/lang/String;
/*    */     //   256: invokevirtual 164	java/lang/StringBuffer:append	(Ljava/lang/String;)Ljava/lang/StringBuffer;
/*    */     //   259: pop
/*    */     //   260: aload 10
/*    */     //   262: ldc_w 300
/*    */     //   265: invokevirtual 164	java/lang/StringBuffer:append	(Ljava/lang/String;)Ljava/lang/StringBuffer;
/*    */     //   268: iconst_0
/*    */     //   269: aload_1
/*    */     //   270: invokevirtual 303	com/yisa/engine/common/InputBean:differ	()I
/*    */     //   273: isub
/*    */     //   274: invokevirtual 249	java/lang/StringBuffer:append	(I)Ljava/lang/StringBuffer;
/*    */     //   277: pop
/*    */     //   278: aload 10
/*    */     //   280: ldc_w 305
/*    */     //   283: invokevirtual 164	java/lang/StringBuffer:append	(Ljava/lang/String;)Ljava/lang/StringBuffer;
/*    */     //   286: aload_1
/*    */     //   287: invokevirtual 303	com/yisa/engine/common/InputBean:differ	()I
/*    */     //   290: invokevirtual 249	java/lang/StringBuffer:append	(I)Ljava/lang/StringBuffer;
/*    */     //   293: pop
/*    */     //   294: aload_1
/*    */     //   295: invokevirtual 308	com/yisa/engine/common/InputBean:carYear	()[Ljava/lang/String;
/*    */     //   298: aconst_null
/*    */     //   299: if_acmpeq +139 -> 438
/*    */     //   302: getstatic 26	scala/Predef$:MODULE$	Lscala/Predef$;
/*    */     //   305: aload_1
/*    */     //   306: invokevirtual 308	com/yisa/engine/common/InputBean:carYear	()[Ljava/lang/String;
/*    */     //   309: checkcast 196	[Ljava/lang/Object;
/*    */     //   312: invokevirtual 200	scala/Predef$:refArrayOps	([Ljava/lang/Object;)Lscala/collection/mutable/ArrayOps;
/*    */     //   315: invokeinterface 311 1 0
/*    */     //   320: iconst_0
/*    */     //   321: if_icmple +117 -> 438
/*    */     //   324: aload_1
/*    */     //   325: invokevirtual 308	com/yisa/engine/common/InputBean:carYear	()[Ljava/lang/String;
/*    */     //   328: iconst_0
/*    */     //   329: aaload
/*    */     //   330: ldc 80
/*    */     //   332: astore 11
/*    */     //   334: dup
/*    */     //   335: ifnonnull +12 -> 347
/*    */     //   338: pop
/*    */     //   339: aload 11
/*    */     //   341: ifnull +97 -> 438
/*    */     //   344: goto +11 -> 355
/*    */     //   347: aload 11
/*    */     //   349: invokevirtual 192	java/lang/Object:equals	(Ljava/lang/Object;)Z
/*    */     //   352: ifne +86 -> 438
/*    */     //   355: aload_1
/*    */     //   356: invokevirtual 308	com/yisa/engine/common/InputBean:carYear	()[Ljava/lang/String;
/*    */     //   359: iconst_0
/*    */     //   360: aaload
/*    */     //   361: ldc -62
/*    */     //   363: astore 12
/*    */     //   365: dup
/*    */     //   366: ifnonnull +12 -> 378
/*    */     //   369: pop
/*    */     //   370: aload 12
/*    */     //   372: ifnull +66 -> 438
/*    */     //   375: goto +11 -> 386
/*    */     //   378: aload 12
/*    */     //   380: invokevirtual 192	java/lang/Object:equals	(Ljava/lang/Object;)Z
/*    */     //   383: ifne +55 -> 438
/*    */     //   386: getstatic 26	scala/Predef$:MODULE$	Lscala/Predef$;
/*    */     //   389: aload_1
/*    */     //   390: invokevirtual 308	com/yisa/engine/common/InputBean:carYear	()[Ljava/lang/String;
/*    */     //   393: checkcast 196	[Ljava/lang/Object;
/*    */     //   396: invokevirtual 200	scala/Predef$:refArrayOps	([Ljava/lang/Object;)Lscala/collection/mutable/ArrayOps;
/*    */     //   399: new 313	com/yisa/engine/branch/SparkEngineV2ForTravelTogetherPresto$$anonfun$3
/*    */     //   402: dup
/*    */     //   403: aload_0
/*    */     //   404: invokespecial 314	com/yisa/engine/branch/SparkEngineV2ForTravelTogetherPresto$$anonfun$3:<init>	(Lcom/yisa/engine/branch/SparkEngineV2ForTravelTogetherPresto;)V
/*    */     //   407: invokeinterface 234 2 0
/*    */     //   412: checkcast 16	java/lang/String
/*    */     //   415: astore 13
/*    */     //   417: aload 10
/*    */     //   419: ldc_w 316
/*    */     //   422: invokevirtual 164	java/lang/StringBuffer:append	(Ljava/lang/String;)Ljava/lang/StringBuffer;
/*    */     //   425: aload 13
/*    */     //   427: invokevirtual 164	java/lang/StringBuffer:append	(Ljava/lang/String;)Ljava/lang/StringBuffer;
/*    */     //   430: ldc -18
/*    */     //   432: invokevirtual 164	java/lang/StringBuffer:append	(Ljava/lang/String;)Ljava/lang/StringBuffer;
/*    */     //   435: goto +6 -> 441
/*    */     //   438: getstatic 244	scala/runtime/BoxedUnit:UNIT	Lscala/runtime/BoxedUnit;
/*    */     //   441: pop
/*    */     //   442: lload 4
/*    */     //   444: lconst_0
/*    */     //   445: lcmp
/*    */     //   446: ifeq +19 -> 465
/*    */     //   449: aload 10
/*    */     //   451: ldc_w 318
/*    */     //   454: invokevirtual 164	java/lang/StringBuffer:append	(Ljava/lang/String;)Ljava/lang/StringBuffer;
/*    */     //   457: lload 4
/*    */     //   459: invokevirtual 182	java/lang/StringBuffer:append	(J)Ljava/lang/StringBuffer;
/*    */     //   462: goto +6 -> 468
/*    */     //   465: getstatic 244	scala/runtime/BoxedUnit:UNIT	Lscala/runtime/BoxedUnit;
/*    */     //   468: pop
/*    */     //   469: lload 6
/*    */     //   471: lconst_0
/*    */     //   472: lcmp
/*    */     //   473: ifeq +19 -> 492
/*    */     //   476: aload 10
/*    */     //   478: ldc_w 320
/*    */     //   481: invokevirtual 164	java/lang/StringBuffer:append	(Ljava/lang/String;)Ljava/lang/StringBuffer;
/*    */     //   484: lload 6
/*    */     //   486: invokevirtual 182	java/lang/StringBuffer:append	(J)Ljava/lang/StringBuffer;
/*    */     //   489: goto +6 -> 495
/*    */     //   492: getstatic 244	scala/runtime/BoxedUnit:UNIT	Lscala/runtime/BoxedUnit;
/*    */     //   495: pop
/*    */     //   496: lload 4
/*    */     //   498: lconst_0
/*    */     //   499: lcmp
/*    */     //   500: ifeq +18 -> 518
/*    */     //   503: aload 10
/*    */     //   505: ldc -10
/*    */     //   507: invokevirtual 164	java/lang/StringBuffer:append	(Ljava/lang/String;)Ljava/lang/StringBuffer;
/*    */     //   510: iload 8
/*    */     //   512: invokevirtual 249	java/lang/StringBuffer:append	(I)Ljava/lang/StringBuffer;
/*    */     //   515: goto +6 -> 521
/*    */     //   518: getstatic 244	scala/runtime/BoxedUnit:UNIT	Lscala/runtime/BoxedUnit;
/*    */     //   521: pop
/*    */     //   522: lload 6
/*    */     //   524: lconst_0
/*    */     //   525: lcmp
/*    */     //   526: ifeq +18 -> 544
/*    */     //   529: aload 10
/*    */     //   531: ldc -5
/*    */     //   533: invokevirtual 164	java/lang/StringBuffer:append	(Ljava/lang/String;)Ljava/lang/StringBuffer;
/*    */     //   536: iload 9
/*    */     //   538: invokevirtual 249	java/lang/StringBuffer:append	(I)Ljava/lang/StringBuffer;
/*    */     //   541: goto +6 -> 547
/*    */     //   544: getstatic 244	scala/runtime/BoxedUnit:UNIT	Lscala/runtime/BoxedUnit;
/*    */     //   547: pop
/*    */     //   548: aload_1
/*    */     //   549: invokevirtual 323	com/yisa/engine/common/InputBean:carBrand	()Ljava/lang/String;
/*    */     //   552: astore 14
/*    */     //   554: aload_1
/*    */     //   555: invokevirtual 326	com/yisa/engine/common/InputBean:carModel	()[Ljava/lang/String;
/*    */     //   558: astore 15
/*    */     //   560: aload_1
/*    */     //   561: invokevirtual 329	com/yisa/engine/common/InputBean:carLevel	()[Ljava/lang/String;
/*    */     //   564: astore 16
/*    */     //   566: aload_1
/*    */     //   567: invokevirtual 332	com/yisa/engine/common/InputBean:carColor	()Ljava/lang/String;
/*    */     //   570: astore 17
/*    */     //   572: aload 15
/*    */     //   574: aconst_null
/*    */     //   575: if_acmpeq +91 -> 666
/*    */     //   578: aload 15
/*    */     //   580: arraylength
/*    */     //   581: iconst_0
/*    */     //   582: if_icmple +84 -> 666
/*    */     //   585: aload_1
/*    */     //   586: invokevirtual 326	com/yisa/engine/common/InputBean:carModel	()[Ljava/lang/String;
/*    */     //   589: iconst_0
/*    */     //   590: aaload
/*    */     //   591: ldc -62
/*    */     //   593: astore 18
/*    */     //   595: dup
/*    */     //   596: ifnonnull +12 -> 608
/*    */     //   599: pop
/*    */     //   600: aload 18
/*    */     //   602: ifnull +64 -> 666
/*    */     //   605: goto +11 -> 616
/*    */     //   608: aload 18
/*    */     //   610: invokevirtual 192	java/lang/Object:equals	(Ljava/lang/Object;)Z
/*    */     //   613: ifne +53 -> 666
/*    */     //   616: getstatic 26	scala/Predef$:MODULE$	Lscala/Predef$;
/*    */     //   619: aload 15
/*    */     //   621: checkcast 196	[Ljava/lang/Object;
/*    */     //   624: invokevirtual 200	scala/Predef$:refArrayOps	([Ljava/lang/Object;)Lscala/collection/mutable/ArrayOps;
/*    */     //   627: new 334	com/yisa/engine/branch/SparkEngineV2ForTravelTogetherPresto$$anonfun$4
/*    */     //   630: dup
/*    */     //   631: aload_0
/*    */     //   632: invokespecial 335	com/yisa/engine/branch/SparkEngineV2ForTravelTogetherPresto$$anonfun$4:<init>	(Lcom/yisa/engine/branch/SparkEngineV2ForTravelTogetherPresto;)V
/*    */     //   635: invokeinterface 234 2 0
/*    */     //   640: checkcast 16	java/lang/String
/*    */     //   643: astore 19
/*    */     //   645: aload 10
/*    */     //   647: ldc_w 337
/*    */     //   650: invokevirtual 164	java/lang/StringBuffer:append	(Ljava/lang/String;)Ljava/lang/StringBuffer;
/*    */     //   653: aload 19
/*    */     //   655: invokevirtual 164	java/lang/StringBuffer:append	(Ljava/lang/String;)Ljava/lang/StringBuffer;
/*    */     //   658: ldc -18
/*    */     //   660: invokevirtual 164	java/lang/StringBuffer:append	(Ljava/lang/String;)Ljava/lang/StringBuffer;
/*    */     //   663: goto +6 -> 669
/*    */     //   666: getstatic 244	scala/runtime/BoxedUnit:UNIT	Lscala/runtime/BoxedUnit;
/*    */     //   669: pop
/*    */     //   670: aload 14
/*    */     //   672: ifnull +57 -> 729
/*    */     //   675: aload 14
/*    */     //   677: ldc 80
/*    */     //   679: astore 20
/*    */     //   681: dup
/*    */     //   682: ifnonnull +12 -> 694
/*    */     //   685: pop
/*    */     //   686: aload 20
/*    */     //   688: ifnull +41 -> 729
/*    */     //   691: goto +11 -> 702
/*    */     //   694: aload 20
/*    */     //   696: invokevirtual 192	java/lang/Object:equals	(Ljava/lang/Object;)Z
/*    */     //   699: ifne +30 -> 729
/*    */     //   702: aload 14
/*    */     //   704: ldc -62
/*    */     //   706: astore 21
/*    */     //   708: dup
/*    */     //   709: ifnonnull +12 -> 721
/*    */     //   712: pop
/*    */     //   713: aload 21
/*    */     //   715: ifnull +14 -> 729
/*    */     //   718: goto +17 -> 735
/*    */     //   721: aload 21
/*    */     //   723: invokevirtual 192	java/lang/Object:equals	(Ljava/lang/Object;)Z
/*    */     //   726: ifeq +9 -> 735
/*    */     //   729: getstatic 244	scala/runtime/BoxedUnit:UNIT	Lscala/runtime/BoxedUnit;
/*    */     //   732: goto +16 -> 748
/*    */     //   735: aload 10
/*    */     //   737: ldc_w 339
/*    */     //   740: invokevirtual 164	java/lang/StringBuffer:append	(Ljava/lang/String;)Ljava/lang/StringBuffer;
/*    */     //   743: aload 14
/*    */     //   745: invokevirtual 164	java/lang/StringBuffer:append	(Ljava/lang/String;)Ljava/lang/StringBuffer;
/*    */     //   748: pop
/*    */     //   749: aload 16
/*    */     //   751: aconst_null
/*    */     //   752: if_acmpeq +91 -> 843
/*    */     //   755: aload 16
/*    */     //   757: arraylength
/*    */     //   758: iconst_0
/*    */     //   759: if_icmple +84 -> 843
/*    */     //   762: aload_1
/*    */     //   763: invokevirtual 329	com/yisa/engine/common/InputBean:carLevel	()[Ljava/lang/String;
/*    */     //   766: iconst_0
/*    */     //   767: aaload
/*    */     //   768: ldc -62
/*    */     //   770: astore 22
/*    */     //   772: dup
/*    */     //   773: ifnonnull +12 -> 785
/*    */     //   776: pop
/*    */     //   777: aload 22
/*    */     //   779: ifnull +64 -> 843
/*    */     //   782: goto +11 -> 793
/*    */     //   785: aload 22
/*    */     //   787: invokevirtual 192	java/lang/Object:equals	(Ljava/lang/Object;)Z
/*    */     //   790: ifne +53 -> 843
/*    */     //   793: getstatic 26	scala/Predef$:MODULE$	Lscala/Predef$;
/*    */     //   796: aload 16
/*    */     //   798: checkcast 196	[Ljava/lang/Object;
/*    */     //   801: invokevirtual 200	scala/Predef$:refArrayOps	([Ljava/lang/Object;)Lscala/collection/mutable/ArrayOps;
/*    */     //   804: new 341	com/yisa/engine/branch/SparkEngineV2ForTravelTogetherPresto$$anonfun$5
/*    */     //   807: dup
/*    */     //   808: aload_0
/*    */     //   809: invokespecial 342	com/yisa/engine/branch/SparkEngineV2ForTravelTogetherPresto$$anonfun$5:<init>	(Lcom/yisa/engine/branch/SparkEngineV2ForTravelTogetherPresto;)V
/*    */     //   812: invokeinterface 234 2 0
/*    */     //   817: checkcast 16	java/lang/String
/*    */     //   820: astore 23
/*    */     //   822: aload 10
/*    */     //   824: ldc_w 344
/*    */     //   827: invokevirtual 164	java/lang/StringBuffer:append	(Ljava/lang/String;)Ljava/lang/StringBuffer;
/*    */     //   830: aload 23
/*    */     //   832: invokevirtual 164	java/lang/StringBuffer:append	(Ljava/lang/String;)Ljava/lang/StringBuffer;
/*    */     //   835: ldc -18
/*    */     //   837: invokevirtual 164	java/lang/StringBuffer:append	(Ljava/lang/String;)Ljava/lang/StringBuffer;
/*    */     //   840: goto +6 -> 846
/*    */     //   843: getstatic 244	scala/runtime/BoxedUnit:UNIT	Lscala/runtime/BoxedUnit;
/*    */     //   846: pop
/*    */     //   847: aload 17
/*    */     //   849: ifnull +57 -> 906
/*    */     //   852: aload 17
/*    */     //   854: ldc 80
/*    */     //   856: astore 24
/*    */     //   858: dup
/*    */     //   859: ifnonnull +12 -> 871
/*    */     //   862: pop
/*    */     //   863: aload 24
/*    */     //   865: ifnull +41 -> 906
/*    */     //   868: goto +11 -> 879
/*    */     //   871: aload 24
/*    */     //   873: invokevirtual 192	java/lang/Object:equals	(Ljava/lang/Object;)Z
/*    */     //   876: ifne +30 -> 906
/*    */     //   879: aload 17
/*    */     //   881: ldc -62
/*    */     //   883: astore 25
/*    */     //   885: dup
/*    */     //   886: ifnonnull +12 -> 898
/*    */     //   889: pop
/*    */     //   890: aload 25
/*    */     //   892: ifnull +14 -> 906
/*    */     //   895: goto +17 -> 912
/*    */     //   898: aload 25
/*    */     //   900: invokevirtual 192	java/lang/Object:equals	(Ljava/lang/Object;)Z
/*    */     //   903: ifeq +9 -> 912
/*    */     //   906: getstatic 244	scala/runtime/BoxedUnit:UNIT	Lscala/runtime/BoxedUnit;
/*    */     //   909: goto +16 -> 925
/*    */     //   912: aload 10
/*    */     //   914: ldc_w 346
/*    */     //   917: invokevirtual 164	java/lang/StringBuffer:append	(Ljava/lang/String;)Ljava/lang/StringBuffer;
/*    */     //   920: aload 17
/*    */     //   922: invokevirtual 164	java/lang/StringBuffer:append	(Ljava/lang/String;)Ljava/lang/StringBuffer;
/*    */     //   925: pop
/*    */     //   926: aload 10
/*    */     //   928: ldc_w 348
/*    */     //   931: invokevirtual 164	java/lang/StringBuffer:append	(Ljava/lang/String;)Ljava/lang/StringBuffer;
/*    */     //   934: pop
/*    */     //   935: aload 10
/*    */     //   937: ldc_w 350
/*    */     //   940: invokevirtual 164	java/lang/StringBuffer:append	(Ljava/lang/String;)Ljava/lang/StringBuffer;
/*    */     //   943: pop
/*    */     //   944: aload 10
/*    */     //   946: ldc_w 352
/*    */     //   949: invokevirtual 164	java/lang/StringBuffer:append	(Ljava/lang/String;)Ljava/lang/StringBuffer;
/*    */     //   952: pop
/*    */     //   953: aload 10
/*    */     //   955: ldc_w 354
/*    */     //   958: invokevirtual 164	java/lang/StringBuffer:append	(Ljava/lang/String;)Ljava/lang/StringBuffer;
/*    */     //   961: aload_1
/*    */     //   962: invokevirtual 55	com/yisa/engine/common/InputBean:count	()I
/*    */     //   965: invokevirtual 249	java/lang/StringBuffer:append	(I)Ljava/lang/StringBuffer;
/*    */     //   968: pop
/*    */     //   969: aload 10
/*    */     //   971: invokevirtual 252	java/lang/StringBuffer:toString	()Ljava/lang/String;
/*    */     //   974: areturn
/*    */     // Line number table:
/*    */     //   Java source line #96	-> byte code offset #0
/*    */     //   Java source line #97	-> byte code offset #12
/*    */     //   Java source line #99	-> byte code offset #24
/*    */     //   Java source line #100	-> byte code offset #36
/*    */     //   Java source line #102	-> byte code offset #48
/*    */     //   Java source line #103	-> byte code offset #57
/*    */     //   Java source line #104	-> byte code offset #66
/*    */     //   Java source line #105	-> byte code offset #75
/*    */     //   Java source line #106	-> byte code offset #84
/*    */     //   Java source line #107	-> byte code offset #93
/*    */     //   Java source line #108	-> byte code offset #102
/*    */     //   Java source line #110	-> byte code offset #111
/*    */     //   Java source line #112	-> byte code offset #120
/*    */     //   Java source line #114	-> byte code offset #129
/*    */     //   Java source line #116	-> byte code offset #147
/*    */     //   Java source line #117	-> byte code offset #156
/*    */     //   Java source line #119	-> byte code offset #165
/*    */     //   Java source line #121	-> byte code offset #177
/*    */     //   Java source line #123	-> byte code offset #186
/*    */     //   Java source line #124	-> byte code offset #201
/*    */     //   Java source line #126	-> byte code offset #216
/*    */     //   Java source line #128	-> byte code offset #225
/*    */     //   Java source line #130	-> byte code offset #260
/*    */     //   Java source line #131	-> byte code offset #278
/*    */     //   Java source line #133	-> byte code offset #294
/*    */     //   Java source line #134	-> byte code offset #386
/*    */     //   Java source line #135	-> byte code offset #417
/*    */     //   Java source line #133	-> byte code offset #438
/*    */     //   Java source line #138	-> byte code offset #442
/*    */     //   Java source line #139	-> byte code offset #449
/*    */     //   Java source line #138	-> byte code offset #465
/*    */     //   Java source line #142	-> byte code offset #469
/*    */     //   Java source line #143	-> byte code offset #476
/*    */     //   Java source line #142	-> byte code offset #492
/*    */     //   Java source line #146	-> byte code offset #496
/*    */     //   Java source line #147	-> byte code offset #503
/*    */     //   Java source line #146	-> byte code offset #518
/*    */     //   Java source line #150	-> byte code offset #522
/*    */     //   Java source line #151	-> byte code offset #529
/*    */     //   Java source line #150	-> byte code offset #544
/*    */     //   Java source line #154	-> byte code offset #548
/*    */     //   Java source line #156	-> byte code offset #554
/*    */     //   Java source line #158	-> byte code offset #560
/*    */     //   Java source line #160	-> byte code offset #566
/*    */     //   Java source line #162	-> byte code offset #572
/*    */     //   Java source line #163	-> byte code offset #616
/*    */     //   Java source line #164	-> byte code offset #645
/*    */     //   Java source line #162	-> byte code offset #666
/*    */     //   Java source line #167	-> byte code offset #670
/*    */     //   Java source line #168	-> byte code offset #735
/*    */     //   Java source line #167	-> byte code offset #748
/*    */     //   Java source line #170	-> byte code offset #749
/*    */     //   Java source line #171	-> byte code offset #793
/*    */     //   Java source line #172	-> byte code offset #822
/*    */     //   Java source line #170	-> byte code offset #843
/*    */     //   Java source line #175	-> byte code offset #847
/*    */     //   Java source line #176	-> byte code offset #912
/*    */     //   Java source line #175	-> byte code offset #925
/*    */     //   Java source line #179	-> byte code offset #926
/*    */     //   Java source line #181	-> byte code offset #935
/*    */     //   Java source line #184	-> byte code offset #944
/*    */     //   Java source line #185	-> byte code offset #953
/*    */     //   Java source line #187	-> byte code offset #969
/*    */     // Local variable table:
/*    */     //   start	length	slot	name	signature
/*    */     //   0	975	0	this	SparkEngineV2ForTravelTogetherPresto
/*    */     //   0	975	1	travelTogethers	InputBean
/*    */     //   0	975	2	js	String
/*    */     //   0	975	3	tableName	String
/*    */     //   12	962	4	startTime	long
/*    */     //   24	950	6	endTime	long
/*    */     //   36	938	8	startTimeDateid	int
/*    */     //   48	926	9	endTimeDateid	int
/*    */     //   57	917	10	sb	StringBuffer
/*    */     //   417	18	13	m	String
/*    */     //   554	420	14	carBrand	String
/*    */     //   560	414	15	carModel	String[]
/*    */     //   566	408	16	carLevel	String[]
/*    */     //   572	402	17	carColor	String
/*    */     //   645	18	19	m	String
/*    */     //   822	18	23	m	String
/*    */   }
/*    */ }


/* Location:              E:\BaiduYunDownload\伊萨时期的一些代码\SparkEngine终极版\jars\YISAEngineBySpark2-4.0.6-SNAPSHOT-jar-with-dependencies.jar!\com\yisa\engine\branch\SparkEngineV2ForTravelTogetherPresto.class
 * Java compiler version: 6 (50.0)
 * JD-Core Version:       0.7.1
 */