/*     */ package com.yisa.engine.branch;
/*     */ 
/*     */ import com.google.gson.reflect.TypeToken;
/*     */ import com.yisa.engine.common.InputBean;
/*     */ import java.text.SimpleDateFormat;
/*     */ import java.util.Calendar;
/*     */ import scala.Predef.;
/*     */ import scala.Predef.ArrowAssoc.;
/*     */ import scala.Serializable;
/*     */ import scala.collection.mutable.HashMap;
/*     */ import scala.collection.mutable.StringBuilder;
/*     */ import scala.reflect.ScalaSignature;
/*     */ import scala.runtime.AbstractFunction1;
/*     */ import scala.runtime.AbstractFunction2;
/*     */ import scala.runtime.BoxedUnit;
/*     */ import scala.runtime.IntRef;
/*     */ import scala.runtime.ObjectRef;
/*     */ 
/*     */ @ScalaSignature(bytes="\006\001}3A!\001\002\001\027\ti2\013]1sW\026sw-\0338f-J2uN]\"bg\026\034\025M\035)sKN$xN\003\002\004\t\0051!M]1oG\"T!!\002\004\002\r\025tw-\0338f\025\t9\001\"\001\003zSN\f'\"A\005\002\007\r|Wn\001\001\024\007\001aA\003\005\002\016%5\taB\003\002\020!\005!A.\0318h\025\005\t\022\001\0026bm\006L!a\005\b\003\r=\023'.Z2u!\tiQ#\003\002\027\035\tA!+\0368oC\ndW\r\003\005\031\001\t\005\t\025!\003\032\003\021a\027N\\3\021\005i\001cBA\016\037\033\005a\"\"A\017\002\013M\034\027\r\\1\n\005}a\022A\002)sK\022,g-\003\002\"E\t11\013\036:j]\036T!a\b\017\t\021\021\002!\021!Q\001\ne\t\021\002^1cY\026t\025-\\3\t\021\031\002!\021!Q\001\ne\t!B_6I_N$\bo\034:u\021!A\003A!A!\002\023I\022A\004)sKN$x\016S8tiB{'\017\036\005\006U\001!\taK\001\007y%t\027\016\036 \025\0131rs\006M\031\021\0055\002Q\"\001\002\t\013aI\003\031A\r\t\013\021J\003\031A\r\t\013\031J\003\031A\r\t\013!J\003\031A\r\t\013M\002A\021\t\033\002\007I,h\016F\0016!\tYb'\003\00289\t!QK\\5u\021\025I\004\001\"\001;\003%9W\r^(mI\022\013\027\020F\001\032\021\025a\004\001\"\001>\003597o\0348BeJ\f\027PR;oGR!\021D\020$H\021\025y4\b1\001A\003%Ig\016];u\005\026\fg\016\005\002B\t6\t!I\003\002D\t\00511m\\7n_:L!!\022\"\003\023%s\007/\036;CK\006t\007\"\002\023<\001\004I\002\"\002%<\001\004I\025\001B7baV\002BAS(R#6\t1J\003\002M\033\0069Q.\036;bE2,'B\001(\035\003)\031w\016\0347fGRLwN\\\005\003!.\023q\001S1tQ6\013\007\017\005\002\034%&\0211\013\b\002\004\023:$\b\"B+\001\t\0031\026!B4fiF2D#A,\021\t){\025$\007\005\0063\002!\tAV\001\006O\026$8'\r\005\0067\002!\t\001X\001\nO\026$H)\031;fS\022$\"!G/\t\013yS\006\031A\r\002\025QLW.Z*ue&tw\r")
/*     */ public class SparkEngineV2ForCaseCarPresto
/*     */   implements Runnable
/*     */ {
/*     */   private final String line;
/*     */   
/*     */   /* Error */
/*     */   public void run()
/*     */   {
/*     */     // Byte code:
/*     */     //   0: invokestatic 25	java/lang/System:currentTimeMillis	()J
/*     */     //   3: lstore_1
/*     */     //   4: new 27	scala/collection/mutable/StringBuilder
/*     */     //   7: dup
/*     */     //   8: invokespecial 30	scala/collection/mutable/StringBuilder:<init>	()V
/*     */     //   11: ldc 32
/*     */     //   13: invokevirtual 36	scala/collection/mutable/StringBuilder:append	(Ljava/lang/Object;)Lscala/collection/mutable/StringBuilder;
/*     */     //   16: aload_0
/*     */     //   17: getfield 38	com/yisa/engine/branch/SparkEngineV2ForCaseCarPresto:PrestoHostPort	Ljava/lang/String;
/*     */     //   20: invokevirtual 36	scala/collection/mutable/StringBuilder:append	(Ljava/lang/Object;)Lscala/collection/mutable/StringBuilder;
/*     */     //   23: ldc 40
/*     */     //   25: invokevirtual 36	scala/collection/mutable/StringBuilder:append	(Ljava/lang/Object;)Lscala/collection/mutable/StringBuilder;
/*     */     //   28: invokevirtual 44	scala/collection/mutable/StringBuilder:toString	()Ljava/lang/String;
/*     */     //   31: astore_3
/*     */     //   32: ldc 46
/*     */     //   34: astore 4
/*     */     //   36: ldc 48
/*     */     //   38: astore 5
/*     */     //   40: ldc 50
/*     */     //   42: astore 6
/*     */     //   44: aload 6
/*     */     //   46: invokestatic 56	java/lang/Class:forName	(Ljava/lang/String;)Ljava/lang/Class;
/*     */     //   49: pop
/*     */     //   50: aload_3
/*     */     //   51: aload 4
/*     */     //   53: aconst_null
/*     */     //   54: invokestatic 62	java/sql/DriverManager:getConnection	(Ljava/lang/String;Ljava/lang/String;Ljava/lang/String;)Ljava/sql/Connection;
/*     */     //   57: astore 7
/*     */     //   59: aload 7
/*     */     //   61: invokeinterface 68 1 0
/*     */     //   66: astore 8
/*     */     //   68: invokestatic 25	java/lang/System:currentTimeMillis	()J
/*     */     //   71: lstore 9
/*     */     //   73: getstatic 74	scala/Predef$:MODULE$	Lscala/Predef$;
/*     */     //   76: lload 9
/*     */     //   78: lload_1
/*     */     //   79: lsub
/*     */     //   80: invokestatic 80	scala/runtime/BoxesRunTime:boxToLong	(J)Ljava/lang/Long;
/*     */     //   83: invokevirtual 84	scala/Predef$:println	(Ljava/lang/Object;)V
/*     */     //   86: aconst_null
/*     */     //   87: astore 11
/*     */     //   89: getstatic 89	com/yisa/engine/db/MySQLConnectManager$:MODULE$	Lcom/yisa/engine/db/MySQLConnectManager$;
/*     */     //   92: aload_0
/*     */     //   93: getfield 91	com/yisa/engine/branch/SparkEngineV2ForCaseCarPresto:zkHostport	Ljava/lang/String;
/*     */     //   96: invokevirtual 95	com/yisa/engine/db/MySQLConnectManager$:getConnet	(Ljava/lang/String;)Ljava/sql/Connection;
/*     */     //   99: astore 12
/*     */     //   101: aload 12
/*     */     //   103: iconst_0
/*     */     //   104: invokeinterface 99 2 0
/*     */     //   109: ldc 101
/*     */     //   111: astore 13
/*     */     //   113: aload 12
/*     */     //   115: aload 13
/*     */     //   117: invokeinterface 105 2 0
/*     */     //   122: astore 14
/*     */     //   124: ldc 107
/*     */     //   126: astore 15
/*     */     //   128: aload 12
/*     */     //   130: aload 15
/*     */     //   132: invokeinterface 105 2 0
/*     */     //   137: astore 16
/*     */     //   139: aload_0
/*     */     //   140: getfield 109	com/yisa/engine/branch/SparkEngineV2ForCaseCarPresto:line	Ljava/lang/String;
/*     */     //   143: ldc 111
/*     */     //   145: invokevirtual 117	java/lang/String:split	(Ljava/lang/String;)[Ljava/lang/String;
/*     */     //   148: astore 17
/*     */     //   150: aload 17
/*     */     //   152: iconst_1
/*     */     //   153: aaload
/*     */     //   154: astore 18
/*     */     //   156: aload 17
/*     */     //   158: iconst_2
/*     */     //   159: aaload
/*     */     //   160: astore 19
/*     */     //   162: new 119	com/google/gson/Gson
/*     */     //   165: dup
/*     */     //   166: invokespecial 120	com/google/gson/Gson:<init>	()V
/*     */     //   169: astore 20
/*     */     //   171: new 122	com/yisa/engine/branch/SparkEngineV2ForCaseCarPresto$$anon$1
/*     */     //   174: dup
/*     */     //   175: aload_0
/*     */     //   176: invokespecial 125	com/yisa/engine/branch/SparkEngineV2ForCaseCarPresto$$anon$1:<init>	(Lcom/yisa/engine/branch/SparkEngineV2ForCaseCarPresto;)V
/*     */     //   179: invokevirtual 129	com/yisa/engine/branch/SparkEngineV2ForCaseCarPresto$$anon$1:getType	()Ljava/lang/reflect/Type;
/*     */     //   182: astore 21
/*     */     //   184: aload 20
/*     */     //   186: aload 19
/*     */     //   188: aload 21
/*     */     //   190: invokevirtual 133	com/google/gson/Gson:fromJson	(Ljava/lang/String;Ljava/lang/reflect/Type;)Ljava/lang/Object;
/*     */     //   193: checkcast 135	[Lcom/yisa/engine/common/InputBean;
/*     */     //   196: astore 22
/*     */     //   198: new 137	scala/collection/mutable/HashMap
/*     */     //   201: dup
/*     */     //   202: invokespecial 138	scala/collection/mutable/HashMap:<init>	()V
/*     */     //   205: astore 23
/*     */     //   207: aload 23
/*     */     //   209: getstatic 143	scala/Predef$ArrowAssoc$:MODULE$	Lscala/Predef$ArrowAssoc$;
/*     */     //   212: getstatic 74	scala/Predef$:MODULE$	Lscala/Predef$;
/*     */     //   215: iconst_1
/*     */     //   216: invokestatic 147	scala/runtime/BoxesRunTime:boxToInteger	(I)Ljava/lang/Integer;
/*     */     //   219: invokevirtual 151	scala/Predef$:ArrowAssoc	(Ljava/lang/Object;)Ljava/lang/Object;
/*     */     //   222: iconst_1
/*     */     //   223: invokestatic 147	scala/runtime/BoxesRunTime:boxToInteger	(I)Ljava/lang/Integer;
/*     */     //   226: invokevirtual 155	scala/Predef$ArrowAssoc$:$minus$greater$extension	(Ljava/lang/Object;Ljava/lang/Object;)Lscala/Tuple2;
/*     */     //   229: invokevirtual 159	scala/collection/mutable/HashMap:$plus$eq	(Lscala/Tuple2;)Lscala/collection/mutable/HashMap;
/*     */     //   232: pop
/*     */     //   233: aload 23
/*     */     //   235: getstatic 143	scala/Predef$ArrowAssoc$:MODULE$	Lscala/Predef$ArrowAssoc$;
/*     */     //   238: getstatic 74	scala/Predef$:MODULE$	Lscala/Predef$;
/*     */     //   241: iconst_2
/*     */     //   242: invokestatic 147	scala/runtime/BoxesRunTime:boxToInteger	(I)Ljava/lang/Integer;
/*     */     //   245: invokevirtual 151	scala/Predef$:ArrowAssoc	(Ljava/lang/Object;)Ljava/lang/Object;
/*     */     //   248: iconst_2
/*     */     //   249: invokestatic 147	scala/runtime/BoxesRunTime:boxToInteger	(I)Ljava/lang/Integer;
/*     */     //   252: invokevirtual 155	scala/Predef$ArrowAssoc$:$minus$greater$extension	(Ljava/lang/Object;Ljava/lang/Object;)Lscala/Tuple2;
/*     */     //   255: invokevirtual 159	scala/collection/mutable/HashMap:$plus$eq	(Lscala/Tuple2;)Lscala/collection/mutable/HashMap;
/*     */     //   258: pop
/*     */     //   259: aload 23
/*     */     //   261: getstatic 143	scala/Predef$ArrowAssoc$:MODULE$	Lscala/Predef$ArrowAssoc$;
/*     */     //   264: getstatic 74	scala/Predef$:MODULE$	Lscala/Predef$;
/*     */     //   267: iconst_3
/*     */     //   268: invokestatic 147	scala/runtime/BoxesRunTime:boxToInteger	(I)Ljava/lang/Integer;
/*     */     //   271: invokevirtual 151	scala/Predef$:ArrowAssoc	(Ljava/lang/Object;)Ljava/lang/Object;
/*     */     //   274: iconst_4
/*     */     //   275: invokestatic 147	scala/runtime/BoxesRunTime:boxToInteger	(I)Ljava/lang/Integer;
/*     */     //   278: invokevirtual 155	scala/Predef$ArrowAssoc$:$minus$greater$extension	(Ljava/lang/Object;Ljava/lang/Object;)Lscala/Tuple2;
/*     */     //   281: invokevirtual 159	scala/collection/mutable/HashMap:$plus$eq	(Lscala/Tuple2;)Lscala/collection/mutable/HashMap;
/*     */     //   284: pop
/*     */     //   285: aload 23
/*     */     //   287: getstatic 143	scala/Predef$ArrowAssoc$:MODULE$	Lscala/Predef$ArrowAssoc$;
/*     */     //   290: getstatic 74	scala/Predef$:MODULE$	Lscala/Predef$;
/*     */     //   293: iconst_4
/*     */     //   294: invokestatic 147	scala/runtime/BoxesRunTime:boxToInteger	(I)Ljava/lang/Integer;
/*     */     //   297: invokevirtual 151	scala/Predef$:ArrowAssoc	(Ljava/lang/Object;)Ljava/lang/Object;
/*     */     //   300: bipush 8
/*     */     //   302: invokestatic 147	scala/runtime/BoxesRunTime:boxToInteger	(I)Ljava/lang/Integer;
/*     */     //   305: invokevirtual 155	scala/Predef$ArrowAssoc$:$minus$greater$extension	(Ljava/lang/Object;Ljava/lang/Object;)Lscala/Tuple2;
/*     */     //   308: invokevirtual 159	scala/collection/mutable/HashMap:$plus$eq	(Lscala/Tuple2;)Lscala/collection/mutable/HashMap;
/*     */     //   311: pop
/*     */     //   312: aload 23
/*     */     //   314: getstatic 143	scala/Predef$ArrowAssoc$:MODULE$	Lscala/Predef$ArrowAssoc$;
/*     */     //   317: getstatic 74	scala/Predef$:MODULE$	Lscala/Predef$;
/*     */     //   320: iconst_5
/*     */     //   321: invokestatic 147	scala/runtime/BoxesRunTime:boxToInteger	(I)Ljava/lang/Integer;
/*     */     //   324: invokevirtual 151	scala/Predef$:ArrowAssoc	(Ljava/lang/Object;)Ljava/lang/Object;
/*     */     //   327: bipush 16
/*     */     //   329: invokestatic 147	scala/runtime/BoxesRunTime:boxToInteger	(I)Ljava/lang/Integer;
/*     */     //   332: invokevirtual 155	scala/Predef$ArrowAssoc$:$minus$greater$extension	(Ljava/lang/Object;Ljava/lang/Object;)Lscala/Tuple2;
/*     */     //   335: invokevirtual 159	scala/collection/mutable/HashMap:$plus$eq	(Lscala/Tuple2;)Lscala/collection/mutable/HashMap;
/*     */     //   338: pop
/*     */     //   339: aconst_null
/*     */     //   340: astore 24
/*     */     //   342: aconst_null
/*     */     //   343: astore 25
/*     */     //   345: iconst_0
/*     */     //   346: invokestatic 165	scala/runtime/IntRef:create	(I)Lscala/runtime/IntRef;
/*     */     //   349: astore 26
/*     */     //   351: aload_0
/*     */     //   352: invokevirtual 169	com/yisa/engine/branch/SparkEngineV2ForCaseCarPresto:get16	()Lscala/collection/mutable/HashMap;
/*     */     //   355: astore 27
/*     */     //   357: aload_0
/*     */     //   358: invokevirtual 172	com/yisa/engine/branch/SparkEngineV2ForCaseCarPresto:get31	()Lscala/collection/mutable/HashMap;
/*     */     //   361: astore 28
/*     */     //   363: aload 22
/*     */     //   365: arraylength
/*     */     //   366: iconst_0
/*     */     //   367: if_icmple +405 -> 772
/*     */     //   370: ldc 48
/*     */     //   372: astore 31
/*     */     //   374: ldc 48
/*     */     //   376: astore 32
/*     */     //   378: new 174	java/lang/StringBuffer
/*     */     //   381: dup
/*     */     //   382: invokespecial 175	java/lang/StringBuffer:<init>	()V
/*     */     //   385: invokestatic 180	scala/runtime/ObjectRef:create	(Ljava/lang/Object;)Lscala/runtime/ObjectRef;
/*     */     //   388: astore 33
/*     */     //   390: aload 33
/*     */     //   392: getfield 184	scala/runtime/ObjectRef:elem	Ljava/lang/Object;
/*     */     //   395: checkcast 174	java/lang/StringBuffer
/*     */     //   398: ldc -70
/*     */     //   400: invokevirtual 189	java/lang/StringBuffer:append	(Ljava/lang/String;)Ljava/lang/StringBuffer;
/*     */     //   403: pop
/*     */     //   404: iconst_1
/*     */     //   405: invokestatic 165	scala/runtime/IntRef:create	(I)Lscala/runtime/IntRef;
/*     */     //   408: astore 34
/*     */     //   410: getstatic 74	scala/Predef$:MODULE$	Lscala/Predef$;
/*     */     //   413: aload 22
/*     */     //   415: checkcast 191	[Ljava/lang/Object;
/*     */     //   418: invokevirtual 195	scala/Predef$:refArrayOps	([Ljava/lang/Object;)Lscala/collection/mutable/ArrayOps;
/*     */     //   421: new 197	com/yisa/engine/branch/SparkEngineV2ForCaseCarPresto$$anonfun$run$1
/*     */     //   424: dup
/*     */     //   425: aload_0
/*     */     //   426: aload 22
/*     */     //   428: aload 23
/*     */     //   430: aload 26
/*     */     //   432: aload 33
/*     */     //   434: aload 34
/*     */     //   436: invokespecial 200	com/yisa/engine/branch/SparkEngineV2ForCaseCarPresto$$anonfun$run$1:<init>	(Lcom/yisa/engine/branch/SparkEngineV2ForCaseCarPresto;[Lcom/yisa/engine/common/InputBean;Lscala/collection/mutable/HashMap;Lscala/runtime/IntRef;Lscala/runtime/ObjectRef;Lscala/runtime/IntRef;)V
/*     */     //   439: invokeinterface 206 2 0
/*     */     //   444: aload 33
/*     */     //   446: getfield 184	scala/runtime/ObjectRef:elem	Ljava/lang/Object;
/*     */     //   449: checkcast 174	java/lang/StringBuffer
/*     */     //   452: ldc -48
/*     */     //   454: invokevirtual 189	java/lang/StringBuffer:append	(Ljava/lang/String;)Ljava/lang/StringBuffer;
/*     */     //   457: pop
/*     */     //   458: getstatic 74	scala/Predef$:MODULE$	Lscala/Predef$;
/*     */     //   461: new 27	scala/collection/mutable/StringBuilder
/*     */     //   464: dup
/*     */     //   465: invokespecial 30	scala/collection/mutable/StringBuilder:<init>	()V
/*     */     //   468: ldc -46
/*     */     //   470: invokevirtual 36	scala/collection/mutable/StringBuilder:append	(Ljava/lang/Object;)Lscala/collection/mutable/StringBuilder;
/*     */     //   473: aload 33
/*     */     //   475: getfield 184	scala/runtime/ObjectRef:elem	Ljava/lang/Object;
/*     */     //   478: checkcast 174	java/lang/StringBuffer
/*     */     //   481: invokevirtual 211	java/lang/StringBuffer:toString	()Ljava/lang/String;
/*     */     //   484: invokevirtual 36	scala/collection/mutable/StringBuilder:append	(Ljava/lang/Object;)Lscala/collection/mutable/StringBuilder;
/*     */     //   487: invokevirtual 44	scala/collection/mutable/StringBuilder:toString	()Ljava/lang/String;
/*     */     //   490: invokevirtual 84	scala/Predef$:println	(Ljava/lang/Object;)V
/*     */     //   493: aload 8
/*     */     //   495: aload 33
/*     */     //   497: getfield 184	scala/runtime/ObjectRef:elem	Ljava/lang/Object;
/*     */     //   500: checkcast 174	java/lang/StringBuffer
/*     */     //   503: invokevirtual 211	java/lang/StringBuffer:toString	()Ljava/lang/String;
/*     */     //   506: invokeinterface 217 2 0
/*     */     //   511: astore 11
/*     */     //   513: iconst_0
/*     */     //   514: istore 35
/*     */     //   516: aload 11
/*     */     //   518: invokeinterface 223 1 0
/*     */     //   523: ifeq +187 -> 710
/*     */     //   526: aload 11
/*     */     //   528: iconst_1
/*     */     //   529: invokeinterface 227 2 0
/*     */     //   534: astore 36
/*     */     //   536: aload 11
/*     */     //   538: iconst_2
/*     */     //   539: invokeinterface 227 2 0
/*     */     //   544: astore 37
/*     */     //   546: aload 26
/*     */     //   548: getfield 230	scala/runtime/IntRef:elem	I
/*     */     //   551: iconst_1
/*     */     //   552: if_icmplt +151 -> 703
/*     */     //   555: aload 26
/*     */     //   557: getfield 230	scala/runtime/IntRef:elem	I
/*     */     //   560: iconst_2
/*     */     //   561: if_icmple +15 -> 576
/*     */     //   564: aload 26
/*     */     //   566: aload 26
/*     */     //   568: getfield 230	scala/runtime/IntRef:elem	I
/*     */     //   571: iconst_1
/*     */     //   572: isub
/*     */     //   573: putfield 230	scala/runtime/IntRef:elem	I
/*     */     //   576: getstatic 74	scala/Predef$:MODULE$	Lscala/Predef$;
/*     */     //   579: aload 28
/*     */     //   581: aload 37
/*     */     //   583: invokevirtual 234	scala/collection/mutable/HashMap:get	(Ljava/lang/Object;)Lscala/Option;
/*     */     //   586: invokevirtual 235	java/lang/Object:toString	()Ljava/lang/String;
/*     */     //   589: ldc -19
/*     */     //   591: invokevirtual 117	java/lang/String:split	(Ljava/lang/String;)[Ljava/lang/String;
/*     */     //   594: checkcast 191	[Ljava/lang/Object;
/*     */     //   597: invokevirtual 195	scala/Predef$:refArrayOps	([Ljava/lang/Object;)Lscala/collection/mutable/ArrayOps;
/*     */     //   600: invokeinterface 241 1 0
/*     */     //   605: istore 38
/*     */     //   607: iload 38
/*     */     //   609: aload 26
/*     */     //   611: getfield 230	scala/runtime/IntRef:elem	I
/*     */     //   614: if_icmplt +83 -> 697
/*     */     //   617: iload 35
/*     */     //   619: iconst_1
/*     */     //   620: iadd
/*     */     //   621: istore 35
/*     */     //   623: aload 14
/*     */     //   625: iconst_1
/*     */     //   626: aload 36
/*     */     //   628: invokeinterface 247 3 0
/*     */     //   633: aload 14
/*     */     //   635: iconst_2
/*     */     //   636: aload 18
/*     */     //   638: invokeinterface 247 3 0
/*     */     //   643: aload 14
/*     */     //   645: iconst_3
/*     */     //   646: aload 28
/*     */     //   648: aload 37
/*     */     //   650: invokevirtual 234	scala/collection/mutable/HashMap:get	(Ljava/lang/Object;)Lscala/Option;
/*     */     //   653: invokevirtual 252	scala/Option:get	()Ljava/lang/Object;
/*     */     //   656: checkcast 113	java/lang/String
/*     */     //   659: invokeinterface 247 3 0
/*     */     //   664: aload 14
/*     */     //   666: invokeinterface 255 1 0
/*     */     //   671: iload 35
/*     */     //   673: sipush 500
/*     */     //   676: irem
/*     */     //   677: iconst_0
/*     */     //   678: if_icmpne +13 -> 691
/*     */     //   681: aload 14
/*     */     //   683: invokeinterface 259 1 0
/*     */     //   688: goto +18 -> 706
/*     */     //   691: getstatic 265	scala/runtime/BoxedUnit:UNIT	Lscala/runtime/BoxedUnit;
/*     */     //   694: goto +12 -> 706
/*     */     //   697: getstatic 265	scala/runtime/BoxedUnit:UNIT	Lscala/runtime/BoxedUnit;
/*     */     //   700: goto +6 -> 706
/*     */     //   703: getstatic 265	scala/runtime/BoxedUnit:UNIT	Lscala/runtime/BoxedUnit;
/*     */     //   706: pop
/*     */     //   707: goto -191 -> 516
/*     */     //   710: iload 35
/*     */     //   712: iconst_0
/*     */     //   713: if_icmpne +6 -> 719
/*     */     //   716: iconst_m1
/*     */     //   717: istore 35
/*     */     //   719: aload 16
/*     */     //   721: iconst_1
/*     */     //   722: aload 18
/*     */     //   724: invokeinterface 247 3 0
/*     */     //   729: aload 16
/*     */     //   731: iconst_2
/*     */     //   732: iload 35
/*     */     //   734: invokeinterface 269 3 0
/*     */     //   739: aload 16
/*     */     //   741: invokeinterface 272 1 0
/*     */     //   746: pop
/*     */     //   747: aload 14
/*     */     //   749: invokeinterface 259 1 0
/*     */     //   754: pop
/*     */     //   755: aload 12
/*     */     //   757: invokeinterface 275 1 0
/*     */     //   762: aload 11
/*     */     //   764: invokeinterface 278 1 0
/*     */     //   769: goto +202 -> 971
/*     */     //   772: getstatic 74	scala/Predef$:MODULE$	Lscala/Predef$;
/*     */     //   775: new 27	scala/collection/mutable/StringBuilder
/*     */     //   778: dup
/*     */     //   779: invokespecial 30	scala/collection/mutable/StringBuilder:<init>	()V
/*     */     //   782: ldc_w 280
/*     */     //   785: invokevirtual 36	scala/collection/mutable/StringBuilder:append	(Ljava/lang/Object;)Lscala/collection/mutable/StringBuilder;
/*     */     //   788: aload 17
/*     */     //   790: invokevirtual 36	scala/collection/mutable/StringBuilder:append	(Ljava/lang/Object;)Lscala/collection/mutable/StringBuilder;
/*     */     //   793: invokevirtual 44	scala/collection/mutable/StringBuilder:toString	()Ljava/lang/String;
/*     */     //   796: invokevirtual 84	scala/Predef$:println	(Ljava/lang/Object;)V
/*     */     //   799: goto +172 -> 971
/*     */     //   802: astore 29
/*     */     //   804: getstatic 74	scala/Predef$:MODULE$	Lscala/Predef$;
/*     */     //   807: new 27	scala/collection/mutable/StringBuilder
/*     */     //   810: dup
/*     */     //   811: invokespecial 30	scala/collection/mutable/StringBuilder:<init>	()V
/*     */     //   814: ldc_w 282
/*     */     //   817: invokevirtual 36	scala/collection/mutable/StringBuilder:append	(Ljava/lang/Object;)Lscala/collection/mutable/StringBuilder;
/*     */     //   820: aload 29
/*     */     //   822: invokevirtual 285	java/lang/Exception:printStackTrace	()V
/*     */     //   825: getstatic 265	scala/runtime/BoxedUnit:UNIT	Lscala/runtime/BoxedUnit;
/*     */     //   828: invokevirtual 36	scala/collection/mutable/StringBuilder:append	(Ljava/lang/Object;)Lscala/collection/mutable/StringBuilder;
/*     */     //   831: invokevirtual 44	scala/collection/mutable/StringBuilder:toString	()Ljava/lang/String;
/*     */     //   834: invokevirtual 84	scala/Predef$:println	(Ljava/lang/Object;)V
/*     */     //   837: goto +134 -> 971
/*     */     //   840: astore 30
/*     */     //   842: aload 16
/*     */     //   844: ifnull +19 -> 863
/*     */     //   847: aload 16
/*     */     //   849: invokeinterface 286 1 0
/*     */     //   854: getstatic 74	scala/Predef$:MODULE$	Lscala/Predef$;
/*     */     //   857: ldc_w 288
/*     */     //   860: invokevirtual 84	scala/Predef$:println	(Ljava/lang/Object;)V
/*     */     //   863: aload 14
/*     */     //   865: ifnull +19 -> 884
/*     */     //   868: aload 14
/*     */     //   870: invokeinterface 286 1 0
/*     */     //   875: getstatic 74	scala/Predef$:MODULE$	Lscala/Predef$;
/*     */     //   878: ldc_w 290
/*     */     //   881: invokevirtual 84	scala/Predef$:println	(Ljava/lang/Object;)V
/*     */     //   884: aload 12
/*     */     //   886: ifnull +19 -> 905
/*     */     //   889: aload 12
/*     */     //   891: invokeinterface 291 1 0
/*     */     //   896: getstatic 74	scala/Predef$:MODULE$	Lscala/Predef$;
/*     */     //   899: ldc_w 293
/*     */     //   902: invokevirtual 84	scala/Predef$:println	(Ljava/lang/Object;)V
/*     */     //   905: aload 11
/*     */     //   907: ifnull +19 -> 926
/*     */     //   910: aload 11
/*     */     //   912: invokeinterface 278 1 0
/*     */     //   917: getstatic 74	scala/Predef$:MODULE$	Lscala/Predef$;
/*     */     //   920: ldc_w 295
/*     */     //   923: invokevirtual 84	scala/Predef$:println	(Ljava/lang/Object;)V
/*     */     //   926: aload 8
/*     */     //   928: ifnull +19 -> 947
/*     */     //   931: aload 8
/*     */     //   933: invokeinterface 296 1 0
/*     */     //   938: getstatic 74	scala/Predef$:MODULE$	Lscala/Predef$;
/*     */     //   941: ldc_w 298
/*     */     //   944: invokevirtual 84	scala/Predef$:println	(Ljava/lang/Object;)V
/*     */     //   947: aload 7
/*     */     //   949: ifnull +19 -> 968
/*     */     //   952: aload 7
/*     */     //   954: invokeinterface 291 1 0
/*     */     //   959: getstatic 74	scala/Predef$:MODULE$	Lscala/Predef$;
/*     */     //   962: ldc_w 300
/*     */     //   965: invokevirtual 84	scala/Predef$:println	(Ljava/lang/Object;)V
/*     */     //   968: aload 30
/*     */     //   970: athrow
/*     */     //   971: aload 16
/*     */     //   973: ifnull +19 -> 992
/*     */     //   976: aload 16
/*     */     //   978: invokeinterface 286 1 0
/*     */     //   983: getstatic 74	scala/Predef$:MODULE$	Lscala/Predef$;
/*     */     //   986: ldc_w 288
/*     */     //   989: invokevirtual 84	scala/Predef$:println	(Ljava/lang/Object;)V
/*     */     //   992: aload 14
/*     */     //   994: ifnull +19 -> 1013
/*     */     //   997: aload 14
/*     */     //   999: invokeinterface 286 1 0
/*     */     //   1004: getstatic 74	scala/Predef$:MODULE$	Lscala/Predef$;
/*     */     //   1007: ldc_w 290
/*     */     //   1010: invokevirtual 84	scala/Predef$:println	(Ljava/lang/Object;)V
/*     */     //   1013: aload 12
/*     */     //   1015: ifnull +19 -> 1034
/*     */     //   1018: aload 12
/*     */     //   1020: invokeinterface 291 1 0
/*     */     //   1025: getstatic 74	scala/Predef$:MODULE$	Lscala/Predef$;
/*     */     //   1028: ldc_w 293
/*     */     //   1031: invokevirtual 84	scala/Predef$:println	(Ljava/lang/Object;)V
/*     */     //   1034: aload 11
/*     */     //   1036: ifnull +19 -> 1055
/*     */     //   1039: aload 11
/*     */     //   1041: invokeinterface 278 1 0
/*     */     //   1046: getstatic 74	scala/Predef$:MODULE$	Lscala/Predef$;
/*     */     //   1049: ldc_w 295
/*     */     //   1052: invokevirtual 84	scala/Predef$:println	(Ljava/lang/Object;)V
/*     */     //   1055: aload 8
/*     */     //   1057: ifnull +19 -> 1076
/*     */     //   1060: aload 8
/*     */     //   1062: invokeinterface 296 1 0
/*     */     //   1067: getstatic 74	scala/Predef$:MODULE$	Lscala/Predef$;
/*     */     //   1070: ldc_w 298
/*     */     //   1073: invokevirtual 84	scala/Predef$:println	(Ljava/lang/Object;)V
/*     */     //   1076: aload 7
/*     */     //   1078: ifnull +19 -> 1097
/*     */     //   1081: aload 7
/*     */     //   1083: invokeinterface 291 1 0
/*     */     //   1088: getstatic 74	scala/Predef$:MODULE$	Lscala/Predef$;
/*     */     //   1091: ldc_w 300
/*     */     //   1094: invokevirtual 84	scala/Predef$:println	(Ljava/lang/Object;)V
/*     */     //   1097: return
/*     */     // Line number table:
/*     */     //   Java source line #26	-> byte code offset #0
/*     */     //   Java source line #27	-> byte code offset #4
/*     */     //   Java source line #28	-> byte code offset #32
/*     */     //   Java source line #29	-> byte code offset #36
/*     */     //   Java source line #30	-> byte code offset #40
/*     */     //   Java source line #32	-> byte code offset #44
/*     */     //   Java source line #33	-> byte code offset #50
/*     */     //   Java source line #35	-> byte code offset #59
/*     */     //   Java source line #36	-> byte code offset #68
/*     */     //   Java source line #37	-> byte code offset #73
/*     */     //   Java source line #39	-> byte code offset #86
/*     */     //   Java source line #41	-> byte code offset #89
/*     */     //   Java source line #42	-> byte code offset #101
/*     */     //   Java source line #43	-> byte code offset #109
/*     */     //   Java source line #44	-> byte code offset #113
/*     */     //   Java source line #46	-> byte code offset #124
/*     */     //   Java source line #47	-> byte code offset #128
/*     */     //   Java source line #49	-> byte code offset #139
/*     */     //   Java source line #51	-> byte code offset #150
/*     */     //   Java source line #52	-> byte code offset #156
/*     */     //   Java source line #54	-> byte code offset #162
/*     */     //   Java source line #55	-> byte code offset #171
/*     */     //   Java source line #56	-> byte code offset #184
/*     */     //   Java source line #58	-> byte code offset #198
/*     */     //   Java source line #59	-> byte code offset #207
/*     */     //   Java source line #60	-> byte code offset #233
/*     */     //   Java source line #61	-> byte code offset #259
/*     */     //   Java source line #62	-> byte code offset #285
/*     */     //   Java source line #63	-> byte code offset #312
/*     */     //   Java source line #65	-> byte code offset #339
/*     */     //   Java source line #67	-> byte code offset #342
/*     */     //   Java source line #69	-> byte code offset #345
/*     */     //   Java source line #71	-> byte code offset #351
/*     */     //   Java source line #73	-> byte code offset #357
/*     */     //   Java source line #78	-> byte code offset #363
/*     */     //   Java source line #81	-> byte code offset #370
/*     */     //   Java source line #82	-> byte code offset #374
/*     */     //   Java source line #84	-> byte code offset #378
/*     */     //   Java source line #86	-> byte code offset #390
/*     */     //   Java source line #88	-> byte code offset #404
/*     */     //   Java source line #90	-> byte code offset #410
/*     */     //   Java source line #108	-> byte code offset #444
/*     */     //   Java source line #110	-> byte code offset #458
/*     */     //   Java source line #112	-> byte code offset #493
/*     */     //   Java source line #114	-> byte code offset #513
/*     */     //   Java source line #117	-> byte code offset #516
/*     */     //   Java source line #119	-> byte code offset #526
/*     */     //   Java source line #120	-> byte code offset #536
/*     */     //   Java source line #122	-> byte code offset #546
/*     */     //   Java source line #123	-> byte code offset #555
/*     */     //   Java source line #124	-> byte code offset #564
/*     */     //   Java source line #127	-> byte code offset #576
/*     */     //   Java source line #129	-> byte code offset #607
/*     */     //   Java source line #131	-> byte code offset #617
/*     */     //   Java source line #133	-> byte code offset #623
/*     */     //   Java source line #134	-> byte code offset #633
/*     */     //   Java source line #135	-> byte code offset #643
/*     */     //   Java source line #136	-> byte code offset #664
/*     */     //   Java source line #139	-> byte code offset #671
/*     */     //   Java source line #141	-> byte code offset #681
/*     */     //   Java source line #139	-> byte code offset #691
/*     */     //   Java source line #129	-> byte code offset #697
/*     */     //   Java source line #122	-> byte code offset #703
/*     */     //   Java source line #152	-> byte code offset #710
/*     */     //   Java source line #153	-> byte code offset #716
/*     */     //   Java source line #156	-> byte code offset #719
/*     */     //   Java source line #157	-> byte code offset #729
/*     */     //   Java source line #158	-> byte code offset #739
/*     */     //   Java source line #160	-> byte code offset #747
/*     */     //   Java source line #161	-> byte code offset #755
/*     */     //   Java source line #163	-> byte code offset #762
/*     */     //   Java source line #167	-> byte code offset #772
/*     */     //   Java source line #172	-> byte code offset #802
/*     */     //   Java source line #75	-> byte code offset #802
/*     */     //   Java source line #173	-> byte code offset #804
/*     */     //   Java source line #176	-> byte code offset #840
/*     */     //   Java source line #178	-> byte code offset #842
/*     */     //   Java source line #179	-> byte code offset #847
/*     */     //   Java source line #181	-> byte code offset #854
/*     */     //   Java source line #184	-> byte code offset #863
/*     */     //   Java source line #185	-> byte code offset #868
/*     */     //   Java source line #187	-> byte code offset #875
/*     */     //   Java source line #190	-> byte code offset #884
/*     */     //   Java source line #191	-> byte code offset #889
/*     */     //   Java source line #193	-> byte code offset #896
/*     */     //   Java source line #196	-> byte code offset #905
/*     */     //   Java source line #197	-> byte code offset #910
/*     */     //   Java source line #199	-> byte code offset #917
/*     */     //   Java source line #202	-> byte code offset #926
/*     */     //   Java source line #203	-> byte code offset #931
/*     */     //   Java source line #205	-> byte code offset #938
/*     */     //   Java source line #208	-> byte code offset #947
/*     */     //   Java source line #209	-> byte code offset #952
/*     */     //   Java source line #211	-> byte code offset #959
/*     */     //   Java source line #178	-> byte code offset #971
/*     */     //   Java source line #179	-> byte code offset #976
/*     */     //   Java source line #181	-> byte code offset #983
/*     */     //   Java source line #184	-> byte code offset #992
/*     */     //   Java source line #185	-> byte code offset #997
/*     */     //   Java source line #187	-> byte code offset #1004
/*     */     //   Java source line #190	-> byte code offset #1013
/*     */     //   Java source line #191	-> byte code offset #1018
/*     */     //   Java source line #193	-> byte code offset #1025
/*     */     //   Java source line #196	-> byte code offset #1034
/*     */     //   Java source line #197	-> byte code offset #1039
/*     */     //   Java source line #199	-> byte code offset #1046
/*     */     //   Java source line #202	-> byte code offset #1055
/*     */     //   Java source line #203	-> byte code offset #1060
/*     */     //   Java source line #205	-> byte code offset #1067
/*     */     //   Java source line #208	-> byte code offset #1076
/*     */     //   Java source line #209	-> byte code offset #1081
/*     */     //   Java source line #211	-> byte code offset #1088
/*     */     //   Java source line #24	-> byte code offset #1097
/*     */     // Local variable table:
/*     */     //   start	length	slot	name	signature
/*     */     //   0	1098	0	this	SparkEngineV2ForCaseCarPresto
/*     */     //   3	76	1	start	long
/*     */     //   31	20	3	PrestoURL	String
/*     */     //   34	18	4	PrestoUser	String
/*     */     //   38	3	5	PrestoPwd	String
/*     */     //   42	3	6	PrestoDriver	String
/*     */     //   57	1025	7	connP	java.sql.Connection
/*     */     //   66	995	8	stmtP	java.sql.Statement
/*     */     //   71	6	9	end	long
/*     */     //   87	953	11	rsP	java.sql.ResultSet
/*     */     //   99	920	12	conn	java.sql.Connection
/*     */     //   111	5	13	sqlI	String
/*     */     //   122	876	14	pstmt	java.sql.PreparedStatement
/*     */     //   126	5	15	sql2	String
/*     */     //   137	840	16	pstmt2	java.sql.PreparedStatement
/*     */     //   148	641	17	line_arr	String[]
/*     */     //   154	569	18	jobId	String
/*     */     //   160	27	19	params	String
/*     */     //   169	16	20	gson	com.google.gson.Gson
/*     */     //   182	7	21	mapType	java.lang.reflect.Type
/*     */     //   196	231	22	map	InputBean[]
/*     */     //   205	224	23	map5	HashMap
/*     */     //   340	3	24	inputBeanRepair	InputBean
/*     */     //   343	3	25	resultData	scala.runtime.Null.
/*     */     //   349	261	26	count	IntRef
/*     */     //   355	3	27	map16	HashMap
/*     */     //   361	286	28	map31	HashMap
/*     */     //   802	19	29	localException	Exception
/*     */     //   840	129	30	localObject	Object
/*     */     //   372	3	31	isType	String
/*     */     //   376	3	32	isTypeShow	String
/*     */     //   388	108	33	sql	ObjectRef
/*     */     //   408	27	34	i	IntRef
/*     */     //   514	219	35	number	int
/*     */     //   534	93	36	solrid	String
/*     */     //   544	105	37	types	String
/*     */     //   605	3	38	lenTem	int
/*     */     // Exception table:
/*     */     //   from	to	target	type
/*     */     //   363	802	802	java/lang/Exception
/*     */     //   363	840	840	finally
/*     */   }
/*     */   
/*     */   public String getOldDay()
/*     */   {
/* 218 */     SimpleDateFormat dateFormat = new SimpleDateFormat("yyyyMMdd");
/* 219 */     Calendar cal = Calendar.getInstance();
/* 220 */     cal.add(5, -3);
/* 221 */     String yesterday = dateFormat.format(cal.getTime());
/*     */     
/* 223 */     return yesterday;
/*     */   }
/*     */   
/*     */   /* Error */
/*     */   public String gsonArrayFunc(InputBean inputBean, String tableName, HashMap<Object, Object> map5)
/*     */   {
/*     */     // Byte code:
/*     */     //   0: getstatic 391	com/yisa/engine/uitl/TimeUtil$:MODULE$	Lcom/yisa/engine/uitl/TimeUtil$;
/*     */     //   3: aload_1
/*     */     //   4: invokevirtual 396	com/yisa/engine/common/InputBean:startTime	()Ljava/lang/String;
/*     */     //   7: invokevirtual 400	com/yisa/engine/uitl/TimeUtil$:getTimeStringFormat	(Ljava/lang/String;)Ljava/lang/String;
/*     */     //   10: astore 4
/*     */     //   12: getstatic 391	com/yisa/engine/uitl/TimeUtil$:MODULE$	Lcom/yisa/engine/uitl/TimeUtil$;
/*     */     //   15: aload_1
/*     */     //   16: invokevirtual 403	com/yisa/engine/common/InputBean:endTime	()Ljava/lang/String;
/*     */     //   19: invokevirtual 400	com/yisa/engine/uitl/TimeUtil$:getTimeStringFormat	(Ljava/lang/String;)Ljava/lang/String;
/*     */     //   22: astore 5
/*     */     //   24: aload_1
/*     */     //   25: invokevirtual 407	com/yisa/engine/common/InputBean:locationId	()[Ljava/lang/String;
/*     */     //   28: astore 6
/*     */     //   30: aload_1
/*     */     //   31: invokevirtual 410	com/yisa/engine/common/InputBean:carModel	()[Ljava/lang/String;
/*     */     //   34: astore 7
/*     */     //   36: aload_1
/*     */     //   37: invokevirtual 413	com/yisa/engine/common/InputBean:carBrand	()Ljava/lang/String;
/*     */     //   40: astore 8
/*     */     //   42: aload_1
/*     */     //   43: invokevirtual 416	com/yisa/engine/common/InputBean:carYear	()[Ljava/lang/String;
/*     */     //   46: astore 9
/*     */     //   48: aload_1
/*     */     //   49: invokevirtual 419	com/yisa/engine/common/InputBean:carColor	()Ljava/lang/String;
/*     */     //   52: astore 10
/*     */     //   54: aload_1
/*     */     //   55: invokevirtual 422	com/yisa/engine/common/InputBean:plateNumber	()Ljava/lang/String;
/*     */     //   58: astore 11
/*     */     //   60: aload_1
/*     */     //   61: invokevirtual 425	com/yisa/engine/common/InputBean:differ	()I
/*     */     //   64: istore 12
/*     */     //   66: new 174	java/lang/StringBuffer
/*     */     //   69: dup
/*     */     //   70: invokespecial 175	java/lang/StringBuffer:<init>	()V
/*     */     //   73: astore 13
/*     */     //   75: aload 13
/*     */     //   77: ldc_w 427
/*     */     //   80: invokevirtual 189	java/lang/StringBuffer:append	(Ljava/lang/String;)Ljava/lang/StringBuffer;
/*     */     //   83: pop
/*     */     //   84: aload 13
/*     */     //   86: aload_3
/*     */     //   87: iload 12
/*     */     //   89: invokestatic 147	scala/runtime/BoxesRunTime:boxToInteger	(I)Ljava/lang/Integer;
/*     */     //   92: invokevirtual 234	scala/collection/mutable/HashMap:get	(Ljava/lang/Object;)Lscala/Option;
/*     */     //   95: invokevirtual 252	scala/Option:get	()Ljava/lang/Object;
/*     */     //   98: invokestatic 431	scala/runtime/BoxesRunTime:unboxToInt	(Ljava/lang/Object;)I
/*     */     //   101: invokevirtual 434	java/lang/StringBuffer:append	(I)Ljava/lang/StringBuffer;
/*     */     //   104: ldc_w 436
/*     */     //   107: invokevirtual 189	java/lang/StringBuffer:append	(Ljava/lang/String;)Ljava/lang/StringBuffer;
/*     */     //   110: aload_2
/*     */     //   111: invokevirtual 189	java/lang/StringBuffer:append	(Ljava/lang/String;)Ljava/lang/StringBuffer;
/*     */     //   114: pop
/*     */     //   115: aload 4
/*     */     //   117: ifnonnull +9 -> 126
/*     */     //   120: getstatic 265	scala/runtime/BoxedUnit:UNIT	Lscala/runtime/BoxedUnit;
/*     */     //   123: goto +20 -> 143
/*     */     //   126: aload 13
/*     */     //   128: ldc_w 438
/*     */     //   131: invokevirtual 189	java/lang/StringBuffer:append	(Ljava/lang/String;)Ljava/lang/StringBuffer;
/*     */     //   134: aload_0
/*     */     //   135: aload 4
/*     */     //   137: invokevirtual 441	com/yisa/engine/branch/SparkEngineV2ForCaseCarPresto:getDateid	(Ljava/lang/String;)Ljava/lang/String;
/*     */     //   140: invokevirtual 189	java/lang/StringBuffer:append	(Ljava/lang/String;)Ljava/lang/StringBuffer;
/*     */     //   143: pop
/*     */     //   144: aload 5
/*     */     //   146: ifnonnull +9 -> 155
/*     */     //   149: getstatic 265	scala/runtime/BoxedUnit:UNIT	Lscala/runtime/BoxedUnit;
/*     */     //   152: goto +20 -> 172
/*     */     //   155: aload 13
/*     */     //   157: ldc_w 443
/*     */     //   160: invokevirtual 189	java/lang/StringBuffer:append	(Ljava/lang/String;)Ljava/lang/StringBuffer;
/*     */     //   163: aload_0
/*     */     //   164: aload 5
/*     */     //   166: invokevirtual 441	com/yisa/engine/branch/SparkEngineV2ForCaseCarPresto:getDateid	(Ljava/lang/String;)Ljava/lang/String;
/*     */     //   169: invokevirtual 189	java/lang/StringBuffer:append	(Ljava/lang/String;)Ljava/lang/StringBuffer;
/*     */     //   172: pop
/*     */     //   173: aload 6
/*     */     //   175: aconst_null
/*     */     //   176: if_acmpeq +97 -> 273
/*     */     //   179: aload 6
/*     */     //   181: arraylength
/*     */     //   182: iconst_0
/*     */     //   183: if_icmple +90 -> 273
/*     */     //   186: getstatic 74	scala/Predef$:MODULE$	Lscala/Predef$;
/*     */     //   189: getstatic 74	scala/Predef$:MODULE$	Lscala/Predef$;
/*     */     //   192: aload 6
/*     */     //   194: checkcast 191	[Ljava/lang/Object;
/*     */     //   197: invokevirtual 195	scala/Predef$:refArrayOps	([Ljava/lang/Object;)Lscala/collection/mutable/ArrayOps;
/*     */     //   200: new 445	com/yisa/engine/branch/SparkEngineV2ForCaseCarPresto$$anonfun$1
/*     */     //   203: dup
/*     */     //   204: aload_0
/*     */     //   205: invokespecial 446	com/yisa/engine/branch/SparkEngineV2ForCaseCarPresto$$anonfun$1:<init>	(Lcom/yisa/engine/branch/SparkEngineV2ForCaseCarPresto;)V
/*     */     //   208: getstatic 451	scala/Array$:MODULE$	Lscala/Array$;
/*     */     //   211: getstatic 456	scala/reflect/ClassTag$:MODULE$	Lscala/reflect/ClassTag$;
/*     */     //   214: ldc 113
/*     */     //   216: invokevirtual 460	scala/reflect/ClassTag$:apply	(Ljava/lang/Class;)Lscala/reflect/ClassTag;
/*     */     //   219: invokevirtual 464	scala/Array$:canBuildFrom	(Lscala/reflect/ClassTag;)Lscala/collection/generic/CanBuildFrom;
/*     */     //   222: invokeinterface 467 3 0
/*     */     //   227: checkcast 191	[Ljava/lang/Object;
/*     */     //   230: invokevirtual 195	scala/Predef$:refArrayOps	([Ljava/lang/Object;)Lscala/collection/mutable/ArrayOps;
/*     */     //   233: new 469	com/yisa/engine/branch/SparkEngineV2ForCaseCarPresto$$anonfun$2
/*     */     //   236: dup
/*     */     //   237: aload_0
/*     */     //   238: invokespecial 470	com/yisa/engine/branch/SparkEngineV2ForCaseCarPresto$$anonfun$2:<init>	(Lcom/yisa/engine/branch/SparkEngineV2ForCaseCarPresto;)V
/*     */     //   241: invokeinterface 474 2 0
/*     */     //   246: checkcast 113	java/lang/String
/*     */     //   249: astore 14
/*     */     //   251: aload 13
/*     */     //   253: ldc_w 476
/*     */     //   256: invokevirtual 189	java/lang/StringBuffer:append	(Ljava/lang/String;)Ljava/lang/StringBuffer;
/*     */     //   259: aload 14
/*     */     //   261: invokevirtual 189	java/lang/StringBuffer:append	(Ljava/lang/String;)Ljava/lang/StringBuffer;
/*     */     //   264: ldc_w 478
/*     */     //   267: invokevirtual 189	java/lang/StringBuffer:append	(Ljava/lang/String;)Ljava/lang/StringBuffer;
/*     */     //   270: goto +6 -> 276
/*     */     //   273: getstatic 265	scala/runtime/BoxedUnit:UNIT	Lscala/runtime/BoxedUnit;
/*     */     //   276: pop
/*     */     //   277: aload 9
/*     */     //   279: aconst_null
/*     */     //   280: if_acmpeq +61 -> 341
/*     */     //   283: aload 9
/*     */     //   285: arraylength
/*     */     //   286: iconst_0
/*     */     //   287: if_icmple +54 -> 341
/*     */     //   290: getstatic 74	scala/Predef$:MODULE$	Lscala/Predef$;
/*     */     //   293: aload 9
/*     */     //   295: checkcast 191	[Ljava/lang/Object;
/*     */     //   298: invokevirtual 195	scala/Predef$:refArrayOps	([Ljava/lang/Object;)Lscala/collection/mutable/ArrayOps;
/*     */     //   301: new 480	com/yisa/engine/branch/SparkEngineV2ForCaseCarPresto$$anonfun$3
/*     */     //   304: dup
/*     */     //   305: aload_0
/*     */     //   306: invokespecial 481	com/yisa/engine/branch/SparkEngineV2ForCaseCarPresto$$anonfun$3:<init>	(Lcom/yisa/engine/branch/SparkEngineV2ForCaseCarPresto;)V
/*     */     //   309: invokeinterface 474 2 0
/*     */     //   314: checkcast 113	java/lang/String
/*     */     //   317: astore 15
/*     */     //   319: aload 13
/*     */     //   321: ldc_w 483
/*     */     //   324: invokevirtual 189	java/lang/StringBuffer:append	(Ljava/lang/String;)Ljava/lang/StringBuffer;
/*     */     //   327: aload 15
/*     */     //   329: invokevirtual 189	java/lang/StringBuffer:append	(Ljava/lang/String;)Ljava/lang/StringBuffer;
/*     */     //   332: ldc_w 478
/*     */     //   335: invokevirtual 189	java/lang/StringBuffer:append	(Ljava/lang/String;)Ljava/lang/StringBuffer;
/*     */     //   338: goto +6 -> 344
/*     */     //   341: getstatic 265	scala/runtime/BoxedUnit:UNIT	Lscala/runtime/BoxedUnit;
/*     */     //   344: pop
/*     */     //   345: aload 7
/*     */     //   347: aconst_null
/*     */     //   348: if_acmpeq +61 -> 409
/*     */     //   351: aload 7
/*     */     //   353: arraylength
/*     */     //   354: iconst_0
/*     */     //   355: if_icmple +54 -> 409
/*     */     //   358: getstatic 74	scala/Predef$:MODULE$	Lscala/Predef$;
/*     */     //   361: aload 7
/*     */     //   363: checkcast 191	[Ljava/lang/Object;
/*     */     //   366: invokevirtual 195	scala/Predef$:refArrayOps	([Ljava/lang/Object;)Lscala/collection/mutable/ArrayOps;
/*     */     //   369: new 485	com/yisa/engine/branch/SparkEngineV2ForCaseCarPresto$$anonfun$4
/*     */     //   372: dup
/*     */     //   373: aload_0
/*     */     //   374: invokespecial 486	com/yisa/engine/branch/SparkEngineV2ForCaseCarPresto$$anonfun$4:<init>	(Lcom/yisa/engine/branch/SparkEngineV2ForCaseCarPresto;)V
/*     */     //   377: invokeinterface 474 2 0
/*     */     //   382: checkcast 113	java/lang/String
/*     */     //   385: astore 16
/*     */     //   387: aload 13
/*     */     //   389: ldc_w 488
/*     */     //   392: invokevirtual 189	java/lang/StringBuffer:append	(Ljava/lang/String;)Ljava/lang/StringBuffer;
/*     */     //   395: aload 16
/*     */     //   397: invokevirtual 189	java/lang/StringBuffer:append	(Ljava/lang/String;)Ljava/lang/StringBuffer;
/*     */     //   400: ldc_w 478
/*     */     //   403: invokevirtual 189	java/lang/StringBuffer:append	(Ljava/lang/String;)Ljava/lang/StringBuffer;
/*     */     //   406: goto +6 -> 412
/*     */     //   409: getstatic 265	scala/runtime/BoxedUnit:UNIT	Lscala/runtime/BoxedUnit;
/*     */     //   412: pop
/*     */     //   413: aload 8
/*     */     //   415: ifnull +30 -> 445
/*     */     //   418: aload 8
/*     */     //   420: ldc 48
/*     */     //   422: astore 17
/*     */     //   424: dup
/*     */     //   425: ifnonnull +12 -> 437
/*     */     //   428: pop
/*     */     //   429: aload 17
/*     */     //   431: ifnull +14 -> 445
/*     */     //   434: goto +17 -> 451
/*     */     //   437: aload 17
/*     */     //   439: invokevirtual 492	java/lang/Object:equals	(Ljava/lang/Object;)Z
/*     */     //   442: ifeq +9 -> 451
/*     */     //   445: getstatic 265	scala/runtime/BoxedUnit:UNIT	Lscala/runtime/BoxedUnit;
/*     */     //   448: goto +16 -> 464
/*     */     //   451: aload 13
/*     */     //   453: ldc_w 494
/*     */     //   456: invokevirtual 189	java/lang/StringBuffer:append	(Ljava/lang/String;)Ljava/lang/StringBuffer;
/*     */     //   459: aload 8
/*     */     //   461: invokevirtual 189	java/lang/StringBuffer:append	(Ljava/lang/String;)Ljava/lang/StringBuffer;
/*     */     //   464: pop
/*     */     //   465: aload 10
/*     */     //   467: ifnull +30 -> 497
/*     */     //   470: aload 10
/*     */     //   472: ldc 48
/*     */     //   474: astore 18
/*     */     //   476: dup
/*     */     //   477: ifnonnull +12 -> 489
/*     */     //   480: pop
/*     */     //   481: aload 18
/*     */     //   483: ifnull +14 -> 497
/*     */     //   486: goto +17 -> 503
/*     */     //   489: aload 18
/*     */     //   491: invokevirtual 492	java/lang/Object:equals	(Ljava/lang/Object;)Z
/*     */     //   494: ifeq +9 -> 503
/*     */     //   497: getstatic 265	scala/runtime/BoxedUnit:UNIT	Lscala/runtime/BoxedUnit;
/*     */     //   500: goto +16 -> 516
/*     */     //   503: aload 13
/*     */     //   505: ldc_w 496
/*     */     //   508: invokevirtual 189	java/lang/StringBuffer:append	(Ljava/lang/String;)Ljava/lang/StringBuffer;
/*     */     //   511: aload 10
/*     */     //   513: invokevirtual 189	java/lang/StringBuffer:append	(Ljava/lang/String;)Ljava/lang/StringBuffer;
/*     */     //   516: pop
/*     */     //   517: aload 11
/*     */     //   519: ifnull +30 -> 549
/*     */     //   522: aload 11
/*     */     //   524: ldc 48
/*     */     //   526: astore 19
/*     */     //   528: dup
/*     */     //   529: ifnonnull +12 -> 541
/*     */     //   532: pop
/*     */     //   533: aload 19
/*     */     //   535: ifnull +14 -> 549
/*     */     //   538: goto +17 -> 555
/*     */     //   541: aload 19
/*     */     //   543: invokevirtual 492	java/lang/Object:equals	(Ljava/lang/Object;)Z
/*     */     //   546: ifeq +9 -> 555
/*     */     //   549: getstatic 265	scala/runtime/BoxedUnit:UNIT	Lscala/runtime/BoxedUnit;
/*     */     //   552: goto +84 -> 636
/*     */     //   555: aload 11
/*     */     //   557: ldc_w 498
/*     */     //   560: invokevirtual 502	java/lang/String:contains	(Ljava/lang/CharSequence;)Z
/*     */     //   563: ifne +14 -> 577
/*     */     //   566: aload 11
/*     */     //   568: ldc_w 504
/*     */     //   571: invokevirtual 502	java/lang/String:contains	(Ljava/lang/CharSequence;)Z
/*     */     //   574: ifeq +43 -> 617
/*     */     //   577: aload 13
/*     */     //   579: ldc_w 506
/*     */     //   582: invokevirtual 189	java/lang/StringBuffer:append	(Ljava/lang/String;)Ljava/lang/StringBuffer;
/*     */     //   585: aload 11
/*     */     //   587: ldc_w 498
/*     */     //   590: ldc_w 508
/*     */     //   593: invokevirtual 512	java/lang/String:replace	(Ljava/lang/CharSequence;Ljava/lang/CharSequence;)Ljava/lang/String;
/*     */     //   596: ldc_w 504
/*     */     //   599: ldc_w 514
/*     */     //   602: invokevirtual 512	java/lang/String:replace	(Ljava/lang/CharSequence;Ljava/lang/CharSequence;)Ljava/lang/String;
/*     */     //   605: invokevirtual 189	java/lang/StringBuffer:append	(Ljava/lang/String;)Ljava/lang/StringBuffer;
/*     */     //   608: ldc_w 516
/*     */     //   611: invokevirtual 189	java/lang/StringBuffer:append	(Ljava/lang/String;)Ljava/lang/StringBuffer;
/*     */     //   614: goto +22 -> 636
/*     */     //   617: aload 13
/*     */     //   619: ldc_w 518
/*     */     //   622: invokevirtual 189	java/lang/StringBuffer:append	(Ljava/lang/String;)Ljava/lang/StringBuffer;
/*     */     //   625: aload 11
/*     */     //   627: invokevirtual 189	java/lang/StringBuffer:append	(Ljava/lang/String;)Ljava/lang/StringBuffer;
/*     */     //   630: ldc_w 520
/*     */     //   633: invokevirtual 189	java/lang/StringBuffer:append	(Ljava/lang/String;)Ljava/lang/StringBuffer;
/*     */     //   636: pop
/*     */     //   637: aload 13
/*     */     //   639: ldc_w 522
/*     */     //   642: invokevirtual 189	java/lang/StringBuffer:append	(Ljava/lang/String;)Ljava/lang/StringBuffer;
/*     */     //   645: pop
/*     */     //   646: getstatic 74	scala/Predef$:MODULE$	Lscala/Predef$;
/*     */     //   649: new 27	scala/collection/mutable/StringBuilder
/*     */     //   652: dup
/*     */     //   653: invokespecial 30	scala/collection/mutable/StringBuilder:<init>	()V
/*     */     //   656: ldc_w 524
/*     */     //   659: invokevirtual 36	scala/collection/mutable/StringBuilder:append	(Ljava/lang/Object;)Lscala/collection/mutable/StringBuilder;
/*     */     //   662: aload 13
/*     */     //   664: invokevirtual 211	java/lang/StringBuffer:toString	()Ljava/lang/String;
/*     */     //   667: invokevirtual 36	scala/collection/mutable/StringBuilder:append	(Ljava/lang/Object;)Lscala/collection/mutable/StringBuilder;
/*     */     //   670: invokevirtual 44	scala/collection/mutable/StringBuilder:toString	()Ljava/lang/String;
/*     */     //   673: invokevirtual 84	scala/Predef$:println	(Ljava/lang/Object;)V
/*     */     //   676: aload 13
/*     */     //   678: invokevirtual 211	java/lang/StringBuffer:toString	()Ljava/lang/String;
/*     */     //   681: areturn
/*     */     // Line number table:
/*     */     //   Java source line #231	-> byte code offset #0
/*     */     //   Java source line #232	-> byte code offset #12
/*     */     //   Java source line #233	-> byte code offset #24
/*     */     //   Java source line #234	-> byte code offset #30
/*     */     //   Java source line #235	-> byte code offset #36
/*     */     //   Java source line #236	-> byte code offset #42
/*     */     //   Java source line #237	-> byte code offset #48
/*     */     //   Java source line #238	-> byte code offset #54
/*     */     //   Java source line #239	-> byte code offset #60
/*     */     //   Java source line #241	-> byte code offset #66
/*     */     //   Java source line #243	-> byte code offset #75
/*     */     //   Java source line #245	-> byte code offset #84
/*     */     //   Java source line #247	-> byte code offset #115
/*     */     //   Java source line #248	-> byte code offset #126
/*     */     //   Java source line #247	-> byte code offset #143
/*     */     //   Java source line #251	-> byte code offset #144
/*     */     //   Java source line #252	-> byte code offset #155
/*     */     //   Java source line #251	-> byte code offset #172
/*     */     //   Java source line #255	-> byte code offset #173
/*     */     //   Java source line #256	-> byte code offset #186
/*     */     //   Java source line #257	-> byte code offset #251
/*     */     //   Java source line #255	-> byte code offset #273
/*     */     //   Java source line #260	-> byte code offset #277
/*     */     //   Java source line #261	-> byte code offset #290
/*     */     //   Java source line #262	-> byte code offset #319
/*     */     //   Java source line #260	-> byte code offset #341
/*     */     //   Java source line #265	-> byte code offset #345
/*     */     //   Java source line #266	-> byte code offset #358
/*     */     //   Java source line #267	-> byte code offset #387
/*     */     //   Java source line #265	-> byte code offset #409
/*     */     //   Java source line #270	-> byte code offset #413
/*     */     //   Java source line #271	-> byte code offset #451
/*     */     //   Java source line #270	-> byte code offset #464
/*     */     //   Java source line #274	-> byte code offset #465
/*     */     //   Java source line #275	-> byte code offset #503
/*     */     //   Java source line #274	-> byte code offset #516
/*     */     //   Java source line #278	-> byte code offset #517
/*     */     //   Java source line #279	-> byte code offset #555
/*     */     //   Java source line #280	-> byte code offset #577
/*     */     //   Java source line #282	-> byte code offset #617
/*     */     //   Java source line #278	-> byte code offset #636
/*     */     //   Java source line #286	-> byte code offset #637
/*     */     //   Java source line #288	-> byte code offset #646
/*     */     //   Java source line #290	-> byte code offset #676
/*     */     // Local variable table:
/*     */     //   start	length	slot	name	signature
/*     */     //   0	682	0	this	SparkEngineV2ForCaseCarPresto
/*     */     //   0	682	1	inputBean	InputBean
/*     */     //   0	682	2	tableName	String
/*     */     //   0	682	3	map5	HashMap
/*     */     //   12	669	4	startTime1	String
/*     */     //   24	657	5	endTime1	String
/*     */     //   30	651	6	locationId	String[]
/*     */     //   36	645	7	carModel	String[]
/*     */     //   42	639	8	carBrand	String
/*     */     //   48	633	9	carYear	String[]
/*     */     //   54	627	10	carColor	String
/*     */     //   60	621	11	plateNumber	String
/*     */     //   66	615	12	differ	int
/*     */     //   75	606	13	sb	StringBuffer
/*     */     //   251	19	14	l	String
/*     */     //   319	19	15	m	String
/*     */     //   387	19	16	m	String
/*     */   }
/*     */   
/*     */   public HashMap<String, String> get16()
/*     */   {
/* 296 */     HashMap map16 = new HashMap();
/* 297 */     map16.$plus$eq(Predef.ArrowAssoc..MODULE$.$minus$greater$extension(Predef..MODULE$.ArrowAssoc("1"), "1"));
/* 298 */     map16.$plus$eq(Predef.ArrowAssoc..MODULE$.$minus$greater$extension(Predef..MODULE$.ArrowAssoc("2"), "2"));
/* 299 */     map16.$plus$eq(Predef.ArrowAssoc..MODULE$.$minus$greater$extension(Predef..MODULE$.ArrowAssoc("3"), "1,2"));
/* 300 */     map16.$plus$eq(Predef.ArrowAssoc..MODULE$.$minus$greater$extension(Predef..MODULE$.ArrowAssoc("4"), "4"));
/* 301 */     map16.$plus$eq(Predef.ArrowAssoc..MODULE$.$minus$greater$extension(Predef..MODULE$.ArrowAssoc("5"), "1,4"));
/* 302 */     map16.$plus$eq(Predef.ArrowAssoc..MODULE$.$minus$greater$extension(Predef..MODULE$.ArrowAssoc("6"), "2,4"));
/* 303 */     map16.$plus$eq(Predef.ArrowAssoc..MODULE$.$minus$greater$extension(Predef..MODULE$.ArrowAssoc("7"), "1,2,4"));
/* 304 */     map16.$plus$eq(Predef.ArrowAssoc..MODULE$.$minus$greater$extension(Predef..MODULE$.ArrowAssoc("8"), "8"));
/* 305 */     map16.$plus$eq(Predef.ArrowAssoc..MODULE$.$minus$greater$extension(Predef..MODULE$.ArrowAssoc("9"), "1,8"));
/* 306 */     map16.$plus$eq(Predef.ArrowAssoc..MODULE$.$minus$greater$extension(Predef..MODULE$.ArrowAssoc("10"), "2,8"));
/* 307 */     map16.$plus$eq(Predef.ArrowAssoc..MODULE$.$minus$greater$extension(Predef..MODULE$.ArrowAssoc("11"), "1,2,8"));
/* 308 */     map16.$plus$eq(Predef.ArrowAssoc..MODULE$.$minus$greater$extension(Predef..MODULE$.ArrowAssoc("12"), "4,8"));
/* 309 */     map16.$plus$eq(Predef.ArrowAssoc..MODULE$.$minus$greater$extension(Predef..MODULE$.ArrowAssoc("13"), "1,4,8"));
/* 310 */     map16.$plus$eq(Predef.ArrowAssoc..MODULE$.$minus$greater$extension(Predef..MODULE$.ArrowAssoc("14"), "2,4,8"));
/* 311 */     map16.$plus$eq(Predef.ArrowAssoc..MODULE$.$minus$greater$extension(Predef..MODULE$.ArrowAssoc("15"), "1,2,4,8"));
/* 312 */     map16.$plus$eq(Predef.ArrowAssoc..MODULE$.$minus$greater$extension(Predef..MODULE$.ArrowAssoc("16"), "16"));
/* 313 */     map16.$plus$eq(Predef.ArrowAssoc..MODULE$.$minus$greater$extension(Predef..MODULE$.ArrowAssoc("17"), "1,16"));
/* 314 */     map16.$plus$eq(Predef.ArrowAssoc..MODULE$.$minus$greater$extension(Predef..MODULE$.ArrowAssoc("18"), "2,16"));
/* 315 */     map16.$plus$eq(Predef.ArrowAssoc..MODULE$.$minus$greater$extension(Predef..MODULE$.ArrowAssoc("19"), "1,2,16"));
/* 316 */     map16.$plus$eq(Predef.ArrowAssoc..MODULE$.$minus$greater$extension(Predef..MODULE$.ArrowAssoc("20"), "4,16"));
/* 317 */     map16.$plus$eq(Predef.ArrowAssoc..MODULE$.$minus$greater$extension(Predef..MODULE$.ArrowAssoc("21"), "1,4,16"));
/* 318 */     map16.$plus$eq(Predef.ArrowAssoc..MODULE$.$minus$greater$extension(Predef..MODULE$.ArrowAssoc("22"), "2,4,16"));
/* 319 */     map16.$plus$eq(Predef.ArrowAssoc..MODULE$.$minus$greater$extension(Predef..MODULE$.ArrowAssoc("23"), "1,2,4,16"));
/* 320 */     map16.$plus$eq(Predef.ArrowAssoc..MODULE$.$minus$greater$extension(Predef..MODULE$.ArrowAssoc("24"), "8,16"));
/* 321 */     map16.$plus$eq(Predef.ArrowAssoc..MODULE$.$minus$greater$extension(Predef..MODULE$.ArrowAssoc("25"), "1,8,16"));
/* 322 */     map16.$plus$eq(Predef.ArrowAssoc..MODULE$.$minus$greater$extension(Predef..MODULE$.ArrowAssoc("26"), "2,8,16"));
/* 323 */     map16.$plus$eq(Predef.ArrowAssoc..MODULE$.$minus$greater$extension(Predef..MODULE$.ArrowAssoc("27"), "1,2,8,16"));
/* 324 */     map16.$plus$eq(Predef.ArrowAssoc..MODULE$.$minus$greater$extension(Predef..MODULE$.ArrowAssoc("28"), "4,8,16"));
/* 325 */     map16.$plus$eq(Predef.ArrowAssoc..MODULE$.$minus$greater$extension(Predef..MODULE$.ArrowAssoc("29"), "1,4,8,16"));
/* 326 */     map16.$plus$eq(Predef.ArrowAssoc..MODULE$.$minus$greater$extension(Predef..MODULE$.ArrowAssoc("30"), "2,4,8,16"));
/* 327 */     map16.$plus$eq(Predef.ArrowAssoc..MODULE$.$minus$greater$extension(Predef..MODULE$.ArrowAssoc("31"), "1,2,4,8,16"));
/*     */     
/* 329 */     return map16;
/*     */   }
/*     */   
/*     */ 
/*     */   public HashMap<String, String> get31()
/*     */   {
/* 335 */     HashMap map16 = new HashMap();
/* 336 */     map16.$plus$eq(Predef.ArrowAssoc..MODULE$.$minus$greater$extension(Predef..MODULE$.ArrowAssoc("1"), "1"));
/* 337 */     map16.$plus$eq(Predef.ArrowAssoc..MODULE$.$minus$greater$extension(Predef..MODULE$.ArrowAssoc("2"), "2"));
/* 338 */     map16.$plus$eq(Predef.ArrowAssoc..MODULE$.$minus$greater$extension(Predef..MODULE$.ArrowAssoc("3"), "1,2"));
/* 339 */     map16.$plus$eq(Predef.ArrowAssoc..MODULE$.$minus$greater$extension(Predef..MODULE$.ArrowAssoc("4"), "3"));
/* 340 */     map16.$plus$eq(Predef.ArrowAssoc..MODULE$.$minus$greater$extension(Predef..MODULE$.ArrowAssoc("5"), "1,3"));
/* 341 */     map16.$plus$eq(Predef.ArrowAssoc..MODULE$.$minus$greater$extension(Predef..MODULE$.ArrowAssoc("6"), "2,3"));
/* 342 */     map16.$plus$eq(Predef.ArrowAssoc..MODULE$.$minus$greater$extension(Predef..MODULE$.ArrowAssoc("7"), "1,2,3"));
/* 343 */     map16.$plus$eq(Predef.ArrowAssoc..MODULE$.$minus$greater$extension(Predef..MODULE$.ArrowAssoc("8"), "4"));
/* 344 */     map16.$plus$eq(Predef.ArrowAssoc..MODULE$.$minus$greater$extension(Predef..MODULE$.ArrowAssoc("9"), "1,4"));
/* 345 */     map16.$plus$eq(Predef.ArrowAssoc..MODULE$.$minus$greater$extension(Predef..MODULE$.ArrowAssoc("10"), "2,4"));
/* 346 */     map16.$plus$eq(Predef.ArrowAssoc..MODULE$.$minus$greater$extension(Predef..MODULE$.ArrowAssoc("11"), "1,2,4"));
/* 347 */     map16.$plus$eq(Predef.ArrowAssoc..MODULE$.$minus$greater$extension(Predef..MODULE$.ArrowAssoc("12"), "3,4"));
/* 348 */     map16.$plus$eq(Predef.ArrowAssoc..MODULE$.$minus$greater$extension(Predef..MODULE$.ArrowAssoc("13"), "1,3,4"));
/* 349 */     map16.$plus$eq(Predef.ArrowAssoc..MODULE$.$minus$greater$extension(Predef..MODULE$.ArrowAssoc("14"), "2,3,4"));
/* 350 */     map16.$plus$eq(Predef.ArrowAssoc..MODULE$.$minus$greater$extension(Predef..MODULE$.ArrowAssoc("15"), "1,2,3,4"));
/* 351 */     map16.$plus$eq(Predef.ArrowAssoc..MODULE$.$minus$greater$extension(Predef..MODULE$.ArrowAssoc("16"), "5"));
/* 352 */     map16.$plus$eq(Predef.ArrowAssoc..MODULE$.$minus$greater$extension(Predef..MODULE$.ArrowAssoc("17"), "1,5"));
/* 353 */     map16.$plus$eq(Predef.ArrowAssoc..MODULE$.$minus$greater$extension(Predef..MODULE$.ArrowAssoc("18"), "2,5"));
/* 354 */     map16.$plus$eq(Predef.ArrowAssoc..MODULE$.$minus$greater$extension(Predef..MODULE$.ArrowAssoc("19"), "1,2,5"));
/* 355 */     map16.$plus$eq(Predef.ArrowAssoc..MODULE$.$minus$greater$extension(Predef..MODULE$.ArrowAssoc("20"), "3,5"));
/* 356 */     map16.$plus$eq(Predef.ArrowAssoc..MODULE$.$minus$greater$extension(Predef..MODULE$.ArrowAssoc("21"), "1,3,5"));
/* 357 */     map16.$plus$eq(Predef.ArrowAssoc..MODULE$.$minus$greater$extension(Predef..MODULE$.ArrowAssoc("22"), "2,3,5"));
/* 358 */     map16.$plus$eq(Predef.ArrowAssoc..MODULE$.$minus$greater$extension(Predef..MODULE$.ArrowAssoc("23"), "1,2,3,5"));
/* 359 */     map16.$plus$eq(Predef.ArrowAssoc..MODULE$.$minus$greater$extension(Predef..MODULE$.ArrowAssoc("24"), "4,5"));
/* 360 */     map16.$plus$eq(Predef.ArrowAssoc..MODULE$.$minus$greater$extension(Predef..MODULE$.ArrowAssoc("25"), "1,4,5"));
/* 361 */     map16.$plus$eq(Predef.ArrowAssoc..MODULE$.$minus$greater$extension(Predef..MODULE$.ArrowAssoc("26"), "2,4,5"));
/* 362 */     map16.$plus$eq(Predef.ArrowAssoc..MODULE$.$minus$greater$extension(Predef..MODULE$.ArrowAssoc("27"), "1,2,4,5"));
/* 363 */     map16.$plus$eq(Predef.ArrowAssoc..MODULE$.$minus$greater$extension(Predef..MODULE$.ArrowAssoc("28"), "3,4,5"));
/* 364 */     map16.$plus$eq(Predef.ArrowAssoc..MODULE$.$minus$greater$extension(Predef..MODULE$.ArrowAssoc("29"), "1,3,4,5"));
/* 365 */     map16.$plus$eq(Predef.ArrowAssoc..MODULE$.$minus$greater$extension(Predef..MODULE$.ArrowAssoc("30"), "2,3,4,5"));
/* 366 */     map16.$plus$eq(Predef.ArrowAssoc..MODULE$.$minus$greater$extension(Predef..MODULE$.ArrowAssoc("31"), "1,2,3,4,5"));
/*     */     
/* 368 */     return map16;
/*     */   }
/*     */   
/*     */ 
/*     */   public String getDateid(String timeString)
/*     */   {
/* 374 */     String timeLong = timeString.replaceAll("[-\\s:]", "");
/*     */     
/* 376 */     return timeLong.substring(0, 8);
/*     */   }
/*     */   
/*     */   public SparkEngineV2ForCaseCarPresto(String line, String tableName, String zkHostport, String PrestoHostPort) {}
/*     */ }


/* Location:              E:\BaiduYunDownload\\SparkEngine\jars\YISAEngineBySpark2-4.0.6-SNAPSHOT-jar-with-dependencies.jar!\com\yisa\engine\branch\SparkEngineV2ForCaseCarPresto.class
 * Java compiler version: 6 (50.0)
 * JD-Core Version:       0.7.1
 */