/*     */ package com.yisa.engine.branch;
/*     */ 
/*     */ import com.yisa.engine.common.InputBean;
/*     */ import java.sql.Connection;
/*     */ import java.sql.PreparedStatement;
/*     */ import java.text.SimpleDateFormat;
/*     */ import java.util.Calendar;
/*     */ import org.apache.spark.sql.Dataset;
/*     */ import org.apache.spark.sql.Row;
/*     */ import org.apache.spark.sql.SparkSession;
/*     */ import scala.Predef.;
/*     */ import scala.Serializable;
/*     */ import scala.collection.mutable.StringBuilder;
/*     */ import scala.runtime.AbstractFunction2;
/*     */ import scala.runtime.BoxesRunTime;
/*     */ import scala.runtime.IntRef;
/*     */ import scala.runtime.ObjectRef;
/*     */ 
/*     */ @scala.reflect.ScalaSignature(bytes="\006\001Y3A!\001\002\001\027\tQ2\013]1sW\026sw-\0338f-J2uN]'vYRL\007k\\5oi*\0211\001B\001\007EJ\fgn\0315\013\005\0251\021AB3oO&tWM\003\002\b\021\005!\0210[:b\025\005I\021aA2p[\016\0011C\001\001\r!\ti\001#D\001\017\025\005y\021!B:dC2\f\027BA\t\017\005\031\te.\037*fM\")1\003\001C\001)\0051A(\0338jiz\"\022!\006\t\003-\001i\021A\001\005\0061\001!\t!G\001\021g\026\f'o\0315Nk2$\030\016U8j]R$bAG\017/gqr\004CA\007\034\023\tabB\001\003V]&$\b\"\002\020\030\001\004y\022!C:qCJ\\G)\031;b!\r\001\023fK\007\002C)\021!eI\001\004gFd'B\001\023&\003\025\031\b/\031:l\025\t1s%\001\004ba\006\034\007.\032\006\002Q\005\031qN]4\n\005)\n#a\002#bi\006\034X\r\036\t\003A1J!!L\021\003\007I{w\017C\0030/\001\007\001'\001\006tc2\034uN\034;fqR\004\"\001I\031\n\005I\n#\001D*qCJ\\7+Z:tS>t\007\"\002\033\030\001\004)\024\001\0027j]\026\004\"AN\035\017\00559\024B\001\035\017\003\031\001&/\0323fM&\021!h\017\002\007'R\024\030N\\4\013\005ar\001\"B\037\030\001\004)\024!\003;bE2,g*Y7f\021\025yt\0031\0016\003)Q8\016S8tiB|'\017\036\005\006\003\002!\tAQ\001\nO\026$x\n\0343ECf$\022!\016\005\006\t\002!\t!R\001\016ON|g.\021:sCf4UO\\2\025\tU2e\n\025\005\006\017\016\003\r\001S\001\nS:\004X\017\036\"fC:\004\"!\023'\016\003)S!a\023\003\002\r\r|W.\\8o\023\ti%JA\005J]B,HOQ3b]\")qj\021a\001k\005)A/\0379f\007\")Qh\021a\001k!)!\013\001C\001'\006Iq-\032;ECR,\027\016\032\013\003kQCQ!V)A\002U\n!\002^5nKN#(/\0338h\001")
/*     */ public class SparkEngineV2ForMultiPoint
/*     */ {
/*     */   public void searchMultiPoint(Dataset<Row> sparkData, final SparkSession sqlContext, String line, final String tableName, String zkHostport)
/*     */   {
/*  24 */     String[] line_arr = line.split("\\|");
/*     */     
/*  26 */     final String jobId = line_arr[1];
/*  27 */     String params = line_arr[2];
/*     */     
/*  29 */     com.google.gson.Gson gson = new com.google.gson.Gson();
/*  30 */     java.lang.reflect.Type mapType = new com.google.gson.reflect.TypeToken() {}.getType();
/*  31 */     InputBean[] map = (InputBean[])gson.fromJson(params, mapType);
/*     */     
/*  33 */     final ObjectRef inputBeanRepair = ObjectRef.create(null);
/*     */     
/*  35 */     scala.runtime.Null. resultData = null;
/*     */     
/*  37 */     final IntRef count = IntRef.create(0);
/*     */     
/*     */ 
/*  40 */     if (map.length > 0)
/*     */     {
/*  42 */       final IntRef i = IntRef.create(1);
/*  43 */       final ObjectRef df = ObjectRef.create(null);
/*  44 */       Dataset dfNot = null;
/*     */       
/*  46 */       StringBuffer sqlAll = new StringBuffer();
/*     */       
/*  48 */       Predef..MODULE$.refArrayOps((Object[])map).foreach(new scala.runtime.AbstractFunction1() { public static final long serialVersionUID = 0L;
/*     */         
/*  50 */         public final void apply(InputBean m) { if (m.isRepair() == 1) {
/*  51 */             inputBeanRepair.elem = m;
/*     */           }
/*     */           else {
/*  54 */             SimpleDateFormat format2 = new SimpleDateFormat("yyyyMMddHHmmss");
/*     */             
/*  56 */             long startTime = format2.parse(m.startTime()).getTime() / 1000L;
/*  57 */             long endTime = format2.parse(m.endTime()).getTime() / 1000L;
/*     */             
/*  59 */             if (i.elem == 1) {
/*  60 */               df.elem = sqlContext.sql(SparkEngineV2ForMultiPoint.this.gsonArrayFunc(m, new StringBuilder().append(i.elem).append("").toString(), tableName));
/*     */               
/*  62 */               i.elem += 1;
/*     */               
/*  64 */               count.elem = m.count();
/*     */             }
/*     */             else
/*     */             {
/*  68 */               Dataset dfTemp = sqlContext.sql(SparkEngineV2ForMultiPoint.this.gsonArrayFunc(m, new StringBuilder().append(i.elem).append("").toString(), tableName));
/*     */               
/*  70 */               df.elem = ((Dataset)df.elem).union(dfTemp);
/*     */               
/*  72 */               i.elem += 1;
/*     */             }
/*     */             
/*     */           }
/*     */           
/*     */         }
/*  78 */       });
/*  79 */       Dataset dfIs = null;
/*  80 */       if ((Dataset)df.elem != null)
/*     */       {
/*     */ 
/*  83 */         dfNot = sqlContext.sql(gsonArrayFunc((InputBean)inputBeanRepair.elem, new StringBuilder().append(i.elem).append("").toString(), tableName));((InputBean)inputBeanRepair.elem == null ? scala.runtime.BoxedUnit.UNIT : 
/*     */         
/*  85 */           ((Dataset)df.elem).union(dfNot));
/*     */         
/*     */ 
/*  88 */         ((Dataset)df.elem).createOrReplaceTempView("df");
/*     */         
/*  90 */         int countSql = 2;
/*  91 */         if (count.elem > 2) {
/*  92 */           countSql = count.elem - 1;
/*     */         }
/*     */         
/*  95 */         StringBuffer sqlUnion = new StringBuffer();
/*     */         
/*     */ 
/*     */ 
/*  99 */         sqlUnion.append("select max_by(solrid,capturetime) as solrid,platenumber,concat_ws(',',collect_set(type)) as types,size(collect_set(type)) as typesize from df group by platenumber ");
/* 100 */         sqlUnion.append(new StringBuilder().append(" HAVING typesize >= ").append(BoxesRunTime.boxToInteger(countSql)).toString());
/*     */         
/* 102 */         String sqlUnionS = sqlUnion.toString();
/*     */         
/* 104 */         Predef..MODULE$.println(new StringBuilder().append("sql : ").append(sqlUnion.toString()).toString());
/*     */         
/* 106 */         dfIs = sqlContext.sql(sqlUnionS);
/*     */         
/* 108 */         if ((InputBean)inputBeanRepair.elem == null)
/*     */         {
/*     */ 
/*     */ 
/*     */ 
/*     */ 
/*     */ 
/*     */ 
/*     */ 
/*     */ 
/*     */ 
/*     */ 
/*     */ 
/*     */ 
/*     */ 
/*     */ 
/*     */ 
/*     */ 
/*     */ 
/*     */ 
/*     */ 
/*     */ 
/*     */ 
/*     */ 
/*     */ 
/*     */ 
/*     */ 
/*     */ 
/*     */ 
/*     */ 
/*     */ 
/*     */ 
/*     */ 
/*     */ 
/*     */ 
/*     */ 
/*     */ 
/*     */ 
/*     */ 
/*     */ 
/*     */ 
/*     */ 
/*     */ 
/*     */ 
/*     */ 
/*     */ 
/*     */ 
/*     */ 
/*     */ 
/*     */ 
/*     */ 
/*     */ 
/*     */ 
/*     */ 
/*     */ 
/*     */ 
/*     */ 
/*     */ 
/*     */ 
/*     */ 
/* 168 */           Connection conn = com.yisa.engine.db.MySQLConnectManager..MODULE$.getConnet(zkHostport);
/* 169 */           conn.setAutoCommit(false);
/* 170 */           String sql = "insert into zdypz_result (s_id,j_id,t_id) values(?,?,?)";
/* 171 */           final ObjectRef pstmt = ObjectRef.create(conn.prepareStatement(sql));
/*     */           
/* 173 */           final IntRef number = IntRef.create(0);
/* 174 */           Predef..MODULE$.refArrayOps((Object[])dfIs.collect()).foreach(new scala.runtime.AbstractFunction1() { public static final long serialVersionUID = 0L;
/*     */             
/* 176 */             public final void apply(Row t) { number.elem += 1;
/*     */               
/* 178 */               ((PreparedStatement)pstmt.elem).setString(1, t.apply(0).toString());
/* 179 */               ((PreparedStatement)pstmt.elem).setString(2, jobId);
/* 180 */               ((PreparedStatement)pstmt.elem).setString(3, t.apply(2).toString());
/* 181 */               ((PreparedStatement)pstmt.elem).addBatch();
/*     */             }
/*     */             
/* 184 */           });
/* 185 */           String sql2 = "insert into zdypz_progress (jobid,total) values(?,?)";
/* 186 */           PreparedStatement pstmt2 = conn.prepareStatement(sql2);
/*     */           
/* 188 */           if (number.elem == 0) {
/* 189 */             number.elem = -1;
/*     */           }
/* 191 */           pstmt2.setString(1, jobId);
/* 192 */           pstmt2.setInt(2, number.elem);
/* 193 */           pstmt2.executeUpdate();
/* 194 */           pstmt2.close();
/*     */           
/* 196 */           ((PreparedStatement)pstmt.elem).executeBatch();
/* 197 */           conn.commit();
/* 198 */           ((PreparedStatement)pstmt.elem).close();
/*     */           
/* 200 */           conn.close();
/*     */         }
/*     */         else
/*     */         {
/* 110 */           dfIs.createOrReplaceTempView("dfIs");
/*     */           
/* 112 */           String sqlNot = new StringBuilder().append("SELECT solrid, types FROM dfIs WHERE types NOT LIKE '%").append(BoxesRunTime.boxToInteger(i.elem)).append("%'").toString();
/*     */           
/* 114 */           Dataset re = sqlContext.sql(sqlNot);
/*     */           
/* 116 */           Connection conn = com.yisa.engine.db.MySQLConnectManager..MODULE$.getConnet(zkHostport);
/* 117 */           conn.setAutoCommit(false);
/* 118 */           String sql = "insert into zdypz_result (s_id,j_id,t_id) values(?,?,?)";
/* 119 */           final ObjectRef pstmt = ObjectRef.create(conn.prepareStatement(sql));
/*     */           
/* 121 */           final IntRef number = IntRef.create(0);
/*     */           
/* 123 */           Row[] reCollect = (Row[])re.collect();
/*     */           
/* 125 */           Predef..MODULE$.println(new StringBuilder().append("reCollect count:").append(BoxesRunTime.boxToInteger(reCollect.length)).toString());
/*     */           
/* 127 */           Predef..MODULE$.refArrayOps((Object[])reCollect).foreach(new scala.runtime.AbstractFunction1() { public static final long serialVersionUID = 0L;
/*     */             
/* 129 */             public final void apply(Row t) { number.elem += 1;
/*     */               
/* 131 */               ((PreparedStatement)pstmt.elem).setString(1, t.apply(0).toString());
/* 132 */               ((PreparedStatement)pstmt.elem).setString(2, jobId);
/* 133 */               ((PreparedStatement)pstmt.elem).setString(3, new StringBuilder().append(t.apply(1).toString()).append(",").append(BoxesRunTime.boxToInteger(i.elem)).toString());
/* 134 */               ((PreparedStatement)pstmt.elem).addBatch();
/*     */             }
/*     */             
/* 137 */           });
/* 138 */           String sql2 = "insert into zdypz_progress (jobid,total) values(?,?)";
/* 139 */           PreparedStatement pstmt2 = conn.prepareStatement(sql2);
/*     */           
/* 141 */           if (number.elem == 0) {
/* 142 */             number.elem = -1;
/*     */           }
/*     */           
/* 145 */           pstmt2.setString(1, jobId);
/* 146 */           pstmt2.setInt(2, number.elem);
/* 147 */           pstmt2.executeUpdate();
/* 148 */           pstmt2.close();
/*     */           
/* 150 */           ((PreparedStatement)pstmt.elem).executeBatch();
/* 151 */           conn.commit();
/* 152 */           ((PreparedStatement)pstmt.elem).close();
/* 153 */           conn.close();
/*     */         }
/*     */       }
/*     */     }
/*     */   }
/*     */   
/*     */ 
/*     */ 
/*     */ 
/*     */ 
/*     */ 
/*     */ 
/*     */ 
/*     */ 
/*     */ 
/*     */ 
/*     */ 
/*     */ 
/*     */ 
/*     */ 
/*     */ 
/*     */ 
/*     */ 
/*     */ 
/*     */ 
/*     */ 
/*     */ 
/*     */ 
/*     */ 
/*     */ 
/*     */ 
/*     */ 
/*     */ 
/*     */ 
/*     */ 
/*     */ 
/*     */ 
/*     */ 
/*     */ 
/*     */ 
/*     */ 
/*     */ 
/*     */ 
/*     */ 
/*     */ 
/*     */ 
/*     */ 
/*     */ 
/*     */ 
/*     */ 
/*     */ 
/*     */ 
/*     */ 
/*     */ 
/*     */ 
/*     */ 
/*     */   public String getOldDay()
/*     */   {
/* 211 */     SimpleDateFormat dateFormat = new SimpleDateFormat("yyyyMMdd");
/* 212 */     Calendar cal = Calendar.getInstance();
/* 213 */     cal.add(5, -3);
/* 214 */     String yesterday = dateFormat.format(cal.getTime());
/*     */     
/* 216 */     return yesterday;
/*     */   }
/*     */   
/*     */   /* Error */
/*     */   public String gsonArrayFunc(InputBean inputBean, String typeC, String tableName)
/*     */   {
/*     */     // Byte code:
/*     */     //   0: getstatic 300	com/yisa/engine/uitl/TimeUtil$:MODULE$	Lcom/yisa/engine/uitl/TimeUtil$;
/*     */     //   3: aload_1
/*     */     //   4: invokevirtual 303	com/yisa/engine/common/InputBean:startTime	()Ljava/lang/String;
/*     */     //   7: invokevirtual 307	com/yisa/engine/uitl/TimeUtil$:getTimeStringFormat	(Ljava/lang/String;)Ljava/lang/String;
/*     */     //   10: astore 4
/*     */     //   12: getstatic 300	com/yisa/engine/uitl/TimeUtil$:MODULE$	Lcom/yisa/engine/uitl/TimeUtil$;
/*     */     //   15: aload_1
/*     */     //   16: invokevirtual 310	com/yisa/engine/common/InputBean:endTime	()Ljava/lang/String;
/*     */     //   19: invokevirtual 307	com/yisa/engine/uitl/TimeUtil$:getTimeStringFormat	(Ljava/lang/String;)Ljava/lang/String;
/*     */     //   22: astore 5
/*     */     //   24: aload_1
/*     */     //   25: invokevirtual 314	com/yisa/engine/common/InputBean:locationId	()[Ljava/lang/String;
/*     */     //   28: astore 6
/*     */     //   30: aload_1
/*     */     //   31: invokevirtual 317	com/yisa/engine/common/InputBean:carModel	()[Ljava/lang/String;
/*     */     //   34: astore 7
/*     */     //   36: aload_1
/*     */     //   37: invokevirtual 320	com/yisa/engine/common/InputBean:carBrand	()Ljava/lang/String;
/*     */     //   40: astore 8
/*     */     //   42: aload_1
/*     */     //   43: invokevirtual 323	com/yisa/engine/common/InputBean:carYear	()[Ljava/lang/String;
/*     */     //   46: astore 9
/*     */     //   48: aload_1
/*     */     //   49: invokevirtual 326	com/yisa/engine/common/InputBean:carColor	()Ljava/lang/String;
/*     */     //   52: astore 10
/*     */     //   54: aload_1
/*     */     //   55: invokevirtual 329	com/yisa/engine/common/InputBean:plateNumber	()Ljava/lang/String;
/*     */     //   58: astore 11
/*     */     //   60: aload_1
/*     */     //   61: invokevirtual 332	com/yisa/engine/common/InputBean:carLevel	()[Ljava/lang/String;
/*     */     //   64: astore 12
/*     */     //   66: new 269	java/text/SimpleDateFormat
/*     */     //   69: dup
/*     */     //   70: ldc_w 334
/*     */     //   73: invokespecial 273	java/text/SimpleDateFormat:<init>	(Ljava/lang/String;)V
/*     */     //   76: astore 13
/*     */     //   78: aload 13
/*     */     //   80: aload_1
/*     */     //   81: invokevirtual 303	com/yisa/engine/common/InputBean:startTime	()Ljava/lang/String;
/*     */     //   84: invokevirtual 338	java/text/SimpleDateFormat:parse	(Ljava/lang/String;)Ljava/util/Date;
/*     */     //   87: invokevirtual 343	java/util/Date:getTime	()J
/*     */     //   90: ldc2_w 344
/*     */     //   93: ldiv
/*     */     //   94: lstore 14
/*     */     //   96: aload 13
/*     */     //   98: aload_1
/*     */     //   99: invokevirtual 310	com/yisa/engine/common/InputBean:endTime	()Ljava/lang/String;
/*     */     //   102: invokevirtual 338	java/text/SimpleDateFormat:parse	(Ljava/lang/String;)Ljava/util/Date;
/*     */     //   105: invokevirtual 343	java/util/Date:getTime	()J
/*     */     //   108: ldc2_w 344
/*     */     //   111: ldiv
/*     */     //   112: lstore 16
/*     */     //   114: aload_1
/*     */     //   115: invokevirtual 348	com/yisa/engine/common/InputBean:direction	()Ljava/lang/String;
/*     */     //   118: astore 18
/*     */     //   120: new 52	java/lang/StringBuffer
/*     */     //   123: dup
/*     */     //   124: invokespecial 53	java/lang/StringBuffer:<init>	()V
/*     */     //   127: astore 19
/*     */     //   129: aload 19
/*     */     //   131: ldc_w 350
/*     */     //   134: invokevirtual 134	java/lang/StringBuffer:append	(Ljava/lang/String;)Ljava/lang/StringBuffer;
/*     */     //   137: pop
/*     */     //   138: aload 19
/*     */     //   140: aload_2
/*     */     //   141: invokevirtual 134	java/lang/StringBuffer:append	(Ljava/lang/String;)Ljava/lang/StringBuffer;
/*     */     //   144: ldc_w 352
/*     */     //   147: invokevirtual 134	java/lang/StringBuffer:append	(Ljava/lang/String;)Ljava/lang/StringBuffer;
/*     */     //   150: aload_3
/*     */     //   151: invokevirtual 134	java/lang/StringBuffer:append	(Ljava/lang/String;)Ljava/lang/StringBuffer;
/*     */     //   154: pop
/*     */     //   155: lload 14
/*     */     //   157: lconst_0
/*     */     //   158: lcmp
/*     */     //   159: ifeq +19 -> 178
/*     */     //   162: aload 19
/*     */     //   164: ldc_w 354
/*     */     //   167: invokevirtual 134	java/lang/StringBuffer:append	(Ljava/lang/String;)Ljava/lang/StringBuffer;
/*     */     //   170: lload 14
/*     */     //   172: invokevirtual 357	java/lang/StringBuffer:append	(J)Ljava/lang/StringBuffer;
/*     */     //   175: goto +6 -> 181
/*     */     //   178: getstatic 90	scala/runtime/BoxedUnit:UNIT	Lscala/runtime/BoxedUnit;
/*     */     //   181: pop
/*     */     //   182: lload 16
/*     */     //   184: lconst_0
/*     */     //   185: lcmp
/*     */     //   186: ifeq +19 -> 205
/*     */     //   189: aload 19
/*     */     //   191: ldc_w 359
/*     */     //   194: invokevirtual 134	java/lang/StringBuffer:append	(Ljava/lang/String;)Ljava/lang/StringBuffer;
/*     */     //   197: lload 16
/*     */     //   199: invokevirtual 357	java/lang/StringBuffer:append	(J)Ljava/lang/StringBuffer;
/*     */     //   202: goto +6 -> 208
/*     */     //   205: getstatic 90	scala/runtime/BoxedUnit:UNIT	Lscala/runtime/BoxedUnit;
/*     */     //   208: pop
/*     */     //   209: aload 4
/*     */     //   211: ifnonnull +9 -> 220
/*     */     //   214: getstatic 90	scala/runtime/BoxedUnit:UNIT	Lscala/runtime/BoxedUnit;
/*     */     //   217: goto +20 -> 237
/*     */     //   220: aload 19
/*     */     //   222: ldc_w 361
/*     */     //   225: invokevirtual 134	java/lang/StringBuffer:append	(Ljava/lang/String;)Ljava/lang/StringBuffer;
/*     */     //   228: aload_0
/*     */     //   229: aload 4
/*     */     //   231: invokevirtual 364	com/yisa/engine/branch/SparkEngineV2ForMultiPoint:getDateid	(Ljava/lang/String;)Ljava/lang/String;
/*     */     //   234: invokevirtual 134	java/lang/StringBuffer:append	(Ljava/lang/String;)Ljava/lang/StringBuffer;
/*     */     //   237: pop
/*     */     //   238: aload 5
/*     */     //   240: ifnonnull +9 -> 249
/*     */     //   243: getstatic 90	scala/runtime/BoxedUnit:UNIT	Lscala/runtime/BoxedUnit;
/*     */     //   246: goto +20 -> 266
/*     */     //   249: aload 19
/*     */     //   251: ldc_w 366
/*     */     //   254: invokevirtual 134	java/lang/StringBuffer:append	(Ljava/lang/String;)Ljava/lang/StringBuffer;
/*     */     //   257: aload_0
/*     */     //   258: aload 5
/*     */     //   260: invokevirtual 364	com/yisa/engine/branch/SparkEngineV2ForMultiPoint:getDateid	(Ljava/lang/String;)Ljava/lang/String;
/*     */     //   263: invokevirtual 134	java/lang/StringBuffer:append	(Ljava/lang/String;)Ljava/lang/StringBuffer;
/*     */     //   266: pop
/*     */     //   267: aload 6
/*     */     //   269: aconst_null
/*     */     //   270: if_acmpeq +97 -> 367
/*     */     //   273: aload 6
/*     */     //   275: arraylength
/*     */     //   276: iconst_0
/*     */     //   277: if_icmple +90 -> 367
/*     */     //   280: getstatic 59	scala/Predef$:MODULE$	Lscala/Predef$;
/*     */     //   283: getstatic 59	scala/Predef$:MODULE$	Lscala/Predef$;
/*     */     //   286: aload 6
/*     */     //   288: checkcast 61	[Ljava/lang/Object;
/*     */     //   291: invokevirtual 65	scala/Predef$:refArrayOps	([Ljava/lang/Object;)Lscala/collection/mutable/ArrayOps;
/*     */     //   294: new 368	com/yisa/engine/branch/SparkEngineV2ForMultiPoint$$anonfun$1
/*     */     //   297: dup
/*     */     //   298: aload_0
/*     */     //   299: invokespecial 369	com/yisa/engine/branch/SparkEngineV2ForMultiPoint$$anonfun$1:<init>	(Lcom/yisa/engine/branch/SparkEngineV2ForMultiPoint;)V
/*     */     //   302: getstatic 374	scala/Array$:MODULE$	Lscala/Array$;
/*     */     //   305: getstatic 379	scala/reflect/ClassTag$:MODULE$	Lscala/reflect/ClassTag$;
/*     */     //   308: ldc 14
/*     */     //   310: invokevirtual 383	scala/reflect/ClassTag$:apply	(Ljava/lang/Class;)Lscala/reflect/ClassTag;
/*     */     //   313: invokevirtual 387	scala/Array$:canBuildFrom	(Lscala/reflect/ClassTag;)Lscala/collection/generic/CanBuildFrom;
/*     */     //   316: invokeinterface 390 3 0
/*     */     //   321: checkcast 61	[Ljava/lang/Object;
/*     */     //   324: invokevirtual 65	scala/Predef$:refArrayOps	([Ljava/lang/Object;)Lscala/collection/mutable/ArrayOps;
/*     */     //   327: new 392	com/yisa/engine/branch/SparkEngineV2ForMultiPoint$$anonfun$2
/*     */     //   330: dup
/*     */     //   331: aload_0
/*     */     //   332: invokespecial 393	com/yisa/engine/branch/SparkEngineV2ForMultiPoint$$anonfun$2:<init>	(Lcom/yisa/engine/branch/SparkEngineV2ForMultiPoint;)V
/*     */     //   335: invokeinterface 397 2 0
/*     */     //   340: checkcast 14	java/lang/String
/*     */     //   343: astore 20
/*     */     //   345: aload 19
/*     */     //   347: ldc_w 399
/*     */     //   350: invokevirtual 134	java/lang/StringBuffer:append	(Ljava/lang/String;)Ljava/lang/StringBuffer;
/*     */     //   353: aload 20
/*     */     //   355: invokevirtual 134	java/lang/StringBuffer:append	(Ljava/lang/String;)Ljava/lang/StringBuffer;
/*     */     //   358: ldc_w 401
/*     */     //   361: invokevirtual 134	java/lang/StringBuffer:append	(Ljava/lang/String;)Ljava/lang/StringBuffer;
/*     */     //   364: goto +6 -> 370
/*     */     //   367: getstatic 90	scala/runtime/BoxedUnit:UNIT	Lscala/runtime/BoxedUnit;
/*     */     //   370: pop
/*     */     //   371: aload 9
/*     */     //   373: aconst_null
/*     */     //   374: if_acmpeq +61 -> 435
/*     */     //   377: aload 9
/*     */     //   379: arraylength
/*     */     //   380: iconst_0
/*     */     //   381: if_icmple +54 -> 435
/*     */     //   384: getstatic 59	scala/Predef$:MODULE$	Lscala/Predef$;
/*     */     //   387: aload 9
/*     */     //   389: checkcast 61	[Ljava/lang/Object;
/*     */     //   392: invokevirtual 65	scala/Predef$:refArrayOps	([Ljava/lang/Object;)Lscala/collection/mutable/ArrayOps;
/*     */     //   395: new 403	com/yisa/engine/branch/SparkEngineV2ForMultiPoint$$anonfun$3
/*     */     //   398: dup
/*     */     //   399: aload_0
/*     */     //   400: invokespecial 404	com/yisa/engine/branch/SparkEngineV2ForMultiPoint$$anonfun$3:<init>	(Lcom/yisa/engine/branch/SparkEngineV2ForMultiPoint;)V
/*     */     //   403: invokeinterface 397 2 0
/*     */     //   408: checkcast 14	java/lang/String
/*     */     //   411: astore 21
/*     */     //   413: aload 19
/*     */     //   415: ldc_w 406
/*     */     //   418: invokevirtual 134	java/lang/StringBuffer:append	(Ljava/lang/String;)Ljava/lang/StringBuffer;
/*     */     //   421: aload 21
/*     */     //   423: invokevirtual 134	java/lang/StringBuffer:append	(Ljava/lang/String;)Ljava/lang/StringBuffer;
/*     */     //   426: ldc_w 401
/*     */     //   429: invokevirtual 134	java/lang/StringBuffer:append	(Ljava/lang/String;)Ljava/lang/StringBuffer;
/*     */     //   432: goto +6 -> 438
/*     */     //   435: getstatic 90	scala/runtime/BoxedUnit:UNIT	Lscala/runtime/BoxedUnit;
/*     */     //   438: pop
/*     */     //   439: aload 12
/*     */     //   441: aconst_null
/*     */     //   442: if_acmpeq +61 -> 503
/*     */     //   445: aload 12
/*     */     //   447: arraylength
/*     */     //   448: iconst_0
/*     */     //   449: if_icmple +54 -> 503
/*     */     //   452: getstatic 59	scala/Predef$:MODULE$	Lscala/Predef$;
/*     */     //   455: aload 12
/*     */     //   457: checkcast 61	[Ljava/lang/Object;
/*     */     //   460: invokevirtual 65	scala/Predef$:refArrayOps	([Ljava/lang/Object;)Lscala/collection/mutable/ArrayOps;
/*     */     //   463: new 408	com/yisa/engine/branch/SparkEngineV2ForMultiPoint$$anonfun$4
/*     */     //   466: dup
/*     */     //   467: aload_0
/*     */     //   468: invokespecial 409	com/yisa/engine/branch/SparkEngineV2ForMultiPoint$$anonfun$4:<init>	(Lcom/yisa/engine/branch/SparkEngineV2ForMultiPoint;)V
/*     */     //   471: invokeinterface 397 2 0
/*     */     //   476: checkcast 14	java/lang/String
/*     */     //   479: astore 22
/*     */     //   481: aload 19
/*     */     //   483: ldc_w 411
/*     */     //   486: invokevirtual 134	java/lang/StringBuffer:append	(Ljava/lang/String;)Ljava/lang/StringBuffer;
/*     */     //   489: aload 22
/*     */     //   491: invokevirtual 134	java/lang/StringBuffer:append	(Ljava/lang/String;)Ljava/lang/StringBuffer;
/*     */     //   494: ldc_w 401
/*     */     //   497: invokevirtual 134	java/lang/StringBuffer:append	(Ljava/lang/String;)Ljava/lang/StringBuffer;
/*     */     //   500: goto +6 -> 506
/*     */     //   503: getstatic 90	scala/runtime/BoxedUnit:UNIT	Lscala/runtime/BoxedUnit;
/*     */     //   506: pop
/*     */     //   507: aload 7
/*     */     //   509: aconst_null
/*     */     //   510: if_acmpeq +61 -> 571
/*     */     //   513: aload 7
/*     */     //   515: arraylength
/*     */     //   516: iconst_0
/*     */     //   517: if_icmple +54 -> 571
/*     */     //   520: getstatic 59	scala/Predef$:MODULE$	Lscala/Predef$;
/*     */     //   523: aload 7
/*     */     //   525: checkcast 61	[Ljava/lang/Object;
/*     */     //   528: invokevirtual 65	scala/Predef$:refArrayOps	([Ljava/lang/Object;)Lscala/collection/mutable/ArrayOps;
/*     */     //   531: new 413	com/yisa/engine/branch/SparkEngineV2ForMultiPoint$$anonfun$5
/*     */     //   534: dup
/*     */     //   535: aload_0
/*     */     //   536: invokespecial 414	com/yisa/engine/branch/SparkEngineV2ForMultiPoint$$anonfun$5:<init>	(Lcom/yisa/engine/branch/SparkEngineV2ForMultiPoint;)V
/*     */     //   539: invokeinterface 397 2 0
/*     */     //   544: checkcast 14	java/lang/String
/*     */     //   547: astore 23
/*     */     //   549: aload 19
/*     */     //   551: ldc_w 416
/*     */     //   554: invokevirtual 134	java/lang/StringBuffer:append	(Ljava/lang/String;)Ljava/lang/StringBuffer;
/*     */     //   557: aload 23
/*     */     //   559: invokevirtual 134	java/lang/StringBuffer:append	(Ljava/lang/String;)Ljava/lang/StringBuffer;
/*     */     //   562: ldc_w 401
/*     */     //   565: invokevirtual 134	java/lang/StringBuffer:append	(Ljava/lang/String;)Ljava/lang/StringBuffer;
/*     */     //   568: goto +6 -> 574
/*     */     //   571: getstatic 90	scala/runtime/BoxedUnit:UNIT	Lscala/runtime/BoxedUnit;
/*     */     //   574: pop
/*     */     //   575: aload 18
/*     */     //   577: ifnull +30 -> 607
/*     */     //   580: aload 18
/*     */     //   582: ldc 102
/*     */     //   584: astore 24
/*     */     //   586: dup
/*     */     //   587: ifnonnull +12 -> 599
/*     */     //   590: pop
/*     */     //   591: aload 24
/*     */     //   593: ifnull +14 -> 607
/*     */     //   596: goto +17 -> 613
/*     */     //   599: aload 24
/*     */     //   601: invokevirtual 420	java/lang/Object:equals	(Ljava/lang/Object;)Z
/*     */     //   604: ifeq +9 -> 613
/*     */     //   607: getstatic 90	scala/runtime/BoxedUnit:UNIT	Lscala/runtime/BoxedUnit;
/*     */     //   610: goto +22 -> 632
/*     */     //   613: aload 19
/*     */     //   615: ldc_w 422
/*     */     //   618: invokevirtual 134	java/lang/StringBuffer:append	(Ljava/lang/String;)Ljava/lang/StringBuffer;
/*     */     //   621: aload 18
/*     */     //   623: invokevirtual 134	java/lang/StringBuffer:append	(Ljava/lang/String;)Ljava/lang/StringBuffer;
/*     */     //   626: ldc_w 424
/*     */     //   629: invokevirtual 134	java/lang/StringBuffer:append	(Ljava/lang/String;)Ljava/lang/StringBuffer;
/*     */     //   632: pop
/*     */     //   633: aload 8
/*     */     //   635: ifnull +30 -> 665
/*     */     //   638: aload 8
/*     */     //   640: ldc 102
/*     */     //   642: astore 25
/*     */     //   644: dup
/*     */     //   645: ifnonnull +12 -> 657
/*     */     //   648: pop
/*     */     //   649: aload 25
/*     */     //   651: ifnull +14 -> 665
/*     */     //   654: goto +17 -> 671
/*     */     //   657: aload 25
/*     */     //   659: invokevirtual 420	java/lang/Object:equals	(Ljava/lang/Object;)Z
/*     */     //   662: ifeq +9 -> 671
/*     */     //   665: getstatic 90	scala/runtime/BoxedUnit:UNIT	Lscala/runtime/BoxedUnit;
/*     */     //   668: goto +16 -> 684
/*     */     //   671: aload 19
/*     */     //   673: ldc_w 426
/*     */     //   676: invokevirtual 134	java/lang/StringBuffer:append	(Ljava/lang/String;)Ljava/lang/StringBuffer;
/*     */     //   679: aload 8
/*     */     //   681: invokevirtual 134	java/lang/StringBuffer:append	(Ljava/lang/String;)Ljava/lang/StringBuffer;
/*     */     //   684: pop
/*     */     //   685: aload 10
/*     */     //   687: ifnull +30 -> 717
/*     */     //   690: aload 10
/*     */     //   692: ldc 102
/*     */     //   694: astore 26
/*     */     //   696: dup
/*     */     //   697: ifnonnull +12 -> 709
/*     */     //   700: pop
/*     */     //   701: aload 26
/*     */     //   703: ifnull +14 -> 717
/*     */     //   706: goto +17 -> 723
/*     */     //   709: aload 26
/*     */     //   711: invokevirtual 420	java/lang/Object:equals	(Ljava/lang/Object;)Z
/*     */     //   714: ifeq +9 -> 723
/*     */     //   717: getstatic 90	scala/runtime/BoxedUnit:UNIT	Lscala/runtime/BoxedUnit;
/*     */     //   720: goto +16 -> 736
/*     */     //   723: aload 19
/*     */     //   725: ldc_w 428
/*     */     //   728: invokevirtual 134	java/lang/StringBuffer:append	(Ljava/lang/String;)Ljava/lang/StringBuffer;
/*     */     //   731: aload 10
/*     */     //   733: invokevirtual 134	java/lang/StringBuffer:append	(Ljava/lang/String;)Ljava/lang/StringBuffer;
/*     */     //   736: pop
/*     */     //   737: aload 11
/*     */     //   739: ifnull +30 -> 769
/*     */     //   742: aload 11
/*     */     //   744: ldc 102
/*     */     //   746: astore 27
/*     */     //   748: dup
/*     */     //   749: ifnonnull +12 -> 761
/*     */     //   752: pop
/*     */     //   753: aload 27
/*     */     //   755: ifnull +14 -> 769
/*     */     //   758: goto +17 -> 775
/*     */     //   761: aload 27
/*     */     //   763: invokevirtual 420	java/lang/Object:equals	(Ljava/lang/Object;)Z
/*     */     //   766: ifeq +9 -> 775
/*     */     //   769: getstatic 90	scala/runtime/BoxedUnit:UNIT	Lscala/runtime/BoxedUnit;
/*     */     //   772: goto +83 -> 855
/*     */     //   775: aload 11
/*     */     //   777: ldc_w 430
/*     */     //   780: invokevirtual 434	java/lang/String:contains	(Ljava/lang/CharSequence;)Z
/*     */     //   783: ifne +14 -> 797
/*     */     //   786: aload 11
/*     */     //   788: ldc_w 436
/*     */     //   791: invokevirtual 434	java/lang/String:contains	(Ljava/lang/CharSequence;)Z
/*     */     //   794: ifeq +42 -> 836
/*     */     //   797: aload 19
/*     */     //   799: ldc_w 438
/*     */     //   802: invokevirtual 134	java/lang/StringBuffer:append	(Ljava/lang/String;)Ljava/lang/StringBuffer;
/*     */     //   805: aload 11
/*     */     //   807: ldc_w 430
/*     */     //   810: ldc_w 440
/*     */     //   813: invokevirtual 444	java/lang/String:replace	(Ljava/lang/CharSequence;Ljava/lang/CharSequence;)Ljava/lang/String;
/*     */     //   816: ldc_w 436
/*     */     //   819: ldc_w 446
/*     */     //   822: invokevirtual 444	java/lang/String:replace	(Ljava/lang/CharSequence;Ljava/lang/CharSequence;)Ljava/lang/String;
/*     */     //   825: invokevirtual 134	java/lang/StringBuffer:append	(Ljava/lang/String;)Ljava/lang/StringBuffer;
/*     */     //   828: ldc -44
/*     */     //   830: invokevirtual 134	java/lang/StringBuffer:append	(Ljava/lang/String;)Ljava/lang/StringBuffer;
/*     */     //   833: goto +22 -> 855
/*     */     //   836: aload 19
/*     */     //   838: ldc_w 448
/*     */     //   841: invokevirtual 134	java/lang/StringBuffer:append	(Ljava/lang/String;)Ljava/lang/StringBuffer;
/*     */     //   844: aload 11
/*     */     //   846: invokevirtual 134	java/lang/StringBuffer:append	(Ljava/lang/String;)Ljava/lang/StringBuffer;
/*     */     //   849: ldc_w 424
/*     */     //   852: invokevirtual 134	java/lang/StringBuffer:append	(Ljava/lang/String;)Ljava/lang/StringBuffer;
/*     */     //   855: pop
/*     */     //   856: getstatic 59	scala/Predef$:MODULE$	Lscala/Predef$;
/*     */     //   859: aload 19
/*     */     //   861: invokevirtual 143	java/lang/StringBuffer:toString	()Ljava/lang/String;
/*     */     //   864: invokevirtual 149	scala/Predef$:println	(Ljava/lang/Object;)V
/*     */     //   867: aload 19
/*     */     //   869: invokevirtual 143	java/lang/StringBuffer:toString	()Ljava/lang/String;
/*     */     //   872: areturn
/*     */     // Line number table:
/*     */     //   Java source line #224	-> byte code offset #0
/*     */     //   Java source line #225	-> byte code offset #12
/*     */     //   Java source line #226	-> byte code offset #24
/*     */     //   Java source line #227	-> byte code offset #30
/*     */     //   Java source line #228	-> byte code offset #36
/*     */     //   Java source line #229	-> byte code offset #42
/*     */     //   Java source line #230	-> byte code offset #48
/*     */     //   Java source line #231	-> byte code offset #54
/*     */     //   Java source line #232	-> byte code offset #60
/*     */     //   Java source line #234	-> byte code offset #66
/*     */     //   Java source line #236	-> byte code offset #78
/*     */     //   Java source line #237	-> byte code offset #96
/*     */     //   Java source line #239	-> byte code offset #114
/*     */     //   Java source line #241	-> byte code offset #120
/*     */     //   Java source line #243	-> byte code offset #129
/*     */     //   Java source line #246	-> byte code offset #138
/*     */     //   Java source line #248	-> byte code offset #155
/*     */     //   Java source line #249	-> byte code offset #162
/*     */     //   Java source line #248	-> byte code offset #178
/*     */     //   Java source line #252	-> byte code offset #182
/*     */     //   Java source line #253	-> byte code offset #189
/*     */     //   Java source line #252	-> byte code offset #205
/*     */     //   Java source line #256	-> byte code offset #209
/*     */     //   Java source line #257	-> byte code offset #220
/*     */     //   Java source line #256	-> byte code offset #237
/*     */     //   Java source line #260	-> byte code offset #238
/*     */     //   Java source line #261	-> byte code offset #249
/*     */     //   Java source line #260	-> byte code offset #266
/*     */     //   Java source line #264	-> byte code offset #267
/*     */     //   Java source line #265	-> byte code offset #280
/*     */     //   Java source line #267	-> byte code offset #345
/*     */     //   Java source line #264	-> byte code offset #367
/*     */     //   Java source line #270	-> byte code offset #371
/*     */     //   Java source line #271	-> byte code offset #384
/*     */     //   Java source line #272	-> byte code offset #413
/*     */     //   Java source line #270	-> byte code offset #435
/*     */     //   Java source line #275	-> byte code offset #439
/*     */     //   Java source line #276	-> byte code offset #452
/*     */     //   Java source line #277	-> byte code offset #481
/*     */     //   Java source line #275	-> byte code offset #503
/*     */     //   Java source line #280	-> byte code offset #507
/*     */     //   Java source line #281	-> byte code offset #520
/*     */     //   Java source line #282	-> byte code offset #549
/*     */     //   Java source line #280	-> byte code offset #571
/*     */     //   Java source line #285	-> byte code offset #575
/*     */     //   Java source line #286	-> byte code offset #613
/*     */     //   Java source line #285	-> byte code offset #632
/*     */     //   Java source line #289	-> byte code offset #633
/*     */     //   Java source line #290	-> byte code offset #671
/*     */     //   Java source line #289	-> byte code offset #684
/*     */     //   Java source line #293	-> byte code offset #685
/*     */     //   Java source line #294	-> byte code offset #723
/*     */     //   Java source line #293	-> byte code offset #736
/*     */     //   Java source line #297	-> byte code offset #737
/*     */     //   Java source line #298	-> byte code offset #775
/*     */     //   Java source line #299	-> byte code offset #797
/*     */     //   Java source line #301	-> byte code offset #836
/*     */     //   Java source line #297	-> byte code offset #855
/*     */     //   Java source line #307	-> byte code offset #856
/*     */     //   Java source line #309	-> byte code offset #867
/*     */     // Local variable table:
/*     */     //   start	length	slot	name	signature
/*     */     //   0	873	0	this	SparkEngineV2ForMultiPoint
/*     */     //   0	873	1	inputBean	InputBean
/*     */     //   0	873	2	typeC	String
/*     */     //   0	873	3	tableName	String
/*     */     //   12	860	4	startTime1	String
/*     */     //   24	848	5	endTime1	String
/*     */     //   30	842	6	locationId	String[]
/*     */     //   36	836	7	carModel	String[]
/*     */     //   42	830	8	carBrand	String
/*     */     //   48	824	9	carYear	String[]
/*     */     //   54	818	10	carColor	String
/*     */     //   60	812	11	plateNumber	String
/*     */     //   66	806	12	carLevel	String[]
/*     */     //   78	794	13	format2	SimpleDateFormat
/*     */     //   96	776	14	startTime2	long
/*     */     //   114	758	16	endTime2	long
/*     */     //   120	752	18	direction	String
/*     */     //   129	743	19	sb	StringBuffer
/*     */     //   345	19	20	l	String
/*     */     //   413	19	21	m	String
/*     */     //   481	19	22	m	String
/*     */     //   549	19	23	m	String
/*     */   }
/*     */   
/*     */   public String getDateid(String timeString)
/*     */   {
/* 315 */     String timeLong = timeString.replaceAll("[-\\s:]", "");
/*     */     
/* 317 */     return timeLong.substring(0, 8);
/*     */   }
/*     */ }


/* Location:              E:\BaiduYunDownload\伊萨时期的一些代码\SparkEngine终极版\jars\YISAEngineBySpark2-4.0.6-SNAPSHOT-jar-with-dependencies.jar!\com\yisa\engine\branch\SparkEngineV2ForMultiPoint.class
 * Java compiler version: 6 (50.0)
 * JD-Core Version:       0.7.1
 */