/*     */ package com.yisa.engine.branch;
/*     */ 
/*     */ import com.google.gson.reflect.TypeToken;
/*     */ import com.yisa.engine.common.InputBean;
/*     */ import scala.Option;
/*     */ import scala.Predef.;
/*     */ import scala.Predef.ArrowAssoc.;
/*     */ import scala.Serializable;
/*     */ import scala.Tuple2;
/*     */ import scala.collection.mutable.HashMap;
/*     */ import scala.collection.mutable.StringBuilder;
/*     */ import scala.reflect.ScalaSignature;
/*     */ import scala.runtime.AbstractFunction1;
/*     */ import scala.runtime.AbstractFunction2;
/*     */ import scala.runtime.BoxedUnit;
/*     */ import scala.runtime.BoxesRunTime;
/*     */ import scala.runtime.IntRef;
/*     */ import scala.runtime.ObjectRef;
/*     */ 
/*     */ @ScalaSignature(bytes="\006\001q3A!\001\002\001\027\t\0013\013]1sW\026sw-\0338f-J2uN]'vYRL\007k\\5oiB\023Xm\035;p\025\t\031A!\001\004ce\006t7\r\033\006\003\013\031\ta!\0328hS:,'BA\004\t\003\021I\030n]1\013\003%\t1aY8n\007\001\0312\001\001\007\025!\ti!#D\001\017\025\ty\001#\001\003mC:<'\"A\t\002\t)\fg/Y\005\003'9\021aa\0242kK\016$\bCA\007\026\023\t1bB\001\005Sk:t\027M\0317f\021!A\002A!A!\002\023I\022\001\0027j]\026\004\"A\007\021\017\005mqR\"\001\017\013\003u\tQa]2bY\006L!a\b\017\002\rA\023X\rZ3g\023\t\t#E\001\004TiJLgn\032\006\003?qA\001\002\n\001\003\002\003\006I!G\001\ni\006\024G.\032(b[\026D\001B\n\001\003\002\003\006I!G\001\013u.Dun\035;q_J$\b\002\003\025\001\005\003\005\013\021B\r\002\035A\023Xm\035;p\021>\034H\017U8si\")!\006\001C\001W\0051A(\0338jiz\"R\001\f\0300aE\002\"!\f\001\016\003\tAQ\001G\025A\002eAQ\001J\025A\002eAQAJ\025A\002eAQ\001K\025A\002eAQa\r\001\005BQ\n1A];o)\005)\004CA\0167\023\t9DD\001\003V]&$\b\"B\035\001\t\003Q\024!D4t_:\f%O]1z\rVt7\r\006\003\032w\r#\005\"\002\0379\001\004i\024!C5oaV$()Z1o!\tq\024)D\001@\025\t\001E!\001\004d_6lwN\\\005\003\005~\022\021\"\0238qkR\024U-\0318\t\013\021B\004\031A\r\t\013\025C\004\031\001$\002\t5\f\007/\016\t\005\0172se*D\001I\025\tI%*A\004nkR\f'\r\\3\013\005-c\022AC2pY2,7\r^5p]&\021Q\n\023\002\b\021\006\034\b.T1q!\tYr*\003\002Q9\t\031\021J\034;\t\013I\003A\021A*\002\013\035,G/\r\034\025\003Q\003Ba\022'\0323!)a\013\001C\001'\006)q-\032;4c!)\001\f\001C\0013\006Iq-\032;ECR,\027\016\032\013\0033iCQaW,A\002e\t!\002^5nKN#(/\0338h\001")
/*     */ public class SparkEngineV2ForMultiPointPresto
/*     */   implements Runnable
/*     */ {
/*     */   private final String line;
/*     */   
/*     */   /* Error */
/*     */   public void run()
/*     */   {
/*     */     // Byte code:
/*     */     //   0: new 21	scala/collection/mutable/StringBuilder
/*     */     //   3: dup
/*     */     //   4: invokespecial 24	scala/collection/mutable/StringBuilder:<init>	()V
/*     */     //   7: ldc 26
/*     */     //   9: invokevirtual 30	scala/collection/mutable/StringBuilder:append	(Ljava/lang/Object;)Lscala/collection/mutable/StringBuilder;
/*     */     //   12: aload_0
/*     */     //   13: getfield 32	com/yisa/engine/branch/SparkEngineV2ForMultiPointPresto:PrestoHostPort	Ljava/lang/String;
/*     */     //   16: invokevirtual 30	scala/collection/mutable/StringBuilder:append	(Ljava/lang/Object;)Lscala/collection/mutable/StringBuilder;
/*     */     //   19: ldc 34
/*     */     //   21: invokevirtual 30	scala/collection/mutable/StringBuilder:append	(Ljava/lang/Object;)Lscala/collection/mutable/StringBuilder;
/*     */     //   24: invokevirtual 38	scala/collection/mutable/StringBuilder:toString	()Ljava/lang/String;
/*     */     //   27: astore_1
/*     */     //   28: ldc 40
/*     */     //   30: astore_2
/*     */     //   31: ldc 42
/*     */     //   33: astore_3
/*     */     //   34: ldc 44
/*     */     //   36: astore 4
/*     */     //   38: aconst_null
/*     */     //   39: astore 5
/*     */     //   41: aconst_null
/*     */     //   42: astore 6
/*     */     //   44: aconst_null
/*     */     //   45: astore 7
/*     */     //   47: aconst_null
/*     */     //   48: astore 8
/*     */     //   50: ldc 46
/*     */     //   52: astore 9
/*     */     //   54: aconst_null
/*     */     //   55: astore 10
/*     */     //   57: ldc 48
/*     */     //   59: astore 11
/*     */     //   61: aconst_null
/*     */     //   62: astore 12
/*     */     //   64: aload_0
/*     */     //   65: getfield 50	com/yisa/engine/branch/SparkEngineV2ForMultiPointPresto:line	Ljava/lang/String;
/*     */     //   68: ldc 52
/*     */     //   70: invokevirtual 58	java/lang/String:split	(Ljava/lang/String;)[Ljava/lang/String;
/*     */     //   73: astore 13
/*     */     //   75: aload 13
/*     */     //   77: iconst_1
/*     */     //   78: aaload
/*     */     //   79: astore 14
/*     */     //   81: aload 13
/*     */     //   83: iconst_2
/*     */     //   84: aaload
/*     */     //   85: astore 15
/*     */     //   87: new 60	com/google/gson/Gson
/*     */     //   90: dup
/*     */     //   91: invokespecial 61	com/google/gson/Gson:<init>	()V
/*     */     //   94: astore 16
/*     */     //   96: new 63	com/yisa/engine/branch/SparkEngineV2ForMultiPointPresto$$anon$1
/*     */     //   99: dup
/*     */     //   100: aload_0
/*     */     //   101: invokespecial 66	com/yisa/engine/branch/SparkEngineV2ForMultiPointPresto$$anon$1:<init>	(Lcom/yisa/engine/branch/SparkEngineV2ForMultiPointPresto;)V
/*     */     //   104: invokevirtual 70	com/yisa/engine/branch/SparkEngineV2ForMultiPointPresto$$anon$1:getType	()Ljava/lang/reflect/Type;
/*     */     //   107: astore 17
/*     */     //   109: aload 16
/*     */     //   111: aload 15
/*     */     //   113: aload 17
/*     */     //   115: invokevirtual 74	com/google/gson/Gson:fromJson	(Ljava/lang/String;Ljava/lang/reflect/Type;)Ljava/lang/Object;
/*     */     //   118: checkcast 76	[Lcom/yisa/engine/common/InputBean;
/*     */     //   121: astore 18
/*     */     //   123: new 78	scala/collection/mutable/HashMap
/*     */     //   126: dup
/*     */     //   127: invokespecial 79	scala/collection/mutable/HashMap:<init>	()V
/*     */     //   130: astore 19
/*     */     //   132: aload 19
/*     */     //   134: getstatic 85	scala/Predef$ArrowAssoc$:MODULE$	Lscala/Predef$ArrowAssoc$;
/*     */     //   137: getstatic 90	scala/Predef$:MODULE$	Lscala/Predef$;
/*     */     //   140: iconst_1
/*     */     //   141: invokestatic 96	scala/runtime/BoxesRunTime:boxToInteger	(I)Ljava/lang/Integer;
/*     */     //   144: invokevirtual 100	scala/Predef$:ArrowAssoc	(Ljava/lang/Object;)Ljava/lang/Object;
/*     */     //   147: iconst_1
/*     */     //   148: invokestatic 96	scala/runtime/BoxesRunTime:boxToInteger	(I)Ljava/lang/Integer;
/*     */     //   151: invokevirtual 104	scala/Predef$ArrowAssoc$:$minus$greater$extension	(Ljava/lang/Object;Ljava/lang/Object;)Lscala/Tuple2;
/*     */     //   154: invokevirtual 108	scala/collection/mutable/HashMap:$plus$eq	(Lscala/Tuple2;)Lscala/collection/mutable/HashMap;
/*     */     //   157: pop
/*     */     //   158: aload 19
/*     */     //   160: getstatic 85	scala/Predef$ArrowAssoc$:MODULE$	Lscala/Predef$ArrowAssoc$;
/*     */     //   163: getstatic 90	scala/Predef$:MODULE$	Lscala/Predef$;
/*     */     //   166: iconst_2
/*     */     //   167: invokestatic 96	scala/runtime/BoxesRunTime:boxToInteger	(I)Ljava/lang/Integer;
/*     */     //   170: invokevirtual 100	scala/Predef$:ArrowAssoc	(Ljava/lang/Object;)Ljava/lang/Object;
/*     */     //   173: iconst_2
/*     */     //   174: invokestatic 96	scala/runtime/BoxesRunTime:boxToInteger	(I)Ljava/lang/Integer;
/*     */     //   177: invokevirtual 104	scala/Predef$ArrowAssoc$:$minus$greater$extension	(Ljava/lang/Object;Ljava/lang/Object;)Lscala/Tuple2;
/*     */     //   180: invokevirtual 108	scala/collection/mutable/HashMap:$plus$eq	(Lscala/Tuple2;)Lscala/collection/mutable/HashMap;
/*     */     //   183: pop
/*     */     //   184: aload 19
/*     */     //   186: getstatic 85	scala/Predef$ArrowAssoc$:MODULE$	Lscala/Predef$ArrowAssoc$;
/*     */     //   189: getstatic 90	scala/Predef$:MODULE$	Lscala/Predef$;
/*     */     //   192: iconst_3
/*     */     //   193: invokestatic 96	scala/runtime/BoxesRunTime:boxToInteger	(I)Ljava/lang/Integer;
/*     */     //   196: invokevirtual 100	scala/Predef$:ArrowAssoc	(Ljava/lang/Object;)Ljava/lang/Object;
/*     */     //   199: iconst_4
/*     */     //   200: invokestatic 96	scala/runtime/BoxesRunTime:boxToInteger	(I)Ljava/lang/Integer;
/*     */     //   203: invokevirtual 104	scala/Predef$ArrowAssoc$:$minus$greater$extension	(Ljava/lang/Object;Ljava/lang/Object;)Lscala/Tuple2;
/*     */     //   206: invokevirtual 108	scala/collection/mutable/HashMap:$plus$eq	(Lscala/Tuple2;)Lscala/collection/mutable/HashMap;
/*     */     //   209: pop
/*     */     //   210: aload 19
/*     */     //   212: getstatic 85	scala/Predef$ArrowAssoc$:MODULE$	Lscala/Predef$ArrowAssoc$;
/*     */     //   215: getstatic 90	scala/Predef$:MODULE$	Lscala/Predef$;
/*     */     //   218: iconst_4
/*     */     //   219: invokestatic 96	scala/runtime/BoxesRunTime:boxToInteger	(I)Ljava/lang/Integer;
/*     */     //   222: invokevirtual 100	scala/Predef$:ArrowAssoc	(Ljava/lang/Object;)Ljava/lang/Object;
/*     */     //   225: bipush 8
/*     */     //   227: invokestatic 96	scala/runtime/BoxesRunTime:boxToInteger	(I)Ljava/lang/Integer;
/*     */     //   230: invokevirtual 104	scala/Predef$ArrowAssoc$:$minus$greater$extension	(Ljava/lang/Object;Ljava/lang/Object;)Lscala/Tuple2;
/*     */     //   233: invokevirtual 108	scala/collection/mutable/HashMap:$plus$eq	(Lscala/Tuple2;)Lscala/collection/mutable/HashMap;
/*     */     //   236: pop
/*     */     //   237: aload 19
/*     */     //   239: getstatic 85	scala/Predef$ArrowAssoc$:MODULE$	Lscala/Predef$ArrowAssoc$;
/*     */     //   242: getstatic 90	scala/Predef$:MODULE$	Lscala/Predef$;
/*     */     //   245: iconst_5
/*     */     //   246: invokestatic 96	scala/runtime/BoxesRunTime:boxToInteger	(I)Ljava/lang/Integer;
/*     */     //   249: invokevirtual 100	scala/Predef$:ArrowAssoc	(Ljava/lang/Object;)Ljava/lang/Object;
/*     */     //   252: bipush 16
/*     */     //   254: invokestatic 96	scala/runtime/BoxesRunTime:boxToInteger	(I)Ljava/lang/Integer;
/*     */     //   257: invokevirtual 104	scala/Predef$ArrowAssoc$:$minus$greater$extension	(Ljava/lang/Object;Ljava/lang/Object;)Lscala/Tuple2;
/*     */     //   260: invokevirtual 108	scala/collection/mutable/HashMap:$plus$eq	(Lscala/Tuple2;)Lscala/collection/mutable/HashMap;
/*     */     //   263: pop
/*     */     //   264: aconst_null
/*     */     //   265: astore 20
/*     */     //   267: aconst_null
/*     */     //   268: astore 21
/*     */     //   270: iconst_0
/*     */     //   271: invokestatic 114	scala/runtime/IntRef:create	(I)Lscala/runtime/IntRef;
/*     */     //   274: astore 22
/*     */     //   276: aload_0
/*     */     //   277: invokevirtual 118	com/yisa/engine/branch/SparkEngineV2ForMultiPointPresto:get16	()Lscala/collection/mutable/HashMap;
/*     */     //   280: invokestatic 123	scala/runtime/ObjectRef:create	(Ljava/lang/Object;)Lscala/runtime/ObjectRef;
/*     */     //   283: astore 23
/*     */     //   285: aload_0
/*     */     //   286: invokevirtual 126	com/yisa/engine/branch/SparkEngineV2ForMultiPointPresto:get31	()Lscala/collection/mutable/HashMap;
/*     */     //   289: astore 24
/*     */     //   291: aload 18
/*     */     //   293: arraylength
/*     */     //   294: iconst_0
/*     */     //   295: if_icmple +791 -> 1086
/*     */     //   298: ldc 42
/*     */     //   300: invokestatic 123	scala/runtime/ObjectRef:create	(Ljava/lang/Object;)Lscala/runtime/ObjectRef;
/*     */     //   303: astore 27
/*     */     //   305: ldc 42
/*     */     //   307: invokestatic 123	scala/runtime/ObjectRef:create	(Ljava/lang/Object;)Lscala/runtime/ObjectRef;
/*     */     //   310: astore 28
/*     */     //   312: new 128	java/lang/StringBuffer
/*     */     //   315: dup
/*     */     //   316: invokespecial 129	java/lang/StringBuffer:<init>	()V
/*     */     //   319: invokestatic 123	scala/runtime/ObjectRef:create	(Ljava/lang/Object;)Lscala/runtime/ObjectRef;
/*     */     //   322: astore 29
/*     */     //   324: aload 29
/*     */     //   326: getfield 133	scala/runtime/ObjectRef:elem	Ljava/lang/Object;
/*     */     //   329: checkcast 128	java/lang/StringBuffer
/*     */     //   332: ldc -121
/*     */     //   334: invokevirtual 138	java/lang/StringBuffer:append	(Ljava/lang/String;)Ljava/lang/StringBuffer;
/*     */     //   337: pop
/*     */     //   338: iconst_1
/*     */     //   339: invokestatic 114	scala/runtime/IntRef:create	(I)Lscala/runtime/IntRef;
/*     */     //   342: astore 30
/*     */     //   344: getstatic 90	scala/Predef$:MODULE$	Lscala/Predef$;
/*     */     //   347: aload 18
/*     */     //   349: checkcast 140	[Ljava/lang/Object;
/*     */     //   352: invokevirtual 144	scala/Predef$:refArrayOps	([Ljava/lang/Object;)Lscala/collection/mutable/ArrayOps;
/*     */     //   355: new 146	com/yisa/engine/branch/SparkEngineV2ForMultiPointPresto$$anonfun$run$1
/*     */     //   358: dup
/*     */     //   359: aload_0
/*     */     //   360: aload 18
/*     */     //   362: aload 19
/*     */     //   364: aload 22
/*     */     //   366: aload 23
/*     */     //   368: aload 27
/*     */     //   370: aload 28
/*     */     //   372: aload 29
/*     */     //   374: aload 30
/*     */     //   376: invokespecial 149	com/yisa/engine/branch/SparkEngineV2ForMultiPointPresto$$anonfun$run$1:<init>	(Lcom/yisa/engine/branch/SparkEngineV2ForMultiPointPresto;[Lcom/yisa/engine/common/InputBean;Lscala/collection/mutable/HashMap;Lscala/runtime/IntRef;Lscala/runtime/ObjectRef;Lscala/runtime/ObjectRef;Lscala/runtime/ObjectRef;Lscala/runtime/ObjectRef;Lscala/runtime/IntRef;)V
/*     */     //   379: invokeinterface 155 2 0
/*     */     //   384: aload 29
/*     */     //   386: getfield 133	scala/runtime/ObjectRef:elem	Ljava/lang/Object;
/*     */     //   389: checkcast 128	java/lang/StringBuffer
/*     */     //   392: ldc -99
/*     */     //   394: invokevirtual 138	java/lang/StringBuffer:append	(Ljava/lang/String;)Ljava/lang/StringBuffer;
/*     */     //   397: pop
/*     */     //   398: getstatic 90	scala/Predef$:MODULE$	Lscala/Predef$;
/*     */     //   401: new 21	scala/collection/mutable/StringBuilder
/*     */     //   404: dup
/*     */     //   405: invokespecial 24	scala/collection/mutable/StringBuilder:<init>	()V
/*     */     //   408: ldc -97
/*     */     //   410: invokevirtual 30	scala/collection/mutable/StringBuilder:append	(Ljava/lang/Object;)Lscala/collection/mutable/StringBuilder;
/*     */     //   413: aload 29
/*     */     //   415: getfield 133	scala/runtime/ObjectRef:elem	Ljava/lang/Object;
/*     */     //   418: checkcast 128	java/lang/StringBuffer
/*     */     //   421: invokevirtual 160	java/lang/StringBuffer:toString	()Ljava/lang/String;
/*     */     //   424: invokevirtual 30	scala/collection/mutable/StringBuilder:append	(Ljava/lang/Object;)Lscala/collection/mutable/StringBuilder;
/*     */     //   427: invokevirtual 38	scala/collection/mutable/StringBuilder:toString	()Ljava/lang/String;
/*     */     //   430: invokevirtual 164	scala/Predef$:println	(Ljava/lang/Object;)V
/*     */     //   433: iconst_0
/*     */     //   434: istore 31
/*     */     //   436: getstatic 169	com/yisa/engine/db/MySQLConnectManager$:MODULE$	Lcom/yisa/engine/db/MySQLConnectManager$;
/*     */     //   439: aload_0
/*     */     //   440: getfield 171	com/yisa/engine/branch/SparkEngineV2ForMultiPointPresto:zkHostport	Ljava/lang/String;
/*     */     //   443: invokevirtual 175	com/yisa/engine/db/MySQLConnectManager$:getConnet	(Ljava/lang/String;)Ljava/sql/Connection;
/*     */     //   446: astore 8
/*     */     //   448: aload 8
/*     */     //   450: iconst_0
/*     */     //   451: invokeinterface 181 2 0
/*     */     //   456: aload 8
/*     */     //   458: aload 9
/*     */     //   460: invokeinterface 185 2 0
/*     */     //   465: astore 10
/*     */     //   467: aload 8
/*     */     //   469: aload 11
/*     */     //   471: invokeinterface 185 2 0
/*     */     //   476: astore 12
/*     */     //   478: aload 4
/*     */     //   480: invokestatic 191	java/lang/Class:forName	(Ljava/lang/String;)Ljava/lang/Class;
/*     */     //   483: pop
/*     */     //   484: aload_1
/*     */     //   485: aload_2
/*     */     //   486: aconst_null
/*     */     //   487: invokestatic 197	java/sql/DriverManager:getConnection	(Ljava/lang/String;Ljava/lang/String;Ljava/lang/String;)Ljava/sql/Connection;
/*     */     //   490: astore 5
/*     */     //   492: aload 5
/*     */     //   494: invokeinterface 201 1 0
/*     */     //   499: astore 6
/*     */     //   501: aload 6
/*     */     //   503: aload 29
/*     */     //   505: getfield 133	scala/runtime/ObjectRef:elem	Ljava/lang/Object;
/*     */     //   508: checkcast 128	java/lang/StringBuffer
/*     */     //   511: invokevirtual 160	java/lang/StringBuffer:toString	()Ljava/lang/String;
/*     */     //   514: invokeinterface 207 2 0
/*     */     //   519: astore 7
/*     */     //   521: ldc 42
/*     */     //   523: aload 27
/*     */     //   525: getfield 133	scala/runtime/ObjectRef:elem	Ljava/lang/Object;
/*     */     //   528: checkcast 54	java/lang/String
/*     */     //   531: invokevirtual 211	java/lang/String:equals	(Ljava/lang/Object;)Z
/*     */     //   534: ifeq +252 -> 786
/*     */     //   537: aload 7
/*     */     //   539: invokeinterface 217 1 0
/*     */     //   544: ifeq +187 -> 731
/*     */     //   547: aload 7
/*     */     //   549: iconst_1
/*     */     //   550: invokeinterface 221 2 0
/*     */     //   555: astore 32
/*     */     //   557: aload 7
/*     */     //   559: iconst_2
/*     */     //   560: invokeinterface 221 2 0
/*     */     //   565: astore 33
/*     */     //   567: aload 22
/*     */     //   569: getfield 224	scala/runtime/IntRef:elem	I
/*     */     //   572: iconst_2
/*     */     //   573: if_icmplt +151 -> 724
/*     */     //   576: aload 22
/*     */     //   578: getfield 224	scala/runtime/IntRef:elem	I
/*     */     //   581: iconst_2
/*     */     //   582: if_icmple +15 -> 597
/*     */     //   585: aload 22
/*     */     //   587: aload 22
/*     */     //   589: getfield 224	scala/runtime/IntRef:elem	I
/*     */     //   592: iconst_1
/*     */     //   593: isub
/*     */     //   594: putfield 224	scala/runtime/IntRef:elem	I
/*     */     //   597: getstatic 90	scala/Predef$:MODULE$	Lscala/Predef$;
/*     */     //   600: aload 24
/*     */     //   602: aload 33
/*     */     //   604: invokevirtual 228	scala/collection/mutable/HashMap:get	(Ljava/lang/Object;)Lscala/Option;
/*     */     //   607: invokevirtual 229	java/lang/Object:toString	()Ljava/lang/String;
/*     */     //   610: ldc -25
/*     */     //   612: invokevirtual 58	java/lang/String:split	(Ljava/lang/String;)[Ljava/lang/String;
/*     */     //   615: checkcast 140	[Ljava/lang/Object;
/*     */     //   618: invokevirtual 144	scala/Predef$:refArrayOps	([Ljava/lang/Object;)Lscala/collection/mutable/ArrayOps;
/*     */     //   621: invokeinterface 235 1 0
/*     */     //   626: istore 34
/*     */     //   628: iload 34
/*     */     //   630: aload 22
/*     */     //   632: getfield 224	scala/runtime/IntRef:elem	I
/*     */     //   635: if_icmplt +83 -> 718
/*     */     //   638: iload 31
/*     */     //   640: iconst_1
/*     */     //   641: iadd
/*     */     //   642: istore 31
/*     */     //   644: aload 10
/*     */     //   646: iconst_1
/*     */     //   647: aload 32
/*     */     //   649: invokeinterface 241 3 0
/*     */     //   654: aload 10
/*     */     //   656: iconst_2
/*     */     //   657: aload 14
/*     */     //   659: invokeinterface 241 3 0
/*     */     //   664: aload 10
/*     */     //   666: iconst_3
/*     */     //   667: aload 24
/*     */     //   669: aload 33
/*     */     //   671: invokevirtual 228	scala/collection/mutable/HashMap:get	(Ljava/lang/Object;)Lscala/Option;
/*     */     //   674: invokevirtual 246	scala/Option:get	()Ljava/lang/Object;
/*     */     //   677: checkcast 54	java/lang/String
/*     */     //   680: invokeinterface 241 3 0
/*     */     //   685: aload 10
/*     */     //   687: invokeinterface 249 1 0
/*     */     //   692: iload 31
/*     */     //   694: sipush 500
/*     */     //   697: irem
/*     */     //   698: iconst_0
/*     */     //   699: if_icmpne +13 -> 712
/*     */     //   702: aload 10
/*     */     //   704: invokeinterface 253 1 0
/*     */     //   709: goto +18 -> 727
/*     */     //   712: getstatic 259	scala/runtime/BoxedUnit:UNIT	Lscala/runtime/BoxedUnit;
/*     */     //   715: goto +12 -> 727
/*     */     //   718: getstatic 259	scala/runtime/BoxedUnit:UNIT	Lscala/runtime/BoxedUnit;
/*     */     //   721: goto +6 -> 727
/*     */     //   724: getstatic 259	scala/runtime/BoxedUnit:UNIT	Lscala/runtime/BoxedUnit;
/*     */     //   727: pop
/*     */     //   728: goto -191 -> 537
/*     */     //   731: iload 31
/*     */     //   733: iconst_0
/*     */     //   734: if_icmpne +6 -> 740
/*     */     //   737: iconst_m1
/*     */     //   738: istore 31
/*     */     //   740: aload 12
/*     */     //   742: iconst_1
/*     */     //   743: aload 14
/*     */     //   745: invokeinterface 241 3 0
/*     */     //   750: aload 12
/*     */     //   752: iconst_2
/*     */     //   753: iload 31
/*     */     //   755: invokeinterface 263 3 0
/*     */     //   760: aload 12
/*     */     //   762: invokeinterface 266 1 0
/*     */     //   767: pop
/*     */     //   768: aload 10
/*     */     //   770: invokeinterface 253 1 0
/*     */     //   775: pop
/*     */     //   776: aload 8
/*     */     //   778: invokeinterface 269 1 0
/*     */     //   783: goto +529 -> 1312
/*     */     //   786: aload 7
/*     */     //   788: invokeinterface 217 1 0
/*     */     //   793: ifeq +238 -> 1031
/*     */     //   796: aload 7
/*     */     //   798: iconst_1
/*     */     //   799: invokeinterface 221 2 0
/*     */     //   804: astore 35
/*     */     //   806: aload 7
/*     */     //   808: iconst_2
/*     */     //   809: invokeinterface 221 2 0
/*     */     //   814: astore 36
/*     */     //   816: aload 23
/*     */     //   818: getfield 133	scala/runtime/ObjectRef:elem	Ljava/lang/Object;
/*     */     //   821: checkcast 78	scala/collection/mutable/HashMap
/*     */     //   824: aload 36
/*     */     //   826: invokevirtual 272	scala/collection/mutable/HashMap:contains	(Ljava/lang/Object;)Z
/*     */     //   829: ifeq +195 -> 1024
/*     */     //   832: aload 22
/*     */     //   834: getfield 224	scala/runtime/IntRef:elem	I
/*     */     //   837: iconst_2
/*     */     //   838: if_icmplt +180 -> 1018
/*     */     //   841: aload 22
/*     */     //   843: getfield 224	scala/runtime/IntRef:elem	I
/*     */     //   846: iconst_2
/*     */     //   847: if_icmple +15 -> 862
/*     */     //   850: aload 22
/*     */     //   852: aload 22
/*     */     //   854: getfield 224	scala/runtime/IntRef:elem	I
/*     */     //   857: iconst_1
/*     */     //   858: isub
/*     */     //   859: putfield 224	scala/runtime/IntRef:elem	I
/*     */     //   862: getstatic 90	scala/Predef$:MODULE$	Lscala/Predef$;
/*     */     //   865: aload 24
/*     */     //   867: aload 36
/*     */     //   869: invokevirtual 228	scala/collection/mutable/HashMap:get	(Ljava/lang/Object;)Lscala/Option;
/*     */     //   872: invokevirtual 229	java/lang/Object:toString	()Ljava/lang/String;
/*     */     //   875: ldc -25
/*     */     //   877: invokevirtual 58	java/lang/String:split	(Ljava/lang/String;)[Ljava/lang/String;
/*     */     //   880: checkcast 140	[Ljava/lang/Object;
/*     */     //   883: invokevirtual 144	scala/Predef$:refArrayOps	([Ljava/lang/Object;)Lscala/collection/mutable/ArrayOps;
/*     */     //   886: invokeinterface 235 1 0
/*     */     //   891: istore 37
/*     */     //   893: iload 37
/*     */     //   895: aload 22
/*     */     //   897: getfield 224	scala/runtime/IntRef:elem	I
/*     */     //   900: if_icmplt +112 -> 1012
/*     */     //   903: iload 31
/*     */     //   905: iconst_1
/*     */     //   906: iadd
/*     */     //   907: istore 31
/*     */     //   909: aload 10
/*     */     //   911: iconst_1
/*     */     //   912: aload 35
/*     */     //   914: invokeinterface 241 3 0
/*     */     //   919: aload 10
/*     */     //   921: iconst_2
/*     */     //   922: aload 14
/*     */     //   924: invokeinterface 241 3 0
/*     */     //   929: aload 10
/*     */     //   931: iconst_3
/*     */     //   932: new 21	scala/collection/mutable/StringBuilder
/*     */     //   935: dup
/*     */     //   936: invokespecial 24	scala/collection/mutable/StringBuilder:<init>	()V
/*     */     //   939: aload 24
/*     */     //   941: aload 36
/*     */     //   943: invokevirtual 228	scala/collection/mutable/HashMap:get	(Ljava/lang/Object;)Lscala/Option;
/*     */     //   946: invokevirtual 246	scala/Option:get	()Ljava/lang/Object;
/*     */     //   949: checkcast 54	java/lang/String
/*     */     //   952: invokevirtual 30	scala/collection/mutable/StringBuilder:append	(Ljava/lang/Object;)Lscala/collection/mutable/StringBuilder;
/*     */     //   955: ldc -25
/*     */     //   957: invokevirtual 30	scala/collection/mutable/StringBuilder:append	(Ljava/lang/Object;)Lscala/collection/mutable/StringBuilder;
/*     */     //   960: aload 28
/*     */     //   962: getfield 133	scala/runtime/ObjectRef:elem	Ljava/lang/Object;
/*     */     //   965: checkcast 54	java/lang/String
/*     */     //   968: invokevirtual 30	scala/collection/mutable/StringBuilder:append	(Ljava/lang/Object;)Lscala/collection/mutable/StringBuilder;
/*     */     //   971: invokevirtual 38	scala/collection/mutable/StringBuilder:toString	()Ljava/lang/String;
/*     */     //   974: invokeinterface 241 3 0
/*     */     //   979: aload 10
/*     */     //   981: invokeinterface 249 1 0
/*     */     //   986: iload 31
/*     */     //   988: sipush 500
/*     */     //   991: irem
/*     */     //   992: iconst_0
/*     */     //   993: if_icmpne +13 -> 1006
/*     */     //   996: aload 10
/*     */     //   998: invokeinterface 253 1 0
/*     */     //   1003: goto +24 -> 1027
/*     */     //   1006: getstatic 259	scala/runtime/BoxedUnit:UNIT	Lscala/runtime/BoxedUnit;
/*     */     //   1009: goto +18 -> 1027
/*     */     //   1012: getstatic 259	scala/runtime/BoxedUnit:UNIT	Lscala/runtime/BoxedUnit;
/*     */     //   1015: goto +12 -> 1027
/*     */     //   1018: getstatic 259	scala/runtime/BoxedUnit:UNIT	Lscala/runtime/BoxedUnit;
/*     */     //   1021: goto +6 -> 1027
/*     */     //   1024: getstatic 259	scala/runtime/BoxedUnit:UNIT	Lscala/runtime/BoxedUnit;
/*     */     //   1027: pop
/*     */     //   1028: goto -242 -> 786
/*     */     //   1031: iload 31
/*     */     //   1033: iconst_0
/*     */     //   1034: if_icmpne +6 -> 1040
/*     */     //   1037: iconst_m1
/*     */     //   1038: istore 31
/*     */     //   1040: aload 12
/*     */     //   1042: iconst_1
/*     */     //   1043: aload 14
/*     */     //   1045: invokeinterface 241 3 0
/*     */     //   1050: aload 12
/*     */     //   1052: iconst_2
/*     */     //   1053: iload 31
/*     */     //   1055: invokeinterface 263 3 0
/*     */     //   1060: aload 12
/*     */     //   1062: invokeinterface 266 1 0
/*     */     //   1067: pop
/*     */     //   1068: aload 10
/*     */     //   1070: invokeinterface 253 1 0
/*     */     //   1075: pop
/*     */     //   1076: aload 8
/*     */     //   1078: invokeinterface 269 1 0
/*     */     //   1083: goto +229 -> 1312
/*     */     //   1086: getstatic 90	scala/Predef$:MODULE$	Lscala/Predef$;
/*     */     //   1089: new 21	scala/collection/mutable/StringBuilder
/*     */     //   1092: dup
/*     */     //   1093: invokespecial 24	scala/collection/mutable/StringBuilder:<init>	()V
/*     */     //   1096: ldc_w 274
/*     */     //   1099: invokevirtual 30	scala/collection/mutable/StringBuilder:append	(Ljava/lang/Object;)Lscala/collection/mutable/StringBuilder;
/*     */     //   1102: aload 13
/*     */     //   1104: invokevirtual 30	scala/collection/mutable/StringBuilder:append	(Ljava/lang/Object;)Lscala/collection/mutable/StringBuilder;
/*     */     //   1107: invokevirtual 38	scala/collection/mutable/StringBuilder:toString	()Ljava/lang/String;
/*     */     //   1110: invokevirtual 164	scala/Predef$:println	(Ljava/lang/Object;)V
/*     */     //   1113: goto +199 -> 1312
/*     */     //   1116: astore 25
/*     */     //   1118: getstatic 90	scala/Predef$:MODULE$	Lscala/Predef$;
/*     */     //   1121: new 21	scala/collection/mutable/StringBuilder
/*     */     //   1124: dup
/*     */     //   1125: invokespecial 24	scala/collection/mutable/StringBuilder:<init>	()V
/*     */     //   1128: ldc_w 276
/*     */     //   1131: invokevirtual 30	scala/collection/mutable/StringBuilder:append	(Ljava/lang/Object;)Lscala/collection/mutable/StringBuilder;
/*     */     //   1134: aload 25
/*     */     //   1136: invokevirtual 279	java/lang/Exception:printStackTrace	()V
/*     */     //   1139: getstatic 259	scala/runtime/BoxedUnit:UNIT	Lscala/runtime/BoxedUnit;
/*     */     //   1142: invokevirtual 30	scala/collection/mutable/StringBuilder:append	(Ljava/lang/Object;)Lscala/collection/mutable/StringBuilder;
/*     */     //   1145: invokevirtual 38	scala/collection/mutable/StringBuilder:toString	()Ljava/lang/String;
/*     */     //   1148: invokevirtual 164	scala/Predef$:println	(Ljava/lang/Object;)V
/*     */     //   1151: aload 12
/*     */     //   1153: iconst_1
/*     */     //   1154: aload 14
/*     */     //   1156: invokeinterface 241 3 0
/*     */     //   1161: aload 12
/*     */     //   1163: iconst_2
/*     */     //   1164: iconst_m1
/*     */     //   1165: invokeinterface 263 3 0
/*     */     //   1170: aload 12
/*     */     //   1172: invokeinterface 266 1 0
/*     */     //   1177: pop
/*     */     //   1178: goto +134 -> 1312
/*     */     //   1181: astore 26
/*     */     //   1183: aload 12
/*     */     //   1185: ifnull +19 -> 1204
/*     */     //   1188: aload 12
/*     */     //   1190: invokeinterface 282 1 0
/*     */     //   1195: getstatic 90	scala/Predef$:MODULE$	Lscala/Predef$;
/*     */     //   1198: ldc_w 284
/*     */     //   1201: invokevirtual 164	scala/Predef$:println	(Ljava/lang/Object;)V
/*     */     //   1204: aload 10
/*     */     //   1206: ifnull +19 -> 1225
/*     */     //   1209: aload 10
/*     */     //   1211: invokeinterface 282 1 0
/*     */     //   1216: getstatic 90	scala/Predef$:MODULE$	Lscala/Predef$;
/*     */     //   1219: ldc_w 286
/*     */     //   1222: invokevirtual 164	scala/Predef$:println	(Ljava/lang/Object;)V
/*     */     //   1225: aload 8
/*     */     //   1227: ifnull +19 -> 1246
/*     */     //   1230: aload 8
/*     */     //   1232: invokeinterface 287 1 0
/*     */     //   1237: getstatic 90	scala/Predef$:MODULE$	Lscala/Predef$;
/*     */     //   1240: ldc_w 289
/*     */     //   1243: invokevirtual 164	scala/Predef$:println	(Ljava/lang/Object;)V
/*     */     //   1246: aload 7
/*     */     //   1248: ifnull +19 -> 1267
/*     */     //   1251: aload 7
/*     */     //   1253: invokeinterface 290 1 0
/*     */     //   1258: getstatic 90	scala/Predef$:MODULE$	Lscala/Predef$;
/*     */     //   1261: ldc_w 292
/*     */     //   1264: invokevirtual 164	scala/Predef$:println	(Ljava/lang/Object;)V
/*     */     //   1267: aload 6
/*     */     //   1269: ifnull +19 -> 1288
/*     */     //   1272: aload 6
/*     */     //   1274: invokeinterface 293 1 0
/*     */     //   1279: getstatic 90	scala/Predef$:MODULE$	Lscala/Predef$;
/*     */     //   1282: ldc_w 295
/*     */     //   1285: invokevirtual 164	scala/Predef$:println	(Ljava/lang/Object;)V
/*     */     //   1288: aload 5
/*     */     //   1290: ifnull +19 -> 1309
/*     */     //   1293: aload 5
/*     */     //   1295: invokeinterface 287 1 0
/*     */     //   1300: getstatic 90	scala/Predef$:MODULE$	Lscala/Predef$;
/*     */     //   1303: ldc_w 297
/*     */     //   1306: invokevirtual 164	scala/Predef$:println	(Ljava/lang/Object;)V
/*     */     //   1309: aload 26
/*     */     //   1311: athrow
/*     */     //   1312: aload 12
/*     */     //   1314: ifnull +19 -> 1333
/*     */     //   1317: aload 12
/*     */     //   1319: invokeinterface 282 1 0
/*     */     //   1324: getstatic 90	scala/Predef$:MODULE$	Lscala/Predef$;
/*     */     //   1327: ldc_w 284
/*     */     //   1330: invokevirtual 164	scala/Predef$:println	(Ljava/lang/Object;)V
/*     */     //   1333: aload 10
/*     */     //   1335: ifnull +19 -> 1354
/*     */     //   1338: aload 10
/*     */     //   1340: invokeinterface 282 1 0
/*     */     //   1345: getstatic 90	scala/Predef$:MODULE$	Lscala/Predef$;
/*     */     //   1348: ldc_w 286
/*     */     //   1351: invokevirtual 164	scala/Predef$:println	(Ljava/lang/Object;)V
/*     */     //   1354: aload 8
/*     */     //   1356: ifnull +19 -> 1375
/*     */     //   1359: aload 8
/*     */     //   1361: invokeinterface 287 1 0
/*     */     //   1366: getstatic 90	scala/Predef$:MODULE$	Lscala/Predef$;
/*     */     //   1369: ldc_w 289
/*     */     //   1372: invokevirtual 164	scala/Predef$:println	(Ljava/lang/Object;)V
/*     */     //   1375: aload 7
/*     */     //   1377: ifnull +19 -> 1396
/*     */     //   1380: aload 7
/*     */     //   1382: invokeinterface 290 1 0
/*     */     //   1387: getstatic 90	scala/Predef$:MODULE$	Lscala/Predef$;
/*     */     //   1390: ldc_w 292
/*     */     //   1393: invokevirtual 164	scala/Predef$:println	(Ljava/lang/Object;)V
/*     */     //   1396: aload 6
/*     */     //   1398: ifnull +19 -> 1417
/*     */     //   1401: aload 6
/*     */     //   1403: invokeinterface 293 1 0
/*     */     //   1408: getstatic 90	scala/Predef$:MODULE$	Lscala/Predef$;
/*     */     //   1411: ldc_w 295
/*     */     //   1414: invokevirtual 164	scala/Predef$:println	(Ljava/lang/Object;)V
/*     */     //   1417: aload 5
/*     */     //   1419: ifnull +19 -> 1438
/*     */     //   1422: aload 5
/*     */     //   1424: invokeinterface 287 1 0
/*     */     //   1429: getstatic 90	scala/Predef$:MODULE$	Lscala/Predef$;
/*     */     //   1432: ldc_w 297
/*     */     //   1435: invokevirtual 164	scala/Predef$:println	(Ljava/lang/Object;)V
/*     */     //   1438: return
/*     */     // Line number table:
/*     */     //   Java source line #30	-> byte code offset #0
/*     */     //   Java source line #31	-> byte code offset #28
/*     */     //   Java source line #32	-> byte code offset #31
/*     */     //   Java source line #33	-> byte code offset #34
/*     */     //   Java source line #35	-> byte code offset #38
/*     */     //   Java source line #36	-> byte code offset #41
/*     */     //   Java source line #37	-> byte code offset #44
/*     */     //   Java source line #40	-> byte code offset #47
/*     */     //   Java source line #41	-> byte code offset #50
/*     */     //   Java source line #42	-> byte code offset #54
/*     */     //   Java source line #44	-> byte code offset #57
/*     */     //   Java source line #45	-> byte code offset #61
/*     */     //   Java source line #48	-> byte code offset #64
/*     */     //   Java source line #50	-> byte code offset #75
/*     */     //   Java source line #51	-> byte code offset #81
/*     */     //   Java source line #53	-> byte code offset #87
/*     */     //   Java source line #54	-> byte code offset #96
/*     */     //   Java source line #55	-> byte code offset #109
/*     */     //   Java source line #57	-> byte code offset #123
/*     */     //   Java source line #58	-> byte code offset #132
/*     */     //   Java source line #59	-> byte code offset #158
/*     */     //   Java source line #60	-> byte code offset #184
/*     */     //   Java source line #61	-> byte code offset #210
/*     */     //   Java source line #62	-> byte code offset #237
/*     */     //   Java source line #64	-> byte code offset #264
/*     */     //   Java source line #66	-> byte code offset #267
/*     */     //   Java source line #68	-> byte code offset #270
/*     */     //   Java source line #70	-> byte code offset #276
/*     */     //   Java source line #72	-> byte code offset #285
/*     */     //   Java source line #78	-> byte code offset #291
/*     */     //   Java source line #81	-> byte code offset #298
/*     */     //   Java source line #82	-> byte code offset #305
/*     */     //   Java source line #84	-> byte code offset #312
/*     */     //   Java source line #86	-> byte code offset #324
/*     */     //   Java source line #88	-> byte code offset #338
/*     */     //   Java source line #90	-> byte code offset #344
/*     */     //   Java source line #118	-> byte code offset #384
/*     */     //   Java source line #120	-> byte code offset #398
/*     */     //   Java source line #122	-> byte code offset #433
/*     */     //   Java source line #124	-> byte code offset #436
/*     */     //   Java source line #125	-> byte code offset #448
/*     */     //   Java source line #126	-> byte code offset #456
/*     */     //   Java source line #127	-> byte code offset #467
/*     */     //   Java source line #129	-> byte code offset #478
/*     */     //   Java source line #130	-> byte code offset #484
/*     */     //   Java source line #131	-> byte code offset #492
/*     */     //   Java source line #132	-> byte code offset #501
/*     */     //   Java source line #135	-> byte code offset #521
/*     */     //   Java source line #138	-> byte code offset #537
/*     */     //   Java source line #140	-> byte code offset #547
/*     */     //   Java source line #141	-> byte code offset #557
/*     */     //   Java source line #143	-> byte code offset #567
/*     */     //   Java source line #144	-> byte code offset #576
/*     */     //   Java source line #145	-> byte code offset #585
/*     */     //   Java source line #148	-> byte code offset #597
/*     */     //   Java source line #150	-> byte code offset #628
/*     */     //   Java source line #152	-> byte code offset #638
/*     */     //   Java source line #154	-> byte code offset #644
/*     */     //   Java source line #155	-> byte code offset #654
/*     */     //   Java source line #156	-> byte code offset #664
/*     */     //   Java source line #157	-> byte code offset #685
/*     */     //   Java source line #160	-> byte code offset #692
/*     */     //   Java source line #162	-> byte code offset #702
/*     */     //   Java source line #160	-> byte code offset #712
/*     */     //   Java source line #150	-> byte code offset #718
/*     */     //   Java source line #143	-> byte code offset #724
/*     */     //   Java source line #172	-> byte code offset #731
/*     */     //   Java source line #173	-> byte code offset #737
/*     */     //   Java source line #176	-> byte code offset #740
/*     */     //   Java source line #177	-> byte code offset #750
/*     */     //   Java source line #178	-> byte code offset #760
/*     */     //   Java source line #180	-> byte code offset #768
/*     */     //   Java source line #181	-> byte code offset #776
/*     */     //   Java source line #187	-> byte code offset #786
/*     */     //   Java source line #189	-> byte code offset #796
/*     */     //   Java source line #190	-> byte code offset #806
/*     */     //   Java source line #193	-> byte code offset #816
/*     */     //   Java source line #195	-> byte code offset #832
/*     */     //   Java source line #196	-> byte code offset #841
/*     */     //   Java source line #197	-> byte code offset #850
/*     */     //   Java source line #200	-> byte code offset #862
/*     */     //   Java source line #202	-> byte code offset #893
/*     */     //   Java source line #204	-> byte code offset #903
/*     */     //   Java source line #206	-> byte code offset #909
/*     */     //   Java source line #207	-> byte code offset #919
/*     */     //   Java source line #208	-> byte code offset #929
/*     */     //   Java source line #209	-> byte code offset #979
/*     */     //   Java source line #212	-> byte code offset #986
/*     */     //   Java source line #214	-> byte code offset #996
/*     */     //   Java source line #212	-> byte code offset #1006
/*     */     //   Java source line #202	-> byte code offset #1012
/*     */     //   Java source line #195	-> byte code offset #1018
/*     */     //   Java source line #193	-> byte code offset #1024
/*     */     //   Java source line #226	-> byte code offset #1031
/*     */     //   Java source line #227	-> byte code offset #1037
/*     */     //   Java source line #230	-> byte code offset #1040
/*     */     //   Java source line #231	-> byte code offset #1050
/*     */     //   Java source line #232	-> byte code offset #1060
/*     */     //   Java source line #234	-> byte code offset #1068
/*     */     //   Java source line #235	-> byte code offset #1076
/*     */     //   Java source line #241	-> byte code offset #1086
/*     */     //   Java source line #247	-> byte code offset #1116
/*     */     //   Java source line #75	-> byte code offset #1116
/*     */     //   Java source line #248	-> byte code offset #1118
/*     */     //   Java source line #250	-> byte code offset #1151
/*     */     //   Java source line #251	-> byte code offset #1161
/*     */     //   Java source line #252	-> byte code offset #1170
/*     */     //   Java source line #255	-> byte code offset #1181
/*     */     //   Java source line #257	-> byte code offset #1183
/*     */     //   Java source line #258	-> byte code offset #1188
/*     */     //   Java source line #260	-> byte code offset #1195
/*     */     //   Java source line #263	-> byte code offset #1204
/*     */     //   Java source line #264	-> byte code offset #1209
/*     */     //   Java source line #266	-> byte code offset #1216
/*     */     //   Java source line #269	-> byte code offset #1225
/*     */     //   Java source line #270	-> byte code offset #1230
/*     */     //   Java source line #272	-> byte code offset #1237
/*     */     //   Java source line #275	-> byte code offset #1246
/*     */     //   Java source line #276	-> byte code offset #1251
/*     */     //   Java source line #278	-> byte code offset #1258
/*     */     //   Java source line #281	-> byte code offset #1267
/*     */     //   Java source line #282	-> byte code offset #1272
/*     */     //   Java source line #284	-> byte code offset #1279
/*     */     //   Java source line #287	-> byte code offset #1288
/*     */     //   Java source line #288	-> byte code offset #1293
/*     */     //   Java source line #290	-> byte code offset #1300
/*     */     //   Java source line #257	-> byte code offset #1312
/*     */     //   Java source line #258	-> byte code offset #1317
/*     */     //   Java source line #260	-> byte code offset #1324
/*     */     //   Java source line #263	-> byte code offset #1333
/*     */     //   Java source line #264	-> byte code offset #1338
/*     */     //   Java source line #266	-> byte code offset #1345
/*     */     //   Java source line #269	-> byte code offset #1354
/*     */     //   Java source line #270	-> byte code offset #1359
/*     */     //   Java source line #272	-> byte code offset #1366
/*     */     //   Java source line #275	-> byte code offset #1375
/*     */     //   Java source line #276	-> byte code offset #1380
/*     */     //   Java source line #278	-> byte code offset #1387
/*     */     //   Java source line #281	-> byte code offset #1396
/*     */     //   Java source line #282	-> byte code offset #1401
/*     */     //   Java source line #284	-> byte code offset #1408
/*     */     //   Java source line #287	-> byte code offset #1417
/*     */     //   Java source line #288	-> byte code offset #1422
/*     */     //   Java source line #290	-> byte code offset #1429
/*     */     //   Java source line #27	-> byte code offset #1438
/*     */     // Local variable table:
/*     */     //   start	length	slot	name	signature
/*     */     //   0	1439	0	this	SparkEngineV2ForMultiPointPresto
/*     */     //   27	458	1	PrestoURL	String
/*     */     //   30	456	2	PrestoUser	String
/*     */     //   33	2	3	PrestoPwd	String
/*     */     //   36	443	4	PrestoDriver	String
/*     */     //   39	1384	5	connP	java.sql.Connection
/*     */     //   42	1360	6	stmtP	java.sql.Statement
/*     */     //   45	1336	7	rsP	java.sql.ResultSet
/*     */     //   48	1312	8	conn	java.sql.Connection
/*     */     //   52	407	9	sqlI	String
/*     */     //   55	1284	10	pstmt	java.sql.PreparedStatement
/*     */     //   59	411	11	sql2	String
/*     */     //   62	1256	12	pstmt2	java.sql.PreparedStatement
/*     */     //   73	1030	13	line_arr	String[]
/*     */     //   79	1076	14	jobId	String
/*     */     //   85	27	15	params	String
/*     */     //   94	16	16	gson	com.google.gson.Gson
/*     */     //   107	7	17	mapType	java.lang.reflect.Type
/*     */     //   121	240	18	map	InputBean[]
/*     */     //   130	233	19	map5	HashMap
/*     */     //   265	3	20	inputBeanRepair	InputBean
/*     */     //   268	3	21	resultData	scala.runtime.Null.
/*     */     //   274	622	22	count	IntRef
/*     */     //   283	534	23	map16	ObjectRef
/*     */     //   289	651	24	map31	HashMap
/*     */     //   1116	19	25	localException	Exception
/*     */     //   1181	129	26	localObject	Object
/*     */     //   303	221	27	isType	ObjectRef
/*     */     //   310	651	28	isTypeShow	ObjectRef
/*     */     //   322	182	29	sql	ObjectRef
/*     */     //   342	33	30	i	IntRef
/*     */     //   434	620	31	number	int
/*     */     //   555	93	32	solrid	String
/*     */     //   565	105	33	types	String
/*     */     //   626	3	34	lenTem	int
/*     */     //   804	109	35	solrid	String
/*     */     //   814	128	36	types	String
/*     */     //   891	3	37	lenTem	int
/*     */     // Exception table:
/*     */     //   from	to	target	type
/*     */     //   291	1116	1116	java/lang/Exception
/*     */     //   291	1181	1181	finally
/*     */   }
/*     */   
/*     */   /* Error */
/*     */   public String gsonArrayFunc(InputBean inputBean, String tableName, HashMap<Object, Object> map5)
/*     */   {
/*     */     // Byte code:
/*     */     //   0: getstatic 355	com/yisa/engine/uitl/TimeUtil$:MODULE$	Lcom/yisa/engine/uitl/TimeUtil$;
/*     */     //   3: aload_1
/*     */     //   4: invokevirtual 360	com/yisa/engine/common/InputBean:startTime	()Ljava/lang/String;
/*     */     //   7: invokevirtual 364	com/yisa/engine/uitl/TimeUtil$:getTimeStringFormat	(Ljava/lang/String;)Ljava/lang/String;
/*     */     //   10: astore 4
/*     */     //   12: getstatic 355	com/yisa/engine/uitl/TimeUtil$:MODULE$	Lcom/yisa/engine/uitl/TimeUtil$;
/*     */     //   15: aload_1
/*     */     //   16: invokevirtual 367	com/yisa/engine/common/InputBean:endTime	()Ljava/lang/String;
/*     */     //   19: invokevirtual 364	com/yisa/engine/uitl/TimeUtil$:getTimeStringFormat	(Ljava/lang/String;)Ljava/lang/String;
/*     */     //   22: astore 5
/*     */     //   24: aload_1
/*     */     //   25: invokevirtual 371	com/yisa/engine/common/InputBean:locationId	()[Ljava/lang/String;
/*     */     //   28: astore 6
/*     */     //   30: aload_1
/*     */     //   31: invokevirtual 374	com/yisa/engine/common/InputBean:carModel	()[Ljava/lang/String;
/*     */     //   34: astore 7
/*     */     //   36: aload_1
/*     */     //   37: invokevirtual 377	com/yisa/engine/common/InputBean:carBrand	()Ljava/lang/String;
/*     */     //   40: astore 8
/*     */     //   42: aload_1
/*     */     //   43: invokevirtual 380	com/yisa/engine/common/InputBean:carYear	()[Ljava/lang/String;
/*     */     //   46: astore 9
/*     */     //   48: aload_1
/*     */     //   49: invokevirtual 383	com/yisa/engine/common/InputBean:carColor	()Ljava/lang/String;
/*     */     //   52: astore 10
/*     */     //   54: aload_1
/*     */     //   55: invokevirtual 386	com/yisa/engine/common/InputBean:plateNumber	()Ljava/lang/String;
/*     */     //   58: astore 11
/*     */     //   60: aload_1
/*     */     //   61: invokevirtual 389	com/yisa/engine/common/InputBean:differ	()I
/*     */     //   64: istore 12
/*     */     //   66: aload_1
/*     */     //   67: invokevirtual 392	com/yisa/engine/common/InputBean:direction	()Ljava/lang/String;
/*     */     //   70: astore 13
/*     */     //   72: aload_1
/*     */     //   73: invokevirtual 395	com/yisa/engine/common/InputBean:carLevel	()[Ljava/lang/String;
/*     */     //   76: astore 14
/*     */     //   78: new 397	java/text/SimpleDateFormat
/*     */     //   81: dup
/*     */     //   82: ldc_w 399
/*     */     //   85: invokespecial 402	java/text/SimpleDateFormat:<init>	(Ljava/lang/String;)V
/*     */     //   88: astore 15
/*     */     //   90: aload 15
/*     */     //   92: aload_1
/*     */     //   93: invokevirtual 360	com/yisa/engine/common/InputBean:startTime	()Ljava/lang/String;
/*     */     //   96: invokevirtual 406	java/text/SimpleDateFormat:parse	(Ljava/lang/String;)Ljava/util/Date;
/*     */     //   99: invokevirtual 412	java/util/Date:getTime	()J
/*     */     //   102: ldc2_w 413
/*     */     //   105: ldiv
/*     */     //   106: lstore 16
/*     */     //   108: aload 15
/*     */     //   110: aload_1
/*     */     //   111: invokevirtual 367	com/yisa/engine/common/InputBean:endTime	()Ljava/lang/String;
/*     */     //   114: invokevirtual 406	java/text/SimpleDateFormat:parse	(Ljava/lang/String;)Ljava/util/Date;
/*     */     //   117: invokevirtual 412	java/util/Date:getTime	()J
/*     */     //   120: ldc2_w 413
/*     */     //   123: ldiv
/*     */     //   124: lstore 18
/*     */     //   126: new 128	java/lang/StringBuffer
/*     */     //   129: dup
/*     */     //   130: invokespecial 129	java/lang/StringBuffer:<init>	()V
/*     */     //   133: astore 20
/*     */     //   135: aload 20
/*     */     //   137: ldc_w 416
/*     */     //   140: invokevirtual 138	java/lang/StringBuffer:append	(Ljava/lang/String;)Ljava/lang/StringBuffer;
/*     */     //   143: pop
/*     */     //   144: aload 20
/*     */     //   146: aload_3
/*     */     //   147: iload 12
/*     */     //   149: invokestatic 96	scala/runtime/BoxesRunTime:boxToInteger	(I)Ljava/lang/Integer;
/*     */     //   152: invokevirtual 228	scala/collection/mutable/HashMap:get	(Ljava/lang/Object;)Lscala/Option;
/*     */     //   155: invokevirtual 246	scala/Option:get	()Ljava/lang/Object;
/*     */     //   158: invokestatic 420	scala/runtime/BoxesRunTime:unboxToInt	(Ljava/lang/Object;)I
/*     */     //   161: invokevirtual 423	java/lang/StringBuffer:append	(I)Ljava/lang/StringBuffer;
/*     */     //   164: ldc_w 425
/*     */     //   167: invokevirtual 138	java/lang/StringBuffer:append	(Ljava/lang/String;)Ljava/lang/StringBuffer;
/*     */     //   170: aload_2
/*     */     //   171: invokevirtual 138	java/lang/StringBuffer:append	(Ljava/lang/String;)Ljava/lang/StringBuffer;
/*     */     //   174: pop
/*     */     //   175: aload 4
/*     */     //   177: ifnonnull +9 -> 186
/*     */     //   180: getstatic 259	scala/runtime/BoxedUnit:UNIT	Lscala/runtime/BoxedUnit;
/*     */     //   183: goto +20 -> 203
/*     */     //   186: aload 20
/*     */     //   188: ldc_w 427
/*     */     //   191: invokevirtual 138	java/lang/StringBuffer:append	(Ljava/lang/String;)Ljava/lang/StringBuffer;
/*     */     //   194: aload_0
/*     */     //   195: aload 4
/*     */     //   197: invokevirtual 430	com/yisa/engine/branch/SparkEngineV2ForMultiPointPresto:getDateid	(Ljava/lang/String;)Ljava/lang/String;
/*     */     //   200: invokevirtual 138	java/lang/StringBuffer:append	(Ljava/lang/String;)Ljava/lang/StringBuffer;
/*     */     //   203: pop
/*     */     //   204: aload 5
/*     */     //   206: ifnonnull +9 -> 215
/*     */     //   209: getstatic 259	scala/runtime/BoxedUnit:UNIT	Lscala/runtime/BoxedUnit;
/*     */     //   212: goto +20 -> 232
/*     */     //   215: aload 20
/*     */     //   217: ldc_w 432
/*     */     //   220: invokevirtual 138	java/lang/StringBuffer:append	(Ljava/lang/String;)Ljava/lang/StringBuffer;
/*     */     //   223: aload_0
/*     */     //   224: aload 5
/*     */     //   226: invokevirtual 430	com/yisa/engine/branch/SparkEngineV2ForMultiPointPresto:getDateid	(Ljava/lang/String;)Ljava/lang/String;
/*     */     //   229: invokevirtual 138	java/lang/StringBuffer:append	(Ljava/lang/String;)Ljava/lang/StringBuffer;
/*     */     //   232: pop
/*     */     //   233: lload 16
/*     */     //   235: lconst_0
/*     */     //   236: lcmp
/*     */     //   237: ifeq +19 -> 256
/*     */     //   240: aload 20
/*     */     //   242: ldc_w 434
/*     */     //   245: invokevirtual 138	java/lang/StringBuffer:append	(Ljava/lang/String;)Ljava/lang/StringBuffer;
/*     */     //   248: lload 16
/*     */     //   250: invokevirtual 437	java/lang/StringBuffer:append	(J)Ljava/lang/StringBuffer;
/*     */     //   253: goto +6 -> 259
/*     */     //   256: getstatic 259	scala/runtime/BoxedUnit:UNIT	Lscala/runtime/BoxedUnit;
/*     */     //   259: pop
/*     */     //   260: lload 18
/*     */     //   262: lconst_0
/*     */     //   263: lcmp
/*     */     //   264: ifeq +19 -> 283
/*     */     //   267: aload 20
/*     */     //   269: ldc_w 439
/*     */     //   272: invokevirtual 138	java/lang/StringBuffer:append	(Ljava/lang/String;)Ljava/lang/StringBuffer;
/*     */     //   275: lload 18
/*     */     //   277: invokevirtual 437	java/lang/StringBuffer:append	(J)Ljava/lang/StringBuffer;
/*     */     //   280: goto +6 -> 286
/*     */     //   283: getstatic 259	scala/runtime/BoxedUnit:UNIT	Lscala/runtime/BoxedUnit;
/*     */     //   286: pop
/*     */     //   287: aload 6
/*     */     //   289: aconst_null
/*     */     //   290: if_acmpeq +97 -> 387
/*     */     //   293: aload 6
/*     */     //   295: arraylength
/*     */     //   296: iconst_0
/*     */     //   297: if_icmple +90 -> 387
/*     */     //   300: getstatic 90	scala/Predef$:MODULE$	Lscala/Predef$;
/*     */     //   303: getstatic 90	scala/Predef$:MODULE$	Lscala/Predef$;
/*     */     //   306: aload 6
/*     */     //   308: checkcast 140	[Ljava/lang/Object;
/*     */     //   311: invokevirtual 144	scala/Predef$:refArrayOps	([Ljava/lang/Object;)Lscala/collection/mutable/ArrayOps;
/*     */     //   314: new 441	com/yisa/engine/branch/SparkEngineV2ForMultiPointPresto$$anonfun$1
/*     */     //   317: dup
/*     */     //   318: aload_0
/*     */     //   319: invokespecial 442	com/yisa/engine/branch/SparkEngineV2ForMultiPointPresto$$anonfun$1:<init>	(Lcom/yisa/engine/branch/SparkEngineV2ForMultiPointPresto;)V
/*     */     //   322: getstatic 447	scala/Array$:MODULE$	Lscala/Array$;
/*     */     //   325: getstatic 452	scala/reflect/ClassTag$:MODULE$	Lscala/reflect/ClassTag$;
/*     */     //   328: ldc 54
/*     */     //   330: invokevirtual 456	scala/reflect/ClassTag$:apply	(Ljava/lang/Class;)Lscala/reflect/ClassTag;
/*     */     //   333: invokevirtual 460	scala/Array$:canBuildFrom	(Lscala/reflect/ClassTag;)Lscala/collection/generic/CanBuildFrom;
/*     */     //   336: invokeinterface 463 3 0
/*     */     //   341: checkcast 140	[Ljava/lang/Object;
/*     */     //   344: invokevirtual 144	scala/Predef$:refArrayOps	([Ljava/lang/Object;)Lscala/collection/mutable/ArrayOps;
/*     */     //   347: new 465	com/yisa/engine/branch/SparkEngineV2ForMultiPointPresto$$anonfun$2
/*     */     //   350: dup
/*     */     //   351: aload_0
/*     */     //   352: invokespecial 466	com/yisa/engine/branch/SparkEngineV2ForMultiPointPresto$$anonfun$2:<init>	(Lcom/yisa/engine/branch/SparkEngineV2ForMultiPointPresto;)V
/*     */     //   355: invokeinterface 470 2 0
/*     */     //   360: checkcast 54	java/lang/String
/*     */     //   363: astore 21
/*     */     //   365: aload 20
/*     */     //   367: ldc_w 472
/*     */     //   370: invokevirtual 138	java/lang/StringBuffer:append	(Ljava/lang/String;)Ljava/lang/StringBuffer;
/*     */     //   373: aload 21
/*     */     //   375: invokevirtual 138	java/lang/StringBuffer:append	(Ljava/lang/String;)Ljava/lang/StringBuffer;
/*     */     //   378: ldc_w 474
/*     */     //   381: invokevirtual 138	java/lang/StringBuffer:append	(Ljava/lang/String;)Ljava/lang/StringBuffer;
/*     */     //   384: goto +6 -> 390
/*     */     //   387: getstatic 259	scala/runtime/BoxedUnit:UNIT	Lscala/runtime/BoxedUnit;
/*     */     //   390: pop
/*     */     //   391: aload 14
/*     */     //   393: aconst_null
/*     */     //   394: if_acmpeq +61 -> 455
/*     */     //   397: aload 14
/*     */     //   399: arraylength
/*     */     //   400: iconst_0
/*     */     //   401: if_icmple +54 -> 455
/*     */     //   404: getstatic 90	scala/Predef$:MODULE$	Lscala/Predef$;
/*     */     //   407: aload 14
/*     */     //   409: checkcast 140	[Ljava/lang/Object;
/*     */     //   412: invokevirtual 144	scala/Predef$:refArrayOps	([Ljava/lang/Object;)Lscala/collection/mutable/ArrayOps;
/*     */     //   415: new 476	com/yisa/engine/branch/SparkEngineV2ForMultiPointPresto$$anonfun$3
/*     */     //   418: dup
/*     */     //   419: aload_0
/*     */     //   420: invokespecial 477	com/yisa/engine/branch/SparkEngineV2ForMultiPointPresto$$anonfun$3:<init>	(Lcom/yisa/engine/branch/SparkEngineV2ForMultiPointPresto;)V
/*     */     //   423: invokeinterface 470 2 0
/*     */     //   428: checkcast 54	java/lang/String
/*     */     //   431: astore 22
/*     */     //   433: aload 20
/*     */     //   435: ldc_w 479
/*     */     //   438: invokevirtual 138	java/lang/StringBuffer:append	(Ljava/lang/String;)Ljava/lang/StringBuffer;
/*     */     //   441: aload 22
/*     */     //   443: invokevirtual 138	java/lang/StringBuffer:append	(Ljava/lang/String;)Ljava/lang/StringBuffer;
/*     */     //   446: ldc_w 474
/*     */     //   449: invokevirtual 138	java/lang/StringBuffer:append	(Ljava/lang/String;)Ljava/lang/StringBuffer;
/*     */     //   452: goto +6 -> 458
/*     */     //   455: getstatic 259	scala/runtime/BoxedUnit:UNIT	Lscala/runtime/BoxedUnit;
/*     */     //   458: pop
/*     */     //   459: aload 9
/*     */     //   461: aconst_null
/*     */     //   462: if_acmpeq +61 -> 523
/*     */     //   465: aload 9
/*     */     //   467: arraylength
/*     */     //   468: iconst_0
/*     */     //   469: if_icmple +54 -> 523
/*     */     //   472: getstatic 90	scala/Predef$:MODULE$	Lscala/Predef$;
/*     */     //   475: aload 9
/*     */     //   477: checkcast 140	[Ljava/lang/Object;
/*     */     //   480: invokevirtual 144	scala/Predef$:refArrayOps	([Ljava/lang/Object;)Lscala/collection/mutable/ArrayOps;
/*     */     //   483: new 481	com/yisa/engine/branch/SparkEngineV2ForMultiPointPresto$$anonfun$4
/*     */     //   486: dup
/*     */     //   487: aload_0
/*     */     //   488: invokespecial 482	com/yisa/engine/branch/SparkEngineV2ForMultiPointPresto$$anonfun$4:<init>	(Lcom/yisa/engine/branch/SparkEngineV2ForMultiPointPresto;)V
/*     */     //   491: invokeinterface 470 2 0
/*     */     //   496: checkcast 54	java/lang/String
/*     */     //   499: astore 23
/*     */     //   501: aload 20
/*     */     //   503: ldc_w 484
/*     */     //   506: invokevirtual 138	java/lang/StringBuffer:append	(Ljava/lang/String;)Ljava/lang/StringBuffer;
/*     */     //   509: aload 23
/*     */     //   511: invokevirtual 138	java/lang/StringBuffer:append	(Ljava/lang/String;)Ljava/lang/StringBuffer;
/*     */     //   514: ldc_w 474
/*     */     //   517: invokevirtual 138	java/lang/StringBuffer:append	(Ljava/lang/String;)Ljava/lang/StringBuffer;
/*     */     //   520: goto +6 -> 526
/*     */     //   523: getstatic 259	scala/runtime/BoxedUnit:UNIT	Lscala/runtime/BoxedUnit;
/*     */     //   526: pop
/*     */     //   527: aload 7
/*     */     //   529: aconst_null
/*     */     //   530: if_acmpeq +61 -> 591
/*     */     //   533: aload 7
/*     */     //   535: arraylength
/*     */     //   536: iconst_0
/*     */     //   537: if_icmple +54 -> 591
/*     */     //   540: getstatic 90	scala/Predef$:MODULE$	Lscala/Predef$;
/*     */     //   543: aload 7
/*     */     //   545: checkcast 140	[Ljava/lang/Object;
/*     */     //   548: invokevirtual 144	scala/Predef$:refArrayOps	([Ljava/lang/Object;)Lscala/collection/mutable/ArrayOps;
/*     */     //   551: new 486	com/yisa/engine/branch/SparkEngineV2ForMultiPointPresto$$anonfun$5
/*     */     //   554: dup
/*     */     //   555: aload_0
/*     */     //   556: invokespecial 487	com/yisa/engine/branch/SparkEngineV2ForMultiPointPresto$$anonfun$5:<init>	(Lcom/yisa/engine/branch/SparkEngineV2ForMultiPointPresto;)V
/*     */     //   559: invokeinterface 470 2 0
/*     */     //   564: checkcast 54	java/lang/String
/*     */     //   567: astore 24
/*     */     //   569: aload 20
/*     */     //   571: ldc_w 489
/*     */     //   574: invokevirtual 138	java/lang/StringBuffer:append	(Ljava/lang/String;)Ljava/lang/StringBuffer;
/*     */     //   577: aload 24
/*     */     //   579: invokevirtual 138	java/lang/StringBuffer:append	(Ljava/lang/String;)Ljava/lang/StringBuffer;
/*     */     //   582: ldc_w 474
/*     */     //   585: invokevirtual 138	java/lang/StringBuffer:append	(Ljava/lang/String;)Ljava/lang/StringBuffer;
/*     */     //   588: goto +6 -> 594
/*     */     //   591: getstatic 259	scala/runtime/BoxedUnit:UNIT	Lscala/runtime/BoxedUnit;
/*     */     //   594: pop
/*     */     //   595: aload 13
/*     */     //   597: ifnull +30 -> 627
/*     */     //   600: aload 13
/*     */     //   602: ldc 42
/*     */     //   604: astore 25
/*     */     //   606: dup
/*     */     //   607: ifnonnull +12 -> 619
/*     */     //   610: pop
/*     */     //   611: aload 25
/*     */     //   613: ifnull +14 -> 627
/*     */     //   616: goto +17 -> 633
/*     */     //   619: aload 25
/*     */     //   621: invokevirtual 490	java/lang/Object:equals	(Ljava/lang/Object;)Z
/*     */     //   624: ifeq +9 -> 633
/*     */     //   627: getstatic 259	scala/runtime/BoxedUnit:UNIT	Lscala/runtime/BoxedUnit;
/*     */     //   630: goto +22 -> 652
/*     */     //   633: aload 20
/*     */     //   635: ldc_w 492
/*     */     //   638: invokevirtual 138	java/lang/StringBuffer:append	(Ljava/lang/String;)Ljava/lang/StringBuffer;
/*     */     //   641: aload 13
/*     */     //   643: invokevirtual 138	java/lang/StringBuffer:append	(Ljava/lang/String;)Ljava/lang/StringBuffer;
/*     */     //   646: ldc_w 494
/*     */     //   649: invokevirtual 138	java/lang/StringBuffer:append	(Ljava/lang/String;)Ljava/lang/StringBuffer;
/*     */     //   652: pop
/*     */     //   653: aload 8
/*     */     //   655: ifnull +30 -> 685
/*     */     //   658: aload 8
/*     */     //   660: ldc 42
/*     */     //   662: astore 26
/*     */     //   664: dup
/*     */     //   665: ifnonnull +12 -> 677
/*     */     //   668: pop
/*     */     //   669: aload 26
/*     */     //   671: ifnull +14 -> 685
/*     */     //   674: goto +17 -> 691
/*     */     //   677: aload 26
/*     */     //   679: invokevirtual 490	java/lang/Object:equals	(Ljava/lang/Object;)Z
/*     */     //   682: ifeq +9 -> 691
/*     */     //   685: getstatic 259	scala/runtime/BoxedUnit:UNIT	Lscala/runtime/BoxedUnit;
/*     */     //   688: goto +16 -> 704
/*     */     //   691: aload 20
/*     */     //   693: ldc_w 496
/*     */     //   696: invokevirtual 138	java/lang/StringBuffer:append	(Ljava/lang/String;)Ljava/lang/StringBuffer;
/*     */     //   699: aload 8
/*     */     //   701: invokevirtual 138	java/lang/StringBuffer:append	(Ljava/lang/String;)Ljava/lang/StringBuffer;
/*     */     //   704: pop
/*     */     //   705: aload 10
/*     */     //   707: ifnull +30 -> 737
/*     */     //   710: aload 10
/*     */     //   712: ldc 42
/*     */     //   714: astore 27
/*     */     //   716: dup
/*     */     //   717: ifnonnull +12 -> 729
/*     */     //   720: pop
/*     */     //   721: aload 27
/*     */     //   723: ifnull +14 -> 737
/*     */     //   726: goto +17 -> 743
/*     */     //   729: aload 27
/*     */     //   731: invokevirtual 490	java/lang/Object:equals	(Ljava/lang/Object;)Z
/*     */     //   734: ifeq +9 -> 743
/*     */     //   737: getstatic 259	scala/runtime/BoxedUnit:UNIT	Lscala/runtime/BoxedUnit;
/*     */     //   740: goto +16 -> 756
/*     */     //   743: aload 20
/*     */     //   745: ldc_w 498
/*     */     //   748: invokevirtual 138	java/lang/StringBuffer:append	(Ljava/lang/String;)Ljava/lang/StringBuffer;
/*     */     //   751: aload 10
/*     */     //   753: invokevirtual 138	java/lang/StringBuffer:append	(Ljava/lang/String;)Ljava/lang/StringBuffer;
/*     */     //   756: pop
/*     */     //   757: aload 11
/*     */     //   759: ifnull +30 -> 789
/*     */     //   762: aload 11
/*     */     //   764: ldc 42
/*     */     //   766: astore 28
/*     */     //   768: dup
/*     */     //   769: ifnonnull +12 -> 781
/*     */     //   772: pop
/*     */     //   773: aload 28
/*     */     //   775: ifnull +14 -> 789
/*     */     //   778: goto +17 -> 795
/*     */     //   781: aload 28
/*     */     //   783: invokevirtual 490	java/lang/Object:equals	(Ljava/lang/Object;)Z
/*     */     //   786: ifeq +9 -> 795
/*     */     //   789: getstatic 259	scala/runtime/BoxedUnit:UNIT	Lscala/runtime/BoxedUnit;
/*     */     //   792: goto +84 -> 876
/*     */     //   795: aload 11
/*     */     //   797: ldc_w 500
/*     */     //   800: invokevirtual 503	java/lang/String:contains	(Ljava/lang/CharSequence;)Z
/*     */     //   803: ifne +14 -> 817
/*     */     //   806: aload 11
/*     */     //   808: ldc_w 505
/*     */     //   811: invokevirtual 503	java/lang/String:contains	(Ljava/lang/CharSequence;)Z
/*     */     //   814: ifeq +43 -> 857
/*     */     //   817: aload 20
/*     */     //   819: ldc_w 507
/*     */     //   822: invokevirtual 138	java/lang/StringBuffer:append	(Ljava/lang/String;)Ljava/lang/StringBuffer;
/*     */     //   825: aload 11
/*     */     //   827: ldc_w 500
/*     */     //   830: ldc_w 509
/*     */     //   833: invokevirtual 513	java/lang/String:replace	(Ljava/lang/CharSequence;Ljava/lang/CharSequence;)Ljava/lang/String;
/*     */     //   836: ldc_w 505
/*     */     //   839: ldc_w 515
/*     */     //   842: invokevirtual 513	java/lang/String:replace	(Ljava/lang/CharSequence;Ljava/lang/CharSequence;)Ljava/lang/String;
/*     */     //   845: invokevirtual 138	java/lang/StringBuffer:append	(Ljava/lang/String;)Ljava/lang/StringBuffer;
/*     */     //   848: ldc_w 517
/*     */     //   851: invokevirtual 138	java/lang/StringBuffer:append	(Ljava/lang/String;)Ljava/lang/StringBuffer;
/*     */     //   854: goto +22 -> 876
/*     */     //   857: aload 20
/*     */     //   859: ldc_w 519
/*     */     //   862: invokevirtual 138	java/lang/StringBuffer:append	(Ljava/lang/String;)Ljava/lang/StringBuffer;
/*     */     //   865: aload 11
/*     */     //   867: invokevirtual 138	java/lang/StringBuffer:append	(Ljava/lang/String;)Ljava/lang/StringBuffer;
/*     */     //   870: ldc_w 494
/*     */     //   873: invokevirtual 138	java/lang/StringBuffer:append	(Ljava/lang/String;)Ljava/lang/StringBuffer;
/*     */     //   876: pop
/*     */     //   877: aload 20
/*     */     //   879: ldc_w 521
/*     */     //   882: invokevirtual 138	java/lang/StringBuffer:append	(Ljava/lang/String;)Ljava/lang/StringBuffer;
/*     */     //   885: pop
/*     */     //   886: getstatic 90	scala/Predef$:MODULE$	Lscala/Predef$;
/*     */     //   889: new 21	scala/collection/mutable/StringBuilder
/*     */     //   892: dup
/*     */     //   893: invokespecial 24	scala/collection/mutable/StringBuilder:<init>	()V
/*     */     //   896: ldc_w 523
/*     */     //   899: invokevirtual 30	scala/collection/mutable/StringBuilder:append	(Ljava/lang/Object;)Lscala/collection/mutable/StringBuilder;
/*     */     //   902: aload 20
/*     */     //   904: invokevirtual 160	java/lang/StringBuffer:toString	()Ljava/lang/String;
/*     */     //   907: invokevirtual 30	scala/collection/mutable/StringBuilder:append	(Ljava/lang/Object;)Lscala/collection/mutable/StringBuilder;
/*     */     //   910: invokevirtual 38	scala/collection/mutable/StringBuilder:toString	()Ljava/lang/String;
/*     */     //   913: invokevirtual 164	scala/Predef$:println	(Ljava/lang/Object;)V
/*     */     //   916: aload 20
/*     */     //   918: invokevirtual 160	java/lang/StringBuffer:toString	()Ljava/lang/String;
/*     */     //   921: areturn
/*     */     // Line number table:
/*     */     //   Java source line #297	-> byte code offset #0
/*     */     //   Java source line #298	-> byte code offset #12
/*     */     //   Java source line #299	-> byte code offset #24
/*     */     //   Java source line #300	-> byte code offset #30
/*     */     //   Java source line #301	-> byte code offset #36
/*     */     //   Java source line #302	-> byte code offset #42
/*     */     //   Java source line #303	-> byte code offset #48
/*     */     //   Java source line #304	-> byte code offset #54
/*     */     //   Java source line #305	-> byte code offset #60
/*     */     //   Java source line #306	-> byte code offset #66
/*     */     //   Java source line #307	-> byte code offset #72
/*     */     //   Java source line #309	-> byte code offset #78
/*     */     //   Java source line #311	-> byte code offset #90
/*     */     //   Java source line #312	-> byte code offset #108
/*     */     //   Java source line #314	-> byte code offset #126
/*     */     //   Java source line #316	-> byte code offset #135
/*     */     //   Java source line #318	-> byte code offset #144
/*     */     //   Java source line #320	-> byte code offset #175
/*     */     //   Java source line #321	-> byte code offset #186
/*     */     //   Java source line #320	-> byte code offset #203
/*     */     //   Java source line #324	-> byte code offset #204
/*     */     //   Java source line #325	-> byte code offset #215
/*     */     //   Java source line #324	-> byte code offset #232
/*     */     //   Java source line #328	-> byte code offset #233
/*     */     //   Java source line #329	-> byte code offset #240
/*     */     //   Java source line #328	-> byte code offset #256
/*     */     //   Java source line #332	-> byte code offset #260
/*     */     //   Java source line #333	-> byte code offset #267
/*     */     //   Java source line #332	-> byte code offset #283
/*     */     //   Java source line #336	-> byte code offset #287
/*     */     //   Java source line #337	-> byte code offset #300
/*     */     //   Java source line #338	-> byte code offset #365
/*     */     //   Java source line #336	-> byte code offset #387
/*     */     //   Java source line #341	-> byte code offset #391
/*     */     //   Java source line #342	-> byte code offset #404
/*     */     //   Java source line #343	-> byte code offset #433
/*     */     //   Java source line #341	-> byte code offset #455
/*     */     //   Java source line #346	-> byte code offset #459
/*     */     //   Java source line #347	-> byte code offset #472
/*     */     //   Java source line #348	-> byte code offset #501
/*     */     //   Java source line #346	-> byte code offset #523
/*     */     //   Java source line #351	-> byte code offset #527
/*     */     //   Java source line #352	-> byte code offset #540
/*     */     //   Java source line #353	-> byte code offset #569
/*     */     //   Java source line #351	-> byte code offset #591
/*     */     //   Java source line #356	-> byte code offset #595
/*     */     //   Java source line #357	-> byte code offset #633
/*     */     //   Java source line #356	-> byte code offset #652
/*     */     //   Java source line #360	-> byte code offset #653
/*     */     //   Java source line #361	-> byte code offset #691
/*     */     //   Java source line #360	-> byte code offset #704
/*     */     //   Java source line #364	-> byte code offset #705
/*     */     //   Java source line #365	-> byte code offset #743
/*     */     //   Java source line #364	-> byte code offset #756
/*     */     //   Java source line #368	-> byte code offset #757
/*     */     //   Java source line #369	-> byte code offset #795
/*     */     //   Java source line #370	-> byte code offset #817
/*     */     //   Java source line #372	-> byte code offset #857
/*     */     //   Java source line #368	-> byte code offset #876
/*     */     //   Java source line #376	-> byte code offset #877
/*     */     //   Java source line #378	-> byte code offset #886
/*     */     //   Java source line #380	-> byte code offset #916
/*     */     // Local variable table:
/*     */     //   start	length	slot	name	signature
/*     */     //   0	922	0	this	SparkEngineV2ForMultiPointPresto
/*     */     //   0	922	1	inputBean	InputBean
/*     */     //   0	922	2	tableName	String
/*     */     //   0	922	3	map5	HashMap
/*     */     //   12	909	4	startTime1	String
/*     */     //   24	897	5	endTime1	String
/*     */     //   30	891	6	locationId	String[]
/*     */     //   36	885	7	carModel	String[]
/*     */     //   42	879	8	carBrand	String
/*     */     //   48	873	9	carYear	String[]
/*     */     //   54	867	10	carColor	String
/*     */     //   60	861	11	plateNumber	String
/*     */     //   66	855	12	differ	int
/*     */     //   72	849	13	direction	String
/*     */     //   78	843	14	carLevel	String[]
/*     */     //   90	831	15	format2	java.text.SimpleDateFormat
/*     */     //   108	813	16	startTime2	long
/*     */     //   126	795	18	endTime2	long
/*     */     //   135	786	20	sb	StringBuffer
/*     */     //   365	19	21	l	String
/*     */     //   433	19	22	m	String
/*     */     //   501	19	23	m	String
/*     */     //   569	19	24	m	String
/*     */   }
/*     */   
/*     */   public HashMap<String, String> get16()
/*     */   {
/* 386 */     HashMap map16 = new HashMap();
/* 387 */     map16.$plus$eq(Predef.ArrowAssoc..MODULE$.$minus$greater$extension(Predef..MODULE$.ArrowAssoc("1"), "1"));
/* 388 */     map16.$plus$eq(Predef.ArrowAssoc..MODULE$.$minus$greater$extension(Predef..MODULE$.ArrowAssoc("2"), "2"));
/* 389 */     map16.$plus$eq(Predef.ArrowAssoc..MODULE$.$minus$greater$extension(Predef..MODULE$.ArrowAssoc("3"), "1,2"));
/* 390 */     map16.$plus$eq(Predef.ArrowAssoc..MODULE$.$minus$greater$extension(Predef..MODULE$.ArrowAssoc("4"), "4"));
/* 391 */     map16.$plus$eq(Predef.ArrowAssoc..MODULE$.$minus$greater$extension(Predef..MODULE$.ArrowAssoc("5"), "1,4"));
/* 392 */     map16.$plus$eq(Predef.ArrowAssoc..MODULE$.$minus$greater$extension(Predef..MODULE$.ArrowAssoc("6"), "2,4"));
/* 393 */     map16.$plus$eq(Predef.ArrowAssoc..MODULE$.$minus$greater$extension(Predef..MODULE$.ArrowAssoc("7"), "1,2,4"));
/* 394 */     map16.$plus$eq(Predef.ArrowAssoc..MODULE$.$minus$greater$extension(Predef..MODULE$.ArrowAssoc("8"), "8"));
/* 395 */     map16.$plus$eq(Predef.ArrowAssoc..MODULE$.$minus$greater$extension(Predef..MODULE$.ArrowAssoc("9"), "1,8"));
/* 396 */     map16.$plus$eq(Predef.ArrowAssoc..MODULE$.$minus$greater$extension(Predef..MODULE$.ArrowAssoc("10"), "2,8"));
/* 397 */     map16.$plus$eq(Predef.ArrowAssoc..MODULE$.$minus$greater$extension(Predef..MODULE$.ArrowAssoc("11"), "1,2,8"));
/* 398 */     map16.$plus$eq(Predef.ArrowAssoc..MODULE$.$minus$greater$extension(Predef..MODULE$.ArrowAssoc("12"), "4,8"));
/* 399 */     map16.$plus$eq(Predef.ArrowAssoc..MODULE$.$minus$greater$extension(Predef..MODULE$.ArrowAssoc("13"), "1,4,8"));
/* 400 */     map16.$plus$eq(Predef.ArrowAssoc..MODULE$.$minus$greater$extension(Predef..MODULE$.ArrowAssoc("14"), "2,4,8"));
/* 401 */     map16.$plus$eq(Predef.ArrowAssoc..MODULE$.$minus$greater$extension(Predef..MODULE$.ArrowAssoc("15"), "1,2,4,8"));
/* 402 */     map16.$plus$eq(Predef.ArrowAssoc..MODULE$.$minus$greater$extension(Predef..MODULE$.ArrowAssoc("16"), "16"));
/* 403 */     map16.$plus$eq(Predef.ArrowAssoc..MODULE$.$minus$greater$extension(Predef..MODULE$.ArrowAssoc("17"), "1,16"));
/* 404 */     map16.$plus$eq(Predef.ArrowAssoc..MODULE$.$minus$greater$extension(Predef..MODULE$.ArrowAssoc("18"), "2,16"));
/* 405 */     map16.$plus$eq(Predef.ArrowAssoc..MODULE$.$minus$greater$extension(Predef..MODULE$.ArrowAssoc("19"), "1,2,16"));
/* 406 */     map16.$plus$eq(Predef.ArrowAssoc..MODULE$.$minus$greater$extension(Predef..MODULE$.ArrowAssoc("20"), "4,16"));
/* 407 */     map16.$plus$eq(Predef.ArrowAssoc..MODULE$.$minus$greater$extension(Predef..MODULE$.ArrowAssoc("21"), "1,4,16"));
/* 408 */     map16.$plus$eq(Predef.ArrowAssoc..MODULE$.$minus$greater$extension(Predef..MODULE$.ArrowAssoc("22"), "2,4,16"));
/* 409 */     map16.$plus$eq(Predef.ArrowAssoc..MODULE$.$minus$greater$extension(Predef..MODULE$.ArrowAssoc("23"), "1,2,4,16"));
/* 410 */     map16.$plus$eq(Predef.ArrowAssoc..MODULE$.$minus$greater$extension(Predef..MODULE$.ArrowAssoc("24"), "8,16"));
/* 411 */     map16.$plus$eq(Predef.ArrowAssoc..MODULE$.$minus$greater$extension(Predef..MODULE$.ArrowAssoc("25"), "1,8,16"));
/* 412 */     map16.$plus$eq(Predef.ArrowAssoc..MODULE$.$minus$greater$extension(Predef..MODULE$.ArrowAssoc("26"), "2,8,16"));
/* 413 */     map16.$plus$eq(Predef.ArrowAssoc..MODULE$.$minus$greater$extension(Predef..MODULE$.ArrowAssoc("27"), "1,2,8,16"));
/* 414 */     map16.$plus$eq(Predef.ArrowAssoc..MODULE$.$minus$greater$extension(Predef..MODULE$.ArrowAssoc("28"), "4,8,16"));
/* 415 */     map16.$plus$eq(Predef.ArrowAssoc..MODULE$.$minus$greater$extension(Predef..MODULE$.ArrowAssoc("29"), "1,4,8,16"));
/* 416 */     map16.$plus$eq(Predef.ArrowAssoc..MODULE$.$minus$greater$extension(Predef..MODULE$.ArrowAssoc("30"), "2,4,8,16"));
/* 417 */     map16.$plus$eq(Predef.ArrowAssoc..MODULE$.$minus$greater$extension(Predef..MODULE$.ArrowAssoc("31"), "1,2,4,8,16"));
/*     */     
/* 419 */     return map16;
/*     */   }
/*     */   
/*     */ 
/*     */   public HashMap<String, String> get31()
/*     */   {
/* 425 */     HashMap map16 = new HashMap();
/* 426 */     map16.$plus$eq(Predef.ArrowAssoc..MODULE$.$minus$greater$extension(Predef..MODULE$.ArrowAssoc("1"), "1"));
/* 427 */     map16.$plus$eq(Predef.ArrowAssoc..MODULE$.$minus$greater$extension(Predef..MODULE$.ArrowAssoc("2"), "2"));
/* 428 */     map16.$plus$eq(Predef.ArrowAssoc..MODULE$.$minus$greater$extension(Predef..MODULE$.ArrowAssoc("3"), "1,2"));
/* 429 */     map16.$plus$eq(Predef.ArrowAssoc..MODULE$.$minus$greater$extension(Predef..MODULE$.ArrowAssoc("4"), "3"));
/* 430 */     map16.$plus$eq(Predef.ArrowAssoc..MODULE$.$minus$greater$extension(Predef..MODULE$.ArrowAssoc("5"), "1,3"));
/* 431 */     map16.$plus$eq(Predef.ArrowAssoc..MODULE$.$minus$greater$extension(Predef..MODULE$.ArrowAssoc("6"), "2,3"));
/* 432 */     map16.$plus$eq(Predef.ArrowAssoc..MODULE$.$minus$greater$extension(Predef..MODULE$.ArrowAssoc("7"), "1,2,3"));
/* 433 */     map16.$plus$eq(Predef.ArrowAssoc..MODULE$.$minus$greater$extension(Predef..MODULE$.ArrowAssoc("8"), "4"));
/* 434 */     map16.$plus$eq(Predef.ArrowAssoc..MODULE$.$minus$greater$extension(Predef..MODULE$.ArrowAssoc("9"), "1,4"));
/* 435 */     map16.$plus$eq(Predef.ArrowAssoc..MODULE$.$minus$greater$extension(Predef..MODULE$.ArrowAssoc("10"), "2,4"));
/* 436 */     map16.$plus$eq(Predef.ArrowAssoc..MODULE$.$minus$greater$extension(Predef..MODULE$.ArrowAssoc("11"), "1,2,4"));
/* 437 */     map16.$plus$eq(Predef.ArrowAssoc..MODULE$.$minus$greater$extension(Predef..MODULE$.ArrowAssoc("12"), "3,4"));
/* 438 */     map16.$plus$eq(Predef.ArrowAssoc..MODULE$.$minus$greater$extension(Predef..MODULE$.ArrowAssoc("13"), "1,3,4"));
/* 439 */     map16.$plus$eq(Predef.ArrowAssoc..MODULE$.$minus$greater$extension(Predef..MODULE$.ArrowAssoc("14"), "2,3,4"));
/* 440 */     map16.$plus$eq(Predef.ArrowAssoc..MODULE$.$minus$greater$extension(Predef..MODULE$.ArrowAssoc("15"), "1,2,3,4"));
/* 441 */     map16.$plus$eq(Predef.ArrowAssoc..MODULE$.$minus$greater$extension(Predef..MODULE$.ArrowAssoc("16"), "5"));
/* 442 */     map16.$plus$eq(Predef.ArrowAssoc..MODULE$.$minus$greater$extension(Predef..MODULE$.ArrowAssoc("17"), "1,5"));
/* 443 */     map16.$plus$eq(Predef.ArrowAssoc..MODULE$.$minus$greater$extension(Predef..MODULE$.ArrowAssoc("18"), "2,5"));
/* 444 */     map16.$plus$eq(Predef.ArrowAssoc..MODULE$.$minus$greater$extension(Predef..MODULE$.ArrowAssoc("19"), "1,2,5"));
/* 445 */     map16.$plus$eq(Predef.ArrowAssoc..MODULE$.$minus$greater$extension(Predef..MODULE$.ArrowAssoc("20"), "3,5"));
/* 446 */     map16.$plus$eq(Predef.ArrowAssoc..MODULE$.$minus$greater$extension(Predef..MODULE$.ArrowAssoc("21"), "1,3,5"));
/* 447 */     map16.$plus$eq(Predef.ArrowAssoc..MODULE$.$minus$greater$extension(Predef..MODULE$.ArrowAssoc("22"), "2,3,5"));
/* 448 */     map16.$plus$eq(Predef.ArrowAssoc..MODULE$.$minus$greater$extension(Predef..MODULE$.ArrowAssoc("23"), "1,2,3,5"));
/* 449 */     map16.$plus$eq(Predef.ArrowAssoc..MODULE$.$minus$greater$extension(Predef..MODULE$.ArrowAssoc("24"), "4,5"));
/* 450 */     map16.$plus$eq(Predef.ArrowAssoc..MODULE$.$minus$greater$extension(Predef..MODULE$.ArrowAssoc("25"), "1,4,5"));
/* 451 */     map16.$plus$eq(Predef.ArrowAssoc..MODULE$.$minus$greater$extension(Predef..MODULE$.ArrowAssoc("26"), "2,4,5"));
/* 452 */     map16.$plus$eq(Predef.ArrowAssoc..MODULE$.$minus$greater$extension(Predef..MODULE$.ArrowAssoc("27"), "1,2,4,5"));
/* 453 */     map16.$plus$eq(Predef.ArrowAssoc..MODULE$.$minus$greater$extension(Predef..MODULE$.ArrowAssoc("28"), "3,4,5"));
/* 454 */     map16.$plus$eq(Predef.ArrowAssoc..MODULE$.$minus$greater$extension(Predef..MODULE$.ArrowAssoc("29"), "1,3,4,5"));
/* 455 */     map16.$plus$eq(Predef.ArrowAssoc..MODULE$.$minus$greater$extension(Predef..MODULE$.ArrowAssoc("30"), "2,3,4,5"));
/* 456 */     map16.$plus$eq(Predef.ArrowAssoc..MODULE$.$minus$greater$extension(Predef..MODULE$.ArrowAssoc("31"), "1,2,3,4,5"));
/*     */     
/* 458 */     return map16;
/*     */   }
/*     */   
/*     */ 
/*     */   public String getDateid(String timeString)
/*     */   {
/* 464 */     String timeLong = timeString.replaceAll("[-\\s:]", "");
/*     */     
/* 466 */     return timeLong.substring(0, 8);
/*     */   }
/*     */   
/*     */   public SparkEngineV2ForMultiPointPresto(String line, String tableName, String zkHostport, String PrestoHostPort) {}
/*     */ }


/* Location:              E:\BaiduYunDownload\\SparkEngine\jars\YISAEngineBySpark2-4.0.6-SNAPSHOT-jar-with-dependencies.jar!\com\yisa\engine\branch\SparkEngineV2ForMultiPointPresto.class
 * Java compiler version: 6 (50.0)
 * JD-Core Version:       0.7.1
 */