/*     */ package com.yisa.engine.branch;
/*     */ 
/*     */ import com.yisa.engine.common.InputBean;
/*     */ import java.sql.Connection;
/*     */ import java.sql.PreparedStatement;
/*     */ import java.sql.ResultSet;
/*     */ import java.text.SimpleDateFormat;
/*     */ import java.util.ArrayList;
/*     */ import java.util.List;
/*     */ import scala.Predef.;
/*     */ import scala.Serializable;
/*     */ import scala.collection.mutable.StringBuilder;
/*     */ import scala.runtime.AbstractFunction2;
/*     */ import scala.runtime.NonLocalReturnControl;
/*     */ import scala.runtime.ObjectRef;
/*     */ import scala.runtime.RichInt.;
/*     */ 
/*     */ @scala.reflect.ScalaSignature(bytes="\006\001Q4A!\001\002\001\027\t\0213\013]1sW\026sw-\0338f-J2uN]*j[&d\027M\035)mCR,\007K]3ti>T!a\001\003\002\r\t\024\030M\\2i\025\t)a!\001\004f]\036Lg.\032\006\003\017!\tA!_5tC*\t\021\"A\002d_6\034\001aE\002\001\031Q\001\"!\004\n\016\0039Q!a\004\t\002\t1\fgn\032\006\002#\005!!.\031<b\023\t\031bB\001\004PE*,7\r\036\t\003\033UI!A\006\b\003\021I+hN\\1cY\026D\001\002\007\001\003\002\003\006I!G\001\005Y&tW\r\005\002\033A9\0211DH\007\0029)\tQ$A\003tG\006d\027-\003\002 9\0051\001K]3eK\032L!!\t\022\003\rM#(/\0338h\025\tyB\004\003\005%\001\t\005\t\025!\003\032\003%!\030M\0317f\035\006lW\r\003\005'\001\t\005\t\025!\003\032\003)Q8\016S8tiB|'\017\036\005\tQ\001\021\t\021)A\0053\005q\001K]3ti>Dun\035;Q_J$\b\"\002\026\001\t\003Y\023A\002\037j]&$h\bF\003-]=\002\024\007\005\002.\0015\t!\001C\003\031S\001\007\021\004C\003%S\001\007\021\004C\003'S\001\007\021\004C\003)S\001\007\021\004C\0034\001\021\005C'A\002sk:$\022!\016\t\0037YJ!a\016\017\003\tUs\027\016\036\005\006s\001!\tAO\001\017O\026$\b\013\\1uK:+XNY3s)\035)4\b\021\"E\r:CQ\001\020\035A\002u\n\021\002[3bI&sG-\032=\021\005mq\024BA \035\005\rIe\016\036\005\006\003b\002\r!P\001\007Y\026tw\r\0365\t\013\rC\004\031A\r\002\013%t7\017\036:\t\013\025C\004\031A\037\002\0039DQa\022\035A\002!\013A\001\\5tiB\031\021\nT\037\016\003)S!a\023\t\002\tU$\030\016\\\005\003\033*\023A\001T5ti\")q\n\017a\001!\006\031!/Z:\021\007%c\025\004C\003S\001\021\0051+A\004hKR\034\026\017\034\032\025\007e!F\fC\003V#\002\007a+A\003qCJ\fW\016\005\002X56\t\001L\003\002Z\t\00511m\\7n_:L!a\027-\003\023%s\007/\036;CK\006t\007\"B/R\001\004I\022!\002;bE2,\007\"B0\001\t\003\001\027AC4fiRKW.Z*rYR\031\021$\0312\t\013Us\006\031\001,\t\013us\006\031A\r\t\013\021\004A\021A3\002%\035,G\017V5nKN#\030-\0349TK\016|g\016\032\013\003M&\004\"aG4\n\005!d\"\001\002'p]\036DQA[2A\002e\tA\001^5nK\")A\016\001C\001[\006Iq-\032;ECR,\027\016\032\013\00339DQa\\6A\002e\t!\002^5nKN#(/\0338h\021\025\t\b\001\"\001s\003-9W\r\036+j[\026duN\\4\025\005\031\034\b\"B8q\001\004I\002")
/*     */ public class SparkEngineV2ForSimilarPlatePresto implements Runnable
/*     */ {
/*     */   private final String line;
/*     */   
/*     */   public void run()
/*     */   {
/*  25 */     String[] line_arr = this.line.split("\\|");
/*  26 */     String job_id = line_arr[1];
/*  27 */     String[] line2 = line_arr[2].split(",");
/*  28 */     String model = null;
/*  29 */     String bInsert = null;
/*  30 */     String testSql = null;
/*     */     
/*  32 */     com.google.gson.Gson gson = new com.google.gson.Gson();
/*  33 */     java.lang.reflect.Type mapType = new com.google.gson.reflect.TypeToken() {}.getType();
/*  34 */     InputBean map = (InputBean)gson.fromJson(line_arr[2], mapType);
/*     */     
/*  36 */     String sql2 = getSql2(map, this.tableName);
/*  37 */     Predef..MODULE$.println(new StringBuilder().append("sql2:").append(sql2).toString());
/*     */     
/*  39 */     int count2 = map.count();
/*     */     
/*  41 */     String PrestoURL = new StringBuilder().append("jdbc:presto://").append(this.PrestoHostPort).append("/hive/yisadata").toString();
/*  42 */     String PrestoUser = "spark";
/*  43 */     String PrestoPwd = "";
/*  44 */     String PrestoDriver = "com.facebook.presto.jdbc.PrestoDriver";
/*     */     
/*  46 */     Class.forName(PrestoDriver);
/*  47 */     Connection conn = java.sql.DriverManager.getConnection(PrestoURL, PrestoUser, null);
/*     */     
/*  49 */     java.sql.Statement stmt = conn.createStatement();
/*     */     
/*  51 */     ResultSet rs = stmt.executeQuery(sql2);
/*     */     
/*  53 */     Connection mysqlconn = com.yisa.engine.db.MySQLConnectManager..MODULE$.getConnet(this.zkHostport);
/*  54 */     mysqlconn.setAutoCommit(false);
/*     */     
/*  56 */     String sql = "insert into xscpcb_result(j_id, s_id,y_id,count) values(?, ?, ?, ?)";
/*  57 */     PreparedStatement mysqlpstmt = mysqlconn.prepareStatement(sql);
/*     */     
/*  59 */     int count = 0;
/*     */     
/*  61 */     while (rs.next())
/*     */     {
/*  63 */       mysqlpstmt.setString(1, job_id);
/*  64 */       mysqlpstmt.setString(2, rs.getString(2));
/*     */       
/*  66 */       mysqlpstmt.setString(3, new StringBuilder().append(rs.getInt(3)).append("").toString());
/*  67 */       mysqlpstmt.setString(4, new StringBuilder().append(rs.getInt(4)).append("").toString());
/*  68 */       mysqlpstmt.addBatch();
/*  69 */       count += 1;
/*     */     }
/*  71 */     mysqlpstmt.executeBatch();
/*     */     
/*  73 */     String sqlProcess = "insert into xscpcb_progress(jobid,pronum,total) values(?,?,?)";
/*  74 */     PreparedStatement pstmtProcess = mysqlconn.prepareStatement(sqlProcess);
/*     */     
/*  76 */     if (count == 0) {
/*  77 */       count = -1;
/*     */     }
/*  79 */     pstmtProcess.setString(1, job_id);
/*  80 */     pstmtProcess.setInt(2, 0);
/*  81 */     pstmtProcess.setInt(3, count);
/*  82 */     pstmtProcess.executeUpdate();
/*  83 */     pstmtProcess.close();
/*     */     
/*  85 */     mysqlconn.commit();
/*  86 */     mysqlpstmt.close();
/*  87 */     mysqlconn.close();
/*     */     
/*  89 */     rs.close();
/*  90 */     stmt.close();
/*  91 */     conn.close();
/*     */   }
/*     */   
/*     */   public void getPlateNumber(int headIndex, final int length, final String instr, final int n, final List<Object> list, final List<String> res) {
/*  95 */     final Object localObject = new Object();
/*     */     try {
/*  97 */       final ObjectRef list2 = ObjectRef.create(new ArrayList());
/*  98 */       ((ArrayList)list2.elem).addAll(list);
/*  99 */       int len = instr.length() + length - n;RichInt..MODULE$
/* 100 */         .until$extension0(Predef..MODULE$.intWrapper(headIndex), len).foreach(new scala.runtime.AbstractFunction1.mcZI.sp() { public final boolean apply(int i) { return apply$mcZI$sp(i); }
/*     */           
/* 102 */           public boolean apply$mcZI$sp(int i) { if (length <= n)
/*     */             {
/*     */ 
/* 105 */               list.add(scala.runtime.BoxesRunTime.boxToInteger(i));
/*     */               
/* 107 */               SparkEngineV2ForSimilarPlatePresto.this.getPlateNumber(i + 1, length + 1, instr, n, list, res);
/*     */               
/* 109 */               final ObjectRef array = ObjectRef.create(instr.toCharArray());
/*     */               
/*     */ 
/* 112 */               System.out.println(list.toString());
/* 113 */               RichInt..MODULE$
/*     */               
/* 115 */                 .until$extension0(Predef..MODULE$.intWrapper(0), list.size()).foreach$mVc$sp(new scala.runtime.AbstractFunction1.mcVI.sp() { public final void apply(int t) { apply$mcVI$sp(t); }
/* 116 */                   public void apply$mcVI$sp(int t) { ((char[])array.elem)[scala.runtime.BoxesRunTime.unboxToInt(SparkEngineV2ForSimilarPlatePresto..anonfun.getPlateNumber.1.this.list$1.get(t))] = 95;
/*     */                   }
/* 118 */                 });
/* 119 */               System.out.println(new StringBuilder().append("====").append(String.valueOf((char[])array.elem)).toString());
/*     */               
/*     */ 
/*     */ 
/*     */ 
/*     */ 
/*     */ 
/*     */ 
/*     */ 
/* 128 */               list.clear();
/* 129 */               return list.addAll((ArrayList)list2.elem);
/*     */             }
/* 124 */             throw new NonLocalReturnControl.mcV.sp(localObject, scala.runtime.BoxedUnit.UNIT);
/*     */           }
/*     */         });
/*     */     }
/*     */     catch (NonLocalReturnControl localNonLocalReturnControl) {}
/*  96 */     if (localNonLocalReturnControl.key() == localObject) { localNonLocalReturnControl.value$mcV$sp();return; } throw localNonLocalReturnControl;
/*     */   }
/*     */   
/*     */   public static final long serialVersionUID = 0L;
/*     */   public static final long serialVersionUID = 0L;
/*     */   /* Error */
/*     */   public String getSql2(InputBean param, String table)
/*     */   {
/*     */     // Byte code:
/*     */     //   0: aload_1
/*     */     //   1: invokevirtual 293	com/yisa/engine/common/InputBean:plateNumber	()Ljava/lang/String;
/*     */     //   4: astore_3
/*     */     //   5: aload_1
/*     */     //   6: invokevirtual 296	com/yisa/engine/common/InputBean:differ	()I
/*     */     //   9: istore 4
/*     */     //   11: lconst_0
/*     */     //   12: lstore 5
/*     */     //   14: lconst_0
/*     */     //   15: lstore 7
/*     */     //   17: aload_1
/*     */     //   18: invokevirtual 299	com/yisa/engine/common/InputBean:startTime	()Ljava/lang/String;
/*     */     //   21: ifnull +13 -> 34
/*     */     //   24: aload_0
/*     */     //   25: aload_1
/*     */     //   26: invokevirtual 299	com/yisa/engine/common/InputBean:startTime	()Ljava/lang/String;
/*     */     //   29: invokevirtual 303	com/yisa/engine/branch/SparkEngineV2ForSimilarPlatePresto:getTimeStampSecond	(Ljava/lang/String;)J
/*     */     //   32: lstore 5
/*     */     //   34: aload_1
/*     */     //   35: invokevirtual 306	com/yisa/engine/common/InputBean:endTime	()Ljava/lang/String;
/*     */     //   38: ifnull +13 -> 51
/*     */     //   41: aload_0
/*     */     //   42: aload_1
/*     */     //   43: invokevirtual 306	com/yisa/engine/common/InputBean:endTime	()Ljava/lang/String;
/*     */     //   46: invokevirtual 303	com/yisa/engine/branch/SparkEngineV2ForSimilarPlatePresto:getTimeStampSecond	(Ljava/lang/String;)J
/*     */     //   49: lstore 7
/*     */     //   51: new 308	java/lang/StringBuffer
/*     */     //   54: dup
/*     */     //   55: invokespecial 309	java/lang/StringBuffer:<init>	()V
/*     */     //   58: astore 9
/*     */     //   60: aload 9
/*     */     //   62: new 63	scala/collection/mutable/StringBuilder
/*     */     //   65: dup
/*     */     //   66: invokespecial 64	scala/collection/mutable/StringBuilder:<init>	()V
/*     */     //   69: ldc_w 311
/*     */     //   72: invokevirtual 70	scala/collection/mutable/StringBuilder:append	(Ljava/lang/Object;)Lscala/collection/mutable/StringBuilder;
/*     */     //   75: aload_2
/*     */     //   76: invokevirtual 70	scala/collection/mutable/StringBuilder:append	(Ljava/lang/Object;)Lscala/collection/mutable/StringBuilder;
/*     */     //   79: invokevirtual 74	scala/collection/mutable/StringBuilder:toString	()Ljava/lang/String;
/*     */     //   82: invokevirtual 314	java/lang/StringBuffer:append	(Ljava/lang/String;)Ljava/lang/StringBuffer;
/*     */     //   85: pop
/*     */     //   86: aload 9
/*     */     //   88: ldc_w 316
/*     */     //   91: invokevirtual 314	java/lang/StringBuffer:append	(Ljava/lang/String;)Ljava/lang/StringBuffer;
/*     */     //   94: pop
/*     */     //   95: aload_1
/*     */     //   96: invokevirtual 320	com/yisa/engine/common/InputBean:carYear	()[Ljava/lang/String;
/*     */     //   99: aconst_null
/*     */     //   100: if_acmpeq +128 -> 228
/*     */     //   103: aload_1
/*     */     //   104: invokevirtual 320	com/yisa/engine/common/InputBean:carYear	()[Ljava/lang/String;
/*     */     //   107: arraylength
/*     */     //   108: iconst_0
/*     */     //   109: if_icmpeq +119 -> 228
/*     */     //   112: aload_1
/*     */     //   113: invokevirtual 320	com/yisa/engine/common/InputBean:carYear	()[Ljava/lang/String;
/*     */     //   116: iconst_0
/*     */     //   117: aaload
/*     */     //   118: ldc 92
/*     */     //   120: astore 10
/*     */     //   122: dup
/*     */     //   123: ifnonnull +12 -> 135
/*     */     //   126: pop
/*     */     //   127: aload 10
/*     */     //   129: ifnull +99 -> 228
/*     */     //   132: goto +11 -> 143
/*     */     //   135: aload 10
/*     */     //   137: invokevirtual 324	java/lang/Object:equals	(Ljava/lang/Object;)Z
/*     */     //   140: ifne +88 -> 228
/*     */     //   143: aload_1
/*     */     //   144: invokevirtual 320	com/yisa/engine/common/InputBean:carYear	()[Ljava/lang/String;
/*     */     //   147: iconst_0
/*     */     //   148: aaload
/*     */     //   149: ldc_w 326
/*     */     //   152: astore 11
/*     */     //   154: dup
/*     */     //   155: ifnonnull +12 -> 167
/*     */     //   158: pop
/*     */     //   159: aload 11
/*     */     //   161: ifnull +67 -> 228
/*     */     //   164: goto +11 -> 175
/*     */     //   167: aload 11
/*     */     //   169: invokevirtual 324	java/lang/Object:equals	(Ljava/lang/Object;)Z
/*     */     //   172: ifne +56 -> 228
/*     */     //   175: getstatic 61	scala/Predef$:MODULE$	Lscala/Predef$;
/*     */     //   178: aload_1
/*     */     //   179: invokevirtual 320	com/yisa/engine/common/InputBean:carYear	()[Ljava/lang/String;
/*     */     //   182: checkcast 328	[Ljava/lang/Object;
/*     */     //   185: invokevirtual 332	scala/Predef$:refArrayOps	([Ljava/lang/Object;)Lscala/collection/mutable/ArrayOps;
/*     */     //   188: new 334	com/yisa/engine/branch/SparkEngineV2ForSimilarPlatePresto$$anonfun$1
/*     */     //   191: dup
/*     */     //   192: aload_0
/*     */     //   193: invokespecial 335	com/yisa/engine/branch/SparkEngineV2ForSimilarPlatePresto$$anonfun$1:<init>	(Lcom/yisa/engine/branch/SparkEngineV2ForSimilarPlatePresto;)V
/*     */     //   196: invokeinterface 341 2 0
/*     */     //   201: checkcast 23	java/lang/String
/*     */     //   204: astore 12
/*     */     //   206: aload 9
/*     */     //   208: ldc_w 343
/*     */     //   211: invokevirtual 314	java/lang/StringBuffer:append	(Ljava/lang/String;)Ljava/lang/StringBuffer;
/*     */     //   214: aload 12
/*     */     //   216: invokevirtual 314	java/lang/StringBuffer:append	(Ljava/lang/String;)Ljava/lang/StringBuffer;
/*     */     //   219: ldc_w 345
/*     */     //   222: invokevirtual 314	java/lang/StringBuffer:append	(Ljava/lang/String;)Ljava/lang/StringBuffer;
/*     */     //   225: goto +6 -> 231
/*     */     //   228: getstatic 351	scala/runtime/BoxedUnit:UNIT	Lscala/runtime/BoxedUnit;
/*     */     //   231: pop
/*     */     //   232: lload 5
/*     */     //   234: lconst_0
/*     */     //   235: lcmp
/*     */     //   236: ifeq +25 -> 261
/*     */     //   239: aload 9
/*     */     //   241: ldc_w 353
/*     */     //   244: invokevirtual 314	java/lang/StringBuffer:append	(Ljava/lang/String;)Ljava/lang/StringBuffer;
/*     */     //   247: aload_0
/*     */     //   248: aload_1
/*     */     //   249: invokevirtual 299	com/yisa/engine/common/InputBean:startTime	()Ljava/lang/String;
/*     */     //   252: invokevirtual 357	com/yisa/engine/branch/SparkEngineV2ForSimilarPlatePresto:getDateid	(Ljava/lang/String;)Ljava/lang/String;
/*     */     //   255: invokevirtual 314	java/lang/StringBuffer:append	(Ljava/lang/String;)Ljava/lang/StringBuffer;
/*     */     //   258: goto +6 -> 264
/*     */     //   261: getstatic 351	scala/runtime/BoxedUnit:UNIT	Lscala/runtime/BoxedUnit;
/*     */     //   264: pop
/*     */     //   265: lload 7
/*     */     //   267: lconst_0
/*     */     //   268: lcmp
/*     */     //   269: ifeq +25 -> 294
/*     */     //   272: aload 9
/*     */     //   274: ldc_w 359
/*     */     //   277: invokevirtual 314	java/lang/StringBuffer:append	(Ljava/lang/String;)Ljava/lang/StringBuffer;
/*     */     //   280: aload_0
/*     */     //   281: aload_1
/*     */     //   282: invokevirtual 306	com/yisa/engine/common/InputBean:endTime	()Ljava/lang/String;
/*     */     //   285: invokevirtual 357	com/yisa/engine/branch/SparkEngineV2ForSimilarPlatePresto:getDateid	(Ljava/lang/String;)Ljava/lang/String;
/*     */     //   288: invokevirtual 314	java/lang/StringBuffer:append	(Ljava/lang/String;)Ljava/lang/StringBuffer;
/*     */     //   291: goto +6 -> 297
/*     */     //   294: getstatic 351	scala/runtime/BoxedUnit:UNIT	Lscala/runtime/BoxedUnit;
/*     */     //   297: pop
/*     */     //   298: lload 5
/*     */     //   300: lconst_0
/*     */     //   301: lcmp
/*     */     //   302: ifeq +19 -> 321
/*     */     //   305: aload 9
/*     */     //   307: ldc_w 361
/*     */     //   310: invokevirtual 314	java/lang/StringBuffer:append	(Ljava/lang/String;)Ljava/lang/StringBuffer;
/*     */     //   313: lload 5
/*     */     //   315: invokevirtual 364	java/lang/StringBuffer:append	(J)Ljava/lang/StringBuffer;
/*     */     //   318: goto +6 -> 324
/*     */     //   321: getstatic 351	scala/runtime/BoxedUnit:UNIT	Lscala/runtime/BoxedUnit;
/*     */     //   324: pop
/*     */     //   325: lload 7
/*     */     //   327: lconst_0
/*     */     //   328: lcmp
/*     */     //   329: ifeq +19 -> 348
/*     */     //   332: aload 9
/*     */     //   334: ldc_w 366
/*     */     //   337: invokevirtual 314	java/lang/StringBuffer:append	(Ljava/lang/String;)Ljava/lang/StringBuffer;
/*     */     //   340: lload 7
/*     */     //   342: invokevirtual 364	java/lang/StringBuffer:append	(J)Ljava/lang/StringBuffer;
/*     */     //   345: goto +6 -> 351
/*     */     //   348: getstatic 351	scala/runtime/BoxedUnit:UNIT	Lscala/runtime/BoxedUnit;
/*     */     //   351: pop
/*     */     //   352: aload_1
/*     */     //   353: invokevirtual 369	com/yisa/engine/common/InputBean:carModel	()[Ljava/lang/String;
/*     */     //   356: aconst_null
/*     */     //   357: if_acmpeq +101 -> 458
/*     */     //   360: aload_1
/*     */     //   361: invokevirtual 369	com/yisa/engine/common/InputBean:carModel	()[Ljava/lang/String;
/*     */     //   364: arraylength
/*     */     //   365: iconst_0
/*     */     //   366: if_icmple +92 -> 458
/*     */     //   369: aload_1
/*     */     //   370: invokevirtual 369	com/yisa/engine/common/InputBean:carModel	()[Ljava/lang/String;
/*     */     //   373: iconst_0
/*     */     //   374: aaload
/*     */     //   375: ldc_w 326
/*     */     //   378: astore 13
/*     */     //   380: dup
/*     */     //   381: ifnonnull +12 -> 393
/*     */     //   384: pop
/*     */     //   385: aload 13
/*     */     //   387: ifnull +71 -> 458
/*     */     //   390: goto +11 -> 401
/*     */     //   393: aload 13
/*     */     //   395: invokevirtual 324	java/lang/Object:equals	(Ljava/lang/Object;)Z
/*     */     //   398: ifne +60 -> 458
/*     */     //   401: aload_1
/*     */     //   402: invokevirtual 369	com/yisa/engine/common/InputBean:carModel	()[Ljava/lang/String;
/*     */     //   405: astore 14
/*     */     //   407: getstatic 61	scala/Predef$:MODULE$	Lscala/Predef$;
/*     */     //   410: aload 14
/*     */     //   412: checkcast 328	[Ljava/lang/Object;
/*     */     //   415: invokevirtual 332	scala/Predef$:refArrayOps	([Ljava/lang/Object;)Lscala/collection/mutable/ArrayOps;
/*     */     //   418: new 371	com/yisa/engine/branch/SparkEngineV2ForSimilarPlatePresto$$anonfun$2
/*     */     //   421: dup
/*     */     //   422: aload_0
/*     */     //   423: invokespecial 372	com/yisa/engine/branch/SparkEngineV2ForSimilarPlatePresto$$anonfun$2:<init>	(Lcom/yisa/engine/branch/SparkEngineV2ForSimilarPlatePresto;)V
/*     */     //   426: invokeinterface 341 2 0
/*     */     //   431: checkcast 23	java/lang/String
/*     */     //   434: astore 15
/*     */     //   436: aload 9
/*     */     //   438: ldc_w 374
/*     */     //   441: invokevirtual 314	java/lang/StringBuffer:append	(Ljava/lang/String;)Ljava/lang/StringBuffer;
/*     */     //   444: aload 15
/*     */     //   446: invokevirtual 314	java/lang/StringBuffer:append	(Ljava/lang/String;)Ljava/lang/StringBuffer;
/*     */     //   449: ldc_w 345
/*     */     //   452: invokevirtual 314	java/lang/StringBuffer:append	(Ljava/lang/String;)Ljava/lang/StringBuffer;
/*     */     //   455: goto +6 -> 461
/*     */     //   458: getstatic 351	scala/runtime/BoxedUnit:UNIT	Lscala/runtime/BoxedUnit;
/*     */     //   461: pop
/*     */     //   462: aload_1
/*     */     //   463: invokevirtual 377	com/yisa/engine/common/InputBean:carBrand	()Ljava/lang/String;
/*     */     //   466: ifnull +62 -> 528
/*     */     //   469: aload_1
/*     */     //   470: invokevirtual 377	com/yisa/engine/common/InputBean:carBrand	()Ljava/lang/String;
/*     */     //   473: ldc 92
/*     */     //   475: astore 16
/*     */     //   477: dup
/*     */     //   478: ifnonnull +12 -> 490
/*     */     //   481: pop
/*     */     //   482: aload 16
/*     */     //   484: ifnull +44 -> 528
/*     */     //   487: goto +11 -> 498
/*     */     //   490: aload 16
/*     */     //   492: invokevirtual 324	java/lang/Object:equals	(Ljava/lang/Object;)Z
/*     */     //   495: ifne +33 -> 528
/*     */     //   498: aload_1
/*     */     //   499: invokevirtual 377	com/yisa/engine/common/InputBean:carBrand	()Ljava/lang/String;
/*     */     //   502: ldc_w 326
/*     */     //   505: astore 17
/*     */     //   507: dup
/*     */     //   508: ifnonnull +12 -> 520
/*     */     //   511: pop
/*     */     //   512: aload 17
/*     */     //   514: ifnull +14 -> 528
/*     */     //   517: goto +17 -> 534
/*     */     //   520: aload 17
/*     */     //   522: invokevirtual 324	java/lang/Object:equals	(Ljava/lang/Object;)Z
/*     */     //   525: ifeq +9 -> 534
/*     */     //   528: getstatic 351	scala/runtime/BoxedUnit:UNIT	Lscala/runtime/BoxedUnit;
/*     */     //   531: goto +22 -> 553
/*     */     //   534: aload_1
/*     */     //   535: invokevirtual 377	com/yisa/engine/common/InputBean:carBrand	()Ljava/lang/String;
/*     */     //   538: astore 18
/*     */     //   540: aload 9
/*     */     //   542: ldc_w 379
/*     */     //   545: invokevirtual 314	java/lang/StringBuffer:append	(Ljava/lang/String;)Ljava/lang/StringBuffer;
/*     */     //   548: aload 18
/*     */     //   550: invokevirtual 314	java/lang/StringBuffer:append	(Ljava/lang/String;)Ljava/lang/StringBuffer;
/*     */     //   553: pop
/*     */     //   554: aload_1
/*     */     //   555: invokevirtual 382	com/yisa/engine/common/InputBean:locationId	()[Ljava/lang/String;
/*     */     //   558: aconst_null
/*     */     //   559: if_acmpeq +164 -> 723
/*     */     //   562: aload_1
/*     */     //   563: invokevirtual 382	com/yisa/engine/common/InputBean:locationId	()[Ljava/lang/String;
/*     */     //   566: arraylength
/*     */     //   567: iconst_0
/*     */     //   568: if_icmpeq +155 -> 723
/*     */     //   571: aload_1
/*     */     //   572: invokevirtual 382	com/yisa/engine/common/InputBean:locationId	()[Ljava/lang/String;
/*     */     //   575: iconst_0
/*     */     //   576: aaload
/*     */     //   577: ldc 92
/*     */     //   579: astore 19
/*     */     //   581: dup
/*     */     //   582: ifnonnull +12 -> 594
/*     */     //   585: pop
/*     */     //   586: aload 19
/*     */     //   588: ifnull +135 -> 723
/*     */     //   591: goto +11 -> 602
/*     */     //   594: aload 19
/*     */     //   596: invokevirtual 324	java/lang/Object:equals	(Ljava/lang/Object;)Z
/*     */     //   599: ifne +124 -> 723
/*     */     //   602: aload_1
/*     */     //   603: invokevirtual 382	com/yisa/engine/common/InputBean:locationId	()[Ljava/lang/String;
/*     */     //   606: iconst_0
/*     */     //   607: aaload
/*     */     //   608: ldc_w 326
/*     */     //   611: astore 20
/*     */     //   613: dup
/*     */     //   614: ifnonnull +12 -> 626
/*     */     //   617: pop
/*     */     //   618: aload 20
/*     */     //   620: ifnull +103 -> 723
/*     */     //   623: goto +11 -> 634
/*     */     //   626: aload 20
/*     */     //   628: invokevirtual 324	java/lang/Object:equals	(Ljava/lang/Object;)Z
/*     */     //   631: ifne +92 -> 723
/*     */     //   634: getstatic 61	scala/Predef$:MODULE$	Lscala/Predef$;
/*     */     //   637: getstatic 61	scala/Predef$:MODULE$	Lscala/Predef$;
/*     */     //   640: aload_1
/*     */     //   641: invokevirtual 382	com/yisa/engine/common/InputBean:locationId	()[Ljava/lang/String;
/*     */     //   644: checkcast 328	[Ljava/lang/Object;
/*     */     //   647: invokevirtual 332	scala/Predef$:refArrayOps	([Ljava/lang/Object;)Lscala/collection/mutable/ArrayOps;
/*     */     //   650: new 384	com/yisa/engine/branch/SparkEngineV2ForSimilarPlatePresto$$anonfun$3
/*     */     //   653: dup
/*     */     //   654: aload_0
/*     */     //   655: invokespecial 385	com/yisa/engine/branch/SparkEngineV2ForSimilarPlatePresto$$anonfun$3:<init>	(Lcom/yisa/engine/branch/SparkEngineV2ForSimilarPlatePresto;)V
/*     */     //   658: getstatic 390	scala/Array$:MODULE$	Lscala/Array$;
/*     */     //   661: getstatic 395	scala/reflect/ClassTag$:MODULE$	Lscala/reflect/ClassTag$;
/*     */     //   664: ldc 23
/*     */     //   666: invokevirtual 399	scala/reflect/ClassTag$:apply	(Ljava/lang/Class;)Lscala/reflect/ClassTag;
/*     */     //   669: invokevirtual 403	scala/Array$:canBuildFrom	(Lscala/reflect/ClassTag;)Lscala/collection/generic/CanBuildFrom;
/*     */     //   672: invokeinterface 406 3 0
/*     */     //   677: checkcast 328	[Ljava/lang/Object;
/*     */     //   680: invokevirtual 332	scala/Predef$:refArrayOps	([Ljava/lang/Object;)Lscala/collection/mutable/ArrayOps;
/*     */     //   683: new 408	com/yisa/engine/branch/SparkEngineV2ForSimilarPlatePresto$$anonfun$4
/*     */     //   686: dup
/*     */     //   687: aload_0
/*     */     //   688: invokespecial 409	com/yisa/engine/branch/SparkEngineV2ForSimilarPlatePresto$$anonfun$4:<init>	(Lcom/yisa/engine/branch/SparkEngineV2ForSimilarPlatePresto;)V
/*     */     //   691: invokeinterface 341 2 0
/*     */     //   696: checkcast 23	java/lang/String
/*     */     //   699: astore 21
/*     */     //   701: aload 9
/*     */     //   703: ldc_w 411
/*     */     //   706: invokevirtual 314	java/lang/StringBuffer:append	(Ljava/lang/String;)Ljava/lang/StringBuffer;
/*     */     //   709: aload 21
/*     */     //   711: invokevirtual 314	java/lang/StringBuffer:append	(Ljava/lang/String;)Ljava/lang/StringBuffer;
/*     */     //   714: ldc_w 345
/*     */     //   717: invokevirtual 314	java/lang/StringBuffer:append	(Ljava/lang/String;)Ljava/lang/StringBuffer;
/*     */     //   720: goto +6 -> 726
/*     */     //   723: getstatic 351	scala/runtime/BoxedUnit:UNIT	Lscala/runtime/BoxedUnit;
/*     */     //   726: pop
/*     */     //   727: new 231	java/util/ArrayList
/*     */     //   730: dup
/*     */     //   731: invokespecial 232	java/util/ArrayList:<init>	()V
/*     */     //   734: astore 22
/*     */     //   736: new 231	java/util/ArrayList
/*     */     //   739: dup
/*     */     //   740: invokespecial 232	java/util/ArrayList:<init>	()V
/*     */     //   743: invokestatic 238	scala/runtime/ObjectRef:create	(Ljava/lang/Object;)Lscala/runtime/ObjectRef;
/*     */     //   746: astore 23
/*     */     //   748: aload_0
/*     */     //   749: iconst_0
/*     */     //   750: iconst_1
/*     */     //   751: aload_3
/*     */     //   752: iload 4
/*     */     //   754: aload 22
/*     */     //   756: aload 23
/*     */     //   758: getfield 242	scala/runtime/ObjectRef:elem	Ljava/lang/Object;
/*     */     //   761: checkcast 231	java/util/ArrayList
/*     */     //   764: invokevirtual 413	com/yisa/engine/branch/SparkEngineV2ForSimilarPlatePresto:getPlateNumber	(IILjava/lang/String;ILjava/util/List;Ljava/util/List;)V
/*     */     //   767: aload 23
/*     */     //   769: getfield 242	scala/runtime/ObjectRef:elem	Ljava/lang/Object;
/*     */     //   772: checkcast 231	java/util/ArrayList
/*     */     //   775: invokevirtual 416	java/util/ArrayList:size	()I
/*     */     //   778: iconst_0
/*     */     //   779: if_icmple +62 -> 841
/*     */     //   782: aload 9
/*     */     //   784: ldc_w 418
/*     */     //   787: invokevirtual 314	java/lang/StringBuffer:append	(Ljava/lang/String;)Ljava/lang/StringBuffer;
/*     */     //   790: pop
/*     */     //   791: getstatic 254	scala/runtime/RichInt$:MODULE$	Lscala/runtime/RichInt$;
/*     */     //   794: getstatic 61	scala/Predef$:MODULE$	Lscala/Predef$;
/*     */     //   797: iconst_0
/*     */     //   798: invokevirtual 257	scala/Predef$:intWrapper	(I)I
/*     */     //   801: aload 23
/*     */     //   803: getfield 242	scala/runtime/ObjectRef:elem	Ljava/lang/Object;
/*     */     //   806: checkcast 231	java/util/ArrayList
/*     */     //   809: invokevirtual 416	java/util/ArrayList:size	()I
/*     */     //   812: invokevirtual 261	scala/runtime/RichInt$:until$extension0	(II)Lscala/collection/immutable/Range;
/*     */     //   815: new 420	com/yisa/engine/branch/SparkEngineV2ForSimilarPlatePresto$$anonfun$getSql2$1
/*     */     //   818: dup
/*     */     //   819: aload_0
/*     */     //   820: aload 9
/*     */     //   822: aload 23
/*     */     //   824: invokespecial 423	com/yisa/engine/branch/SparkEngineV2ForSimilarPlatePresto$$anonfun$getSql2$1:<init>	(Lcom/yisa/engine/branch/SparkEngineV2ForSimilarPlatePresto;Ljava/lang/StringBuffer;Lscala/runtime/ObjectRef;)V
/*     */     //   827: invokevirtual 272	scala/collection/immutable/Range:foreach	(Lscala/Function1;)V
/*     */     //   830: aload 9
/*     */     //   832: ldc_w 425
/*     */     //   835: invokevirtual 314	java/lang/StringBuffer:append	(Ljava/lang/String;)Ljava/lang/StringBuffer;
/*     */     //   838: goto +6 -> 844
/*     */     //   841: getstatic 351	scala/runtime/BoxedUnit:UNIT	Lscala/runtime/BoxedUnit;
/*     */     //   844: pop
/*     */     //   845: aload 9
/*     */     //   847: ldc_w 427
/*     */     //   850: invokevirtual 314	java/lang/StringBuffer:append	(Ljava/lang/String;)Ljava/lang/StringBuffer;
/*     */     //   853: pop
/*     */     //   854: aload 9
/*     */     //   856: invokevirtual 428	java/lang/StringBuffer:toString	()Ljava/lang/String;
/*     */     //   859: areturn
/*     */     // Line number table:
/*     */     //   Java source line #136	-> byte code offset #0
/*     */     //   Java source line #137	-> byte code offset #5
/*     */     //   Java source line #138	-> byte code offset #11
/*     */     //   Java source line #139	-> byte code offset #14
/*     */     //   Java source line #140	-> byte code offset #17
/*     */     //   Java source line #142	-> byte code offset #24
/*     */     //   Java source line #144	-> byte code offset #34
/*     */     //   Java source line #146	-> byte code offset #41
/*     */     //   Java source line #150	-> byte code offset #51
/*     */     //   Java source line #152	-> byte code offset #60
/*     */     //   Java source line #153	-> byte code offset #86
/*     */     //   Java source line #156	-> byte code offset #95
/*     */     //   Java source line #157	-> byte code offset #175
/*     */     //   Java source line #158	-> byte code offset #206
/*     */     //   Java source line #156	-> byte code offset #228
/*     */     //   Java source line #161	-> byte code offset #232
/*     */     //   Java source line #162	-> byte code offset #239
/*     */     //   Java source line #161	-> byte code offset #261
/*     */     //   Java source line #165	-> byte code offset #265
/*     */     //   Java source line #166	-> byte code offset #272
/*     */     //   Java source line #165	-> byte code offset #294
/*     */     //   Java source line #169	-> byte code offset #298
/*     */     //   Java source line #170	-> byte code offset #305
/*     */     //   Java source line #169	-> byte code offset #321
/*     */     //   Java source line #173	-> byte code offset #325
/*     */     //   Java source line #174	-> byte code offset #332
/*     */     //   Java source line #173	-> byte code offset #348
/*     */     //   Java source line #177	-> byte code offset #352
/*     */     //   Java source line #178	-> byte code offset #401
/*     */     //   Java source line #179	-> byte code offset #407
/*     */     //   Java source line #180	-> byte code offset #436
/*     */     //   Java source line #177	-> byte code offset #458
/*     */     //   Java source line #183	-> byte code offset #462
/*     */     //   Java source line #184	-> byte code offset #534
/*     */     //   Java source line #185	-> byte code offset #540
/*     */     //   Java source line #183	-> byte code offset #553
/*     */     //   Java source line #188	-> byte code offset #554
/*     */     //   Java source line #189	-> byte code offset #634
/*     */     //   Java source line #190	-> byte code offset #701
/*     */     //   Java source line #188	-> byte code offset #723
/*     */     //   Java source line #194	-> byte code offset #727
/*     */     //   Java source line #195	-> byte code offset #736
/*     */     //   Java source line #196	-> byte code offset #748
/*     */     //   Java source line #197	-> byte code offset #767
/*     */     //   Java source line #198	-> byte code offset #782
/*     */     //   Java source line #199	-> byte code offset #794
/*     */     //   Java source line #206	-> byte code offset #830
/*     */     //   Java source line #197	-> byte code offset #841
/*     */     //   Java source line #209	-> byte code offset #845
/*     */     //   Java source line #211	-> byte code offset #854
/*     */     // Local variable table:
/*     */     //   start	length	slot	name	signature
/*     */     //   0	860	0	this	SparkEngineV2ForSimilarPlatePresto
/*     */     //   0	860	1	param	InputBean
/*     */     //   0	860	2	table	String
/*     */     //   5	854	3	plateNumber	String
/*     */     //   11	848	4	differ	int
/*     */     //   14	845	5	startTime	long
/*     */     //   17	842	7	endTime	long
/*     */     //   60	799	9	sql	StringBuffer
/*     */     //   206	19	12	m	String
/*     */     //   407	48	14	model	String[]
/*     */     //   436	19	15	m	String
/*     */     //   540	13	18	brand	String
/*     */     //   701	19	21	l	String
/*     */     //   736	123	22	list	ArrayList
/*     */     //   748	111	23	plateList	ObjectRef
/*     */   }
/*     */   
/*     */   public String getTimeSql(InputBean param, String table)
/*     */   {
/* 216 */     String plateNumber = param.plateNumber();
/* 217 */     int differ = param.differ();
/* 218 */     long startTime = 0L;
/* 219 */     if (param.startTime() != null)
/*     */     {
/* 221 */       startTime = getTimeStampSecond(param.startTime());
/*     */     }
/* 223 */     long endTime = 0L;
/* 224 */     if (param.endTime() != null)
/*     */     {
/* 226 */       endTime = getTimeStampSecond(param.endTime());
/*     */     }
/*     */     
/* 229 */     StringBuffer sql = new StringBuffer();
/*     */     
/*     */ 
/*     */ 
/*     */ 
/*     */ 
/*     */ 
/*     */ 
/*     */ 
/*     */ 
/*     */ 
/*     */ 
/*     */ 
/*     */ 
/*     */ 
/*     */ 
/*     */ 
/*     */ 
/*     */ 
/* 248 */     return sql.toString();
/*     */   }
/*     */   
/*     */   public long getTimeStampSecond(String time)
/*     */   {
/* 253 */     SimpleDateFormat format = new SimpleDateFormat("yyyyMMddHHmmss");
/* 254 */     return format.parse(time).getTime() / 1000L;
/*     */   }
/*     */   
/*     */   public String getDateid(String timeString)
/*     */   {
/* 259 */     String timeLong = timeString.replaceAll("[-\\s:]", "");
/*     */     
/* 261 */     return timeLong.substring(0, 8);
/*     */   }
/*     */   
/*     */   public long getTimeLong(String timeString) {
/* 265 */     String timeLong = timeString.replaceAll("[-\\s:]", "");
/*     */     
/* 267 */     return new scala.collection.immutable.StringOps(Predef..MODULE$.augmentString(timeLong.substring(0, 14))).toLong();
/*     */   }
/*     */   
/*     */   public SparkEngineV2ForSimilarPlatePresto(String line, String tableName, String zkHostport, String PrestoHostPort) {}
/*     */ }


/* Location:              E:\BaiduYunDownload\伊萨时期的一些代码\SparkEngine终极版\jars\YISAEngineBySpark2-4.0.6-SNAPSHOT-jar-with-dependencies.jar!\com\yisa\engine\branch\SparkEngineV2ForSimilarPlatePresto.class
 * Java compiler version: 6 (50.0)
 * JD-Core Version:       0.7.1
 */