/*    */ package com.yisa.engine.branch;
/*    */ 
/*    */ import com.google.gson.Gson;
/*    */ import com.yisa.engine.common.InputBean;
/*    */ import java.sql.Connection;
/*    */ import java.sql.PreparedStatement;
/*    */ import java.util.Date;
/*    */ import org.apache.spark.sql.Dataset;
/*    */ import org.apache.spark.sql.Row;
/*    */ import org.apache.spark.sql.SparkSession;
/*    */ import scala.Predef.;
/*    */ import scala.Serializable;
/*    */ import scala.collection.Iterator;
/*    */ import scala.collection.mutable.StringBuilder;
/*    */ import scala.runtime.AbstractFunction1;
/*    */ import scala.runtime.AbstractFunction2;
/*    */ import scala.runtime.BoxedUnit;
/*    */ import scala.runtime.BoxesRunTime;
/*    */ 
/*    */ @scala.reflect.ScalaSignature(bytes="\006\001Q4A!\001\002\001\027\t92\013]1sW\026sw-\0338f-J2uN]#yC6\004H.\032\006\003\007\021\taA\031:b]\016D'BA\003\007\003\031)gnZ5oK*\021q\001C\001\005s&\034\030MC\001\n\003\r\031w.\\\002\001'\t\001A\002\005\002\016!5\taBC\001\020\003\025\0318-\0317b\023\t\tbB\001\004B]f\024VM\032\005\006'\001!\t\001F\001\007y%t\027\016\036 \025\003U\001\"A\006\001\016\003\tAQ\001\007\001\005\002e\tabU3be\016D7)\031:CsBK7\r\006\004\033;9\032DH\020\t\003\033mI!\001\b\b\003\tUs\027\016\036\005\006=]\001\raH\001\ngB\f'o\033#bi\006\0042\001I\025,\033\005\t#B\001\022$\003\r\031\030\017\034\006\003I\025\nQa\0359be.T!AJ\024\002\r\005\004\030m\0315f\025\005A\023aA8sO&\021!&\t\002\b\t\006$\030m]3u!\t\001C&\003\002.C\t\031!k\\<\t\013=:\002\031\001\031\002\031M\004\030M]6TKN\034\030n\0348\021\005\001\n\024B\001\032\"\0051\031\006/\031:l'\026\0348/[8o\021\025!t\0031\0016\003\021a\027N\\3\021\005YJdBA\0078\023\tAd\"\001\004Qe\026$WMZ\005\003um\022aa\025;sS:<'B\001\035\017\021\025it\0031\0016\003%!\030M\0317f\035\006lW\rC\003@/\001\007Q'\001\006{W\"{7\017\0369peRDQ!\021\001\005\002\t\0131$\032=fGV$Xm\0259be.\034\026\013T+tKB\013'\017^5uS>tG#B\"V/fS\006C\001#S\035\t)\005K\004\002G\037:\021qI\024\b\003\0216s!!\023'\016\003)S!a\023\006\002\rq\022xn\034;?\023\005A\023B\001\024(\023\t!S%\003\002#G%\021\021+I\001\ba\006\0347.Y4f\023\t\031FKA\005ECR\fgI]1nK*\021\021+\t\005\006-\002\003\r\001M\001\013gFd7i\0348uKb$\b\"\002-A\001\004)\024!B:rY~\033\006\"B A\001\004)\004\"B.A\001\004)\024A\0026pE~KG\rC\003^\001\021\005a,\001\004hKR\034\026\013\024\013\005?\032tw\016\005\002aK6\t\021M\003\002cG\006!A.\0318h\025\005!\027\001\0026bm\006L!AO1\t\013\035d\006\031\0015\002\0075\f\007\017\005\002jY6\t!N\003\002l\t\00511m\\7n_:L!!\0346\003\023%s\007/\036;CK\006t\007\"B\037]\001\004)\004\"\0029]\001\004\t\030aD:j[&d\027M]5us2KW.\033;\021\0055\021\030BA:\017\005\035\021un\0347fC:\004")
/*    */ public class SparkEngineV2ForExample
/*    */ {
/*    */   public void SearchCarByPic(Dataset<Row> sparkData, SparkSession sparkSession, String line, String tableName, String zkHostport)
/*    */   {
/* 25 */     long now1 = new Date().getTime();
/* 26 */     String[] line_arr = line.split("\\|");
/* 27 */     String job_type = line_arr[0];
/* 28 */     String job_id = line_arr[1];
/*    */     
/* 30 */     Gson gson = new Gson();
/* 31 */     java.lang.reflect.Type mapType = new com.google.gson.reflect.TypeToken() {}.getType();
/* 32 */     InputBean map = (InputBean)gson.fromJson(line_arr[2], mapType);
/*    */     
/*    */ 
/* 35 */     String sql1 = getSQL(map, tableName, true);
/* 36 */     Predef..MODULE$.println(new StringBuilder().append("SQL--------------:").append(sql1).toString());
/*    */     
/*    */ 
/* 39 */     Dataset resultData = executeSparkSQLUsePartition(sparkSession, sql1, zkHostport, job_id);
/* 40 */     long insertMySQLEnd = new Date().getTime();
/*    */     
/*    */ 
/* 43 */     long tempCount = resultData.count();
/*    */     
/* 45 */     Predef..MODULE$.println(new StringBuilder().append("have no result first time ,set similarityLimit false ,run again , tempCount :").append(BoxesRunTime.boxToLong(tempCount)).toString());
/* 46 */     String sql2 = getSQL(map, tableName, false);
/* 47 */     Predef..MODULE$.println(new StringBuilder().append("SQL--------------:").append(sql2).toString());
/*    */     
/*    */ 
/* 50 */     long now3 = new Date().getTime();
/* 51 */     Predef..MODULE$.println(new StringBuilder().append("have  result or not , time :").append(BoxesRunTime.boxToLong(now3 - insertMySQLEnd)).toString());
/*    */   }
/*    */   
/*    */   public Dataset<Row> executeSparkSQLUsePartition(SparkSession sqlContext, String sql_S, final String zkHostport, final String job_id)
/*    */   {
/* 56 */     long now1 = new Date().getTime();
/*    */     
/* 58 */     Dataset resultData = sqlContext.sql(sql_S);
/* 59 */     long sparkTaskEnd = new Date().getTime();
/*    */     
/* 61 */     Predef..MODULE$.println(new StringBuilder().append("get result time :").append(BoxesRunTime.boxToLong(sparkTaskEnd - now1)).toString());
/*    */     
/*    */ 
/*    */ 
/* 65 */     resultData.foreachPartition(new AbstractFunction1() {
/*    */       public static final long serialVersionUID = 0L;
/*    */       
/* 68 */       public final void apply(Iterator<Row> data) { Connection conn = com.yisa.engine.db.MySQLConnectManager..MODULE$.getConnet(zkHostport);
/* 69 */         conn.setAutoCommit(false);
/* 70 */         String sql = "insert into gpu_index_job (job_id,solr_id,sort_value,plate_number) values(?,?,?,?)";
/* 71 */         final PreparedStatement pstmt = conn.prepareStatement(sql);
/*    */         
/* 73 */         data.foreach(new AbstractFunction1() {
/*    */           public static final long serialVersionUID = 0L;
/*    */           
/* 76 */           public final void apply(Row t) { pstmt.setString(1, SparkEngineV2ForExample..anonfun.executeSparkSQLUsePartition.1.this.job_id$1);
/* 77 */             pstmt.setString(2, t.apply(0).toString());
/* 78 */             pstmt.setString(3, t.apply(1).toString());
/* 79 */             pstmt.setString(4, t.apply(2).toString());
/* 80 */             pstmt.addBatch();
/*    */           }
/* 82 */         });
/* 83 */         int[] test = pstmt.executeBatch();
/* 84 */         conn.commit();
/* 85 */         pstmt.close();
/* 86 */         conn.close();
/*    */ 
/*    */       }
/*    */       
/*    */ 
/*    */ 
/* 92 */     });
/* 93 */     long insertMySQLEnd = new Date().getTime();
/* 94 */     Predef..MODULE$.println(new StringBuilder().append("insert mysql  time :").append(BoxesRunTime.boxToLong(insertMySQLEnd - sparkTaskEnd)).toString());
/* 95 */     return resultData;
/*    */   }
/*    */   
/*    */   /* Error */
/*    */   public String getSQL(InputBean map, String tableName, boolean similarityLimit)
/*    */   {
/*    */     // Byte code:
/*    */     //   0: aload_1
/*    */     //   1: invokevirtual 154	com/yisa/engine/common/InputBean:feature	()Ljava/lang/String;
/*    */     //   4: astore 4
/*    */     //   6: aload_1
/*    */     //   7: invokevirtual 157	com/yisa/engine/common/InputBean:carBrand	()Ljava/lang/String;
/*    */     //   10: astore 5
/*    */     //   12: aload_1
/*    */     //   13: invokevirtual 161	com/yisa/engine/common/InputBean:carModel	()[Ljava/lang/String;
/*    */     //   16: astore 6
/*    */     //   18: getstatic 166	com/yisa/engine/uitl/TimeUtil$:MODULE$	Lcom/yisa/engine/uitl/TimeUtil$;
/*    */     //   21: aload_1
/*    */     //   22: invokevirtual 169	com/yisa/engine/common/InputBean:startTime	()Ljava/lang/String;
/*    */     //   25: invokevirtual 173	com/yisa/engine/uitl/TimeUtil$:getTimeStringFormat	(Ljava/lang/String;)Ljava/lang/String;
/*    */     //   28: astore 7
/*    */     //   30: getstatic 166	com/yisa/engine/uitl/TimeUtil$:MODULE$	Lcom/yisa/engine/uitl/TimeUtil$;
/*    */     //   33: aload_1
/*    */     //   34: invokevirtual 176	com/yisa/engine/common/InputBean:endTime	()Ljava/lang/String;
/*    */     //   37: invokevirtual 173	com/yisa/engine/uitl/TimeUtil$:getTimeStringFormat	(Ljava/lang/String;)Ljava/lang/String;
/*    */     //   40: astore 8
/*    */     //   42: new 178	java/lang/StringBuffer
/*    */     //   45: dup
/*    */     //   46: invokespecial 179	java/lang/StringBuffer:<init>	()V
/*    */     //   49: astore 9
/*    */     //   51: aload 9
/*    */     //   53: ldc -75
/*    */     //   55: invokevirtual 184	java/lang/StringBuffer:append	(Ljava/lang/String;)Ljava/lang/StringBuffer;
/*    */     //   58: pop
/*    */     //   59: aload 9
/*    */     //   61: ldc -70
/*    */     //   63: invokevirtual 184	java/lang/StringBuffer:append	(Ljava/lang/String;)Ljava/lang/StringBuffer;
/*    */     //   66: pop
/*    */     //   67: aload 9
/*    */     //   69: new 58	scala/collection/mutable/StringBuilder
/*    */     //   72: dup
/*    */     //   73: invokespecial 59	scala/collection/mutable/StringBuilder:<init>	()V
/*    */     //   76: ldc -68
/*    */     //   78: invokevirtual 65	scala/collection/mutable/StringBuilder:append	(Ljava/lang/Object;)Lscala/collection/mutable/StringBuilder;
/*    */     //   81: aload 4
/*    */     //   83: invokevirtual 65	scala/collection/mutable/StringBuilder:append	(Ljava/lang/Object;)Lscala/collection/mutable/StringBuilder;
/*    */     //   86: ldc -66
/*    */     //   88: invokevirtual 65	scala/collection/mutable/StringBuilder:append	(Ljava/lang/Object;)Lscala/collection/mutable/StringBuilder;
/*    */     //   91: invokevirtual 69	scala/collection/mutable/StringBuilder:toString	()Ljava/lang/String;
/*    */     //   94: invokevirtual 184	java/lang/StringBuffer:append	(Ljava/lang/String;)Ljava/lang/StringBuffer;
/*    */     //   97: pop
/*    */     //   98: aload 9
/*    */     //   100: new 58	scala/collection/mutable/StringBuilder
/*    */     //   103: dup
/*    */     //   104: invokespecial 59	scala/collection/mutable/StringBuilder:<init>	()V
/*    */     //   107: ldc -64
/*    */     //   109: invokevirtual 65	scala/collection/mutable/StringBuilder:append	(Ljava/lang/Object;)Lscala/collection/mutable/StringBuilder;
/*    */     //   112: aload_2
/*    */     //   113: invokevirtual 65	scala/collection/mutable/StringBuilder:append	(Ljava/lang/Object;)Lscala/collection/mutable/StringBuilder;
/*    */     //   116: ldc -62
/*    */     //   118: invokevirtual 65	scala/collection/mutable/StringBuilder:append	(Ljava/lang/Object;)Lscala/collection/mutable/StringBuilder;
/*    */     //   121: invokevirtual 69	scala/collection/mutable/StringBuilder:toString	()Ljava/lang/String;
/*    */     //   124: invokevirtual 184	java/lang/StringBuffer:append	(Ljava/lang/String;)Ljava/lang/StringBuffer;
/*    */     //   127: pop
/*    */     //   128: aload_1
/*    */     //   129: invokevirtual 197	com/yisa/engine/common/InputBean:carYear	()[Ljava/lang/String;
/*    */     //   132: aconst_null
/*    */     //   133: if_acmpeq +116 -> 249
/*    */     //   136: aload_1
/*    */     //   137: invokevirtual 197	com/yisa/engine/common/InputBean:carYear	()[Ljava/lang/String;
/*    */     //   140: iconst_0
/*    */     //   141: aaload
/*    */     //   142: ldc -57
/*    */     //   144: astore 10
/*    */     //   146: dup
/*    */     //   147: ifnonnull +12 -> 159
/*    */     //   150: pop
/*    */     //   151: aload 10
/*    */     //   153: ifnull +96 -> 249
/*    */     //   156: goto +11 -> 167
/*    */     //   159: aload 10
/*    */     //   161: invokevirtual 203	java/lang/Object:equals	(Ljava/lang/Object;)Z
/*    */     //   164: ifne +85 -> 249
/*    */     //   167: aload_1
/*    */     //   168: invokevirtual 197	com/yisa/engine/common/InputBean:carYear	()[Ljava/lang/String;
/*    */     //   171: iconst_0
/*    */     //   172: aaload
/*    */     //   173: ldc -51
/*    */     //   175: astore 11
/*    */     //   177: dup
/*    */     //   178: ifnonnull +12 -> 190
/*    */     //   181: pop
/*    */     //   182: aload 11
/*    */     //   184: ifnull +65 -> 249
/*    */     //   187: goto +11 -> 198
/*    */     //   190: aload 11
/*    */     //   192: invokevirtual 203	java/lang/Object:equals	(Ljava/lang/Object;)Z
/*    */     //   195: ifne +54 -> 249
/*    */     //   198: getstatic 56	scala/Predef$:MODULE$	Lscala/Predef$;
/*    */     //   201: aload_1
/*    */     //   202: invokevirtual 197	com/yisa/engine/common/InputBean:carYear	()[Ljava/lang/String;
/*    */     //   205: checkcast 207	[Ljava/lang/Object;
/*    */     //   208: invokevirtual 211	scala/Predef$:refArrayOps	([Ljava/lang/Object;)Lscala/collection/mutable/ArrayOps;
/*    */     //   211: new 213	com/yisa/engine/branch/SparkEngineV2ForExample$$anonfun$1
/*    */     //   214: dup
/*    */     //   215: aload_0
/*    */     //   216: invokespecial 214	com/yisa/engine/branch/SparkEngineV2ForExample$$anonfun$1:<init>	(Lcom/yisa/engine/branch/SparkEngineV2ForExample;)V
/*    */     //   219: invokeinterface 220 2 0
/*    */     //   224: checkcast 24	java/lang/String
/*    */     //   227: astore 12
/*    */     //   229: aload 9
/*    */     //   231: ldc -34
/*    */     //   233: invokevirtual 184	java/lang/StringBuffer:append	(Ljava/lang/String;)Ljava/lang/StringBuffer;
/*    */     //   236: aload 12
/*    */     //   238: invokevirtual 184	java/lang/StringBuffer:append	(Ljava/lang/String;)Ljava/lang/StringBuffer;
/*    */     //   241: ldc -32
/*    */     //   243: invokevirtual 184	java/lang/StringBuffer:append	(Ljava/lang/String;)Ljava/lang/StringBuffer;
/*    */     //   246: goto +6 -> 252
/*    */     //   249: getstatic 96	scala/runtime/BoxedUnit:UNIT	Lscala/runtime/BoxedUnit;
/*    */     //   252: pop
/*    */     //   253: aload 7
/*    */     //   255: ifnonnull +9 -> 264
/*    */     //   258: getstatic 96	scala/runtime/BoxedUnit:UNIT	Lscala/runtime/BoxedUnit;
/*    */     //   261: goto +20 -> 281
/*    */     //   264: aload 9
/*    */     //   266: ldc -30
/*    */     //   268: invokevirtual 184	java/lang/StringBuffer:append	(Ljava/lang/String;)Ljava/lang/StringBuffer;
/*    */     //   271: aload 7
/*    */     //   273: invokevirtual 184	java/lang/StringBuffer:append	(Ljava/lang/String;)Ljava/lang/StringBuffer;
/*    */     //   276: ldc -28
/*    */     //   278: invokevirtual 184	java/lang/StringBuffer:append	(Ljava/lang/String;)Ljava/lang/StringBuffer;
/*    */     //   281: pop
/*    */     //   282: aload 8
/*    */     //   284: ifnonnull +9 -> 293
/*    */     //   287: getstatic 96	scala/runtime/BoxedUnit:UNIT	Lscala/runtime/BoxedUnit;
/*    */     //   290: goto +20 -> 310
/*    */     //   293: aload 9
/*    */     //   295: ldc -26
/*    */     //   297: invokevirtual 184	java/lang/StringBuffer:append	(Ljava/lang/String;)Ljava/lang/StringBuffer;
/*    */     //   300: aload 8
/*    */     //   302: invokevirtual 184	java/lang/StringBuffer:append	(Ljava/lang/String;)Ljava/lang/StringBuffer;
/*    */     //   305: ldc -28
/*    */     //   307: invokevirtual 184	java/lang/StringBuffer:append	(Ljava/lang/String;)Ljava/lang/StringBuffer;
/*    */     //   310: pop
/*    */     //   311: aload 6
/*    */     //   313: aconst_null
/*    */     //   314: if_acmpeq +90 -> 404
/*    */     //   317: aload 6
/*    */     //   319: arraylength
/*    */     //   320: iconst_0
/*    */     //   321: if_icmple +83 -> 404
/*    */     //   324: aload_1
/*    */     //   325: invokevirtual 161	com/yisa/engine/common/InputBean:carModel	()[Ljava/lang/String;
/*    */     //   328: iconst_0
/*    */     //   329: aaload
/*    */     //   330: ldc -51
/*    */     //   332: astore 13
/*    */     //   334: dup
/*    */     //   335: ifnonnull +12 -> 347
/*    */     //   338: pop
/*    */     //   339: aload 13
/*    */     //   341: ifnull +63 -> 404
/*    */     //   344: goto +11 -> 355
/*    */     //   347: aload 13
/*    */     //   349: invokevirtual 203	java/lang/Object:equals	(Ljava/lang/Object;)Z
/*    */     //   352: ifne +52 -> 404
/*    */     //   355: getstatic 56	scala/Predef$:MODULE$	Lscala/Predef$;
/*    */     //   358: aload 6
/*    */     //   360: checkcast 207	[Ljava/lang/Object;
/*    */     //   363: invokevirtual 211	scala/Predef$:refArrayOps	([Ljava/lang/Object;)Lscala/collection/mutable/ArrayOps;
/*    */     //   366: new 232	com/yisa/engine/branch/SparkEngineV2ForExample$$anonfun$2
/*    */     //   369: dup
/*    */     //   370: aload_0
/*    */     //   371: invokespecial 233	com/yisa/engine/branch/SparkEngineV2ForExample$$anonfun$2:<init>	(Lcom/yisa/engine/branch/SparkEngineV2ForExample;)V
/*    */     //   374: invokeinterface 220 2 0
/*    */     //   379: checkcast 24	java/lang/String
/*    */     //   382: astore 14
/*    */     //   384: aload 9
/*    */     //   386: ldc -21
/*    */     //   388: invokevirtual 184	java/lang/StringBuffer:append	(Ljava/lang/String;)Ljava/lang/StringBuffer;
/*    */     //   391: aload 14
/*    */     //   393: invokevirtual 184	java/lang/StringBuffer:append	(Ljava/lang/String;)Ljava/lang/StringBuffer;
/*    */     //   396: ldc -32
/*    */     //   398: invokevirtual 184	java/lang/StringBuffer:append	(Ljava/lang/String;)Ljava/lang/StringBuffer;
/*    */     //   401: goto +6 -> 407
/*    */     //   404: getstatic 96	scala/runtime/BoxedUnit:UNIT	Lscala/runtime/BoxedUnit;
/*    */     //   407: pop
/*    */     //   408: aload 5
/*    */     //   410: ifnull +57 -> 467
/*    */     //   413: aload 5
/*    */     //   415: ldc -57
/*    */     //   417: astore 15
/*    */     //   419: dup
/*    */     //   420: ifnonnull +12 -> 432
/*    */     //   423: pop
/*    */     //   424: aload 15
/*    */     //   426: ifnull +41 -> 467
/*    */     //   429: goto +11 -> 440
/*    */     //   432: aload 15
/*    */     //   434: invokevirtual 203	java/lang/Object:equals	(Ljava/lang/Object;)Z
/*    */     //   437: ifne +30 -> 467
/*    */     //   440: aload 5
/*    */     //   442: ldc -51
/*    */     //   444: astore 16
/*    */     //   446: dup
/*    */     //   447: ifnonnull +12 -> 459
/*    */     //   450: pop
/*    */     //   451: aload 16
/*    */     //   453: ifnull +14 -> 467
/*    */     //   456: goto +17 -> 473
/*    */     //   459: aload 16
/*    */     //   461: invokevirtual 203	java/lang/Object:equals	(Ljava/lang/Object;)Z
/*    */     //   464: ifeq +9 -> 473
/*    */     //   467: getstatic 96	scala/runtime/BoxedUnit:UNIT	Lscala/runtime/BoxedUnit;
/*    */     //   470: goto +15 -> 485
/*    */     //   473: aload 9
/*    */     //   475: ldc -19
/*    */     //   477: invokevirtual 184	java/lang/StringBuffer:append	(Ljava/lang/String;)Ljava/lang/StringBuffer;
/*    */     //   480: aload 5
/*    */     //   482: invokevirtual 184	java/lang/StringBuffer:append	(Ljava/lang/String;)Ljava/lang/StringBuffer;
/*    */     //   485: pop
/*    */     //   486: aload 9
/*    */     //   488: ldc -17
/*    */     //   490: invokevirtual 184	java/lang/StringBuffer:append	(Ljava/lang/String;)Ljava/lang/StringBuffer;
/*    */     //   493: pop
/*    */     //   494: iload_3
/*    */     //   495: ifeq +21 -> 516
/*    */     //   498: aload 9
/*    */     //   500: ldc -15
/*    */     //   502: invokevirtual 184	java/lang/StringBuffer:append	(Ljava/lang/String;)Ljava/lang/StringBuffer;
/*    */     //   505: pop
/*    */     //   506: aload 9
/*    */     //   508: ldc -13
/*    */     //   510: invokevirtual 184	java/lang/StringBuffer:append	(Ljava/lang/String;)Ljava/lang/StringBuffer;
/*    */     //   513: goto +6 -> 519
/*    */     //   516: getstatic 96	scala/runtime/BoxedUnit:UNIT	Lscala/runtime/BoxedUnit;
/*    */     //   519: pop
/*    */     //   520: aload 9
/*    */     //   522: ldc -11
/*    */     //   524: invokevirtual 184	java/lang/StringBuffer:append	(Ljava/lang/String;)Ljava/lang/StringBuffer;
/*    */     //   527: pop
/*    */     //   528: aload 9
/*    */     //   530: invokevirtual 246	java/lang/StringBuffer:toString	()Ljava/lang/String;
/*    */     //   533: areturn
/*    */     // Line number table:
/*    */     //   Java source line #99	-> byte code offset #0
/*    */     //   Java source line #101	-> byte code offset #6
/*    */     //   Java source line #103	-> byte code offset #12
/*    */     //   Java source line #105	-> byte code offset #18
/*    */     //   Java source line #106	-> byte code offset #30
/*    */     //   Java source line #108	-> byte code offset #42
/*    */     //   Java source line #110	-> byte code offset #51
/*    */     //   Java source line #111	-> byte code offset #59
/*    */     //   Java source line #112	-> byte code offset #67
/*    */     //   Java source line #114	-> byte code offset #98
/*    */     //   Java source line #116	-> byte code offset #128
/*    */     //   Java source line #117	-> byte code offset #198
/*    */     //   Java source line #118	-> byte code offset #229
/*    */     //   Java source line #116	-> byte code offset #249
/*    */     //   Java source line #121	-> byte code offset #253
/*    */     //   Java source line #122	-> byte code offset #264
/*    */     //   Java source line #121	-> byte code offset #281
/*    */     //   Java source line #125	-> byte code offset #282
/*    */     //   Java source line #126	-> byte code offset #293
/*    */     //   Java source line #125	-> byte code offset #310
/*    */     //   Java source line #129	-> byte code offset #311
/*    */     //   Java source line #130	-> byte code offset #355
/*    */     //   Java source line #131	-> byte code offset #384
/*    */     //   Java source line #129	-> byte code offset #404
/*    */     //   Java source line #134	-> byte code offset #408
/*    */     //   Java source line #135	-> byte code offset #473
/*    */     //   Java source line #134	-> byte code offset #485
/*    */     //   Java source line #139	-> byte code offset #486
/*    */     //   Java source line #141	-> byte code offset #494
/*    */     //   Java source line #142	-> byte code offset #498
/*    */     //   Java source line #143	-> byte code offset #506
/*    */     //   Java source line #141	-> byte code offset #516
/*    */     //   Java source line #146	-> byte code offset #520
/*    */     //   Java source line #147	-> byte code offset #528
/*    */     // Local variable table:
/*    */     //   start	length	slot	name	signature
/*    */     //   0	534	0	this	SparkEngineV2ForExample
/*    */     //   0	534	1	map	InputBean
/*    */     //   0	534	2	tableName	String
/*    */     //   0	534	3	similarityLimit	boolean
/*    */     //   6	527	4	feature	String
/*    */     //   12	521	5	carBrand	String
/*    */     //   18	515	6	carModel	String[]
/*    */     //   30	503	7	startTime	String
/*    */     //   42	491	8	endTime	String
/*    */     //   51	482	9	sb	StringBuffer
/*    */     //   229	17	12	m	String
/*    */     //   384	17	14	m	String
/*    */   }
/*    */ }


/* Location:              E:\BaiduYunDownload\伊萨时期的一些代码\SparkEngine终极版\jars\YISAEngineBySpark2-4.0.6-SNAPSHOT-jar-with-dependencies.jar!\com\yisa\engine\branch\SparkEngineV2ForExample.class
 * Java compiler version: 6 (50.0)
 * JD-Core Version:       0.7.1
 */