/*    */ package com.yisa.engine.branch;
/*    */ 
/*    */ import com.yisa.engine.common.InputBean;
/*    */ import java.sql.Connection;
/*    */ import java.sql.PreparedStatement;
/*    */ import org.apache.spark.sql.Row;
/*    */ import org.apache.spark.sql.SparkSession;
/*    */ import scala.Predef.;
/*    */ import scala.Serializable;
/*    */ import scala.collection.Iterator;
/*    */ import scala.collection.mutable.StringBuilder;
/*    */ import scala.runtime.AbstractFunction1;
/*    */ import scala.runtime.AbstractFunction2;
/*    */ import scala.runtime.IntRef;
/*    */ import scala.runtime.ObjectRef;
/*    */ 
/*    */ 
/*    */ 
/*    */ @scala.reflect.ScalaSignature(bytes="\006\001A3A!\001\002\001\027\ti2\013]1sW\026sw-\0338f-J2uN\035$sKF,XM\034;ms\016\013'O\003\002\004\t\0051!M]1oG\"T!!\002\004\002\r\025tw-\0338f\025\t9\001\"\001\003zSN\f'\"A\005\002\007\r|Wn\001\001\024\005\001a\001CA\007\021\033\005q!\"A\b\002\013M\034\027\r\\1\n\005Eq!AB!osJ+g\rC\003\024\001\021\005A#\001\004=S:LGO\020\013\002+A\021a\003A\007\002\005!9\001\004\001a\001\n\003I\022aA7baV\t!\004\005\002\034=5\tAD\003\002\036\t\00511m\\7n_:L!a\b\017\003\023%s\007/\036;CK\006t\007bB\021\001\001\004%\tAI\001\b[\006\004x\fJ3r)\t\031c\005\005\002\016I%\021QE\004\002\005+:LG\017C\004(A\005\005\t\031\001\016\002\007a$\023\007\003\004*\001\001\006KAG\001\005[\006\004\b\005C\003,\001\021\005A&A\007Ge\026\fX/\0328uYf\034\025M\035\013\007G5ZDI\022%\t\0139R\003\031A\030\002\031M\004\030M]6TKN\034\030n\0348\021\005AJT\"A\031\013\005I\032\024aA:rY*\021A'N\001\006gB\f'o\033\006\003m]\na!\0319bG\",'\"\001\035\002\007=\024x-\003\002;c\ta1\013]1sWN+7o]5p]\")AH\013a\001{\005!A.\0338f!\tq\024I\004\002\016%\021\001ID\001\007!J,G-\0324\n\005\t\033%AB*ue&twM\003\002A\035!)QI\013a\001{\005IA/\0312mK:\013W.\032\005\006\017*\002\r!P\001\fe\026\034X\017\034;UC\ndW\rC\003JU\001\007Q(\001\006{W\"{7\017\0369peRDQa\023\001\005\0021\013QbZ:p]\006\023(/Y=Gk:\034GcA\037N\037\")aJ\023a\001{\005\021!n\035\005\006\013*\003\r!\020")
/*    */ public class SparkEngineV2ForFrequentlyCar
/*    */ {
/* 22 */   public InputBean map() { return this.map; } public void map_$eq(InputBean x$1) { this.map = x$1; } private InputBean map = null;
/*    */   
/*    */ 
/*    */   public void FrequentlyCar(SparkSession sparkSession, String line, String tableName, String resultTable, final String zkHostport)
/*    */   {
/* 27 */     final String jdbcTable = resultTable;
/*    */     
/* 29 */     String[] line_arr = line.split("\\|");
/*    */     
/* 31 */     final String jobId = line_arr[1];
/* 32 */     String params = line_arr[2];
/*    */     
/*    */ 
/*    */ 
/* 36 */     String sqlStr = gsonArrayFunc(params, tableName);
/*    */     
/* 38 */     Predef..MODULE$.println(sqlStr);
/*    */     
/* 40 */     org.apache.spark.sql.Dataset resultData = sparkSession.sql(sqlStr);
/*    */     
/* 42 */     Predef..MODULE$.println(new StringBuilder().append("SQL--------------:").append(sqlStr).toString());
/*    */     
/*    */ 
/*    */ 
/* 46 */     int count2 = map().count();
/*    */     
/*    */ 
/*    */ 
/*    */ 
/*    */ 
/* 52 */     resultData.foreachPartition(new AbstractFunction1() { public static final long serialVersionUID = 0L;
/*    */       
/* 54 */       public final void apply(Iterator<Row> data) { Connection conn = com.yisa.engine.db.MySQLConnectManager..MODULE$.getConnet(zkHostport);
/* 55 */         conn.setAutoCommit(false);
/* 56 */         String sql = new StringBuilder().append("insert into ").append(jdbcTable).append(" (s_id,count,j_id,l_id) values(?,?,?,?)").toString();
/* 57 */         final ObjectRef pstmt = ObjectRef.create(conn.prepareStatement(sql));
/* 58 */         final IntRef count = IntRef.create(0);
/*    */         
/* 60 */         data.foreach(new AbstractFunction1()
/*    */         {
/*    */           public static final long serialVersionUID = 0L;
/*    */           
/*    */           public final void apply(Row t) {
/* 65 */             ((PreparedStatement)pstmt.elem).setString(1, t.apply(0).toString());
/* 66 */             ((PreparedStatement)pstmt.elem).setInt(2, new scala.collection.immutable.StringOps(Predef..MODULE$.augmentString(t.apply(1).toString())).toInt());
/* 67 */             ((PreparedStatement)pstmt.elem).setString(3, SparkEngineV2ForFrequentlyCar..anonfun.FrequentlyCar.1.this.jobId$1);
/* 68 */             if (t.apply(2) == null)
/*    */             {
/*    */ 
/* 71 */               ((PreparedStatement)pstmt.elem).setString(4, "");
/*    */             } else {
/* 69 */               ((PreparedStatement)pstmt.elem).setString(4, t.apply(2).toString());
/*    */             }
/*    */             
/*    */ 
/* 73 */             ((PreparedStatement)pstmt.elem).addBatch();
/* 74 */             count.elem += 1;
/*    */           }
/*    */           
/*    */ 
/* 78 */         });
/* 79 */         String sql2 = "insert into pfgc_count (j_id,count) values(?,?)";
/* 80 */         PreparedStatement pstmt2 = conn.prepareStatement(sql2);
/*    */         
/* 82 */         if (count.elem == 0) {
/* 83 */           count.elem = -1;
/*    */         }
/* 85 */         pstmt2.setString(1, jobId);
/* 86 */         pstmt2.setInt(2, count.elem);
/* 87 */         pstmt2.executeUpdate();
/* 88 */         pstmt2.close();
/*    */         
/* 90 */         ((PreparedStatement)pstmt.elem).executeBatch();
/* 91 */         conn.commit();
/* 92 */         ((PreparedStatement)pstmt.elem).close();
/* 93 */         conn.close();
/*    */       }
/*    */     });
/*    */   }
/*    */   
/*    */   /* Error */
/*    */   public String gsonArrayFunc(String js, String tableName)
/*    */   {
/*    */     // Byte code:
/*    */     //   0: new 102	com/google/gson/Gson
/*    */     //   3: dup
/*    */     //   4: invokespecial 103	com/google/gson/Gson:<init>	()V
/*    */     //   7: astore_3
/*    */     //   8: new 105	com/yisa/engine/branch/SparkEngineV2ForFrequentlyCar$$anon$1
/*    */     //   11: dup
/*    */     //   12: aload_0
/*    */     //   13: invokespecial 108	com/yisa/engine/branch/SparkEngineV2ForFrequentlyCar$$anon$1:<init>	(Lcom/yisa/engine/branch/SparkEngineV2ForFrequentlyCar;)V
/*    */     //   16: invokevirtual 112	com/yisa/engine/branch/SparkEngineV2ForFrequentlyCar$$anon$1:getType	()Ljava/lang/reflect/Type;
/*    */     //   19: astore 4
/*    */     //   21: aload_0
/*    */     //   22: aload_3
/*    */     //   23: aload_1
/*    */     //   24: aload 4
/*    */     //   26: invokevirtual 116	com/google/gson/Gson:fromJson	(Ljava/lang/String;Ljava/lang/reflect/Type;)Ljava/lang/Object;
/*    */     //   29: checkcast 68	com/yisa/engine/common/InputBean
/*    */     //   32: invokevirtual 118	com/yisa/engine/branch/SparkEngineV2ForFrequentlyCar:map_$eq	(Lcom/yisa/engine/common/InputBean;)V
/*    */     //   35: getstatic 123	com/yisa/engine/uitl/TimeUtil$:MODULE$	Lcom/yisa/engine/uitl/TimeUtil$;
/*    */     //   38: aload_0
/*    */     //   39: invokevirtual 66	com/yisa/engine/branch/SparkEngineV2ForFrequentlyCar:map	()Lcom/yisa/engine/common/InputBean;
/*    */     //   42: invokevirtual 126	com/yisa/engine/common/InputBean:startTime	()Ljava/lang/String;
/*    */     //   45: invokevirtual 130	com/yisa/engine/uitl/TimeUtil$:getTimestampLong	(Ljava/lang/String;)J
/*    */     //   48: lstore 5
/*    */     //   50: getstatic 123	com/yisa/engine/uitl/TimeUtil$:MODULE$	Lcom/yisa/engine/uitl/TimeUtil$;
/*    */     //   53: aload_0
/*    */     //   54: invokevirtual 66	com/yisa/engine/branch/SparkEngineV2ForFrequentlyCar:map	()Lcom/yisa/engine/common/InputBean;
/*    */     //   57: invokevirtual 133	com/yisa/engine/common/InputBean:endTime	()Ljava/lang/String;
/*    */     //   60: invokevirtual 130	com/yisa/engine/uitl/TimeUtil$:getTimestampLong	(Ljava/lang/String;)J
/*    */     //   63: lstore 7
/*    */     //   65: getstatic 123	com/yisa/engine/uitl/TimeUtil$:MODULE$	Lcom/yisa/engine/uitl/TimeUtil$;
/*    */     //   68: aload_0
/*    */     //   69: invokevirtual 66	com/yisa/engine/branch/SparkEngineV2ForFrequentlyCar:map	()Lcom/yisa/engine/common/InputBean;
/*    */     //   72: invokevirtual 126	com/yisa/engine/common/InputBean:startTime	()Ljava/lang/String;
/*    */     //   75: invokevirtual 137	com/yisa/engine/uitl/TimeUtil$:getDateId	(Ljava/lang/String;)I
/*    */     //   78: istore 9
/*    */     //   80: getstatic 123	com/yisa/engine/uitl/TimeUtil$:MODULE$	Lcom/yisa/engine/uitl/TimeUtil$;
/*    */     //   83: aload_0
/*    */     //   84: invokevirtual 66	com/yisa/engine/branch/SparkEngineV2ForFrequentlyCar:map	()Lcom/yisa/engine/common/InputBean;
/*    */     //   87: invokevirtual 133	com/yisa/engine/common/InputBean:endTime	()Ljava/lang/String;
/*    */     //   90: invokevirtual 137	com/yisa/engine/uitl/TimeUtil$:getDateId	(Ljava/lang/String;)I
/*    */     //   93: istore 10
/*    */     //   95: aload_0
/*    */     //   96: invokevirtual 66	com/yisa/engine/branch/SparkEngineV2ForFrequentlyCar:map	()Lcom/yisa/engine/common/InputBean;
/*    */     //   99: invokevirtual 141	com/yisa/engine/common/InputBean:locationId	()[Ljava/lang/String;
/*    */     //   102: astore 11
/*    */     //   104: aload_0
/*    */     //   105: invokevirtual 66	com/yisa/engine/branch/SparkEngineV2ForFrequentlyCar:map	()Lcom/yisa/engine/common/InputBean;
/*    */     //   108: invokevirtual 144	com/yisa/engine/common/InputBean:carModel	()[Ljava/lang/String;
/*    */     //   111: astore 12
/*    */     //   113: aload_0
/*    */     //   114: invokevirtual 66	com/yisa/engine/branch/SparkEngineV2ForFrequentlyCar:map	()Lcom/yisa/engine/common/InputBean;
/*    */     //   117: invokevirtual 147	com/yisa/engine/common/InputBean:carBrand	()Ljava/lang/String;
/*    */     //   120: astore 13
/*    */     //   122: aload_0
/*    */     //   123: invokevirtual 66	com/yisa/engine/branch/SparkEngineV2ForFrequentlyCar:map	()Lcom/yisa/engine/common/InputBean;
/*    */     //   126: invokevirtual 150	com/yisa/engine/common/InputBean:carYear	()[Ljava/lang/String;
/*    */     //   129: astore 14
/*    */     //   131: aload_0
/*    */     //   132: invokevirtual 66	com/yisa/engine/branch/SparkEngineV2ForFrequentlyCar:map	()Lcom/yisa/engine/common/InputBean;
/*    */     //   135: invokevirtual 153	com/yisa/engine/common/InputBean:carColor	()Ljava/lang/String;
/*    */     //   138: astore 15
/*    */     //   140: aload_0
/*    */     //   141: invokevirtual 66	com/yisa/engine/branch/SparkEngineV2ForFrequentlyCar:map	()Lcom/yisa/engine/common/InputBean;
/*    */     //   144: invokevirtual 156	com/yisa/engine/common/InputBean:plateNumber	()Ljava/lang/String;
/*    */     //   147: astore 16
/*    */     //   149: aload_0
/*    */     //   150: invokevirtual 66	com/yisa/engine/branch/SparkEngineV2ForFrequentlyCar:map	()Lcom/yisa/engine/common/InputBean;
/*    */     //   153: invokevirtual 72	com/yisa/engine/common/InputBean:count	()I
/*    */     //   156: istore 17
/*    */     //   158: new 158	java/lang/StringBuffer
/*    */     //   161: dup
/*    */     //   162: invokespecial 159	java/lang/StringBuffer:<init>	()V
/*    */     //   165: astore 18
/*    */     //   167: aload 18
/*    */     //   169: ldc -95
/*    */     //   171: invokevirtual 164	java/lang/StringBuffer:append	(Ljava/lang/String;)Ljava/lang/StringBuffer;
/*    */     //   174: pop
/*    */     //   175: aload 18
/*    */     //   177: ldc -90
/*    */     //   179: invokevirtual 164	java/lang/StringBuffer:append	(Ljava/lang/String;)Ljava/lang/StringBuffer;
/*    */     //   182: aload_2
/*    */     //   183: invokevirtual 164	java/lang/StringBuffer:append	(Ljava/lang/String;)Ljava/lang/StringBuffer;
/*    */     //   186: pop
/*    */     //   187: aload 18
/*    */     //   189: ldc -88
/*    */     //   191: invokevirtual 164	java/lang/StringBuffer:append	(Ljava/lang/String;)Ljava/lang/StringBuffer;
/*    */     //   194: pop
/*    */     //   195: lload 5
/*    */     //   197: lconst_0
/*    */     //   198: lcmp
/*    */     //   199: ifeq +18 -> 217
/*    */     //   202: aload 18
/*    */     //   204: ldc -86
/*    */     //   206: invokevirtual 164	java/lang/StringBuffer:append	(Ljava/lang/String;)Ljava/lang/StringBuffer;
/*    */     //   209: lload 5
/*    */     //   211: invokevirtual 173	java/lang/StringBuffer:append	(J)Ljava/lang/StringBuffer;
/*    */     //   214: goto +6 -> 220
/*    */     //   217: getstatic 179	scala/runtime/BoxedUnit:UNIT	Lscala/runtime/BoxedUnit;
/*    */     //   220: pop
/*    */     //   221: lload 7
/*    */     //   223: lconst_0
/*    */     //   224: lcmp
/*    */     //   225: ifeq +18 -> 243
/*    */     //   228: aload 18
/*    */     //   230: ldc -75
/*    */     //   232: invokevirtual 164	java/lang/StringBuffer:append	(Ljava/lang/String;)Ljava/lang/StringBuffer;
/*    */     //   235: lload 7
/*    */     //   237: invokevirtual 173	java/lang/StringBuffer:append	(J)Ljava/lang/StringBuffer;
/*    */     //   240: goto +6 -> 246
/*    */     //   243: getstatic 179	scala/runtime/BoxedUnit:UNIT	Lscala/runtime/BoxedUnit;
/*    */     //   246: pop
/*    */     //   247: aload 11
/*    */     //   249: aconst_null
/*    */     //   250: if_acmpeq +95 -> 345
/*    */     //   253: aload 11
/*    */     //   255: arraylength
/*    */     //   256: iconst_0
/*    */     //   257: if_icmple +88 -> 345
/*    */     //   260: getstatic 38	scala/Predef$:MODULE$	Lscala/Predef$;
/*    */     //   263: getstatic 38	scala/Predef$:MODULE$	Lscala/Predef$;
/*    */     //   266: aload 11
/*    */     //   268: checkcast 183	[Ljava/lang/Object;
/*    */     //   271: invokevirtual 187	scala/Predef$:refArrayOps	([Ljava/lang/Object;)Lscala/collection/mutable/ArrayOps;
/*    */     //   274: new 189	com/yisa/engine/branch/SparkEngineV2ForFrequentlyCar$$anonfun$1
/*    */     //   277: dup
/*    */     //   278: aload_0
/*    */     //   279: invokespecial 190	com/yisa/engine/branch/SparkEngineV2ForFrequentlyCar$$anonfun$1:<init>	(Lcom/yisa/engine/branch/SparkEngineV2ForFrequentlyCar;)V
/*    */     //   282: getstatic 195	scala/Array$:MODULE$	Lscala/Array$;
/*    */     //   285: getstatic 200	scala/reflect/ClassTag$:MODULE$	Lscala/reflect/ClassTag$;
/*    */     //   288: ldc 24
/*    */     //   290: invokevirtual 204	scala/reflect/ClassTag$:apply	(Ljava/lang/Class;)Lscala/reflect/ClassTag;
/*    */     //   293: invokevirtual 208	scala/Array$:canBuildFrom	(Lscala/reflect/ClassTag;)Lscala/collection/generic/CanBuildFrom;
/*    */     //   296: invokeinterface 213 3 0
/*    */     //   301: checkcast 183	[Ljava/lang/Object;
/*    */     //   304: invokevirtual 187	scala/Predef$:refArrayOps	([Ljava/lang/Object;)Lscala/collection/mutable/ArrayOps;
/*    */     //   307: new 215	com/yisa/engine/branch/SparkEngineV2ForFrequentlyCar$$anonfun$2
/*    */     //   310: dup
/*    */     //   311: aload_0
/*    */     //   312: invokespecial 216	com/yisa/engine/branch/SparkEngineV2ForFrequentlyCar$$anonfun$2:<init>	(Lcom/yisa/engine/branch/SparkEngineV2ForFrequentlyCar;)V
/*    */     //   315: invokeinterface 220 2 0
/*    */     //   320: checkcast 24	java/lang/String
/*    */     //   323: astore 19
/*    */     //   325: aload 18
/*    */     //   327: ldc -34
/*    */     //   329: invokevirtual 164	java/lang/StringBuffer:append	(Ljava/lang/String;)Ljava/lang/StringBuffer;
/*    */     //   332: aload 19
/*    */     //   334: invokevirtual 164	java/lang/StringBuffer:append	(Ljava/lang/String;)Ljava/lang/StringBuffer;
/*    */     //   337: ldc -32
/*    */     //   339: invokevirtual 164	java/lang/StringBuffer:append	(Ljava/lang/String;)Ljava/lang/StringBuffer;
/*    */     //   342: goto +6 -> 348
/*    */     //   345: getstatic 179	scala/runtime/BoxedUnit:UNIT	Lscala/runtime/BoxedUnit;
/*    */     //   348: pop
/*    */     //   349: aload 12
/*    */     //   351: aconst_null
/*    */     //   352: if_acmpeq +59 -> 411
/*    */     //   355: aload 12
/*    */     //   357: arraylength
/*    */     //   358: iconst_0
/*    */     //   359: if_icmple +52 -> 411
/*    */     //   362: getstatic 38	scala/Predef$:MODULE$	Lscala/Predef$;
/*    */     //   365: aload 12
/*    */     //   367: checkcast 183	[Ljava/lang/Object;
/*    */     //   370: invokevirtual 187	scala/Predef$:refArrayOps	([Ljava/lang/Object;)Lscala/collection/mutable/ArrayOps;
/*    */     //   373: new 226	com/yisa/engine/branch/SparkEngineV2ForFrequentlyCar$$anonfun$3
/*    */     //   376: dup
/*    */     //   377: aload_0
/*    */     //   378: invokespecial 227	com/yisa/engine/branch/SparkEngineV2ForFrequentlyCar$$anonfun$3:<init>	(Lcom/yisa/engine/branch/SparkEngineV2ForFrequentlyCar;)V
/*    */     //   381: invokeinterface 220 2 0
/*    */     //   386: checkcast 24	java/lang/String
/*    */     //   389: astore 20
/*    */     //   391: aload 18
/*    */     //   393: ldc -27
/*    */     //   395: invokevirtual 164	java/lang/StringBuffer:append	(Ljava/lang/String;)Ljava/lang/StringBuffer;
/*    */     //   398: aload 20
/*    */     //   400: invokevirtual 164	java/lang/StringBuffer:append	(Ljava/lang/String;)Ljava/lang/StringBuffer;
/*    */     //   403: ldc -32
/*    */     //   405: invokevirtual 164	java/lang/StringBuffer:append	(Ljava/lang/String;)Ljava/lang/StringBuffer;
/*    */     //   408: goto +6 -> 414
/*    */     //   411: getstatic 179	scala/runtime/BoxedUnit:UNIT	Lscala/runtime/BoxedUnit;
/*    */     //   414: pop
/*    */     //   415: aload 14
/*    */     //   417: aconst_null
/*    */     //   418: if_acmpeq +59 -> 477
/*    */     //   421: aload 14
/*    */     //   423: arraylength
/*    */     //   424: iconst_0
/*    */     //   425: if_icmple +52 -> 477
/*    */     //   428: getstatic 38	scala/Predef$:MODULE$	Lscala/Predef$;
/*    */     //   431: aload 14
/*    */     //   433: checkcast 183	[Ljava/lang/Object;
/*    */     //   436: invokevirtual 187	scala/Predef$:refArrayOps	([Ljava/lang/Object;)Lscala/collection/mutable/ArrayOps;
/*    */     //   439: new 231	com/yisa/engine/branch/SparkEngineV2ForFrequentlyCar$$anonfun$4
/*    */     //   442: dup
/*    */     //   443: aload_0
/*    */     //   444: invokespecial 232	com/yisa/engine/branch/SparkEngineV2ForFrequentlyCar$$anonfun$4:<init>	(Lcom/yisa/engine/branch/SparkEngineV2ForFrequentlyCar;)V
/*    */     //   447: invokeinterface 220 2 0
/*    */     //   452: checkcast 24	java/lang/String
/*    */     //   455: astore 21
/*    */     //   457: aload 18
/*    */     //   459: ldc -22
/*    */     //   461: invokevirtual 164	java/lang/StringBuffer:append	(Ljava/lang/String;)Ljava/lang/StringBuffer;
/*    */     //   464: aload 21
/*    */     //   466: invokevirtual 164	java/lang/StringBuffer:append	(Ljava/lang/String;)Ljava/lang/StringBuffer;
/*    */     //   469: ldc -32
/*    */     //   471: invokevirtual 164	java/lang/StringBuffer:append	(Ljava/lang/String;)Ljava/lang/StringBuffer;
/*    */     //   474: goto +6 -> 480
/*    */     //   477: getstatic 179	scala/runtime/BoxedUnit:UNIT	Lscala/runtime/BoxedUnit;
/*    */     //   480: pop
/*    */     //   481: aload 13
/*    */     //   483: ifnull +30 -> 513
/*    */     //   486: aload 13
/*    */     //   488: ldc -20
/*    */     //   490: astore 22
/*    */     //   492: dup
/*    */     //   493: ifnonnull +12 -> 505
/*    */     //   496: pop
/*    */     //   497: aload 22
/*    */     //   499: ifnull +14 -> 513
/*    */     //   502: goto +17 -> 519
/*    */     //   505: aload 22
/*    */     //   507: invokevirtual 240	java/lang/Object:equals	(Ljava/lang/Object;)Z
/*    */     //   510: ifeq +9 -> 519
/*    */     //   513: getstatic 179	scala/runtime/BoxedUnit:UNIT	Lscala/runtime/BoxedUnit;
/*    */     //   516: goto +15 -> 531
/*    */     //   519: aload 18
/*    */     //   521: ldc -14
/*    */     //   523: invokevirtual 164	java/lang/StringBuffer:append	(Ljava/lang/String;)Ljava/lang/StringBuffer;
/*    */     //   526: aload 13
/*    */     //   528: invokevirtual 164	java/lang/StringBuffer:append	(Ljava/lang/String;)Ljava/lang/StringBuffer;
/*    */     //   531: pop
/*    */     //   532: aload 15
/*    */     //   534: ifnull +30 -> 564
/*    */     //   537: aload 15
/*    */     //   539: ldc -20
/*    */     //   541: astore 23
/*    */     //   543: dup
/*    */     //   544: ifnonnull +12 -> 556
/*    */     //   547: pop
/*    */     //   548: aload 23
/*    */     //   550: ifnull +14 -> 564
/*    */     //   553: goto +17 -> 570
/*    */     //   556: aload 23
/*    */     //   558: invokevirtual 240	java/lang/Object:equals	(Ljava/lang/Object;)Z
/*    */     //   561: ifeq +9 -> 570
/*    */     //   564: getstatic 179	scala/runtime/BoxedUnit:UNIT	Lscala/runtime/BoxedUnit;
/*    */     //   567: goto +15 -> 582
/*    */     //   570: aload 18
/*    */     //   572: ldc -12
/*    */     //   574: invokevirtual 164	java/lang/StringBuffer:append	(Ljava/lang/String;)Ljava/lang/StringBuffer;
/*    */     //   577: aload 15
/*    */     //   579: invokevirtual 164	java/lang/StringBuffer:append	(Ljava/lang/String;)Ljava/lang/StringBuffer;
/*    */     //   582: pop
/*    */     //   583: aload 16
/*    */     //   585: ifnull +30 -> 615
/*    */     //   588: aload 16
/*    */     //   590: ldc -20
/*    */     //   592: astore 24
/*    */     //   594: dup
/*    */     //   595: ifnonnull +12 -> 607
/*    */     //   598: pop
/*    */     //   599: aload 24
/*    */     //   601: ifnull +14 -> 615
/*    */     //   604: goto +17 -> 621
/*    */     //   607: aload 24
/*    */     //   609: invokevirtual 240	java/lang/Object:equals	(Ljava/lang/Object;)Z
/*    */     //   612: ifeq +9 -> 621
/*    */     //   615: getstatic 179	scala/runtime/BoxedUnit:UNIT	Lscala/runtime/BoxedUnit;
/*    */     //   618: goto +79 -> 697
/*    */     //   621: aload 16
/*    */     //   623: ldc -10
/*    */     //   625: invokevirtual 250	java/lang/String:contains	(Ljava/lang/CharSequence;)Z
/*    */     //   628: ifne +13 -> 641
/*    */     //   631: aload 16
/*    */     //   633: ldc -4
/*    */     //   635: invokevirtual 250	java/lang/String:contains	(Ljava/lang/CharSequence;)Z
/*    */     //   638: ifeq +40 -> 678
/*    */     //   641: aload 18
/*    */     //   643: ldc -2
/*    */     //   645: invokevirtual 164	java/lang/StringBuffer:append	(Ljava/lang/String;)Ljava/lang/StringBuffer;
/*    */     //   648: aload 16
/*    */     //   650: ldc -10
/*    */     //   652: ldc_w 256
/*    */     //   655: invokevirtual 260	java/lang/String:replace	(Ljava/lang/CharSequence;Ljava/lang/CharSequence;)Ljava/lang/String;
/*    */     //   658: ldc -4
/*    */     //   660: ldc_w 262
/*    */     //   663: invokevirtual 260	java/lang/String:replace	(Ljava/lang/CharSequence;Ljava/lang/CharSequence;)Ljava/lang/String;
/*    */     //   666: invokevirtual 164	java/lang/StringBuffer:append	(Ljava/lang/String;)Ljava/lang/StringBuffer;
/*    */     //   669: ldc_w 264
/*    */     //   672: invokevirtual 164	java/lang/StringBuffer:append	(Ljava/lang/String;)Ljava/lang/StringBuffer;
/*    */     //   675: goto +22 -> 697
/*    */     //   678: aload 18
/*    */     //   680: ldc_w 266
/*    */     //   683: invokevirtual 164	java/lang/StringBuffer:append	(Ljava/lang/String;)Ljava/lang/StringBuffer;
/*    */     //   686: aload 16
/*    */     //   688: invokevirtual 164	java/lang/StringBuffer:append	(Ljava/lang/String;)Ljava/lang/StringBuffer;
/*    */     //   691: ldc_w 268
/*    */     //   694: invokevirtual 164	java/lang/StringBuffer:append	(Ljava/lang/String;)Ljava/lang/StringBuffer;
/*    */     //   697: pop
/*    */     //   698: lload 5
/*    */     //   700: lconst_0
/*    */     //   701: lcmp
/*    */     //   702: ifeq +19 -> 721
/*    */     //   705: aload 18
/*    */     //   707: ldc_w 270
/*    */     //   710: invokevirtual 164	java/lang/StringBuffer:append	(Ljava/lang/String;)Ljava/lang/StringBuffer;
/*    */     //   713: iload 9
/*    */     //   715: invokevirtual 273	java/lang/StringBuffer:append	(I)Ljava/lang/StringBuffer;
/*    */     //   718: goto +6 -> 724
/*    */     //   721: getstatic 179	scala/runtime/BoxedUnit:UNIT	Lscala/runtime/BoxedUnit;
/*    */     //   724: pop
/*    */     //   725: lload 7
/*    */     //   727: lconst_0
/*    */     //   728: lcmp
/*    */     //   729: ifeq +19 -> 748
/*    */     //   732: aload 18
/*    */     //   734: ldc_w 275
/*    */     //   737: invokevirtual 164	java/lang/StringBuffer:append	(Ljava/lang/String;)Ljava/lang/StringBuffer;
/*    */     //   740: iload 10
/*    */     //   742: invokevirtual 273	java/lang/StringBuffer:append	(I)Ljava/lang/StringBuffer;
/*    */     //   745: goto +6 -> 751
/*    */     //   748: getstatic 179	scala/runtime/BoxedUnit:UNIT	Lscala/runtime/BoxedUnit;
/*    */     //   751: pop
/*    */     //   752: aload 18
/*    */     //   754: ldc_w 277
/*    */     //   757: invokevirtual 164	java/lang/StringBuffer:append	(Ljava/lang/String;)Ljava/lang/StringBuffer;
/*    */     //   760: pop
/*    */     //   761: aload 18
/*    */     //   763: ldc_w 279
/*    */     //   766: invokevirtual 164	java/lang/StringBuffer:append	(Ljava/lang/String;)Ljava/lang/StringBuffer;
/*    */     //   769: iload 17
/*    */     //   771: invokevirtual 273	java/lang/StringBuffer:append	(I)Ljava/lang/StringBuffer;
/*    */     //   774: pop
/*    */     //   775: aload 18
/*    */     //   777: ldc_w 281
/*    */     //   780: invokevirtual 164	java/lang/StringBuffer:append	(Ljava/lang/String;)Ljava/lang/StringBuffer;
/*    */     //   783: pop
/*    */     //   784: aload 18
/*    */     //   786: ldc_w 283
/*    */     //   789: invokevirtual 164	java/lang/StringBuffer:append	(Ljava/lang/String;)Ljava/lang/StringBuffer;
/*    */     //   792: pop
/*    */     //   793: aload 18
/*    */     //   795: invokevirtual 284	java/lang/StringBuffer:toString	()Ljava/lang/String;
/*    */     //   798: areturn
/*    */     // Line number table:
/*    */     //   Java source line #101	-> byte code offset #0
/*    */     //   Java source line #102	-> byte code offset #8
/*    */     //   Java source line #103	-> byte code offset #21
/*    */     //   Java source line #108	-> byte code offset #35
/*    */     //   Java source line #109	-> byte code offset #50
/*    */     //   Java source line #111	-> byte code offset #65
/*    */     //   Java source line #112	-> byte code offset #80
/*    */     //   Java source line #114	-> byte code offset #95
/*    */     //   Java source line #115	-> byte code offset #104
/*    */     //   Java source line #116	-> byte code offset #113
/*    */     //   Java source line #117	-> byte code offset #122
/*    */     //   Java source line #118	-> byte code offset #131
/*    */     //   Java source line #119	-> byte code offset #140
/*    */     //   Java source line #120	-> byte code offset #149
/*    */     //   Java source line #122	-> byte code offset #158
/*    */     //   Java source line #124	-> byte code offset #167
/*    */     //   Java source line #127	-> byte code offset #175
/*    */     //   Java source line #130	-> byte code offset #187
/*    */     //   Java source line #133	-> byte code offset #195
/*    */     //   Java source line #134	-> byte code offset #202
/*    */     //   Java source line #133	-> byte code offset #217
/*    */     //   Java source line #137	-> byte code offset #221
/*    */     //   Java source line #138	-> byte code offset #228
/*    */     //   Java source line #137	-> byte code offset #243
/*    */     //   Java source line #149	-> byte code offset #247
/*    */     //   Java source line #150	-> byte code offset #260
/*    */     //   Java source line #152	-> byte code offset #325
/*    */     //   Java source line #149	-> byte code offset #345
/*    */     //   Java source line #155	-> byte code offset #349
/*    */     //   Java source line #156	-> byte code offset #362
/*    */     //   Java source line #157	-> byte code offset #391
/*    */     //   Java source line #155	-> byte code offset #411
/*    */     //   Java source line #160	-> byte code offset #415
/*    */     //   Java source line #161	-> byte code offset #428
/*    */     //   Java source line #162	-> byte code offset #457
/*    */     //   Java source line #160	-> byte code offset #477
/*    */     //   Java source line #165	-> byte code offset #481
/*    */     //   Java source line #166	-> byte code offset #519
/*    */     //   Java source line #165	-> byte code offset #531
/*    */     //   Java source line #169	-> byte code offset #532
/*    */     //   Java source line #170	-> byte code offset #570
/*    */     //   Java source line #169	-> byte code offset #582
/*    */     //   Java source line #173	-> byte code offset #583
/*    */     //   Java source line #174	-> byte code offset #621
/*    */     //   Java source line #175	-> byte code offset #641
/*    */     //   Java source line #177	-> byte code offset #678
/*    */     //   Java source line #173	-> byte code offset #697
/*    */     //   Java source line #189	-> byte code offset #698
/*    */     //   Java source line #190	-> byte code offset #705
/*    */     //   Java source line #189	-> byte code offset #721
/*    */     //   Java source line #193	-> byte code offset #725
/*    */     //   Java source line #194	-> byte code offset #732
/*    */     //   Java source line #193	-> byte code offset #748
/*    */     //   Java source line #197	-> byte code offset #752
/*    */     //   Java source line #199	-> byte code offset #761
/*    */     //   Java source line #200	-> byte code offset #775
/*    */     //   Java source line #201	-> byte code offset #784
/*    */     //   Java source line #203	-> byte code offset #793
/*    */     // Local variable table:
/*    */     //   start	length	slot	name	signature
/*    */     //   0	799	0	this	SparkEngineV2ForFrequentlyCar
/*    */     //   0	799	1	js	String
/*    */     //   0	799	2	tableName	String
/*    */     //   8	790	3	gson	com.google.gson.Gson
/*    */     //   21	777	4	mapType	java.lang.reflect.Type
/*    */     //   50	748	5	startTime	long
/*    */     //   65	733	7	endTime	long
/*    */     //   80	718	9	startTimeDateid	int
/*    */     //   95	703	10	endTimeDateid	int
/*    */     //   104	694	11	locationId	String[]
/*    */     //   113	685	12	carModel	String[]
/*    */     //   122	676	13	carBrand	String
/*    */     //   131	667	14	carYear	String[]
/*    */     //   140	658	15	carColor	String
/*    */     //   149	649	16	plateNumber	String
/*    */     //   158	640	17	count	int
/*    */     //   167	631	18	sb	StringBuffer
/*    */     //   325	17	19	l	String
/*    */     //   391	17	20	m	String
/*    */     //   457	17	21	m	String
/*    */   }
/*    */ }


/* Location:              E:\BaiduYunDownload\伊萨时期的一些代码\SparkEngine终极版\jars\YISAEngineBySpark2-4.0.6-SNAPSHOT-jar-with-dependencies.jar!\com\yisa\engine\branch\SparkEngineV2ForFrequentlyCar.class
 * Java compiler version: 6 (50.0)
 * JD-Core Version:       0.7.1
 */