package com.yisa.engine.branch;

import com.google.gson.Gson;
import com.google.gson.reflect.TypeToken;
import com.yisa.engine.common.InputBean;
import com.yisa.engine.common.Locationid_detail;
import com.yisa.engine.db.MySQLConnectManager.;
import java.sql.Connection;
import java.sql.PreparedStatement;
import java.util.ArrayList;
import java.util.List;
import org.apache.spark.sql.Row;
import scala.MatchError;
import scala.Option;
import scala.Predef.;
import scala.Predef.ArrowAssoc.;
import scala.Serializable;
import scala.Tuple2;
import scala.collection.immutable.Map;
import scala.collection.immutable.Map.;
import scala.collection.immutable.Nil.;
import scala.collection.immutable.StringOps;
import scala.collection.mutable.StringBuilder;
import scala.reflect.ScalaSignature;
import scala.runtime.AbstractFunction1;
import scala.runtime.AbstractFunction2;
import scala.runtime.BoxedUnit;
import scala.runtime.BoxesRunTime;
import scala.runtime.ObjectRef;

@ScalaSignature(bytes="\006\00193A!\001\002\001\027\tq2\013]1sW\026sw-\0338f-J2uN\035+sCZ,G\016V8hKRDWM\035\006\003\007\021\taA\031:b]\016D'BA\003\007\003\031)gnZ5oK*\021q\001C\001\005s&\034\030MC\001\n\003\r\031w.\\\002\001'\t\001A\002\005\002\016!5\taBC\001\020\003\025\0318-\0317b\023\t\tbB\001\004B]f\024VM\032\005\006'\001!\t\001F\001\007y%t\027\016\036 \025\003U\001\"A\006\001\016\003\tAQ\001\007\001\005\002e\ta\002\026:bm\026dGk\\4fi\",'\017F\003\033;-\"d\007\005\002\0167%\021AD\004\002\005+:LG\017C\003\037/\001\007q$\001\007ta\006\0248nU3tg&|g\016\005\002!S5\t\021E\003\002#G\005\0311/\0357\013\005\021*\023!B:qCJ\\'B\001\024(\003\031\t\007/Y2iK*\t\001&A\002pe\036L!AK\021\003\031M\003\030M]6TKN\034\030n\0348\t\0131:\002\031A\027\002\t1Lg.\032\t\003]Er!!D\030\n\005Ar\021A\002)sK\022,g-\003\0023g\t11\013\036:j]\036T!\001\r\b\t\013U:\002\031A\027\002\023Q\f'\r\\3OC6,\007\"B\034\030\001\004i\023A\003>l\021>\034H\017]8si\")\021\b\001C\001u\005q!/Z4jgR$V\016\035+bE2,G\003B\027<\007\022CQ\001\020\035A\002u\nq\002\036:bm\026dGk\\4fi\",'o\035\t\003}\005k\021a\020\006\003\001\022\taaY8n[>t\027B\001\"@\005%Ie\016];u\005\026\fg\016C\003\037q\001\007q\004C\0036q\001\007Q\006C\003G\001\021\005q)\001\004hKR\034\026\013\024\013\006[!K5\n\024\005\006y\025\003\r!\020\005\006\025\026\003\r!L\001\003UNDQ!N#A\0025BQ!T#A\0025\n\001\002^7q)\006\024G.\032")
public class SparkEngineV2ForTravelTogether
{
  /* Error */
  public void TravelTogether(org.apache.spark.sql.SparkSession sparkSession, String line, String tableName, final String zkHostport)
  {
    // Byte code:
    //   0: ldc 14
    //   2: astore 5
    //   4: aload_2
    //   5: ldc 16
    //   7: invokevirtual 22	java/lang/String:split	(Ljava/lang/String;)[Ljava/lang/String;
    //   10: astore 6
    //   12: aload 6
    //   14: iconst_1
    //   15: aaload
    //   16: astore 7
    //   18: aload 6
    //   20: iconst_2
    //   21: aaload
    //   22: astore 8
    //   24: getstatic 28	scala/Predef$:MODULE$	Lscala/Predef$;
    //   27: aload 8
    //   29: invokevirtual 32	scala/Predef$:println	(Ljava/lang/Object;)V
    //   32: new 34	com/google/gson/Gson
    //   35: dup
    //   36: invokespecial 38	com/google/gson/Gson:<init>	()V
    //   39: astore 9
    //   41: new 40	com/yisa/engine/branch/SparkEngineV2ForTravelTogether$$anon$1
    //   44: dup
    //   45: aload_0
    //   46: invokespecial 43	com/yisa/engine/branch/SparkEngineV2ForTravelTogether$$anon$1:<init>	(Lcom/yisa/engine/branch/SparkEngineV2ForTravelTogether;)V
    //   49: invokevirtual 47	com/yisa/engine/branch/SparkEngineV2ForTravelTogether$$anon$1:getType	()Ljava/lang/reflect/Type;
    //   52: astore 10
    //   54: aload 9
    //   56: aload 8
    //   58: aload 10
    //   60: invokevirtual 51	com/google/gson/Gson:fromJson	(Ljava/lang/String;Ljava/lang/reflect/Type;)Ljava/lang/Object;
    //   63: checkcast 53	com/yisa/engine/common/InputBean
    //   66: astore 11
    //   68: aload 11
    //   70: invokevirtual 57	com/yisa/engine/common/InputBean:count	()I
    //   73: istore 12
    //   75: aload_0
    //   76: aload 11
    //   78: aload_1
    //   79: aload_3
    //   80: invokevirtual 61	com/yisa/engine/branch/SparkEngineV2ForTravelTogether:registTmpTable	(Lcom/yisa/engine/common/InputBean;Lorg/apache/spark/sql/SparkSession;Ljava/lang/String;)Ljava/lang/String;
    //   83: astore 13
    //   85: aload_0
    //   86: aload 11
    //   88: aload 8
    //   90: aload_3
    //   91: aload 13
    //   93: invokevirtual 65	com/yisa/engine/branch/SparkEngineV2ForTravelTogether:getSQL	(Lcom/yisa/engine/common/InputBean;Ljava/lang/String;Ljava/lang/String;Ljava/lang/String;)Ljava/lang/String;
    //   96: astore 14
    //   98: getstatic 28	scala/Predef$:MODULE$	Lscala/Predef$;
    //   101: new 67	scala/collection/mutable/StringBuilder
    //   104: dup
    //   105: invokespecial 68	scala/collection/mutable/StringBuilder:<init>	()V
    //   108: ldc 70
    //   110: invokevirtual 74	scala/collection/mutable/StringBuilder:append	(Ljava/lang/Object;)Lscala/collection/mutable/StringBuilder;
    //   113: aload 14
    //   115: invokevirtual 74	scala/collection/mutable/StringBuilder:append	(Ljava/lang/Object;)Lscala/collection/mutable/StringBuilder;
    //   118: invokevirtual 78	scala/collection/mutable/StringBuilder:toString	()Ljava/lang/String;
    //   121: invokevirtual 32	scala/Predef$:println	(Ljava/lang/Object;)V
    //   124: aload_1
    //   125: aload 14
    //   127: invokevirtual 84	org/apache/spark/sql/SparkSession:sql	(Ljava/lang/String;)Lorg/apache/spark/sql/Dataset;
    //   130: astore 15
    //   132: aload 15
    //   134: new 86	com/yisa/engine/branch/SparkEngineV2ForTravelTogether$$anonfun$TravelTogether$1
    //   137: dup
    //   138: aload_0
    //   139: aload 4
    //   141: aload 5
    //   143: aload 7
    //   145: invokespecial 89	com/yisa/engine/branch/SparkEngineV2ForTravelTogether$$anonfun$TravelTogether$1:<init>	(Lcom/yisa/engine/branch/SparkEngineV2ForTravelTogether;Ljava/lang/String;Ljava/lang/String;Ljava/lang/String;)V
    //   148: invokevirtual 95	org/apache/spark/sql/Dataset:foreachPartition	(Lscala/Function1;)V
    //   151: getstatic 100	com/yisa/engine/db/MySQLConnectManager$:MODULE$	Lcom/yisa/engine/db/MySQLConnectManager$;
    //   154: aload 4
    //   156: invokevirtual 104	com/yisa/engine/db/MySQLConnectManager$:getConnet	(Ljava/lang/String;)Ljava/sql/Connection;
    //   159: astore 16
    //   161: new 67	scala/collection/mutable/StringBuilder
    //   164: dup
    //   165: invokespecial 68	scala/collection/mutable/StringBuilder:<init>	()V
    //   168: ldc 106
    //   170: invokevirtual 74	scala/collection/mutable/StringBuilder:append	(Ljava/lang/Object;)Lscala/collection/mutable/StringBuilder;
    //   173: aload 5
    //   175: invokevirtual 74	scala/collection/mutable/StringBuilder:append	(Ljava/lang/Object;)Lscala/collection/mutable/StringBuilder;
    //   178: ldc 108
    //   180: invokevirtual 74	scala/collection/mutable/StringBuilder:append	(Ljava/lang/Object;)Lscala/collection/mutable/StringBuilder;
    //   183: aload 7
    //   185: invokevirtual 74	scala/collection/mutable/StringBuilder:append	(Ljava/lang/Object;)Lscala/collection/mutable/StringBuilder;
    //   188: ldc 110
    //   190: invokevirtual 74	scala/collection/mutable/StringBuilder:append	(Ljava/lang/Object;)Lscala/collection/mutable/StringBuilder;
    //   193: invokevirtual 78	scala/collection/mutable/StringBuilder:toString	()Ljava/lang/String;
    //   196: astore 17
    //   198: aload 16
    //   200: aload 17
    //   202: invokeinterface 116 2 0
    //   207: astore 18
    //   209: ldc 118
    //   211: astore 19
    //   213: aload 16
    //   215: aload 19
    //   217: invokeinterface 116 2 0
    //   222: astore 20
    //   224: aload 20
    //   226: iconst_1
    //   227: aload 7
    //   229: invokeinterface 124 3 0
    //   234: aload 18
    //   236: invokeinterface 128 1 0
    //   241: invokeinterface 134 1 0
    //   246: ifeq +15 -> 261
    //   249: aload 20
    //   251: iconst_2
    //   252: iconst_1
    //   253: invokeinterface 138 3 0
    //   258: goto +12 -> 270
    //   261: aload 20
    //   263: iconst_2
    //   264: iconst_m1
    //   265: invokeinterface 138 3 0
    //   270: aload 20
    //   272: invokeinterface 141 1 0
    //   277: pop
    //   278: goto +67 -> 345
    //   281: astore 21
    //   283: getstatic 28	scala/Predef$:MODULE$	Lscala/Predef$;
    //   286: ldc -113
    //   288: invokevirtual 32	scala/Predef$:println	(Ljava/lang/Object;)V
    //   291: getstatic 28	scala/Predef$:MODULE$	Lscala/Predef$;
    //   294: aload 21
    //   296: invokevirtual 146	java/lang/Exception:getMessage	()Ljava/lang/String;
    //   299: invokevirtual 32	scala/Predef$:println	(Ljava/lang/Object;)V
    //   302: getstatic 28	scala/Predef$:MODULE$	Lscala/Predef$;
    //   305: aload 21
    //   307: invokevirtual 149	java/lang/Exception:printStackTrace	()V
    //   310: getstatic 155	scala/runtime/BoxedUnit:UNIT	Lscala/runtime/BoxedUnit;
    //   313: invokevirtual 32	scala/Predef$:println	(Ljava/lang/Object;)V
    //   316: goto +29 -> 345
    //   319: astore 22
    //   321: aload 20
    //   323: invokeinterface 158 1 0
    //   328: aload 18
    //   330: invokeinterface 158 1 0
    //   335: aload 16
    //   337: invokeinterface 159 1 0
    //   342: aload 22
    //   344: athrow
    //   345: aload 20
    //   347: invokeinterface 158 1 0
    //   352: aload 18
    //   354: invokeinterface 158 1 0
    //   359: aload 16
    //   361: invokeinterface 159 1 0
    //   366: return
    // Line number table:
    //   Java source line #36	-> byte code offset #0
    //   Java source line #38	-> byte code offset #4
    //   Java source line #40	-> byte code offset #12
    //   Java source line #41	-> byte code offset #18
    //   Java source line #43	-> byte code offset #24
    //   Java source line #45	-> byte code offset #32
    //   Java source line #46	-> byte code offset #41
    //   Java source line #47	-> byte code offset #54
    //   Java source line #49	-> byte code offset #68
    //   Java source line #51	-> byte code offset #75
    //   Java source line #53	-> byte code offset #85
    //   Java source line #54	-> byte code offset #98
    //   Java source line #56	-> byte code offset #124
    //   Java source line #57	-> byte code offset #132
    //   Java source line #151	-> byte code offset #151
    //   Java source line #152	-> byte code offset #161
    //   Java source line #153	-> byte code offset #198
    //   Java source line #154	-> byte code offset #209
    //   Java source line #155	-> byte code offset #213
    //   Java source line #157	-> byte code offset #224
    //   Java source line #158	-> byte code offset #234
    //   Java source line #160	-> byte code offset #249
    //   Java source line #163	-> byte code offset #261
    //   Java source line #165	-> byte code offset #270
    //   Java source line #167	-> byte code offset #281
    //   Java source line #156	-> byte code offset #281
    //   Java source line #168	-> byte code offset #283
    //   Java source line #169	-> byte code offset #291
    //   Java source line #170	-> byte code offset #302
    //   Java source line #172	-> byte code offset #319
    //   Java source line #174	-> byte code offset #321
    //   Java source line #175	-> byte code offset #328
    //   Java source line #176	-> byte code offset #335
    //   Java source line #174	-> byte code offset #345
    //   Java source line #175	-> byte code offset #352
    //   Java source line #176	-> byte code offset #359
    // Local variable table:
    //   start	length	slot	name	signature
    //   0	367	0	this	SparkEngineV2ForTravelTogether
    //   0	367	1	sparkSession	org.apache.spark.sql.SparkSession
    //   0	367	2	line	String
    //   0	367	3	tableName	String
    //   0	367	4	zkHostport	String
    //   2	172	5	jdbcTable	String
    //   10	9	6	line_arr	String[]
    //   16	212	7	jobId	String
    //   22	67	8	params	String
    //   39	16	9	gson	Gson
    //   52	7	10	mapType	java.lang.reflect.Type
    //   66	21	11	travelTogether	InputBean
    //   73	3	12	countT	int
    //   83	9	13	tmpTable	String
    //   96	30	14	sqlStr	String
    //   130	3	15	resultData	org.apache.spark.sql.Dataset
    //   159	201	16	conn	Connection
    //   196	5	17	query	String
    //   207	146	18	stmt3	PreparedStatement
    //   211	5	19	sql2	String
    //   222	124	20	pstmt2	PreparedStatement
    //   281	25	21	localException	Exception
    //   319	24	22	localObject	Object
    // Exception table:
    //   from	to	target	type
    //   224	281	281	java/lang/Exception
    //   224	319	319	finally
  }
  
  /* Error */
  public String registTmpTable(InputBean travelTogethers, org.apache.spark.sql.SparkSession sparkSession, String tableName)
  {
    // Byte code:
    //   0: getstatic 201	com/yisa/engine/uitl/TimeUtil$:MODULE$	Lcom/yisa/engine/uitl/TimeUtil$;
    //   3: aload_1
    //   4: invokevirtual 204	com/yisa/engine/common/InputBean:startTime	()Ljava/lang/String;
    //   7: invokevirtual 208	com/yisa/engine/uitl/TimeUtil$:getDateId	(Ljava/lang/String;)I
    //   10: istore 4
    //   12: getstatic 201	com/yisa/engine/uitl/TimeUtil$:MODULE$	Lcom/yisa/engine/uitl/TimeUtil$;
    //   15: aload_1
    //   16: invokevirtual 211	com/yisa/engine/common/InputBean:endTime	()Ljava/lang/String;
    //   19: invokevirtual 208	com/yisa/engine/uitl/TimeUtil$:getDateId	(Ljava/lang/String;)I
    //   22: istore 5
    //   24: new 213	java/lang/StringBuffer
    //   27: dup
    //   28: invokespecial 214	java/lang/StringBuffer:<init>	()V
    //   31: astore 6
    //   33: aload 6
    //   35: ldc -40
    //   37: invokevirtual 219	java/lang/StringBuffer:append	(Ljava/lang/String;)Ljava/lang/StringBuffer;
    //   40: ldc -35
    //   42: invokevirtual 219	java/lang/StringBuffer:append	(Ljava/lang/String;)Ljava/lang/StringBuffer;
    //   45: aload_3
    //   46: invokevirtual 219	java/lang/StringBuffer:append	(Ljava/lang/String;)Ljava/lang/StringBuffer;
    //   49: pop
    //   50: aload 6
    //   52: ldc -33
    //   54: invokevirtual 219	java/lang/StringBuffer:append	(Ljava/lang/String;)Ljava/lang/StringBuffer;
    //   57: aload_1
    //   58: invokevirtual 226	com/yisa/engine/common/InputBean:plateNumber	()Ljava/lang/String;
    //   61: invokevirtual 219	java/lang/StringBuffer:append	(Ljava/lang/String;)Ljava/lang/StringBuffer;
    //   64: ldc -28
    //   66: invokevirtual 219	java/lang/StringBuffer:append	(Ljava/lang/String;)Ljava/lang/StringBuffer;
    //   69: pop
    //   70: aload 6
    //   72: ldc -26
    //   74: invokevirtual 219	java/lang/StringBuffer:append	(Ljava/lang/String;)Ljava/lang/StringBuffer;
    //   77: getstatic 201	com/yisa/engine/uitl/TimeUtil$:MODULE$	Lcom/yisa/engine/uitl/TimeUtil$;
    //   80: aload_1
    //   81: invokevirtual 204	com/yisa/engine/common/InputBean:startTime	()Ljava/lang/String;
    //   84: invokevirtual 234	com/yisa/engine/uitl/TimeUtil$:getTimestampLong	(Ljava/lang/String;)J
    //   87: invokevirtual 237	java/lang/StringBuffer:append	(J)Ljava/lang/StringBuffer;
    //   90: pop
    //   91: aload 6
    //   93: ldc -17
    //   95: invokevirtual 219	java/lang/StringBuffer:append	(Ljava/lang/String;)Ljava/lang/StringBuffer;
    //   98: getstatic 201	com/yisa/engine/uitl/TimeUtil$:MODULE$	Lcom/yisa/engine/uitl/TimeUtil$;
    //   101: aload_1
    //   102: invokevirtual 211	com/yisa/engine/common/InputBean:endTime	()Ljava/lang/String;
    //   105: invokevirtual 234	com/yisa/engine/uitl/TimeUtil$:getTimestampLong	(Ljava/lang/String;)J
    //   108: invokevirtual 237	java/lang/StringBuffer:append	(J)Ljava/lang/StringBuffer;
    //   111: pop
    //   112: aload_1
    //   113: invokevirtual 243	com/yisa/engine/common/InputBean:locationId	()[Ljava/lang/String;
    //   116: aconst_null
    //   117: if_acmpeq +163 -> 280
    //   120: aload_1
    //   121: invokevirtual 243	com/yisa/engine/common/InputBean:locationId	()[Ljava/lang/String;
    //   124: arraylength
    //   125: iconst_0
    //   126: if_icmpeq +154 -> 280
    //   129: aload_1
    //   130: invokevirtual 243	com/yisa/engine/common/InputBean:locationId	()[Ljava/lang/String;
    //   133: iconst_0
    //   134: aaload
    //   135: ldc -11
    //   137: astore 7
    //   139: dup
    //   140: ifnonnull +12 -> 152
    //   143: pop
    //   144: aload 7
    //   146: ifnull +134 -> 280
    //   149: goto +11 -> 160
    //   152: aload 7
    //   154: invokevirtual 249	java/lang/Object:equals	(Ljava/lang/Object;)Z
    //   157: ifne +123 -> 280
    //   160: aload_1
    //   161: invokevirtual 243	com/yisa/engine/common/InputBean:locationId	()[Ljava/lang/String;
    //   164: iconst_0
    //   165: aaload
    //   166: ldc -5
    //   168: astore 8
    //   170: dup
    //   171: ifnonnull +12 -> 183
    //   174: pop
    //   175: aload 8
    //   177: ifnull +103 -> 280
    //   180: goto +11 -> 191
    //   183: aload 8
    //   185: invokevirtual 249	java/lang/Object:equals	(Ljava/lang/Object;)Z
    //   188: ifne +92 -> 280
    //   191: getstatic 28	scala/Predef$:MODULE$	Lscala/Predef$;
    //   194: getstatic 28	scala/Predef$:MODULE$	Lscala/Predef$;
    //   197: aload_1
    //   198: invokevirtual 243	com/yisa/engine/common/InputBean:locationId	()[Ljava/lang/String;
    //   201: checkcast 253	[Ljava/lang/Object;
    //   204: invokevirtual 257	scala/Predef$:refArrayOps	([Ljava/lang/Object;)Lscala/collection/mutable/ArrayOps;
    //   207: new 259	com/yisa/engine/branch/SparkEngineV2ForTravelTogether$$anonfun$1
    //   210: dup
    //   211: aload_0
    //   212: invokespecial 260	com/yisa/engine/branch/SparkEngineV2ForTravelTogether$$anonfun$1:<init>	(Lcom/yisa/engine/branch/SparkEngineV2ForTravelTogether;)V
    //   215: getstatic 265	scala/Array$:MODULE$	Lscala/Array$;
    //   218: getstatic 270	scala/reflect/ClassTag$:MODULE$	Lscala/reflect/ClassTag$;
    //   221: ldc 18
    //   223: invokevirtual 274	scala/reflect/ClassTag$:apply	(Ljava/lang/Class;)Lscala/reflect/ClassTag;
    //   226: invokevirtual 278	scala/Array$:canBuildFrom	(Lscala/reflect/ClassTag;)Lscala/collection/generic/CanBuildFrom;
    //   229: invokeinterface 284 3 0
    //   234: checkcast 253	[Ljava/lang/Object;
    //   237: invokevirtual 257	scala/Predef$:refArrayOps	([Ljava/lang/Object;)Lscala/collection/mutable/ArrayOps;
    //   240: new 286	com/yisa/engine/branch/SparkEngineV2ForTravelTogether$$anonfun$2
    //   243: dup
    //   244: aload_0
    //   245: invokespecial 287	com/yisa/engine/branch/SparkEngineV2ForTravelTogether$$anonfun$2:<init>	(Lcom/yisa/engine/branch/SparkEngineV2ForTravelTogether;)V
    //   248: invokeinterface 291 2 0
    //   253: checkcast 18	java/lang/String
    //   256: astore 9
    //   258: aload 6
    //   260: ldc_w 293
    //   263: invokevirtual 219	java/lang/StringBuffer:append	(Ljava/lang/String;)Ljava/lang/StringBuffer;
    //   266: aload 9
    //   268: invokevirtual 219	java/lang/StringBuffer:append	(Ljava/lang/String;)Ljava/lang/StringBuffer;
    //   271: ldc_w 295
    //   274: invokevirtual 219	java/lang/StringBuffer:append	(Ljava/lang/String;)Ljava/lang/StringBuffer;
    //   277: goto +6 -> 283
    //   280: getstatic 155	scala/runtime/BoxedUnit:UNIT	Lscala/runtime/BoxedUnit;
    //   283: pop
    //   284: aload 6
    //   286: ldc_w 297
    //   289: invokevirtual 219	java/lang/StringBuffer:append	(Ljava/lang/String;)Ljava/lang/StringBuffer;
    //   292: iload 4
    //   294: invokevirtual 300	java/lang/StringBuffer:append	(I)Ljava/lang/StringBuffer;
    //   297: pop
    //   298: aload 6
    //   300: ldc_w 302
    //   303: invokevirtual 219	java/lang/StringBuffer:append	(Ljava/lang/String;)Ljava/lang/StringBuffer;
    //   306: iload 5
    //   308: invokevirtual 300	java/lang/StringBuffer:append	(I)Ljava/lang/StringBuffer;
    //   311: pop
    //   312: ldc_w 304
    //   315: astore 10
    //   317: aload_2
    //   318: aload 6
    //   320: invokevirtual 305	java/lang/StringBuffer:toString	()Ljava/lang/String;
    //   323: invokevirtual 84	org/apache/spark/sql/SparkSession:sql	(Ljava/lang/String;)Lorg/apache/spark/sql/Dataset;
    //   326: astore 11
    //   328: getstatic 28	scala/Predef$:MODULE$	Lscala/Predef$;
    //   331: aload 6
    //   333: invokevirtual 305	java/lang/StringBuffer:toString	()Ljava/lang/String;
    //   336: invokevirtual 32	scala/Predef$:println	(Ljava/lang/Object;)V
    //   339: aload 11
    //   341: aload 10
    //   343: invokevirtual 309	org/apache/spark/sql/Dataset:createOrReplaceTempView	(Ljava/lang/String;)V
    //   346: aload 10
    //   348: areturn
    // Line number table:
    //   Java source line #184	-> byte code offset #0
    //   Java source line #185	-> byte code offset #12
    //   Java source line #187	-> byte code offset #24
    //   Java source line #188	-> byte code offset #33
    //   Java source line #189	-> byte code offset #50
    //   Java source line #191	-> byte code offset #70
    //   Java source line #192	-> byte code offset #91
    //   Java source line #194	-> byte code offset #112
    //   Java source line #195	-> byte code offset #191
    //   Java source line #196	-> byte code offset #258
    //   Java source line #194	-> byte code offset #280
    //   Java source line #199	-> byte code offset #284
    //   Java source line #201	-> byte code offset #298
    //   Java source line #203	-> byte code offset #312
    //   Java source line #205	-> byte code offset #317
    //   Java source line #207	-> byte code offset #328
    //   Java source line #209	-> byte code offset #339
    //   Java source line #211	-> byte code offset #346
    // Local variable table:
    //   start	length	slot	name	signature
    //   0	349	0	this	SparkEngineV2ForTravelTogether
    //   0	349	1	travelTogethers	InputBean
    //   0	349	2	sparkSession	org.apache.spark.sql.SparkSession
    //   0	349	3	tableName	String
    //   12	337	4	startTimeDateid	int
    //   24	325	5	endTimeDateid	int
    //   33	316	6	sql	StringBuffer
    //   258	19	9	l	String
    //   317	32	10	tmpTable	String
    //   328	21	11	resultData_1	org.apache.spark.sql.Dataset
  }
  
  /* Error */
  public String getSQL(InputBean travelTogethers, String js, String tableName, String tmpTable)
  {
    // Byte code:
    //   0: getstatic 201	com/yisa/engine/uitl/TimeUtil$:MODULE$	Lcom/yisa/engine/uitl/TimeUtil$;
    //   3: aload_1
    //   4: invokevirtual 204	com/yisa/engine/common/InputBean:startTime	()Ljava/lang/String;
    //   7: invokevirtual 234	com/yisa/engine/uitl/TimeUtil$:getTimestampLong	(Ljava/lang/String;)J
    //   10: lstore 5
    //   12: getstatic 201	com/yisa/engine/uitl/TimeUtil$:MODULE$	Lcom/yisa/engine/uitl/TimeUtil$;
    //   15: aload_1
    //   16: invokevirtual 211	com/yisa/engine/common/InputBean:endTime	()Ljava/lang/String;
    //   19: invokevirtual 234	com/yisa/engine/uitl/TimeUtil$:getTimestampLong	(Ljava/lang/String;)J
    //   22: lstore 7
    //   24: getstatic 201	com/yisa/engine/uitl/TimeUtil$:MODULE$	Lcom/yisa/engine/uitl/TimeUtil$;
    //   27: aload_1
    //   28: invokevirtual 204	com/yisa/engine/common/InputBean:startTime	()Ljava/lang/String;
    //   31: invokevirtual 208	com/yisa/engine/uitl/TimeUtil$:getDateId	(Ljava/lang/String;)I
    //   34: istore 9
    //   36: getstatic 201	com/yisa/engine/uitl/TimeUtil$:MODULE$	Lcom/yisa/engine/uitl/TimeUtil$;
    //   39: aload_1
    //   40: invokevirtual 211	com/yisa/engine/common/InputBean:endTime	()Ljava/lang/String;
    //   43: invokevirtual 208	com/yisa/engine/uitl/TimeUtil$:getDateId	(Ljava/lang/String;)I
    //   46: istore 10
    //   48: new 213	java/lang/StringBuffer
    //   51: dup
    //   52: invokespecial 214	java/lang/StringBuffer:<init>	()V
    //   55: astore 11
    //   57: aload 11
    //   59: ldc_w 317
    //   62: invokevirtual 219	java/lang/StringBuffer:append	(Ljava/lang/String;)Ljava/lang/StringBuffer;
    //   65: pop
    //   66: aload 11
    //   68: ldc_w 319
    //   71: invokevirtual 219	java/lang/StringBuffer:append	(Ljava/lang/String;)Ljava/lang/StringBuffer;
    //   74: pop
    //   75: aload 11
    //   77: ldc_w 321
    //   80: invokevirtual 219	java/lang/StringBuffer:append	(Ljava/lang/String;)Ljava/lang/StringBuffer;
    //   83: pop
    //   84: aload 11
    //   86: ldc_w 323
    //   89: invokevirtual 219	java/lang/StringBuffer:append	(Ljava/lang/String;)Ljava/lang/StringBuffer;
    //   92: pop
    //   93: aload 11
    //   95: ldc_w 325
    //   98: invokevirtual 219	java/lang/StringBuffer:append	(Ljava/lang/String;)Ljava/lang/StringBuffer;
    //   101: pop
    //   102: aload 11
    //   104: ldc_w 327
    //   107: invokevirtual 219	java/lang/StringBuffer:append	(Ljava/lang/String;)Ljava/lang/StringBuffer;
    //   110: pop
    //   111: aload 11
    //   113: ldc_w 329
    //   116: invokevirtual 219	java/lang/StringBuffer:append	(Ljava/lang/String;)Ljava/lang/StringBuffer;
    //   119: pop
    //   120: aload 11
    //   122: ldc_w 331
    //   125: invokevirtual 219	java/lang/StringBuffer:append	(Ljava/lang/String;)Ljava/lang/StringBuffer;
    //   128: pop
    //   129: aload 11
    //   131: ldc -35
    //   133: invokevirtual 219	java/lang/StringBuffer:append	(Ljava/lang/String;)Ljava/lang/StringBuffer;
    //   136: aload_3
    //   137: invokevirtual 219	java/lang/StringBuffer:append	(Ljava/lang/String;)Ljava/lang/StringBuffer;
    //   140: ldc_w 333
    //   143: invokevirtual 219	java/lang/StringBuffer:append	(Ljava/lang/String;)Ljava/lang/StringBuffer;
    //   146: aload 4
    //   148: invokevirtual 219	java/lang/StringBuffer:append	(Ljava/lang/String;)Ljava/lang/StringBuffer;
    //   151: ldc_w 335
    //   154: invokevirtual 219	java/lang/StringBuffer:append	(Ljava/lang/String;)Ljava/lang/StringBuffer;
    //   157: pop
    //   158: aload 11
    //   160: ldc_w 337
    //   163: invokevirtual 219	java/lang/StringBuffer:append	(Ljava/lang/String;)Ljava/lang/StringBuffer;
    //   166: ldc_w 339
    //   169: invokevirtual 219	java/lang/StringBuffer:append	(Ljava/lang/String;)Ljava/lang/StringBuffer;
    //   172: pop
    //   173: aload 11
    //   175: ldc_w 341
    //   178: invokevirtual 219	java/lang/StringBuffer:append	(Ljava/lang/String;)Ljava/lang/StringBuffer;
    //   181: pop
    //   182: aload 11
    //   184: new 67	scala/collection/mutable/StringBuilder
    //   187: dup
    //   188: invokespecial 68	scala/collection/mutable/StringBuilder:<init>	()V
    //   191: ldc_w 343
    //   194: invokevirtual 74	scala/collection/mutable/StringBuilder:append	(Ljava/lang/Object;)Lscala/collection/mutable/StringBuilder;
    //   197: aload_1
    //   198: invokevirtual 226	com/yisa/engine/common/InputBean:plateNumber	()Ljava/lang/String;
    //   201: invokevirtual 74	scala/collection/mutable/StringBuilder:append	(Ljava/lang/Object;)Lscala/collection/mutable/StringBuilder;
    //   204: ldc_w 345
    //   207: invokevirtual 74	scala/collection/mutable/StringBuilder:append	(Ljava/lang/Object;)Lscala/collection/mutable/StringBuilder;
    //   210: invokevirtual 78	scala/collection/mutable/StringBuilder:toString	()Ljava/lang/String;
    //   213: invokevirtual 219	java/lang/StringBuffer:append	(Ljava/lang/String;)Ljava/lang/StringBuffer;
    //   216: pop
    //   217: aload 11
    //   219: ldc_w 347
    //   222: invokevirtual 219	java/lang/StringBuffer:append	(Ljava/lang/String;)Ljava/lang/StringBuffer;
    //   225: iconst_0
    //   226: aload_1
    //   227: invokevirtual 350	com/yisa/engine/common/InputBean:differ	()I
    //   230: isub
    //   231: invokevirtual 300	java/lang/StringBuffer:append	(I)Ljava/lang/StringBuffer;
    //   234: pop
    //   235: aload 11
    //   237: ldc_w 352
    //   240: invokevirtual 219	java/lang/StringBuffer:append	(Ljava/lang/String;)Ljava/lang/StringBuffer;
    //   243: aload_1
    //   244: invokevirtual 350	com/yisa/engine/common/InputBean:differ	()I
    //   247: invokevirtual 300	java/lang/StringBuffer:append	(I)Ljava/lang/StringBuffer;
    //   250: pop
    //   251: aload_1
    //   252: invokevirtual 355	com/yisa/engine/common/InputBean:carYear	()[Ljava/lang/String;
    //   255: aconst_null
    //   256: if_acmpeq +140 -> 396
    //   259: getstatic 28	scala/Predef$:MODULE$	Lscala/Predef$;
    //   262: aload_1
    //   263: invokevirtual 355	com/yisa/engine/common/InputBean:carYear	()[Ljava/lang/String;
    //   266: checkcast 253	[Ljava/lang/Object;
    //   269: invokevirtual 257	scala/Predef$:refArrayOps	([Ljava/lang/Object;)Lscala/collection/mutable/ArrayOps;
    //   272: invokeinterface 358 1 0
    //   277: iconst_0
    //   278: if_icmple +118 -> 396
    //   281: aload_1
    //   282: invokevirtual 355	com/yisa/engine/common/InputBean:carYear	()[Ljava/lang/String;
    //   285: iconst_0
    //   286: aaload
    //   287: ldc -11
    //   289: astore 12
    //   291: dup
    //   292: ifnonnull +12 -> 304
    //   295: pop
    //   296: aload 12
    //   298: ifnull +98 -> 396
    //   301: goto +11 -> 312
    //   304: aload 12
    //   306: invokevirtual 249	java/lang/Object:equals	(Ljava/lang/Object;)Z
    //   309: ifne +87 -> 396
    //   312: aload_1
    //   313: invokevirtual 355	com/yisa/engine/common/InputBean:carYear	()[Ljava/lang/String;
    //   316: iconst_0
    //   317: aaload
    //   318: ldc -5
    //   320: astore 13
    //   322: dup
    //   323: ifnonnull +12 -> 335
    //   326: pop
    //   327: aload 13
    //   329: ifnull +67 -> 396
    //   332: goto +11 -> 343
    //   335: aload 13
    //   337: invokevirtual 249	java/lang/Object:equals	(Ljava/lang/Object;)Z
    //   340: ifne +56 -> 396
    //   343: getstatic 28	scala/Predef$:MODULE$	Lscala/Predef$;
    //   346: aload_1
    //   347: invokevirtual 355	com/yisa/engine/common/InputBean:carYear	()[Ljava/lang/String;
    //   350: checkcast 253	[Ljava/lang/Object;
    //   353: invokevirtual 257	scala/Predef$:refArrayOps	([Ljava/lang/Object;)Lscala/collection/mutable/ArrayOps;
    //   356: new 360	com/yisa/engine/branch/SparkEngineV2ForTravelTogether$$anonfun$3
    //   359: dup
    //   360: aload_0
    //   361: invokespecial 361	com/yisa/engine/branch/SparkEngineV2ForTravelTogether$$anonfun$3:<init>	(Lcom/yisa/engine/branch/SparkEngineV2ForTravelTogether;)V
    //   364: invokeinterface 291 2 0
    //   369: checkcast 18	java/lang/String
    //   372: astore 14
    //   374: aload 11
    //   376: ldc_w 363
    //   379: invokevirtual 219	java/lang/StringBuffer:append	(Ljava/lang/String;)Ljava/lang/StringBuffer;
    //   382: aload 14
    //   384: invokevirtual 219	java/lang/StringBuffer:append	(Ljava/lang/String;)Ljava/lang/StringBuffer;
    //   387: ldc_w 295
    //   390: invokevirtual 219	java/lang/StringBuffer:append	(Ljava/lang/String;)Ljava/lang/StringBuffer;
    //   393: goto +6 -> 399
    //   396: getstatic 155	scala/runtime/BoxedUnit:UNIT	Lscala/runtime/BoxedUnit;
    //   399: pop
    //   400: lload 5
    //   402: lconst_0
    //   403: lcmp
    //   404: ifeq +19 -> 423
    //   407: aload 11
    //   409: ldc_w 365
    //   412: invokevirtual 219	java/lang/StringBuffer:append	(Ljava/lang/String;)Ljava/lang/StringBuffer;
    //   415: lload 5
    //   417: invokevirtual 237	java/lang/StringBuffer:append	(J)Ljava/lang/StringBuffer;
    //   420: goto +6 -> 426
    //   423: getstatic 155	scala/runtime/BoxedUnit:UNIT	Lscala/runtime/BoxedUnit;
    //   426: pop
    //   427: lload 7
    //   429: lconst_0
    //   430: lcmp
    //   431: ifeq +19 -> 450
    //   434: aload 11
    //   436: ldc_w 367
    //   439: invokevirtual 219	java/lang/StringBuffer:append	(Ljava/lang/String;)Ljava/lang/StringBuffer;
    //   442: lload 7
    //   444: invokevirtual 237	java/lang/StringBuffer:append	(J)Ljava/lang/StringBuffer;
    //   447: goto +6 -> 453
    //   450: getstatic 155	scala/runtime/BoxedUnit:UNIT	Lscala/runtime/BoxedUnit;
    //   453: pop
    //   454: lload 5
    //   456: lconst_0
    //   457: lcmp
    //   458: ifeq +19 -> 477
    //   461: aload 11
    //   463: ldc_w 297
    //   466: invokevirtual 219	java/lang/StringBuffer:append	(Ljava/lang/String;)Ljava/lang/StringBuffer;
    //   469: iload 9
    //   471: invokevirtual 300	java/lang/StringBuffer:append	(I)Ljava/lang/StringBuffer;
    //   474: goto +6 -> 480
    //   477: getstatic 155	scala/runtime/BoxedUnit:UNIT	Lscala/runtime/BoxedUnit;
    //   480: pop
    //   481: lload 7
    //   483: lconst_0
    //   484: lcmp
    //   485: ifeq +19 -> 504
    //   488: aload 11
    //   490: ldc_w 302
    //   493: invokevirtual 219	java/lang/StringBuffer:append	(Ljava/lang/String;)Ljava/lang/StringBuffer;
    //   496: iload 10
    //   498: invokevirtual 300	java/lang/StringBuffer:append	(I)Ljava/lang/StringBuffer;
    //   501: goto +6 -> 507
    //   504: getstatic 155	scala/runtime/BoxedUnit:UNIT	Lscala/runtime/BoxedUnit;
    //   507: pop
    //   508: aload_1
    //   509: invokevirtual 370	com/yisa/engine/common/InputBean:carBrand	()Ljava/lang/String;
    //   512: astore 15
    //   514: aload_1
    //   515: invokevirtual 373	com/yisa/engine/common/InputBean:carModel	()[Ljava/lang/String;
    //   518: astore 16
    //   520: aload_1
    //   521: invokevirtual 376	com/yisa/engine/common/InputBean:carLevel	()[Ljava/lang/String;
    //   524: astore 17
    //   526: aload_1
    //   527: invokevirtual 379	com/yisa/engine/common/InputBean:carColor	()Ljava/lang/String;
    //   530: astore 18
    //   532: aload 16
    //   534: aconst_null
    //   535: if_acmpeq +92 -> 627
    //   538: aload 16
    //   540: arraylength
    //   541: iconst_0
    //   542: if_icmple +85 -> 627
    //   545: aload_1
    //   546: invokevirtual 373	com/yisa/engine/common/InputBean:carModel	()[Ljava/lang/String;
    //   549: iconst_0
    //   550: aaload
    //   551: ldc -5
    //   553: astore 19
    //   555: dup
    //   556: ifnonnull +12 -> 568
    //   559: pop
    //   560: aload 19
    //   562: ifnull +65 -> 627
    //   565: goto +11 -> 576
    //   568: aload 19
    //   570: invokevirtual 249	java/lang/Object:equals	(Ljava/lang/Object;)Z
    //   573: ifne +54 -> 627
    //   576: getstatic 28	scala/Predef$:MODULE$	Lscala/Predef$;
    //   579: aload 16
    //   581: checkcast 253	[Ljava/lang/Object;
    //   584: invokevirtual 257	scala/Predef$:refArrayOps	([Ljava/lang/Object;)Lscala/collection/mutable/ArrayOps;
    //   587: new 381	com/yisa/engine/branch/SparkEngineV2ForTravelTogether$$anonfun$4
    //   590: dup
    //   591: aload_0
    //   592: invokespecial 382	com/yisa/engine/branch/SparkEngineV2ForTravelTogether$$anonfun$4:<init>	(Lcom/yisa/engine/branch/SparkEngineV2ForTravelTogether;)V
    //   595: invokeinterface 291 2 0
    //   600: checkcast 18	java/lang/String
    //   603: astore 20
    //   605: aload 11
    //   607: ldc_w 384
    //   610: invokevirtual 219	java/lang/StringBuffer:append	(Ljava/lang/String;)Ljava/lang/StringBuffer;
    //   613: aload 20
    //   615: invokevirtual 219	java/lang/StringBuffer:append	(Ljava/lang/String;)Ljava/lang/StringBuffer;
    //   618: ldc_w 295
    //   621: invokevirtual 219	java/lang/StringBuffer:append	(Ljava/lang/String;)Ljava/lang/StringBuffer;
    //   624: goto +6 -> 630
    //   627: getstatic 155	scala/runtime/BoxedUnit:UNIT	Lscala/runtime/BoxedUnit;
    //   630: pop
    //   631: aload 15
    //   633: ifnull +57 -> 690
    //   636: aload 15
    //   638: ldc -11
    //   640: astore 21
    //   642: dup
    //   643: ifnonnull +12 -> 655
    //   646: pop
    //   647: aload 21
    //   649: ifnull +41 -> 690
    //   652: goto +11 -> 663
    //   655: aload 21
    //   657: invokevirtual 249	java/lang/Object:equals	(Ljava/lang/Object;)Z
    //   660: ifne +30 -> 690
    //   663: aload 15
    //   665: ldc -5
    //   667: astore 22
    //   669: dup
    //   670: ifnonnull +12 -> 682
    //   673: pop
    //   674: aload 22
    //   676: ifnull +14 -> 690
    //   679: goto +17 -> 696
    //   682: aload 22
    //   684: invokevirtual 249	java/lang/Object:equals	(Ljava/lang/Object;)Z
    //   687: ifeq +9 -> 696
    //   690: getstatic 155	scala/runtime/BoxedUnit:UNIT	Lscala/runtime/BoxedUnit;
    //   693: goto +16 -> 709
    //   696: aload 11
    //   698: ldc_w 386
    //   701: invokevirtual 219	java/lang/StringBuffer:append	(Ljava/lang/String;)Ljava/lang/StringBuffer;
    //   704: aload 15
    //   706: invokevirtual 219	java/lang/StringBuffer:append	(Ljava/lang/String;)Ljava/lang/StringBuffer;
    //   709: pop
    //   710: aload 17
    //   712: aconst_null
    //   713: if_acmpeq +92 -> 805
    //   716: aload 17
    //   718: arraylength
    //   719: iconst_0
    //   720: if_icmple +85 -> 805
    //   723: aload_1
    //   724: invokevirtual 376	com/yisa/engine/common/InputBean:carLevel	()[Ljava/lang/String;
    //   727: iconst_0
    //   728: aaload
    //   729: ldc -5
    //   731: astore 23
    //   733: dup
    //   734: ifnonnull +12 -> 746
    //   737: pop
    //   738: aload 23
    //   740: ifnull +65 -> 805
    //   743: goto +11 -> 754
    //   746: aload 23
    //   748: invokevirtual 249	java/lang/Object:equals	(Ljava/lang/Object;)Z
    //   751: ifne +54 -> 805
    //   754: getstatic 28	scala/Predef$:MODULE$	Lscala/Predef$;
    //   757: aload 17
    //   759: checkcast 253	[Ljava/lang/Object;
    //   762: invokevirtual 257	scala/Predef$:refArrayOps	([Ljava/lang/Object;)Lscala/collection/mutable/ArrayOps;
    //   765: new 388	com/yisa/engine/branch/SparkEngineV2ForTravelTogether$$anonfun$5
    //   768: dup
    //   769: aload_0
    //   770: invokespecial 389	com/yisa/engine/branch/SparkEngineV2ForTravelTogether$$anonfun$5:<init>	(Lcom/yisa/engine/branch/SparkEngineV2ForTravelTogether;)V
    //   773: invokeinterface 291 2 0
    //   778: checkcast 18	java/lang/String
    //   781: astore 24
    //   783: aload 11
    //   785: ldc_w 391
    //   788: invokevirtual 219	java/lang/StringBuffer:append	(Ljava/lang/String;)Ljava/lang/StringBuffer;
    //   791: aload 24
    //   793: invokevirtual 219	java/lang/StringBuffer:append	(Ljava/lang/String;)Ljava/lang/StringBuffer;
    //   796: ldc_w 295
    //   799: invokevirtual 219	java/lang/StringBuffer:append	(Ljava/lang/String;)Ljava/lang/StringBuffer;
    //   802: goto +6 -> 808
    //   805: getstatic 155	scala/runtime/BoxedUnit:UNIT	Lscala/runtime/BoxedUnit;
    //   808: pop
    //   809: aload 18
    //   811: ifnull +57 -> 868
    //   814: aload 18
    //   816: ldc -11
    //   818: astore 25
    //   820: dup
    //   821: ifnonnull +12 -> 833
    //   824: pop
    //   825: aload 25
    //   827: ifnull +41 -> 868
    //   830: goto +11 -> 841
    //   833: aload 25
    //   835: invokevirtual 249	java/lang/Object:equals	(Ljava/lang/Object;)Z
    //   838: ifne +30 -> 868
    //   841: aload 18
    //   843: ldc -5
    //   845: astore 26
    //   847: dup
    //   848: ifnonnull +12 -> 860
    //   851: pop
    //   852: aload 26
    //   854: ifnull +14 -> 868
    //   857: goto +17 -> 874
    //   860: aload 26
    //   862: invokevirtual 249	java/lang/Object:equals	(Ljava/lang/Object;)Z
    //   865: ifeq +9 -> 874
    //   868: getstatic 155	scala/runtime/BoxedUnit:UNIT	Lscala/runtime/BoxedUnit;
    //   871: goto +16 -> 887
    //   874: aload 11
    //   876: ldc_w 393
    //   879: invokevirtual 219	java/lang/StringBuffer:append	(Ljava/lang/String;)Ljava/lang/StringBuffer;
    //   882: aload 18
    //   884: invokevirtual 219	java/lang/StringBuffer:append	(Ljava/lang/String;)Ljava/lang/StringBuffer;
    //   887: pop
    //   888: aload 11
    //   890: ldc_w 395
    //   893: invokevirtual 219	java/lang/StringBuffer:append	(Ljava/lang/String;)Ljava/lang/StringBuffer;
    //   896: pop
    //   897: aload 11
    //   899: ldc_w 397
    //   902: invokevirtual 219	java/lang/StringBuffer:append	(Ljava/lang/String;)Ljava/lang/StringBuffer;
    //   905: pop
    //   906: aload 11
    //   908: ldc_w 399
    //   911: invokevirtual 219	java/lang/StringBuffer:append	(Ljava/lang/String;)Ljava/lang/StringBuffer;
    //   914: pop
    //   915: aload 11
    //   917: ldc_w 401
    //   920: invokevirtual 219	java/lang/StringBuffer:append	(Ljava/lang/String;)Ljava/lang/StringBuffer;
    //   923: pop
    //   924: aload 11
    //   926: ldc_w 403
    //   929: invokevirtual 219	java/lang/StringBuffer:append	(Ljava/lang/String;)Ljava/lang/StringBuffer;
    //   932: aload_1
    //   933: invokevirtual 57	com/yisa/engine/common/InputBean:count	()I
    //   936: invokevirtual 300	java/lang/StringBuffer:append	(I)Ljava/lang/StringBuffer;
    //   939: pop
    //   940: aload 11
    //   942: invokevirtual 305	java/lang/StringBuffer:toString	()Ljava/lang/String;
    //   945: areturn
    // Line number table:
    //   Java source line #217	-> byte code offset #0
    //   Java source line #218	-> byte code offset #12
    //   Java source line #220	-> byte code offset #24
    //   Java source line #221	-> byte code offset #36
    //   Java source line #223	-> byte code offset #48
    //   Java source line #224	-> byte code offset #57
    //   Java source line #225	-> byte code offset #66
    //   Java source line #226	-> byte code offset #75
    //   Java source line #227	-> byte code offset #84
    //   Java source line #228	-> byte code offset #93
    //   Java source line #229	-> byte code offset #102
    //   Java source line #231	-> byte code offset #111
    //   Java source line #233	-> byte code offset #120
    //   Java source line #235	-> byte code offset #129
    //   Java source line #238	-> byte code offset #158
    //   Java source line #240	-> byte code offset #173
    //   Java source line #242	-> byte code offset #182
    //   Java source line #244	-> byte code offset #217
    //   Java source line #245	-> byte code offset #235
    //   Java source line #247	-> byte code offset #251
    //   Java source line #248	-> byte code offset #343
    //   Java source line #249	-> byte code offset #374
    //   Java source line #247	-> byte code offset #396
    //   Java source line #252	-> byte code offset #400
    //   Java source line #253	-> byte code offset #407
    //   Java source line #252	-> byte code offset #423
    //   Java source line #256	-> byte code offset #427
    //   Java source line #257	-> byte code offset #434
    //   Java source line #256	-> byte code offset #450
    //   Java source line #260	-> byte code offset #454
    //   Java source line #261	-> byte code offset #461
    //   Java source line #260	-> byte code offset #477
    //   Java source line #264	-> byte code offset #481
    //   Java source line #265	-> byte code offset #488
    //   Java source line #264	-> byte code offset #504
    //   Java source line #268	-> byte code offset #508
    //   Java source line #270	-> byte code offset #514
    //   Java source line #272	-> byte code offset #520
    //   Java source line #274	-> byte code offset #526
    //   Java source line #276	-> byte code offset #532
    //   Java source line #277	-> byte code offset #576
    //   Java source line #278	-> byte code offset #605
    //   Java source line #276	-> byte code offset #627
    //   Java source line #281	-> byte code offset #631
    //   Java source line #282	-> byte code offset #696
    //   Java source line #281	-> byte code offset #709
    //   Java source line #284	-> byte code offset #710
    //   Java source line #285	-> byte code offset #754
    //   Java source line #286	-> byte code offset #783
    //   Java source line #284	-> byte code offset #805
    //   Java source line #289	-> byte code offset #809
    //   Java source line #290	-> byte code offset #874
    //   Java source line #289	-> byte code offset #887
    //   Java source line #293	-> byte code offset #888
    //   Java source line #295	-> byte code offset #897
    //   Java source line #297	-> byte code offset #906
    //   Java source line #300	-> byte code offset #915
    //   Java source line #301	-> byte code offset #924
    //   Java source line #303	-> byte code offset #940
    // Local variable table:
    //   start	length	slot	name	signature
    //   0	946	0	this	SparkEngineV2ForTravelTogether
    //   0	946	1	travelTogethers	InputBean
    //   0	946	2	js	String
    //   0	946	3	tableName	String
    //   0	946	4	tmpTable	String
    //   12	933	5	startTime	long
    //   24	921	7	endTime	long
    //   36	909	9	startTimeDateid	int
    //   48	897	10	endTimeDateid	int
    //   57	888	11	sb	StringBuffer
    //   374	19	14	m	String
    //   514	431	15	carBrand	String
    //   520	425	16	carModel	String[]
    //   526	419	17	carLevel	String[]
    //   532	413	18	carColor	String
    //   605	19	20	m	String
    //   783	19	24	m	String
  }
}


/* Location:              E:\BaiduYunDownload\伊萨时期的一些代码\SparkEngine终极版\jars\YISAEngineBySpark2-4.0.6-SNAPSHOT-jar-with-dependencies.jar!\com\yisa\engine\branch\SparkEngineV2ForTravelTogether.class
 * Java compiler version: 6 (50.0)
 * JD-Core Version:       0.7.1
 */