/*     */ package com.yisa.engine.branch;
/*     */ 
/*     */ import com.yisa.engine.common.InputBean;
/*     */ import java.sql.Connection;
/*     */ import java.sql.PreparedStatement;
/*     */ import java.text.SimpleDateFormat;
/*     */ import java.util.Calendar;
/*     */ import org.apache.spark.sql.Dataset;
/*     */ import org.apache.spark.sql.Row;
/*     */ import org.apache.spark.sql.SparkSession;
/*     */ import scala.Predef.;
/*     */ import scala.Serializable;
/*     */ import scala.collection.mutable.StringBuilder;
/*     */ import scala.runtime.BoxesRunTime;
/*     */ import scala.runtime.IntRef;
/*     */ import scala.runtime.ObjectRef;
/*     */ 
/*     */ @scala.reflect.ScalaSignature(bytes="\006\001Y3A!\001\002\001\027\t92\013]1sW\026sw-\0338f-J2uN]\"bg\026\034\025M\035\006\003\007\021\taA\031:b]\016D'BA\003\007\003\031)gnZ5oK*\021q\001C\001\005s&\034\030MC\001\n\003\r\031w.\\\002\001'\t\001A\002\005\002\016!5\taBC\001\020\003\025\0318-\0317b\023\t\tbB\001\004B]f\024VM\032\005\006'\001!\t\001F\001\007y%t\027\016\036 \025\003U\001\"A\006\001\016\003\tAQ\001\007\001\005\002e\tQb]3be\016D7)Y:f\007\006\024HC\002\016\036]Mbd\b\005\002\0167%\021AD\004\002\005+:LG\017C\003\037/\001\007q$A\005ta\006\0248\016R1uCB\031\001%K\026\016\003\005R!AI\022\002\007M\fHN\003\002%K\005)1\017]1sW*\021aeJ\001\007CB\f7\r[3\013\003!\n1a\034:h\023\tQ\023EA\004ECR\f7/\032;\021\005\001b\023BA\027\"\005\r\021vn\036\005\006_]\001\r\001M\001\013gFd7i\0348uKb$\bC\001\0212\023\t\021\024E\001\007Ta\006\0248nU3tg&|g\016C\0035/\001\007Q'\001\003mS:,\007C\001\034:\035\tiq'\003\0029\035\0051\001K]3eK\032L!AO\036\003\rM#(/\0338h\025\tAd\002C\003>/\001\007Q'A\005uC\ndWMT1nK\")qh\006a\001k\005Q!p\033%pgR\004xN\035;\t\013\005\003A\021\001\"\002\023\035,Go\0247e\t\006LH#A\033\t\013\021\003A\021A#\002\033\035\034xN\\!se\006Lh)\0368d)\021)dI\024)\t\013\035\033\005\031\001%\002\023%t\007/\036;CK\006t\007CA%M\033\005Q%BA&\005\003\031\031w.\\7p]&\021QJ\023\002\n\023:\004X\017\036\"fC:DQaT\"A\002U\nQ\001^=qK\016CQ!P\"A\002UBQA\025\001\005\002M\013\021bZ3u\t\006$X-\0333\025\005U\"\006\"B+R\001\004)\024A\003;j[\026\034FO]5oO\002")
/*     */ public class SparkEngineV2ForCaseCar
/*     */ {
/*     */   public void searchCaseCar(Dataset<Row> sparkData, final SparkSession sqlContext, String line, final String tableName, String zkHostport)
/*     */   {
/*  23 */     Connection conn = com.yisa.engine.db.MySQLConnectManager..MODULE$.getConnet(zkHostport);
/*  24 */     conn.setAutoCommit(false);
/*  25 */     String sql = "insert into scajcb_result (s_id,j_id,t_id) values(?,?,?)";
/*  26 */     final ObjectRef pstmt = ObjectRef.create(conn.prepareStatement(sql));
/*     */     
/*  28 */     String[] line_arr = line.split("\\|");
/*     */     
/*  30 */     final String jobId = line_arr[1];
/*  31 */     String params = line_arr[2];
/*     */     
/*  33 */     com.google.gson.Gson gson = new com.google.gson.Gson();
/*  34 */     java.lang.reflect.Type mapType = new com.google.gson.reflect.TypeToken() {}.getType();
/*  35 */     InputBean[] map = (InputBean[])gson.fromJson(params, mapType);
/*     */     
/*  37 */     InputBean inputBeanRepair = null;
/*     */     
/*  39 */     scala.runtime.Null. resultData = null;
/*     */     
/*  41 */     final IntRef count = IntRef.create(0);
/*     */     
/*     */ 
/*  44 */     if (map.length > 0)
/*     */     {
/*  46 */       final IntRef i = IntRef.create(1);
/*  47 */       final ObjectRef df = ObjectRef.create(null);
/*  48 */       Dataset dfNot = null;
/*     */       
/*  50 */       Predef..MODULE$.refArrayOps((Object[])map).foreach(new scala.runtime.AbstractFunction1() { public static final long serialVersionUID = 0L;
/*     */         
/*  52 */         public final void apply(InputBean m) { SimpleDateFormat format2 = new SimpleDateFormat("yyyyMMddHHmmss");
/*     */           
/*  54 */           long startTime = format2.parse(m.startTime()).getTime() / 1000L;
/*  55 */           long endTime = format2.parse(m.endTime()).getTime() / 1000L;
/*     */           
/*  57 */           if (i.elem == 1) {
/*  58 */             df.elem = sqlContext.sql(SparkEngineV2ForCaseCar.this.gsonArrayFunc(m, new StringBuilder().append(i.elem).append("").toString(), tableName))
/*  59 */               .filter(new StringBuilder().append("capturetime >= ").append(BoxesRunTime.boxToLong(startTime)).toString())
/*  60 */               .filter(new StringBuilder().append("capturetime <= ").append(BoxesRunTime.boxToLong(endTime)).toString());
/*     */             
/*  62 */             i.elem += 1;
/*     */             
/*  64 */             count.elem = m.count();
/*     */           }
/*     */           else
/*     */           {
/*  68 */             Dataset dfTemp = sqlContext.sql(SparkEngineV2ForCaseCar.this.gsonArrayFunc(m, new StringBuilder().append(i.elem).append("").toString(), tableName))
/*  69 */               .filter(new StringBuilder().append("capturetime >= ").append(BoxesRunTime.boxToLong(startTime)).toString())
/*  70 */               .filter(new StringBuilder().append("capturetime <= ").append(BoxesRunTime.boxToLong(endTime)).toString());
/*     */             
/*  72 */             df.elem = ((Dataset)df.elem).union(dfTemp);
/*     */             
/*  74 */             i.elem += 1;
/*     */           }
/*     */           
/*     */         }
/*  78 */       });
/*  79 */       Dataset dfIs = null;
/*  80 */       if ((Dataset)df.elem != null)
/*     */       {
/*  82 */         ((Dataset)df.elem).createOrReplaceTempView("df");
/*     */         
/*  84 */         String sqlUnion = "SELECT first(solrid) as solrid, platenumber, concat_ws(',',collect_set(type)) as types from df group by platenumber";
/*  85 */         dfIs = sqlContext.sql(sqlUnion);
/*     */         
/*  87 */         if (count.elem >= 2)
/*     */         {
/*  89 */           if (count.elem > 2) {
/*  90 */             count.elem -= 1;
/*     */           }
/*     */           
/*  93 */           dfIs = dfIs.filter(new scala.runtime.AbstractFunction1() { public final boolean apply(Row x) { return ((String)x.getAs("types")).split(",").length >= count.elem; }
/*     */           });
/*     */         }
/*     */         
/*  97 */         dfIs.createOrReplaceTempView("dfIs");
/*     */         
/*  99 */         final IntRef number = IntRef.create(0);
/* 100 */         Predef..MODULE$.refArrayOps((Object[])dfIs.collect()).foreach(new scala.runtime.AbstractFunction1() { public static final long serialVersionUID = 0L;
/*     */           
/* 102 */           public final void apply(Row data) { number.elem += 1;
/*     */             
/* 104 */             ((PreparedStatement)pstmt.elem).setString(1, data.apply(0).toString());
/* 105 */             ((PreparedStatement)pstmt.elem).setString(2, jobId);
/* 106 */             ((PreparedStatement)pstmt.elem).setString(3, data.apply(2).toString());
/* 107 */             ((PreparedStatement)pstmt.elem).addBatch();
/*     */           }
/* 109 */         });
/* 110 */         String sql2 = "insert into scajcb_progress (jobid,total) values(?,?)";
/* 111 */         PreparedStatement pstmt2 = conn.prepareStatement(sql2);
/*     */         
/* 113 */         if (number.elem == 0) {
/* 114 */           number.elem = -1;
/*     */         }
/* 116 */         pstmt2.setString(1, jobId);
/* 117 */         pstmt2.setInt(2, number.elem);
/* 118 */         pstmt2.executeUpdate();
/* 119 */         pstmt2.close();
/*     */         
/* 121 */         ((PreparedStatement)pstmt.elem).executeBatch();
/* 122 */         conn.commit();
/* 123 */         ((PreparedStatement)pstmt.elem).close();
/* 124 */         conn.close();
/*     */       }
/*     */     }
/*     */   }
/*     */   
/*     */ 
/*     */   public static final long serialVersionUID = 0L;
/*     */   public String getOldDay()
/*     */   {
/* 133 */     SimpleDateFormat dateFormat = new SimpleDateFormat("yyyyMMdd");
/* 134 */     Calendar cal = Calendar.getInstance();
/* 135 */     cal.add(5, -3);
/* 136 */     String yesterday = dateFormat.format(cal.getTime());
/*     */     
/* 138 */     return yesterday;
/*     */   }
/*     */   
/*     */   /* Error */
/*     */   public String gsonArrayFunc(InputBean inputBean, String typeC, String tableName)
/*     */   {
/*     */     // Byte code:
/*     */     //   0: getstatic 240	com/yisa/engine/uitl/TimeUtil$:MODULE$	Lcom/yisa/engine/uitl/TimeUtil$;
/*     */     //   3: aload_1
/*     */     //   4: invokevirtual 245	com/yisa/engine/common/InputBean:startTime	()Ljava/lang/String;
/*     */     //   7: invokevirtual 249	com/yisa/engine/uitl/TimeUtil$:getTimeStringFormat	(Ljava/lang/String;)Ljava/lang/String;
/*     */     //   10: astore 4
/*     */     //   12: getstatic 240	com/yisa/engine/uitl/TimeUtil$:MODULE$	Lcom/yisa/engine/uitl/TimeUtil$;
/*     */     //   15: aload_1
/*     */     //   16: invokevirtual 252	com/yisa/engine/common/InputBean:endTime	()Ljava/lang/String;
/*     */     //   19: invokevirtual 249	com/yisa/engine/uitl/TimeUtil$:getTimeStringFormat	(Ljava/lang/String;)Ljava/lang/String;
/*     */     //   22: astore 5
/*     */     //   24: aload_1
/*     */     //   25: invokevirtual 256	com/yisa/engine/common/InputBean:locationId	()[Ljava/lang/String;
/*     */     //   28: astore 6
/*     */     //   30: aload_1
/*     */     //   31: invokevirtual 259	com/yisa/engine/common/InputBean:carModel	()[Ljava/lang/String;
/*     */     //   34: astore 7
/*     */     //   36: aload_1
/*     */     //   37: invokevirtual 262	com/yisa/engine/common/InputBean:carBrand	()Ljava/lang/String;
/*     */     //   40: astore 8
/*     */     //   42: aload_1
/*     */     //   43: invokevirtual 265	com/yisa/engine/common/InputBean:carYear	()[Ljava/lang/String;
/*     */     //   46: astore 9
/*     */     //   48: aload_1
/*     */     //   49: invokevirtual 268	com/yisa/engine/common/InputBean:carColor	()Ljava/lang/String;
/*     */     //   52: astore 10
/*     */     //   54: aload_1
/*     */     //   55: invokevirtual 271	com/yisa/engine/common/InputBean:plateNumber	()Ljava/lang/String;
/*     */     //   58: astore 11
/*     */     //   60: getstatic 77	scala/Predef$:MODULE$	Lscala/Predef$;
/*     */     //   63: aload_1
/*     */     //   64: invokevirtual 256	com/yisa/engine/common/InputBean:locationId	()[Ljava/lang/String;
/*     */     //   67: invokevirtual 275	scala/Predef$:println	(Ljava/lang/Object;)V
/*     */     //   70: new 277	java/lang/StringBuffer
/*     */     //   73: dup
/*     */     //   74: invokespecial 278	java/lang/StringBuffer:<init>	()V
/*     */     //   77: astore 12
/*     */     //   79: aload 12
/*     */     //   81: ldc_w 280
/*     */     //   84: invokevirtual 284	java/lang/StringBuffer:append	(Ljava/lang/String;)Ljava/lang/StringBuffer;
/*     */     //   87: pop
/*     */     //   88: aload 12
/*     */     //   90: aload_2
/*     */     //   91: invokevirtual 284	java/lang/StringBuffer:append	(Ljava/lang/String;)Ljava/lang/StringBuffer;
/*     */     //   94: ldc_w 286
/*     */     //   97: invokevirtual 284	java/lang/StringBuffer:append	(Ljava/lang/String;)Ljava/lang/StringBuffer;
/*     */     //   100: aload_3
/*     */     //   101: invokevirtual 284	java/lang/StringBuffer:append	(Ljava/lang/String;)Ljava/lang/StringBuffer;
/*     */     //   104: pop
/*     */     //   105: aload 4
/*     */     //   107: ifnonnull +9 -> 116
/*     */     //   110: getstatic 292	scala/runtime/BoxedUnit:UNIT	Lscala/runtime/BoxedUnit;
/*     */     //   113: goto +20 -> 133
/*     */     //   116: aload 12
/*     */     //   118: ldc_w 294
/*     */     //   121: invokevirtual 284	java/lang/StringBuffer:append	(Ljava/lang/String;)Ljava/lang/StringBuffer;
/*     */     //   124: aload_0
/*     */     //   125: aload 4
/*     */     //   127: invokevirtual 297	com/yisa/engine/branch/SparkEngineV2ForCaseCar:getDateid	(Ljava/lang/String;)Ljava/lang/String;
/*     */     //   130: invokevirtual 284	java/lang/StringBuffer:append	(Ljava/lang/String;)Ljava/lang/StringBuffer;
/*     */     //   133: pop
/*     */     //   134: aload 5
/*     */     //   136: ifnonnull +9 -> 145
/*     */     //   139: getstatic 292	scala/runtime/BoxedUnit:UNIT	Lscala/runtime/BoxedUnit;
/*     */     //   142: goto +20 -> 162
/*     */     //   145: aload 12
/*     */     //   147: ldc_w 299
/*     */     //   150: invokevirtual 284	java/lang/StringBuffer:append	(Ljava/lang/String;)Ljava/lang/StringBuffer;
/*     */     //   153: aload_0
/*     */     //   154: aload 5
/*     */     //   156: invokevirtual 297	com/yisa/engine/branch/SparkEngineV2ForCaseCar:getDateid	(Ljava/lang/String;)Ljava/lang/String;
/*     */     //   159: invokevirtual 284	java/lang/StringBuffer:append	(Ljava/lang/String;)Ljava/lang/StringBuffer;
/*     */     //   162: pop
/*     */     //   163: aload 6
/*     */     //   165: aconst_null
/*     */     //   166: if_acmpeq +97 -> 263
/*     */     //   169: aload 6
/*     */     //   171: arraylength
/*     */     //   172: iconst_0
/*     */     //   173: if_icmple +90 -> 263
/*     */     //   176: getstatic 77	scala/Predef$:MODULE$	Lscala/Predef$;
/*     */     //   179: getstatic 77	scala/Predef$:MODULE$	Lscala/Predef$;
/*     */     //   182: aload 6
/*     */     //   184: checkcast 79	[Ljava/lang/Object;
/*     */     //   187: invokevirtual 83	scala/Predef$:refArrayOps	([Ljava/lang/Object;)Lscala/collection/mutable/ArrayOps;
/*     */     //   190: new 301	com/yisa/engine/branch/SparkEngineV2ForCaseCar$$anonfun$1
/*     */     //   193: dup
/*     */     //   194: aload_0
/*     */     //   195: invokespecial 302	com/yisa/engine/branch/SparkEngineV2ForCaseCar$$anonfun$1:<init>	(Lcom/yisa/engine/branch/SparkEngineV2ForCaseCar;)V
/*     */     //   198: getstatic 307	scala/Array$:MODULE$	Lscala/Array$;
/*     */     //   201: getstatic 312	scala/reflect/ClassTag$:MODULE$	Lscala/reflect/ClassTag$;
/*     */     //   204: ldc 42
/*     */     //   206: invokevirtual 316	scala/reflect/ClassTag$:apply	(Ljava/lang/Class;)Lscala/reflect/ClassTag;
/*     */     //   209: invokevirtual 320	scala/Array$:canBuildFrom	(Lscala/reflect/ClassTag;)Lscala/collection/generic/CanBuildFrom;
/*     */     //   212: invokeinterface 323 3 0
/*     */     //   217: checkcast 79	[Ljava/lang/Object;
/*     */     //   220: invokevirtual 83	scala/Predef$:refArrayOps	([Ljava/lang/Object;)Lscala/collection/mutable/ArrayOps;
/*     */     //   223: new 325	com/yisa/engine/branch/SparkEngineV2ForCaseCar$$anonfun$2
/*     */     //   226: dup
/*     */     //   227: aload_0
/*     */     //   228: invokespecial 326	com/yisa/engine/branch/SparkEngineV2ForCaseCar$$anonfun$2:<init>	(Lcom/yisa/engine/branch/SparkEngineV2ForCaseCar;)V
/*     */     //   231: invokeinterface 330 2 0
/*     */     //   236: checkcast 42	java/lang/String
/*     */     //   239: astore 13
/*     */     //   241: aload 12
/*     */     //   243: ldc_w 332
/*     */     //   246: invokevirtual 284	java/lang/StringBuffer:append	(Ljava/lang/String;)Ljava/lang/StringBuffer;
/*     */     //   249: aload 13
/*     */     //   251: invokevirtual 284	java/lang/StringBuffer:append	(Ljava/lang/String;)Ljava/lang/StringBuffer;
/*     */     //   254: ldc_w 334
/*     */     //   257: invokevirtual 284	java/lang/StringBuffer:append	(Ljava/lang/String;)Ljava/lang/StringBuffer;
/*     */     //   260: goto +6 -> 266
/*     */     //   263: getstatic 292	scala/runtime/BoxedUnit:UNIT	Lscala/runtime/BoxedUnit;
/*     */     //   266: pop
/*     */     //   267: aload 9
/*     */     //   269: aconst_null
/*     */     //   270: if_acmpeq +61 -> 331
/*     */     //   273: aload 9
/*     */     //   275: arraylength
/*     */     //   276: iconst_0
/*     */     //   277: if_icmple +54 -> 331
/*     */     //   280: getstatic 77	scala/Predef$:MODULE$	Lscala/Predef$;
/*     */     //   283: aload 9
/*     */     //   285: checkcast 79	[Ljava/lang/Object;
/*     */     //   288: invokevirtual 83	scala/Predef$:refArrayOps	([Ljava/lang/Object;)Lscala/collection/mutable/ArrayOps;
/*     */     //   291: new 336	com/yisa/engine/branch/SparkEngineV2ForCaseCar$$anonfun$3
/*     */     //   294: dup
/*     */     //   295: aload_0
/*     */     //   296: invokespecial 337	com/yisa/engine/branch/SparkEngineV2ForCaseCar$$anonfun$3:<init>	(Lcom/yisa/engine/branch/SparkEngineV2ForCaseCar;)V
/*     */     //   299: invokeinterface 330 2 0
/*     */     //   304: checkcast 42	java/lang/String
/*     */     //   307: astore 14
/*     */     //   309: aload 12
/*     */     //   311: ldc_w 339
/*     */     //   314: invokevirtual 284	java/lang/StringBuffer:append	(Ljava/lang/String;)Ljava/lang/StringBuffer;
/*     */     //   317: aload 14
/*     */     //   319: invokevirtual 284	java/lang/StringBuffer:append	(Ljava/lang/String;)Ljava/lang/StringBuffer;
/*     */     //   322: ldc_w 334
/*     */     //   325: invokevirtual 284	java/lang/StringBuffer:append	(Ljava/lang/String;)Ljava/lang/StringBuffer;
/*     */     //   328: goto +6 -> 334
/*     */     //   331: getstatic 292	scala/runtime/BoxedUnit:UNIT	Lscala/runtime/BoxedUnit;
/*     */     //   334: pop
/*     */     //   335: aload 7
/*     */     //   337: aconst_null
/*     */     //   338: if_acmpeq +61 -> 399
/*     */     //   341: aload 7
/*     */     //   343: arraylength
/*     */     //   344: iconst_0
/*     */     //   345: if_icmple +54 -> 399
/*     */     //   348: getstatic 77	scala/Predef$:MODULE$	Lscala/Predef$;
/*     */     //   351: aload 7
/*     */     //   353: checkcast 79	[Ljava/lang/Object;
/*     */     //   356: invokevirtual 83	scala/Predef$:refArrayOps	([Ljava/lang/Object;)Lscala/collection/mutable/ArrayOps;
/*     */     //   359: new 341	com/yisa/engine/branch/SparkEngineV2ForCaseCar$$anonfun$4
/*     */     //   362: dup
/*     */     //   363: aload_0
/*     */     //   364: invokespecial 342	com/yisa/engine/branch/SparkEngineV2ForCaseCar$$anonfun$4:<init>	(Lcom/yisa/engine/branch/SparkEngineV2ForCaseCar;)V
/*     */     //   367: invokeinterface 330 2 0
/*     */     //   372: checkcast 42	java/lang/String
/*     */     //   375: astore 15
/*     */     //   377: aload 12
/*     */     //   379: ldc_w 344
/*     */     //   382: invokevirtual 284	java/lang/StringBuffer:append	(Ljava/lang/String;)Ljava/lang/StringBuffer;
/*     */     //   385: aload 15
/*     */     //   387: invokevirtual 284	java/lang/StringBuffer:append	(Ljava/lang/String;)Ljava/lang/StringBuffer;
/*     */     //   390: ldc_w 334
/*     */     //   393: invokevirtual 284	java/lang/StringBuffer:append	(Ljava/lang/String;)Ljava/lang/StringBuffer;
/*     */     //   396: goto +6 -> 402
/*     */     //   399: getstatic 292	scala/runtime/BoxedUnit:UNIT	Lscala/runtime/BoxedUnit;
/*     */     //   402: pop
/*     */     //   403: aload 8
/*     */     //   405: ifnull +31 -> 436
/*     */     //   408: aload 8
/*     */     //   410: ldc_w 346
/*     */     //   413: astore 16
/*     */     //   415: dup
/*     */     //   416: ifnonnull +12 -> 428
/*     */     //   419: pop
/*     */     //   420: aload 16
/*     */     //   422: ifnull +14 -> 436
/*     */     //   425: goto +17 -> 442
/*     */     //   428: aload 16
/*     */     //   430: invokevirtual 350	java/lang/Object:equals	(Ljava/lang/Object;)Z
/*     */     //   433: ifeq +9 -> 442
/*     */     //   436: getstatic 292	scala/runtime/BoxedUnit:UNIT	Lscala/runtime/BoxedUnit;
/*     */     //   439: goto +16 -> 455
/*     */     //   442: aload 12
/*     */     //   444: ldc_w 352
/*     */     //   447: invokevirtual 284	java/lang/StringBuffer:append	(Ljava/lang/String;)Ljava/lang/StringBuffer;
/*     */     //   450: aload 8
/*     */     //   452: invokevirtual 284	java/lang/StringBuffer:append	(Ljava/lang/String;)Ljava/lang/StringBuffer;
/*     */     //   455: pop
/*     */     //   456: aload 10
/*     */     //   458: ifnull +31 -> 489
/*     */     //   461: aload 10
/*     */     //   463: ldc_w 346
/*     */     //   466: astore 17
/*     */     //   468: dup
/*     */     //   469: ifnonnull +12 -> 481
/*     */     //   472: pop
/*     */     //   473: aload 17
/*     */     //   475: ifnull +14 -> 489
/*     */     //   478: goto +17 -> 495
/*     */     //   481: aload 17
/*     */     //   483: invokevirtual 350	java/lang/Object:equals	(Ljava/lang/Object;)Z
/*     */     //   486: ifeq +9 -> 495
/*     */     //   489: getstatic 292	scala/runtime/BoxedUnit:UNIT	Lscala/runtime/BoxedUnit;
/*     */     //   492: goto +16 -> 508
/*     */     //   495: aload 12
/*     */     //   497: ldc_w 354
/*     */     //   500: invokevirtual 284	java/lang/StringBuffer:append	(Ljava/lang/String;)Ljava/lang/StringBuffer;
/*     */     //   503: aload 10
/*     */     //   505: invokevirtual 284	java/lang/StringBuffer:append	(Ljava/lang/String;)Ljava/lang/StringBuffer;
/*     */     //   508: pop
/*     */     //   509: aload 11
/*     */     //   511: ifnull +31 -> 542
/*     */     //   514: aload 11
/*     */     //   516: ldc_w 346
/*     */     //   519: astore 18
/*     */     //   521: dup
/*     */     //   522: ifnonnull +12 -> 534
/*     */     //   525: pop
/*     */     //   526: aload 18
/*     */     //   528: ifnull +14 -> 542
/*     */     //   531: goto +17 -> 548
/*     */     //   534: aload 18
/*     */     //   536: invokevirtual 350	java/lang/Object:equals	(Ljava/lang/Object;)Z
/*     */     //   539: ifeq +9 -> 548
/*     */     //   542: getstatic 292	scala/runtime/BoxedUnit:UNIT	Lscala/runtime/BoxedUnit;
/*     */     //   545: goto +84 -> 629
/*     */     //   548: aload 11
/*     */     //   550: ldc_w 356
/*     */     //   553: invokevirtual 360	java/lang/String:contains	(Ljava/lang/CharSequence;)Z
/*     */     //   556: ifne +14 -> 570
/*     */     //   559: aload 11
/*     */     //   561: ldc_w 362
/*     */     //   564: invokevirtual 360	java/lang/String:contains	(Ljava/lang/CharSequence;)Z
/*     */     //   567: ifeq +43 -> 610
/*     */     //   570: aload 12
/*     */     //   572: ldc_w 364
/*     */     //   575: invokevirtual 284	java/lang/StringBuffer:append	(Ljava/lang/String;)Ljava/lang/StringBuffer;
/*     */     //   578: aload 11
/*     */     //   580: ldc_w 356
/*     */     //   583: ldc_w 366
/*     */     //   586: invokevirtual 370	java/lang/String:replace	(Ljava/lang/CharSequence;Ljava/lang/CharSequence;)Ljava/lang/String;
/*     */     //   589: ldc_w 362
/*     */     //   592: ldc_w 372
/*     */     //   595: invokevirtual 370	java/lang/String:replace	(Ljava/lang/CharSequence;Ljava/lang/CharSequence;)Ljava/lang/String;
/*     */     //   598: invokevirtual 284	java/lang/StringBuffer:append	(Ljava/lang/String;)Ljava/lang/StringBuffer;
/*     */     //   601: ldc_w 374
/*     */     //   604: invokevirtual 284	java/lang/StringBuffer:append	(Ljava/lang/String;)Ljava/lang/StringBuffer;
/*     */     //   607: goto +22 -> 629
/*     */     //   610: aload 12
/*     */     //   612: ldc_w 376
/*     */     //   615: invokevirtual 284	java/lang/StringBuffer:append	(Ljava/lang/String;)Ljava/lang/StringBuffer;
/*     */     //   618: aload 11
/*     */     //   620: invokevirtual 284	java/lang/StringBuffer:append	(Ljava/lang/String;)Ljava/lang/StringBuffer;
/*     */     //   623: ldc_w 378
/*     */     //   626: invokevirtual 284	java/lang/StringBuffer:append	(Ljava/lang/String;)Ljava/lang/StringBuffer;
/*     */     //   629: pop
/*     */     //   630: getstatic 77	scala/Predef$:MODULE$	Lscala/Predef$;
/*     */     //   633: aload 12
/*     */     //   635: invokevirtual 381	java/lang/StringBuffer:toString	()Ljava/lang/String;
/*     */     //   638: invokevirtual 275	scala/Predef$:println	(Ljava/lang/Object;)V
/*     */     //   641: aload 12
/*     */     //   643: invokevirtual 381	java/lang/StringBuffer:toString	()Ljava/lang/String;
/*     */     //   646: areturn
/*     */     // Line number table:
/*     */     //   Java source line #146	-> byte code offset #0
/*     */     //   Java source line #147	-> byte code offset #12
/*     */     //   Java source line #148	-> byte code offset #24
/*     */     //   Java source line #149	-> byte code offset #30
/*     */     //   Java source line #150	-> byte code offset #36
/*     */     //   Java source line #151	-> byte code offset #42
/*     */     //   Java source line #152	-> byte code offset #48
/*     */     //   Java source line #153	-> byte code offset #54
/*     */     //   Java source line #155	-> byte code offset #60
/*     */     //   Java source line #157	-> byte code offset #70
/*     */     //   Java source line #159	-> byte code offset #79
/*     */     //   Java source line #161	-> byte code offset #88
/*     */     //   Java source line #163	-> byte code offset #105
/*     */     //   Java source line #164	-> byte code offset #116
/*     */     //   Java source line #163	-> byte code offset #133
/*     */     //   Java source line #167	-> byte code offset #134
/*     */     //   Java source line #168	-> byte code offset #145
/*     */     //   Java source line #167	-> byte code offset #162
/*     */     //   Java source line #171	-> byte code offset #163
/*     */     //   Java source line #172	-> byte code offset #176
/*     */     //   Java source line #174	-> byte code offset #241
/*     */     //   Java source line #171	-> byte code offset #263
/*     */     //   Java source line #177	-> byte code offset #267
/*     */     //   Java source line #178	-> byte code offset #280
/*     */     //   Java source line #179	-> byte code offset #309
/*     */     //   Java source line #177	-> byte code offset #331
/*     */     //   Java source line #182	-> byte code offset #335
/*     */     //   Java source line #183	-> byte code offset #348
/*     */     //   Java source line #184	-> byte code offset #377
/*     */     //   Java source line #182	-> byte code offset #399
/*     */     //   Java source line #187	-> byte code offset #403
/*     */     //   Java source line #188	-> byte code offset #442
/*     */     //   Java source line #187	-> byte code offset #455
/*     */     //   Java source line #191	-> byte code offset #456
/*     */     //   Java source line #192	-> byte code offset #495
/*     */     //   Java source line #191	-> byte code offset #508
/*     */     //   Java source line #195	-> byte code offset #509
/*     */     //   Java source line #196	-> byte code offset #548
/*     */     //   Java source line #197	-> byte code offset #570
/*     */     //   Java source line #199	-> byte code offset #610
/*     */     //   Java source line #195	-> byte code offset #629
/*     */     //   Java source line #205	-> byte code offset #630
/*     */     //   Java source line #207	-> byte code offset #641
/*     */     // Local variable table:
/*     */     //   start	length	slot	name	signature
/*     */     //   0	647	0	this	SparkEngineV2ForCaseCar
/*     */     //   0	647	1	inputBean	InputBean
/*     */     //   0	647	2	typeC	String
/*     */     //   0	647	3	tableName	String
/*     */     //   12	634	4	startTime1	String
/*     */     //   24	622	5	endTime1	String
/*     */     //   30	616	6	locationId	String[]
/*     */     //   36	610	7	carModel	String[]
/*     */     //   42	604	8	carBrand	String
/*     */     //   48	598	9	carYear	String[]
/*     */     //   54	592	10	carColor	String
/*     */     //   60	586	11	plateNumber	String
/*     */     //   79	567	12	sb	StringBuffer
/*     */     //   241	19	13	l	String
/*     */     //   309	19	14	m	String
/*     */     //   377	19	15	m	String
/*     */   }
/*     */   
/*     */   public String getDateid(String timeString)
/*     */   {
/* 213 */     String timeLong = timeString.replaceAll("[-\\s:]", "");
/*     */     
/* 215 */     return timeLong.substring(0, 8);
/*     */   }
/*     */ }


/* Location:              E:\BaiduYunDownload\伊萨时期的一些代码\SparkEngine终极版\jars\YISAEngineBySpark2-4.0.6-SNAPSHOT-jar-with-dependencies.jar!\com\yisa\engine\branch\SparkEngineV2ForCaseCar.class
 * Java compiler version: 6 (50.0)
 * JD-Core Version:       0.7.1
 */