/*    */ package com.yisa.engine.other;
/*    */ 
/*    */ import scala.runtime.ScalaRunTime.;
/*    */ 
/*    */ @scala.reflect.ScalaSignature(bytes="\006\001\005}s!B\001\003\021\003Y\021AD*qCJ\\7+\025'LC\032\\\027M\r\006\003\007\021\tQa\034;iKJT!!\002\004\002\r\025tw-\0338f\025\t9\001\"\001\003zSN\f'\"A\005\002\007\r|Wn\001\001\021\0051iQ\"\001\002\007\0139\021\001\022A\b\003\035M\003\030M]6T#2[\025MZ6beM\021Q\002\005\t\003#Qi\021A\005\006\002'\005)1oY1mC&\021QC\005\002\007\003:L(+\0324\t\013]iA\021\001\r\002\rqJg.\033;?)\005Ya\001\002\016\016\001n\021a\001U3sg>t7\003B\r\0219}\001\"!E\017\n\005y\021\"a\002)s_\022,8\r\036\t\003#\001J!!\t\n\003\031M+'/[1mSj\f'\r\\3\t\021\rJ\"Q3A\005\002\021\nAA\\1nKV\tQ\005\005\002'S9\021\021cJ\005\003QI\ta\001\025:fI\0264\027B\001\026,\005\031\031FO]5oO*\021\001F\005\005\t[e\021\t\022)A\005K\005)a.Y7fA!Aq&\007BK\002\023\005\001'A\002bO\026,\022!\r\t\003#IJ!a\r\n\003\007%sG\017\003\00563\tE\t\025!\0032\003\021\tw-\032\021\t\013]IB\021A\034\025\007aR4\b\005\002:35\tQ\002C\003$m\001\007Q\005C\0030m\001\007\021\007C\004>3\005\005I\021\001 \002\t\r|\007/\037\013\004q}\002\005bB\022=!\003\005\r!\n\005\b_q\002\n\0211\0012\021\035\021\025$%A\005\002\r\013abY8qs\022\"WMZ1vYR$\023'F\001EU\t)SiK\001G!\t9E*D\001I\025\tI%*A\005v]\016DWmY6fI*\0211JE\001\013C:tw\016^1uS>t\027BA'I\005E)hn\0315fG.,GMV1sS\006t7-\032\005\b\037f\t\n\021\"\001Q\0039\031w\016]=%I\0264\027-\0367uII*\022!\025\026\003c\025CqaU\r\002\002\023\005C+A\007qe>$Wo\031;Qe\0264\027\016_\013\002+B\021akW\007\002/*\021\001,W\001\005Y\006twMC\001[\003\021Q\027M^1\n\005):\006bB/\032\003\003%\t\001M\001\raJ|G-^2u\003JLG/\037\005\b?f\t\t\021\"\001a\0039\001(o\0343vGR,E.Z7f]R$\"!\0313\021\005E\021\027BA2\023\005\r\te.\037\005\bKz\013\t\0211\0012\003\rAH%\r\005\bOf\t\t\021\"\021i\003=\001(o\0343vGRLE/\032:bi>\024X#A5\021\007)l\027-D\001l\025\ta'#\001\006d_2dWm\031;j_:L!A\\6\003\021%#XM]1u_JDq\001]\r\002\002\023\005\021/\001\005dC:,\025/^1m)\t\021X\017\005\002\022g&\021AO\005\002\b\005>|G.Z1o\021\035)w.!AA\002\005Dqa^\r\002\002\023\005\0030\001\005iCND7i\0343f)\005\t\004b\002>\032\003\003%\te_\001\ti>\034FO]5oOR\tQ\013C\004~3\005\005I\021\t@\002\r\025\fX/\0317t)\t\021x\020C\004fy\006\005\t\031A1\b\023\005\rQ\"!A\t\002\005\025\021A\002)feN|g\016E\002:\003\0171\001BG\007\002\002#\005\021\021B\n\006\003\017\tYa\b\t\b\003\033\t\031\"J\0319\033\t\tyAC\002\002\022I\tqA];oi&lW-\003\003\002\026\005=!!E!cgR\024\030m\031;Gk:\034G/[8oe!9q#a\002\005\002\005eACAA\003\021!Q\030qAA\001\n\013Z\bBCA\020\003\017\t\t\021\"!\002\"\005)\021\r\0359msR)\001(a\t\002&!11%!\bA\002\025BaaLA\017\001\004\t\004BCA\025\003\017\t\t\021\"!\002,\0059QO\\1qa2LH\003BA\027\003s\001R!EA\030\003gI1!!\r\023\005\031y\005\017^5p]B)\021#!\016&c%\031\021q\007\n\003\rQ+\b\017\\33\021%\tY$a\n\002\002\003\007\001(A\002yIAB!\"a\020\002\b\005\005I\021BA!\003-\021X-\0313SKN|GN^3\025\005\005\r\003c\001,\002F%\031\021qI,\003\r=\023'.Z2u\021\035\tY%\004C\001\003\033\nA!\\1j]R!\021qJA+!\r\t\022\021K\005\004\003'\022\"\001B+oSRD\001\"a\026\002J\001\007\021\021L\001\005CJ<7\017\005\003\022\0037*\023bAA/%\t)\021I\035:bs\002")
/*    */ public final class SparkSQLKafka2
/*    */ {
/*    */   public static void main(String[] paramArrayOfString) {
/*    */     SparkSQLKafka2..MODULE$.main(paramArrayOfString);
/*    */   }
/*    */   
/*    */   public static class Person implements scala.Product, scala.Serializable {
/*    */     private final String name;
/*    */     
/*    */     public Person(String name, int age) {
/* 16 */       scala.Product.class.$init$(this);
/*    */     }
/*    */     
/*    */     /* Error */
/*    */     public boolean equals(Object x$1)
/*    */     {
/*    */       // Byte code:
/*    */       //   0: aload_0
/*    */       //   1: aload_1
/*    */       //   2: if_acmpeq +90 -> 92
/*    */       //   5: aload_1
/*    */       //   6: astore_2
/*    */       //   7: aload_2
/*    */       //   8: instanceof 2
/*    */       //   11: ifeq +8 -> 19
/*    */       //   14: iconst_1
/*    */       //   15: istore_3
/*    */       //   16: goto +5 -> 21
/*    */       //   19: iconst_0
/*    */       //   20: istore_3
/*    */       //   21: iload_3
/*    */       //   22: ifeq +74 -> 96
/*    */       //   25: aload_1
/*    */       //   26: checkcast 2	com/yisa/engine/other/SparkSQLKafka2$Person
/*    */       //   29: astore 4
/*    */       //   31: aload_0
/*    */       //   32: invokevirtual 30	com/yisa/engine/other/SparkSQLKafka2$Person:name	()Ljava/lang/String;
/*    */       //   35: aload 4
/*    */       //   37: invokevirtual 30	com/yisa/engine/other/SparkSQLKafka2$Person:name	()Ljava/lang/String;
/*    */       //   40: astore 5
/*    */       //   42: dup
/*    */       //   43: ifnonnull +12 -> 55
/*    */       //   46: pop
/*    */       //   47: aload 5
/*    */       //   49: ifnull +14 -> 63
/*    */       //   52: goto +36 -> 88
/*    */       //   55: aload 5
/*    */       //   57: invokevirtual 91	java/lang/Object:equals	(Ljava/lang/Object;)Z
/*    */       //   60: ifeq +28 -> 88
/*    */       //   63: aload_0
/*    */       //   64: invokevirtual 33	com/yisa/engine/other/SparkSQLKafka2$Person:age	()I
/*    */       //   67: aload 4
/*    */       //   69: invokevirtual 33	com/yisa/engine/other/SparkSQLKafka2$Person:age	()I
/*    */       //   72: if_icmpne +16 -> 88
/*    */       //   75: aload 4
/*    */       //   77: aload_0
/*    */       //   78: invokevirtual 93	com/yisa/engine/other/SparkSQLKafka2$Person:canEqual	(Ljava/lang/Object;)Z
/*    */       //   81: ifeq +7 -> 88
/*    */       //   84: iconst_1
/*    */       //   85: goto +4 -> 89
/*    */       //   88: iconst_0
/*    */       //   89: ifeq +7 -> 96
/*    */       //   92: iconst_1
/*    */       //   93: goto +4 -> 97
/*    */       //   96: iconst_0
/*    */       //   97: ireturn
/*    */       // Line number table:
/*    */       //   Java source line #16	-> byte code offset #0
/*    */       // Local variable table:
/*    */       //   start	length	slot	name	signature
/*    */       //   0	98	0	this	Person
/*    */       //   0	98	1	x$1	Object
/*    */     }
/*    */     
/* 16 */     public String toString() { return ScalaRunTime..MODULE$._toString(this); } public int hashCode() { int i = -889275714;i = scala.runtime.Statics.mix(i, scala.runtime.Statics.anyHash(name()));i = scala.runtime.Statics.mix(i, age());return scala.runtime.Statics.finalizeHash(i, 2); } public boolean canEqual(Object x$1) { return x$1 instanceof Person; } public scala.collection.Iterator<Object> productIterator() { return ScalaRunTime..MODULE$.typedProductIterator(this); } public Object productElement(int x$1) { int i = x$1; switch (i) {default:  throw new IndexOutOfBoundsException(scala.runtime.BoxesRunTime.boxToInteger(x$1).toString()); case 1:  break; } return name(); } public int productArity() { return 2; } public String productPrefix() { return "Person"; } public int copy$default$2() { return age(); } public String copy$default$1() { return name(); } public Person copy(String name, int age) { return new Person(name, age); } public int age() { return this.age; } public String name() { return this.name; }
/*    */   }
/*    */ }


/* Location:              E:\BaiduYunDownload\伊萨时期的一些代码\SparkEngine终极版\jars\YISAEngineBySpark2-4.0.6-SNAPSHOT-jar-with-dependencies.jar!\com\yisa\engine\other\SparkSQLKafka2.class
 * Java compiler version: 6 (50.0)
 * JD-Core Version:       0.7.1
 */