/*   */ package com.yisa.engine.other;
/*   */ 
/*   */ import scala.runtime.ScalaRunTime.;
/*   */ 
/*   */ @scala.reflect.ScalaSignature(bytes="\006\001\005}s!B\001\003\021\003Y\021!\002+fgRD$BA\002\005\003\025yG\017[3s\025\t)a!\001\004f]\036Lg.\032\006\003\017!\tA!_5tC*\t\021\"A\002d_6\034\001\001\005\002\r\0335\t!AB\003\017\005!\005qBA\003UKN$\bh\005\002\016!A\021\021\003F\007\002%)\t1#A\003tG\006d\027-\003\002\026%\t1\021I\\=SK\032DQaF\007\005\002a\ta\001P5oSRtD#A\006\007\tii\001i\007\002\007!\026\0248o\0348\024\te\001Bd\b\t\003#uI!A\b\n\003\017A\023x\016Z;diB\021\021\003I\005\003CI\021AbU3sS\006d\027N_1cY\026D\001bI\r\003\026\004%\t\001J\001\005]\006lW-F\001&!\t1\023F\004\002\022O%\021\001FE\001\007!J,G-\0324\n\005)Z#AB*ue&twM\003\002)%!AQ&\007B\tB\003%Q%A\003oC6,\007\005\003\00503\tU\r\021\"\0011\003\r\tw-Z\013\002cA\021\021CM\005\003gI\0211!\0238u\021!)\024D!E!\002\023\t\024\001B1hK\002BQaF\r\005\002]\"2\001\017\036<!\tI\024$D\001\016\021\025\031c\0071\001&\021\025yc\0071\0012\021\035i\024$!A\005\002y\nAaY8qsR\031\001h\020!\t\017\rb\004\023!a\001K!9q\006\020I\001\002\004\t\004b\002\"\032#\003%\taQ\001\017G>\004\030\020\n3fM\006,H\016\036\0232+\005!%FA\023FW\0051\005CA$M\033\005A%BA%K\003%)hn\0315fG.,GM\003\002L%\005Q\021M\0348pi\006$\030n\0348\n\0055C%!E;oG\",7m[3e-\006\024\030.\0318dK\"9q*GI\001\n\003\001\026AD2paf$C-\0324bk2$HEM\013\002#*\022\021'\022\005\b'f\t\t\021\"\021U\0035\001(o\0343vGR\004&/\0324jqV\tQ\013\005\002W76\tqK\003\002Y3\006!A.\0318h\025\005Q\026\001\0026bm\006L!AK,\t\017uK\022\021!C\001a\005a\001O]8ek\016$\030I]5us\"9q,GA\001\n\003\001\027A\0049s_\022,8\r^#mK6,g\016\036\013\003C\022\004\"!\0052\n\005\r\024\"aA!os\"9QMXA\001\002\004\t\024a\001=%c!9q-GA\001\n\003B\027a\0049s_\022,8\r^%uKJ\fGo\034:\026\003%\0042A[7b\033\005Y'B\0017\023\003)\031w\016\0347fGRLwN\\\005\003].\024\001\"\023;fe\006$xN\035\005\baf\t\t\021\"\001r\003!\031\027M\\#rk\006dGC\001:v!\t\t2/\003\002u%\t9!i\\8mK\006t\007bB3p\003\003\005\r!\031\005\bof\t\t\021\"\021y\003!A\027m\0355D_\022,G#A\031\t\017iL\022\021!C!w\006AAo\\*ue&tw\rF\001V\021\035i\030$!A\005By\fa!Z9vC2\034HC\001:\000\021\035)G0!AA\002\005<\021\"a\001\016\003\003E\t!!\002\002\rA+'o]8o!\rI\024q\001\004\t55\t\t\021#\001\002\nM)\021qAA\006?A9\021QBA\nKEBTBAA\b\025\r\t\tBE\001\beVtG/[7f\023\021\t)\"a\004\003#\005\0237\017\036:bGR4UO\\2uS>t'\007C\004\030\003\017!\t!!\007\025\005\005\025\001\002\003>\002\b\005\005IQI>\t\025\005}\021qAA\001\n\003\013\t#A\003baBd\027\020F\0039\003G\t)\003\003\004$\003;\001\r!\n\005\007_\005u\001\031A\031\t\025\005%\022qAA\001\n\003\013Y#A\004v]\006\004\b\017\\=\025\t\0055\022\021\b\t\006#\005=\0221G\005\004\003c\021\"AB(qi&|g\016E\003\022\003k)\023'C\002\0028I\021a\001V;qY\026\024\004\"CA\036\003O\t\t\0211\0019\003\rAH\005\r\005\013\003\t9!!A\005\n\005\005\023a\003:fC\022\024Vm]8mm\026$\"!a\021\021\007Y\013)%C\002\002H]\023aa\0242kK\016$\bbBA&\033\021\005\021QJ\001\005[\006Lg\016\006\003\002P\005U\003cA\t\002R%\031\0211\013\n\003\tUs\027\016\036\005\t\003/\nI\0051\001\002Z\005!\021M]4t!\021\t\0221L\023\n\007\005u#CA\003BeJ\f\027\020")
/*   */ public final class Test8 { public static void main(String[] paramArrayOfString) { Test8..MODULE$.main(paramArrayOfString); }
/*   */   
/* 8 */   public static class Person implements scala.Product, scala.Serializable { public Person(String name, int age) { scala.Product.class.$init$(this); }
/*   */     
/*   */     private final String name;
/*   */     /* Error */
/*   */     public boolean equals(Object x$1)
/*   */     {
/*   */       // Byte code:
/*   */       //   0: aload_0
/*   */       //   1: aload_1
/*   */       //   2: if_acmpeq +90 -> 92
/*   */       //   5: aload_1
/*   */       //   6: astore_2
/*   */       //   7: aload_2
/*   */       //   8: instanceof 2
/*   */       //   11: ifeq +8 -> 19
/*   */       //   14: iconst_1
/*   */       //   15: istore_3
/*   */       //   16: goto +5 -> 21
/*   */       //   19: iconst_0
/*   */       //   20: istore_3
/*   */       //   21: iload_3
/*   */       //   22: ifeq +74 -> 96
/*   */       //   25: aload_1
/*   */       //   26: checkcast 2	com/yisa/engine/other/Test8$Person
/*   */       //   29: astore 4
/*   */       //   31: aload_0
/*   */       //   32: invokevirtual 30	com/yisa/engine/other/Test8$Person:name	()Ljava/lang/String;
/*   */       //   35: aload 4
/*   */       //   37: invokevirtual 30	com/yisa/engine/other/Test8$Person:name	()Ljava/lang/String;
/*   */       //   40: astore 5
/*   */       //   42: dup
/*   */       //   43: ifnonnull +12 -> 55
/*   */       //   46: pop
/*   */       //   47: aload 5
/*   */       //   49: ifnull +14 -> 63
/*   */       //   52: goto +36 -> 88
/*   */       //   55: aload 5
/*   */       //   57: invokevirtual 91	java/lang/Object:equals	(Ljava/lang/Object;)Z
/*   */       //   60: ifeq +28 -> 88
/*   */       //   63: aload_0
/*   */       //   64: invokevirtual 33	com/yisa/engine/other/Test8$Person:age	()I
/*   */       //   67: aload 4
/*   */       //   69: invokevirtual 33	com/yisa/engine/other/Test8$Person:age	()I
/*   */       //   72: if_icmpne +16 -> 88
/*   */       //   75: aload 4
/*   */       //   77: aload_0
/*   */       //   78: invokevirtual 93	com/yisa/engine/other/Test8$Person:canEqual	(Ljava/lang/Object;)Z
/*   */       //   81: ifeq +7 -> 88
/*   */       //   84: iconst_1
/*   */       //   85: goto +4 -> 89
/*   */       //   88: iconst_0
/*   */       //   89: ifeq +7 -> 96
/*   */       //   92: iconst_1
/*   */       //   93: goto +4 -> 97
/*   */       //   96: iconst_0
/*   */       //   97: ireturn
/*   */       // Line number table:
/*   */       //   Java source line #8	-> byte code offset #0
/*   */       // Local variable table:
/*   */       //   start	length	slot	name	signature
/*   */       //   0	98	0	this	Person
/*   */       //   0	98	1	x$1	Object
/*   */     }
/*   */     
/* 8 */     public String toString() { return ScalaRunTime..MODULE$._toString(this); } public int hashCode() { int i = -889275714;i = scala.runtime.Statics.mix(i, scala.runtime.Statics.anyHash(name()));i = scala.runtime.Statics.mix(i, age());return scala.runtime.Statics.finalizeHash(i, 2); } public boolean canEqual(Object x$1) { return x$1 instanceof Person; } public scala.collection.Iterator<Object> productIterator() { return ScalaRunTime..MODULE$.typedProductIterator(this); } public Object productElement(int x$1) { int i = x$1; switch (i) {default:  throw new IndexOutOfBoundsException(scala.runtime.BoxesRunTime.boxToInteger(x$1).toString()); case 1:  break; } return name(); } public int productArity() { return 2; } public String productPrefix() { return "Person"; } public int copy$default$2() { return age(); } public String copy$default$1() { return name(); } public Person copy(String name, int age) { return new Person(name, age); } public int age() { return this.age; } public String name() { return this.name; }
/*   */   }
/*   */ }


/* Location:              E:\BaiduYunDownload\伊萨时期的一些代码\SparkEngine终极版\jars\YISAEngineBySpark2-4.0.6-SNAPSHOT-jar-with-dependencies.jar!\com\yisa\engine\other\Test8.class
 * Java compiler version: 6 (50.0)
 * JD-Core Version:       0.7.1
 */