/*    */ package com.yisa.engine.common; import scala.runtime.Statics;
/*    */ 
/*    */ @scala.reflect.ScalaSignature(bytes="\006\001\tma\001B\001\003\001.\021\021\"\0238qkR\024U-\0318\013\005\r!\021AB2p[6|gN\003\002\006\r\0051QM\\4j]\026T!a\002\005\002\teL7/\031\006\002\023\005\0311m\\7\004\001M!\001\001\004\n\026!\ti\001#D\001\017\025\005y\021!B:dC2\f\027BA\t\017\005\031\te.\037*fMB\021QbE\005\003)9\021q\001\025:pIV\034G\017\005\002\016-%\021qC\004\002\r'\026\024\030.\0317ju\006\024G.\032\005\t3\001\021)\032!C\0015\005I1\017^1siRKW.Z\013\0027A\021Ad\b\b\003\033uI!A\b\b\002\rA\023X\rZ3g\023\t\001\023E\001\004TiJLgn\032\006\003=9A\001b\t\001\003\022\003\006IaG\001\013gR\f'\017\036+j[\026\004\003\002C\023\001\005+\007I\021\001\016\002\017\025tG\rV5nK\"Aq\005\001B\tB\003%1$\001\005f]\022$\026.\\3!\021!I\003A!f\001\n\003Q\023A\0037pG\006$\030n\0348JIV\t1\006E\002\016YmI!!\f\b\003\013\005\023(/Y=\t\021=\002!\021#Q\001\n-\n1\002\\8dCRLwN\\%eA!A\021\007\001BK\002\023\005!&\001\005dCJlu\016Z3m\021!\031\004A!E!\002\023Y\023!C2be6{G-\0327!\021!)\004A!f\001\n\003Q\022\001C2be\n\023\030M\0343\t\021]\002!\021#Q\001\nm\t\021bY1s\005J\fg\016\032\021\t\021e\002!Q3A\005\002)\nqaY1s3\026\f'\017\003\005<\001\tE\t\025!\003,\003!\031\027M]-fCJ\004\003\002C\037\001\005+\007I\021\001\016\002\021\r\f'oQ8m_JD\001b\020\001\003\022\003\006IaG\001\nG\006\0248i\0347pe\002B\001\"\021\001\003\026\004%\tAG\001\fa2\fG/\032(v[\n,'\017\003\005D\001\tE\t\025!\003\034\0031\001H.\031;f\035Vl'-\032:!\021!)\005A!f\001\n\0031\025!B2pk:$X#A$\021\0055A\025BA%\017\005\rIe\016\036\005\t\027\002\021\t\022)A\005\017\00611m\\;oi\002B\001\"\024\001\003\026\004%\tAG\001\bM\026\fG/\036:f\021!y\005A!E!\002\023Y\022\001\0034fCR,(/\032\021\t\021E\003!Q3A\005\002\031\013a\001Z5gM\026\024\b\002C*\001\005#\005\013\021B$\002\017\021LgMZ3sA!AQ\013\001BK\002\023\005a)\001\005jgJ+\007/Y5s\021!9\006A!E!\002\0239\025!C5t%\026\004\030-\033:!\021!I\006A!f\001\n\003Q\023\001C2be2+g/\0327\t\021m\003!\021#Q\001\n-\n\021bY1s\031\0264X\r\034\021\t\021u\003!Q3A\005\002i\t\021\002Z5sK\016$\030n\0348\t\021}\003!\021#Q\001\nm\t!\002Z5sK\016$\030n\0348!\021\025\t\007\001\"\001c\003\031a\024N\\5u}Qy1-\0324hQ&T7\016\\7o_B\f(\017\005\002e\0015\t!\001C\003\032A\002\0071\004C\003&A\002\0071\004C\003*A\002\0071\006C\0032A\002\0071\006C\0036A\002\0071\004C\003:A\002\0071\006C\003>A\002\0071\004C\003BA\002\0071\004C\003FA\002\007q\tC\003NA\002\0071\004C\003RA\002\007q\tC\003VA\002\007q\tC\003ZA\002\0071\006C\003^A\002\0071\004C\004u\001\005\005I\021A;\002\t\r|\007/\037\013\024GZ<\b0\037>|yvtx0!\001\002\004\005\025\021q\001\005\b3M\004\n\0211\001\034\021\035)3\017%AA\002mAq!K:\021\002\003\0071\006C\0042gB\005\t\031A\026\t\017U\032\b\023!a\0017!9\021h\035I\001\002\004Y\003bB\037t!\003\005\ra\007\005\b\003N\004\n\0211\001\034\021\035)5\017%AA\002\035Cq!T:\021\002\003\0071\004C\004RgB\005\t\031A$\t\017U\033\b\023!a\001\017\"9\021l\035I\001\002\004Y\003bB/t!\003\005\ra\007\005\n\003\027\001\021\023!C\001\003\033\tabY8qs\022\"WMZ1vYR$\023'\006\002\002\020)\0321$!\005,\005\005M\001\003BA\013\003?i!!a\006\013\t\005e\0211D\001\nk:\034\007.Z2lK\022T1!!\b\017\003)\tgN\\8uCRLwN\\\005\005\003C\t9BA\tv]\016DWmY6fIZ\013'/[1oG\026D\021\"!\n\001#\003%\t!!\004\002\035\r|\007/\037\023eK\032\fW\017\034;%e!I\021\021\006\001\022\002\023\005\0211F\001\017G>\004\030\020\n3fM\006,H\016\036\0234+\t\tiCK\002,\003#A\021\"!\r\001#\003%\t!a\013\002\035\r|\007/\037\023eK\032\fW\017\034;%i!I\021Q\007\001\022\002\023\005\021QB\001\017G>\004\030\020\n3fM\006,H\016\036\0236\021%\tI\004AI\001\n\003\tY#\001\bd_BLH\005Z3gCVdG\017\n\034\t\023\005u\002!%A\005\002\0055\021AD2paf$C-\0324bk2$He\016\005\n\003\003\002\021\023!C\001\003\033\tabY8qs\022\"WMZ1vYR$\003\bC\005\002F\001\t\n\021\"\001\002H\005q1m\0349zI\021,g-Y;mi\022JTCAA%U\r9\025\021\003\005\n\003\033\002\021\023!C\001\003\033\tqbY8qs\022\"WMZ1vYR$\023\007\r\005\n\003#\002\021\023!C\001\003\017\nqbY8qs\022\"WMZ1vYR$\023'\r\005\n\003+\002\021\023!C\001\003\017\nqbY8qs\022\"WMZ1vYR$\023G\r\005\n\0033\002\021\023!C\001\003W\tqbY8qs\022\"WMZ1vYR$\023g\r\005\n\003;\002\021\023!C\001\003\033\tqbY8qs\022\"WMZ1vYR$\023\007\016\005\n\003C\002\021\021!C!\003G\nQ\002\035:pIV\034G\017\025:fM&DXCAA3!\021\t9'!\035\016\005\005%$\002BA6\003[\nA\001\\1oO*\021\021qN\001\005U\0064\030-C\002!\003SB\001\"!\036\001\003\003%\tAR\001\raJ|G-^2u\003JLG/\037\005\n\003s\002\021\021!C\001\003w\na\002\035:pIV\034G/\0227f[\026tG\017\006\003\002~\005\r\005cA\007\002\000%\031\021\021\021\b\003\007\005s\027\020C\005\002\006\006]\024\021!a\001\017\006\031\001\020J\031\t\023\005%\005!!A\005B\005-\025a\0049s_\022,8\r^%uKJ\fGo\034:\026\005\0055\005CBAH\003+\013i(\004\002\002\022*\031\0211\023\b\002\025\r|G\016\\3di&|g.\003\003\002\030\006E%\001C%uKJ\fGo\034:\t\023\005m\005!!A\005\002\005u\025\001C2b]\026\013X/\0317\025\t\005}\025Q\025\t\004\033\005\005\026bAAR\035\t9!i\\8mK\006t\007BCAC\0033\013\t\0211\001\002~!I\021\021\026\001\002\002\023\005\0231V\001\tQ\006\034\bnQ8eKR\tq\tC\005\0020\002\t\t\021\"\021\0022\006AAo\\*ue&tw\r\006\002\002f!I\021Q\027\001\002\002\023\005\023qW\001\007KF,\030\r\\:\025\t\005}\025\021\030\005\013\003\013\013\031,!AA\002\005ut!CA_\005\005\005\t\022AA`\003%Ie\016];u\005\026\fg\016E\002e\003\0034\001\"\001\002\002\002#\005\0211Y\n\006\003\003\f)-\006\t\024\003\017\fimG\016,WmY3dG$\034\017\036[3dY\007\003\003\023T1!a3\017\003\035\021XO\034;j[\026LA!a4\002J\n\021\022IY:ue\006\034GOR;oGRLwN\\\0315\021\035\t\027\021\031C\001\003'$\"!a0\t\025\005=\026\021YA\001\n\013\n\t\f\003\006\002Z\006\005\027\021!CA\0037\fQ!\0319qYf$RdYAo\003?\f\t/a9\002f\006\035\030\021^Av\003[\fy/!=\002t\006U\030q\037\005\0073\005]\007\031A\016\t\r\025\n9\0161\001\034\021\031I\023q\033a\001W!1\021'a6A\002-Ba!NAl\001\004Y\002BB\035\002X\002\0071\006\003\004>\003/\004\ra\007\005\007\003\006]\007\031A\016\t\r\025\0139\0161\001H\021\031i\025q\033a\0017!1\021+a6A\002\035Ca!VAl\001\0049\005BB-\002X\002\0071\006\003\004^\003/\004\ra\007\005\013\003w\f\t-!A\005\002\006u\030aB;oCB\004H.\037\013\005\003\024Y\001E\003\016\005\003\021)!C\002\003\0049\021aa\0249uS>t\007#E\007\003\bmY2fK\016,7m95dR$,7%\031!\021\002\b\003\017Q+\b\017\\32i!I!QBA}\003\003\005\raY\001\004q\022\002\004B\003B\t\003\003\f\t\021\"\003\003\024\005Y!/Z1e%\026\034x\016\034<f)\t\021)\002\005\003\002h\t]\021\002\002B\r\003S\022aa\0242kK\016$\b")
/*  3 */ public class InputBean implements scala.Product, scala.Serializable { public String productPrefix() { return "InputBean"; } public int productArity() { return 14; } public Object productElement(int x$1) { int i = x$1; switch (i) {default:  throw new IndexOutOfBoundsException(scala.runtime.BoxesRunTime.boxToInteger(x$1).toString()); case 13:  break; case 12:  break; case 11:  break; case 10:  break; case 9:  break; case 8:  break; case 7:  break; case 6:  break; case 5:  break; case 4:  break; case 3:  break; case 2:  break; case 1:  break; } return startTime(); } public scala.collection.Iterator<Object> productIterator() { return scala.runtime.ScalaRunTime..MODULE$.typedProductIterator(this); } public boolean canEqual(Object x$1) { return x$1 instanceof InputBean; } public int hashCode() { int i = -889275714;i = Statics.mix(i, Statics.anyHash(startTime()));i = Statics.mix(i, Statics.anyHash(endTime()));i = Statics.mix(i, Statics.anyHash(locationId()));i = Statics.mix(i, Statics.anyHash(carModel()));i = Statics.mix(i, Statics.anyHash(carBrand()));i = Statics.mix(i, Statics.anyHash(carYear()));i = Statics.mix(i, Statics.anyHash(carColor()));i = Statics.mix(i, Statics.anyHash(plateNumber()));i = Statics.mix(i, count());i = Statics.mix(i, Statics.anyHash(feature()));i = Statics.mix(i, differ());i = Statics.mix(i, isRepair());i = Statics.mix(i, Statics.anyHash(carLevel()));i = Statics.mix(i, Statics.anyHash(direction()));return Statics.finalizeHash(i, 14); } public String toString() { return scala.runtime.ScalaRunTime..MODULE$._toString(this); } public InputBean(String startTime, String endTime, String[] locationId, String[] carModel, String carBrand, String[] carYear, String carColor, String plateNumber, int count, String feature, int differ, int isRepair, String[] carLevel, String direction) { scala.Product.class.$init$(this); }
/*    */   
/*  5 */   public String startTime() { return this.startTime; } public String copy$default$1() { return startTime(); }
/*  6 */   public String endTime() { return this.endTime; } public String copy$default$2() { return endTime(); }
/*  7 */   public String[] locationId() { return this.locationId; } public String[] copy$default$3() { return locationId(); }
/*  8 */   public String[] carModel() { return this.carModel; } public String[] copy$default$4() { return carModel(); }
/*  9 */   public String carBrand() { return this.carBrand; } public String copy$default$5() { return carBrand(); }
/* 10 */   public String[] carYear() { return this.carYear; } public String[] copy$default$6() { return carYear(); }
/* 11 */   public String carColor() { return this.carColor; } public String copy$default$7() { return carColor(); }
/* 12 */   public String plateNumber() { return this.plateNumber; } public String copy$default$8() { return plateNumber(); }
/* 13 */   public int count() { return this.count; } public int copy$default$9() { return count(); }
/* 14 */   public String feature() { return this.feature; } public String copy$default$10() { return feature(); }
/* 15 */   public int differ() { return this.differ; } public int copy$default$11() { return differ(); }
/* 16 */   public int isRepair() { return this.isRepair; } public int copy$default$12() { return isRepair(); }
/* 17 */   public String[] carLevel() { return this.carLevel; } public String[] copy$default$13() { return carLevel(); }
/* 18 */   public String direction() { return this.direction; }
/*    */   
/*    */   private final String startTime;
/*    */   public InputBean copy(String startTime, String endTime, String[] locationId, String[] carModel, String carBrand, String[] carYear, String carColor, String plateNumber, int count, String feature, int differ, int isRepair, String[] carLevel, String direction)
/*    */   {
/*  3 */     return new InputBean(
/*    */     
/*  5 */       startTime, 
/*  6 */       endTime, 
/*  7 */       locationId, 
/*  8 */       carModel, 
/*  9 */       carBrand, 
/* 10 */       carYear, 
/* 11 */       carColor, 
/* 12 */       plateNumber, 
/* 13 */       count, 
/* 14 */       feature, 
/* 15 */       differ, 
/* 16 */       isRepair, 
/* 17 */       carLevel, 
/* 18 */       direction); } public String copy$default$14() { return direction(); }
/*    */   
/*    */   public static scala.Option<scala.Tuple14<String, String, String[], String[], String, String[], String, String, Object, String, Object, Object, String[], String>> unapply(InputBean paramInputBean)
/*    */   {
/*    */     return InputBean..MODULE$.unapply(paramInputBean);
/*    */   }
/*    */   
/*    */   public static InputBean apply(String paramString1, String paramString2, String[] paramArrayOfString1, String[] paramArrayOfString2, String paramString3, String[] paramArrayOfString3, String paramString4, String paramString5, int paramInt1, String paramString6, int paramInt2, int paramInt3, String[] paramArrayOfString4, String paramString7)
/*    */   {
/*    */     return InputBean..MODULE$.apply(paramString1, paramString2, paramArrayOfString1, paramArrayOfString2, paramString3, paramArrayOfString3, paramString4, paramString5, paramInt1, paramString6, paramInt2, paramInt3, paramArrayOfString4, paramString7);
/*    */   }
/*    */   
/*    */   public static scala.Function1<scala.Tuple14<String, String, String[], String[], String, String[], String, String, Object, String, Object, Object, String[], String>, InputBean> tupled()
/*    */   {
/*    */     return InputBean..MODULE$.tupled();
/*    */   }
/*    */   
/*    */   public static scala.Function1<String, scala.Function1<String, scala.Function1<String[], scala.Function1<String[], scala.Function1<String, scala.Function1<String[], scala.Function1<String, scala.Function1<String, scala.Function1<Object, scala.Function1<String, scala.Function1<Object, scala.Function1<Object, scala.Function1<String[], scala.Function1<String, InputBean>>>>>>>>>>>>>> curried()
/*    */   {
/*    */     return InputBean..MODULE$.curried();
/*    */   }
/*    */   
/*    */   /* Error */
/*    */   public boolean equals(Object x$1)
/*    */   {
/*    */     // Byte code:
/*    */     //   0: aload_0
/*    */     //   1: aload_1
/*    */     //   2: if_acmpeq +354 -> 356
/*    */     //   5: aload_1
/*    */     //   6: astore_2
/*    */     //   7: aload_2
/*    */     //   8: instanceof 2
/*    */     //   11: ifeq +8 -> 19
/*    */     //   14: iconst_1
/*    */     //   15: istore_3
/*    */     //   16: goto +5 -> 21
/*    */     //   19: iconst_0
/*    */     //   20: istore_3
/*    */     //   21: iload_3
/*    */     //   22: ifeq +338 -> 360
/*    */     //   25: aload_1
/*    */     //   26: checkcast 2	com/yisa/engine/common/InputBean
/*    */     //   29: astore 4
/*    */     //   31: aload_0
/*    */     //   32: invokevirtual 91	com/yisa/engine/common/InputBean:startTime	()Ljava/lang/String;
/*    */     //   35: aload 4
/*    */     //   37: invokevirtual 91	com/yisa/engine/common/InputBean:startTime	()Ljava/lang/String;
/*    */     //   40: astore 5
/*    */     //   42: dup
/*    */     //   43: ifnonnull +12 -> 55
/*    */     //   46: pop
/*    */     //   47: aload 5
/*    */     //   49: ifnull +14 -> 63
/*    */     //   52: goto +300 -> 352
/*    */     //   55: aload 5
/*    */     //   57: invokevirtual 187	java/lang/Object:equals	(Ljava/lang/Object;)Z
/*    */     //   60: ifeq +292 -> 352
/*    */     //   63: aload_0
/*    */     //   64: invokevirtual 94	com/yisa/engine/common/InputBean:endTime	()Ljava/lang/String;
/*    */     //   67: aload 4
/*    */     //   69: invokevirtual 94	com/yisa/engine/common/InputBean:endTime	()Ljava/lang/String;
/*    */     //   72: astore 6
/*    */     //   74: dup
/*    */     //   75: ifnonnull +12 -> 87
/*    */     //   78: pop
/*    */     //   79: aload 6
/*    */     //   81: ifnull +14 -> 95
/*    */     //   84: goto +268 -> 352
/*    */     //   87: aload 6
/*    */     //   89: invokevirtual 187	java/lang/Object:equals	(Ljava/lang/Object;)Z
/*    */     //   92: ifeq +260 -> 352
/*    */     //   95: aload_0
/*    */     //   96: invokevirtual 97	com/yisa/engine/common/InputBean:locationId	()[Ljava/lang/String;
/*    */     //   99: aload 4
/*    */     //   101: invokevirtual 97	com/yisa/engine/common/InputBean:locationId	()[Ljava/lang/String;
/*    */     //   104: if_acmpne +248 -> 352
/*    */     //   107: aload_0
/*    */     //   108: invokevirtual 100	com/yisa/engine/common/InputBean:carModel	()[Ljava/lang/String;
/*    */     //   111: aload 4
/*    */     //   113: invokevirtual 100	com/yisa/engine/common/InputBean:carModel	()[Ljava/lang/String;
/*    */     //   116: if_acmpne +236 -> 352
/*    */     //   119: aload_0
/*    */     //   120: invokevirtual 103	com/yisa/engine/common/InputBean:carBrand	()Ljava/lang/String;
/*    */     //   123: aload 4
/*    */     //   125: invokevirtual 103	com/yisa/engine/common/InputBean:carBrand	()Ljava/lang/String;
/*    */     //   128: astore 7
/*    */     //   130: dup
/*    */     //   131: ifnonnull +12 -> 143
/*    */     //   134: pop
/*    */     //   135: aload 7
/*    */     //   137: ifnull +14 -> 151
/*    */     //   140: goto +212 -> 352
/*    */     //   143: aload 7
/*    */     //   145: invokevirtual 187	java/lang/Object:equals	(Ljava/lang/Object;)Z
/*    */     //   148: ifeq +204 -> 352
/*    */     //   151: aload_0
/*    */     //   152: invokevirtual 106	com/yisa/engine/common/InputBean:carYear	()[Ljava/lang/String;
/*    */     //   155: aload 4
/*    */     //   157: invokevirtual 106	com/yisa/engine/common/InputBean:carYear	()[Ljava/lang/String;
/*    */     //   160: if_acmpne +192 -> 352
/*    */     //   163: aload_0
/*    */     //   164: invokevirtual 109	com/yisa/engine/common/InputBean:carColor	()Ljava/lang/String;
/*    */     //   167: aload 4
/*    */     //   169: invokevirtual 109	com/yisa/engine/common/InputBean:carColor	()Ljava/lang/String;
/*    */     //   172: astore 8
/*    */     //   174: dup
/*    */     //   175: ifnonnull +12 -> 187
/*    */     //   178: pop
/*    */     //   179: aload 8
/*    */     //   181: ifnull +14 -> 195
/*    */     //   184: goto +168 -> 352
/*    */     //   187: aload 8
/*    */     //   189: invokevirtual 187	java/lang/Object:equals	(Ljava/lang/Object;)Z
/*    */     //   192: ifeq +160 -> 352
/*    */     //   195: aload_0
/*    */     //   196: invokevirtual 112	com/yisa/engine/common/InputBean:plateNumber	()Ljava/lang/String;
/*    */     //   199: aload 4
/*    */     //   201: invokevirtual 112	com/yisa/engine/common/InputBean:plateNumber	()Ljava/lang/String;
/*    */     //   204: astore 9
/*    */     //   206: dup
/*    */     //   207: ifnonnull +12 -> 219
/*    */     //   210: pop
/*    */     //   211: aload 9
/*    */     //   213: ifnull +14 -> 227
/*    */     //   216: goto +136 -> 352
/*    */     //   219: aload 9
/*    */     //   221: invokevirtual 187	java/lang/Object:equals	(Ljava/lang/Object;)Z
/*    */     //   224: ifeq +128 -> 352
/*    */     //   227: aload_0
/*    */     //   228: invokevirtual 115	com/yisa/engine/common/InputBean:count	()I
/*    */     //   231: aload 4
/*    */     //   233: invokevirtual 115	com/yisa/engine/common/InputBean:count	()I
/*    */     //   236: if_icmpne +116 -> 352
/*    */     //   239: aload_0
/*    */     //   240: invokevirtual 118	com/yisa/engine/common/InputBean:feature	()Ljava/lang/String;
/*    */     //   243: aload 4
/*    */     //   245: invokevirtual 118	com/yisa/engine/common/InputBean:feature	()Ljava/lang/String;
/*    */     //   248: astore 10
/*    */     //   250: dup
/*    */     //   251: ifnonnull +12 -> 263
/*    */     //   254: pop
/*    */     //   255: aload 10
/*    */     //   257: ifnull +14 -> 271
/*    */     //   260: goto +92 -> 352
/*    */     //   263: aload 10
/*    */     //   265: invokevirtual 187	java/lang/Object:equals	(Ljava/lang/Object;)Z
/*    */     //   268: ifeq +84 -> 352
/*    */     //   271: aload_0
/*    */     //   272: invokevirtual 121	com/yisa/engine/common/InputBean:differ	()I
/*    */     //   275: aload 4
/*    */     //   277: invokevirtual 121	com/yisa/engine/common/InputBean:differ	()I
/*    */     //   280: if_icmpne +72 -> 352
/*    */     //   283: aload_0
/*    */     //   284: invokevirtual 124	com/yisa/engine/common/InputBean:isRepair	()I
/*    */     //   287: aload 4
/*    */     //   289: invokevirtual 124	com/yisa/engine/common/InputBean:isRepair	()I
/*    */     //   292: if_icmpne +60 -> 352
/*    */     //   295: aload_0
/*    */     //   296: invokevirtual 127	com/yisa/engine/common/InputBean:carLevel	()[Ljava/lang/String;
/*    */     //   299: aload 4
/*    */     //   301: invokevirtual 127	com/yisa/engine/common/InputBean:carLevel	()[Ljava/lang/String;
/*    */     //   304: if_acmpne +48 -> 352
/*    */     //   307: aload_0
/*    */     //   308: invokevirtual 130	com/yisa/engine/common/InputBean:direction	()Ljava/lang/String;
/*    */     //   311: aload 4
/*    */     //   313: invokevirtual 130	com/yisa/engine/common/InputBean:direction	()Ljava/lang/String;
/*    */     //   316: astore 11
/*    */     //   318: dup
/*    */     //   319: ifnonnull +12 -> 331
/*    */     //   322: pop
/*    */     //   323: aload 11
/*    */     //   325: ifnull +14 -> 339
/*    */     //   328: goto +24 -> 352
/*    */     //   331: aload 11
/*    */     //   333: invokevirtual 187	java/lang/Object:equals	(Ljava/lang/Object;)Z
/*    */     //   336: ifeq +16 -> 352
/*    */     //   339: aload 4
/*    */     //   341: aload_0
/*    */     //   342: invokevirtual 189	com/yisa/engine/common/InputBean:canEqual	(Ljava/lang/Object;)Z
/*    */     //   345: ifeq +7 -> 352
/*    */     //   348: iconst_1
/*    */     //   349: goto +4 -> 353
/*    */     //   352: iconst_0
/*    */     //   353: ifeq +7 -> 360
/*    */     //   356: iconst_1
/*    */     //   357: goto +4 -> 361
/*    */     //   360: iconst_0
/*    */     //   361: ireturn
/*    */     // Line number table:
/*    */     //   Java source line #3	-> byte code offset #0
/*    */     // Local variable table:
/*    */     //   start	length	slot	name	signature
/*    */     //   0	362	0	this	InputBean
/*    */     //   0	362	1	x$1	Object
/*    */   }
/*    */ }


/* Location:              E:\BaiduYunDownload\伊萨时期的一些代码\SparkEngine终极版\jars\YISAEngineBySpark2-4.0.6-SNAPSHOT-jar-with-dependencies.jar!\com\yisa\engine\common\InputBean.class
 * Java compiler version: 6 (50.0)
 * JD-Core Version:       0.7.1
 */