/*   */ package com.yisa.engine.common; import scala.runtime.ScalaRunTime.;
/*   */ 
/*   */ @scala.reflect.ScalaSignature(bytes="\006\001\005]b\001B\001\003\001.\021\021\003T8dCRLwN\\5e?\022,G/Y5m\025\t\031A!\001\004d_6lwN\034\006\003\013\031\ta!\0328hS:,'BA\004\t\003\021I\030n]1\013\003%\t1aY8n\007\001\031B\001\001\007\023+A\021Q\002E\007\002\035)\tq\"A\003tG\006d\027-\003\002\022\035\t1\021I\\=SK\032\004\"!D\n\n\005Qq!a\002)s_\022,8\r\036\t\003\033YI!a\006\b\003\031M+'/[1mSj\f'\r\\3\t\021e\001!Q3A\005\002i\t!\002\\8dCRLwN\\5e+\005Y\002C\001\017 \035\tiQ$\003\002\037\035\0051\001K]3eK\032L!\001I\021\003\rM#(/\0338h\025\tqb\002\003\005$\001\tE\t\025!\003\034\003-awnY1uS>t\027\016\032\021\t\021\025\002!Q3A\005\002\031\nQ\001^5nKN,\022a\n\t\003\033!J!!\013\b\003\007%sG\017\003\005,\001\tE\t\025!\003(\003\031!\030.\\3tA!)Q\006\001C\001]\0051A(\0338jiz\"2aL\0313!\t\001\004!D\001\003\021\025IB\0061\001\034\021\025)C\0061\001(\021\035!\004!!A\005\002U\nAaY8qsR\031qFN\034\t\017e\031\004\023!a\0017!9Qe\rI\001\002\0049\003bB\035\001#\003%\tAO\001\017G>\004\030\020\n3fM\006,H\016\036\0232+\005Y$FA\016=W\005i\004C\001 D\033\005y$B\001!B\003%)hn\0315fG.,GM\003\002C\035\005Q\021M\0348pi\006$\030n\0348\n\005\021{$!E;oG\",7m[3e-\006\024\030.\0318dK\"9a\tAI\001\n\0039\025AD2paf$C-\0324bk2$HEM\013\002\021*\022q\005\020\005\b\025\002\t\t\021\"\021L\0035\001(o\0343vGR\004&/\0324jqV\tA\n\005\002N%6\taJ\003\002P!\006!A.\0318h\025\005\t\026\001\0026bm\006L!\001\t(\t\017Q\003\021\021!C\001M\005a\001O]8ek\016$\030I]5us\"9a\013AA\001\n\0039\026A\0049s_\022,8\r^#mK6,g\016\036\013\0031n\003\"!D-\n\005is!aA!os\"9A,VA\001\002\0049\023a\001=%c!9a\fAA\001\n\003z\026a\0049s_\022,8\r^%uKJ\fGo\034:\026\003\001\0042!\0313Y\033\005\021'BA2\017\003)\031w\016\0347fGRLwN\\\005\003K\n\024\001\"\023;fe\006$xN\035\005\bO\002\t\t\021\"\001i\003!\031\027M\\#rk\006dGCA5m!\ti!.\003\002l\035\t9!i\\8mK\006t\007b\002/g\003\003\005\r\001\027\005\b]\002\t\t\021\"\021p\003!A\027m\0355D_\022,G#A\024\t\017E\004\021\021!C!e\006AAo\\*ue&tw\rF\001M\021\035!\b!!A\005BU\fa!Z9vC2\034HCA5w\021\035a6/!AA\002a;q\001\037\002\002\002#\005\0210A\tM_\016\fG/[8oS\022|F-\032;bS2\004\"\001\r>\007\017\005\021\021\021!E\001wN\031!\020`\013\021\ru\f\taG\0240\033\005q(BA@\017\003\035\021XO\034;j[\026L1!a\001\005E\t%m\035;sC\016$h)\0368di&|gN\r\005\007[i$\t!a\002\025\003eDq!\035>\002\002\023\025#\017C\005\002\016i\f\t\021\"!\002\020\005)\021\r\0359msR)q&!\005\002\024!1\021$a\003A\002mAa!JA\006\001\0049\003\"CA\fu\006\005I\021QA\r\003\035)h.\0319qYf$B!a\007\002(A)Q\"!\b\002\"%\031\021q\004\b\003\r=\003H/[8o!\025i\0211E\016(\023\r\t)C\004\002\007)V\004H.\032\032\t\023\005%\022QCA\001\002\004y\023a\001=%a!I\021Q\006>\002\002\023%\021qF\001\fe\026\fGMU3t_24X\r\006\002\0022A\031Q*a\r\n\007\005UbJ\001\004PE*,7\r\036")
/* 3 */ public class Locationid_detail implements scala.Product, scala.Serializable { public String productPrefix() { return "Locationid_detail"; } public int productArity() { return 2; } public Object productElement(int x$1) { int i = x$1; switch (i) {default:  throw new IndexOutOfBoundsException(scala.runtime.BoxesRunTime.boxToInteger(x$1).toString()); case 1:  break; } return locationid(); } public scala.collection.Iterator<Object> productIterator() { return ScalaRunTime..MODULE$.typedProductIterator(this); } public boolean canEqual(Object x$1) { return x$1 instanceof Locationid_detail; } public int hashCode() { int i = -889275714;i = scala.runtime.Statics.mix(i, scala.runtime.Statics.anyHash(locationid()));i = scala.runtime.Statics.mix(i, times());return scala.runtime.Statics.finalizeHash(i, 2); } public String toString() { return ScalaRunTime..MODULE$._toString(this); } public Locationid_detail(String locationid, int times) { scala.Product.class.$init$(this); }
/* 4 */   public String locationid() { return this.locationid; } public String copy$default$1() { return locationid(); }
/* 5 */   public int times() { return this.times; }
/*   */   
/*   */   private final String locationid;
/*   */   public Locationid_detail copy(String locationid, int times)
/*   */   {
/* 3 */     return new Locationid_detail(
/* 4 */       locationid, 
/* 5 */       times); } public int copy$default$2() { return times(); }
/*   */   
/*   */   public static scala.Option<scala.Tuple2<String, Object>> unapply(Locationid_detail paramLocationid_detail)
/*   */   {
/*   */     return Locationid_detail..MODULE$.unapply(paramLocationid_detail);
/*   */   }
/*   */   
/*   */   public static Locationid_detail apply(String paramString, int paramInt)
/*   */   {
/*   */     return Locationid_detail..MODULE$.apply(paramString, paramInt);
/*   */   }
/*   */   
/*   */   public static scala.Function1<scala.Tuple2<String, Object>, Locationid_detail> tupled()
/*   */   {
/*   */     return Locationid_detail..MODULE$.tupled();
/*   */   }
/*   */   
/*   */   public static scala.Function1<String, scala.Function1<Object, Locationid_detail>> curried()
/*   */   {
/*   */     return Locationid_detail..MODULE$.curried();
/*   */   }
/*   */   
/*   */   /* Error */
/*   */   public boolean equals(Object x$1)
/*   */   {
/*   */     // Byte code:
/*   */     //   0: aload_0
/*   */     //   1: aload_1
/*   */     //   2: if_acmpeq +90 -> 92
/*   */     //   5: aload_1
/*   */     //   6: astore_2
/*   */     //   7: aload_2
/*   */     //   8: instanceof 2
/*   */     //   11: ifeq +8 -> 19
/*   */     //   14: iconst_1
/*   */     //   15: istore_3
/*   */     //   16: goto +5 -> 21
/*   */     //   19: iconst_0
/*   */     //   20: istore_3
/*   */     //   21: iload_3
/*   */     //   22: ifeq +74 -> 96
/*   */     //   25: aload_1
/*   */     //   26: checkcast 2	com/yisa/engine/common/Locationid_detail
/*   */     //   29: astore 4
/*   */     //   31: aload_0
/*   */     //   32: invokevirtual 53	com/yisa/engine/common/Locationid_detail:locationid	()Ljava/lang/String;
/*   */     //   35: aload 4
/*   */     //   37: invokevirtual 53	com/yisa/engine/common/Locationid_detail:locationid	()Ljava/lang/String;
/*   */     //   40: astore 5
/*   */     //   42: dup
/*   */     //   43: ifnonnull +12 -> 55
/*   */     //   46: pop
/*   */     //   47: aload 5
/*   */     //   49: ifnull +14 -> 63
/*   */     //   52: goto +36 -> 88
/*   */     //   55: aload 5
/*   */     //   57: invokevirtual 113	java/lang/Object:equals	(Ljava/lang/Object;)Z
/*   */     //   60: ifeq +28 -> 88
/*   */     //   63: aload_0
/*   */     //   64: invokevirtual 56	com/yisa/engine/common/Locationid_detail:times	()I
/*   */     //   67: aload 4
/*   */     //   69: invokevirtual 56	com/yisa/engine/common/Locationid_detail:times	()I
/*   */     //   72: if_icmpne +16 -> 88
/*   */     //   75: aload 4
/*   */     //   77: aload_0
/*   */     //   78: invokevirtual 115	com/yisa/engine/common/Locationid_detail:canEqual	(Ljava/lang/Object;)Z
/*   */     //   81: ifeq +7 -> 88
/*   */     //   84: iconst_1
/*   */     //   85: goto +4 -> 89
/*   */     //   88: iconst_0
/*   */     //   89: ifeq +7 -> 96
/*   */     //   92: iconst_1
/*   */     //   93: goto +4 -> 97
/*   */     //   96: iconst_0
/*   */     //   97: ireturn
/*   */     // Line number table:
/*   */     //   Java source line #3	-> byte code offset #0
/*   */     // Local variable table:
/*   */     //   start	length	slot	name	signature
/*   */     //   0	98	0	this	Locationid_detail
/*   */     //   0	98	1	x$1	Object
/*   */   }
/*   */ }


/* Location:              E:\BaiduYunDownload\伊萨时期的一些代码\SparkEngine终极版\jars\YISAEngineBySpark2-4.0.6-SNAPSHOT-jar-with-dependencies.jar!\com\yisa\engine\common\Locationid_detail.class
 * Java compiler version: 6 (50.0)
 * JD-Core Version:       0.7.1
 */