/*    */ package com.yisa.engine.branchV3;
/*    */ 
/*    */ import com.google.gson.Gson;
/*    */ import com.yisa.engine.common.InputBean;
/*    */ import com.yisa.engine.db.MySQLConnectManager.;
/*    */ import java.lang.reflect.Type;
/*    */ import java.sql.Connection;
/*    */ import java.sql.DriverManager;
/*    */ import java.sql.PreparedStatement;
/*    */ import java.sql.ResultSet;
/*    */ import java.sql.Statement;
/*    */ import scala.Predef.;
/*    */ import scala.Serializable;
/*    */ import scala.collection.mutable.StringBuilder;
/*    */ import scala.reflect.ScalaSignature;
/*    */ import scala.runtime.AbstractFunction1;
/*    */ import scala.runtime.AbstractFunction2;
/*    */ 
/*    */ @ScalaSignature(bytes="\006\001%3A!\001\002\001\027\t\0313\013]1sW\026sw-\0338f-N2uN\035$sKF,XM\034;ms\016\013'\017\025:fgR|'BA\002\005\003!\021'/\0318dQZ\033$BA\003\007\003\031)gnZ5oK*\021q\001C\001\005s&\034\030MC\001\n\003\r\031w.\\\002\001'\r\001A\002\006\t\003\033Ii\021A\004\006\003\037A\tA\001\\1oO*\t\021#\001\003kCZ\f\027BA\n\017\005\031y%M[3diB\021Q\"F\005\003-9\021\001BU;o]\006\024G.\032\005\t1\001\021\t\021)A\0053\005!A.\0338f!\tQ\002E\004\002\034=5\tADC\001\036\003\025\0318-\0317b\023\tyB$\001\004Qe\026$WMZ\005\003C\t\022aa\025;sS:<'BA\020\035\021!!\003A!A!\002\023I\022!\003;bE2,g*Y7f\021!1\003A!A!\002\023I\022a\003:fgVdG\017V1cY\026D\001\002\013\001\003\002\003\006I!G\001\013u.Dun\035;q_J$\b\002\003\026\001\005\003\005\013\021B\r\002\035A\023Xm\035;p\021>\034H\017U8si\")A\006\001C\001[\0051A(\0338jiz\"bA\f\0312eM\"\004CA\030\001\033\005\021\001\"\002\r,\001\004I\002\"\002\023,\001\004I\002\"\002\024,\001\004I\002\"\002\025,\001\004I\002\"\002\026,\001\004I\002\"\002\034\001\t\003:\024a\001:v]R\t\001\b\005\002\034s%\021!\b\b\002\005+:LG\017C\003=\001\021\005Q(A\007hg>t\027I\035:bs\032+hn\031\013\0053y2\005\nC\003@w\001\007\001)A\002nCB\004\"!\021#\016\003\tS!a\021\003\002\r\r|W.\\8o\023\t)%IA\005J]B,HOQ3b]\")qi\017a\0013\005\021!n\035\005\006Im\002\r!\007")
/*    */ public class SparkEngineV3ForFrequentlyCarPresto implements Runnable
/*    */ {
/*    */   private final String line;
/*    */   
/*    */   public void run()
/*    */   {
/* 26 */     String jdbcTable = this.resultTable;
/*    */     
/* 28 */     String[] line_arr = this.line.split("\\|");
/*    */     
/* 30 */     String jobId = line_arr[1];
/* 31 */     String params = line_arr[2];
/*    */     
/* 33 */     Gson gson = new Gson();
/* 34 */     Type mapType = new com.google.gson.reflect.TypeToken() {}.getType();
/* 35 */     InputBean map = (InputBean)gson.fromJson(params, mapType);
/*    */     
/* 37 */     String sqlStr = gsonArrayFunc(map, params, this.tableName);
/*    */     
/* 39 */     Predef..MODULE$.println(sqlStr);
/*    */     
/*    */ 
/*    */ 
/* 43 */     Predef..MODULE$.println(new StringBuilder().append("SQL--------------:").append(sqlStr).toString());
/*    */     
/* 45 */     int count2 = map.count();
/*    */     
/* 47 */     String PrestoURL = new StringBuilder().append("jdbc:presto://").append(this.PrestoHostPort).append("/hive/yisadata").toString();
/* 48 */     String PrestoUser = "spark";
/* 49 */     String PrestoPwd = "";
/* 50 */     String PrestoDriver = "com.facebook.presto.jdbc.PrestoDriver";
/*    */     
/* 52 */     Class.forName(PrestoDriver);
/* 53 */     Connection conn = DriverManager.getConnection(PrestoURL, PrestoUser, null);
/*    */     
/* 55 */     Statement stmt = conn.createStatement();
/*    */     
/* 57 */     ResultSet rs = stmt.executeQuery(sqlStr);
/*    */     
/* 59 */     Connection mysqlConn = MySQLConnectManager..MODULE$.getConnet(this.zkHostport);
/* 60 */     mysqlConn.setAutoCommit(false);
/* 61 */     String sql = new StringBuilder().append("insert into ").append(jdbcTable).append(" (s_id,count,j_id,l_id) values(?,?,?,?)").toString();
/* 62 */     PreparedStatement mysqlPstmt = mysqlConn.prepareStatement(sql);
/* 63 */     int count = 0;
/*    */     
/* 65 */     while (rs.next())
/*    */     {
/* 67 */       mysqlPstmt.setString(1, rs.getString(1));
/* 68 */       mysqlPstmt.setInt(2, rs.getInt(2));
/* 69 */       mysqlPstmt.setString(3, jobId);
/* 70 */       String l_id = rs.getString(3);
/* 71 */       if (l_id == null)
/*    */       {
/*    */ 
/* 74 */         mysqlPstmt.setString(4, "");
/*    */       } else {
/* 72 */         mysqlPstmt.setString(4, l_id);
/*    */       }
/*    */       
/*    */ 
/* 76 */       mysqlPstmt.addBatch();
/* 77 */       count += 1;
/*    */     }
/*    */     
/* 80 */     mysqlPstmt.executeBatch();
/*    */     
/* 82 */     String sql2 = "insert into pfgc_count (j_id,count) values(?,?)";
/* 83 */     PreparedStatement mysqlpstmt2 = mysqlConn.prepareStatement(sql2);
/*    */     
/* 85 */     if (count == 0) {
/* 86 */       count = -1;
/*    */     }
/* 88 */     mysqlpstmt2.setString(1, jobId);
/* 89 */     mysqlpstmt2.setInt(2, count);
/* 90 */     mysqlpstmt2.executeUpdate();
/* 91 */     mysqlpstmt2.close();
/*    */     
/* 93 */     mysqlConn.commit();
/* 94 */     mysqlPstmt.close();
/* 95 */     mysqlConn.close();
/*    */     
/* 97 */     rs.close();
/* 98 */     stmt.close();
/* 99 */     conn.close();
/*    */   }
/*    */   
/*    */   /* Error */
/*    */   public String gsonArrayFunc(InputBean map, String js, String tableName)
/*    */   {
/*    */     // Byte code:
/*    */     //   0: getstatic 228	com/yisa/engine/uitl/TimeUtil$:MODULE$	Lcom/yisa/engine/uitl/TimeUtil$;
/*    */     //   3: aload_1
/*    */     //   4: invokevirtual 231	com/yisa/engine/common/InputBean:startTime	()Ljava/lang/String;
/*    */     //   7: invokevirtual 235	com/yisa/engine/uitl/TimeUtil$:getTimestampLong	(Ljava/lang/String;)J
/*    */     //   10: lstore 4
/*    */     //   12: getstatic 228	com/yisa/engine/uitl/TimeUtil$:MODULE$	Lcom/yisa/engine/uitl/TimeUtil$;
/*    */     //   15: aload_1
/*    */     //   16: invokevirtual 238	com/yisa/engine/common/InputBean:endTime	()Ljava/lang/String;
/*    */     //   19: invokevirtual 235	com/yisa/engine/uitl/TimeUtil$:getTimestampLong	(Ljava/lang/String;)J
/*    */     //   22: lstore 6
/*    */     //   24: getstatic 228	com/yisa/engine/uitl/TimeUtil$:MODULE$	Lcom/yisa/engine/uitl/TimeUtil$;
/*    */     //   27: aload_1
/*    */     //   28: invokevirtual 231	com/yisa/engine/common/InputBean:startTime	()Ljava/lang/String;
/*    */     //   31: invokevirtual 242	com/yisa/engine/uitl/TimeUtil$:getDateId	(Ljava/lang/String;)I
/*    */     //   34: istore 8
/*    */     //   36: getstatic 228	com/yisa/engine/uitl/TimeUtil$:MODULE$	Lcom/yisa/engine/uitl/TimeUtil$;
/*    */     //   39: aload_1
/*    */     //   40: invokevirtual 238	com/yisa/engine/common/InputBean:endTime	()Ljava/lang/String;
/*    */     //   43: invokevirtual 242	com/yisa/engine/uitl/TimeUtil$:getDateId	(Ljava/lang/String;)I
/*    */     //   46: istore 9
/*    */     //   48: aload_1
/*    */     //   49: invokevirtual 246	com/yisa/engine/common/InputBean:locationId	()[Ljava/lang/String;
/*    */     //   52: astore 10
/*    */     //   54: aload_1
/*    */     //   55: invokevirtual 249	com/yisa/engine/common/InputBean:carModel	()[Ljava/lang/String;
/*    */     //   58: astore 11
/*    */     //   60: aload_1
/*    */     //   61: invokevirtual 252	com/yisa/engine/common/InputBean:carBrand	()Ljava/lang/String;
/*    */     //   64: astore 12
/*    */     //   66: aload_1
/*    */     //   67: invokevirtual 255	com/yisa/engine/common/InputBean:carYear	()[Ljava/lang/String;
/*    */     //   70: astore 13
/*    */     //   72: aload_1
/*    */     //   73: invokevirtual 258	com/yisa/engine/common/InputBean:carColor	()Ljava/lang/String;
/*    */     //   76: astore 14
/*    */     //   78: aload_1
/*    */     //   79: invokevirtual 261	com/yisa/engine/common/InputBean:plateNumber	()Ljava/lang/String;
/*    */     //   82: astore 15
/*    */     //   84: aload_1
/*    */     //   85: invokevirtual 83	com/yisa/engine/common/InputBean:count	()I
/*    */     //   88: istore 16
/*    */     //   90: new 263	java/lang/StringBuffer
/*    */     //   93: dup
/*    */     //   94: invokespecial 264	java/lang/StringBuffer:<init>	()V
/*    */     //   97: astore 17
/*    */     //   99: aload 17
/*    */     //   101: ldc_w 266
/*    */     //   104: invokevirtual 269	java/lang/StringBuffer:append	(Ljava/lang/String;)Ljava/lang/StringBuffer;
/*    */     //   107: pop
/*    */     //   108: aload 17
/*    */     //   110: ldc_w 271
/*    */     //   113: invokevirtual 269	java/lang/StringBuffer:append	(Ljava/lang/String;)Ljava/lang/StringBuffer;
/*    */     //   116: aload_3
/*    */     //   117: invokevirtual 269	java/lang/StringBuffer:append	(Ljava/lang/String;)Ljava/lang/StringBuffer;
/*    */     //   120: pop
/*    */     //   121: aload 17
/*    */     //   123: ldc_w 273
/*    */     //   126: invokevirtual 269	java/lang/StringBuffer:append	(Ljava/lang/String;)Ljava/lang/StringBuffer;
/*    */     //   129: pop
/*    */     //   130: aload 17
/*    */     //   132: ldc_w 275
/*    */     //   135: invokevirtual 269	java/lang/StringBuffer:append	(Ljava/lang/String;)Ljava/lang/StringBuffer;
/*    */     //   138: pop
/*    */     //   139: aload 17
/*    */     //   141: ldc_w 277
/*    */     //   144: invokevirtual 269	java/lang/StringBuffer:append	(Ljava/lang/String;)Ljava/lang/StringBuffer;
/*    */     //   147: pop
/*    */     //   148: lload 4
/*    */     //   150: lconst_0
/*    */     //   151: lcmp
/*    */     //   152: ifeq +19 -> 171
/*    */     //   155: aload 17
/*    */     //   157: ldc_w 279
/*    */     //   160: invokevirtual 269	java/lang/StringBuffer:append	(Ljava/lang/String;)Ljava/lang/StringBuffer;
/*    */     //   163: lload 4
/*    */     //   165: invokevirtual 282	java/lang/StringBuffer:append	(J)Ljava/lang/StringBuffer;
/*    */     //   168: goto +6 -> 174
/*    */     //   171: getstatic 288	scala/runtime/BoxedUnit:UNIT	Lscala/runtime/BoxedUnit;
/*    */     //   174: pop
/*    */     //   175: lload 6
/*    */     //   177: lconst_0
/*    */     //   178: lcmp
/*    */     //   179: ifeq +19 -> 198
/*    */     //   182: aload 17
/*    */     //   184: ldc_w 290
/*    */     //   187: invokevirtual 269	java/lang/StringBuffer:append	(Ljava/lang/String;)Ljava/lang/StringBuffer;
/*    */     //   190: lload 6
/*    */     //   192: invokevirtual 282	java/lang/StringBuffer:append	(J)Ljava/lang/StringBuffer;
/*    */     //   195: goto +6 -> 201
/*    */     //   198: getstatic 288	scala/runtime/BoxedUnit:UNIT	Lscala/runtime/BoxedUnit;
/*    */     //   201: pop
/*    */     //   202: aload 10
/*    */     //   204: aconst_null
/*    */     //   205: if_acmpeq +97 -> 302
/*    */     //   208: aload 10
/*    */     //   210: arraylength
/*    */     //   211: iconst_0
/*    */     //   212: if_icmple +90 -> 302
/*    */     //   215: getstatic 62	scala/Predef$:MODULE$	Lscala/Predef$;
/*    */     //   218: getstatic 62	scala/Predef$:MODULE$	Lscala/Predef$;
/*    */     //   221: aload 10
/*    */     //   223: checkcast 292	[Ljava/lang/Object;
/*    */     //   226: invokevirtual 296	scala/Predef$:refArrayOps	([Ljava/lang/Object;)Lscala/collection/mutable/ArrayOps;
/*    */     //   229: new 298	com/yisa/engine/branchV3/SparkEngineV3ForFrequentlyCarPresto$$anonfun$1
/*    */     //   232: dup
/*    */     //   233: aload_0
/*    */     //   234: invokespecial 299	com/yisa/engine/branchV3/SparkEngineV3ForFrequentlyCarPresto$$anonfun$1:<init>	(Lcom/yisa/engine/branchV3/SparkEngineV3ForFrequentlyCarPresto;)V
/*    */     //   237: getstatic 304	scala/Array$:MODULE$	Lscala/Array$;
/*    */     //   240: getstatic 309	scala/reflect/ClassTag$:MODULE$	Lscala/reflect/ClassTag$;
/*    */     //   243: ldc 26
/*    */     //   245: invokevirtual 313	scala/reflect/ClassTag$:apply	(Ljava/lang/Class;)Lscala/reflect/ClassTag;
/*    */     //   248: invokevirtual 317	scala/Array$:canBuildFrom	(Lscala/reflect/ClassTag;)Lscala/collection/generic/CanBuildFrom;
/*    */     //   251: invokeinterface 322 3 0
/*    */     //   256: checkcast 292	[Ljava/lang/Object;
/*    */     //   259: invokevirtual 296	scala/Predef$:refArrayOps	([Ljava/lang/Object;)Lscala/collection/mutable/ArrayOps;
/*    */     //   262: new 324	com/yisa/engine/branchV3/SparkEngineV3ForFrequentlyCarPresto$$anonfun$2
/*    */     //   265: dup
/*    */     //   266: aload_0
/*    */     //   267: invokespecial 325	com/yisa/engine/branchV3/SparkEngineV3ForFrequentlyCarPresto$$anonfun$2:<init>	(Lcom/yisa/engine/branchV3/SparkEngineV3ForFrequentlyCarPresto;)V
/*    */     //   270: invokeinterface 329 2 0
/*    */     //   275: checkcast 26	java/lang/String
/*    */     //   278: astore 18
/*    */     //   280: aload 17
/*    */     //   282: ldc_w 331
/*    */     //   285: invokevirtual 269	java/lang/StringBuffer:append	(Ljava/lang/String;)Ljava/lang/StringBuffer;
/*    */     //   288: aload 18
/*    */     //   290: invokevirtual 269	java/lang/StringBuffer:append	(Ljava/lang/String;)Ljava/lang/StringBuffer;
/*    */     //   293: ldc_w 333
/*    */     //   296: invokevirtual 269	java/lang/StringBuffer:append	(Ljava/lang/String;)Ljava/lang/StringBuffer;
/*    */     //   299: goto +6 -> 305
/*    */     //   302: getstatic 288	scala/runtime/BoxedUnit:UNIT	Lscala/runtime/BoxedUnit;
/*    */     //   305: pop
/*    */     //   306: aload 13
/*    */     //   308: aconst_null
/*    */     //   309: if_acmpeq +61 -> 370
/*    */     //   312: aload 13
/*    */     //   314: arraylength
/*    */     //   315: iconst_0
/*    */     //   316: if_icmple +54 -> 370
/*    */     //   319: getstatic 62	scala/Predef$:MODULE$	Lscala/Predef$;
/*    */     //   322: aload 13
/*    */     //   324: checkcast 292	[Ljava/lang/Object;
/*    */     //   327: invokevirtual 296	scala/Predef$:refArrayOps	([Ljava/lang/Object;)Lscala/collection/mutable/ArrayOps;
/*    */     //   330: new 335	com/yisa/engine/branchV3/SparkEngineV3ForFrequentlyCarPresto$$anonfun$3
/*    */     //   333: dup
/*    */     //   334: aload_0
/*    */     //   335: invokespecial 336	com/yisa/engine/branchV3/SparkEngineV3ForFrequentlyCarPresto$$anonfun$3:<init>	(Lcom/yisa/engine/branchV3/SparkEngineV3ForFrequentlyCarPresto;)V
/*    */     //   338: invokeinterface 329 2 0
/*    */     //   343: checkcast 26	java/lang/String
/*    */     //   346: astore 19
/*    */     //   348: aload 17
/*    */     //   350: ldc_w 338
/*    */     //   353: invokevirtual 269	java/lang/StringBuffer:append	(Ljava/lang/String;)Ljava/lang/StringBuffer;
/*    */     //   356: aload 19
/*    */     //   358: invokevirtual 269	java/lang/StringBuffer:append	(Ljava/lang/String;)Ljava/lang/StringBuffer;
/*    */     //   361: ldc_w 333
/*    */     //   364: invokevirtual 269	java/lang/StringBuffer:append	(Ljava/lang/String;)Ljava/lang/StringBuffer;
/*    */     //   367: goto +6 -> 373
/*    */     //   370: getstatic 288	scala/runtime/BoxedUnit:UNIT	Lscala/runtime/BoxedUnit;
/*    */     //   373: pop
/*    */     //   374: aload 11
/*    */     //   376: aconst_null
/*    */     //   377: if_acmpeq +61 -> 438
/*    */     //   380: aload 11
/*    */     //   382: arraylength
/*    */     //   383: iconst_0
/*    */     //   384: if_icmple +54 -> 438
/*    */     //   387: getstatic 62	scala/Predef$:MODULE$	Lscala/Predef$;
/*    */     //   390: aload 11
/*    */     //   392: checkcast 292	[Ljava/lang/Object;
/*    */     //   395: invokevirtual 296	scala/Predef$:refArrayOps	([Ljava/lang/Object;)Lscala/collection/mutable/ArrayOps;
/*    */     //   398: new 340	com/yisa/engine/branchV3/SparkEngineV3ForFrequentlyCarPresto$$anonfun$4
/*    */     //   401: dup
/*    */     //   402: aload_0
/*    */     //   403: invokespecial 341	com/yisa/engine/branchV3/SparkEngineV3ForFrequentlyCarPresto$$anonfun$4:<init>	(Lcom/yisa/engine/branchV3/SparkEngineV3ForFrequentlyCarPresto;)V
/*    */     //   406: invokeinterface 329 2 0
/*    */     //   411: checkcast 26	java/lang/String
/*    */     //   414: astore 20
/*    */     //   416: aload 17
/*    */     //   418: ldc_w 343
/*    */     //   421: invokevirtual 269	java/lang/StringBuffer:append	(Ljava/lang/String;)Ljava/lang/StringBuffer;
/*    */     //   424: aload 20
/*    */     //   426: invokevirtual 269	java/lang/StringBuffer:append	(Ljava/lang/String;)Ljava/lang/StringBuffer;
/*    */     //   429: ldc_w 333
/*    */     //   432: invokevirtual 269	java/lang/StringBuffer:append	(Ljava/lang/String;)Ljava/lang/StringBuffer;
/*    */     //   435: goto +6 -> 441
/*    */     //   438: getstatic 288	scala/runtime/BoxedUnit:UNIT	Lscala/runtime/BoxedUnit;
/*    */     //   441: pop
/*    */     //   442: aload 12
/*    */     //   444: ifnull +30 -> 474
/*    */     //   447: aload 12
/*    */     //   449: ldc 93
/*    */     //   451: astore 21
/*    */     //   453: dup
/*    */     //   454: ifnonnull +12 -> 466
/*    */     //   457: pop
/*    */     //   458: aload 21
/*    */     //   460: ifnull +14 -> 474
/*    */     //   463: goto +17 -> 480
/*    */     //   466: aload 21
/*    */     //   468: invokevirtual 347	java/lang/Object:equals	(Ljava/lang/Object;)Z
/*    */     //   471: ifeq +9 -> 480
/*    */     //   474: getstatic 288	scala/runtime/BoxedUnit:UNIT	Lscala/runtime/BoxedUnit;
/*    */     //   477: goto +16 -> 493
/*    */     //   480: aload 17
/*    */     //   482: ldc_w 349
/*    */     //   485: invokevirtual 269	java/lang/StringBuffer:append	(Ljava/lang/String;)Ljava/lang/StringBuffer;
/*    */     //   488: aload 12
/*    */     //   490: invokevirtual 269	java/lang/StringBuffer:append	(Ljava/lang/String;)Ljava/lang/StringBuffer;
/*    */     //   493: pop
/*    */     //   494: aload 14
/*    */     //   496: ifnull +30 -> 526
/*    */     //   499: aload 14
/*    */     //   501: ldc 93
/*    */     //   503: astore 22
/*    */     //   505: dup
/*    */     //   506: ifnonnull +12 -> 518
/*    */     //   509: pop
/*    */     //   510: aload 22
/*    */     //   512: ifnull +14 -> 526
/*    */     //   515: goto +17 -> 532
/*    */     //   518: aload 22
/*    */     //   520: invokevirtual 347	java/lang/Object:equals	(Ljava/lang/Object;)Z
/*    */     //   523: ifeq +9 -> 532
/*    */     //   526: getstatic 288	scala/runtime/BoxedUnit:UNIT	Lscala/runtime/BoxedUnit;
/*    */     //   529: goto +16 -> 545
/*    */     //   532: aload 17
/*    */     //   534: ldc_w 351
/*    */     //   537: invokevirtual 269	java/lang/StringBuffer:append	(Ljava/lang/String;)Ljava/lang/StringBuffer;
/*    */     //   540: aload 14
/*    */     //   542: invokevirtual 269	java/lang/StringBuffer:append	(Ljava/lang/String;)Ljava/lang/StringBuffer;
/*    */     //   545: pop
/*    */     //   546: aload 15
/*    */     //   548: ifnull +30 -> 578
/*    */     //   551: aload 15
/*    */     //   553: ldc 93
/*    */     //   555: astore 23
/*    */     //   557: dup
/*    */     //   558: ifnonnull +12 -> 570
/*    */     //   561: pop
/*    */     //   562: aload 23
/*    */     //   564: ifnull +14 -> 578
/*    */     //   567: goto +17 -> 584
/*    */     //   570: aload 23
/*    */     //   572: invokevirtual 347	java/lang/Object:equals	(Ljava/lang/Object;)Z
/*    */     //   575: ifeq +9 -> 584
/*    */     //   578: getstatic 288	scala/runtime/BoxedUnit:UNIT	Lscala/runtime/BoxedUnit;
/*    */     //   581: goto +84 -> 665
/*    */     //   584: aload 15
/*    */     //   586: ldc_w 353
/*    */     //   589: invokevirtual 357	java/lang/String:contains	(Ljava/lang/CharSequence;)Z
/*    */     //   592: ifne +14 -> 606
/*    */     //   595: aload 15
/*    */     //   597: ldc_w 359
/*    */     //   600: invokevirtual 357	java/lang/String:contains	(Ljava/lang/CharSequence;)Z
/*    */     //   603: ifeq +43 -> 646
/*    */     //   606: aload 17
/*    */     //   608: ldc_w 361
/*    */     //   611: invokevirtual 269	java/lang/StringBuffer:append	(Ljava/lang/String;)Ljava/lang/StringBuffer;
/*    */     //   614: aload 15
/*    */     //   616: ldc_w 353
/*    */     //   619: ldc_w 363
/*    */     //   622: invokevirtual 367	java/lang/String:replace	(Ljava/lang/CharSequence;Ljava/lang/CharSequence;)Ljava/lang/String;
/*    */     //   625: ldc_w 359
/*    */     //   628: ldc_w 369
/*    */     //   631: invokevirtual 367	java/lang/String:replace	(Ljava/lang/CharSequence;Ljava/lang/CharSequence;)Ljava/lang/String;
/*    */     //   634: invokevirtual 269	java/lang/StringBuffer:append	(Ljava/lang/String;)Ljava/lang/StringBuffer;
/*    */     //   637: ldc_w 371
/*    */     //   640: invokevirtual 269	java/lang/StringBuffer:append	(Ljava/lang/String;)Ljava/lang/StringBuffer;
/*    */     //   643: goto +22 -> 665
/*    */     //   646: aload 17
/*    */     //   648: ldc_w 373
/*    */     //   651: invokevirtual 269	java/lang/StringBuffer:append	(Ljava/lang/String;)Ljava/lang/StringBuffer;
/*    */     //   654: aload 15
/*    */     //   656: invokevirtual 269	java/lang/StringBuffer:append	(Ljava/lang/String;)Ljava/lang/StringBuffer;
/*    */     //   659: ldc_w 375
/*    */     //   662: invokevirtual 269	java/lang/StringBuffer:append	(Ljava/lang/String;)Ljava/lang/StringBuffer;
/*    */     //   665: pop
/*    */     //   666: lload 4
/*    */     //   668: lconst_0
/*    */     //   669: lcmp
/*    */     //   670: ifeq +19 -> 689
/*    */     //   673: aload 17
/*    */     //   675: ldc_w 377
/*    */     //   678: invokevirtual 269	java/lang/StringBuffer:append	(Ljava/lang/String;)Ljava/lang/StringBuffer;
/*    */     //   681: iload 8
/*    */     //   683: invokevirtual 380	java/lang/StringBuffer:append	(I)Ljava/lang/StringBuffer;
/*    */     //   686: goto +6 -> 692
/*    */     //   689: getstatic 288	scala/runtime/BoxedUnit:UNIT	Lscala/runtime/BoxedUnit;
/*    */     //   692: pop
/*    */     //   693: lload 6
/*    */     //   695: lconst_0
/*    */     //   696: lcmp
/*    */     //   697: ifeq +19 -> 716
/*    */     //   700: aload 17
/*    */     //   702: ldc_w 382
/*    */     //   705: invokevirtual 269	java/lang/StringBuffer:append	(Ljava/lang/String;)Ljava/lang/StringBuffer;
/*    */     //   708: iload 9
/*    */     //   710: invokevirtual 380	java/lang/StringBuffer:append	(I)Ljava/lang/StringBuffer;
/*    */     //   713: goto +6 -> 719
/*    */     //   716: getstatic 288	scala/runtime/BoxedUnit:UNIT	Lscala/runtime/BoxedUnit;
/*    */     //   719: pop
/*    */     //   720: aload 17
/*    */     //   722: ldc_w 384
/*    */     //   725: invokevirtual 269	java/lang/StringBuffer:append	(Ljava/lang/String;)Ljava/lang/StringBuffer;
/*    */     //   728: pop
/*    */     //   729: aload 17
/*    */     //   731: ldc_w 386
/*    */     //   734: invokevirtual 269	java/lang/StringBuffer:append	(Ljava/lang/String;)Ljava/lang/StringBuffer;
/*    */     //   737: iload 16
/*    */     //   739: invokevirtual 380	java/lang/StringBuffer:append	(I)Ljava/lang/StringBuffer;
/*    */     //   742: pop
/*    */     //   743: aload 17
/*    */     //   745: ldc_w 388
/*    */     //   748: invokevirtual 269	java/lang/StringBuffer:append	(Ljava/lang/String;)Ljava/lang/StringBuffer;
/*    */     //   751: pop
/*    */     //   752: aload 17
/*    */     //   754: ldc_w 390
/*    */     //   757: invokevirtual 269	java/lang/StringBuffer:append	(Ljava/lang/String;)Ljava/lang/StringBuffer;
/*    */     //   760: pop
/*    */     //   761: aload 17
/*    */     //   763: invokevirtual 391	java/lang/StringBuffer:toString	()Ljava/lang/String;
/*    */     //   766: areturn
/*    */     // Line number table:
/*    */     //   Java source line #108	-> byte code offset #0
/*    */     //   Java source line #109	-> byte code offset #12
/*    */     //   Java source line #111	-> byte code offset #24
/*    */     //   Java source line #112	-> byte code offset #36
/*    */     //   Java source line #114	-> byte code offset #48
/*    */     //   Java source line #115	-> byte code offset #54
/*    */     //   Java source line #116	-> byte code offset #60
/*    */     //   Java source line #117	-> byte code offset #66
/*    */     //   Java source line #118	-> byte code offset #72
/*    */     //   Java source line #119	-> byte code offset #78
/*    */     //   Java source line #120	-> byte code offset #84
/*    */     //   Java source line #122	-> byte code offset #90
/*    */     //   Java source line #124	-> byte code offset #99
/*    */     //   Java source line #127	-> byte code offset #108
/*    */     //   Java source line #129	-> byte code offset #121
/*    */     //   Java source line #130	-> byte code offset #130
/*    */     //   Java source line #131	-> byte code offset #139
/*    */     //   Java source line #133	-> byte code offset #148
/*    */     //   Java source line #134	-> byte code offset #155
/*    */     //   Java source line #133	-> byte code offset #171
/*    */     //   Java source line #137	-> byte code offset #175
/*    */     //   Java source line #138	-> byte code offset #182
/*    */     //   Java source line #137	-> byte code offset #198
/*    */     //   Java source line #141	-> byte code offset #202
/*    */     //   Java source line #142	-> byte code offset #215
/*    */     //   Java source line #143	-> byte code offset #280
/*    */     //   Java source line #141	-> byte code offset #302
/*    */     //   Java source line #146	-> byte code offset #306
/*    */     //   Java source line #147	-> byte code offset #319
/*    */     //   Java source line #148	-> byte code offset #348
/*    */     //   Java source line #146	-> byte code offset #370
/*    */     //   Java source line #151	-> byte code offset #374
/*    */     //   Java source line #152	-> byte code offset #387
/*    */     //   Java source line #153	-> byte code offset #416
/*    */     //   Java source line #151	-> byte code offset #438
/*    */     //   Java source line #156	-> byte code offset #442
/*    */     //   Java source line #157	-> byte code offset #480
/*    */     //   Java source line #156	-> byte code offset #493
/*    */     //   Java source line #160	-> byte code offset #494
/*    */     //   Java source line #161	-> byte code offset #532
/*    */     //   Java source line #160	-> byte code offset #545
/*    */     //   Java source line #164	-> byte code offset #546
/*    */     //   Java source line #165	-> byte code offset #584
/*    */     //   Java source line #166	-> byte code offset #606
/*    */     //   Java source line #168	-> byte code offset #646
/*    */     //   Java source line #164	-> byte code offset #665
/*    */     //   Java source line #179	-> byte code offset #666
/*    */     //   Java source line #180	-> byte code offset #673
/*    */     //   Java source line #179	-> byte code offset #689
/*    */     //   Java source line #183	-> byte code offset #693
/*    */     //   Java source line #184	-> byte code offset #700
/*    */     //   Java source line #183	-> byte code offset #716
/*    */     //   Java source line #187	-> byte code offset #720
/*    */     //   Java source line #189	-> byte code offset #729
/*    */     //   Java source line #190	-> byte code offset #743
/*    */     //   Java source line #191	-> byte code offset #752
/*    */     //   Java source line #193	-> byte code offset #761
/*    */     // Local variable table:
/*    */     //   start	length	slot	name	signature
/*    */     //   0	767	0	this	SparkEngineV3ForFrequentlyCarPresto
/*    */     //   0	767	1	map	InputBean
/*    */     //   0	767	2	js	String
/*    */     //   0	767	3	tableName	String
/*    */     //   12	754	4	startTime	long
/*    */     //   24	742	6	endTime	long
/*    */     //   36	730	8	startTimeDateid	int
/*    */     //   48	718	9	endTimeDateid	int
/*    */     //   54	712	10	locationId	String[]
/*    */     //   60	706	11	carModel	String[]
/*    */     //   66	700	12	carBrand	String
/*    */     //   72	694	13	carYear	String[]
/*    */     //   78	688	14	carColor	String
/*    */     //   84	682	15	plateNumber	String
/*    */     //   90	676	16	count	int
/*    */     //   99	667	17	sb	StringBuffer
/*    */     //   280	19	18	l	String
/*    */     //   348	19	19	m	String
/*    */     //   416	19	20	m	String
/*    */   }
/*    */   
/*    */   public SparkEngineV3ForFrequentlyCarPresto(String line, String tableName, String resultTable, String zkHostport, String PrestoHostPort) {}
/*    */ }


/* Location:              E:\BaiduYunDownload\伊萨时期的一些代码\SparkEngine终极版\jars\YISAEngineBySpark2-4.0.6-SNAPSHOT-jar-with-dependencies.jar!\com\yisa\engine\branchV3\SparkEngineV3ForFrequentlyCarPresto.class
 * Java compiler version: 6 (50.0)
 * JD-Core Version:       0.7.1
 */