/*     */ package com.yisa.engine.branchV3;
/*     */ 
/*     */ import com.yisa.engine.common.InputBean;
/*     */ import java.sql.Connection;
/*     */ import java.sql.PreparedStatement;
/*     */ import java.text.SimpleDateFormat;
/*     */ import org.apache.spark.sql.Dataset;
/*     */ import org.apache.spark.sql.Row;
/*     */ import scala.Serializable;
/*     */ import scala.collection.mutable.StringBuilder;
/*     */ import scala.runtime.IntRef;
/*     */ import scala.runtime.ObjectRef;
/*     */ 
/*     */ @scala.reflect.ScalaSignature(bytes="\006\001\r4A!\001\002\001\027\t92\013]1sW\026sw-\0338f-N2uN]\"bg\026\034\025M\035\006\003\007\021\t\001B\031:b]\016Dgk\r\006\003\013\031\ta!\0328hS:,'BA\004\t\003\021I\030n]1\013\003%\t1aY8n\007\001\0312\001\001\007\025!\ti!#D\001\017\025\ty\001#\001\003mC:<'\"A\t\002\t)\fg/Y\005\003'9\021aa\0242kK\016$\bCA\007\026\023\t1bB\001\005Sk:t\027M\0317f\021!A\002A!A!\002\023I\022!C:qCJ\\G)\031;b!\rQ2%J\007\0027)\021A$H\001\004gFd'B\001\020 \003\025\031\b/\031:l\025\t\001\023%\001\004ba\006\034\007.\032\006\002E\005\031qN]4\n\005\021Z\"a\002#bi\006\034X\r\036\t\0035\031J!aJ\016\003\007I{w\017\003\005*\001\t\005\t\025!\003+\003)\031\030\017\\\"p]R,\007\020\036\t\0035-J!\001L\016\003\031M\003\030M]6TKN\034\030n\0348\t\0219\002!\021!Q\001\n=\nA\001\\5oKB\021\001G\016\b\003cQj\021A\r\006\002g\005)1oY1mC&\021QGM\001\007!J,G-\0324\n\005]B$AB*ue&twM\003\0026e!A!\b\001B\001B\003%q&A\005uC\ndWMT1nK\"AA\b\001B\001B\003%q&\001\006{W\"{7\017\0369peRDQA\020\001\005\002}\na\001P5oSRtDC\002!C\007\022+e\t\005\002B\0015\t!\001C\003\031{\001\007\021\004C\003*{\001\007!\006C\003/{\001\007q\006C\003;{\001\007q\006C\003={\001\007q\006C\003I\001\021\005\023*A\002sk:$\022A\023\t\003c-K!\001\024\032\003\tUs\027\016\036\005\006\035\002!\taT\001\nO\026$x\n\0343ECf$\022a\f\005\006#\002!\tAU\001\016ON|g.\021:sCf4UO\\2\025\t=\0326,\030\005\006)B\003\r!V\001\nS:\004X\017\036\"fC:\004\"AV-\016\003]S!\001\027\003\002\r\r|W.\\8o\023\tQvKA\005J]B,HOQ3b]\")A\f\025a\001_\005)A/\0379f\007\")!\b\025a\001_!)q\f\001C\001A\006Iq-\032;ECR,\027\016\032\013\003_\005DQA\0310A\002=\n!\002^5nKN#(/\0338h\001")
/*     */ public class SparkEngineV3ForCaseCar implements Runnable
/*     */ {
/*     */   public void run()
/*     */   {
/*  19 */     Connection conn = com.yisa.engine.db.MySQLConnectManager..MODULE$.getConnet(this.zkHostport);
/*  20 */     conn.setAutoCommit(false);
/*  21 */     String sql = "insert into scajcb_result (s_id,j_id,t_id) values(?,?,?)";
/*  22 */     final ObjectRef pstmt = ObjectRef.create(conn.prepareStatement(sql));
/*     */     
/*  24 */     String[] line_arr = this.line.split("\\|");
/*     */     
/*  26 */     final String jobId = line_arr[1];
/*  27 */     String params = line_arr[2];
/*     */     
/*  29 */     com.google.gson.Gson gson = new com.google.gson.Gson();
/*  30 */     java.lang.reflect.Type mapType = new com.google.gson.reflect.TypeToken() {}.getType();
/*  31 */     InputBean[] map = (InputBean[])gson.fromJson(params, mapType);
/*     */     
/*  33 */     InputBean inputBeanRepair = null;
/*     */     
/*  35 */     scala.runtime.Null. resultData = null;
/*     */     
/*  37 */     final IntRef count = IntRef.create(0);
/*     */     
/*     */ 
/*  40 */     if (map.length > 0)
/*     */     {
/*  42 */       final IntRef i = IntRef.create(1);
/*  43 */       final ObjectRef df = ObjectRef.create(null);
/*  44 */       Dataset dfNot = null;
/*     */       
/*  46 */       scala.Predef..MODULE$.refArrayOps((Object[])map).foreach(new scala.runtime.AbstractFunction1() { public static final long serialVersionUID = 0L;
/*     */         
/*  48 */         public final void apply(InputBean m) { SimpleDateFormat format2 = new SimpleDateFormat("yyyyMMddHHmmss");
/*     */           
/*  50 */           long startTime = format2.parse(m.startTime()).getTime() / 1000L;
/*  51 */           long endTime = format2.parse(m.endTime()).getTime() / 1000L;
/*     */           
/*  53 */           if (i.elem == 1) {
/*  54 */             df.elem = SparkEngineV3ForCaseCar.this.com$yisa$engine$branchV3$SparkEngineV3ForCaseCar$$sqlContext.sql(SparkEngineV3ForCaseCar.this.gsonArrayFunc(m, new StringBuilder().append(i.elem).append("").toString(), SparkEngineV3ForCaseCar.this.com$yisa$engine$branchV3$SparkEngineV3ForCaseCar$$tableName))
/*  55 */               .filter(new StringBuilder().append("capturetime >= ").append(scala.runtime.BoxesRunTime.boxToLong(startTime)).toString())
/*  56 */               .filter(new StringBuilder().append("capturetime <= ").append(scala.runtime.BoxesRunTime.boxToLong(endTime)).toString());
/*     */             
/*  58 */             i.elem += 1;
/*     */             
/*  60 */             count.elem = m.count();
/*     */           }
/*     */           else
/*     */           {
/*  64 */             Dataset dfTemp = SparkEngineV3ForCaseCar.this.com$yisa$engine$branchV3$SparkEngineV3ForCaseCar$$sqlContext.sql(SparkEngineV3ForCaseCar.this.gsonArrayFunc(m, new StringBuilder().append(i.elem).append("").toString(), SparkEngineV3ForCaseCar.this.com$yisa$engine$branchV3$SparkEngineV3ForCaseCar$$tableName))
/*  65 */               .filter(new StringBuilder().append("capturetime >= ").append(scala.runtime.BoxesRunTime.boxToLong(startTime)).toString())
/*  66 */               .filter(new StringBuilder().append("capturetime <= ").append(scala.runtime.BoxesRunTime.boxToLong(endTime)).toString());
/*     */             
/*  68 */             df.elem = ((Dataset)df.elem).union(dfTemp);
/*     */             
/*  70 */             i.elem += 1;
/*     */           }
/*     */           
/*     */         }
/*  74 */       });
/*  75 */       Dataset dfIs = null;
/*  76 */       if ((Dataset)df.elem != null)
/*     */       {
/*  78 */         ((Dataset)df.elem).createOrReplaceTempView("df");
/*     */         
/*  80 */         String sqlUnion = "SELECT first(solrid) as solrid, platenumber, concat_ws(',',collect_set(type)) as types from df group by platenumber order by types desc limit 1000";
/*  81 */         dfIs = this.com$yisa$engine$branchV3$SparkEngineV3ForCaseCar$$sqlContext.sql(sqlUnion);
/*     */         
/*  83 */         if (count.elem >= 2)
/*     */         {
/*  85 */           if (count.elem > 2) {
/*  86 */             count.elem -= 1;
/*     */           }
/*     */           
/*  89 */           dfIs = dfIs.filter(new scala.runtime.AbstractFunction1() { public final boolean apply(Row x) { return ((String)x.getAs("types")).split(",").length >= count.elem; }
/*     */           });
/*     */         }
/*     */         
/*  93 */         dfIs.createOrReplaceTempView("dfIs");
/*     */         
/*  95 */         final IntRef number = IntRef.create(0);
/*  96 */         scala.Predef..MODULE$.refArrayOps((Object[])dfIs.collect()).foreach(new scala.runtime.AbstractFunction1() { public static final long serialVersionUID = 0L;
/*     */           
/*  98 */           public final void apply(Row data) { number.elem += 1;
/*     */             
/* 100 */             ((PreparedStatement)pstmt.elem).setString(1, data.apply(0).toString());
/* 101 */             ((PreparedStatement)pstmt.elem).setString(2, jobId);
/* 102 */             ((PreparedStatement)pstmt.elem).setString(3, data.apply(2).toString());
/* 103 */             ((PreparedStatement)pstmt.elem).addBatch();
/*     */           }
/* 105 */         });
/* 106 */         String sql2 = "insert into scajcb_progress (jobid,total) values(?,?)";
/* 107 */         PreparedStatement pstmt2 = conn.prepareStatement(sql2);
/*     */         
/* 109 */         if (number.elem == 0) {
/* 110 */           number.elem = -1;
/*     */         }
/* 112 */         pstmt2.setString(1, jobId);
/* 113 */         pstmt2.setInt(2, number.elem);
/* 114 */         pstmt2.executeUpdate();
/* 115 */         pstmt2.close();
/*     */         
/* 117 */         ((PreparedStatement)pstmt.elem).executeBatch();
/* 118 */         conn.commit();
/* 119 */         ((PreparedStatement)pstmt.elem).close();
/* 120 */         conn.close();
/*     */       }
/*     */     }
/*     */   }
/*     */   
/*     */ 
/*     */   public static final long serialVersionUID = 0L;
/*     */   public String getOldDay()
/*     */   {
/* 129 */     SimpleDateFormat dateFormat = new SimpleDateFormat("yyyyMMdd");
/* 130 */     java.util.Calendar cal = java.util.Calendar.getInstance();
/* 131 */     cal.add(5, -3);
/* 132 */     String yesterday = dateFormat.format(cal.getTime());
/*     */     
/* 134 */     return yesterday;
/*     */   }
/*     */   
/*     */   /* Error */
/*     */   public String gsonArrayFunc(InputBean inputBean, String typeC, String tableName)
/*     */   {
/*     */     // Byte code:
/*     */     //   0: getstatic 246	com/yisa/engine/uitl/TimeUtil$:MODULE$	Lcom/yisa/engine/uitl/TimeUtil$;
/*     */     //   3: aload_1
/*     */     //   4: invokevirtual 251	com/yisa/engine/common/InputBean:startTime	()Ljava/lang/String;
/*     */     //   7: invokevirtual 255	com/yisa/engine/uitl/TimeUtil$:getTimeStringFormat	(Ljava/lang/String;)Ljava/lang/String;
/*     */     //   10: astore 4
/*     */     //   12: getstatic 246	com/yisa/engine/uitl/TimeUtil$:MODULE$	Lcom/yisa/engine/uitl/TimeUtil$;
/*     */     //   15: aload_1
/*     */     //   16: invokevirtual 258	com/yisa/engine/common/InputBean:endTime	()Ljava/lang/String;
/*     */     //   19: invokevirtual 255	com/yisa/engine/uitl/TimeUtil$:getTimeStringFormat	(Ljava/lang/String;)Ljava/lang/String;
/*     */     //   22: astore 5
/*     */     //   24: aload_1
/*     */     //   25: invokevirtual 262	com/yisa/engine/common/InputBean:locationId	()[Ljava/lang/String;
/*     */     //   28: astore 6
/*     */     //   30: aload_1
/*     */     //   31: invokevirtual 265	com/yisa/engine/common/InputBean:carModel	()[Ljava/lang/String;
/*     */     //   34: astore 7
/*     */     //   36: aload_1
/*     */     //   37: invokevirtual 268	com/yisa/engine/common/InputBean:carBrand	()Ljava/lang/String;
/*     */     //   40: astore 8
/*     */     //   42: aload_1
/*     */     //   43: invokevirtual 271	com/yisa/engine/common/InputBean:carYear	()[Ljava/lang/String;
/*     */     //   46: astore 9
/*     */     //   48: aload_1
/*     */     //   49: invokevirtual 274	com/yisa/engine/common/InputBean:carColor	()Ljava/lang/String;
/*     */     //   52: astore 10
/*     */     //   54: aload_1
/*     */     //   55: invokevirtual 277	com/yisa/engine/common/InputBean:plateNumber	()Ljava/lang/String;
/*     */     //   58: astore 11
/*     */     //   60: getstatic 88	scala/Predef$:MODULE$	Lscala/Predef$;
/*     */     //   63: aload_1
/*     */     //   64: invokevirtual 262	com/yisa/engine/common/InputBean:locationId	()[Ljava/lang/String;
/*     */     //   67: invokevirtual 281	scala/Predef$:println	(Ljava/lang/Object;)V
/*     */     //   70: new 283	java/lang/StringBuffer
/*     */     //   73: dup
/*     */     //   74: invokespecial 284	java/lang/StringBuffer:<init>	()V
/*     */     //   77: astore 12
/*     */     //   79: aload 12
/*     */     //   81: ldc_w 286
/*     */     //   84: invokevirtual 290	java/lang/StringBuffer:append	(Ljava/lang/String;)Ljava/lang/StringBuffer;
/*     */     //   87: pop
/*     */     //   88: aload 12
/*     */     //   90: aload_2
/*     */     //   91: invokevirtual 290	java/lang/StringBuffer:append	(Ljava/lang/String;)Ljava/lang/StringBuffer;
/*     */     //   94: ldc_w 292
/*     */     //   97: invokevirtual 290	java/lang/StringBuffer:append	(Ljava/lang/String;)Ljava/lang/StringBuffer;
/*     */     //   100: aload_3
/*     */     //   101: invokevirtual 290	java/lang/StringBuffer:append	(Ljava/lang/String;)Ljava/lang/StringBuffer;
/*     */     //   104: pop
/*     */     //   105: aload 4
/*     */     //   107: ifnonnull +9 -> 116
/*     */     //   110: getstatic 298	scala/runtime/BoxedUnit:UNIT	Lscala/runtime/BoxedUnit;
/*     */     //   113: goto +20 -> 133
/*     */     //   116: aload 12
/*     */     //   118: ldc_w 300
/*     */     //   121: invokevirtual 290	java/lang/StringBuffer:append	(Ljava/lang/String;)Ljava/lang/StringBuffer;
/*     */     //   124: aload_0
/*     */     //   125: aload 4
/*     */     //   127: invokevirtual 303	com/yisa/engine/branchV3/SparkEngineV3ForCaseCar:getDateid	(Ljava/lang/String;)Ljava/lang/String;
/*     */     //   130: invokevirtual 290	java/lang/StringBuffer:append	(Ljava/lang/String;)Ljava/lang/StringBuffer;
/*     */     //   133: pop
/*     */     //   134: aload 5
/*     */     //   136: ifnonnull +9 -> 145
/*     */     //   139: getstatic 298	scala/runtime/BoxedUnit:UNIT	Lscala/runtime/BoxedUnit;
/*     */     //   142: goto +20 -> 162
/*     */     //   145: aload 12
/*     */     //   147: ldc_w 305
/*     */     //   150: invokevirtual 290	java/lang/StringBuffer:append	(Ljava/lang/String;)Ljava/lang/StringBuffer;
/*     */     //   153: aload_0
/*     */     //   154: aload 5
/*     */     //   156: invokevirtual 303	com/yisa/engine/branchV3/SparkEngineV3ForCaseCar:getDateid	(Ljava/lang/String;)Ljava/lang/String;
/*     */     //   159: invokevirtual 290	java/lang/StringBuffer:append	(Ljava/lang/String;)Ljava/lang/StringBuffer;
/*     */     //   162: pop
/*     */     //   163: aload 6
/*     */     //   165: aconst_null
/*     */     //   166: if_acmpeq +97 -> 263
/*     */     //   169: aload 6
/*     */     //   171: arraylength
/*     */     //   172: iconst_0
/*     */     //   173: if_icmple +90 -> 263
/*     */     //   176: getstatic 88	scala/Predef$:MODULE$	Lscala/Predef$;
/*     */     //   179: getstatic 88	scala/Predef$:MODULE$	Lscala/Predef$;
/*     */     //   182: aload 6
/*     */     //   184: checkcast 90	[Ljava/lang/Object;
/*     */     //   187: invokevirtual 94	scala/Predef$:refArrayOps	([Ljava/lang/Object;)Lscala/collection/mutable/ArrayOps;
/*     */     //   190: new 307	com/yisa/engine/branchV3/SparkEngineV3ForCaseCar$$anonfun$1
/*     */     //   193: dup
/*     */     //   194: aload_0
/*     */     //   195: invokespecial 308	com/yisa/engine/branchV3/SparkEngineV3ForCaseCar$$anonfun$1:<init>	(Lcom/yisa/engine/branchV3/SparkEngineV3ForCaseCar;)V
/*     */     //   198: getstatic 313	scala/Array$:MODULE$	Lscala/Array$;
/*     */     //   201: getstatic 318	scala/reflect/ClassTag$:MODULE$	Lscala/reflect/ClassTag$;
/*     */     //   204: ldc 54
/*     */     //   206: invokevirtual 322	scala/reflect/ClassTag$:apply	(Ljava/lang/Class;)Lscala/reflect/ClassTag;
/*     */     //   209: invokevirtual 326	scala/Array$:canBuildFrom	(Lscala/reflect/ClassTag;)Lscala/collection/generic/CanBuildFrom;
/*     */     //   212: invokeinterface 329 3 0
/*     */     //   217: checkcast 90	[Ljava/lang/Object;
/*     */     //   220: invokevirtual 94	scala/Predef$:refArrayOps	([Ljava/lang/Object;)Lscala/collection/mutable/ArrayOps;
/*     */     //   223: new 331	com/yisa/engine/branchV3/SparkEngineV3ForCaseCar$$anonfun$2
/*     */     //   226: dup
/*     */     //   227: aload_0
/*     */     //   228: invokespecial 332	com/yisa/engine/branchV3/SparkEngineV3ForCaseCar$$anonfun$2:<init>	(Lcom/yisa/engine/branchV3/SparkEngineV3ForCaseCar;)V
/*     */     //   231: invokeinterface 336 2 0
/*     */     //   236: checkcast 54	java/lang/String
/*     */     //   239: astore 13
/*     */     //   241: aload 12
/*     */     //   243: ldc_w 338
/*     */     //   246: invokevirtual 290	java/lang/StringBuffer:append	(Ljava/lang/String;)Ljava/lang/StringBuffer;
/*     */     //   249: aload 13
/*     */     //   251: invokevirtual 290	java/lang/StringBuffer:append	(Ljava/lang/String;)Ljava/lang/StringBuffer;
/*     */     //   254: ldc_w 340
/*     */     //   257: invokevirtual 290	java/lang/StringBuffer:append	(Ljava/lang/String;)Ljava/lang/StringBuffer;
/*     */     //   260: goto +6 -> 266
/*     */     //   263: getstatic 298	scala/runtime/BoxedUnit:UNIT	Lscala/runtime/BoxedUnit;
/*     */     //   266: pop
/*     */     //   267: aload 7
/*     */     //   269: aconst_null
/*     */     //   270: if_acmpeq +61 -> 331
/*     */     //   273: aload 7
/*     */     //   275: arraylength
/*     */     //   276: iconst_0
/*     */     //   277: if_icmple +54 -> 331
/*     */     //   280: getstatic 88	scala/Predef$:MODULE$	Lscala/Predef$;
/*     */     //   283: aload 7
/*     */     //   285: checkcast 90	[Ljava/lang/Object;
/*     */     //   288: invokevirtual 94	scala/Predef$:refArrayOps	([Ljava/lang/Object;)Lscala/collection/mutable/ArrayOps;
/*     */     //   291: new 342	com/yisa/engine/branchV3/SparkEngineV3ForCaseCar$$anonfun$3
/*     */     //   294: dup
/*     */     //   295: aload_0
/*     */     //   296: invokespecial 343	com/yisa/engine/branchV3/SparkEngineV3ForCaseCar$$anonfun$3:<init>	(Lcom/yisa/engine/branchV3/SparkEngineV3ForCaseCar;)V
/*     */     //   299: invokeinterface 336 2 0
/*     */     //   304: checkcast 54	java/lang/String
/*     */     //   307: astore 14
/*     */     //   309: aload 12
/*     */     //   311: ldc_w 345
/*     */     //   314: invokevirtual 290	java/lang/StringBuffer:append	(Ljava/lang/String;)Ljava/lang/StringBuffer;
/*     */     //   317: aload 14
/*     */     //   319: invokevirtual 290	java/lang/StringBuffer:append	(Ljava/lang/String;)Ljava/lang/StringBuffer;
/*     */     //   322: ldc_w 340
/*     */     //   325: invokevirtual 290	java/lang/StringBuffer:append	(Ljava/lang/String;)Ljava/lang/StringBuffer;
/*     */     //   328: goto +6 -> 334
/*     */     //   331: getstatic 298	scala/runtime/BoxedUnit:UNIT	Lscala/runtime/BoxedUnit;
/*     */     //   334: pop
/*     */     //   335: aload 8
/*     */     //   337: ifnull +31 -> 368
/*     */     //   340: aload 8
/*     */     //   342: ldc_w 347
/*     */     //   345: astore 15
/*     */     //   347: dup
/*     */     //   348: ifnonnull +12 -> 360
/*     */     //   351: pop
/*     */     //   352: aload 15
/*     */     //   354: ifnull +14 -> 368
/*     */     //   357: goto +17 -> 374
/*     */     //   360: aload 15
/*     */     //   362: invokevirtual 351	java/lang/Object:equals	(Ljava/lang/Object;)Z
/*     */     //   365: ifeq +9 -> 374
/*     */     //   368: getstatic 298	scala/runtime/BoxedUnit:UNIT	Lscala/runtime/BoxedUnit;
/*     */     //   371: goto +16 -> 387
/*     */     //   374: aload 12
/*     */     //   376: ldc_w 353
/*     */     //   379: invokevirtual 290	java/lang/StringBuffer:append	(Ljava/lang/String;)Ljava/lang/StringBuffer;
/*     */     //   382: aload 8
/*     */     //   384: invokevirtual 290	java/lang/StringBuffer:append	(Ljava/lang/String;)Ljava/lang/StringBuffer;
/*     */     //   387: pop
/*     */     //   388: aload 10
/*     */     //   390: ifnull +31 -> 421
/*     */     //   393: aload 10
/*     */     //   395: ldc_w 347
/*     */     //   398: astore 16
/*     */     //   400: dup
/*     */     //   401: ifnonnull +12 -> 413
/*     */     //   404: pop
/*     */     //   405: aload 16
/*     */     //   407: ifnull +14 -> 421
/*     */     //   410: goto +17 -> 427
/*     */     //   413: aload 16
/*     */     //   415: invokevirtual 351	java/lang/Object:equals	(Ljava/lang/Object;)Z
/*     */     //   418: ifeq +9 -> 427
/*     */     //   421: getstatic 298	scala/runtime/BoxedUnit:UNIT	Lscala/runtime/BoxedUnit;
/*     */     //   424: goto +16 -> 440
/*     */     //   427: aload 12
/*     */     //   429: ldc_w 355
/*     */     //   432: invokevirtual 290	java/lang/StringBuffer:append	(Ljava/lang/String;)Ljava/lang/StringBuffer;
/*     */     //   435: aload 10
/*     */     //   437: invokevirtual 290	java/lang/StringBuffer:append	(Ljava/lang/String;)Ljava/lang/StringBuffer;
/*     */     //   440: pop
/*     */     //   441: aload 11
/*     */     //   443: ifnull +31 -> 474
/*     */     //   446: aload 11
/*     */     //   448: ldc_w 347
/*     */     //   451: astore 17
/*     */     //   453: dup
/*     */     //   454: ifnonnull +12 -> 466
/*     */     //   457: pop
/*     */     //   458: aload 17
/*     */     //   460: ifnull +14 -> 474
/*     */     //   463: goto +17 -> 480
/*     */     //   466: aload 17
/*     */     //   468: invokevirtual 351	java/lang/Object:equals	(Ljava/lang/Object;)Z
/*     */     //   471: ifeq +9 -> 480
/*     */     //   474: getstatic 298	scala/runtime/BoxedUnit:UNIT	Lscala/runtime/BoxedUnit;
/*     */     //   477: goto +16 -> 493
/*     */     //   480: aload 12
/*     */     //   482: ldc_w 357
/*     */     //   485: invokevirtual 290	java/lang/StringBuffer:append	(Ljava/lang/String;)Ljava/lang/StringBuffer;
/*     */     //   488: aload 11
/*     */     //   490: invokevirtual 290	java/lang/StringBuffer:append	(Ljava/lang/String;)Ljava/lang/StringBuffer;
/*     */     //   493: pop
/*     */     //   494: getstatic 88	scala/Predef$:MODULE$	Lscala/Predef$;
/*     */     //   497: aload 12
/*     */     //   499: invokevirtual 360	java/lang/StringBuffer:toString	()Ljava/lang/String;
/*     */     //   502: invokevirtual 281	scala/Predef$:println	(Ljava/lang/Object;)V
/*     */     //   505: aload 12
/*     */     //   507: invokevirtual 360	java/lang/StringBuffer:toString	()Ljava/lang/String;
/*     */     //   510: areturn
/*     */     // Line number table:
/*     */     //   Java source line #142	-> byte code offset #0
/*     */     //   Java source line #143	-> byte code offset #12
/*     */     //   Java source line #144	-> byte code offset #24
/*     */     //   Java source line #145	-> byte code offset #30
/*     */     //   Java source line #146	-> byte code offset #36
/*     */     //   Java source line #147	-> byte code offset #42
/*     */     //   Java source line #148	-> byte code offset #48
/*     */     //   Java source line #149	-> byte code offset #54
/*     */     //   Java source line #151	-> byte code offset #60
/*     */     //   Java source line #153	-> byte code offset #70
/*     */     //   Java source line #155	-> byte code offset #79
/*     */     //   Java source line #157	-> byte code offset #88
/*     */     //   Java source line #159	-> byte code offset #105
/*     */     //   Java source line #160	-> byte code offset #116
/*     */     //   Java source line #159	-> byte code offset #133
/*     */     //   Java source line #163	-> byte code offset #134
/*     */     //   Java source line #164	-> byte code offset #145
/*     */     //   Java source line #163	-> byte code offset #162
/*     */     //   Java source line #167	-> byte code offset #163
/*     */     //   Java source line #168	-> byte code offset #176
/*     */     //   Java source line #170	-> byte code offset #241
/*     */     //   Java source line #167	-> byte code offset #263
/*     */     //   Java source line #173	-> byte code offset #267
/*     */     //   Java source line #174	-> byte code offset #280
/*     */     //   Java source line #175	-> byte code offset #309
/*     */     //   Java source line #173	-> byte code offset #331
/*     */     //   Java source line #178	-> byte code offset #335
/*     */     //   Java source line #179	-> byte code offset #374
/*     */     //   Java source line #178	-> byte code offset #387
/*     */     //   Java source line #182	-> byte code offset #388
/*     */     //   Java source line #183	-> byte code offset #427
/*     */     //   Java source line #182	-> byte code offset #440
/*     */     //   Java source line #186	-> byte code offset #441
/*     */     //   Java source line #187	-> byte code offset #480
/*     */     //   Java source line #186	-> byte code offset #493
/*     */     //   Java source line #192	-> byte code offset #494
/*     */     //   Java source line #194	-> byte code offset #505
/*     */     // Local variable table:
/*     */     //   start	length	slot	name	signature
/*     */     //   0	511	0	this	SparkEngineV3ForCaseCar
/*     */     //   0	511	1	inputBean	InputBean
/*     */     //   0	511	2	typeC	String
/*     */     //   0	511	3	tableName	String
/*     */     //   12	498	4	startTime1	String
/*     */     //   24	486	5	endTime1	String
/*     */     //   30	480	6	locationId	String[]
/*     */     //   36	474	7	carModel	String[]
/*     */     //   42	468	8	carBrand	String
/*     */     //   48	462	9	carYear	String[]
/*     */     //   54	456	10	carColor	String
/*     */     //   60	450	11	plateNumber	String
/*     */     //   79	431	12	sb	StringBuffer
/*     */     //   241	19	13	l	String
/*     */     //   309	19	14	m	String
/*     */   }
/*     */   
/*     */   public String getDateid(String timeString)
/*     */   {
/* 200 */     String timeLong = timeString.replaceAll("[-\\s:]", "");
/*     */     
/* 202 */     return timeLong.substring(0, 8);
/*     */   }
/*     */   
/*     */   public SparkEngineV3ForCaseCar(Dataset<Row> sparkData, org.apache.spark.sql.SparkSession sqlContext, String line, String tableName, String zkHostport) {}
/*     */ }


/* Location:              E:\BaiduYunDownload\伊萨时期的一些代码\SparkEngine终极版\jars\YISAEngineBySpark2-4.0.6-SNAPSHOT-jar-with-dependencies.jar!\com\yisa\engine\branchV3\SparkEngineV3ForCaseCar.class
 * Java compiler version: 6 (50.0)
 * JD-Core Version:       0.7.1
 */