/*     */ package com.yisa.engine.branchV3;
/*     */ 
/*     */ import com.yisa.engine.common.InputBean;
/*     */ import java.sql.Connection;
/*     */ import java.sql.PreparedStatement;
/*     */ import org.apache.spark.sql.Dataset;
/*     */ import org.apache.spark.sql.Row;
/*     */ import org.apache.spark.sql.SparkSession;
/*     */ import scala.Serializable;
/*     */ import scala.collection.mutable.StringBuilder;
/*     */ import scala.runtime.IntRef;
/*     */ import scala.runtime.ObjectRef;
/*     */ 
/*     */ @scala.reflect.ScalaSignature(bytes="\006\001\r4A!\001\002\001\027\tQ2\013]1sW\026sw-\0338f-N2uN]'vYRL\007k\\5oi*\0211\001B\001\tEJ\fgn\0315Wg)\021QAB\001\007K:<\027N\\3\013\005\035A\021\001B=jg\006T\021!C\001\004G>l7\001A\n\004\0011!\002CA\007\023\033\005q!BA\b\021\003\021a\027M\\4\013\003E\tAA[1wC&\0211C\004\002\007\037\nTWm\031;\021\0055)\022B\001\f\017\005!\021VO\0348bE2,\007\002\003\r\001\005\003\005\013\021B\r\002\023M\004\030M]6ECR\f\007c\001\016$K5\t1D\003\002\035;\005\0311/\0357\013\005yy\022!B:qCJ\\'B\001\021\"\003\031\t\007/Y2iK*\t!%A\002pe\036L!\001J\016\003\017\021\013G/Y:fiB\021!DJ\005\003Om\0211AU8x\021!I\003A!A!\002\023Q\023AC:rY\016{g\016^3yiB\021!dK\005\003Ym\021Ab\0259be.\034Vm]:j_:D\001B\f\001\003\002\003\006IaL\001\005Y&tW\r\005\0021m9\021\021\007N\007\002e)\t1'A\003tG\006d\027-\003\0026e\0051\001K]3eK\032L!a\016\035\003\rM#(/\0338h\025\t)$\007\003\005;\001\t\005\t\025!\0030\003%!\030M\0317f\035\006lW\r\003\005=\001\t\005\t\025!\0030\003)Q8\016S8tiB|'\017\036\005\006}\001!\taP\001\007y%t\027\016\036 \025\r\001\0235\tR#G!\t\t\005!D\001\003\021\025AR\b1\001\032\021\025IS\b1\001+\021\025qS\b1\0010\021\025QT\b1\0010\021\025aT\b1\0010\021\025A\005\001\"\021J\003\r\021XO\034\013\002\025B\021\021gS\005\003\031J\022A!\0268ji\")a\n\001C\001\037\006Iq-\032;PY\022$\025-\037\013\002_!)\021\013\001C\001%\006iqm]8o\003J\024\030-\037$v]\016$BaL*\\;\")A\013\025a\001+\006I\021N\0349vi\n+\027M\034\t\003-fk\021a\026\006\0031\022\taaY8n[>t\027B\001.X\005%Ie\016];u\005\026\fg\016C\003]!\002\007q&A\003usB,7\tC\003;!\002\007q\006C\003`\001\021\005\001-A\005hKR$\025\r^3jIR\021q&\031\005\006Ez\003\raL\001\013i&lWm\025;sS:<\007")
/*     */ public class SparkEngineV3ForMultiPoint implements Runnable
/*     */ {
/*     */   public void run()
/*     */   {
/*  19 */     String[] line_arr = this.line.split("\\|");
/*     */     
/*  21 */     final String jobId = line_arr[1];
/*  22 */     String params = line_arr[2];
/*     */     
/*  24 */     com.google.gson.Gson gson = new com.google.gson.Gson();
/*  25 */     java.lang.reflect.Type mapType = new com.google.gson.reflect.TypeToken() {}.getType();
/*  26 */     InputBean[] map = (InputBean[])gson.fromJson(params, mapType);
/*     */     
/*  28 */     final ObjectRef inputBeanRepair = ObjectRef.create(null);
/*     */     
/*  30 */     scala.runtime.Null. resultData = null;
/*     */     
/*  32 */     final IntRef count = IntRef.create(0);
/*     */     
/*     */ 
/*  35 */     if (map.length > 0)
/*     */     {
/*  37 */       final IntRef i = IntRef.create(1);
/*  38 */       final ObjectRef df = ObjectRef.create(null);
/*  39 */       Dataset dfNot = null;
/*     */       
/*  41 */       scala.Predef..MODULE$.refArrayOps((Object[])map).foreach(new scala.runtime.AbstractFunction1() { public static final long serialVersionUID = 0L;
/*     */         
/*  43 */         public final void apply(InputBean m) { if (m.isRepair() == 1) {
/*  44 */             inputBeanRepair.elem = m;
/*     */           }
/*     */           else {
/*  47 */             java.text.SimpleDateFormat format2 = new java.text.SimpleDateFormat("yyyyMMddHHmmss");
/*     */             
/*  49 */             long startTime = format2.parse(m.startTime()).getTime() / 1000L;
/*  50 */             long endTime = format2.parse(m.endTime()).getTime() / 1000L;
/*     */             
/*  52 */             if (i.elem == 1) {
/*  53 */               df.elem = SparkEngineV3ForMultiPoint.this.com$yisa$engine$branchV3$SparkEngineV3ForMultiPoint$$sqlContext.sql(SparkEngineV3ForMultiPoint.this.gsonArrayFunc(m, new StringBuilder().append(i.elem).append("").toString(), SparkEngineV3ForMultiPoint.this.com$yisa$engine$branchV3$SparkEngineV3ForMultiPoint$$tableName))
/*  54 */                 .filter(new StringBuilder().append("capturetime >= ").append(scala.runtime.BoxesRunTime.boxToLong(startTime)).toString())
/*  55 */                 .filter(new StringBuilder().append("capturetime <= ").append(scala.runtime.BoxesRunTime.boxToLong(endTime)).toString());
/*     */               
/*  57 */               i.elem += 1;
/*     */               
/*  59 */               count.elem = m.count();
/*     */             }
/*     */             else
/*     */             {
/*  63 */               Dataset dfTemp = SparkEngineV3ForMultiPoint.this.com$yisa$engine$branchV3$SparkEngineV3ForMultiPoint$$sqlContext.sql(SparkEngineV3ForMultiPoint.this.gsonArrayFunc(m, new StringBuilder().append(i.elem).append("").toString(), SparkEngineV3ForMultiPoint.this.com$yisa$engine$branchV3$SparkEngineV3ForMultiPoint$$tableName))
/*  64 */                 .filter(new StringBuilder().append("capturetime >= ").append(scala.runtime.BoxesRunTime.boxToLong(startTime)).toString())
/*  65 */                 .filter(new StringBuilder().append("capturetime <= ").append(scala.runtime.BoxesRunTime.boxToLong(endTime)).toString());
/*     */               
/*  67 */               df.elem = ((Dataset)df.elem).union(dfTemp);
/*     */               
/*  69 */               i.elem += 1;
/*     */             }
/*     */             
/*     */           }
/*     */           
/*     */         }
/*  75 */       });
/*  76 */       Dataset dfIs = null;
/*  77 */       if ((Dataset)df.elem != null)
/*     */       {
/*     */ 
/*  80 */         dfNot = this.com$yisa$engine$branchV3$SparkEngineV3ForMultiPoint$$sqlContext.sql(gsonArrayFunc((InputBean)inputBeanRepair.elem, new StringBuilder().append(i.elem).append("").toString(), this.com$yisa$engine$branchV3$SparkEngineV3ForMultiPoint$$tableName));((InputBean)inputBeanRepair.elem == null ? scala.runtime.BoxedUnit.UNIT : 
/*     */         
/*  82 */           ((Dataset)df.elem).union(dfNot));
/*     */         
/*     */ 
/*  85 */         ((Dataset)df.elem).createOrReplaceTempView("df");
/*     */         
/*  87 */         String sqlUnion = "SELECT first(solrid) as solrid, platenumber, concat_ws(',',collect_set(type)) as types from df group by platenumber order by types desc limit 1000";
/*  88 */         dfIs = this.com$yisa$engine$branchV3$SparkEngineV3ForMultiPoint$$sqlContext.sql(sqlUnion);
/*     */         
/*  90 */         if ((InputBean)inputBeanRepair.elem == null)
/*     */         {
/*     */ 
/*     */ 
/*     */ 
/*     */ 
/*     */ 
/*     */ 
/*     */ 
/*     */ 
/*     */ 
/*     */ 
/*     */ 
/*     */ 
/*     */ 
/*     */ 
/*     */ 
/*     */ 
/*     */ 
/*     */ 
/*     */ 
/*     */ 
/*     */ 
/*     */ 
/*     */ 
/*     */ 
/*     */ 
/*     */ 
/*     */ 
/*     */ 
/*     */ 
/*     */ 
/*     */ 
/*     */ 
/*     */ 
/*     */ 
/*     */ 
/*     */ 
/*     */ 
/*     */ 
/*     */ 
/*     */ 
/*     */ 
/*     */ 
/*     */ 
/*     */ 
/*     */ 
/*     */ 
/*     */ 
/*     */ 
/*     */ 
/*     */ 
/*     */ 
/*     */ 
/*     */ 
/* 145 */           if (count.elem >= 2)
/*     */           {
/* 147 */             if (count.elem > 2) {
/* 148 */               count.elem -= 1;
/*     */             }
/*     */             
/* 151 */             dfIs = dfIs.filter(new scala.runtime.AbstractFunction1() { public final boolean apply(Row x) { return ((String)x.getAs("types")).split(",").length >= count.elem; }
/*     */             });
/*     */           }
/*     */           
/* 155 */           Connection conn = com.yisa.engine.db.MySQLConnectManager..MODULE$.getConnet(this.zkHostport);
/* 156 */           conn.setAutoCommit(false);
/* 157 */           String sql = "insert into zdypz_result (s_id,j_id,t_id) values(?,?,?)";
/* 158 */           final ObjectRef pstmt = ObjectRef.create(conn.prepareStatement(sql));
/*     */           
/* 160 */           final IntRef number = IntRef.create(0);
/* 161 */           scala.Predef..MODULE$.refArrayOps((Object[])dfIs.collect()).foreach(new scala.runtime.AbstractFunction1() { public static final long serialVersionUID = 0L;
/*     */             
/* 163 */             public final void apply(Row t) { number.elem += 1;
/*     */               
/* 165 */               ((PreparedStatement)pstmt.elem).setString(1, t.apply(0).toString());
/* 166 */               ((PreparedStatement)pstmt.elem).setString(2, jobId);
/* 167 */               ((PreparedStatement)pstmt.elem).setString(3, t.apply(2).toString());
/* 168 */               ((PreparedStatement)pstmt.elem).addBatch();
/*     */             }
/*     */             
/* 171 */           });
/* 172 */           String sql2 = "insert into zdypz_progress (jobid,total) values(?,?)";
/* 173 */           PreparedStatement pstmt2 = conn.prepareStatement(sql2);
/*     */           
/* 175 */           if (number.elem == 0) {
/* 176 */             number.elem = -1;
/*     */           }
/* 178 */           pstmt2.setString(1, jobId);
/* 179 */           pstmt2.setInt(2, number.elem);
/* 180 */           pstmt2.executeUpdate();
/* 181 */           pstmt2.close();
/*     */           
/* 183 */           ((PreparedStatement)pstmt.elem).executeBatch();
/* 184 */           conn.commit();
/* 185 */           ((PreparedStatement)pstmt.elem).close();
/*     */           
/* 187 */           conn.close();
/*     */         }
/*     */         else
/*     */         {
/*  93 */           if (count.elem >= 2)
/*     */           {
/*  95 */             if (count.elem > 2) {
/*  96 */               count.elem -= 1;
/*     */             }
/*     */             
/*  99 */             dfIs = dfIs.filter(new scala.runtime.AbstractFunction1() { public final boolean apply(Row x) { return ((String)x.getAs("types")).split(",").length >= count.elem; }
/*     */             });
/*     */           }
/*     */           
/* 103 */           dfIs.createOrReplaceTempView("dfIs");
/*     */           
/* 105 */           String sqlNot = new StringBuilder().append("SELECT solrid, types FROM dfIs WHERE types NOT LIKE '%").append(scala.runtime.BoxesRunTime.boxToInteger(i.elem)).append("%'").toString();
/*     */           
/* 107 */           Dataset re = this.com$yisa$engine$branchV3$SparkEngineV3ForMultiPoint$$sqlContext.sql(sqlNot);
/*     */           
/* 109 */           Connection conn = com.yisa.engine.db.MySQLConnectManager..MODULE$.getConnet(this.zkHostport);
/* 110 */           conn.setAutoCommit(false);
/* 111 */           String sql = "insert into zdypz_result (s_id,j_id,t_id) values(?,?,?)";
/* 112 */           final ObjectRef pstmt = ObjectRef.create(conn.prepareStatement(sql));
/*     */           
/* 114 */           final IntRef number = IntRef.create(0);
/*     */           
/* 116 */           scala.Predef..MODULE$.refArrayOps((Object[])re.collect()).foreach(new scala.runtime.AbstractFunction1() { public static final long serialVersionUID = 0L;
/*     */             
/* 118 */             public final void apply(Row t) { number.elem += 1;
/*     */               
/* 120 */               ((PreparedStatement)pstmt.elem).setString(1, t.apply(0).toString());
/* 121 */               ((PreparedStatement)pstmt.elem).setString(2, jobId);
/* 122 */               ((PreparedStatement)pstmt.elem).setString(3, new StringBuilder().append(t.apply(1).toString()).append(",").append(scala.runtime.BoxesRunTime.boxToInteger(i.elem)).toString());
/* 123 */               ((PreparedStatement)pstmt.elem).addBatch();
/*     */             }
/*     */             
/* 126 */           });
/* 127 */           String sql2 = "insert into zdypz_progress (jobid,total) values(?,?)";
/* 128 */           PreparedStatement pstmt2 = conn.prepareStatement(sql2);
/*     */           
/* 130 */           if (number.elem == 0) {
/* 131 */             number.elem = -1;
/*     */           }
/*     */           
/* 134 */           pstmt2.setString(1, jobId);
/* 135 */           pstmt2.setInt(2, number.elem);
/* 136 */           pstmt2.executeUpdate();
/* 137 */           pstmt2.close();
/*     */           
/* 139 */           ((PreparedStatement)pstmt.elem).executeBatch();
/* 140 */           conn.commit();
/* 141 */           ((PreparedStatement)pstmt.elem).close();
/* 142 */           conn.close();
/*     */         }
/*     */       }
/*     */     }
/*     */   }
/*     */   
/*     */ 
/*     */ 
/*     */ 
/*     */ 
/*     */ 
/*     */ 
/*     */ 
/*     */ 
/*     */ 
/*     */ 
/*     */ 
/*     */ 
/*     */ 
/*     */ 
/*     */ 
/*     */ 
/*     */   public static final long serialVersionUID = 0L;
/*     */   
/*     */ 
/*     */ 
/*     */ 
/*     */ 
/*     */ 
/*     */ 
/*     */ 
/*     */ 
/*     */ 
/*     */ 
/*     */ 
/*     */ 
/*     */ 
/*     */ 
/*     */   public static final long serialVersionUID = 0L;
/*     */   
/*     */ 
/*     */ 
/*     */ 
/*     */ 
/*     */ 
/*     */ 
/*     */ 
/*     */ 
/*     */ 
/*     */ 
/*     */ 
/*     */ 
/*     */ 
/*     */ 
/*     */   public String getOldDay()
/*     */   {
/* 198 */     java.text.SimpleDateFormat dateFormat = new java.text.SimpleDateFormat("yyyyMMdd");
/* 199 */     java.util.Calendar cal = java.util.Calendar.getInstance();
/* 200 */     cal.add(5, -3);
/* 201 */     String yesterday = dateFormat.format(cal.getTime());
/*     */     
/* 203 */     return yesterday;
/*     */   }
/*     */   
/*     */   /* Error */
/*     */   public String gsonArrayFunc(InputBean inputBean, String typeC, String tableName)
/*     */   {
/*     */     // Byte code:
/*     */     //   0: getstatic 296	com/yisa/engine/uitl/TimeUtil$:MODULE$	Lcom/yisa/engine/uitl/TimeUtil$;
/*     */     //   3: aload_1
/*     */     //   4: invokevirtual 299	com/yisa/engine/common/InputBean:startTime	()Ljava/lang/String;
/*     */     //   7: invokevirtual 303	com/yisa/engine/uitl/TimeUtil$:getTimeStringFormat	(Ljava/lang/String;)Ljava/lang/String;
/*     */     //   10: astore 4
/*     */     //   12: getstatic 296	com/yisa/engine/uitl/TimeUtil$:MODULE$	Lcom/yisa/engine/uitl/TimeUtil$;
/*     */     //   15: aload_1
/*     */     //   16: invokevirtual 306	com/yisa/engine/common/InputBean:endTime	()Ljava/lang/String;
/*     */     //   19: invokevirtual 303	com/yisa/engine/uitl/TimeUtil$:getTimeStringFormat	(Ljava/lang/String;)Ljava/lang/String;
/*     */     //   22: astore 5
/*     */     //   24: aload_1
/*     */     //   25: invokevirtual 310	com/yisa/engine/common/InputBean:locationId	()[Ljava/lang/String;
/*     */     //   28: astore 6
/*     */     //   30: aload_1
/*     */     //   31: invokevirtual 313	com/yisa/engine/common/InputBean:carModel	()[Ljava/lang/String;
/*     */     //   34: astore 7
/*     */     //   36: aload_1
/*     */     //   37: invokevirtual 316	com/yisa/engine/common/InputBean:carBrand	()Ljava/lang/String;
/*     */     //   40: astore 8
/*     */     //   42: aload_1
/*     */     //   43: invokevirtual 319	com/yisa/engine/common/InputBean:carYear	()[Ljava/lang/String;
/*     */     //   46: astore 9
/*     */     //   48: aload_1
/*     */     //   49: invokevirtual 322	com/yisa/engine/common/InputBean:carColor	()Ljava/lang/String;
/*     */     //   52: astore 10
/*     */     //   54: aload_1
/*     */     //   55: invokevirtual 325	com/yisa/engine/common/InputBean:plateNumber	()Ljava/lang/String;
/*     */     //   58: astore 11
/*     */     //   60: getstatic 65	scala/Predef$:MODULE$	Lscala/Predef$;
/*     */     //   63: aload_1
/*     */     //   64: invokevirtual 310	com/yisa/engine/common/InputBean:locationId	()[Ljava/lang/String;
/*     */     //   67: invokevirtual 329	scala/Predef$:println	(Ljava/lang/Object;)V
/*     */     //   70: new 331	java/lang/StringBuffer
/*     */     //   73: dup
/*     */     //   74: invokespecial 332	java/lang/StringBuffer:<init>	()V
/*     */     //   77: astore 12
/*     */     //   79: aload 12
/*     */     //   81: ldc_w 334
/*     */     //   84: invokevirtual 337	java/lang/StringBuffer:append	(Ljava/lang/String;)Ljava/lang/StringBuffer;
/*     */     //   87: pop
/*     */     //   88: aload 12
/*     */     //   90: aload_2
/*     */     //   91: invokevirtual 337	java/lang/StringBuffer:append	(Ljava/lang/String;)Ljava/lang/StringBuffer;
/*     */     //   94: ldc_w 339
/*     */     //   97: invokevirtual 337	java/lang/StringBuffer:append	(Ljava/lang/String;)Ljava/lang/StringBuffer;
/*     */     //   100: aload_3
/*     */     //   101: invokevirtual 337	java/lang/StringBuffer:append	(Ljava/lang/String;)Ljava/lang/StringBuffer;
/*     */     //   104: pop
/*     */     //   105: aload 4
/*     */     //   107: ifnonnull +9 -> 116
/*     */     //   110: getstatic 96	scala/runtime/BoxedUnit:UNIT	Lscala/runtime/BoxedUnit;
/*     */     //   113: goto +20 -> 133
/*     */     //   116: aload 12
/*     */     //   118: ldc_w 341
/*     */     //   121: invokevirtual 337	java/lang/StringBuffer:append	(Ljava/lang/String;)Ljava/lang/StringBuffer;
/*     */     //   124: aload_0
/*     */     //   125: aload 4
/*     */     //   127: invokevirtual 344	com/yisa/engine/branchV3/SparkEngineV3ForMultiPoint:getDateid	(Ljava/lang/String;)Ljava/lang/String;
/*     */     //   130: invokevirtual 337	java/lang/StringBuffer:append	(Ljava/lang/String;)Ljava/lang/StringBuffer;
/*     */     //   133: pop
/*     */     //   134: aload 5
/*     */     //   136: ifnonnull +9 -> 145
/*     */     //   139: getstatic 96	scala/runtime/BoxedUnit:UNIT	Lscala/runtime/BoxedUnit;
/*     */     //   142: goto +20 -> 162
/*     */     //   145: aload 12
/*     */     //   147: ldc_w 346
/*     */     //   150: invokevirtual 337	java/lang/StringBuffer:append	(Ljava/lang/String;)Ljava/lang/StringBuffer;
/*     */     //   153: aload_0
/*     */     //   154: aload 5
/*     */     //   156: invokevirtual 344	com/yisa/engine/branchV3/SparkEngineV3ForMultiPoint:getDateid	(Ljava/lang/String;)Ljava/lang/String;
/*     */     //   159: invokevirtual 337	java/lang/StringBuffer:append	(Ljava/lang/String;)Ljava/lang/StringBuffer;
/*     */     //   162: pop
/*     */     //   163: aload 6
/*     */     //   165: aconst_null
/*     */     //   166: if_acmpeq +97 -> 263
/*     */     //   169: aload 6
/*     */     //   171: arraylength
/*     */     //   172: iconst_0
/*     */     //   173: if_icmple +90 -> 263
/*     */     //   176: getstatic 65	scala/Predef$:MODULE$	Lscala/Predef$;
/*     */     //   179: getstatic 65	scala/Predef$:MODULE$	Lscala/Predef$;
/*     */     //   182: aload 6
/*     */     //   184: checkcast 67	[Ljava/lang/Object;
/*     */     //   187: invokevirtual 71	scala/Predef$:refArrayOps	([Ljava/lang/Object;)Lscala/collection/mutable/ArrayOps;
/*     */     //   190: new 348	com/yisa/engine/branchV3/SparkEngineV3ForMultiPoint$$anonfun$1
/*     */     //   193: dup
/*     */     //   194: aload_0
/*     */     //   195: invokespecial 349	com/yisa/engine/branchV3/SparkEngineV3ForMultiPoint$$anonfun$1:<init>	(Lcom/yisa/engine/branchV3/SparkEngineV3ForMultiPoint;)V
/*     */     //   198: getstatic 354	scala/Array$:MODULE$	Lscala/Array$;
/*     */     //   201: getstatic 359	scala/reflect/ClassTag$:MODULE$	Lscala/reflect/ClassTag$;
/*     */     //   204: ldc 24
/*     */     //   206: invokevirtual 363	scala/reflect/ClassTag$:apply	(Ljava/lang/Class;)Lscala/reflect/ClassTag;
/*     */     //   209: invokevirtual 367	scala/Array$:canBuildFrom	(Lscala/reflect/ClassTag;)Lscala/collection/generic/CanBuildFrom;
/*     */     //   212: invokeinterface 370 3 0
/*     */     //   217: checkcast 67	[Ljava/lang/Object;
/*     */     //   220: invokevirtual 71	scala/Predef$:refArrayOps	([Ljava/lang/Object;)Lscala/collection/mutable/ArrayOps;
/*     */     //   223: new 372	com/yisa/engine/branchV3/SparkEngineV3ForMultiPoint$$anonfun$2
/*     */     //   226: dup
/*     */     //   227: aload_0
/*     */     //   228: invokespecial 373	com/yisa/engine/branchV3/SparkEngineV3ForMultiPoint$$anonfun$2:<init>	(Lcom/yisa/engine/branchV3/SparkEngineV3ForMultiPoint;)V
/*     */     //   231: invokeinterface 377 2 0
/*     */     //   236: checkcast 24	java/lang/String
/*     */     //   239: astore 13
/*     */     //   241: aload 12
/*     */     //   243: ldc_w 379
/*     */     //   246: invokevirtual 337	java/lang/StringBuffer:append	(Ljava/lang/String;)Ljava/lang/StringBuffer;
/*     */     //   249: aload 13
/*     */     //   251: invokevirtual 337	java/lang/StringBuffer:append	(Ljava/lang/String;)Ljava/lang/StringBuffer;
/*     */     //   254: ldc_w 381
/*     */     //   257: invokevirtual 337	java/lang/StringBuffer:append	(Ljava/lang/String;)Ljava/lang/StringBuffer;
/*     */     //   260: goto +6 -> 266
/*     */     //   263: getstatic 96	scala/runtime/BoxedUnit:UNIT	Lscala/runtime/BoxedUnit;
/*     */     //   266: pop
/*     */     //   267: aload 7
/*     */     //   269: aconst_null
/*     */     //   270: if_acmpeq +61 -> 331
/*     */     //   273: aload 7
/*     */     //   275: arraylength
/*     */     //   276: iconst_0
/*     */     //   277: if_icmple +54 -> 331
/*     */     //   280: getstatic 65	scala/Predef$:MODULE$	Lscala/Predef$;
/*     */     //   283: aload 7
/*     */     //   285: checkcast 67	[Ljava/lang/Object;
/*     */     //   288: invokevirtual 71	scala/Predef$:refArrayOps	([Ljava/lang/Object;)Lscala/collection/mutable/ArrayOps;
/*     */     //   291: new 383	com/yisa/engine/branchV3/SparkEngineV3ForMultiPoint$$anonfun$3
/*     */     //   294: dup
/*     */     //   295: aload_0
/*     */     //   296: invokespecial 384	com/yisa/engine/branchV3/SparkEngineV3ForMultiPoint$$anonfun$3:<init>	(Lcom/yisa/engine/branchV3/SparkEngineV3ForMultiPoint;)V
/*     */     //   299: invokeinterface 377 2 0
/*     */     //   304: checkcast 24	java/lang/String
/*     */     //   307: astore 14
/*     */     //   309: aload 12
/*     */     //   311: ldc_w 386
/*     */     //   314: invokevirtual 337	java/lang/StringBuffer:append	(Ljava/lang/String;)Ljava/lang/StringBuffer;
/*     */     //   317: aload 14
/*     */     //   319: invokevirtual 337	java/lang/StringBuffer:append	(Ljava/lang/String;)Ljava/lang/StringBuffer;
/*     */     //   322: ldc_w 381
/*     */     //   325: invokevirtual 337	java/lang/StringBuffer:append	(Ljava/lang/String;)Ljava/lang/StringBuffer;
/*     */     //   328: goto +6 -> 334
/*     */     //   331: getstatic 96	scala/runtime/BoxedUnit:UNIT	Lscala/runtime/BoxedUnit;
/*     */     //   334: pop
/*     */     //   335: aload 8
/*     */     //   337: ifnull +30 -> 367
/*     */     //   340: aload 8
/*     */     //   342: ldc 110
/*     */     //   344: astore 15
/*     */     //   346: dup
/*     */     //   347: ifnonnull +12 -> 359
/*     */     //   350: pop
/*     */     //   351: aload 15
/*     */     //   353: ifnull +14 -> 367
/*     */     //   356: goto +17 -> 373
/*     */     //   359: aload 15
/*     */     //   361: invokevirtual 390	java/lang/Object:equals	(Ljava/lang/Object;)Z
/*     */     //   364: ifeq +9 -> 373
/*     */     //   367: getstatic 96	scala/runtime/BoxedUnit:UNIT	Lscala/runtime/BoxedUnit;
/*     */     //   370: goto +16 -> 386
/*     */     //   373: aload 12
/*     */     //   375: ldc_w 392
/*     */     //   378: invokevirtual 337	java/lang/StringBuffer:append	(Ljava/lang/String;)Ljava/lang/StringBuffer;
/*     */     //   381: aload 8
/*     */     //   383: invokevirtual 337	java/lang/StringBuffer:append	(Ljava/lang/String;)Ljava/lang/StringBuffer;
/*     */     //   386: pop
/*     */     //   387: aload 10
/*     */     //   389: ifnull +30 -> 419
/*     */     //   392: aload 10
/*     */     //   394: ldc 110
/*     */     //   396: astore 16
/*     */     //   398: dup
/*     */     //   399: ifnonnull +12 -> 411
/*     */     //   402: pop
/*     */     //   403: aload 16
/*     */     //   405: ifnull +14 -> 419
/*     */     //   408: goto +17 -> 425
/*     */     //   411: aload 16
/*     */     //   413: invokevirtual 390	java/lang/Object:equals	(Ljava/lang/Object;)Z
/*     */     //   416: ifeq +9 -> 425
/*     */     //   419: getstatic 96	scala/runtime/BoxedUnit:UNIT	Lscala/runtime/BoxedUnit;
/*     */     //   422: goto +16 -> 438
/*     */     //   425: aload 12
/*     */     //   427: ldc_w 394
/*     */     //   430: invokevirtual 337	java/lang/StringBuffer:append	(Ljava/lang/String;)Ljava/lang/StringBuffer;
/*     */     //   433: aload 10
/*     */     //   435: invokevirtual 337	java/lang/StringBuffer:append	(Ljava/lang/String;)Ljava/lang/StringBuffer;
/*     */     //   438: pop
/*     */     //   439: aload 11
/*     */     //   441: ifnull +30 -> 471
/*     */     //   444: aload 11
/*     */     //   446: ldc 110
/*     */     //   448: astore 17
/*     */     //   450: dup
/*     */     //   451: ifnonnull +12 -> 463
/*     */     //   454: pop
/*     */     //   455: aload 17
/*     */     //   457: ifnull +14 -> 471
/*     */     //   460: goto +17 -> 477
/*     */     //   463: aload 17
/*     */     //   465: invokevirtual 390	java/lang/Object:equals	(Ljava/lang/Object;)Z
/*     */     //   468: ifeq +9 -> 477
/*     */     //   471: getstatic 96	scala/runtime/BoxedUnit:UNIT	Lscala/runtime/BoxedUnit;
/*     */     //   474: goto +16 -> 490
/*     */     //   477: aload 12
/*     */     //   479: ldc_w 396
/*     */     //   482: invokevirtual 337	java/lang/StringBuffer:append	(Ljava/lang/String;)Ljava/lang/StringBuffer;
/*     */     //   485: aload 11
/*     */     //   487: invokevirtual 337	java/lang/StringBuffer:append	(Ljava/lang/String;)Ljava/lang/StringBuffer;
/*     */     //   490: pop
/*     */     //   491: getstatic 65	scala/Predef$:MODULE$	Lscala/Predef$;
/*     */     //   494: aload 12
/*     */     //   496: invokevirtual 397	java/lang/StringBuffer:toString	()Ljava/lang/String;
/*     */     //   499: invokevirtual 329	scala/Predef$:println	(Ljava/lang/Object;)V
/*     */     //   502: aload 12
/*     */     //   504: invokevirtual 397	java/lang/StringBuffer:toString	()Ljava/lang/String;
/*     */     //   507: areturn
/*     */     // Line number table:
/*     */     //   Java source line #211	-> byte code offset #0
/*     */     //   Java source line #212	-> byte code offset #12
/*     */     //   Java source line #213	-> byte code offset #24
/*     */     //   Java source line #214	-> byte code offset #30
/*     */     //   Java source line #215	-> byte code offset #36
/*     */     //   Java source line #216	-> byte code offset #42
/*     */     //   Java source line #217	-> byte code offset #48
/*     */     //   Java source line #218	-> byte code offset #54
/*     */     //   Java source line #220	-> byte code offset #60
/*     */     //   Java source line #222	-> byte code offset #70
/*     */     //   Java source line #224	-> byte code offset #79
/*     */     //   Java source line #227	-> byte code offset #88
/*     */     //   Java source line #237	-> byte code offset #105
/*     */     //   Java source line #238	-> byte code offset #116
/*     */     //   Java source line #237	-> byte code offset #133
/*     */     //   Java source line #241	-> byte code offset #134
/*     */     //   Java source line #242	-> byte code offset #145
/*     */     //   Java source line #241	-> byte code offset #162
/*     */     //   Java source line #245	-> byte code offset #163
/*     */     //   Java source line #246	-> byte code offset #176
/*     */     //   Java source line #248	-> byte code offset #241
/*     */     //   Java source line #245	-> byte code offset #263
/*     */     //   Java source line #251	-> byte code offset #267
/*     */     //   Java source line #252	-> byte code offset #280
/*     */     //   Java source line #253	-> byte code offset #309
/*     */     //   Java source line #251	-> byte code offset #331
/*     */     //   Java source line #256	-> byte code offset #335
/*     */     //   Java source line #257	-> byte code offset #373
/*     */     //   Java source line #256	-> byte code offset #386
/*     */     //   Java source line #260	-> byte code offset #387
/*     */     //   Java source line #261	-> byte code offset #425
/*     */     //   Java source line #260	-> byte code offset #438
/*     */     //   Java source line #264	-> byte code offset #439
/*     */     //   Java source line #265	-> byte code offset #477
/*     */     //   Java source line #264	-> byte code offset #490
/*     */     //   Java source line #270	-> byte code offset #491
/*     */     //   Java source line #272	-> byte code offset #502
/*     */     // Local variable table:
/*     */     //   start	length	slot	name	signature
/*     */     //   0	508	0	this	SparkEngineV3ForMultiPoint
/*     */     //   0	508	1	inputBean	InputBean
/*     */     //   0	508	2	typeC	String
/*     */     //   0	508	3	tableName	String
/*     */     //   12	495	4	startTime1	String
/*     */     //   24	483	5	endTime1	String
/*     */     //   30	477	6	locationId	String[]
/*     */     //   36	471	7	carModel	String[]
/*     */     //   42	465	8	carBrand	String
/*     */     //   48	459	9	carYear	String[]
/*     */     //   54	453	10	carColor	String
/*     */     //   60	447	11	plateNumber	String
/*     */     //   79	428	12	sb	StringBuffer
/*     */     //   241	19	13	l	String
/*     */     //   309	19	14	m	String
/*     */   }
/*     */   
/*     */   public String getDateid(String timeString)
/*     */   {
/* 278 */     String timeLong = timeString.replaceAll("[-\\s:]", "");
/*     */     
/* 280 */     return timeLong.substring(0, 8);
/*     */   }
/*     */   
/*     */   public SparkEngineV3ForMultiPoint(Dataset<Row> sparkData, SparkSession sqlContext, String line, String tableName, String zkHostport) {}
/*     */ }


/* Location:              E:\BaiduYunDownload\伊萨时期的一些代码\SparkEngine终极版\jars\YISAEngineBySpark2-4.0.6-SNAPSHOT-jar-with-dependencies.jar!\com\yisa\engine\branchV3\SparkEngineV3ForMultiPoint.class
 * Java compiler version: 6 (50.0)
 * JD-Core Version:       0.7.1
 */