/*     */ package com.yisa.engine.branchV3;
/*     */ 
/*     */ import com.google.gson.Gson;
/*     */ import com.yisa.engine.common.InputBean;
/*     */ import com.yisa.engine.db.MySQLConnectManager.;
/*     */ import java.lang.reflect.Type;
/*     */ import java.sql.Connection;
/*     */ import java.sql.DriverManager;
/*     */ import java.sql.PreparedStatement;
/*     */ import java.sql.ResultSet;
/*     */ import java.sql.Statement;
/*     */ import java.util.Date;
/*     */ import org.apache.spark.sql.SparkSession;
/*     */ import scala.Predef.;
/*     */ import scala.Serializable;
/*     */ import scala.collection.mutable.StringBuilder;
/*     */ import scala.runtime.AbstractFunction2;
/*     */ import scala.runtime.BoxesRunTime;
/*     */ 
/*     */ @scala.reflect.ScalaSignature(bytes="\006\001)4A!\001\002\001\027\t!3\013]1sW\026sw-\0338f-N2uN]*fCJ\034\007nQ1s\005f\004\026n\031)sKN$xN\003\002\004\t\005A!M]1oG\"46G\003\002\006\r\0051QM\\4j]\026T!a\002\005\002\teL7/\031\006\002\023\005\0311m\\7\004\001M\031\001\001\004\013\021\0055\021R\"\001\b\013\005=\001\022\001\0027b]\036T\021!E\001\005U\0064\030-\003\002\024\035\t1qJ\0316fGR\004\"!D\013\n\005Yq!\001\003*v]:\f'\r\\3\t\021a\001!\021!Q\001\ne\t!b]9m\007>tG/\032=u!\tQ2%D\001\034\025\taR$A\002tc2T!AH\020\002\013M\004\030M]6\013\005\001\n\023AB1qC\016DWMC\001#\003\ry'oZ\005\003Im\021Ab\0259be.\034Vm]:j_:D\001B\n\001\003\002\003\006IaJ\001\005Y&tW\r\005\002)]9\021\021\006L\007\002U)\t1&A\003tG\006d\027-\003\002.U\0051\001K]3eK\032L!a\f\031\003\rM#(/\0338h\025\ti#\006\003\0053\001\t\005\t\025!\003(\003%!\030M\0317f\035\006lW\r\003\0055\001\t\005\t\025!\003(\003)Q8\016S8tiB|'\017\036\005\tm\001\021\t\021)A\005O\005q\001K]3ti>Dun\035;Q_J$\b\"\002\035\001\t\003I\024A\002\037j]&$h\b\006\004;yurt\b\021\t\003w\001i\021A\001\005\0061]\002\r!\007\005\006M]\002\ra\n\005\006e]\002\ra\n\005\006i]\002\ra\n\005\006m]\002\ra\n\005\006\005\002!\teQ\001\004eVtG#\001#\021\005%*\025B\001$+\005\021)f.\033;\t\013!\003A\021A%\002\033I,7/\0367u\023:\024FIQ'T)\021QU\nV+\021\005%Z\025B\001'+\005\rIe\016\036\005\006\035\036\003\raT\001\003eN\004\"\001\025*\016\003ES!\001\b\t\n\005M\013&!\003*fgVdGoU3u\021\025!t\t1\001(\021\0251v\t1\001(\003\031QwNY0jI\")\001\f\001C\0013\0061q-\032;T#2#BA\027/eKB\021QbW\005\003_9AQ!X,A\002y\0131!\\1q!\ty&-D\001a\025\t\tG!\001\004d_6lwN\\\005\003G\002\024\021\"\0238qkR\024U-\0318\t\013I:\006\031A\024\t\013\031<\006\031A4\002\037MLW.\0337be&$\030\020T5nSR\004\"!\0135\n\005%T#a\002\"p_2,\027M\034")
/*     */ public class SparkEngineV3ForSearchCarByPicPresto implements Runnable
/*     */ {
/*     */   public void run()
/*     */   {
/*  25 */     long now1 = new Date().getTime();
/*  26 */     String[] line_arr = this.line.split("\\|");
/*  27 */     String job_id = line_arr[1];
/*     */     
/*  29 */     Gson gson = new Gson();
/*  30 */     Type mapType = new com.google.gson.reflect.TypeToken() {}.getType();
/*  31 */     InputBean map = (InputBean)gson.fromJson(line_arr[2], mapType);
/*     */     
/*     */ 
/*  34 */     String sql1 = getSQL(map, this.tableName, true);
/*     */     
/*  36 */     Predef..MODULE$.println(new StringBuilder().append("SQL--------------:").append(sql1).toString());
/*     */     
/*     */ 
/*     */ 
/*  40 */     String PrestoURL = new StringBuilder().append("jdbc:presto://").append(this.PrestoHostPort).append("/hive/yisadata").toString();
/*  41 */     String PrestoUser = "sparkPic";
/*  42 */     String PrestoPwd = "";
/*  43 */     String PrestoDriver = "com.facebook.presto.jdbc.PrestoDriver";
/*     */     
/*  45 */     Class.forName(PrestoDriver);
/*  46 */     Connection conn = DriverManager.getConnection(PrestoURL, PrestoUser, null);
/*     */     
/*  48 */     Statement stmt = conn.createStatement();
/*     */     
/*  50 */     ResultSet rs = stmt.executeQuery(sql1);
/*     */     
/*  52 */     int count = resultInRDBMS(rs, this.zkHostport, job_id);
/*  53 */     rs.close();
/*     */     
/*     */ 
/*  56 */     if (count == 0) {
/*  57 */       Predef..MODULE$.println("< 20000 hasnt data,run again without simily limit");
/*     */       
/*  59 */       String sql2 = getSQL(map, this.tableName, false);
/*     */       
/*  61 */       Predef..MODULE$.println(new StringBuilder().append("SQL--------------:").append(sql2).toString());
/*  62 */       ResultSet rs2 = stmt.executeQuery(sql2);
/*  63 */       int count = resultInRDBMS(rs2, this.zkHostport, job_id);
/*  64 */       rs2.close();
/*     */     }
/*     */     
/*  67 */     Predef..MODULE$.println(new StringBuilder().append("result conut --------------:").append(BoxesRunTime.boxToInteger(count)).toString());
/*     */     
/*  69 */     stmt.close();
/*  70 */     conn.close();
/*     */   }
/*     */   
/*     */ 
/*     */   public int resultInRDBMS(ResultSet rs, String zkHostport, String job_id)
/*     */   {
/*  76 */     Connection mysqlConn = MySQLConnectManager..MODULE$.getConnet(zkHostport);
/*  77 */     mysqlConn.setAutoCommit(false);
/*  78 */     String sql = "insert into gpu_index_job (job_id,solr_id,sort_value,plate_number) values(?,?,?,?)";
/*  79 */     PreparedStatement mysqlPstmt = mysqlConn.prepareStatement(sql);
/*  80 */     int count = 0;
/*     */     
/*  82 */     while (rs.next())
/*     */     {
/*  84 */       mysqlPstmt.setString(1, job_id);
/*  85 */       mysqlPstmt.setString(2, rs.getString(1));
/*  86 */       mysqlPstmt.setInt(3, rs.getInt(2));
/*  87 */       mysqlPstmt.setString(4, rs.getString(3));
/*  88 */       String l_id = rs.getString(3);
/*     */       
/*  90 */       mysqlPstmt.addBatch();
/*  91 */       count += 1;
/*     */     }
/*     */     
/*  94 */     mysqlPstmt.executeBatch();
/*     */     
/*  96 */     mysqlConn.commit();
/*  97 */     mysqlPstmt.close();
/*  98 */     mysqlConn.close();
/*     */     
/* 100 */     return count;
/*     */   }
/*     */   
/*     */   /* Error */
/*     */   public String getSQL(InputBean map, String tableName, boolean similarityLimit)
/*     */   {
/*     */     // Byte code:
/*     */     //   0: aload_1
/*     */     //   1: invokevirtual 233	com/yisa/engine/common/InputBean:feature	()Ljava/lang/String;
/*     */     //   4: astore 4
/*     */     //   6: aload_1
/*     */     //   7: invokevirtual 236	com/yisa/engine/common/InputBean:carBrand	()Ljava/lang/String;
/*     */     //   10: astore 5
/*     */     //   12: aload_1
/*     */     //   13: invokevirtual 240	com/yisa/engine/common/InputBean:carModel	()[Ljava/lang/String;
/*     */     //   16: astore 6
/*     */     //   18: getstatic 245	com/yisa/engine/uitl/TimeUtil$:MODULE$	Lcom/yisa/engine/uitl/TimeUtil$;
/*     */     //   21: aload_1
/*     */     //   22: invokevirtual 248	com/yisa/engine/common/InputBean:startTime	()Ljava/lang/String;
/*     */     //   25: invokevirtual 252	com/yisa/engine/uitl/TimeUtil$:getTimestampLong	(Ljava/lang/String;)J
/*     */     //   28: lstore 7
/*     */     //   30: getstatic 245	com/yisa/engine/uitl/TimeUtil$:MODULE$	Lcom/yisa/engine/uitl/TimeUtil$;
/*     */     //   33: aload_1
/*     */     //   34: invokevirtual 255	com/yisa/engine/common/InputBean:endTime	()Ljava/lang/String;
/*     */     //   37: invokevirtual 252	com/yisa/engine/uitl/TimeUtil$:getTimestampLong	(Ljava/lang/String;)J
/*     */     //   40: lstore 9
/*     */     //   42: new 257	java/lang/StringBuffer
/*     */     //   45: dup
/*     */     //   46: invokespecial 258	java/lang/StringBuffer:<init>	()V
/*     */     //   49: astore 11
/*     */     //   51: aload 11
/*     */     //   53: ldc_w 260
/*     */     //   56: invokevirtual 263	java/lang/StringBuffer:append	(Ljava/lang/String;)Ljava/lang/StringBuffer;
/*     */     //   59: pop
/*     */     //   60: aload 11
/*     */     //   62: ldc_w 265
/*     */     //   65: invokevirtual 263	java/lang/StringBuffer:append	(Ljava/lang/String;)Ljava/lang/StringBuffer;
/*     */     //   68: pop
/*     */     //   69: aload 11
/*     */     //   71: new 68	scala/collection/mutable/StringBuilder
/*     */     //   74: dup
/*     */     //   75: invokespecial 69	scala/collection/mutable/StringBuilder:<init>	()V
/*     */     //   78: ldc_w 267
/*     */     //   81: invokevirtual 75	scala/collection/mutable/StringBuilder:append	(Ljava/lang/Object;)Lscala/collection/mutable/StringBuilder;
/*     */     //   84: aload 4
/*     */     //   86: invokevirtual 75	scala/collection/mutable/StringBuilder:append	(Ljava/lang/Object;)Lscala/collection/mutable/StringBuilder;
/*     */     //   89: ldc_w 269
/*     */     //   92: invokevirtual 75	scala/collection/mutable/StringBuilder:append	(Ljava/lang/Object;)Lscala/collection/mutable/StringBuilder;
/*     */     //   95: invokevirtual 79	scala/collection/mutable/StringBuilder:toString	()Ljava/lang/String;
/*     */     //   98: invokevirtual 263	java/lang/StringBuffer:append	(Ljava/lang/String;)Ljava/lang/StringBuffer;
/*     */     //   101: pop
/*     */     //   102: aload 11
/*     */     //   104: new 68	scala/collection/mutable/StringBuilder
/*     */     //   107: dup
/*     */     //   108: invokespecial 69	scala/collection/mutable/StringBuilder:<init>	()V
/*     */     //   111: ldc_w 271
/*     */     //   114: invokevirtual 75	scala/collection/mutable/StringBuilder:append	(Ljava/lang/Object;)Lscala/collection/mutable/StringBuilder;
/*     */     //   117: aload_2
/*     */     //   118: invokevirtual 75	scala/collection/mutable/StringBuilder:append	(Ljava/lang/Object;)Lscala/collection/mutable/StringBuilder;
/*     */     //   121: ldc_w 273
/*     */     //   124: invokevirtual 75	scala/collection/mutable/StringBuilder:append	(Ljava/lang/Object;)Lscala/collection/mutable/StringBuilder;
/*     */     //   127: invokevirtual 79	scala/collection/mutable/StringBuilder:toString	()Ljava/lang/String;
/*     */     //   130: invokevirtual 263	java/lang/StringBuffer:append	(Ljava/lang/String;)Ljava/lang/StringBuffer;
/*     */     //   133: pop
/*     */     //   134: aload_1
/*     */     //   135: invokevirtual 276	com/yisa/engine/common/InputBean:carYear	()[Ljava/lang/String;
/*     */     //   138: aconst_null
/*     */     //   139: if_acmpeq +119 -> 258
/*     */     //   142: aload_1
/*     */     //   143: invokevirtual 276	com/yisa/engine/common/InputBean:carYear	()[Ljava/lang/String;
/*     */     //   146: iconst_0
/*     */     //   147: aaload
/*     */     //   148: ldc 93
/*     */     //   150: astore 12
/*     */     //   152: dup
/*     */     //   153: ifnonnull +12 -> 165
/*     */     //   156: pop
/*     */     //   157: aload 12
/*     */     //   159: ifnull +99 -> 258
/*     */     //   162: goto +11 -> 173
/*     */     //   165: aload 12
/*     */     //   167: invokevirtual 280	java/lang/Object:equals	(Ljava/lang/Object;)Z
/*     */     //   170: ifne +88 -> 258
/*     */     //   173: aload_1
/*     */     //   174: invokevirtual 276	com/yisa/engine/common/InputBean:carYear	()[Ljava/lang/String;
/*     */     //   177: iconst_0
/*     */     //   178: aaload
/*     */     //   179: ldc_w 282
/*     */     //   182: astore 13
/*     */     //   184: dup
/*     */     //   185: ifnonnull +12 -> 197
/*     */     //   188: pop
/*     */     //   189: aload 13
/*     */     //   191: ifnull +67 -> 258
/*     */     //   194: goto +11 -> 205
/*     */     //   197: aload 13
/*     */     //   199: invokevirtual 280	java/lang/Object:equals	(Ljava/lang/Object;)Z
/*     */     //   202: ifne +56 -> 258
/*     */     //   205: getstatic 66	scala/Predef$:MODULE$	Lscala/Predef$;
/*     */     //   208: aload_1
/*     */     //   209: invokevirtual 276	com/yisa/engine/common/InputBean:carYear	()[Ljava/lang/String;
/*     */     //   212: checkcast 284	[Ljava/lang/Object;
/*     */     //   215: invokevirtual 288	scala/Predef$:refArrayOps	([Ljava/lang/Object;)Lscala/collection/mutable/ArrayOps;
/*     */     //   218: new 290	com/yisa/engine/branchV3/SparkEngineV3ForSearchCarByPicPresto$$anonfun$1
/*     */     //   221: dup
/*     */     //   222: aload_0
/*     */     //   223: invokespecial 291	com/yisa/engine/branchV3/SparkEngineV3ForSearchCarByPicPresto$$anonfun$1:<init>	(Lcom/yisa/engine/branchV3/SparkEngineV3ForSearchCarByPicPresto;)V
/*     */     //   226: invokeinterface 297 2 0
/*     */     //   231: checkcast 32	java/lang/String
/*     */     //   234: astore 14
/*     */     //   236: aload 11
/*     */     //   238: ldc_w 299
/*     */     //   241: invokevirtual 263	java/lang/StringBuffer:append	(Ljava/lang/String;)Ljava/lang/StringBuffer;
/*     */     //   244: aload 14
/*     */     //   246: invokevirtual 263	java/lang/StringBuffer:append	(Ljava/lang/String;)Ljava/lang/StringBuffer;
/*     */     //   249: ldc_w 301
/*     */     //   252: invokevirtual 263	java/lang/StringBuffer:append	(Ljava/lang/String;)Ljava/lang/StringBuffer;
/*     */     //   255: goto +6 -> 261
/*     */     //   258: getstatic 307	scala/runtime/BoxedUnit:UNIT	Lscala/runtime/BoxedUnit;
/*     */     //   261: pop
/*     */     //   262: lload 7
/*     */     //   264: lconst_0
/*     */     //   265: lcmp
/*     */     //   266: ifeq +41 -> 307
/*     */     //   269: aload 11
/*     */     //   271: ldc_w 309
/*     */     //   274: invokevirtual 263	java/lang/StringBuffer:append	(Ljava/lang/String;)Ljava/lang/StringBuffer;
/*     */     //   277: getstatic 245	com/yisa/engine/uitl/TimeUtil$:MODULE$	Lcom/yisa/engine/uitl/TimeUtil$;
/*     */     //   280: aload_1
/*     */     //   281: invokevirtual 248	com/yisa/engine/common/InputBean:startTime	()Ljava/lang/String;
/*     */     //   284: invokevirtual 313	com/yisa/engine/uitl/TimeUtil$:getDateId	(Ljava/lang/String;)I
/*     */     //   287: invokevirtual 316	java/lang/StringBuffer:append	(I)Ljava/lang/StringBuffer;
/*     */     //   290: pop
/*     */     //   291: aload 11
/*     */     //   293: ldc_w 318
/*     */     //   296: invokevirtual 263	java/lang/StringBuffer:append	(Ljava/lang/String;)Ljava/lang/StringBuffer;
/*     */     //   299: lload 7
/*     */     //   301: invokevirtual 321	java/lang/StringBuffer:append	(J)Ljava/lang/StringBuffer;
/*     */     //   304: goto +6 -> 310
/*     */     //   307: getstatic 307	scala/runtime/BoxedUnit:UNIT	Lscala/runtime/BoxedUnit;
/*     */     //   310: pop
/*     */     //   311: lload 9
/*     */     //   313: lconst_0
/*     */     //   314: lcmp
/*     */     //   315: ifeq +41 -> 356
/*     */     //   318: aload 11
/*     */     //   320: ldc_w 323
/*     */     //   323: invokevirtual 263	java/lang/StringBuffer:append	(Ljava/lang/String;)Ljava/lang/StringBuffer;
/*     */     //   326: getstatic 245	com/yisa/engine/uitl/TimeUtil$:MODULE$	Lcom/yisa/engine/uitl/TimeUtil$;
/*     */     //   329: aload_1
/*     */     //   330: invokevirtual 255	com/yisa/engine/common/InputBean:endTime	()Ljava/lang/String;
/*     */     //   333: invokevirtual 313	com/yisa/engine/uitl/TimeUtil$:getDateId	(Ljava/lang/String;)I
/*     */     //   336: invokevirtual 316	java/lang/StringBuffer:append	(I)Ljava/lang/StringBuffer;
/*     */     //   339: pop
/*     */     //   340: aload 11
/*     */     //   342: ldc_w 325
/*     */     //   345: invokevirtual 263	java/lang/StringBuffer:append	(Ljava/lang/String;)Ljava/lang/StringBuffer;
/*     */     //   348: lload 9
/*     */     //   350: invokevirtual 321	java/lang/StringBuffer:append	(J)Ljava/lang/StringBuffer;
/*     */     //   353: goto +6 -> 359
/*     */     //   356: getstatic 307	scala/runtime/BoxedUnit:UNIT	Lscala/runtime/BoxedUnit;
/*     */     //   359: pop
/*     */     //   360: aload 6
/*     */     //   362: aconst_null
/*     */     //   363: if_acmpeq +93 -> 456
/*     */     //   366: aload 6
/*     */     //   368: arraylength
/*     */     //   369: iconst_0
/*     */     //   370: if_icmple +86 -> 456
/*     */     //   373: aload_1
/*     */     //   374: invokevirtual 240	com/yisa/engine/common/InputBean:carModel	()[Ljava/lang/String;
/*     */     //   377: iconst_0
/*     */     //   378: aaload
/*     */     //   379: ldc_w 282
/*     */     //   382: astore 15
/*     */     //   384: dup
/*     */     //   385: ifnonnull +12 -> 397
/*     */     //   388: pop
/*     */     //   389: aload 15
/*     */     //   391: ifnull +65 -> 456
/*     */     //   394: goto +11 -> 405
/*     */     //   397: aload 15
/*     */     //   399: invokevirtual 280	java/lang/Object:equals	(Ljava/lang/Object;)Z
/*     */     //   402: ifne +54 -> 456
/*     */     //   405: getstatic 66	scala/Predef$:MODULE$	Lscala/Predef$;
/*     */     //   408: aload 6
/*     */     //   410: checkcast 284	[Ljava/lang/Object;
/*     */     //   413: invokevirtual 288	scala/Predef$:refArrayOps	([Ljava/lang/Object;)Lscala/collection/mutable/ArrayOps;
/*     */     //   416: new 327	com/yisa/engine/branchV3/SparkEngineV3ForSearchCarByPicPresto$$anonfun$2
/*     */     //   419: dup
/*     */     //   420: aload_0
/*     */     //   421: invokespecial 328	com/yisa/engine/branchV3/SparkEngineV3ForSearchCarByPicPresto$$anonfun$2:<init>	(Lcom/yisa/engine/branchV3/SparkEngineV3ForSearchCarByPicPresto;)V
/*     */     //   424: invokeinterface 297 2 0
/*     */     //   429: checkcast 32	java/lang/String
/*     */     //   432: astore 16
/*     */     //   434: aload 11
/*     */     //   436: ldc_w 330
/*     */     //   439: invokevirtual 263	java/lang/StringBuffer:append	(Ljava/lang/String;)Ljava/lang/StringBuffer;
/*     */     //   442: aload 16
/*     */     //   444: invokevirtual 263	java/lang/StringBuffer:append	(Ljava/lang/String;)Ljava/lang/StringBuffer;
/*     */     //   447: ldc_w 301
/*     */     //   450: invokevirtual 263	java/lang/StringBuffer:append	(Ljava/lang/String;)Ljava/lang/StringBuffer;
/*     */     //   453: goto +6 -> 459
/*     */     //   456: getstatic 307	scala/runtime/BoxedUnit:UNIT	Lscala/runtime/BoxedUnit;
/*     */     //   459: pop
/*     */     //   460: aload 5
/*     */     //   462: ifnull +58 -> 520
/*     */     //   465: aload 5
/*     */     //   467: ldc 93
/*     */     //   469: astore 17
/*     */     //   471: dup
/*     */     //   472: ifnonnull +12 -> 484
/*     */     //   475: pop
/*     */     //   476: aload 17
/*     */     //   478: ifnull +42 -> 520
/*     */     //   481: goto +11 -> 492
/*     */     //   484: aload 17
/*     */     //   486: invokevirtual 280	java/lang/Object:equals	(Ljava/lang/Object;)Z
/*     */     //   489: ifne +31 -> 520
/*     */     //   492: aload 5
/*     */     //   494: ldc_w 282
/*     */     //   497: astore 18
/*     */     //   499: dup
/*     */     //   500: ifnonnull +12 -> 512
/*     */     //   503: pop
/*     */     //   504: aload 18
/*     */     //   506: ifnull +14 -> 520
/*     */     //   509: goto +17 -> 526
/*     */     //   512: aload 18
/*     */     //   514: invokevirtual 280	java/lang/Object:equals	(Ljava/lang/Object;)Z
/*     */     //   517: ifeq +9 -> 526
/*     */     //   520: getstatic 307	scala/runtime/BoxedUnit:UNIT	Lscala/runtime/BoxedUnit;
/*     */     //   523: goto +16 -> 539
/*     */     //   526: aload 11
/*     */     //   528: ldc_w 332
/*     */     //   531: invokevirtual 263	java/lang/StringBuffer:append	(Ljava/lang/String;)Ljava/lang/StringBuffer;
/*     */     //   534: aload 5
/*     */     //   536: invokevirtual 263	java/lang/StringBuffer:append	(Ljava/lang/String;)Ljava/lang/StringBuffer;
/*     */     //   539: pop
/*     */     //   540: aload 11
/*     */     //   542: ldc_w 334
/*     */     //   545: invokevirtual 263	java/lang/StringBuffer:append	(Ljava/lang/String;)Ljava/lang/StringBuffer;
/*     */     //   548: pop
/*     */     //   549: iload_3
/*     */     //   550: ifeq +23 -> 573
/*     */     //   553: aload 11
/*     */     //   555: ldc_w 336
/*     */     //   558: invokevirtual 263	java/lang/StringBuffer:append	(Ljava/lang/String;)Ljava/lang/StringBuffer;
/*     */     //   561: pop
/*     */     //   562: aload 11
/*     */     //   564: ldc_w 338
/*     */     //   567: invokevirtual 263	java/lang/StringBuffer:append	(Ljava/lang/String;)Ljava/lang/StringBuffer;
/*     */     //   570: goto +6 -> 576
/*     */     //   573: getstatic 307	scala/runtime/BoxedUnit:UNIT	Lscala/runtime/BoxedUnit;
/*     */     //   576: pop
/*     */     //   577: aload 11
/*     */     //   579: ldc_w 340
/*     */     //   582: invokevirtual 263	java/lang/StringBuffer:append	(Ljava/lang/String;)Ljava/lang/StringBuffer;
/*     */     //   585: pop
/*     */     //   586: aload 11
/*     */     //   588: invokevirtual 341	java/lang/StringBuffer:toString	()Ljava/lang/String;
/*     */     //   591: areturn
/*     */     // Line number table:
/*     */     //   Java source line #105	-> byte code offset #0
/*     */     //   Java source line #107	-> byte code offset #6
/*     */     //   Java source line #109	-> byte code offset #12
/*     */     //   Java source line #113	-> byte code offset #18
/*     */     //   Java source line #114	-> byte code offset #30
/*     */     //   Java source line #116	-> byte code offset #42
/*     */     //   Java source line #118	-> byte code offset #51
/*     */     //   Java source line #119	-> byte code offset #60
/*     */     //   Java source line #120	-> byte code offset #69
/*     */     //   Java source line #122	-> byte code offset #102
/*     */     //   Java source line #124	-> byte code offset #134
/*     */     //   Java source line #125	-> byte code offset #205
/*     */     //   Java source line #126	-> byte code offset #236
/*     */     //   Java source line #124	-> byte code offset #258
/*     */     //   Java source line #129	-> byte code offset #262
/*     */     //   Java source line #130	-> byte code offset #269
/*     */     //   Java source line #131	-> byte code offset #291
/*     */     //   Java source line #129	-> byte code offset #307
/*     */     //   Java source line #134	-> byte code offset #311
/*     */     //   Java source line #135	-> byte code offset #318
/*     */     //   Java source line #136	-> byte code offset #340
/*     */     //   Java source line #134	-> byte code offset #356
/*     */     //   Java source line #139	-> byte code offset #360
/*     */     //   Java source line #140	-> byte code offset #405
/*     */     //   Java source line #141	-> byte code offset #434
/*     */     //   Java source line #139	-> byte code offset #456
/*     */     //   Java source line #144	-> byte code offset #460
/*     */     //   Java source line #145	-> byte code offset #526
/*     */     //   Java source line #144	-> byte code offset #539
/*     */     //   Java source line #149	-> byte code offset #540
/*     */     //   Java source line #151	-> byte code offset #549
/*     */     //   Java source line #152	-> byte code offset #553
/*     */     //   Java source line #153	-> byte code offset #562
/*     */     //   Java source line #151	-> byte code offset #573
/*     */     //   Java source line #156	-> byte code offset #577
/*     */     //   Java source line #157	-> byte code offset #586
/*     */     // Local variable table:
/*     */     //   start	length	slot	name	signature
/*     */     //   0	592	0	this	SparkEngineV3ForSearchCarByPicPresto
/*     */     //   0	592	1	map	InputBean
/*     */     //   0	592	2	tableName	String
/*     */     //   0	592	3	similarityLimit	boolean
/*     */     //   6	585	4	feature	String
/*     */     //   12	579	5	carBrand	String
/*     */     //   18	573	6	carModel	String[]
/*     */     //   30	561	7	startTime	long
/*     */     //   42	549	9	endTime	long
/*     */     //   51	540	11	sb	StringBuffer
/*     */     //   236	19	14	m	String
/*     */     //   434	19	16	m	String
/*     */   }
/*     */   
/*     */   public SparkEngineV3ForSearchCarByPicPresto(SparkSession sqlContext, String line, String tableName, String zkHostport, String PrestoHostPort) {}
/*     */ }


/* Location:              E:\BaiduYunDownload\伊萨时期的一些代码\SparkEngine终极版\jars\YISAEngineBySpark2-4.0.6-SNAPSHOT-jar-with-dependencies.jar!\com\yisa\engine\branchV3\SparkEngineV3ForSearchCarByPicPresto.class
 * Java compiler version: 6 (50.0)
 * JD-Core Version:       0.7.1
 */