/*    */ package com.yisa.engine.branchV3;
/*    */ 
/*    */ import java.sql.Connection;
/*    */ import java.sql.PreparedStatement;
/*    */ import org.apache.spark.sql.Row;
/*    */ import scala.collection.mutable.StringBuilder;
/*    */ import scala.runtime.IntRef;
/*    */ import scala.runtime.ObjectRef;
/*    */ 
/*    */ @scala.reflect.ScalaSignature(bytes="\006\001M3A!\001\002\001\027\ti2\013]1sW\026sw-\0338f-N2uN\035$sKF,XM\034;ms\016\013'O\003\002\004\t\005A!M]1oG\"46G\003\002\006\r\0051QM\\4j]\026T!a\002\005\002\teL7/\031\006\002\023\005\0311m\\7\004\001M\031\001\001\004\013\021\0055\021R\"\001\b\013\005=\001\022\001\0027b]\036T\021!E\001\005U\0064\030-\003\002\024\035\t1qJ\0316fGR\004\"!D\013\n\005Yq!\001\003*v]:\f'\r\\3\t\021a\001!\021!Q\001\ne\tAb\0359be.\034Vm]:j_:\004\"AG\022\016\003mQ!\001H\017\002\007M\fHN\003\002\037?\005)1\017]1sW*\021\001%I\001\007CB\f7\r[3\013\003\t\n1a\034:h\023\t!3D\001\007Ta\006\0248nU3tg&|g\016\003\005'\001\t\005\t\025!\003(\003\021a\027N\\3\021\005!rcBA\025-\033\005Q#\"A\026\002\013M\034\027\r\\1\n\0055R\023A\002)sK\022,g-\003\0020a\t11\013\036:j]\036T!!\f\026\t\021I\002!\021!Q\001\n\035\n\021\002^1cY\026t\025-\\3\t\021Q\002!\021!Q\001\n\035\n1B]3tk2$H+\0312mK\"Aa\007\001B\001B\003%q%\001\006{W\"{7\017\0369peRDQ\001\017\001\005\002e\na\001P5oSRtDC\002\036={yz\004\t\005\002<\0015\t!\001C\003\031o\001\007\021\004C\003'o\001\007q\005C\0033o\001\007q\005C\0035o\001\007q\005C\0037o\001\007q\005C\003C\001\021\0053)A\002sk:$\022\001\022\t\003S\025K!A\022\026\003\tUs\027\016\036\005\006\021\002!\t!S\001\007O\026$8+\025'\025\007\035R%\013C\003L\017\002\007A*A\002nCB\004\"!\024)\016\0039S!a\024\003\002\r\r|W.\\8o\023\t\tfJA\005J]B,HOQ3b]\")!g\022a\001O\001")
/*    */ public class SparkEngineV3ForFrequentlyCar implements Runnable
/*    */ {
/*    */   private final org.apache.spark.sql.SparkSession sparkSession;
/*    */   
/*    */   public void run()
/*    */   {
/* 17 */     long date1 = new java.util.Date().getTime();
/*    */     
/* 19 */     final String jdbcTable = this.resultTable;
/*    */     
/* 21 */     String[] line_arr = this.line.split("\\|");
/*    */     
/* 23 */     final String jobId = line_arr[1];
/* 24 */     String params = line_arr[2];
/*    */     
/* 26 */     com.google.gson.Gson gson = new com.google.gson.Gson();
/* 27 */     java.lang.reflect.Type mapType = new com.google.gson.reflect.TypeToken() {}.getType();
/* 28 */     com.yisa.engine.common.InputBean map = (com.yisa.engine.common.InputBean)gson.fromJson(params, mapType);
/*    */     
/* 30 */     String sqlStr = getSQL(map, this.tableName);
/*    */     
/* 32 */     org.apache.spark.sql.Dataset resultData = this.sparkSession.sql(sqlStr);
/*    */     
/* 34 */     scala.Predef..MODULE$.println(new StringBuilder().append("SQL--------------:").append(sqlStr).toString());
/*    */     
/* 36 */     int count2 = map.count();
/*    */     
/* 38 */     Row[] resultData2 = (Row[])resultData.collect();
/*    */     
/* 40 */     Connection conn = com.yisa.engine.db.MySQLConnectManager..MODULE$.getConnet(this.com$yisa$engine$branchV3$SparkEngineV3ForFrequentlyCar$$zkHostport);
/* 41 */     conn.setAutoCommit(false);
/* 42 */     String sql = new StringBuilder().append("insert into ").append(jdbcTable).append(" (s_id,count,j_id,l_id) values(?,?,?,?)").toString();
/* 43 */     PreparedStatement pstmt = conn.prepareStatement(sql);
/* 44 */     int count = 0;
/*    */     
/* 46 */     resultData.foreachPartition(new scala.runtime.AbstractFunction1() { public static final long serialVersionUID = 0L;
/*    */       
/* 48 */       public final void apply(scala.collection.Iterator<Row> data) { Connection conn = com.yisa.engine.db.MySQLConnectManager..MODULE$.getConnet(SparkEngineV3ForFrequentlyCar.this.com$yisa$engine$branchV3$SparkEngineV3ForFrequentlyCar$$zkHostport);
/* 49 */         conn.setAutoCommit(false);
/* 50 */         String sql = new StringBuilder().append("insert into ").append(jdbcTable).append(" (s_id,count,j_id,l_id) values(?,?,?,?)").toString();
/* 51 */         final ObjectRef pstmt = ObjectRef.create(conn.prepareStatement(sql));
/* 52 */         final IntRef count = IntRef.create(0);
/* 53 */         data.foreach(new scala.runtime.AbstractFunction1()
/*    */         {
/*    */           public static final long serialVersionUID = 0L;
/*    */           
/*    */           public final void apply(Row t) {
/* 58 */             ((PreparedStatement)pstmt.elem).setString(1, t.apply(0).toString());
/* 59 */             ((PreparedStatement)pstmt.elem).setInt(2, new scala.collection.immutable.StringOps(scala.Predef..MODULE$.augmentString(t.apply(1).toString())).toInt());
/* 60 */             ((PreparedStatement)pstmt.elem).setString(3, SparkEngineV3ForFrequentlyCar..anonfun.run.1.this.jobId$1);
/* 61 */             if (t.apply(2) == null)
/*    */             {
/*    */ 
/* 64 */               ((PreparedStatement)pstmt.elem).setString(4, "");
/*    */             } else {
/* 62 */               ((PreparedStatement)pstmt.elem).setString(4, t.apply(2).toString());
/*    */             }
/*    */             
/*    */ 
/* 66 */             ((PreparedStatement)pstmt.elem).addBatch();
/* 67 */             count.elem += 1;
/*    */           }
/*    */           
/*    */ 
/* 71 */         });
/* 72 */         String sql2 = "insert into pfgc_count (j_id,count) values(?,?)";
/* 73 */         PreparedStatement pstmt2 = conn.prepareStatement(sql2);
/*    */         
/* 75 */         if (count.elem == 0) {
/* 76 */           count.elem = -1;
/*    */         }
/* 78 */         pstmt2.setString(1, jobId);
/* 79 */         pstmt2.setInt(2, count.elem);
/* 80 */         pstmt2.executeUpdate();
/* 81 */         pstmt2.close();
/*    */         
/* 83 */         ((PreparedStatement)pstmt.elem).executeBatch();
/* 84 */         conn.commit();
/* 85 */         ((PreparedStatement)pstmt.elem).close();
/* 86 */         conn.close();
/* 87 */       } });
/* 88 */     long date2 = new java.util.Date().getTime();
/* 89 */     scala.Predef..MODULE$.println(new StringBuilder().append("SparkEngineV3ForFrequentlyCar  time :").append(scala.runtime.BoxesRunTime.boxToLong(date2 - date1)).toString());
/*    */   }
/*    */   
/*    */   /* Error */
/*    */   public String getSQL(com.yisa.engine.common.InputBean map, String tableName)
/*    */   {
/*    */     // Byte code:
/*    */     //   0: getstatic 180	com/yisa/engine/uitl/TimeUtil$:MODULE$	Lcom/yisa/engine/uitl/TimeUtil$;
/*    */     //   3: aload_1
/*    */     //   4: invokevirtual 183	com/yisa/engine/common/InputBean:startTime	()Ljava/lang/String;
/*    */     //   7: invokevirtual 187	com/yisa/engine/uitl/TimeUtil$:getTimestampLong	(Ljava/lang/String;)J
/*    */     //   10: lstore_3
/*    */     //   11: getstatic 180	com/yisa/engine/uitl/TimeUtil$:MODULE$	Lcom/yisa/engine/uitl/TimeUtil$;
/*    */     //   14: aload_1
/*    */     //   15: invokevirtual 190	com/yisa/engine/common/InputBean:endTime	()Ljava/lang/String;
/*    */     //   18: invokevirtual 187	com/yisa/engine/uitl/TimeUtil$:getTimestampLong	(Ljava/lang/String;)J
/*    */     //   21: lstore 5
/*    */     //   23: getstatic 180	com/yisa/engine/uitl/TimeUtil$:MODULE$	Lcom/yisa/engine/uitl/TimeUtil$;
/*    */     //   26: aload_1
/*    */     //   27: invokevirtual 183	com/yisa/engine/common/InputBean:startTime	()Ljava/lang/String;
/*    */     //   30: invokevirtual 194	com/yisa/engine/uitl/TimeUtil$:getDateId	(Ljava/lang/String;)I
/*    */     //   33: istore 7
/*    */     //   35: getstatic 180	com/yisa/engine/uitl/TimeUtil$:MODULE$	Lcom/yisa/engine/uitl/TimeUtil$;
/*    */     //   38: aload_1
/*    */     //   39: invokevirtual 190	com/yisa/engine/common/InputBean:endTime	()Ljava/lang/String;
/*    */     //   42: invokevirtual 194	com/yisa/engine/uitl/TimeUtil$:getDateId	(Ljava/lang/String;)I
/*    */     //   45: istore 8
/*    */     //   47: aload_1
/*    */     //   48: invokevirtual 198	com/yisa/engine/common/InputBean:locationId	()[Ljava/lang/String;
/*    */     //   51: astore 9
/*    */     //   53: aload_1
/*    */     //   54: invokevirtual 201	com/yisa/engine/common/InputBean:carModel	()[Ljava/lang/String;
/*    */     //   57: astore 10
/*    */     //   59: aload_1
/*    */     //   60: invokevirtual 204	com/yisa/engine/common/InputBean:carBrand	()Ljava/lang/String;
/*    */     //   63: astore 11
/*    */     //   65: aload_1
/*    */     //   66: invokevirtual 207	com/yisa/engine/common/InputBean:carYear	()[Ljava/lang/String;
/*    */     //   69: astore 12
/*    */     //   71: aload_1
/*    */     //   72: invokevirtual 210	com/yisa/engine/common/InputBean:carColor	()Ljava/lang/String;
/*    */     //   75: astore 13
/*    */     //   77: aload_1
/*    */     //   78: invokevirtual 213	com/yisa/engine/common/InputBean:plateNumber	()Ljava/lang/String;
/*    */     //   81: astore 14
/*    */     //   83: aload_1
/*    */     //   84: invokevirtual 99	com/yisa/engine/common/InputBean:count	()I
/*    */     //   87: istore 15
/*    */     //   89: new 215	java/lang/StringBuffer
/*    */     //   92: dup
/*    */     //   93: invokespecial 216	java/lang/StringBuffer:<init>	()V
/*    */     //   96: astore 16
/*    */     //   98: aload 16
/*    */     //   100: ldc -38
/*    */     //   102: invokevirtual 221	java/lang/StringBuffer:append	(Ljava/lang/String;)Ljava/lang/StringBuffer;
/*    */     //   105: pop
/*    */     //   106: aload 16
/*    */     //   108: ldc -33
/*    */     //   110: invokevirtual 221	java/lang/StringBuffer:append	(Ljava/lang/String;)Ljava/lang/StringBuffer;
/*    */     //   113: aload_2
/*    */     //   114: invokevirtual 221	java/lang/StringBuffer:append	(Ljava/lang/String;)Ljava/lang/StringBuffer;
/*    */     //   117: pop
/*    */     //   118: aload 16
/*    */     //   120: ldc -31
/*    */     //   122: invokevirtual 221	java/lang/StringBuffer:append	(Ljava/lang/String;)Ljava/lang/StringBuffer;
/*    */     //   125: pop
/*    */     //   126: lload_3
/*    */     //   127: lconst_0
/*    */     //   128: lcmp
/*    */     //   129: ifeq +17 -> 146
/*    */     //   132: aload 16
/*    */     //   134: ldc -29
/*    */     //   136: invokevirtual 221	java/lang/StringBuffer:append	(Ljava/lang/String;)Ljava/lang/StringBuffer;
/*    */     //   139: lload_3
/*    */     //   140: invokevirtual 230	java/lang/StringBuffer:append	(J)Ljava/lang/StringBuffer;
/*    */     //   143: goto +6 -> 149
/*    */     //   146: getstatic 236	scala/runtime/BoxedUnit:UNIT	Lscala/runtime/BoxedUnit;
/*    */     //   149: pop
/*    */     //   150: lload 5
/*    */     //   152: lconst_0
/*    */     //   153: lcmp
/*    */     //   154: ifeq +18 -> 172
/*    */     //   157: aload 16
/*    */     //   159: ldc -18
/*    */     //   161: invokevirtual 221	java/lang/StringBuffer:append	(Ljava/lang/String;)Ljava/lang/StringBuffer;
/*    */     //   164: lload 5
/*    */     //   166: invokevirtual 230	java/lang/StringBuffer:append	(J)Ljava/lang/StringBuffer;
/*    */     //   169: goto +6 -> 175
/*    */     //   172: getstatic 236	scala/runtime/BoxedUnit:UNIT	Lscala/runtime/BoxedUnit;
/*    */     //   175: pop
/*    */     //   176: aload 9
/*    */     //   178: aconst_null
/*    */     //   179: if_acmpeq +97 -> 276
/*    */     //   182: aload 9
/*    */     //   184: arraylength
/*    */     //   185: iconst_0
/*    */     //   186: if_icmple +90 -> 276
/*    */     //   189: getstatic 78	scala/Predef$:MODULE$	Lscala/Predef$;
/*    */     //   192: getstatic 78	scala/Predef$:MODULE$	Lscala/Predef$;
/*    */     //   195: aload 9
/*    */     //   197: checkcast 240	[Ljava/lang/Object;
/*    */     //   200: invokevirtual 244	scala/Predef$:refArrayOps	([Ljava/lang/Object;)Lscala/collection/mutable/ArrayOps;
/*    */     //   203: new 246	com/yisa/engine/branchV3/SparkEngineV3ForFrequentlyCar$$anonfun$1
/*    */     //   206: dup
/*    */     //   207: aload_0
/*    */     //   208: invokespecial 247	com/yisa/engine/branchV3/SparkEngineV3ForFrequentlyCar$$anonfun$1:<init>	(Lcom/yisa/engine/branchV3/SparkEngineV3ForFrequentlyCar;)V
/*    */     //   211: getstatic 252	scala/Array$:MODULE$	Lscala/Array$;
/*    */     //   214: getstatic 257	scala/reflect/ClassTag$:MODULE$	Lscala/reflect/ClassTag$;
/*    */     //   217: ldc 36
/*    */     //   219: invokevirtual 261	scala/reflect/ClassTag$:apply	(Ljava/lang/Class;)Lscala/reflect/ClassTag;
/*    */     //   222: invokevirtual 265	scala/Array$:canBuildFrom	(Lscala/reflect/ClassTag;)Lscala/collection/generic/CanBuildFrom;
/*    */     //   225: invokeinterface 270 3 0
/*    */     //   230: checkcast 240	[Ljava/lang/Object;
/*    */     //   233: invokevirtual 244	scala/Predef$:refArrayOps	([Ljava/lang/Object;)Lscala/collection/mutable/ArrayOps;
/*    */     //   236: new 272	com/yisa/engine/branchV3/SparkEngineV3ForFrequentlyCar$$anonfun$2
/*    */     //   239: dup
/*    */     //   240: aload_0
/*    */     //   241: invokespecial 273	com/yisa/engine/branchV3/SparkEngineV3ForFrequentlyCar$$anonfun$2:<init>	(Lcom/yisa/engine/branchV3/SparkEngineV3ForFrequentlyCar;)V
/*    */     //   244: invokeinterface 277 2 0
/*    */     //   249: checkcast 36	java/lang/String
/*    */     //   252: astore 17
/*    */     //   254: aload 16
/*    */     //   256: ldc_w 279
/*    */     //   259: invokevirtual 221	java/lang/StringBuffer:append	(Ljava/lang/String;)Ljava/lang/StringBuffer;
/*    */     //   262: aload 17
/*    */     //   264: invokevirtual 221	java/lang/StringBuffer:append	(Ljava/lang/String;)Ljava/lang/StringBuffer;
/*    */     //   267: ldc_w 281
/*    */     //   270: invokevirtual 221	java/lang/StringBuffer:append	(Ljava/lang/String;)Ljava/lang/StringBuffer;
/*    */     //   273: goto +6 -> 279
/*    */     //   276: getstatic 236	scala/runtime/BoxedUnit:UNIT	Lscala/runtime/BoxedUnit;
/*    */     //   279: pop
/*    */     //   280: aload 10
/*    */     //   282: aconst_null
/*    */     //   283: if_acmpeq +61 -> 344
/*    */     //   286: aload 10
/*    */     //   288: arraylength
/*    */     //   289: iconst_0
/*    */     //   290: if_icmple +54 -> 344
/*    */     //   293: getstatic 78	scala/Predef$:MODULE$	Lscala/Predef$;
/*    */     //   296: aload 10
/*    */     //   298: checkcast 240	[Ljava/lang/Object;
/*    */     //   301: invokevirtual 244	scala/Predef$:refArrayOps	([Ljava/lang/Object;)Lscala/collection/mutable/ArrayOps;
/*    */     //   304: new 283	com/yisa/engine/branchV3/SparkEngineV3ForFrequentlyCar$$anonfun$3
/*    */     //   307: dup
/*    */     //   308: aload_0
/*    */     //   309: invokespecial 284	com/yisa/engine/branchV3/SparkEngineV3ForFrequentlyCar$$anonfun$3:<init>	(Lcom/yisa/engine/branchV3/SparkEngineV3ForFrequentlyCar;)V
/*    */     //   312: invokeinterface 277 2 0
/*    */     //   317: checkcast 36	java/lang/String
/*    */     //   320: astore 18
/*    */     //   322: aload 16
/*    */     //   324: ldc_w 286
/*    */     //   327: invokevirtual 221	java/lang/StringBuffer:append	(Ljava/lang/String;)Ljava/lang/StringBuffer;
/*    */     //   330: aload 18
/*    */     //   332: invokevirtual 221	java/lang/StringBuffer:append	(Ljava/lang/String;)Ljava/lang/StringBuffer;
/*    */     //   335: ldc_w 281
/*    */     //   338: invokevirtual 221	java/lang/StringBuffer:append	(Ljava/lang/String;)Ljava/lang/StringBuffer;
/*    */     //   341: goto +6 -> 347
/*    */     //   344: getstatic 236	scala/runtime/BoxedUnit:UNIT	Lscala/runtime/BoxedUnit;
/*    */     //   347: pop
/*    */     //   348: aload 11
/*    */     //   350: ifnull +31 -> 381
/*    */     //   353: aload 11
/*    */     //   355: ldc_w 288
/*    */     //   358: astore 19
/*    */     //   360: dup
/*    */     //   361: ifnonnull +12 -> 373
/*    */     //   364: pop
/*    */     //   365: aload 19
/*    */     //   367: ifnull +14 -> 381
/*    */     //   370: goto +17 -> 387
/*    */     //   373: aload 19
/*    */     //   375: invokevirtual 292	java/lang/Object:equals	(Ljava/lang/Object;)Z
/*    */     //   378: ifeq +9 -> 387
/*    */     //   381: getstatic 236	scala/runtime/BoxedUnit:UNIT	Lscala/runtime/BoxedUnit;
/*    */     //   384: goto +16 -> 400
/*    */     //   387: aload 16
/*    */     //   389: ldc_w 294
/*    */     //   392: invokevirtual 221	java/lang/StringBuffer:append	(Ljava/lang/String;)Ljava/lang/StringBuffer;
/*    */     //   395: aload 11
/*    */     //   397: invokevirtual 221	java/lang/StringBuffer:append	(Ljava/lang/String;)Ljava/lang/StringBuffer;
/*    */     //   400: pop
/*    */     //   401: aload 13
/*    */     //   403: ifnull +31 -> 434
/*    */     //   406: aload 13
/*    */     //   408: ldc_w 288
/*    */     //   411: astore 20
/*    */     //   413: dup
/*    */     //   414: ifnonnull +12 -> 426
/*    */     //   417: pop
/*    */     //   418: aload 20
/*    */     //   420: ifnull +14 -> 434
/*    */     //   423: goto +17 -> 440
/*    */     //   426: aload 20
/*    */     //   428: invokevirtual 292	java/lang/Object:equals	(Ljava/lang/Object;)Z
/*    */     //   431: ifeq +9 -> 440
/*    */     //   434: getstatic 236	scala/runtime/BoxedUnit:UNIT	Lscala/runtime/BoxedUnit;
/*    */     //   437: goto +16 -> 453
/*    */     //   440: aload 16
/*    */     //   442: ldc_w 296
/*    */     //   445: invokevirtual 221	java/lang/StringBuffer:append	(Ljava/lang/String;)Ljava/lang/StringBuffer;
/*    */     //   448: aload 13
/*    */     //   450: invokevirtual 221	java/lang/StringBuffer:append	(Ljava/lang/String;)Ljava/lang/StringBuffer;
/*    */     //   453: pop
/*    */     //   454: aload 14
/*    */     //   456: ifnull +31 -> 487
/*    */     //   459: aload 14
/*    */     //   461: ldc_w 288
/*    */     //   464: astore 21
/*    */     //   466: dup
/*    */     //   467: ifnonnull +12 -> 479
/*    */     //   470: pop
/*    */     //   471: aload 21
/*    */     //   473: ifnull +14 -> 487
/*    */     //   476: goto +17 -> 493
/*    */     //   479: aload 21
/*    */     //   481: invokevirtual 292	java/lang/Object:equals	(Ljava/lang/Object;)Z
/*    */     //   484: ifeq +9 -> 493
/*    */     //   487: getstatic 236	scala/runtime/BoxedUnit:UNIT	Lscala/runtime/BoxedUnit;
/*    */     //   490: goto +66 -> 556
/*    */     //   493: aload 14
/*    */     //   495: ldc_w 298
/*    */     //   498: invokevirtual 302	java/lang/String:contains	(Ljava/lang/CharSequence;)Z
/*    */     //   501: ifne +14 -> 515
/*    */     //   504: aload 14
/*    */     //   506: ldc_w 304
/*    */     //   509: invokevirtual 302	java/lang/String:contains	(Ljava/lang/CharSequence;)Z
/*    */     //   512: ifeq +25 -> 537
/*    */     //   515: aload 16
/*    */     //   517: ldc_w 306
/*    */     //   520: invokevirtual 221	java/lang/StringBuffer:append	(Ljava/lang/String;)Ljava/lang/StringBuffer;
/*    */     //   523: aload 14
/*    */     //   525: invokevirtual 221	java/lang/StringBuffer:append	(Ljava/lang/String;)Ljava/lang/StringBuffer;
/*    */     //   528: ldc_w 308
/*    */     //   531: invokevirtual 221	java/lang/StringBuffer:append	(Ljava/lang/String;)Ljava/lang/StringBuffer;
/*    */     //   534: goto +22 -> 556
/*    */     //   537: aload 16
/*    */     //   539: ldc_w 310
/*    */     //   542: invokevirtual 221	java/lang/StringBuffer:append	(Ljava/lang/String;)Ljava/lang/StringBuffer;
/*    */     //   545: aload 14
/*    */     //   547: invokevirtual 221	java/lang/StringBuffer:append	(Ljava/lang/String;)Ljava/lang/StringBuffer;
/*    */     //   550: ldc_w 308
/*    */     //   553: invokevirtual 221	java/lang/StringBuffer:append	(Ljava/lang/String;)Ljava/lang/StringBuffer;
/*    */     //   556: pop
/*    */     //   557: lload_3
/*    */     //   558: lconst_0
/*    */     //   559: lcmp
/*    */     //   560: ifeq +19 -> 579
/*    */     //   563: aload 16
/*    */     //   565: ldc_w 312
/*    */     //   568: invokevirtual 221	java/lang/StringBuffer:append	(Ljava/lang/String;)Ljava/lang/StringBuffer;
/*    */     //   571: iload 7
/*    */     //   573: invokevirtual 315	java/lang/StringBuffer:append	(I)Ljava/lang/StringBuffer;
/*    */     //   576: goto +6 -> 582
/*    */     //   579: getstatic 236	scala/runtime/BoxedUnit:UNIT	Lscala/runtime/BoxedUnit;
/*    */     //   582: pop
/*    */     //   583: lload 5
/*    */     //   585: lconst_0
/*    */     //   586: lcmp
/*    */     //   587: ifeq +19 -> 606
/*    */     //   590: aload 16
/*    */     //   592: ldc_w 317
/*    */     //   595: invokevirtual 221	java/lang/StringBuffer:append	(Ljava/lang/String;)Ljava/lang/StringBuffer;
/*    */     //   598: iload 8
/*    */     //   600: invokevirtual 315	java/lang/StringBuffer:append	(I)Ljava/lang/StringBuffer;
/*    */     //   603: goto +6 -> 609
/*    */     //   606: getstatic 236	scala/runtime/BoxedUnit:UNIT	Lscala/runtime/BoxedUnit;
/*    */     //   609: pop
/*    */     //   610: aload 16
/*    */     //   612: ldc_w 319
/*    */     //   615: invokevirtual 221	java/lang/StringBuffer:append	(Ljava/lang/String;)Ljava/lang/StringBuffer;
/*    */     //   618: pop
/*    */     //   619: aload 16
/*    */     //   621: ldc_w 321
/*    */     //   624: invokevirtual 221	java/lang/StringBuffer:append	(Ljava/lang/String;)Ljava/lang/StringBuffer;
/*    */     //   627: iload 15
/*    */     //   629: invokevirtual 315	java/lang/StringBuffer:append	(I)Ljava/lang/StringBuffer;
/*    */     //   632: pop
/*    */     //   633: aload 16
/*    */     //   635: ldc_w 323
/*    */     //   638: invokevirtual 221	java/lang/StringBuffer:append	(Ljava/lang/String;)Ljava/lang/StringBuffer;
/*    */     //   641: pop
/*    */     //   642: aload 16
/*    */     //   644: ldc_w 325
/*    */     //   647: invokevirtual 221	java/lang/StringBuffer:append	(Ljava/lang/String;)Ljava/lang/StringBuffer;
/*    */     //   650: pop
/*    */     //   651: aload 16
/*    */     //   653: invokevirtual 326	java/lang/StringBuffer:toString	()Ljava/lang/String;
/*    */     //   656: areturn
/*    */     // Line number table:
/*    */     //   Java source line #96	-> byte code offset #0
/*    */     //   Java source line #97	-> byte code offset #11
/*    */     //   Java source line #99	-> byte code offset #23
/*    */     //   Java source line #100	-> byte code offset #35
/*    */     //   Java source line #102	-> byte code offset #47
/*    */     //   Java source line #103	-> byte code offset #53
/*    */     //   Java source line #104	-> byte code offset #59
/*    */     //   Java source line #105	-> byte code offset #65
/*    */     //   Java source line #106	-> byte code offset #71
/*    */     //   Java source line #107	-> byte code offset #77
/*    */     //   Java source line #108	-> byte code offset #83
/*    */     //   Java source line #110	-> byte code offset #89
/*    */     //   Java source line #112	-> byte code offset #98
/*    */     //   Java source line #115	-> byte code offset #106
/*    */     //   Java source line #117	-> byte code offset #118
/*    */     //   Java source line #119	-> byte code offset #126
/*    */     //   Java source line #120	-> byte code offset #132
/*    */     //   Java source line #119	-> byte code offset #146
/*    */     //   Java source line #123	-> byte code offset #150
/*    */     //   Java source line #124	-> byte code offset #157
/*    */     //   Java source line #123	-> byte code offset #172
/*    */     //   Java source line #135	-> byte code offset #176
/*    */     //   Java source line #136	-> byte code offset #189
/*    */     //   Java source line #138	-> byte code offset #254
/*    */     //   Java source line #135	-> byte code offset #276
/*    */     //   Java source line #141	-> byte code offset #280
/*    */     //   Java source line #142	-> byte code offset #293
/*    */     //   Java source line #143	-> byte code offset #322
/*    */     //   Java source line #141	-> byte code offset #344
/*    */     //   Java source line #146	-> byte code offset #348
/*    */     //   Java source line #147	-> byte code offset #387
/*    */     //   Java source line #146	-> byte code offset #400
/*    */     //   Java source line #150	-> byte code offset #401
/*    */     //   Java source line #151	-> byte code offset #440
/*    */     //   Java source line #150	-> byte code offset #453
/*    */     //   Java source line #154	-> byte code offset #454
/*    */     //   Java source line #155	-> byte code offset #493
/*    */     //   Java source line #156	-> byte code offset #515
/*    */     //   Java source line #158	-> byte code offset #537
/*    */     //   Java source line #154	-> byte code offset #556
/*    */     //   Java source line #169	-> byte code offset #557
/*    */     //   Java source line #170	-> byte code offset #563
/*    */     //   Java source line #169	-> byte code offset #579
/*    */     //   Java source line #173	-> byte code offset #583
/*    */     //   Java source line #174	-> byte code offset #590
/*    */     //   Java source line #173	-> byte code offset #606
/*    */     //   Java source line #177	-> byte code offset #610
/*    */     //   Java source line #179	-> byte code offset #619
/*    */     //   Java source line #180	-> byte code offset #633
/*    */     //   Java source line #181	-> byte code offset #642
/*    */     //   Java source line #183	-> byte code offset #651
/*    */     // Local variable table:
/*    */     //   start	length	slot	name	signature
/*    */     //   0	657	0	this	SparkEngineV3ForFrequentlyCar
/*    */     //   0	657	1	map	com.yisa.engine.common.InputBean
/*    */     //   0	657	2	tableName	String
/*    */     //   11	645	3	startTime	long
/*    */     //   23	633	5	endTime	long
/*    */     //   35	621	7	startTimeDateid	int
/*    */     //   47	609	8	endTimeDateid	int
/*    */     //   53	603	9	locationId	String[]
/*    */     //   59	597	10	carModel	String[]
/*    */     //   65	591	11	carBrand	String
/*    */     //   71	585	12	carYear	String[]
/*    */     //   77	579	13	carColor	String
/*    */     //   83	573	14	plateNumber	String
/*    */     //   89	567	15	count	int
/*    */     //   98	558	16	sb	StringBuffer
/*    */     //   254	19	17	l	String
/*    */     //   322	19	18	m	String
/*    */   }
/*    */   
/*    */   public SparkEngineV3ForFrequentlyCar(org.apache.spark.sql.SparkSession sparkSession, String line, String tableName, String resultTable, String zkHostport) {}
/*    */ }


/* Location:              E:\BaiduYunDownload\伊萨时期的一些代码\SparkEngine终极版\jars\YISAEngineBySpark2-4.0.6-SNAPSHOT-jar-with-dependencies.jar!\com\yisa\engine\branchV3\SparkEngineV3ForFrequentlyCar.class
 * Java compiler version: 6 (50.0)
 * JD-Core Version:       0.7.1
 */