/*     */ package com.yisa.engine.branchV3;
/*     */ 
/*     */ import java.sql.Connection;
/*     */ import java.sql.PreparedStatement;
/*     */ import org.apache.spark.sql.Dataset;
/*     */ import org.apache.spark.sql.Row;
/*     */ import scala.Predef.;
/*     */ import scala.Serializable;
/*     */ import scala.collection.Iterator;
/*     */ import scala.collection.mutable.Map;
/*     */ import scala.collection.mutable.StringBuilder;
/*     */ import scala.runtime.AbstractFunction1;
/*     */ import scala.runtime.BoxedUnit;
/*     */ import scala.runtime.ObjectRef;
/*     */ 
/*     */ @scala.reflect.ScalaSignature(bytes="\006\001\005Ub\001B\001\003\001-\021Ad\0259be.,enZ5oKZ\033di\034:TS6LG.\031:QY\006$XM\003\002\004\t\005A!M]1oG\"46G\003\002\006\r\0051QM\\4j]\026T!a\002\005\002\teL7/\031\006\002\023\005\0311m\\7\004\001M\031\001\001\004\013\021\0055\021R\"\001\b\013\005=\001\022\001\0027b]\036T\021!E\001\005U\0064\030-\003\002\024\035\t1qJ\0316fGR\004\"!D\013\n\005Yq!\001\003*v]:\f'\r\\3\t\021a\001!\021!Q\001\ne\t\021b\0359be.$\025\r^1\021\007i\031S%D\001\034\025\taR$A\002tc2T!AH\020\002\013M\004\030M]6\013\005\001\n\023AB1qC\016DWMC\001#\003\ry'oZ\005\003Im\021q\001R1uCN,G\017\005\002\033M%\021qe\007\002\004%><\b\002C\025\001\005\003\005\013\021\002\026\002\025M\fHnQ8oi\026DH\017\005\002\033W%\021Af\007\002\r'B\f'o[*fgNLwN\034\005\t]\001\021\t\021)A\005_\005!A.\0338f!\t\001dG\004\0022i5\t!GC\0014\003\025\0318-\0317b\023\t)$'\001\004Qe\026$WMZ\005\003oa\022aa\025;sS:<'BA\0333\021!Q\004A!A!\002\023y\023!\003;bE2,g*Y7f\021!a\004A!A!\002\023y\023A\003>l\021>\034H\017]8si\")a\b\001C\001\0051A(\0338jiz\"b\001\021\"D\t\0263\005CA!\001\033\005\021\001\"\002\r>\001\004I\002\"B\025>\001\004Q\003\"\002\030>\001\004y\003\"\002\036>\001\004y\003\"\002\037>\001\004y\003\"\002%\001\t\003J\025a\001:v]R\t!\n\005\0022\027&\021AJ\r\002\005+:LG\017C\003O\001\021\005q*\001\bhKR\004F.\031;f\035Vl'-\032:\025\017)\003VkV-\\G\")\021+\024a\001%\006I\001.Z1e\023:$W\r\037\t\003cMK!\001\026\032\003\007%sG\017C\003W\033\002\007!+\001\004mK:<G\017\033\005\00616\003\raL\001\006S:\034HO\035\005\00656\003\rAU\001\002]\")A,\024a\001;\006!A.[:u!\rq\026MU\007\002?*\021\001\rE\001\005kRLG.\003\002c?\n!A*[:u\021\025!W\n1\001f\003\r\021Xm\035\t\004=\006|\003\"B4\001\t\003A\027aB4fiN\013Hn\r\013\004_%\f\b\"\0026g\001\004Y\027!\0029be\006l\007C\0017p\033\005i'B\0018\005\003\031\031w.\\7p]&\021\001/\034\002\n\023:\004X\017\036\"fC:DQA\0354A\002=\nQ\001^1cY\026DQ\001\036\001\005\002U\fqaZ3u'Fd'\007F\0020m^DQA[:A\002-DQA]:A\002=BQ!\037\001\005\002i\f!bZ3u)&lWmU9m)\ry3\020 \005\006Ub\004\ra\033\005\006eb\004\ra\f\005\006}\002!\ta`\001\007O\026$8+\0357\025\013=\n\t!a\001\t\013)l\b\031A6\t\013Il\b\031A\030\t\017\005\035\001\001\"\001\002\n\005\021r-\032;US6,7\013^1naN+7m\0348e)\021\tY!!\005\021\007E\ni!C\002\002\020I\022A\001T8oO\"9\0211CA\003\001\004y\023\001\002;j[\026Dq!a\006\001\t\003\tI\"A\005hKR$\025\r^3jIR\031q&a\007\t\017\005u\021Q\003a\001_\005QA/[7f'R\024\030N\\4\t\017\005\005\002\001\"\001\002$\005Yq-\032;US6,Gj\0348h)\021\tY!!\n\t\017\005u\021q\004a\001_!9\021\021\006\001\005\002\005-\022a\0037fm\026t7\017\033;fS:$RAUA\027\003cAq!a\f\002(\001\007q&A\001t\021\035\t\031$a\nA\002=\n\021\001\036")
/*     */ public class SparkEngineV3ForSimilarPlate implements Runnable
/*     */ {
/*     */   public void run()
/*     */   {
/*  21 */     String[] line_arr = this.line.split("\\|");
/*  22 */     final String job_id = line_arr[1];
/*  23 */     String[] line2 = line_arr[2].split(",");
/*  24 */     String model = null;
/*  25 */     String bInsert = null;
/*  26 */     String testSql = null;
/*  27 */     if (line_arr.length > 3) {
/*  28 */       model = line_arr[3];
/*  29 */       bInsert = line_arr[4];
/*  30 */       testSql = line_arr[5];
/*     */     }
/*  32 */     com.google.gson.Gson gson = new com.google.gson.Gson();
/*  33 */     java.lang.reflect.Type mapType = new com.google.gson.reflect.TypeToken() {}.getType();
/*  34 */     com.yisa.engine.common.InputBean map = (com.yisa.engine.common.InputBean)gson.fromJson(line_arr[2], mapType);
/*     */     
/*  36 */     long begintime = System.currentTimeMillis();
/*     */     
/*  38 */     String sql = getSql(map, this.tableName);
/*  39 */     String timeSql = getTimeSql(map, this.tableName);
/*     */     
/*  41 */     Predef..MODULE$.println(new StringBuilder().append("new自定义函数sql查询语句为:").append(sql).toString());
/*  42 */     Predef..MODULE$.println(new StringBuilder().append("new时间sql:").append(timeSql).toString());
/*  43 */     Dataset result = null;
/*  44 */     if ((timeSql == null) || (timeSql.isEmpty()))
/*     */     {
/*     */ 
/*     */ 
/*  48 */       result = this.sqlContext.sql(sql).limit(10000);
/*     */     } else {
/*  45 */       result = this.sqlContext.sql(sql).filter(timeSql).limit(10000);
/*     */     }
/*     */     
/*     */ 
/*     */ 
/*     */ 
/*  51 */     if (model == null) {
/*  52 */       final ObjectRef mapRes = ObjectRef.create((Map) Map..MODULE$.apply(scala.collection.immutable.Nil..MODULE$));
/*  53 */       Connection conn = com.yisa.engine.db.MySQLConnectManager..MODULE$.getConnet(this.com$yisa$engine$branchV3$SparkEngineV3ForSimilarPlate$$zkHostport);
/*  54 */       conn.setAutoCommit(false);
/*  55 */       String sqlProcess = "insert into xscpcb_progress(jobid,pronum,total) values(?,?,?)";
/*  56 */       String sql2 = "insert into xscpcb_result(j_id, s_id, y_id,count) values(?, ?, ?, ?)";
/*  57 */       final PreparedStatement pstmt = conn.prepareStatement(sql2);
/*  58 */       PreparedStatement pstmtProcess = conn.prepareStatement(sqlProcess);
/*     */       
/*  60 */       Predef..MODULE$.refArrayOps((Object[])result.collect()).foreach(new AbstractFunction1() { public static final long serialVersionUID = 0L;
/*     */         
/*  62 */         public final void apply(Row t) { if (!((Map)mapRes.elem).contains(t.apply(0).toString()))
/*     */           {
/*     */ 
/*  65 */             ((Map)mapRes.elem).put(t.apply(0).toString(), scala.runtime.BoxesRunTime.boxToInteger(1));
/*  66 */             pstmt.setString(1, job_id);
/*  67 */             pstmt.setString(2, t.apply(1).toString());
/*  68 */             pstmt.setString(3, any2stringadd..MODULE$.$plus$extension(Predef..MODULE$.any2stringadd(t.apply(2)), ""));
/*  69 */             pstmt.setString(4, t.apply(3).toString());
/*  70 */             pstmt.addBatch();
/*     */           }
/*     */           
/*     */         }
/*     */         
/*  75 */       });
/*  76 */       pstmtProcess.setString(1, job_id);
/*  77 */       pstmtProcess.setInt(2, 0);
/*  78 */       pstmtProcess.setInt(3, -1);
/*     */       
/*     */ 
/*  81 */       pstmtProcess.setString(1, job_id);
/*  82 */       pstmtProcess.setInt(2, 0);
/*  83 */       pstmtProcess.setInt(3, ((Map)mapRes.elem).size());(((Map)mapRes.elem).size() == 0 ? BoxedUnit.UNIT : 
/*  84 */         pstmt.executeBatch());
/*     */       
/*  86 */       pstmtProcess.addBatch();
/*  87 */       pstmtProcess.executeBatch();
/*     */       
/*  89 */       conn.commit();
/*  90 */       pstmt.close();
/*  91 */       pstmtProcess.close();
/*  92 */       conn.close();
/*     */       
/*  94 */       long endtime = System.currentTimeMillis();
/*  95 */       Predef..MODULE$.println(new StringBuilder().append("查询消耗时间:").append(scala.runtime.BoxesRunTime.boxToLong(endtime - begintime)).append("毫秒！").toString());
/*     */     }
/*  97 */     else if (model.equals("01")) {
/*  98 */       long beginTime = System.currentTimeMillis();
/*  99 */       String sql = getSql(map, this.tableName);
/* 100 */       String timeSql = getTimeSql(map, this.tableName);
/*     */       
/* 102 */       Predef..MODULE$.println(new StringBuilder().append("new自定义函数sql查询语句为:").append(sql).toString());
/* 103 */       Predef..MODULE$.println(new StringBuilder().append("new时间sql:").append(timeSql).toString());
/* 104 */       Dataset result = null;
/* 105 */       if ((timeSql == null) || (timeSql.isEmpty()))
/*     */       {
/*     */ 
/*     */ 
/* 109 */         result = this.sqlContext.sql(sql).limit(1000);
/*     */       } else {
/* 106 */         result = this.sqlContext.sql(sql).filter(timeSql).limit(1000);
/*     */       }
/*     */       
/*     */ 
/*     */ 
/*     */ 
/* 112 */       if (bInsert.equals("01")) {
/* 113 */         result.show(100);
/* 114 */       } else if (bInsert.equals("02"))
/*     */       {
/*     */ 
/* 117 */         result.foreachPartition(
/* 118 */           new AbstractFunction1()
/*     */           {
/*     */             public static final long serialVersionUID = 0L;
/*     */             
/*     */ 
/*     */ 
/*     */ 
/*     */ 
/*     */             public final void apply(Iterator<Row> data)
/*     */             {
/* 128 */               data.foreach(new AbstractFunction1() { public static final long serialVersionUID = 0L;
/*     */                 
/* 130 */                 public final void apply(Row t) { Predef..MODULE$.println(new StringBuilder().append("Record:").append(t.apply(1).toString()).toString());
/*     */ 
/*     */                 }
/*     */                 
/*     */ 
/*     */ 
/*     */ 
/*     */               });
/*     */ 
/*     */ 
/*     */             }
/*     */             
/*     */ 
/*     */ 
/*     */ 
/*     */           });
/*     */ 
/*     */ 
/*     */       }
/* 149 */       else if (bInsert.equals("03")) {
/* 150 */         final ObjectRef map = ObjectRef.create((Map) Map..MODULE$.apply(scala.collection.immutable.Nil..MODULE$));
/*     */         
/* 152 */         Connection conn = com.yisa.engine.db.MySQLConnectManager..MODULE$.getConnet(this.com$yisa$engine$branchV3$SparkEngineV3ForSimilarPlate$$zkHostport);
/* 153 */         conn.setAutoCommit(false);
/* 154 */         String sql = "insert into xscpcb_result(j_id, s_id, y_id,count) values(?, ?, ?, ?)";
/* 155 */         final PreparedStatement pstmt = conn.prepareStatement(sql);
/* 156 */         Predef..MODULE$.refArrayOps((Object[])result.collect()).foreach(new AbstractFunction1() { public static final long serialVersionUID = 0L;
/*     */           
/* 158 */           public final void apply(Row t) { if (!((Map)map.elem).contains(t.apply(0).toString()))
/*     */             {
/*     */ 
/* 161 */               ((Map)map.elem).put(t.apply(0).toString(), scala.runtime.BoxesRunTime.boxToInteger(1));
/* 162 */               pstmt.setString(1, job_id);
/* 163 */               pstmt.setString(2, t.apply(1).toString());
/* 164 */               pstmt.setString(3, any2stringadd..MODULE$.$plus$extension(Predef..MODULE$.any2stringadd(t.apply(2)), ""));
/* 165 */               pstmt.setString(4, t.apply(3).toString());
/* 166 */               pstmt.addBatch();
/*     */             }
/*     */           }
/* 169 */         });
/* 170 */         pstmt.executeBatch();
/* 171 */         conn.commit();
/* 172 */         pstmt.close();
/* 173 */         conn.close();
/*     */       }
/*     */       
/* 176 */       long endTime = System.currentTimeMillis();
/* 177 */       Predef..MODULE$.println(new StringBuilder().append("执行自定义函数sql语句完成,消耗时间:").append(scala.runtime.BoxesRunTime.boxToLong(endTime - beginTime)).append("毫秒!").toString());
/* 178 */     } else if (model.equals("02"))
/*     */     {
/* 180 */       long begTime2 = System.currentTimeMillis();
/* 181 */       Predef..MODULE$.println(new StringBuilder().append("开始执行第二句:").append(scala.runtime.BoxesRunTime.boxToLong(begTime2)).toString());
/* 182 */       String sql2 = getSql2(map, this.tableName);
/* 183 */       Predef..MODULE$.println(new StringBuilder().append("sql2:").append(sql2).toString());
/* 184 */       Dataset res2 = this.sqlContext.sql(sql2);
/* 185 */       if (bInsert.equals("01")) {
/* 186 */         res2.show(100);
/* 187 */       } else if (bInsert.equals("02"))
/*     */       {
/*     */ 
/* 190 */         res2.foreachPartition(new AbstractFunction1() { public static final long serialVersionUID = 0L;
/*     */           
/* 192 */           public final void apply(Iterator<Row> data) { Connection conn = com.yisa.engine.db.MySQLConnectManager..MODULE$.getConnet(SparkEngineV3ForSimilarPlate.this.com$yisa$engine$branchV3$SparkEngineV3ForSimilarPlate$$zkHostport);
/* 193 */             conn.setAutoCommit(false);
/*     */             
/* 195 */             String sql = "insert into xscpcb_result(j_id, s_id,y_id,count) values(?, ?, ?, ?)";
/* 196 */             final PreparedStatement pstmt = conn.prepareStatement(sql);
/*     */             
/* 198 */             data.foreach(new AbstractFunction1() {
/*     */               public static final long serialVersionUID = 0L;
/*     */               
/* 201 */               public final void apply(Row t) { pstmt.setString(1, SparkEngineV3ForSimilarPlate..anonfun.run.4.this.job_id$1);
/* 202 */                 pstmt.setString(2, t.apply(1).toString());
/*     */                 
/* 204 */                 pstmt.setString(3, any2stringadd..MODULE$.$plus$extension(Predef..MODULE$.any2stringadd(t.apply(2)), ""));
/* 205 */                 pstmt.setString(4, t.apply(3).toString());
/* 206 */                 pstmt.addBatch();
/*     */               }
/* 208 */             });
/* 209 */             int[] test = pstmt.executeBatch();
/* 210 */             conn.commit();
/* 211 */             pstmt.close();
/* 212 */             conn.close();
/*     */           }
/*     */         });
/*     */       }
/*     */       
/*     */ 
/*     */ 
/* 219 */       long endTime2 = System.currentTimeMillis();
/* 220 */       Predef..MODULE$.println(new StringBuilder().append("执行第二遍完成:").append(scala.runtime.BoxesRunTime.boxToLong(endTime2 - begTime2)).append("毫秒").toString());
/* 221 */     } else if (model.equals("03"))
/*     */     {
/* 223 */       long begTime2 = System.currentTimeMillis();
/* 224 */       Predef..MODULE$.println(new StringBuilder().append("开始执行第三个语句:").append(scala.runtime.BoxesRunTime.boxToLong(begTime2)).toString());
/* 225 */       String sql2 = getSql3(map, this.tableName);
/* 226 */       Predef..MODULE$.println(new StringBuilder().append("new sql3:").append(sql2).toString());
/* 227 */       Dataset res2 = this.sqlContext.sql(sql2);
/* 228 */       if (bInsert.equals("01")) {
/* 229 */         res2.show(100);
/* 230 */       } else if (bInsert.equals("02"))
/*     */       {
/*     */ 
/* 233 */         res2.foreachPartition(new AbstractFunction1() { public static final long serialVersionUID = 0L;
/*     */           
/* 235 */           public final void apply(Iterator<Row> rdd) { rdd.foreach(new AbstractFunction1() {
/* 236 */               public final void apply(Row line) { Predef..MODULE$.println(line.toString()); }
/*     */             }); }
/*     */         });
/*     */       }
/*     */       
/*     */ 
/*     */ 
/*     */ 
/* 244 */       long endTime2 = System.currentTimeMillis();
/* 245 */       Predef..MODULE$.println(new StringBuilder().append("执行第三遍完成:").append(scala.runtime.BoxesRunTime.boxToLong(endTime2 - begTime2)).append("毫秒").toString());
/*     */     }
/* 247 */     else if (model.equals("07"))
/*     */     {
/* 249 */       long begTime2 = System.currentTimeMillis();
/* 250 */       Predef..MODULE$.println(new StringBuilder().append("开始执行第7个语句:").append(scala.runtime.BoxesRunTime.boxToLong(begTime2)).toString());
/*     */       
/* 252 */       Predef..MODULE$.println(new StringBuilder().append("sql:").append(testSql).toString());
/* 253 */       Dataset res2 = this.sqlContext.sql(testSql);
/* 254 */       if (bInsert.equals("01")) {
/* 255 */         res2.show(100);
/* 256 */       } else if (bInsert.equals("02"))
/*     */       {
/* 258 */         res2.foreachPartition(
/* 259 */           new AbstractFunction1() { public static final long serialVersionUID = 0L;
/*     */             
/* 261 */             public final void apply(Iterator<Row> data) { long begConnect = System.currentTimeMillis();
/* 262 */               Connection conn = com.yisa.engine.db.MySQLConnectManager..MODULE$.getConnet(SparkEngineV3ForSimilarPlate.this.com$yisa$engine$branchV3$SparkEngineV3ForSimilarPlate$$zkHostport);
/* 263 */               conn.setAutoCommit(false);
/*     */               
/* 265 */               String sql = "insert into xscpcb_result(j_id, s_id, y_id,count) values(?, ?, ?, ?)";
/* 266 */               final PreparedStatement pstmt = conn.prepareStatement(sql);
/* 267 */               long endConnect = System.currentTimeMillis();
/* 268 */               Predef..MODULE$.println(new StringBuilder().append("获取连接消耗时间:").append(scala.runtime.BoxesRunTime.boxToLong(endConnect - begConnect)).append("毫秒").toString());
/* 269 */               data.foreach(new AbstractFunction1() { public static final long serialVersionUID = 0L;
/*     */                 
/* 271 */                 public final void apply(Row t) { Predef..MODULE$.println(new StringBuilder().append("Record:").append(t.apply(1).toString()).toString());
/* 272 */                   pstmt.setString(1, SparkEngineV3ForSimilarPlate..anonfun.run.6.this.job_id$1);
/* 273 */                   pstmt.setString(2, t.apply(1).toString());
/* 274 */                   pstmt.setString(3, any2stringadd..MODULE$.$plus$extension(Predef..MODULE$.any2stringadd(t.apply(2)), ""));
/* 275 */                   pstmt.setString(4, t.apply(3).toString());
/* 276 */                   pstmt.addBatch();
/*     */                 }
/* 278 */               });
/* 279 */               int[] test = pstmt.executeBatch();
/* 280 */               long end2Connect = System.currentTimeMillis();
/* 281 */               Predef..MODULE$.println(new StringBuilder().append("入partition数据结束:").append(scala.runtime.BoxesRunTime.boxToLong(end2Connect - endConnect)).append("毫秒").toString());
/* 282 */               conn.commit();
/* 283 */               pstmt.close();
/* 284 */               conn.close();
/* 285 */               long end3Connect = System.currentTimeMillis();
/* 286 */               Predef..MODULE$.println(new StringBuilder().append("最后提交消耗:").append(scala.runtime.BoxesRunTime.boxToLong(end3Connect - end2Connect)).append("毫秒").toString());
/*     */             }
/*     */           });
/* 289 */       } else if (bInsert.equals("03")) {
/* 290 */         res2.foreachPartition(new AbstractFunction1() { public static final long serialVersionUID = 0L;
/*     */           
/* 292 */           public final void apply(Iterator<Row> rdd) { Predef..MODULE$.println("---------------------");
/* 293 */             rdd.foreach(new AbstractFunction1() {
/* 294 */               public final void apply(Row line) { Predef..MODULE$.println(line.toString()); }
/*     */             });
/*     */           }
/*     */         });
/* 298 */       } else if (bInsert.equals("04")) {
/* 299 */         Predef..MODULE$.refArrayOps((Object[])res2.collect()).foreach(new AbstractFunction1() { public final void apply(Row x) { Predef..MODULE$.println(x.toString()); }
/*     */         }); } else if (bInsert.equals("05"))
/*     */       {
/* 302 */         final ObjectRef map = ObjectRef.create((Map) Map..MODULE$.apply(scala.collection.immutable.Nil..MODULE$));
/* 303 */         Connection conn = com.yisa.engine.db.MySQLConnectManager..MODULE$.getConnet(this.com$yisa$engine$branchV3$SparkEngineV3ForSimilarPlate$$zkHostport);
/* 304 */         conn.setAutoCommit(false);
/* 305 */         String sql = "insert into xscpcb_result(j_id, s_id, y_id,count) values(?, ?, ?, ?)";
/* 306 */         final PreparedStatement pstmt = conn.prepareStatement(sql);
/* 307 */         Predef..MODULE$.refArrayOps((Object[])res2.collect()).foreach(new AbstractFunction1() { public static final long serialVersionUID = 0L;
/*     */           
/* 309 */           public final void apply(Row t) { if (!((Map)map.elem).contains(t.apply(0).toString()))
/*     */             {
/*     */ 
/* 312 */               ((Map)map.elem).put(t.apply(0).toString(), scala.runtime.BoxesRunTime.boxToInteger(1));
/* 313 */               pstmt.setString(1, job_id);
/* 314 */               pstmt.setString(2, t.apply(1).toString());
/* 315 */               pstmt.setString(3, any2stringadd..MODULE$.$plus$extension(Predef..MODULE$.any2stringadd(t.apply(2)), ""));
/* 316 */               pstmt.setString(4, t.apply(3).toString());
/* 317 */               pstmt.addBatch();
/*     */             }
/*     */             
/*     */           }
/* 321 */         });
/* 322 */         pstmt.executeBatch();
/* 323 */         conn.commit();
/* 324 */         pstmt.close();
/* 325 */         conn.close();
/*     */       }
/* 327 */       long endTime2 = System.currentTimeMillis();
/* 328 */       Predef..MODULE$.println(new StringBuilder().append("执行第7个语句完成:").append(scala.runtime.BoxesRunTime.boxToLong(endTime2 - begTime2)).append("毫秒").toString());
/*     */     }
/*     */   }
/*     */   
/*     */ 
/*     */ 
/*     */ 
/*     */ 
/*     */ 
/*     */ 
/*     */ 
/*     */ 
/*     */   public static final long serialVersionUID = 0L;
/*     */   
/*     */ 
/*     */ 
/*     */ 
/*     */ 
/*     */ 
/*     */ 
/*     */ 
/*     */   public static final long serialVersionUID = 0L;
/*     */   
/*     */ 
/*     */ 
/*     */ 
/*     */ 
/*     */ 
/*     */ 
/*     */ 
/*     */   public static final long serialVersionUID = 0L;
/*     */   
/*     */ 
/*     */ 
/*     */ 
/*     */ 
/*     */ 
/*     */ 
/*     */ 
/*     */   public void getPlateNumber(int headIndex, final int length, final String instr, final int n, final java.util.List<Object> list, final java.util.List<String> res)
/*     */   {
/* 369 */     final Object localObject = new Object();
/*     */     try {
/* 371 */       final ObjectRef list2 = ObjectRef.create(new java.util.ArrayList());
/* 372 */       ((java.util.ArrayList)list2.elem).addAll(list);
/* 373 */       int len = instr.length() + length - n;scala.runtime.RichInt..MODULE$
/* 374 */         .until$extension0(Predef..MODULE$.intWrapper(headIndex), len).foreach(new AbstractFunction1.mcZI.sp() { public final boolean apply(int i) { return apply$mcZI$sp(i); }
/*     */           
/* 376 */           public boolean apply$mcZI$sp(int i) { if (length <= n)
/*     */             {
/*     */ 
/* 379 */               list.add(scala.runtime.BoxesRunTime.boxToInteger(i));
/*     */               
/* 381 */               SparkEngineV3ForSimilarPlate.this.getPlateNumber(i + 1, length + 1, instr, n, list, res);
/*     */               
/* 383 */               final ObjectRef array = ObjectRef.create(instr.toCharArray());
/*     */               
/*     */ 
/* 386 */               System.out.println(list.toString());
/* 387 */               scala.runtime.RichInt..MODULE$
/*     */               
/* 389 */                 .until$extension0(Predef..MODULE$.intWrapper(0), list.size()).foreach$mVc$sp(new AbstractFunction1.mcVI.sp() { public final void apply(int t) { apply$mcVI$sp(t); }
/* 390 */                   public void apply$mcVI$sp(int t) { ((char[])array.elem)[scala.runtime.BoxesRunTime.unboxToInt(SparkEngineV3ForSimilarPlate..anonfun.getPlateNumber.1.this.list$1.get(t))] = 95;
/*     */                   }
/* 392 */                 });
/* 393 */               System.out.println(new StringBuilder().append("====").append(String.valueOf((char[])array.elem)).toString());
/*     */               
/*     */ 
/*     */ 
/*     */ 
/*     */ 
/*     */ 
/*     */ 
/*     */ 
/* 402 */               list.clear();
/* 403 */               return list.addAll((java.util.ArrayList)list2.elem);
/*     */             }
/* 398 */             throw new scala.runtime.NonLocalReturnControl.mcV.sp(localObject, BoxedUnit.UNIT);
/*     */           }
/*     */         });
/*     */     }
/*     */     catch (scala.runtime.NonLocalReturnControl localNonLocalReturnControl) {}
/* 370 */     if (localNonLocalReturnControl.key() == localObject) { localNonLocalReturnControl.value$mcV$sp();return; } throw localNonLocalReturnControl;
/*     */   }
/*     */   
/*     */   public static final long serialVersionUID = 0L;
/*     */   public static final long serialVersionUID = 0L;
/*     */   /* Error */
/*     */   public String getSql3(com.yisa.engine.common.InputBean param, String table)
/*     */   {
/*     */     // Byte code:
/*     */     //   0: aload_1
/*     */     //   1: invokevirtual 400	com/yisa/engine/common/InputBean:plateNumber	()Ljava/lang/String;
/*     */     //   4: astore_3
/*     */     //   5: aload_1
/*     */     //   6: invokevirtual 403	com/yisa/engine/common/InputBean:differ	()I
/*     */     //   9: istore 4
/*     */     //   11: lconst_0
/*     */     //   12: lstore 5
/*     */     //   14: aload_1
/*     */     //   15: invokevirtual 406	com/yisa/engine/common/InputBean:startTime	()Ljava/lang/String;
/*     */     //   18: ifnull +13 -> 31
/*     */     //   21: aload_0
/*     */     //   22: aload_1
/*     */     //   23: invokevirtual 406	com/yisa/engine/common/InputBean:startTime	()Ljava/lang/String;
/*     */     //   26: invokevirtual 410	com/yisa/engine/branchV3/SparkEngineV3ForSimilarPlate:getTimeStampSecond	(Ljava/lang/String;)J
/*     */     //   29: lstore 5
/*     */     //   31: lconst_0
/*     */     //   32: lstore 7
/*     */     //   34: aload_1
/*     */     //   35: invokevirtual 412	com/yisa/engine/common/InputBean:endTime	()Ljava/lang/String;
/*     */     //   38: ifnull +13 -> 51
/*     */     //   41: aload_0
/*     */     //   42: aload_1
/*     */     //   43: invokevirtual 412	com/yisa/engine/common/InputBean:endTime	()Ljava/lang/String;
/*     */     //   46: invokevirtual 410	com/yisa/engine/branchV3/SparkEngineV3ForSimilarPlate:getTimeStampSecond	(Ljava/lang/String;)J
/*     */     //   49: lstore 7
/*     */     //   51: aload_1
/*     */     //   52: invokevirtual 415	com/yisa/engine/common/InputBean:carBrand	()Ljava/lang/String;
/*     */     //   55: astore 9
/*     */     //   57: aload_1
/*     */     //   58: invokevirtual 419	com/yisa/engine/common/InputBean:carModel	()[Ljava/lang/String;
/*     */     //   61: astore 10
/*     */     //   63: aload_1
/*     */     //   64: invokevirtual 422	com/yisa/engine/common/InputBean:carYear	()[Ljava/lang/String;
/*     */     //   67: astore 11
/*     */     //   69: aload_1
/*     */     //   70: invokevirtual 425	com/yisa/engine/common/InputBean:locationId	()[Ljava/lang/String;
/*     */     //   73: astore 12
/*     */     //   75: new 427	java/lang/StringBuffer
/*     */     //   78: dup
/*     */     //   79: invokespecial 428	java/lang/StringBuffer:<init>	()V
/*     */     //   82: astore 13
/*     */     //   84: aload 13
/*     */     //   86: new 73	scala/collection/mutable/StringBuilder
/*     */     //   89: dup
/*     */     //   90: invokespecial 74	scala/collection/mutable/StringBuilder:<init>	()V
/*     */     //   93: ldc_w 430
/*     */     //   96: invokevirtual 80	scala/collection/mutable/StringBuilder:append	(Ljava/lang/Object;)Lscala/collection/mutable/StringBuilder;
/*     */     //   99: aload_3
/*     */     //   100: invokevirtual 80	scala/collection/mutable/StringBuilder:append	(Ljava/lang/Object;)Lscala/collection/mutable/StringBuilder;
/*     */     //   103: ldc_w 432
/*     */     //   106: invokevirtual 80	scala/collection/mutable/StringBuilder:append	(Ljava/lang/Object;)Lscala/collection/mutable/StringBuilder;
/*     */     //   109: aload_2
/*     */     //   110: invokevirtual 80	scala/collection/mutable/StringBuilder:append	(Ljava/lang/Object;)Lscala/collection/mutable/StringBuilder;
/*     */     //   113: invokevirtual 84	scala/collection/mutable/StringBuilder:toString	()Ljava/lang/String;
/*     */     //   116: invokevirtual 435	java/lang/StringBuffer:append	(Ljava/lang/String;)Ljava/lang/StringBuffer;
/*     */     //   119: pop
/*     */     //   120: aload 13
/*     */     //   122: ldc_w 437
/*     */     //   125: invokevirtual 435	java/lang/StringBuffer:append	(Ljava/lang/String;)Ljava/lang/StringBuffer;
/*     */     //   128: pop
/*     */     //   129: aload_1
/*     */     //   130: invokevirtual 422	com/yisa/engine/common/InputBean:carYear	()[Ljava/lang/String;
/*     */     //   133: aconst_null
/*     */     //   134: if_acmpeq +120 -> 254
/*     */     //   137: aload_1
/*     */     //   138: invokevirtual 422	com/yisa/engine/common/InputBean:carYear	()[Ljava/lang/String;
/*     */     //   141: iconst_0
/*     */     //   142: aaload
/*     */     //   143: ldc_w 439
/*     */     //   146: astore 14
/*     */     //   148: dup
/*     */     //   149: ifnonnull +12 -> 161
/*     */     //   152: pop
/*     */     //   153: aload 14
/*     */     //   155: ifnull +99 -> 254
/*     */     //   158: goto +11 -> 169
/*     */     //   161: aload 14
/*     */     //   163: invokevirtual 440	java/lang/Object:equals	(Ljava/lang/Object;)Z
/*     */     //   166: ifne +88 -> 254
/*     */     //   169: aload_1
/*     */     //   170: invokevirtual 422	com/yisa/engine/common/InputBean:carYear	()[Ljava/lang/String;
/*     */     //   173: iconst_0
/*     */     //   174: aaload
/*     */     //   175: ldc_w 442
/*     */     //   178: astore 15
/*     */     //   180: dup
/*     */     //   181: ifnonnull +12 -> 193
/*     */     //   184: pop
/*     */     //   185: aload 15
/*     */     //   187: ifnull +67 -> 254
/*     */     //   190: goto +11 -> 201
/*     */     //   193: aload 15
/*     */     //   195: invokevirtual 440	java/lang/Object:equals	(Ljava/lang/Object;)Z
/*     */     //   198: ifne +56 -> 254
/*     */     //   201: getstatic 71	scala/Predef$:MODULE$	Lscala/Predef$;
/*     */     //   204: aload_1
/*     */     //   205: invokevirtual 422	com/yisa/engine/common/InputBean:carYear	()[Ljava/lang/String;
/*     */     //   208: checkcast 164	[Ljava/lang/Object;
/*     */     //   211: invokevirtual 168	scala/Predef$:refArrayOps	([Ljava/lang/Object;)Lscala/collection/mutable/ArrayOps;
/*     */     //   214: new 444	com/yisa/engine/branchV3/SparkEngineV3ForSimilarPlate$$anonfun$1
/*     */     //   217: dup
/*     */     //   218: aload_0
/*     */     //   219: invokespecial 445	com/yisa/engine/branchV3/SparkEngineV3ForSimilarPlate$$anonfun$1:<init>	(Lcom/yisa/engine/branchV3/SparkEngineV3ForSimilarPlate;)V
/*     */     //   222: invokeinterface 449 2 0
/*     */     //   227: checkcast 24	java/lang/String
/*     */     //   230: astore 16
/*     */     //   232: aload 13
/*     */     //   234: ldc_w 451
/*     */     //   237: invokevirtual 435	java/lang/StringBuffer:append	(Ljava/lang/String;)Ljava/lang/StringBuffer;
/*     */     //   240: aload 16
/*     */     //   242: invokevirtual 435	java/lang/StringBuffer:append	(Ljava/lang/String;)Ljava/lang/StringBuffer;
/*     */     //   245: ldc_w 453
/*     */     //   248: invokevirtual 435	java/lang/StringBuffer:append	(Ljava/lang/String;)Ljava/lang/StringBuffer;
/*     */     //   251: goto +6 -> 257
/*     */     //   254: getstatic 203	scala/runtime/BoxedUnit:UNIT	Lscala/runtime/BoxedUnit;
/*     */     //   257: pop
/*     */     //   258: lload 5
/*     */     //   260: lconst_0
/*     */     //   261: lcmp
/*     */     //   262: ifeq +25 -> 287
/*     */     //   265: aload 13
/*     */     //   267: ldc_w 455
/*     */     //   270: invokevirtual 435	java/lang/StringBuffer:append	(Ljava/lang/String;)Ljava/lang/StringBuffer;
/*     */     //   273: aload_0
/*     */     //   274: aload_1
/*     */     //   275: invokevirtual 406	com/yisa/engine/common/InputBean:startTime	()Ljava/lang/String;
/*     */     //   278: invokevirtual 459	com/yisa/engine/branchV3/SparkEngineV3ForSimilarPlate:getDateid	(Ljava/lang/String;)Ljava/lang/String;
/*     */     //   281: invokevirtual 435	java/lang/StringBuffer:append	(Ljava/lang/String;)Ljava/lang/StringBuffer;
/*     */     //   284: goto +6 -> 290
/*     */     //   287: getstatic 203	scala/runtime/BoxedUnit:UNIT	Lscala/runtime/BoxedUnit;
/*     */     //   290: pop
/*     */     //   291: lload 7
/*     */     //   293: lconst_0
/*     */     //   294: lcmp
/*     */     //   295: ifeq +25 -> 320
/*     */     //   298: aload 13
/*     */     //   300: ldc_w 461
/*     */     //   303: invokevirtual 435	java/lang/StringBuffer:append	(Ljava/lang/String;)Ljava/lang/StringBuffer;
/*     */     //   306: aload_0
/*     */     //   307: aload_1
/*     */     //   308: invokevirtual 412	com/yisa/engine/common/InputBean:endTime	()Ljava/lang/String;
/*     */     //   311: invokevirtual 459	com/yisa/engine/branchV3/SparkEngineV3ForSimilarPlate:getDateid	(Ljava/lang/String;)Ljava/lang/String;
/*     */     //   314: invokevirtual 435	java/lang/StringBuffer:append	(Ljava/lang/String;)Ljava/lang/StringBuffer;
/*     */     //   317: goto +6 -> 323
/*     */     //   320: getstatic 203	scala/runtime/BoxedUnit:UNIT	Lscala/runtime/BoxedUnit;
/*     */     //   323: pop
/*     */     //   324: lload 5
/*     */     //   326: lconst_0
/*     */     //   327: lcmp
/*     */     //   328: ifeq +19 -> 347
/*     */     //   331: aload 13
/*     */     //   333: ldc_w 463
/*     */     //   336: invokevirtual 435	java/lang/StringBuffer:append	(Ljava/lang/String;)Ljava/lang/StringBuffer;
/*     */     //   339: lload 5
/*     */     //   341: invokevirtual 466	java/lang/StringBuffer:append	(J)Ljava/lang/StringBuffer;
/*     */     //   344: goto +6 -> 350
/*     */     //   347: getstatic 203	scala/runtime/BoxedUnit:UNIT	Lscala/runtime/BoxedUnit;
/*     */     //   350: pop
/*     */     //   351: lload 7
/*     */     //   353: lconst_0
/*     */     //   354: lcmp
/*     */     //   355: ifeq +19 -> 374
/*     */     //   358: aload 13
/*     */     //   360: ldc_w 468
/*     */     //   363: invokevirtual 435	java/lang/StringBuffer:append	(Ljava/lang/String;)Ljava/lang/StringBuffer;
/*     */     //   366: lload 7
/*     */     //   368: invokevirtual 466	java/lang/StringBuffer:append	(J)Ljava/lang/StringBuffer;
/*     */     //   371: goto +6 -> 377
/*     */     //   374: getstatic 203	scala/runtime/BoxedUnit:UNIT	Lscala/runtime/BoxedUnit;
/*     */     //   377: pop
/*     */     //   378: aload 10
/*     */     //   380: aconst_null
/*     */     //   381: if_acmpeq +93 -> 474
/*     */     //   384: aload 10
/*     */     //   386: arraylength
/*     */     //   387: iconst_0
/*     */     //   388: if_icmple +86 -> 474
/*     */     //   391: aload_1
/*     */     //   392: invokevirtual 419	com/yisa/engine/common/InputBean:carModel	()[Ljava/lang/String;
/*     */     //   395: iconst_0
/*     */     //   396: aaload
/*     */     //   397: ldc_w 442
/*     */     //   400: astore 17
/*     */     //   402: dup
/*     */     //   403: ifnonnull +12 -> 415
/*     */     //   406: pop
/*     */     //   407: aload 17
/*     */     //   409: ifnull +65 -> 474
/*     */     //   412: goto +11 -> 423
/*     */     //   415: aload 17
/*     */     //   417: invokevirtual 440	java/lang/Object:equals	(Ljava/lang/Object;)Z
/*     */     //   420: ifne +54 -> 474
/*     */     //   423: getstatic 71	scala/Predef$:MODULE$	Lscala/Predef$;
/*     */     //   426: aload 10
/*     */     //   428: checkcast 164	[Ljava/lang/Object;
/*     */     //   431: invokevirtual 168	scala/Predef$:refArrayOps	([Ljava/lang/Object;)Lscala/collection/mutable/ArrayOps;
/*     */     //   434: new 470	com/yisa/engine/branchV3/SparkEngineV3ForSimilarPlate$$anonfun$2
/*     */     //   437: dup
/*     */     //   438: aload_0
/*     */     //   439: invokespecial 471	com/yisa/engine/branchV3/SparkEngineV3ForSimilarPlate$$anonfun$2:<init>	(Lcom/yisa/engine/branchV3/SparkEngineV3ForSimilarPlate;)V
/*     */     //   442: invokeinterface 449 2 0
/*     */     //   447: checkcast 24	java/lang/String
/*     */     //   450: astore 18
/*     */     //   452: aload 13
/*     */     //   454: ldc_w 473
/*     */     //   457: invokevirtual 435	java/lang/StringBuffer:append	(Ljava/lang/String;)Ljava/lang/StringBuffer;
/*     */     //   460: aload 18
/*     */     //   462: invokevirtual 435	java/lang/StringBuffer:append	(Ljava/lang/String;)Ljava/lang/StringBuffer;
/*     */     //   465: ldc_w 453
/*     */     //   468: invokevirtual 435	java/lang/StringBuffer:append	(Ljava/lang/String;)Ljava/lang/StringBuffer;
/*     */     //   471: goto +6 -> 477
/*     */     //   474: getstatic 203	scala/runtime/BoxedUnit:UNIT	Lscala/runtime/BoxedUnit;
/*     */     //   477: pop
/*     */     //   478: aload 9
/*     */     //   480: ifnull +59 -> 539
/*     */     //   483: aload 9
/*     */     //   485: ldc_w 439
/*     */     //   488: astore 19
/*     */     //   490: dup
/*     */     //   491: ifnonnull +12 -> 503
/*     */     //   494: pop
/*     */     //   495: aload 19
/*     */     //   497: ifnull +42 -> 539
/*     */     //   500: goto +11 -> 511
/*     */     //   503: aload 19
/*     */     //   505: invokevirtual 440	java/lang/Object:equals	(Ljava/lang/Object;)Z
/*     */     //   508: ifne +31 -> 539
/*     */     //   511: aload 9
/*     */     //   513: ldc_w 442
/*     */     //   516: astore 20
/*     */     //   518: dup
/*     */     //   519: ifnonnull +12 -> 531
/*     */     //   522: pop
/*     */     //   523: aload 20
/*     */     //   525: ifnull +14 -> 539
/*     */     //   528: goto +17 -> 545
/*     */     //   531: aload 20
/*     */     //   533: invokevirtual 440	java/lang/Object:equals	(Ljava/lang/Object;)Z
/*     */     //   536: ifeq +9 -> 545
/*     */     //   539: getstatic 203	scala/runtime/BoxedUnit:UNIT	Lscala/runtime/BoxedUnit;
/*     */     //   542: goto +16 -> 558
/*     */     //   545: aload 13
/*     */     //   547: ldc_w 475
/*     */     //   550: invokevirtual 435	java/lang/StringBuffer:append	(Ljava/lang/String;)Ljava/lang/StringBuffer;
/*     */     //   553: aload 9
/*     */     //   555: invokevirtual 435	java/lang/StringBuffer:append	(Ljava/lang/String;)Ljava/lang/StringBuffer;
/*     */     //   558: pop
/*     */     //   559: aload 13
/*     */     //   561: new 73	scala/collection/mutable/StringBuilder
/*     */     //   564: dup
/*     */     //   565: invokespecial 74	scala/collection/mutable/StringBuilder:<init>	()V
/*     */     //   568: ldc_w 477
/*     */     //   571: invokevirtual 80	scala/collection/mutable/StringBuilder:append	(Ljava/lang/Object;)Lscala/collection/mutable/StringBuilder;
/*     */     //   574: iload 4
/*     */     //   576: invokestatic 481	scala/runtime/BoxesRunTime:boxToInteger	(I)Ljava/lang/Integer;
/*     */     //   579: invokevirtual 80	scala/collection/mutable/StringBuilder:append	(Ljava/lang/Object;)Lscala/collection/mutable/StringBuilder;
/*     */     //   582: ldc_w 483
/*     */     //   585: invokevirtual 80	scala/collection/mutable/StringBuilder:append	(Ljava/lang/Object;)Lscala/collection/mutable/StringBuilder;
/*     */     //   588: invokevirtual 84	scala/collection/mutable/StringBuilder:toString	()Ljava/lang/String;
/*     */     //   591: invokevirtual 435	java/lang/StringBuffer:append	(Ljava/lang/String;)Ljava/lang/StringBuffer;
/*     */     //   594: pop
/*     */     //   595: aload 13
/*     */     //   597: invokevirtual 484	java/lang/StringBuffer:toString	()Ljava/lang/String;
/*     */     //   600: areturn
/*     */     // Line number table:
/*     */     //   Java source line #410	-> byte code offset #0
/*     */     //   Java source line #411	-> byte code offset #5
/*     */     //   Java source line #412	-> byte code offset #11
/*     */     //   Java source line #413	-> byte code offset #14
/*     */     //   Java source line #415	-> byte code offset #21
/*     */     //   Java source line #417	-> byte code offset #31
/*     */     //   Java source line #418	-> byte code offset #34
/*     */     //   Java source line #420	-> byte code offset #41
/*     */     //   Java source line #423	-> byte code offset #51
/*     */     //   Java source line #424	-> byte code offset #57
/*     */     //   Java source line #425	-> byte code offset #63
/*     */     //   Java source line #426	-> byte code offset #69
/*     */     //   Java source line #427	-> byte code offset #75
/*     */     //   Java source line #431	-> byte code offset #84
/*     */     //   Java source line #432	-> byte code offset #120
/*     */     //   Java source line #435	-> byte code offset #129
/*     */     //   Java source line #436	-> byte code offset #201
/*     */     //   Java source line #437	-> byte code offset #232
/*     */     //   Java source line #435	-> byte code offset #254
/*     */     //   Java source line #440	-> byte code offset #258
/*     */     //   Java source line #441	-> byte code offset #265
/*     */     //   Java source line #440	-> byte code offset #287
/*     */     //   Java source line #444	-> byte code offset #291
/*     */     //   Java source line #445	-> byte code offset #298
/*     */     //   Java source line #444	-> byte code offset #320
/*     */     //   Java source line #448	-> byte code offset #324
/*     */     //   Java source line #449	-> byte code offset #331
/*     */     //   Java source line #448	-> byte code offset #347
/*     */     //   Java source line #452	-> byte code offset #351
/*     */     //   Java source line #453	-> byte code offset #358
/*     */     //   Java source line #452	-> byte code offset #374
/*     */     //   Java source line #464	-> byte code offset #378
/*     */     //   Java source line #465	-> byte code offset #423
/*     */     //   Java source line #466	-> byte code offset #452
/*     */     //   Java source line #464	-> byte code offset #474
/*     */     //   Java source line #469	-> byte code offset #478
/*     */     //   Java source line #470	-> byte code offset #545
/*     */     //   Java source line #469	-> byte code offset #558
/*     */     //   Java source line #475	-> byte code offset #559
/*     */     //   Java source line #476	-> byte code offset #595
/*     */     // Local variable table:
/*     */     //   start	length	slot	name	signature
/*     */     //   0	601	0	this	SparkEngineV3ForSimilarPlate
/*     */     //   0	601	1	param	com.yisa.engine.common.InputBean
/*     */     //   0	601	2	table	String
/*     */     //   5	595	3	plateNumber	String
/*     */     //   11	589	4	differ	int
/*     */     //   14	586	5	startTime	long
/*     */     //   34	566	7	endTime	long
/*     */     //   57	543	9	brand	String
/*     */     //   63	537	10	model	String[]
/*     */     //   69	531	11	yearId	String[]
/*     */     //   75	525	12	location	String[]
/*     */     //   84	516	13	sql	StringBuffer
/*     */     //   232	19	16	m	String
/*     */     //   452	19	18	m	String
/*     */   }
/*     */   
/*     */   /* Error */
/*     */   public String getSql2(com.yisa.engine.common.InputBean param, String table)
/*     */   {
/*     */     // Byte code:
/*     */     //   0: aload_1
/*     */     //   1: invokevirtual 400	com/yisa/engine/common/InputBean:plateNumber	()Ljava/lang/String;
/*     */     //   4: astore_3
/*     */     //   5: aload_1
/*     */     //   6: invokevirtual 403	com/yisa/engine/common/InputBean:differ	()I
/*     */     //   9: istore 4
/*     */     //   11: lconst_0
/*     */     //   12: lstore 5
/*     */     //   14: lconst_0
/*     */     //   15: lstore 7
/*     */     //   17: aload_1
/*     */     //   18: invokevirtual 406	com/yisa/engine/common/InputBean:startTime	()Ljava/lang/String;
/*     */     //   21: ifnull +13 -> 34
/*     */     //   24: aload_0
/*     */     //   25: aload_1
/*     */     //   26: invokevirtual 406	com/yisa/engine/common/InputBean:startTime	()Ljava/lang/String;
/*     */     //   29: invokevirtual 410	com/yisa/engine/branchV3/SparkEngineV3ForSimilarPlate:getTimeStampSecond	(Ljava/lang/String;)J
/*     */     //   32: lstore 5
/*     */     //   34: aload_1
/*     */     //   35: invokevirtual 412	com/yisa/engine/common/InputBean:endTime	()Ljava/lang/String;
/*     */     //   38: ifnull +13 -> 51
/*     */     //   41: aload_0
/*     */     //   42: aload_1
/*     */     //   43: invokevirtual 412	com/yisa/engine/common/InputBean:endTime	()Ljava/lang/String;
/*     */     //   46: invokevirtual 410	com/yisa/engine/branchV3/SparkEngineV3ForSimilarPlate:getTimeStampSecond	(Ljava/lang/String;)J
/*     */     //   49: lstore 7
/*     */     //   51: aload_1
/*     */     //   52: invokevirtual 415	com/yisa/engine/common/InputBean:carBrand	()Ljava/lang/String;
/*     */     //   55: astore 9
/*     */     //   57: aload_1
/*     */     //   58: invokevirtual 419	com/yisa/engine/common/InputBean:carModel	()[Ljava/lang/String;
/*     */     //   61: astore 10
/*     */     //   63: aload_1
/*     */     //   64: invokevirtual 422	com/yisa/engine/common/InputBean:carYear	()[Ljava/lang/String;
/*     */     //   67: astore 11
/*     */     //   69: aload_1
/*     */     //   70: invokevirtual 425	com/yisa/engine/common/InputBean:locationId	()[Ljava/lang/String;
/*     */     //   73: astore 12
/*     */     //   75: new 427	java/lang/StringBuffer
/*     */     //   78: dup
/*     */     //   79: invokespecial 428	java/lang/StringBuffer:<init>	()V
/*     */     //   82: astore 13
/*     */     //   84: aload 13
/*     */     //   86: new 73	scala/collection/mutable/StringBuilder
/*     */     //   89: dup
/*     */     //   90: invokespecial 74	scala/collection/mutable/StringBuilder:<init>	()V
/*     */     //   93: ldc_w 493
/*     */     //   96: invokevirtual 80	scala/collection/mutable/StringBuilder:append	(Ljava/lang/Object;)Lscala/collection/mutable/StringBuilder;
/*     */     //   99: aload_2
/*     */     //   100: invokevirtual 80	scala/collection/mutable/StringBuilder:append	(Ljava/lang/Object;)Lscala/collection/mutable/StringBuilder;
/*     */     //   103: invokevirtual 84	scala/collection/mutable/StringBuilder:toString	()Ljava/lang/String;
/*     */     //   106: invokevirtual 435	java/lang/StringBuffer:append	(Ljava/lang/String;)Ljava/lang/StringBuffer;
/*     */     //   109: pop
/*     */     //   110: aload 13
/*     */     //   112: ldc_w 495
/*     */     //   115: invokevirtual 435	java/lang/StringBuffer:append	(Ljava/lang/String;)Ljava/lang/StringBuffer;
/*     */     //   118: pop
/*     */     //   119: aload_1
/*     */     //   120: invokevirtual 422	com/yisa/engine/common/InputBean:carYear	()[Ljava/lang/String;
/*     */     //   123: aconst_null
/*     */     //   124: if_acmpeq +120 -> 244
/*     */     //   127: aload_1
/*     */     //   128: invokevirtual 422	com/yisa/engine/common/InputBean:carYear	()[Ljava/lang/String;
/*     */     //   131: iconst_0
/*     */     //   132: aaload
/*     */     //   133: ldc_w 439
/*     */     //   136: astore 14
/*     */     //   138: dup
/*     */     //   139: ifnonnull +12 -> 151
/*     */     //   142: pop
/*     */     //   143: aload 14
/*     */     //   145: ifnull +99 -> 244
/*     */     //   148: goto +11 -> 159
/*     */     //   151: aload 14
/*     */     //   153: invokevirtual 440	java/lang/Object:equals	(Ljava/lang/Object;)Z
/*     */     //   156: ifne +88 -> 244
/*     */     //   159: aload_1
/*     */     //   160: invokevirtual 422	com/yisa/engine/common/InputBean:carYear	()[Ljava/lang/String;
/*     */     //   163: iconst_0
/*     */     //   164: aaload
/*     */     //   165: ldc_w 442
/*     */     //   168: astore 15
/*     */     //   170: dup
/*     */     //   171: ifnonnull +12 -> 183
/*     */     //   174: pop
/*     */     //   175: aload 15
/*     */     //   177: ifnull +67 -> 244
/*     */     //   180: goto +11 -> 191
/*     */     //   183: aload 15
/*     */     //   185: invokevirtual 440	java/lang/Object:equals	(Ljava/lang/Object;)Z
/*     */     //   188: ifne +56 -> 244
/*     */     //   191: getstatic 71	scala/Predef$:MODULE$	Lscala/Predef$;
/*     */     //   194: aload_1
/*     */     //   195: invokevirtual 422	com/yisa/engine/common/InputBean:carYear	()[Ljava/lang/String;
/*     */     //   198: checkcast 164	[Ljava/lang/Object;
/*     */     //   201: invokevirtual 168	scala/Predef$:refArrayOps	([Ljava/lang/Object;)Lscala/collection/mutable/ArrayOps;
/*     */     //   204: new 497	com/yisa/engine/branchV3/SparkEngineV3ForSimilarPlate$$anonfun$3
/*     */     //   207: dup
/*     */     //   208: aload_0
/*     */     //   209: invokespecial 498	com/yisa/engine/branchV3/SparkEngineV3ForSimilarPlate$$anonfun$3:<init>	(Lcom/yisa/engine/branchV3/SparkEngineV3ForSimilarPlate;)V
/*     */     //   212: invokeinterface 449 2 0
/*     */     //   217: checkcast 24	java/lang/String
/*     */     //   220: astore 16
/*     */     //   222: aload 13
/*     */     //   224: ldc_w 451
/*     */     //   227: invokevirtual 435	java/lang/StringBuffer:append	(Ljava/lang/String;)Ljava/lang/StringBuffer;
/*     */     //   230: aload 16
/*     */     //   232: invokevirtual 435	java/lang/StringBuffer:append	(Ljava/lang/String;)Ljava/lang/StringBuffer;
/*     */     //   235: ldc_w 453
/*     */     //   238: invokevirtual 435	java/lang/StringBuffer:append	(Ljava/lang/String;)Ljava/lang/StringBuffer;
/*     */     //   241: goto +6 -> 247
/*     */     //   244: getstatic 203	scala/runtime/BoxedUnit:UNIT	Lscala/runtime/BoxedUnit;
/*     */     //   247: pop
/*     */     //   248: lload 5
/*     */     //   250: lconst_0
/*     */     //   251: lcmp
/*     */     //   252: ifeq +25 -> 277
/*     */     //   255: aload 13
/*     */     //   257: ldc_w 455
/*     */     //   260: invokevirtual 435	java/lang/StringBuffer:append	(Ljava/lang/String;)Ljava/lang/StringBuffer;
/*     */     //   263: aload_0
/*     */     //   264: aload_1
/*     */     //   265: invokevirtual 406	com/yisa/engine/common/InputBean:startTime	()Ljava/lang/String;
/*     */     //   268: invokevirtual 459	com/yisa/engine/branchV3/SparkEngineV3ForSimilarPlate:getDateid	(Ljava/lang/String;)Ljava/lang/String;
/*     */     //   271: invokevirtual 435	java/lang/StringBuffer:append	(Ljava/lang/String;)Ljava/lang/StringBuffer;
/*     */     //   274: goto +6 -> 280
/*     */     //   277: getstatic 203	scala/runtime/BoxedUnit:UNIT	Lscala/runtime/BoxedUnit;
/*     */     //   280: pop
/*     */     //   281: lload 7
/*     */     //   283: lconst_0
/*     */     //   284: lcmp
/*     */     //   285: ifeq +25 -> 310
/*     */     //   288: aload 13
/*     */     //   290: ldc_w 461
/*     */     //   293: invokevirtual 435	java/lang/StringBuffer:append	(Ljava/lang/String;)Ljava/lang/StringBuffer;
/*     */     //   296: aload_0
/*     */     //   297: aload_1
/*     */     //   298: invokevirtual 412	com/yisa/engine/common/InputBean:endTime	()Ljava/lang/String;
/*     */     //   301: invokevirtual 459	com/yisa/engine/branchV3/SparkEngineV3ForSimilarPlate:getDateid	(Ljava/lang/String;)Ljava/lang/String;
/*     */     //   304: invokevirtual 435	java/lang/StringBuffer:append	(Ljava/lang/String;)Ljava/lang/StringBuffer;
/*     */     //   307: goto +6 -> 313
/*     */     //   310: getstatic 203	scala/runtime/BoxedUnit:UNIT	Lscala/runtime/BoxedUnit;
/*     */     //   313: pop
/*     */     //   314: lload 5
/*     */     //   316: lconst_0
/*     */     //   317: lcmp
/*     */     //   318: ifeq +25 -> 343
/*     */     //   321: aload 13
/*     */     //   323: ldc_w 500
/*     */     //   326: invokevirtual 435	java/lang/StringBuffer:append	(Ljava/lang/String;)Ljava/lang/StringBuffer;
/*     */     //   329: lload 5
/*     */     //   331: invokevirtual 466	java/lang/StringBuffer:append	(J)Ljava/lang/StringBuffer;
/*     */     //   334: ldc_w 502
/*     */     //   337: invokevirtual 435	java/lang/StringBuffer:append	(Ljava/lang/String;)Ljava/lang/StringBuffer;
/*     */     //   340: goto +6 -> 346
/*     */     //   343: getstatic 203	scala/runtime/BoxedUnit:UNIT	Lscala/runtime/BoxedUnit;
/*     */     //   346: pop
/*     */     //   347: lload 7
/*     */     //   349: lconst_0
/*     */     //   350: lcmp
/*     */     //   351: ifeq +25 -> 376
/*     */     //   354: aload 13
/*     */     //   356: ldc_w 504
/*     */     //   359: invokevirtual 435	java/lang/StringBuffer:append	(Ljava/lang/String;)Ljava/lang/StringBuffer;
/*     */     //   362: lload 7
/*     */     //   364: invokevirtual 466	java/lang/StringBuffer:append	(J)Ljava/lang/StringBuffer;
/*     */     //   367: ldc_w 502
/*     */     //   370: invokevirtual 435	java/lang/StringBuffer:append	(Ljava/lang/String;)Ljava/lang/StringBuffer;
/*     */     //   373: goto +6 -> 379
/*     */     //   376: getstatic 203	scala/runtime/BoxedUnit:UNIT	Lscala/runtime/BoxedUnit;
/*     */     //   379: pop
/*     */     //   380: aload 10
/*     */     //   382: aconst_null
/*     */     //   383: if_acmpeq +93 -> 476
/*     */     //   386: aload 10
/*     */     //   388: arraylength
/*     */     //   389: iconst_0
/*     */     //   390: if_icmple +86 -> 476
/*     */     //   393: aload_1
/*     */     //   394: invokevirtual 419	com/yisa/engine/common/InputBean:carModel	()[Ljava/lang/String;
/*     */     //   397: iconst_0
/*     */     //   398: aaload
/*     */     //   399: ldc_w 442
/*     */     //   402: astore 17
/*     */     //   404: dup
/*     */     //   405: ifnonnull +12 -> 417
/*     */     //   408: pop
/*     */     //   409: aload 17
/*     */     //   411: ifnull +65 -> 476
/*     */     //   414: goto +11 -> 425
/*     */     //   417: aload 17
/*     */     //   419: invokevirtual 440	java/lang/Object:equals	(Ljava/lang/Object;)Z
/*     */     //   422: ifne +54 -> 476
/*     */     //   425: getstatic 71	scala/Predef$:MODULE$	Lscala/Predef$;
/*     */     //   428: aload 10
/*     */     //   430: checkcast 164	[Ljava/lang/Object;
/*     */     //   433: invokevirtual 168	scala/Predef$:refArrayOps	([Ljava/lang/Object;)Lscala/collection/mutable/ArrayOps;
/*     */     //   436: new 506	com/yisa/engine/branchV3/SparkEngineV3ForSimilarPlate$$anonfun$4
/*     */     //   439: dup
/*     */     //   440: aload_0
/*     */     //   441: invokespecial 507	com/yisa/engine/branchV3/SparkEngineV3ForSimilarPlate$$anonfun$4:<init>	(Lcom/yisa/engine/branchV3/SparkEngineV3ForSimilarPlate;)V
/*     */     //   444: invokeinterface 449 2 0
/*     */     //   449: checkcast 24	java/lang/String
/*     */     //   452: astore 18
/*     */     //   454: aload 13
/*     */     //   456: ldc_w 473
/*     */     //   459: invokevirtual 435	java/lang/StringBuffer:append	(Ljava/lang/String;)Ljava/lang/StringBuffer;
/*     */     //   462: aload 18
/*     */     //   464: invokevirtual 435	java/lang/StringBuffer:append	(Ljava/lang/String;)Ljava/lang/StringBuffer;
/*     */     //   467: ldc_w 453
/*     */     //   470: invokevirtual 435	java/lang/StringBuffer:append	(Ljava/lang/String;)Ljava/lang/StringBuffer;
/*     */     //   473: goto +6 -> 479
/*     */     //   476: getstatic 203	scala/runtime/BoxedUnit:UNIT	Lscala/runtime/BoxedUnit;
/*     */     //   479: pop
/*     */     //   480: aload 9
/*     */     //   482: ifnull +59 -> 541
/*     */     //   485: aload 9
/*     */     //   487: ldc_w 439
/*     */     //   490: astore 19
/*     */     //   492: dup
/*     */     //   493: ifnonnull +12 -> 505
/*     */     //   496: pop
/*     */     //   497: aload 19
/*     */     //   499: ifnull +42 -> 541
/*     */     //   502: goto +11 -> 513
/*     */     //   505: aload 19
/*     */     //   507: invokevirtual 440	java/lang/Object:equals	(Ljava/lang/Object;)Z
/*     */     //   510: ifne +31 -> 541
/*     */     //   513: aload 9
/*     */     //   515: ldc_w 442
/*     */     //   518: astore 20
/*     */     //   520: dup
/*     */     //   521: ifnonnull +12 -> 533
/*     */     //   524: pop
/*     */     //   525: aload 20
/*     */     //   527: ifnull +14 -> 541
/*     */     //   530: goto +17 -> 547
/*     */     //   533: aload 20
/*     */     //   535: invokevirtual 440	java/lang/Object:equals	(Ljava/lang/Object;)Z
/*     */     //   538: ifeq +9 -> 547
/*     */     //   541: getstatic 203	scala/runtime/BoxedUnit:UNIT	Lscala/runtime/BoxedUnit;
/*     */     //   544: goto +16 -> 560
/*     */     //   547: aload 13
/*     */     //   549: ldc_w 475
/*     */     //   552: invokevirtual 435	java/lang/StringBuffer:append	(Ljava/lang/String;)Ljava/lang/StringBuffer;
/*     */     //   555: aload 9
/*     */     //   557: invokevirtual 435	java/lang/StringBuffer:append	(Ljava/lang/String;)Ljava/lang/StringBuffer;
/*     */     //   560: pop
/*     */     //   561: new 351	java/util/ArrayList
/*     */     //   564: dup
/*     */     //   565: invokespecial 352	java/util/ArrayList:<init>	()V
/*     */     //   568: astore 21
/*     */     //   570: new 351	java/util/ArrayList
/*     */     //   573: dup
/*     */     //   574: invokespecial 352	java/util/ArrayList:<init>	()V
/*     */     //   577: invokestatic 133	scala/runtime/ObjectRef:create	(Ljava/lang/Object;)Lscala/runtime/ObjectRef;
/*     */     //   580: astore 22
/*     */     //   582: aload_0
/*     */     //   583: iconst_0
/*     */     //   584: iconst_1
/*     */     //   585: aload_3
/*     */     //   586: iload 4
/*     */     //   588: aload 21
/*     */     //   590: aload 22
/*     */     //   592: getfield 183	scala/runtime/ObjectRef:elem	Ljava/lang/Object;
/*     */     //   595: checkcast 351	java/util/ArrayList
/*     */     //   598: invokevirtual 509	com/yisa/engine/branchV3/SparkEngineV3ForSimilarPlate:getPlateNumber	(IILjava/lang/String;ILjava/util/List;Ljava/util/List;)V
/*     */     //   601: aload 22
/*     */     //   603: getfield 183	scala/runtime/ObjectRef:elem	Ljava/lang/Object;
/*     */     //   606: checkcast 351	java/util/ArrayList
/*     */     //   609: invokevirtual 510	java/util/ArrayList:size	()I
/*     */     //   612: iconst_0
/*     */     //   613: if_icmple +62 -> 675
/*     */     //   616: aload 13
/*     */     //   618: ldc_w 512
/*     */     //   621: invokevirtual 435	java/lang/StringBuffer:append	(Ljava/lang/String;)Ljava/lang/StringBuffer;
/*     */     //   624: pop
/*     */     //   625: getstatic 364	scala/runtime/RichInt$:MODULE$	Lscala/runtime/RichInt$;
/*     */     //   628: getstatic 71	scala/Predef$:MODULE$	Lscala/Predef$;
/*     */     //   631: iconst_0
/*     */     //   632: invokevirtual 368	scala/Predef$:intWrapper	(I)I
/*     */     //   635: aload 22
/*     */     //   637: getfield 183	scala/runtime/ObjectRef:elem	Ljava/lang/Object;
/*     */     //   640: checkcast 351	java/util/ArrayList
/*     */     //   643: invokevirtual 510	java/util/ArrayList:size	()I
/*     */     //   646: invokevirtual 372	scala/runtime/RichInt$:until$extension0	(II)Lscala/collection/immutable/Range;
/*     */     //   649: new 514	com/yisa/engine/branchV3/SparkEngineV3ForSimilarPlate$$anonfun$getSql2$1
/*     */     //   652: dup
/*     */     //   653: aload_0
/*     */     //   654: aload 13
/*     */     //   656: aload 22
/*     */     //   658: invokespecial 517	com/yisa/engine/branchV3/SparkEngineV3ForSimilarPlate$$anonfun$getSql2$1:<init>	(Lcom/yisa/engine/branchV3/SparkEngineV3ForSimilarPlate;Ljava/lang/StringBuffer;Lscala/runtime/ObjectRef;)V
/*     */     //   661: invokevirtual 380	scala/collection/immutable/Range:foreach	(Lscala/Function1;)V
/*     */     //   664: aload 13
/*     */     //   666: ldc_w 519
/*     */     //   669: invokevirtual 435	java/lang/StringBuffer:append	(Ljava/lang/String;)Ljava/lang/StringBuffer;
/*     */     //   672: goto +6 -> 678
/*     */     //   675: getstatic 203	scala/runtime/BoxedUnit:UNIT	Lscala/runtime/BoxedUnit;
/*     */     //   678: pop
/*     */     //   679: aload 13
/*     */     //   681: ldc_w 521
/*     */     //   684: invokevirtual 435	java/lang/StringBuffer:append	(Ljava/lang/String;)Ljava/lang/StringBuffer;
/*     */     //   687: pop
/*     */     //   688: aload 13
/*     */     //   690: invokevirtual 484	java/lang/StringBuffer:toString	()Ljava/lang/String;
/*     */     //   693: areturn
/*     */     // Line number table:
/*     */     //   Java source line #481	-> byte code offset #0
/*     */     //   Java source line #482	-> byte code offset #5
/*     */     //   Java source line #483	-> byte code offset #11
/*     */     //   Java source line #484	-> byte code offset #14
/*     */     //   Java source line #485	-> byte code offset #17
/*     */     //   Java source line #487	-> byte code offset #24
/*     */     //   Java source line #489	-> byte code offset #34
/*     */     //   Java source line #491	-> byte code offset #41
/*     */     //   Java source line #495	-> byte code offset #51
/*     */     //   Java source line #496	-> byte code offset #57
/*     */     //   Java source line #497	-> byte code offset #63
/*     */     //   Java source line #498	-> byte code offset #69
/*     */     //   Java source line #499	-> byte code offset #75
/*     */     //   Java source line #501	-> byte code offset #84
/*     */     //   Java source line #502	-> byte code offset #110
/*     */     //   Java source line #505	-> byte code offset #119
/*     */     //   Java source line #506	-> byte code offset #191
/*     */     //   Java source line #507	-> byte code offset #222
/*     */     //   Java source line #505	-> byte code offset #244
/*     */     //   Java source line #510	-> byte code offset #248
/*     */     //   Java source line #511	-> byte code offset #255
/*     */     //   Java source line #510	-> byte code offset #277
/*     */     //   Java source line #514	-> byte code offset #281
/*     */     //   Java source line #515	-> byte code offset #288
/*     */     //   Java source line #514	-> byte code offset #310
/*     */     //   Java source line #518	-> byte code offset #314
/*     */     //   Java source line #519	-> byte code offset #321
/*     */     //   Java source line #518	-> byte code offset #343
/*     */     //   Java source line #522	-> byte code offset #347
/*     */     //   Java source line #523	-> byte code offset #354
/*     */     //   Java source line #522	-> byte code offset #376
/*     */     //   Java source line #526	-> byte code offset #380
/*     */     //   Java source line #527	-> byte code offset #425
/*     */     //   Java source line #528	-> byte code offset #454
/*     */     //   Java source line #526	-> byte code offset #476
/*     */     //   Java source line #531	-> byte code offset #480
/*     */     //   Java source line #532	-> byte code offset #547
/*     */     //   Java source line #531	-> byte code offset #560
/*     */     //   Java source line #536	-> byte code offset #561
/*     */     //   Java source line #537	-> byte code offset #570
/*     */     //   Java source line #538	-> byte code offset #582
/*     */     //   Java source line #539	-> byte code offset #601
/*     */     //   Java source line #540	-> byte code offset #616
/*     */     //   Java source line #541	-> byte code offset #628
/*     */     //   Java source line #548	-> byte code offset #664
/*     */     //   Java source line #539	-> byte code offset #675
/*     */     //   Java source line #551	-> byte code offset #679
/*     */     //   Java source line #554	-> byte code offset #688
/*     */     // Local variable table:
/*     */     //   start	length	slot	name	signature
/*     */     //   0	694	0	this	SparkEngineV3ForSimilarPlate
/*     */     //   0	694	1	param	com.yisa.engine.common.InputBean
/*     */     //   0	694	2	table	String
/*     */     //   5	688	3	plateNumber	String
/*     */     //   11	682	4	differ	int
/*     */     //   14	679	5	startTime	long
/*     */     //   17	676	7	endTime	long
/*     */     //   57	636	9	brand	String
/*     */     //   63	630	10	model	String[]
/*     */     //   69	624	11	yearId	String[]
/*     */     //   75	618	12	location	String[]
/*     */     //   84	609	13	sql	StringBuffer
/*     */     //   222	19	16	m	String
/*     */     //   454	19	18	m	String
/*     */     //   570	123	21	list	java.util.ArrayList
/*     */     //   582	111	22	plateList	ObjectRef
/*     */   }
/*     */   
/*     */   public String getTimeSql(com.yisa.engine.common.InputBean param, String table)
/*     */   {
/* 559 */     String plateNumber = param.plateNumber();
/* 560 */     int differ = param.differ();
/* 561 */     long startTime = 0L;
/* 562 */     if (param.startTime() != null)
/*     */     {
/* 564 */       startTime = getTimeStampSecond(param.startTime());
/*     */     }
/* 566 */     long endTime = 0L;
/* 567 */     if (param.endTime() != null)
/*     */     {
/* 569 */       endTime = getTimeStampSecond(param.endTime());
/*     */     }
/*     */     
/* 572 */     StringBuffer sql = new StringBuffer();
/*     */     
/*     */ 
/*     */ 
/*     */ 
/*     */ 
/*     */ 
/*     */ 
/*     */ 
/*     */ 
/*     */ 
/*     */ 
/*     */ 
/*     */ 
/*     */ 
/*     */ 
/*     */ 
/*     */ 
/*     */ 
/* 591 */     return sql.toString();
/*     */   }
/*     */   
/*     */   /* Error */
/*     */   public String getSql(com.yisa.engine.common.InputBean param, String table)
/*     */   {
/*     */     // Byte code:
/*     */     //   0: aload_1
/*     */     //   1: invokevirtual 400	com/yisa/engine/common/InputBean:plateNumber	()Ljava/lang/String;
/*     */     //   4: astore_3
/*     */     //   5: aload_1
/*     */     //   6: invokevirtual 403	com/yisa/engine/common/InputBean:differ	()I
/*     */     //   9: istore 4
/*     */     //   11: aconst_null
/*     */     //   12: astore 5
/*     */     //   14: aload_1
/*     */     //   15: invokevirtual 406	com/yisa/engine/common/InputBean:startTime	()Ljava/lang/String;
/*     */     //   18: ifnull +15 -> 33
/*     */     //   21: getstatic 530	com/yisa/engine/uitl/TimeUtil$:MODULE$	Lcom/yisa/engine/uitl/TimeUtil$;
/*     */     //   24: aload_1
/*     */     //   25: invokevirtual 406	com/yisa/engine/common/InputBean:startTime	()Ljava/lang/String;
/*     */     //   28: invokevirtual 533	com/yisa/engine/uitl/TimeUtil$:getTimeStringFormat	(Ljava/lang/String;)Ljava/lang/String;
/*     */     //   31: astore 5
/*     */     //   33: aconst_null
/*     */     //   34: astore 6
/*     */     //   36: aload_1
/*     */     //   37: invokevirtual 412	com/yisa/engine/common/InputBean:endTime	()Ljava/lang/String;
/*     */     //   40: ifnull +15 -> 55
/*     */     //   43: getstatic 530	com/yisa/engine/uitl/TimeUtil$:MODULE$	Lcom/yisa/engine/uitl/TimeUtil$;
/*     */     //   46: aload_1
/*     */     //   47: invokevirtual 412	com/yisa/engine/common/InputBean:endTime	()Ljava/lang/String;
/*     */     //   50: invokevirtual 533	com/yisa/engine/uitl/TimeUtil$:getTimeStringFormat	(Ljava/lang/String;)Ljava/lang/String;
/*     */     //   53: astore 6
/*     */     //   55: new 427	java/lang/StringBuffer
/*     */     //   58: dup
/*     */     //   59: invokespecial 428	java/lang/StringBuffer:<init>	()V
/*     */     //   62: astore 7
/*     */     //   64: aload 7
/*     */     //   66: new 73	scala/collection/mutable/StringBuilder
/*     */     //   69: dup
/*     */     //   70: invokespecial 74	scala/collection/mutable/StringBuilder:<init>	()V
/*     */     //   73: ldc_w 535
/*     */     //   76: invokevirtual 80	scala/collection/mutable/StringBuilder:append	(Ljava/lang/Object;)Lscala/collection/mutable/StringBuilder;
/*     */     //   79: aload_3
/*     */     //   80: invokevirtual 80	scala/collection/mutable/StringBuilder:append	(Ljava/lang/Object;)Lscala/collection/mutable/StringBuilder;
/*     */     //   83: ldc_w 537
/*     */     //   86: invokevirtual 80	scala/collection/mutable/StringBuilder:append	(Ljava/lang/Object;)Lscala/collection/mutable/StringBuilder;
/*     */     //   89: aload_2
/*     */     //   90: invokevirtual 80	scala/collection/mutable/StringBuilder:append	(Ljava/lang/Object;)Lscala/collection/mutable/StringBuilder;
/*     */     //   93: invokevirtual 84	scala/collection/mutable/StringBuilder:toString	()Ljava/lang/String;
/*     */     //   96: invokevirtual 435	java/lang/StringBuffer:append	(Ljava/lang/String;)Ljava/lang/StringBuffer;
/*     */     //   99: pop
/*     */     //   100: aload 7
/*     */     //   102: ldc_w 437
/*     */     //   105: invokevirtual 435	java/lang/StringBuffer:append	(Ljava/lang/String;)Ljava/lang/StringBuffer;
/*     */     //   108: pop
/*     */     //   109: aload_1
/*     */     //   110: invokevirtual 425	com/yisa/engine/common/InputBean:locationId	()[Ljava/lang/String;
/*     */     //   113: aconst_null
/*     */     //   114: if_acmpeq +165 -> 279
/*     */     //   117: aload_1
/*     */     //   118: invokevirtual 425	com/yisa/engine/common/InputBean:locationId	()[Ljava/lang/String;
/*     */     //   121: arraylength
/*     */     //   122: iconst_0
/*     */     //   123: if_icmpeq +156 -> 279
/*     */     //   126: aload_1
/*     */     //   127: invokevirtual 425	com/yisa/engine/common/InputBean:locationId	()[Ljava/lang/String;
/*     */     //   130: iconst_0
/*     */     //   131: aaload
/*     */     //   132: ldc_w 439
/*     */     //   135: astore 8
/*     */     //   137: dup
/*     */     //   138: ifnonnull +12 -> 150
/*     */     //   141: pop
/*     */     //   142: aload 8
/*     */     //   144: ifnull +135 -> 279
/*     */     //   147: goto +11 -> 158
/*     */     //   150: aload 8
/*     */     //   152: invokevirtual 440	java/lang/Object:equals	(Ljava/lang/Object;)Z
/*     */     //   155: ifne +124 -> 279
/*     */     //   158: aload_1
/*     */     //   159: invokevirtual 425	com/yisa/engine/common/InputBean:locationId	()[Ljava/lang/String;
/*     */     //   162: iconst_0
/*     */     //   163: aaload
/*     */     //   164: ldc_w 442
/*     */     //   167: astore 9
/*     */     //   169: dup
/*     */     //   170: ifnonnull +12 -> 182
/*     */     //   173: pop
/*     */     //   174: aload 9
/*     */     //   176: ifnull +103 -> 279
/*     */     //   179: goto +11 -> 190
/*     */     //   182: aload 9
/*     */     //   184: invokevirtual 440	java/lang/Object:equals	(Ljava/lang/Object;)Z
/*     */     //   187: ifne +92 -> 279
/*     */     //   190: getstatic 71	scala/Predef$:MODULE$	Lscala/Predef$;
/*     */     //   193: getstatic 71	scala/Predef$:MODULE$	Lscala/Predef$;
/*     */     //   196: aload_1
/*     */     //   197: invokevirtual 425	com/yisa/engine/common/InputBean:locationId	()[Ljava/lang/String;
/*     */     //   200: checkcast 164	[Ljava/lang/Object;
/*     */     //   203: invokevirtual 168	scala/Predef$:refArrayOps	([Ljava/lang/Object;)Lscala/collection/mutable/ArrayOps;
/*     */     //   206: new 539	com/yisa/engine/branchV3/SparkEngineV3ForSimilarPlate$$anonfun$5
/*     */     //   209: dup
/*     */     //   210: aload_0
/*     */     //   211: invokespecial 540	com/yisa/engine/branchV3/SparkEngineV3ForSimilarPlate$$anonfun$5:<init>	(Lcom/yisa/engine/branchV3/SparkEngineV3ForSimilarPlate;)V
/*     */     //   214: getstatic 545	scala/Array$:MODULE$	Lscala/Array$;
/*     */     //   217: getstatic 550	scala/reflect/ClassTag$:MODULE$	Lscala/reflect/ClassTag$;
/*     */     //   220: ldc 24
/*     */     //   222: invokevirtual 553	scala/reflect/ClassTag$:apply	(Ljava/lang/Class;)Lscala/reflect/ClassTag;
/*     */     //   225: invokevirtual 557	scala/Array$:canBuildFrom	(Lscala/reflect/ClassTag;)Lscala/collection/generic/CanBuildFrom;
/*     */     //   228: invokeinterface 560 3 0
/*     */     //   233: checkcast 164	[Ljava/lang/Object;
/*     */     //   236: invokevirtual 168	scala/Predef$:refArrayOps	([Ljava/lang/Object;)Lscala/collection/mutable/ArrayOps;
/*     */     //   239: new 562	com/yisa/engine/branchV3/SparkEngineV3ForSimilarPlate$$anonfun$6
/*     */     //   242: dup
/*     */     //   243: aload_0
/*     */     //   244: invokespecial 563	com/yisa/engine/branchV3/SparkEngineV3ForSimilarPlate$$anonfun$6:<init>	(Lcom/yisa/engine/branchV3/SparkEngineV3ForSimilarPlate;)V
/*     */     //   247: invokeinterface 449 2 0
/*     */     //   252: checkcast 24	java/lang/String
/*     */     //   255: astore 10
/*     */     //   257: aload 7
/*     */     //   259: ldc_w 565
/*     */     //   262: invokevirtual 435	java/lang/StringBuffer:append	(Ljava/lang/String;)Ljava/lang/StringBuffer;
/*     */     //   265: aload 10
/*     */     //   267: invokevirtual 435	java/lang/StringBuffer:append	(Ljava/lang/String;)Ljava/lang/StringBuffer;
/*     */     //   270: ldc_w 453
/*     */     //   273: invokevirtual 435	java/lang/StringBuffer:append	(Ljava/lang/String;)Ljava/lang/StringBuffer;
/*     */     //   276: goto +6 -> 282
/*     */     //   279: getstatic 203	scala/runtime/BoxedUnit:UNIT	Lscala/runtime/BoxedUnit;
/*     */     //   282: pop
/*     */     //   283: aload_1
/*     */     //   284: invokevirtual 422	com/yisa/engine/common/InputBean:carYear	()[Ljava/lang/String;
/*     */     //   287: aconst_null
/*     */     //   288: if_acmpeq +129 -> 417
/*     */     //   291: aload_1
/*     */     //   292: invokevirtual 422	com/yisa/engine/common/InputBean:carYear	()[Ljava/lang/String;
/*     */     //   295: arraylength
/*     */     //   296: iconst_0
/*     */     //   297: if_icmpeq +120 -> 417
/*     */     //   300: aload_1
/*     */     //   301: invokevirtual 422	com/yisa/engine/common/InputBean:carYear	()[Ljava/lang/String;
/*     */     //   304: iconst_0
/*     */     //   305: aaload
/*     */     //   306: ldc_w 439
/*     */     //   309: astore 11
/*     */     //   311: dup
/*     */     //   312: ifnonnull +12 -> 324
/*     */     //   315: pop
/*     */     //   316: aload 11
/*     */     //   318: ifnull +99 -> 417
/*     */     //   321: goto +11 -> 332
/*     */     //   324: aload 11
/*     */     //   326: invokevirtual 440	java/lang/Object:equals	(Ljava/lang/Object;)Z
/*     */     //   329: ifne +88 -> 417
/*     */     //   332: aload_1
/*     */     //   333: invokevirtual 422	com/yisa/engine/common/InputBean:carYear	()[Ljava/lang/String;
/*     */     //   336: iconst_0
/*     */     //   337: aaload
/*     */     //   338: ldc_w 442
/*     */     //   341: astore 12
/*     */     //   343: dup
/*     */     //   344: ifnonnull +12 -> 356
/*     */     //   347: pop
/*     */     //   348: aload 12
/*     */     //   350: ifnull +67 -> 417
/*     */     //   353: goto +11 -> 364
/*     */     //   356: aload 12
/*     */     //   358: invokevirtual 440	java/lang/Object:equals	(Ljava/lang/Object;)Z
/*     */     //   361: ifne +56 -> 417
/*     */     //   364: getstatic 71	scala/Predef$:MODULE$	Lscala/Predef$;
/*     */     //   367: aload_1
/*     */     //   368: invokevirtual 422	com/yisa/engine/common/InputBean:carYear	()[Ljava/lang/String;
/*     */     //   371: checkcast 164	[Ljava/lang/Object;
/*     */     //   374: invokevirtual 168	scala/Predef$:refArrayOps	([Ljava/lang/Object;)Lscala/collection/mutable/ArrayOps;
/*     */     //   377: new 567	com/yisa/engine/branchV3/SparkEngineV3ForSimilarPlate$$anonfun$7
/*     */     //   380: dup
/*     */     //   381: aload_0
/*     */     //   382: invokespecial 568	com/yisa/engine/branchV3/SparkEngineV3ForSimilarPlate$$anonfun$7:<init>	(Lcom/yisa/engine/branchV3/SparkEngineV3ForSimilarPlate;)V
/*     */     //   385: invokeinterface 449 2 0
/*     */     //   390: checkcast 24	java/lang/String
/*     */     //   393: astore 13
/*     */     //   395: aload 7
/*     */     //   397: ldc_w 451
/*     */     //   400: invokevirtual 435	java/lang/StringBuffer:append	(Ljava/lang/String;)Ljava/lang/StringBuffer;
/*     */     //   403: aload 13
/*     */     //   405: invokevirtual 435	java/lang/StringBuffer:append	(Ljava/lang/String;)Ljava/lang/StringBuffer;
/*     */     //   408: ldc_w 453
/*     */     //   411: invokevirtual 435	java/lang/StringBuffer:append	(Ljava/lang/String;)Ljava/lang/StringBuffer;
/*     */     //   414: goto +6 -> 420
/*     */     //   417: getstatic 203	scala/runtime/BoxedUnit:UNIT	Lscala/runtime/BoxedUnit;
/*     */     //   420: pop
/*     */     //   421: aload_1
/*     */     //   422: invokevirtual 419	com/yisa/engine/common/InputBean:carModel	()[Ljava/lang/String;
/*     */     //   425: aconst_null
/*     */     //   426: if_acmpeq +101 -> 527
/*     */     //   429: aload_1
/*     */     //   430: invokevirtual 419	com/yisa/engine/common/InputBean:carModel	()[Ljava/lang/String;
/*     */     //   433: arraylength
/*     */     //   434: iconst_0
/*     */     //   435: if_icmple +92 -> 527
/*     */     //   438: aload_1
/*     */     //   439: invokevirtual 419	com/yisa/engine/common/InputBean:carModel	()[Ljava/lang/String;
/*     */     //   442: iconst_0
/*     */     //   443: aaload
/*     */     //   444: ldc_w 442
/*     */     //   447: astore 14
/*     */     //   449: dup
/*     */     //   450: ifnonnull +12 -> 462
/*     */     //   453: pop
/*     */     //   454: aload 14
/*     */     //   456: ifnull +71 -> 527
/*     */     //   459: goto +11 -> 470
/*     */     //   462: aload 14
/*     */     //   464: invokevirtual 440	java/lang/Object:equals	(Ljava/lang/Object;)Z
/*     */     //   467: ifne +60 -> 527
/*     */     //   470: aload_1
/*     */     //   471: invokevirtual 419	com/yisa/engine/common/InputBean:carModel	()[Ljava/lang/String;
/*     */     //   474: astore 15
/*     */     //   476: getstatic 71	scala/Predef$:MODULE$	Lscala/Predef$;
/*     */     //   479: aload 15
/*     */     //   481: checkcast 164	[Ljava/lang/Object;
/*     */     //   484: invokevirtual 168	scala/Predef$:refArrayOps	([Ljava/lang/Object;)Lscala/collection/mutable/ArrayOps;
/*     */     //   487: new 570	com/yisa/engine/branchV3/SparkEngineV3ForSimilarPlate$$anonfun$8
/*     */     //   490: dup
/*     */     //   491: aload_0
/*     */     //   492: invokespecial 571	com/yisa/engine/branchV3/SparkEngineV3ForSimilarPlate$$anonfun$8:<init>	(Lcom/yisa/engine/branchV3/SparkEngineV3ForSimilarPlate;)V
/*     */     //   495: invokeinterface 449 2 0
/*     */     //   500: checkcast 24	java/lang/String
/*     */     //   503: astore 16
/*     */     //   505: aload 7
/*     */     //   507: ldc_w 473
/*     */     //   510: invokevirtual 435	java/lang/StringBuffer:append	(Ljava/lang/String;)Ljava/lang/StringBuffer;
/*     */     //   513: aload 16
/*     */     //   515: invokevirtual 435	java/lang/StringBuffer:append	(Ljava/lang/String;)Ljava/lang/StringBuffer;
/*     */     //   518: ldc_w 453
/*     */     //   521: invokevirtual 435	java/lang/StringBuffer:append	(Ljava/lang/String;)Ljava/lang/StringBuffer;
/*     */     //   524: goto +6 -> 530
/*     */     //   527: getstatic 203	scala/runtime/BoxedUnit:UNIT	Lscala/runtime/BoxedUnit;
/*     */     //   530: pop
/*     */     //   531: aload_1
/*     */     //   532: invokevirtual 415	com/yisa/engine/common/InputBean:carBrand	()Ljava/lang/String;
/*     */     //   535: ifnull +63 -> 598
/*     */     //   538: aload_1
/*     */     //   539: invokevirtual 415	com/yisa/engine/common/InputBean:carBrand	()Ljava/lang/String;
/*     */     //   542: ldc_w 439
/*     */     //   545: astore 17
/*     */     //   547: dup
/*     */     //   548: ifnonnull +12 -> 560
/*     */     //   551: pop
/*     */     //   552: aload 17
/*     */     //   554: ifnull +44 -> 598
/*     */     //   557: goto +11 -> 568
/*     */     //   560: aload 17
/*     */     //   562: invokevirtual 440	java/lang/Object:equals	(Ljava/lang/Object;)Z
/*     */     //   565: ifne +33 -> 598
/*     */     //   568: aload_1
/*     */     //   569: invokevirtual 415	com/yisa/engine/common/InputBean:carBrand	()Ljava/lang/String;
/*     */     //   572: ldc_w 442
/*     */     //   575: astore 18
/*     */     //   577: dup
/*     */     //   578: ifnonnull +12 -> 590
/*     */     //   581: pop
/*     */     //   582: aload 18
/*     */     //   584: ifnull +14 -> 598
/*     */     //   587: goto +17 -> 604
/*     */     //   590: aload 18
/*     */     //   592: invokevirtual 440	java/lang/Object:equals	(Ljava/lang/Object;)Z
/*     */     //   595: ifeq +9 -> 604
/*     */     //   598: getstatic 203	scala/runtime/BoxedUnit:UNIT	Lscala/runtime/BoxedUnit;
/*     */     //   601: goto +22 -> 623
/*     */     //   604: aload_1
/*     */     //   605: invokevirtual 415	com/yisa/engine/common/InputBean:carBrand	()Ljava/lang/String;
/*     */     //   608: astore 19
/*     */     //   610: aload 7
/*     */     //   612: ldc_w 475
/*     */     //   615: invokevirtual 435	java/lang/StringBuffer:append	(Ljava/lang/String;)Ljava/lang/StringBuffer;
/*     */     //   618: aload 19
/*     */     //   620: invokevirtual 435	java/lang/StringBuffer:append	(Ljava/lang/String;)Ljava/lang/StringBuffer;
/*     */     //   623: pop
/*     */     //   624: aload 7
/*     */     //   626: new 73	scala/collection/mutable/StringBuilder
/*     */     //   629: dup
/*     */     //   630: invokespecial 74	scala/collection/mutable/StringBuilder:<init>	()V
/*     */     //   633: ldc_w 477
/*     */     //   636: invokevirtual 80	scala/collection/mutable/StringBuilder:append	(Ljava/lang/Object;)Lscala/collection/mutable/StringBuilder;
/*     */     //   639: iload 4
/*     */     //   641: invokestatic 481	scala/runtime/BoxesRunTime:boxToInteger	(I)Ljava/lang/Integer;
/*     */     //   644: invokevirtual 80	scala/collection/mutable/StringBuilder:append	(Ljava/lang/Object;)Lscala/collection/mutable/StringBuilder;
/*     */     //   647: invokevirtual 84	scala/collection/mutable/StringBuilder:toString	()Ljava/lang/String;
/*     */     //   650: invokevirtual 435	java/lang/StringBuffer:append	(Ljava/lang/String;)Ljava/lang/StringBuffer;
/*     */     //   653: pop
/*     */     //   654: aload 7
/*     */     //   656: invokevirtual 484	java/lang/StringBuffer:toString	()Ljava/lang/String;
/*     */     //   659: areturn
/*     */     // Line number table:
/*     */     //   Java source line #596	-> byte code offset #0
/*     */     //   Java source line #597	-> byte code offset #5
/*     */     //   Java source line #598	-> byte code offset #11
/*     */     //   Java source line #599	-> byte code offset #14
/*     */     //   Java source line #600	-> byte code offset #21
/*     */     //   Java source line #602	-> byte code offset #33
/*     */     //   Java source line #603	-> byte code offset #36
/*     */     //   Java source line #604	-> byte code offset #43
/*     */     //   Java source line #607	-> byte code offset #55
/*     */     //   Java source line #609	-> byte code offset #64
/*     */     //   Java source line #611	-> byte code offset #100
/*     */     //   Java source line #615	-> byte code offset #109
/*     */     //   Java source line #616	-> byte code offset #190
/*     */     //   Java source line #617	-> byte code offset #257
/*     */     //   Java source line #615	-> byte code offset #279
/*     */     //   Java source line #620	-> byte code offset #283
/*     */     //   Java source line #621	-> byte code offset #364
/*     */     //   Java source line #622	-> byte code offset #395
/*     */     //   Java source line #620	-> byte code offset #417
/*     */     //   Java source line #641	-> byte code offset #421
/*     */     //   Java source line #642	-> byte code offset #470
/*     */     //   Java source line #643	-> byte code offset #476
/*     */     //   Java source line #644	-> byte code offset #505
/*     */     //   Java source line #641	-> byte code offset #527
/*     */     //   Java source line #647	-> byte code offset #531
/*     */     //   Java source line #648	-> byte code offset #604
/*     */     //   Java source line #649	-> byte code offset #610
/*     */     //   Java source line #647	-> byte code offset #623
/*     */     //   Java source line #652	-> byte code offset #624
/*     */     //   Java source line #654	-> byte code offset #654
/*     */     // Local variable table:
/*     */     //   start	length	slot	name	signature
/*     */     //   0	660	0	this	SparkEngineV3ForSimilarPlate
/*     */     //   0	660	1	param	com.yisa.engine.common.InputBean
/*     */     //   0	660	2	table	String
/*     */     //   5	654	3	plateNumber	String
/*     */     //   11	648	4	differ	int
/*     */     //   14	645	5	startTime	String
/*     */     //   36	623	6	endTime	String
/*     */     //   64	595	7	sql	StringBuffer
/*     */     //   257	19	10	l	String
/*     */     //   395	19	13	m	String
/*     */     //   476	48	15	model	String[]
/*     */     //   505	19	16	m	String
/*     */     //   610	13	19	brand	String
/*     */   }
/*     */   
/*     */   public long getTimeStampSecond(String time)
/*     */   {
/* 659 */     java.text.SimpleDateFormat format = new java.text.SimpleDateFormat("yyyyMMddHHmmss");
/* 660 */     return format.parse(time).getTime() / 1000L;
/*     */   }
/*     */   
/*     */   public String getDateid(String timeString)
/*     */   {
/* 665 */     String timeLong = timeString.replaceAll("[-\\s:]", "");
/*     */     
/* 667 */     return timeLong.substring(0, 8);
/*     */   }
/*     */   
/*     */   public long getTimeLong(String timeString) {
/* 671 */     String timeLong = timeString.replaceAll("[-\\s:]", "");
/*     */     
/* 673 */     return new scala.collection.immutable.StringOps(Predef..MODULE$.augmentString(timeLong.substring(0, 14))).toLong();
/*     */   }
/*     */   
/*     */   public int levenshtein(final String s, final String t) {
/* 677 */     int sLen = s.length();
/* 678 */     final int tLen = t.length();
/* 679 */     int si = 0;
/* 680 */     int ti = 0;
/* 681 */     final scala.runtime.CharRef ch1 = scala.runtime.CharRef.create('\000');
/* 682 */     final scala.runtime.CharRef ch2 = scala.runtime.CharRef.create('\000');
/* 683 */     final scala.runtime.IntRef cost = scala.runtime.IntRef.create(0);
/*     */     
/*     */ 
/*     */ 
/*     */ 
/*     */ 
/*     */ 
/*     */ 
/*     */ 
/* 692 */     final ObjectRef d = ObjectRef.create((int[][])scala.Array..MODULE$.ofDim(sLen + 1, tLen + 1, scala.reflect.ClassTag..MODULE$.Int()));scala.runtime.RichInt..MODULE$
/* 693 */       .to$extension0(Predef..MODULE$.intWrapper(0), sLen).foreach$mVc$sp(new AbstractFunction1.mcVI.sp() { public final void apply(int si) { apply$mcVI$sp(si); }
/* 694 */         public void apply$mcVI$sp(int si) { ((int[][])d.elem)[si][0] = si; }
/* 695 */       });scala.runtime.RichInt..MODULE$
/* 696 */       .to$extension0(Predef..MODULE$.intWrapper(0), tLen).foreach$mVc$sp(new AbstractFunction1.mcVI.sp() { public final void apply(int ti) { apply$mcVI$sp(ti); }
/* 697 */         public void apply$mcVI$sp(int ti) { ((int[][])d.elem)[0][ti] = ti; }
/* 698 */       });scala.runtime.RichInt..MODULE$
/* 699 */       .to$extension0(Predef..MODULE$.intWrapper(1), sLen).foreach$mVc$sp(new AbstractFunction1.mcVI.sp() { public static final long serialVersionUID = 0L; public final void apply(int si) { apply$mcVI$sp(si); }
/* 700 */         public void apply$mcVI$sp(final int si) { ch1.elem = s.charAt(si - 1);scala.runtime.RichInt..MODULE$
/* 701 */             .to$extension0(Predef..MODULE$.intWrapper(1), tLen).foreach$mVc$sp(new AbstractFunction1.mcVI.sp() { public final void apply(int ti) { apply$mcVI$sp(ti); }
/* 702 */               public void apply$mcVI$sp(int ti) { SparkEngineV3ForSimilarPlate..anonfun.levenshtein.3.this.ch2$1.elem = SparkEngineV3ForSimilarPlate..anonfun.levenshtein.3.this.t$1.charAt(ti - 1);
/* 703 */                 if (SparkEngineV3ForSimilarPlate..anonfun.levenshtein.3.this.ch1$1.elem == SparkEngineV3ForSimilarPlate..anonfun.levenshtein.3.this.ch2$1.elem) {
/* 704 */                   SparkEngineV3ForSimilarPlate..anonfun.levenshtein.3.this.cost$1.elem = 0;
/*     */                 } else {
/* 706 */                   SparkEngineV3ForSimilarPlate..anonfun.levenshtein.3.this.cost$1.elem = 1;
/*     */                 }
/* 708 */                 ((int[][])SparkEngineV3ForSimilarPlate..anonfun.levenshtein.3.this.d$1.elem)[si][ti] = Math.min(Math.min(((int[][])SparkEngineV3ForSimilarPlate..anonfun.levenshtein.3.this.d$1.elem)[(si - 1)][ti] + 1, ((int[][])SparkEngineV3ForSimilarPlate..anonfun.levenshtein.3.this.d$1.elem)[si][(ti - 1)] + 1), ((int[][])SparkEngineV3ForSimilarPlate..anonfun.levenshtein.3.this.d$1.elem)[(si - 1)][(ti - 1)] + SparkEngineV3ForSimilarPlate..anonfun.levenshtein.3.this.cost$1.elem);
/*     */               }
/*     */             });
/*     */         }
/* 676 */       }
/*     */       
/*     */ 
/*     */ 
/*     */ 
/*     */ 
/*     */ 
/*     */ 
/*     */ 
/*     */ 
/*     */ 
/*     */ 
/*     */ 
/*     */ 
/*     */ 
/*     */ 
/*     */ 
/*     */ 
/*     */ 
/*     */ 
/*     */ 
/*     */ 
/*     */ 
/* 699 */       );return 
/*     */     
/* 701 */        ?  :  ?  :  ?  : 
/*     */       
/*     */ 
/*     */ 
/*     */ 
/*     */ 
/*     */ 
/*     */ 
/*     */ 
/*     */ 
/*     */ 
/* 712 */       ((int[][])d.elem)[sLen][tLen];
/*     */   }
/*     */   
/*     */   public static final long serialVersionUID = 0L;
/*     */   public static final long serialVersionUID = 0L;
/*     */   public static final long serialVersionUID = 0L;
/*     */   public SparkEngineV3ForSimilarPlate(Dataset<Row> sparkData, org.apache.spark.sql.SparkSession sqlContext, String line, String tableName, String zkHostport) {}
/*     */ }


/* Location:              E:\BaiduYunDownload\伊萨时期的一些代码\SparkEngine终极版\jars\YISAEngineBySpark2-4.0.6-SNAPSHOT-jar-with-dependencies.jar!\com\yisa\engine\branchV3\SparkEngineV3ForSimilarPlate.class
 * Java compiler version: 6 (50.0)
 * JD-Core Version:       0.7.1
 */