/*    */ package com.yisa.engine.db;
/*    */ 
/*    */ import com.mchange.v2.c3p0.ComboPooledDataSource;
/*    */ 
/*    */ public final class C3p0ConnectionPool$ implements scala.Serializable { public static final  MODULE$;
/*    */   
/*  7 */   private Object readResolve() { return MODULE$; }
/*  8 */   private ComboPooledDataSource ds() { return this.ds; } private void ds_$eq(ComboPooledDataSource x$1) { this.ds = x$1;
/*    */   }
/*    */   
/*    */   private C3p0ConnectionPool$()
/*    */   {
/*  7 */     MODULE$ = this;
/*  8 */     this.ds = null;
/*    */   }
/*    */   
/*    */ 
/*    */ 
/*    */ 
/*    */ 
/*    */ 
/*    */ 
/*    */ 
/*    */ 
/*    */ 
/*    */ 
/*    */   private volatile ComboPooledDataSource ds;
/*    */   
/*    */ 
/*    */ 
/*    */ 
/*    */ 
/*    */ 
/*    */ 
/*    */ 
/*    */ 
/*    */   public java.sql.Connection getConnet(String zkHostport)
/*    */   {
/* 33 */     synchronized (this) {
/* 34 */       initConnectionPool(zkHostport);
/* 35 */       return ds().getConnection();
/*    */     }
/*    */   }
/*    */   
/*    */   static
/*    */   {
/*    */     new ();
/*    */   }
/*    */   
/*    */   /* Error */
/*    */   public void initConnectionPool(String zkHostport)
/*    */   {
/*    */     // Byte code:
/*    */     //   0: aload_0
/*    */     //   1: invokespecial 27	com/yisa/engine/db/C3p0ConnectionPool$:ds	()Lcom/mchange/v2/c3p0/ComboPooledDataSource;
/*    */     //   4: ifnonnull +140 -> 144
/*    */     //   7: getstatic 32	scala/Predef$:MODULE$	Lscala/Predef$;
/*    */     //   10: ldc 34
/*    */     //   12: invokevirtual 38	scala/Predef$:println	(Ljava/lang/Object;)V
/*    */     //   15: aload_0
/*    */     //   16: dup
/*    */     //   17: astore_2
/*    */     //   18: monitorenter
/*    */     //   19: aload_0
/*    */     //   20: invokespecial 27	com/yisa/engine/db/C3p0ConnectionPool$:ds	()Lcom/mchange/v2/c3p0/ComboPooledDataSource;
/*    */     //   23: ifnonnull +107 -> 130
/*    */     //   26: aload_0
/*    */     //   27: new 40	com/mchange/v2/c3p0/ComboPooledDataSource
/*    */     //   30: dup
/*    */     //   31: invokespecial 41	com/mchange/v2/c3p0/ComboPooledDataSource:<init>	()V
/*    */     //   34: invokespecial 43	com/yisa/engine/db/C3p0ConnectionPool$:ds_$eq	(Lcom/mchange/v2/c3p0/ComboPooledDataSource;)V
/*    */     //   37: new 45	com/yisa/wifi/zookeeper/ZookeeperUtil
/*    */     //   40: dup
/*    */     //   41: invokespecial 46	com/yisa/wifi/zookeeper/ZookeeperUtil:<init>	()V
/*    */     //   44: astore_3
/*    */     //   45: aload_3
/*    */     //   46: aload_1
/*    */     //   47: ldc 48
/*    */     //   49: iconst_0
/*    */     //   50: invokevirtual 52	com/yisa/wifi/zookeeper/ZookeeperUtil:getAllConfig	(Ljava/lang/String;Ljava/lang/String;Z)Ljava/util/Map;
/*    */     //   53: astore 4
/*    */     //   55: aload 4
/*    */     //   57: ldc 54
/*    */     //   59: invokeinterface 60 2 0
/*    */     //   64: checkcast 62	java/lang/String
/*    */     //   67: astore 5
/*    */     //   69: aload 4
/*    */     //   71: ldc 64
/*    */     //   73: invokeinterface 60 2 0
/*    */     //   78: checkcast 62	java/lang/String
/*    */     //   81: astore 6
/*    */     //   83: aload 4
/*    */     //   85: ldc 66
/*    */     //   87: invokeinterface 60 2 0
/*    */     //   92: checkcast 62	java/lang/String
/*    */     //   95: astore 7
/*    */     //   97: aload_0
/*    */     //   98: invokespecial 27	com/yisa/engine/db/C3p0ConnectionPool$:ds	()Lcom/mchange/v2/c3p0/ComboPooledDataSource;
/*    */     //   101: aload 6
/*    */     //   103: invokevirtual 69	com/mchange/v2/c3p0/ComboPooledDataSource:setUser	(Ljava/lang/String;)V
/*    */     //   106: aload_0
/*    */     //   107: invokespecial 27	com/yisa/engine/db/C3p0ConnectionPool$:ds	()Lcom/mchange/v2/c3p0/ComboPooledDataSource;
/*    */     //   110: aload 7
/*    */     //   112: invokevirtual 72	com/mchange/v2/c3p0/ComboPooledDataSource:setPassword	(Ljava/lang/String;)V
/*    */     //   115: aload_0
/*    */     //   116: invokespecial 27	com/yisa/engine/db/C3p0ConnectionPool$:ds	()Lcom/mchange/v2/c3p0/ComboPooledDataSource;
/*    */     //   119: aload 5
/*    */     //   121: invokevirtual 75	com/mchange/v2/c3p0/ComboPooledDataSource:setJdbcUrl	(Ljava/lang/String;)V
/*    */     //   124: getstatic 81	scala/runtime/BoxedUnit:UNIT	Lscala/runtime/BoxedUnit;
/*    */     //   127: goto +6 -> 133
/*    */     //   130: getstatic 81	scala/runtime/BoxedUnit:UNIT	Lscala/runtime/BoxedUnit;
/*    */     //   133: pop
/*    */     //   134: aload_2
/*    */     //   135: monitorexit
/*    */     //   136: getstatic 32	scala/Predef$:MODULE$	Lscala/Predef$;
/*    */     //   139: ldc 83
/*    */     //   141: invokevirtual 38	scala/Predef$:println	(Ljava/lang/Object;)V
/*    */     //   144: return
/*    */     //   145: aload_2
/*    */     //   146: monitorexit
/*    */     //   147: athrow
/*    */     // Line number table:
/*    */     //   Java source line #12	-> byte code offset #0
/*    */     //   Java source line #13	-> byte code offset #7
/*    */     //   Java source line #14	-> byte code offset #15
/*    */     //   Java source line #15	-> byte code offset #19
/*    */     //   Java source line #16	-> byte code offset #26
/*    */     //   Java source line #17	-> byte code offset #37
/*    */     //   Java source line #18	-> byte code offset #45
/*    */     //   Java source line #19	-> byte code offset #55
/*    */     //   Java source line #20	-> byte code offset #69
/*    */     //   Java source line #21	-> byte code offset #83
/*    */     //   Java source line #22	-> byte code offset #97
/*    */     //   Java source line #23	-> byte code offset #106
/*    */     //   Java source line #24	-> byte code offset #115
/*    */     //   Java source line #15	-> byte code offset #130
/*    */     //   Java source line #14	-> byte code offset #135
/*    */     //   Java source line #27	-> byte code offset #136
/*    */     //   Java source line #12	-> byte code offset #144
/*    */     //   Java source line #14	-> byte code offset #145
/*    */     // Local variable table:
/*    */     //   start	length	slot	name	signature
/*    */     //   0	148	0	this	
/*    */     //   0	148	1	zkHostport	String
/*    */     //   17	129	2	Ljava/lang/Object;	Object
/*    */     //   44	2	3	zkUtil	com.yisa.wifi.zookeeper.ZookeeperUtil
/*    */     //   53	31	4	configs	java.util.Map
/*    */     //   67	53	5	URL	String
/*    */     //   81	21	6	USERNAME	String
/*    */     //   95	16	7	PASSWORD	String
/*    */     // Exception table:
/*    */     //   from	to	target	type
/*    */     //   19	136	145	finally
/*    */   }
/*    */ }


/* Location:              E:\BaiduYunDownload\伊萨时期的一些代码\SparkEngine终极版\jars\YISAEngineBySpark2-4.0.6-SNAPSHOT-jar-with-dependencies.jar!\com\yisa\engine\db\C3p0ConnectionPool$.class
 * Java compiler version: 6 (50.0)
 * JD-Core Version:       0.7.1
 */