/*    */ package com.yisa.engine.db;
/*    */ 
/*    */ import org.apache.hadoop.conf.Configuration;
/*    */ import org.apache.hadoop.hbase.HBaseConfiguration;
/*    */ import org.apache.hadoop.hbase.client.Connection;
/*    */ import scala.Predef.;
/*    */ 
/*    */ 
/*    */ 
/*    */ @scala.reflect.ScalaSignature(bytes="\006\001u3Q!\001\002\001\005)\0211\003\023\"bg\026\034uN\0348fGRl\025M\\1hKJT!a\001\003\002\005\021\024'BA\003\007\003\031)gnZ5oK*\021q\001C\001\005s&\034\030MC\001\n\003\r\031w.\\\n\003\001-\001\"\001D\b\016\0035Q\021AD\001\006g\016\fG.Y\005\003!5\021a!\0218z%\0264\007\"\002\n\001\t\003!\022A\002\037j]&$hh\001\001\025\003U\001\"A\006\001\016\003\tAq\001\007\001A\002\023%\021$\001\003d_:tW#\001\016\021\005m1S\"\001\017\013\005uq\022AB2mS\026tGO\003\002 A\005)\001NY1tK*\021\021EI\001\007Q\006$wn\0349\013\005\r\"\023AB1qC\016DWMC\001&\003\ry'oZ\005\003Oq\021!bQ8o]\026\034G/[8o\021\035I\003\0011A\005\n)\n\001bY8o]~#S-\035\013\003W9\002\"\001\004\027\n\0055j!\001B+oSRDqa\f\025\002\002\003\007!$A\002yIEBa!\r\001!B\023Q\022!B2p]:\004\003F\001\0314!\taA'\003\0026\033\tAao\0347bi&dW\rC\0048\001\001\007I\021\002\035\002\r\r|gNZ5h+\005I\004C\001\036>\033\005Y$B\001\037!\003\021\031wN\0344\n\005yZ$!D\"p]\032Lw-\036:bi&|g\016C\004A\001\001\007I\021B!\002\025\r|gNZ5h?\022*\027\017\006\002,\005\"9qfPA\001\002\004I\004B\002#\001A\003&\021(A\004d_:4\027n\032\021)\005\r\033\004bB$\001\005\004%I\001S\001$Q\n\f7/Z0{_>\\W-\0329fe~\003(o\0349feRLxl\0317jK:$\bk\034:u+\005I\005C\001&P\033\005Y%B\001'N\003\021a\027M\\4\013\0039\013AA[1wC&\021\001k\023\002\007'R\024\030N\\4\t\rI\003\001\025!\003J\003\021B'-Y:f?j|wn[3fa\026\024x\f\035:pa\026\024H/_0dY&,g\016\036)peR\004\003b\002+\001\005\004%I\001S\001\027Q\n\f7/Z0{_>\\W-\0329fe~\013Xo\034:v[\"1a\013\001Q\001\n%\013q\003\0332bg\026|&p\\8lK\026\004XM]0rk>\024X/\034\021\t\013a\003A\021A-\002\023\035,GoQ8oM&<G#A\035\t\013m\003A\021\001/\002\023\035,GoQ8o]\026$H#\001\016")
/*    */ public class HBaseConnectManager
/*    */ {
/* 13 */   private Connection conn() { return this.conn; } private void conn_$eq(Connection x$1) { this.conn = x$1; } private volatile Connection conn = null;
/* 14 */   private Configuration config() { return this.config; } private void config_$eq(Configuration x$1) { this.config = x$1; } private volatile Configuration config = null;
/* 15 */   private String hbase_zookeeper_property_clientPort() { return this.hbase_zookeeper_property_clientPort; } private final String hbase_zookeeper_property_clientPort = "2181";
/* 16 */   private String hbase_zookeeper_quorum() { return this.hbase_zookeeper_quorum; } private final String hbase_zookeeper_quorum = "gpu3";
/*    */   
/*    */ 
/*    */ 
/*    */   private final void liftedTree1$1()
/*    */   {
/*    */     try
/*    */     {
/* 24 */       config_$eq(HBaseConfiguration.create());
/* 25 */       config().set("hbase.zookeeper.property.clientPort", hbase_zookeeper_property_clientPort());
/* 26 */       config().set("hbase.zookeeper.quorum", hbase_zookeeper_quorum());
/*    */     }
/*    */     catch (Exception localException) {
/* 29 */       Predef..MODULE$.println("IO Exception");
/*    */     }
/*    */   }
/*    */   
/*    */ 
/*    */ 
/*    */ 
/*    */ 
/*    */ 
/*    */ 
/*    */ 
/*    */ 
/*    */ 
/*    */ 
/*    */   private final void liftedTree2$1(Configuration configuration$1)
/*    */   {
/*    */     try
/*    */     {
/* 47 */       conn_$eq(org.apache.hadoop.hbase.client.ConnectionFactory.createConnection(configuration$1));
/*    */     }
/*    */     catch (Exception localException) {
/* 50 */       Predef..MODULE$.println("IO Exception");
/*    */     }
/*    */   }
/*    */   
/*    */   /* Error */
/*    */   public Configuration getConfig()
/*    */   {
/*    */     // Byte code:
/*    */     //   0: aload_0
/*    */     //   1: invokespecial 36	com/yisa/engine/db/HBaseConnectManager:config	()Lorg/apache/hadoop/conf/Configuration;
/*    */     //   4: ifnonnull +34 -> 38
/*    */     //   7: aload_0
/*    */     //   8: dup
/*    */     //   9: astore_1
/*    */     //   10: monitorenter
/*    */     //   11: aload_0
/*    */     //   12: invokespecial 36	com/yisa/engine/db/HBaseConnectManager:config	()Lorg/apache/hadoop/conf/Configuration;
/*    */     //   15: ifnonnull +13 -> 28
/*    */     //   18: aload_0
/*    */     //   19: invokespecial 40	com/yisa/engine/db/HBaseConnectManager:liftedTree1$1	()V
/*    */     //   22: getstatic 46	scala/runtime/BoxedUnit:UNIT	Lscala/runtime/BoxedUnit;
/*    */     //   25: goto +6 -> 31
/*    */     //   28: getstatic 46	scala/runtime/BoxedUnit:UNIT	Lscala/runtime/BoxedUnit;
/*    */     //   31: astore_2
/*    */     //   32: aload_1
/*    */     //   33: monitorexit
/*    */     //   34: aload_2
/*    */     //   35: goto +6 -> 41
/*    */     //   38: getstatic 46	scala/runtime/BoxedUnit:UNIT	Lscala/runtime/BoxedUnit;
/*    */     //   41: pop
/*    */     //   42: aload_0
/*    */     //   43: invokespecial 36	com/yisa/engine/db/HBaseConnectManager:config	()Lorg/apache/hadoop/conf/Configuration;
/*    */     //   46: areturn
/*    */     //   47: aload_1
/*    */     //   48: monitorexit
/*    */     //   49: athrow
/*    */     // Line number table:
/*    */     //   Java source line #20	-> byte code offset #0
/*    */     //   Java source line #21	-> byte code offset #7
/*    */     //   Java source line #22	-> byte code offset #11
/*    */     //   Java source line #23	-> byte code offset #18
/*    */     //   Java source line #22	-> byte code offset #28
/*    */     //   Java source line #21	-> byte code offset #33
/*    */     //   Java source line #20	-> byte code offset #38
/*    */     //   Java source line #35	-> byte code offset #42
/*    */     //   Java source line #21	-> byte code offset #47
/*    */     // Local variable table:
/*    */     //   start	length	slot	name	signature
/*    */     //   0	50	0	this	HBaseConnectManager
/*    */     //   9	39	1	Ljava/lang/Object;	Object
/*    */     //   31	4	2	localBoxedUnit	scala.runtime.BoxedUnit
/*    */     // Exception table:
/*    */     //   from	to	target	type
/*    */     //   11	34	47	finally
/*    */   }
/*    */   
/*    */   /* Error */
/*    */   public Connection getConnet()
/*    */   {
/*    */     // Byte code:
/*    */     //   0: invokestatic 54	org/apache/hadoop/hbase/HBaseConfiguration:create	()Lorg/apache/hadoop/conf/Configuration;
/*    */     //   3: astore_1
/*    */     //   4: aload_1
/*    */     //   5: ldc 56
/*    */     //   7: aload_0
/*    */     //   8: invokespecial 58	com/yisa/engine/db/HBaseConnectManager:hbase_zookeeper_property_clientPort	()Ljava/lang/String;
/*    */     //   11: invokevirtual 64	org/apache/hadoop/conf/Configuration:set	(Ljava/lang/String;Ljava/lang/String;)V
/*    */     //   14: aload_1
/*    */     //   15: ldc 66
/*    */     //   17: aload_0
/*    */     //   18: invokespecial 68	com/yisa/engine/db/HBaseConnectManager:hbase_zookeeper_quorum	()Ljava/lang/String;
/*    */     //   21: invokevirtual 64	org/apache/hadoop/conf/Configuration:set	(Ljava/lang/String;Ljava/lang/String;)V
/*    */     //   24: aload_0
/*    */     //   25: invokespecial 70	com/yisa/engine/db/HBaseConnectManager:conn	()Lorg/apache/hadoop/hbase/client/Connection;
/*    */     //   28: ifnonnull +35 -> 63
/*    */     //   31: aload_0
/*    */     //   32: dup
/*    */     //   33: astore_2
/*    */     //   34: monitorenter
/*    */     //   35: aload_0
/*    */     //   36: invokespecial 70	com/yisa/engine/db/HBaseConnectManager:conn	()Lorg/apache/hadoop/hbase/client/Connection;
/*    */     //   39: ifnonnull +14 -> 53
/*    */     //   42: aload_0
/*    */     //   43: aload_1
/*    */     //   44: invokespecial 73	com/yisa/engine/db/HBaseConnectManager:liftedTree2$1	(Lorg/apache/hadoop/conf/Configuration;)V
/*    */     //   47: getstatic 46	scala/runtime/BoxedUnit:UNIT	Lscala/runtime/BoxedUnit;
/*    */     //   50: goto +6 -> 56
/*    */     //   53: getstatic 46	scala/runtime/BoxedUnit:UNIT	Lscala/runtime/BoxedUnit;
/*    */     //   56: astore_3
/*    */     //   57: aload_2
/*    */     //   58: monitorexit
/*    */     //   59: aload_3
/*    */     //   60: goto +6 -> 66
/*    */     //   63: getstatic 46	scala/runtime/BoxedUnit:UNIT	Lscala/runtime/BoxedUnit;
/*    */     //   66: pop
/*    */     //   67: aload_0
/*    */     //   68: invokespecial 70	com/yisa/engine/db/HBaseConnectManager:conn	()Lorg/apache/hadoop/hbase/client/Connection;
/*    */     //   71: areturn
/*    */     //   72: aload_2
/*    */     //   73: monitorexit
/*    */     //   74: athrow
/*    */     // Line number table:
/*    */     //   Java source line #40	-> byte code offset #0
/*    */     //   Java source line #41	-> byte code offset #4
/*    */     //   Java source line #42	-> byte code offset #14
/*    */     //   Java source line #43	-> byte code offset #24
/*    */     //   Java source line #44	-> byte code offset #31
/*    */     //   Java source line #45	-> byte code offset #35
/*    */     //   Java source line #46	-> byte code offset #42
/*    */     //   Java source line #45	-> byte code offset #53
/*    */     //   Java source line #44	-> byte code offset #58
/*    */     //   Java source line #43	-> byte code offset #63
/*    */     //   Java source line #56	-> byte code offset #67
/*    */     //   Java source line #44	-> byte code offset #72
/*    */     // Local variable table:
/*    */     //   start	length	slot	name	signature
/*    */     //   0	75	0	this	HBaseConnectManager
/*    */     //   3	41	1	configuration	Configuration
/*    */     //   33	40	2	Ljava/lang/Object;	Object
/*    */     //   56	4	3	localBoxedUnit	scala.runtime.BoxedUnit
/*    */     // Exception table:
/*    */     //   from	to	target	type
/*    */     //   35	59	72	finally
/*    */   }
/*    */ }


/* Location:              E:\BaiduYunDownload\伊萨时期的一些代码\SparkEngine终极版\jars\YISAEngineBySpark2-4.0.6-SNAPSHOT-jar-with-dependencies.jar!\com\yisa\engine\db\HBaseConnectManager.class
 * Java compiler version: 6 (50.0)
 * JD-Core Version:       0.7.1
 */