/*    */ package com.yisa.engine.db;
/*    */ 
/*    */ import java.sql.Connection;
/*    */ 
/*    */ 
/*    */ 
/*    */ public final class JDBCConnectionSinglen$
/*    */ {
/*    */   public static final  MODULE$;
/*    */   private volatile Connection conn;
/*    */   private final String DRIVER;
/*    */   
/* 13 */   private Connection conn() { return this.conn; } private void conn_$eq(Connection x$1) { this.conn = x$1; }
/*    */   
/*    */ 
/*    */ 
/*    */ 
/*    */ 
/*    */ 
/*    */ 
/*    */ 
/*    */ 
/*    */ 
/*    */   public String DRIVER()
/*    */   {
/* 26 */     return this.DRIVER;
/*    */   }
/*    */   
/*    */ 
/*    */ 
/*    */ 
/*    */ 
/*    */ 
/*    */ 
/*    */ 
/*    */ 
/*    */ 
/*    */ 
/*    */ 
/*    */ 
/*    */ 
/*    */ 
/*    */ 
/*    */ 
/*    */ 
/*    */ 
/*    */ 
/*    */ 
/*    */ 
/*    */ 
/*    */ 
/*    */ 
/*    */ 
/*    */ 
/*    */ 
/*    */ 
/*    */ 
/*    */ 
/*    */ 
/*    */ 
/*    */ 
/*    */ 
/*    */ 
/*    */ 
/*    */ 
/*    */   private JDBCConnectionSinglen$()
/*    */   {
/* 68 */     MODULE$ = this;this.conn = null;this.DRIVER = "com.mysql.jdbc.Driver";
/*    */   }
/*    */   
/*    */   static
/*    */   {
/*    */     new ();
/*    */   }
/*    */   
/*    */   /* Error */
/*    */   public Connection getConnet(String zkHostport)
/*    */   {
/*    */     // Byte code:
/*    */     //   0: aload_0
/*    */     //   1: invokespecial 30	com/yisa/engine/db/JDBCConnectionSinglen$:conn	()Ljava/sql/Connection;
/*    */     //   4: ifnull +15 -> 19
/*    */     //   7: aload_0
/*    */     //   8: invokespecial 30	com/yisa/engine/db/JDBCConnectionSinglen$:conn	()Ljava/sql/Connection;
/*    */     //   11: invokeinterface 36 1 0
/*    */     //   16: ifeq +129 -> 145
/*    */     //   19: aload_0
/*    */     //   20: dup
/*    */     //   21: astore_2
/*    */     //   22: monitorenter
/*    */     //   23: aload_0
/*    */     //   24: invokespecial 30	com/yisa/engine/db/JDBCConnectionSinglen$:conn	()Ljava/sql/Connection;
/*    */     //   27: ifnull +15 -> 42
/*    */     //   30: aload_0
/*    */     //   31: invokespecial 30	com/yisa/engine/db/JDBCConnectionSinglen$:conn	()Ljava/sql/Connection;
/*    */     //   34: invokeinterface 36 1 0
/*    */     //   39: ifeq +96 -> 135
/*    */     //   42: new 38	com/yisa/wifi/zookeeper/ZookeeperUtil
/*    */     //   45: dup
/*    */     //   46: invokespecial 39	com/yisa/wifi/zookeeper/ZookeeperUtil:<init>	()V
/*    */     //   49: astore 4
/*    */     //   51: aload 4
/*    */     //   53: aload_1
/*    */     //   54: ldc 41
/*    */     //   56: iconst_0
/*    */     //   57: invokevirtual 45	com/yisa/wifi/zookeeper/ZookeeperUtil:getAllConfig	(Ljava/lang/String;Ljava/lang/String;Z)Ljava/util/Map;
/*    */     //   60: astore 5
/*    */     //   62: aload 5
/*    */     //   64: ldc 47
/*    */     //   66: invokeinterface 53 2 0
/*    */     //   71: checkcast 55	java/lang/String
/*    */     //   74: astore 6
/*    */     //   76: aload 6
/*    */     //   78: astore 7
/*    */     //   80: aload 5
/*    */     //   82: ldc 57
/*    */     //   84: invokeinterface 53 2 0
/*    */     //   89: checkcast 55	java/lang/String
/*    */     //   92: astore 8
/*    */     //   94: aload 5
/*    */     //   96: ldc 59
/*    */     //   98: invokeinterface 53 2 0
/*    */     //   103: checkcast 55	java/lang/String
/*    */     //   106: astore 9
/*    */     //   108: aload_0
/*    */     //   109: invokevirtual 61	com/yisa/engine/db/JDBCConnectionSinglen$:DRIVER	()Ljava/lang/String;
/*    */     //   112: invokestatic 67	java/lang/Class:forName	(Ljava/lang/String;)Ljava/lang/Class;
/*    */     //   115: pop
/*    */     //   116: aload_0
/*    */     //   117: aload 7
/*    */     //   119: aload 8
/*    */     //   121: aload 9
/*    */     //   123: invokestatic 73	java/sql/DriverManager:getConnection	(Ljava/lang/String;Ljava/lang/String;Ljava/lang/String;)Ljava/sql/Connection;
/*    */     //   126: invokespecial 75	com/yisa/engine/db/JDBCConnectionSinglen$:conn_$eq	(Ljava/sql/Connection;)V
/*    */     //   129: getstatic 81	scala/runtime/BoxedUnit:UNIT	Lscala/runtime/BoxedUnit;
/*    */     //   132: goto +6 -> 138
/*    */     //   135: getstatic 81	scala/runtime/BoxedUnit:UNIT	Lscala/runtime/BoxedUnit;
/*    */     //   138: astore_3
/*    */     //   139: aload_2
/*    */     //   140: monitorexit
/*    */     //   141: aload_3
/*    */     //   142: goto +6 -> 148
/*    */     //   145: getstatic 81	scala/runtime/BoxedUnit:UNIT	Lscala/runtime/BoxedUnit;
/*    */     //   148: pop
/*    */     //   149: aload_0
/*    */     //   150: invokespecial 30	com/yisa/engine/db/JDBCConnectionSinglen$:conn	()Ljava/sql/Connection;
/*    */     //   153: areturn
/*    */     //   154: aload_2
/*    */     //   155: monitorexit
/*    */     //   156: athrow
/*    */     // Line number table:
/*    */     //   Java source line #30	-> byte code offset #0
/*    */     //   Java source line #31	-> byte code offset #19
/*    */     //   Java source line #32	-> byte code offset #23
/*    */     //   Java source line #34	-> byte code offset #42
/*    */     //   Java source line #35	-> byte code offset #51
/*    */     //   Java source line #37	-> byte code offset #62
/*    */     //   Java source line #38	-> byte code offset #76
/*    */     //   Java source line #39	-> byte code offset #80
/*    */     //   Java source line #40	-> byte code offset #94
/*    */     //   Java source line #42	-> byte code offset #108
/*    */     //   Java source line #43	-> byte code offset #116
/*    */     //   Java source line #32	-> byte code offset #135
/*    */     //   Java source line #31	-> byte code offset #140
/*    */     //   Java source line #30	-> byte code offset #145
/*    */     //   Java source line #47	-> byte code offset #149
/*    */     //   Java source line #31	-> byte code offset #154
/*    */     // Local variable table:
/*    */     //   start	length	slot	name	signature
/*    */     //   0	157	0	this	
/*    */     //   0	157	1	zkHostport	String
/*    */     //   21	134	2	Ljava/lang/Object;	Object
/*    */     //   138	4	3	localBoxedUnit	scala.runtime.BoxedUnit
/*    */     //   49	3	4	zkUtil	com.yisa.wifi.zookeeper.ZookeeperUtil
/*    */     //   60	35	5	configs	java.util.Map
/*    */     //   74	3	6	jdbc	String
/*    */     //   78	40	7	URL	String
/*    */     //   92	28	8	USERNAME	String
/*    */     //   106	16	9	PASSWORD	String
/*    */     // Exception table:
/*    */     //   from	to	target	type
/*    */     //   23	141	154	finally
/*    */   }
/*    */   
/*    */   /* Error */
/*    */   public Connection getConnet2()
/*    */   {
/*    */     // Byte code:
/*    */     //   0: aload_0
/*    */     //   1: invokespecial 30	com/yisa/engine/db/JDBCConnectionSinglen$:conn	()Ljava/sql/Connection;
/*    */     //   4: ifnull +15 -> 19
/*    */     //   7: aload_0
/*    */     //   8: invokespecial 30	com/yisa/engine/db/JDBCConnectionSinglen$:conn	()Ljava/sql/Connection;
/*    */     //   11: invokeinterface 36 1 0
/*    */     //   16: ifeq +61 -> 77
/*    */     //   19: aload_0
/*    */     //   20: dup
/*    */     //   21: astore_1
/*    */     //   22: monitorenter
/*    */     //   23: aload_0
/*    */     //   24: invokespecial 30	com/yisa/engine/db/JDBCConnectionSinglen$:conn	()Ljava/sql/Connection;
/*    */     //   27: ifnonnull +40 -> 67
/*    */     //   30: ldc 95
/*    */     //   32: astore_3
/*    */     //   33: ldc 97
/*    */     //   35: astore 4
/*    */     //   37: ldc 97
/*    */     //   39: astore 5
/*    */     //   41: aload_0
/*    */     //   42: invokevirtual 61	com/yisa/engine/db/JDBCConnectionSinglen$:DRIVER	()Ljava/lang/String;
/*    */     //   45: invokestatic 67	java/lang/Class:forName	(Ljava/lang/String;)Ljava/lang/Class;
/*    */     //   48: pop
/*    */     //   49: aload_0
/*    */     //   50: aload_3
/*    */     //   51: aload 4
/*    */     //   53: aload 5
/*    */     //   55: invokestatic 73	java/sql/DriverManager:getConnection	(Ljava/lang/String;Ljava/lang/String;Ljava/lang/String;)Ljava/sql/Connection;
/*    */     //   58: invokespecial 75	com/yisa/engine/db/JDBCConnectionSinglen$:conn_$eq	(Ljava/sql/Connection;)V
/*    */     //   61: getstatic 81	scala/runtime/BoxedUnit:UNIT	Lscala/runtime/BoxedUnit;
/*    */     //   64: goto +6 -> 70
/*    */     //   67: getstatic 81	scala/runtime/BoxedUnit:UNIT	Lscala/runtime/BoxedUnit;
/*    */     //   70: astore_2
/*    */     //   71: aload_1
/*    */     //   72: monitorexit
/*    */     //   73: aload_2
/*    */     //   74: goto +6 -> 80
/*    */     //   77: getstatic 81	scala/runtime/BoxedUnit:UNIT	Lscala/runtime/BoxedUnit;
/*    */     //   80: pop
/*    */     //   81: aload_0
/*    */     //   82: invokespecial 30	com/yisa/engine/db/JDBCConnectionSinglen$:conn	()Ljava/sql/Connection;
/*    */     //   85: areturn
/*    */     //   86: aload_1
/*    */     //   87: monitorexit
/*    */     //   88: athrow
/*    */     // Line number table:
/*    */     //   Java source line #52	-> byte code offset #0
/*    */     //   Java source line #53	-> byte code offset #19
/*    */     //   Java source line #54	-> byte code offset #23
/*    */     //   Java source line #55	-> byte code offset #30
/*    */     //   Java source line #57	-> byte code offset #33
/*    */     //   Java source line #58	-> byte code offset #37
/*    */     //   Java source line #60	-> byte code offset #41
/*    */     //   Java source line #61	-> byte code offset #49
/*    */     //   Java source line #54	-> byte code offset #67
/*    */     //   Java source line #53	-> byte code offset #72
/*    */     //   Java source line #52	-> byte code offset #77
/*    */     //   Java source line #65	-> byte code offset #81
/*    */     //   Java source line #53	-> byte code offset #86
/*    */     // Local variable table:
/*    */     //   start	length	slot	name	signature
/*    */     //   0	89	0	this	
/*    */     //   21	66	1	Ljava/lang/Object;	Object
/*    */     //   70	4	2	localBoxedUnit	scala.runtime.BoxedUnit
/*    */     //   32	19	3	URL	String
/*    */     //   35	17	4	USERNAME	String
/*    */     //   39	15	5	PASSWORD	String
/*    */     // Exception table:
/*    */     //   from	to	target	type
/*    */     //   23	73	86	finally
/*    */   }
/*    */ }


/* Location:              E:\BaiduYunDownload\伊萨时期的一些代码\SparkEngine终极版\jars\YISAEngineBySpark2-4.0.6-SNAPSHOT-jar-with-dependencies.jar!\com\yisa\engine\db\JDBCConnectionSinglen$.class
 * Java compiler version: 6 (50.0)
 * JD-Core Version:       0.7.1
 */